{
  "type": "Feature",
  "properties": {
    "gn:admin1_code":"03",
    "gn:asciiname":"Dialaya",
    "gn:country_code":"ML",
    "gn:dem":356,
    "gn:feature_class":"P",
    "gn:feature_code":"PPL",
    "gn:name":"Dialaya",
    "gn:population":0,
    "gn:timezone":"Africa/Bamako",
    "iso:country":"ML",
    "wof:name":"Dialaya",
    "wof:placetype":"locality"
},
  "geometry": {"coordinates":[-9.4172,13.0174],"type":"Point"}
}