{
  "type": "Feature",
  "properties": {
    "gn:admin1_code":"05",
    "gn:asciiname":"Tiemana",
    "gn:country_code":"ML",
    "gn:dem":305,
    "gn:feature_class":"P",
    "gn:feature_code":"PPL",
    "gn:name":"Ti\u00e9mana",
    "gn:population":0,
    "gn:timezone":"Africa/Bamako",
    "iso:country":"ML",
    "name:und_x_variant":[
        "Ti\u00e9mana"
    ],
    "wof:name":"Tiemana",
    "wof:placetype":"locality"
},
  "geometry": {"coordinates":[-5.94704,12.98754],"type":"Point"}
}