{
  "type": "Feature",
  "properties": {
    "gn:admin1_code":"03",
    "gn:asciiname":"Waliya",
    "gn:country_code":"ML",
    "gn:dem":442,
    "gn:feature_class":"P",
    "gn:feature_code":"PPL",
    "gn:name":"Waliya",
    "gn:population":0,
    "gn:timezone":"Africa/Bamako",
    "iso:country":"ML",
    "name:und_x_variant":[
        "Watia",
        "Walia",
        "Waliya"
    ],
    "wof:name":"Waliya",
    "wof:placetype":"locality"
},
  "geometry": {"coordinates":[-11.36239,12.26571],"type":"Point"}
}