{
  "type": "Feature",
  "properties": {
    "gn:admin1_code":"7.0",
    "gn:asciiname":"Bamabougou",
    "gn:country_code":"ML",
    "gn:dem":422,
    "gn:feature_class":"P",
    "gn:feature_code":"PPL",
    "gn:name":"Bamabougou",
    "gn:population":0,
    "gn:timezone":"Africa/Bamako",
    "iso:country":"ML",
    "name:fra_x_preferred":[
        "Bamabougou"
    ],
    "wof:name":"Bamabougou",
    "wof:placetype":"locality"
},
  "geometry": {"coordinates":[-8.0183,13.4454],"type":"Point"}
}