{
  "type": "Feature",
  "properties": {
    "gn:admin1_code":"4.0",
    "gn:asciiname":"Nema",
    "gn:country_code":"ML",
    "gn:dem":280,
    "gn:feature_class":"P",
    "gn:feature_code":"PPL",
    "gn:name":"N\u00e9ma",
    "gn:population":0,
    "gn:timezone":"Africa/Bamako",
    "iso:country":"ML",
    "name:ceb_x_preferred":[
        "Nema"
    ],
    "name:epo_x_preferred":[
        "Nema"
    ],
    "name:fra_x_preferred":[
        "Nema"
    ],
    "name:ita_x_preferred":[
        "Nema"
    ],
    "name:swe_x_preferred":[
        "Nema"
    ],
    "name:tur_x_preferred":[
        "Nema"
    ],
    "wof:name":"Nema",
    "wof:placetype":"locality"
},
  "geometry": {"coordinates":[-3.8614,14.8347],"type":"Point"}
}