{
  "type": "Feature",
  "properties": {
    "gn:admin1_code":"7.0",
    "gn:asciiname":"Kita",
    "gn:country_code":"ML",
    "gn:dem":348,
    "gn:feature_class":"P",
    "gn:feature_code":"PPL",
    "gn:name":"Kita",
    "gn:population":0,
    "gn:timezone":"Africa/Bamako",
    "iso:country":"ML",
    "name:ara_x_preferred":[
        "\u0643\u064a\u062a\u0627"
    ],
    "name:ceb_x_preferred":[
        "Kita"
    ],
    "name:dan_x_preferred":[
        "Kita"
    ],
    "name:deu_x_preferred":[
        "Kita"
    ],
    "name:est_x_preferred":[
        "Kita"
    ],
    "name:fin_x_preferred":[
        "Kita"
    ],
    "name:fra_x_preferred":[
        "Kita"
    ],
    "name:heb_x_preferred":[
        "\u05e7\u05d9\u05d8\u05d4"
    ],
    "name:heb_x_variant":[
        "\u05db\u05d9\u05ea\u05d4"
    ],
    "name:hun_x_preferred":[
        "Kita"
    ],
    "name:ita_x_preferred":[
        "Kita"
    ],
    "name:jpn_x_preferred":[
        "\u30ad\u30bf"
    ],
    "name:lav_x_preferred":[
        "Kita"
    ],
    "name:lit_x_preferred":[
        "Kita"
    ],
    "name:nld_x_preferred":[
        "Kita"
    ],
    "name:pol_x_preferred":[
        "Kita"
    ],
    "name:por_x_preferred":[
        "Kita"
    ],
    "name:ron_x_preferred":[
        "Kita"
    ],
    "name:sco_x_preferred":[
        "Kita"
    ],
    "name:slk_x_preferred":[
        "Kita"
    ],
    "name:slv_x_preferred":[
        "Kita"
    ],
    "name:swe_x_preferred":[
        "Kita"
    ],
    "name:ukr_x_preferred":[
        "\u041a\u0456\u0442\u0430"
    ],
    "wof:name":"Kita",
    "wof:placetype":"locality"
},
  "geometry": {"coordinates":[-7.50077,12.39193],"type":"Point"}
}