{
  "type": "Feature",
  "properties": {
    "gn:admin1_code":"04",
    "gn:asciiname":"Koubitera",
    "gn:country_code":"ML",
    "gn:dem":269,
    "gn:feature_class":"P",
    "gn:feature_code":"PPL",
    "gn:name":"Koubit\u00e9ra",
    "gn:population":0,
    "gn:timezone":"Africa/Bamako",
    "iso:country":"ML",
    "name:und_x_variant":[
        "Koubi",
        "Koubit\u00e9ra"
    ],
    "wof:name":"Koubitera",
    "wof:placetype":"locality"
},
  "geometry": {"coordinates":[-4.68983,14.82327],"type":"Point"}
}