{
  "type": "Feature",
  "properties": {
    "gn:admin1_code":"6.0",
    "gn:asciiname":"Mena",
    "gn:country_code":"ML",
    "gn:dem":359,
    "gn:feature_class":"P",
    "gn:feature_code":"PPL",
    "gn:name":"M\u00e9na",
    "gn:population":0,
    "gn:timezone":"Africa/Bamako",
    "iso:country":"ML",
    "wof:name":"Mena",
    "wof:placetype":"locality"
},
  "geometry": {"coordinates":[-6.34362,11.44523],"type":"Point"}
}