{
  "type": "Feature",
  "properties": {
    "gn:admin1_code":"6.0",
    "gn:asciiname":"Mena",
    "gn:country_code":"ML",
    "gn:dem":359,
    "gn:feature_class":"P",
    "gn:feature_code":"PPL",
    "gn:name":"M\u00e9na",
    "gn:population":0,
    "gn:timezone":"Africa/Bamako",
    "iso:country":"ML",
    "name:bel_x_preferred":[
        "\u041c\u0435\u043d\u0430"
    ],
    "name:cat_x_preferred":[
        "Mena"
    ],
    "name:ceb_x_preferred":[
        "Mena"
    ],
    "name:ces_x_preferred":[
        "Mena"
    ],
    "name:deu_x_preferred":[
        "Mena"
    ],
    "name:fas_x_preferred":[
        "\u0645\u0646\u0627"
    ],
    "name:fin_x_preferred":[
        "Mena"
    ],
    "name:fra_x_preferred":[
        "Mena"
    ],
    "name:ita_x_preferred":[
        "Mena"
    ],
    "name:lav_x_preferred":[
        "Mena"
    ],
    "name:nld_x_preferred":[
        "Mena"
    ],
    "name:por_x_preferred":[
        "Mena"
    ],
    "name:rus_x_preferred":[
        "\u041c\u0435\u043d\u0430"
    ],
    "name:slk_x_preferred":[
        "Mena"
    ],
    "name:spa_x_preferred":[
        "Mena"
    ],
    "name:swe_x_preferred":[
        "Mena"
    ],
    "name:ukr_x_preferred":[
        "\u041c\u0435\u043d\u0430"
    ],
    "wof:name":"Mena",
    "wof:placetype":"locality"
},
  "geometry": {"coordinates":[-6.34362,11.44523],"type":"Point"}
}