{
  "type": "Feature",
  "properties": {
    "gn:admin1_code":"00",
    "gn:asciiname":"Sitokoto",
    "gn:country_code":"ML",
    "gn:dem":263,
    "gn:feature_class":"P",
    "gn:feature_code":"PPL",
    "gn:name":"Sitokoto",
    "gn:population":0,
    "gn:timezone":"Africa/Bamako",
    "iso:country":"ML",
    "wof:name":"Sitokoto",
    "wof:placetype":"locality"
},
  "geometry": {"coordinates":[-3.06667,13.88333],"type":"Point"}
}