{
  "type": "Feature",
  "properties": {
    "gn:admin1_code":"3.0",
    "gn:asciiname":"Berola",
    "gn:country_code":"ML",
    "gn:dem":321,
    "gn:feature_class":"P",
    "gn:feature_code":"PPL",
    "gn:name":"B\u00e9rola",
    "gn:population":0,
    "gn:timezone":"Africa/Bamako",
    "iso:country":"ML",
    "wof:name":"Berola",
    "wof:placetype":"locality"
},
  "geometry": {"coordinates":[-11.01,13.03051],"type":"Point"}
}