{
  "type": "Feature",
  "properties": {
    "gn:admin1_code":"05",
    "gn:asciiname":"Mbeba",
    "gn:country_code":"ML",
    "gn:dem":289,
    "gn:feature_class":"P",
    "gn:feature_code":"PPL",
    "gn:name":"Mb\u00e9ba",
    "gn:population":0,
    "gn:timezone":"Africa/Bamako",
    "iso:country":"ML",
    "name:und_x_variant":[
        "M\u2019Pebala",
        "Mb\u00e9ba"
    ],
    "wof:name":"Mbeba",
    "wof:placetype":"locality"
},
  "geometry": {"coordinates":[-6.1908,13.4851],"type":"Point"}
}