{
  "type": "Feature",
  "properties": {
    "gn:admin1_code":"04",
    "gn:asciiname":"Koume",
    "gn:country_code":"ML",
    "gn:dem":303,
    "gn:feature_class":"P",
    "gn:feature_code":"PPL",
    "gn:name":"Koum\u00e9",
    "gn:population":0,
    "gn:timezone":"Africa/Bamako",
    "iso:country":"ML",
    "wof:name":"Koume",
    "wof:placetype":"locality"
},
  "geometry": {"coordinates":[-3.662,13.7972],"type":"Point"}
}