{
  "type": "Feature",
  "properties": {
    "gn:admin1_code":"4.0",
    "gn:asciiname":"Benndieli",
    "gn:country_code":"ML",
    "gn:dem":446,
    "gn:feature_class":"P",
    "gn:feature_code":"PPL",
    "gn:name":"Benndi\u00e9li",
    "gn:population":0,
    "gn:timezone":"Africa/Bamako",
    "iso:country":"ML",
    "wof:name":"Benndieli",
    "wof:placetype":"locality"
},
  "geometry": {"coordinates":[-3.58689,14.4735],"type":"Point"}
}