{
  "type": "Feature",
  "properties": {
    "gn:admin1_code":"03",
    "gn:asciiname":"Sinzani",
    "gn:country_code":"ML",
    "gn:dem":48,
    "gn:feature_class":"P",
    "gn:feature_code":"PPL",
    "gn:name":"Sinzani",
    "gn:population":0,
    "gn:timezone":"Africa/Bamako",
    "iso:country":"ML",
    "wof:name":"Sinzani",
    "wof:placetype":"locality"
},
  "geometry": {"coordinates":[-11.46071,14.49413],"type":"Point"}
}