{
  "type": "Feature",
  "properties": {
    "gn:admin1_code":"5.0",
    "gn:asciiname":"Tiebakui",
    "gn:country_code":"ML",
    "gn:dem":277,
    "gn:feature_class":"P",
    "gn:feature_code":"PPL",
    "gn:name":"Ti\u00e8bakui",
    "gn:population":0,
    "gn:timezone":"Africa/Bamako",
    "iso:country":"ML",
    "wof:name":"Tiebakui",
    "wof:placetype":"locality"
},
  "geometry": {"coordinates":[-4.54427,13.48728],"type":"Point"}
}