{
  "type": "Feature",
  "properties": {
    "gn:admin1_code":"3.0",
    "gn:asciiname":"Awoeni",
    "gn:country_code":"ML",
    "gn:dem":303,
    "gn:feature_class":"P",
    "gn:feature_code":"PPL",
    "gn:name":"Awo\u00e9ni",
    "gn:population":0,
    "gn:timezone":"Africa/Bamako",
    "iso:country":"ML",
    "wof:name":"Awoeni",
    "wof:placetype":"locality"
},
  "geometry": {"coordinates":[-9.54708,15.15173],"type":"Point"}
}