{
  "type": "Feature",
  "properties": {
    "gn:admin1_code":"6.0",
    "gn:asciiname":"Tinguelini",
    "gn:country_code":"ML",
    "gn:dem":383,
    "gn:feature_class":"P",
    "gn:feature_code":"PPL",
    "gn:name":"Tingu\u00e9lini",
    "gn:population":0,
    "gn:timezone":"Africa/Bamako",
    "iso:country":"ML",
    "wof:name":"Tinguelini",
    "wof:placetype":"locality"
},
  "geometry": {"coordinates":[-7.95846,11.65909],"type":"Point"}
}