{
  "type": "Feature",
  "properties": {
    "gn:admin1_code":"03",
    "gn:asciiname":"Segankane",
    "gn:country_code":"ML",
    "gn:dem":58,
    "gn:feature_class":"P",
    "gn:feature_code":"PPL",
    "gn:name":"S\u00e9gankan\u00e9",
    "gn:population":0,
    "gn:timezone":"Africa/Bamako",
    "iso:country":"ML",
    "wof:name":"Segankane",
    "wof:placetype":"locality"
},
  "geometry": {"coordinates":[-11.25049,14.27589],"type":"Point"}
}