{
  "type": "Feature",
  "properties": {
    "gn:admin1_code":"03",
    "gn:asciiname":"Torolo",
    "gn:country_code":"ML",
    "gn:dem":419,
    "gn:feature_class":"P",
    "gn:feature_code":"PPL",
    "gn:name":"Torolo",
    "gn:population":0,
    "gn:timezone":"Africa/Bamako",
    "iso:country":"ML",
    "name:und_x_variant":[
        "Tourlouro",
        "Toroloro",
        "Torolo"
    ],
    "wof:name":"Torolo",
    "wof:placetype":"locality"
},
  "geometry": {"coordinates":[-8.85267,12.78689],"type":"Point"}
}