{
  "type": "Feature",
  "properties": {
    "gn:admin1_code":"00",
    "gn:asciiname":"Dialakoni",
    "gn:country_code":"ML",
    "gn:dem":345,
    "gn:feature_class":"P",
    "gn:feature_code":"PPL",
    "gn:name":"Dialakoni",
    "gn:population":0,
    "gn:timezone":"Africa/Bamako",
    "iso:country":"ML",
    "wof:name":"Dialakoni",
    "wof:placetype":"locality"
},
  "geometry": {"coordinates":[-9.28333,12.96667],"type":"Point"}
}