{
  "type": "Feature",
  "properties": {
    "gn:admin1_code":"3.0",
    "gn:asciiname":"Komeoulou",
    "gn:country_code":"ML",
    "gn:dem":79,
    "gn:feature_class":"P",
    "gn:feature_code":"PPL",
    "gn:name":"Kom\u00e9oulou",
    "gn:population":0,
    "gn:timezone":"Africa/Bamako",
    "iso:country":"ML",
    "wof:name":"Komeoulou",
    "wof:placetype":"locality"
},
  "geometry": {"coordinates":[-10.81536,15.09302],"type":"Point"}
}