{
  "type": "Feature",
  "properties": {
    "gn:admin1_code":"5.0",
    "gn:asciiname":"Siratigui",
    "gn:country_code":"ML",
    "gn:dem":312,
    "gn:feature_class":"P",
    "gn:feature_code":"PPL",
    "gn:name":"Siratigui",
    "gn:population":0,
    "gn:timezone":"Africa/Bamako",
    "iso:country":"ML",
    "name:fra_x_preferred":[
        "Siratigi"
    ],
    "wof:name":"Siratigui",
    "wof:placetype":"locality"
},
  "geometry": {"coordinates":[-6.7247,12.98],"type":"Point"}
}