{
  "type": "Feature",
  "properties": {
    "gn:admin1_code":"03",
    "gn:asciiname":"Mayel",
    "gn:country_code":"ML",
    "gn:dem":260,
    "gn:feature_class":"P",
    "gn:feature_code":"PPL",
    "gn:name":"Mayel",
    "gn:population":0,
    "gn:timezone":"Africa/Bamako",
    "iso:country":"ML",
    "name:und_x_variant":[
        "Mahel",
        "Mayel"
    ],
    "wof:name":"Mayel",
    "wof:placetype":"locality"
},
  "geometry": {"coordinates":[-9.90366,15.32131],"type":"Point"}
}