{
  "type": "Feature",
  "properties": {
    "gn:admin1_code":"06",
    "gn:asciiname":"Zampiela",
    "gn:country_code":"ML",
    "gn:dem":336,
    "gn:feature_class":"P",
    "gn:feature_code":"PPL",
    "gn:name":"Zampi\u00e9la",
    "gn:population":0,
    "gn:timezone":"Africa/Bamako",
    "iso:country":"ML",
    "name:fra_x_preferred":[
        "Zempi\u00e9la"
    ],
    "name:fra_x_variant":[
        "Zenpi\u00e9la",
        "Dempi\u00e9la"
    ],
    "name:und_x_variant":[
        "Dempi\u00e9la",
        "Zenpi\u00e9la",
        "Zampi\u00e9la",
        "Zempi\u00e9la"
    ],
    "wof:name":"Zampiela",
    "wof:placetype":"locality"
},
  "geometry": {"coordinates":[-6.91376,11.14583],"type":"Point"}
}