{
  "type": "Feature",
  "properties": {
    "gn:admin1_code":"07",
    "gn:asciiname":"Massantola",
    "gn:country_code":"ML",
    "gn:dem":404,
    "gn:feature_class":"P",
    "gn:feature_code":"PPL",
    "gn:name":"Massantola",
    "gn:population":0,
    "gn:timezone":"Africa/Bamako",
    "iso:country":"ML",
    "name:fin_x_preferred":[
        "Massantola"
    ],
    "name:fra_x_preferred":[
        "Massantola"
    ],
    "name:ita_x_preferred":[
        "Massantola"
    ],
    "name:nld_x_preferred":[
        "Massantola"
    ],
    "name:spa_x_preferred":[
        "Massantola"
    ],
    "wof:name":"Massantola",
    "wof:placetype":"locality"
},
  "geometry": {"coordinates":[-7.80505,13.49412],"type":"Point"}
}