{
  "type": "Feature",
  "properties": {
    "gn:admin1_code":"4.0",
    "gn:asciiname":"Bare",
    "gn:country_code":"ML",
    "gn:dem":293,
    "gn:feature_class":"P",
    "gn:feature_code":"PPL",
    "gn:name":"Bar\u00e9",
    "gn:population":0,
    "gn:timezone":"Africa/Bamako",
    "iso:country":"ML",
    "name:bos_x_preferred":[
        "Bare"
    ],
    "name:ceb_x_preferred":[
        "Bare"
    ],
    "name:deu_x_preferred":[
        "Bare"
    ],
    "name:eus_x_preferred":[
        "Bare"
    ],
    "name:fra_x_preferred":[
        "Bare"
    ],
    "name:hrv_x_preferred":[
        "Bare"
    ],
    "name:hun_x_preferred":[
        "Bare"
    ],
    "name:ita_x_preferred":[
        "Bare"
    ],
    "name:nld_x_preferred":[
        "Bare"
    ],
    "name:por_x_preferred":[
        "Bare"
    ],
    "name:slv_x_preferred":[
        "Bare"
    ],
    "name:swe_x_preferred":[
        "Bare"
    ],
    "wof:name":"Bare",
    "wof:placetype":"locality"
},
  "geometry": {"coordinates":[-3.56969,14.0599],"type":"Point"}
}