{
  "type": "Feature",
  "properties": {
    "gn:admin1_code":"7.0",
    "gn:asciiname":"Markabougou",
    "gn:country_code":"ML",
    "gn:dem":324,
    "gn:feature_class":"P",
    "gn:feature_code":"PPL",
    "gn:name":"Markabougou",
    "gn:population":0,
    "gn:timezone":"Africa/Bamako",
    "iso:country":"ML",
    "wof:name":"Markabougou",
    "wof:placetype":"locality"
},
  "geometry": {"coordinates":[-7.39565,12.46239],"type":"Point"}
}