{
  "type": "Feature",
  "properties": {
    "gn:admin1_code":"5.0",
    "gn:asciiname":"Seguebaouli",
    "gn:country_code":"ML",
    "gn:dem":318,
    "gn:feature_class":"P",
    "gn:feature_code":"PPL",
    "gn:name":"S\u00e8gu\u00e8baouli",
    "gn:population":0,
    "gn:timezone":"Africa/Bamako",
    "iso:country":"ML",
    "wof:name":"Seguebaouli",
    "wof:placetype":"locality"
},
  "geometry": {"coordinates":[-6.8966,13.0491],"type":"Point"}
}