{
  "type": "Feature",
  "properties": {
    "gn:admin1_code":"03",
    "gn:asciiname":"Guimba",
    "gn:country_code":"ML",
    "gn:dem":208,
    "gn:feature_class":"P",
    "gn:feature_code":"PPL",
    "gn:name":"Guimba",
    "gn:population":0,
    "gn:timezone":"Africa/Bamako",
    "iso:country":"ML",
    "name:und_x_variant":[
        "Gimbaa",
        "Guimbaa",
        "Guimba"
    ],
    "wof:name":"Guimba",
    "wof:placetype":"locality"
},
  "geometry": {"coordinates":[-9.6544,15.33774],"type":"Point"}
}