{
  "type": "Feature",
  "properties": {
    "gn:admin1_code":"4.0",
    "gn:asciiname":"Goro",
    "gn:country_code":"ML",
    "gn:dem":282,
    "gn:feature_class":"P",
    "gn:feature_code":"PPL",
    "gn:name":"Goro",
    "gn:population":0,
    "gn:timezone":"Africa/Bamako",
    "iso:country":"ML",
    "name:ceb_x_preferred":[
        "Goro"
    ],
    "name:deu_x_preferred":[
        "Goro"
    ],
    "name:eus_x_preferred":[
        "Goro"
    ],
    "name:fin_x_preferred":[
        "Goro"
    ],
    "name:fra_x_preferred":[
        "Goro"
    ],
    "name:ita_x_preferred":[
        "Goro"
    ],
    "name:nld_x_preferred":[
        "Goro"
    ],
    "name:rus_x_preferred":[
        "\u0413\u043e\u0440\u043e"
    ],
    "name:swe_x_preferred":[
        "Goro"
    ],
    "name:tur_x_preferred":[
        "Goro"
    ],
    "name:ukr_x_preferred":[
        "\u0413\u043e\u0440\u043e"
    ],
    "wof:name":"Goro",
    "wof:placetype":"locality"
},
  "geometry": {"coordinates":[-3.5346,14.0493],"type":"Point"}
}