{
  "type": "Feature",
  "properties": {
    "gn:admin1_code":"04",
    "gn:asciiname":"Koporo-Kenie-na",
    "gn:country_code":"ML",
    "gn:dem":276,
    "gn:feature_class":"P",
    "gn:feature_code":"PPL",
    "gn:name":"Koporo-K\u00e9ni\u00e9-na",
    "gn:population":0,
    "gn:timezone":"Africa/Bamako",
    "iso:country":"ML",
    "name:fin_x_preferred":[
        "Koporokendi\u00e9 N\u00e2"
    ],
    "name:fra_x_preferred":[
        "Koporokendi\u00e9 N\u00e2"
    ],
    "name:ita_x_preferred":[
        "Koporokendi\u00e9 N\u00e2"
    ],
    "name:nld_x_preferred":[
        "Koporokendi\u00e9 N\u00e2"
    ],
    "name:spa_x_preferred":[
        "Koporokendie Na"
    ],
    "name:und_x_variant":[
        "Kaborokindi\u00e9",
        "Koporokondi\u00e9-Na",
        "Koporo-K\u00e9m\u00e9ma",
        "Koporo-K\u00e9ni\u00e9-na"
    ],
    "name:zho_x_preferred":[
        "\u79d1\u6ce2\u7f85\u80af\u8fea\u57c3\u7d0d"
    ],
    "wof:name":"Koporo-Kenie-na",
    "wof:placetype":"locality"
},
  "geometry": {"coordinates":[-3.35391,14.13084],"type":"Point"}
}