{
  "type": "Feature",
  "properties": {
    "gn:admin1_code":"6.0",
    "gn:asciiname":"Baniabougou",
    "gn:country_code":"ML",
    "gn:dem":345,
    "gn:feature_class":"P",
    "gn:feature_code":"PPL",
    "gn:name":"Baniabougou",
    "gn:population":0,
    "gn:timezone":"Africa/Bamako",
    "iso:country":"ML",
    "wof:name":"Baniabougou",
    "wof:placetype":"locality"
},
  "geometry": {"coordinates":[-5.92655,11.07442],"type":"Point"}
}