{
  "type": "Feature",
  "properties": {
    "gn:admin1_code":"7.0",
    "gn:asciiname":"Sebeninkoro",
    "gn:country_code":"ML",
    "gn:dem":310,
    "gn:feature_class":"P",
    "gn:feature_code":"PPL",
    "gn:name":"S\u00e9b\u00e9ninkoro",
    "gn:population":0,
    "gn:timezone":"Africa/Bamako",
    "iso:country":"ML",
    "wof:name":"Sebeninkoro",
    "wof:placetype":"locality"
},
  "geometry": {"coordinates":[-7.1513,12.4935],"type":"Point"}
}