{
  "type": "Feature",
  "properties": {
    "gn:admin1_code":"06",
    "gn:asciiname":"Finkolo",
    "gn:country_code":"ML",
    "gn:dem":334,
    "gn:feature_class":"P",
    "gn:feature_code":"PPL",
    "gn:name":"Finkolo",
    "gn:population":0,
    "gn:timezone":"Africa/Bamako",
    "iso:country":"ML",
    "name:bam_x_preferred":[
        "Finkolo"
    ],
    "name:fin_x_preferred":[
        "Finkolo"
    ],
    "name:fra_x_preferred":[
        "Fenkolo"
    ],
    "name:fra_x_variant":[
        "Finkolo"
    ],
    "name:ita_x_preferred":[
        "Finkolo"
    ],
    "name:nld_x_preferred":[
        "Finkolo"
    ],
    "name:por_x_preferred":[
        "Fincolo"
    ],
    "name:spa_x_preferred":[
        "Finkolo"
    ],
    "name:und_x_variant":[
        "Fenkolo"
    ],
    "name:zho_x_preferred":[
        "\u82ac\u79d1\u6d1b"
    ],
    "wof:name":"Finkolo",
    "wof:placetype":"locality"
},
  "geometry": {"coordinates":[-6.19621,11.2265],"type":"Point"}
}