{
  "type": "Feature",
  "properties": {
    "gn:admin1_code":"09",
    "gn:asciiname":"Damne",
    "gn:country_code":"ML",
    "gn:dem":248,
    "gn:feature_class":"P",
    "gn:feature_code":"PPL",
    "gn:name":"Damn\u00e9",
    "gn:population":0,
    "gn:timezone":"Africa/Bamako",
    "iso:country":"ML",
    "wof:name":"Damne",
    "wof:placetype":"locality"
},
  "geometry": {"coordinates":[-0.085,16.4925],"type":"Point"}
}