{
  "type": "Feature",
  "properties": {
    "gn:admin1_code":"03",
    "gn:asciiname":"Sananbougou",
    "gn:country_code":"ML",
    "gn:dem":274,
    "gn:feature_class":"P",
    "gn:feature_code":"PPL",
    "gn:name":"Sananbougou",
    "gn:population":0,
    "gn:timezone":"Africa/Bamako",
    "iso:country":"ML",
    "name:und_x_variant":[
        "Sanandougou",
        "Sananbougou"
    ],
    "wof:name":"Sananbougou",
    "wof:placetype":"locality"
},
  "geometry": {"coordinates":[-9.25703,14.41443],"type":"Point"}
}