{
  "type": "Feature",
  "properties": {
    "gn:admin1_code":"07",
    "gn:asciiname":"Sounssou",
    "gn:country_code":"ML",
    "gn:dem":351,
    "gn:feature_class":"P",
    "gn:feature_code":"PPL",
    "gn:name":"Sounssou",
    "gn:population":0,
    "gn:timezone":"Africa/Bamako",
    "iso:country":"ML",
    "name:fra_x_preferred":[
        "Sounsou"
    ],
    "wof:name":"Sounssou",
    "wof:placetype":"locality"
},
  "geometry": {"coordinates":[-8.275,13.8689],"type":"Point"}
}