{
  "type": "Feature",
  "properties": {
    "gn:admin1_code":"05",
    "gn:asciiname":"Ndiena",
    "gn:country_code":"ML",
    "gn:dem":292,
    "gn:feature_class":"P",
    "gn:feature_code":"PPL",
    "gn:name":"Ndi\u00e9na",
    "gn:population":0,
    "gn:timezone":"Africa/Bamako",
    "iso:country":"ML",
    "name:und_x_variant":[
        "Ndj\u00e9r\u00e9na",
        "Nj\u00e9r\u00e9na",
        "Ndi\u00e9na"
    ],
    "wof:name":"Ndiena",
    "wof:placetype":"locality"
},
  "geometry": {"coordinates":[-5.41877,13.06857],"type":"Point"}
}