{
  "type": "Feature",
  "properties": {
    "gn:admin1_code":"4.0",
    "gn:asciiname":"Simina",
    "gn:country_code":"ML",
    "gn:dem":273,
    "gn:feature_class":"P",
    "gn:feature_code":"PPL",
    "gn:name":"Simina",
    "gn:population":0,
    "gn:timezone":"Africa/Bamako",
    "iso:country":"ML",
    "wof:name":"Simina",
    "wof:placetype":"locality"
},
  "geometry": {"coordinates":[-3.9489,14.7566],"type":"Point"}
}