{
  "type": "Feature",
  "properties": {
    "gn:admin1_code":"3.0",
    "gn:asciiname":"Bingassi",
    "gn:country_code":"ML",
    "gn:dem":162,
    "gn:feature_class":"P",
    "gn:feature_code":"PPL",
    "gn:name":"Bingassi",
    "gn:population":0,
    "gn:timezone":"Africa/Bamako",
    "iso:country":"ML",
    "wof:name":"Bingassi",
    "wof:placetype":"locality"
},
  "geometry": {"coordinates":[-10.4969,13.2511],"type":"Point"}
}