{
  "type": "Feature",
  "properties": {
    "gn:admin1_code":"7.0",
    "gn:asciiname":"Sebekoro",
    "gn:country_code":"ML",
    "gn:dem":379,
    "gn:feature_class":"P",
    "gn:feature_code":"PPL",
    "gn:name":"S\u00e8b\u00e8koro",
    "gn:population":0,
    "gn:timezone":"Africa/Bamako",
    "iso:country":"ML",
    "wof:name":"Sebekoro",
    "wof:placetype":"locality"
},
  "geometry": {"coordinates":[-7.74773,13.32501],"type":"Point"}
}