{
  "type": "Feature",
  "properties": {
    "gn:admin1_code":"5.0",
    "gn:asciiname":"Kona",
    "gn:country_code":"ML",
    "gn:dem":276,
    "gn:feature_class":"P",
    "gn:feature_code":"PPL",
    "gn:name":"Kona",
    "gn:population":0,
    "gn:timezone":"Africa/Bamako",
    "iso:country":"ML",
    "wof:name":"Kona",
    "wof:placetype":"locality"
},
  "geometry": {"coordinates":[-5.6051,14.0071],"type":"Point"}
}