{
  "type": "Feature",
  "properties": {
    "gn:admin1_code":"05",
    "gn:asciiname":"Wolon",
    "gn:country_code":"ML",
    "gn:dem":278,
    "gn:feature_class":"P",
    "gn:feature_code":"PPL",
    "gn:name":"Wolon",
    "gn:population":0,
    "gn:timezone":"Africa/Bamako",
    "iso:country":"ML",
    "wof:name":"Wolon",
    "wof:placetype":"locality"
},
  "geometry": {"coordinates":[-4.8626,13.5018],"type":"Point"}
}