{
  "type": "Feature",
  "properties": {
    "gn:admin1_code":"7.0",
    "gn:asciiname":"Berela",
    "gn:country_code":"ML",
    "gn:dem":470,
    "gn:feature_class":"P",
    "gn:feature_code":"PPL",
    "gn:name":"B\u00e8r\u00e8la",
    "gn:population":0,
    "gn:timezone":"Africa/Bamako",
    "iso:country":"ML",
    "wof:name":"Berela",
    "wof:placetype":"locality"
},
  "geometry": {"coordinates":[-8.38597,12.38779],"type":"Point"}
}