{
  "type": "Feature",
  "properties": {
    "gn:admin1_code":"04",
    "gn:asciiname":"Niondji",
    "gn:country_code":"ML",
    "gn:dem":272,
    "gn:feature_class":"P",
    "gn:feature_code":"PPL",
    "gn:name":"Niondji",
    "gn:population":0,
    "gn:timezone":"Africa/Bamako",
    "iso:country":"ML",
    "name:und_x_variant":[
        "Nioudji",
        "Niondji"
    ],
    "wof:name":"Niondji",
    "wof:placetype":"locality"
},
  "geometry": {"coordinates":[-5.2115,14.6288],"type":"Point"}
}