{
  "type": "Feature",
  "properties": {
    "gn:admin1_code":"7.0",
    "gn:asciiname":"Chela",
    "gn:country_code":"ML",
    "gn:dem":416,
    "gn:feature_class":"P",
    "gn:feature_code":"PPL",
    "gn:name":"Ch\u00e8la",
    "gn:population":0,
    "gn:timezone":"Africa/Bamako",
    "iso:country":"ML",
    "name:ceb_x_preferred":[
        "Chela"
    ],
    "name:deu_x_preferred":[
        "Chela"
    ],
    "name:ita_x_preferred":[
        "Chela"
    ],
    "name:nds_x_preferred":[
        "Chela"
    ],
    "name:nor_x_preferred":[
        "Chela"
    ],
    "name:pol_x_preferred":[
        "Chela"
    ],
    "name:spa_x_preferred":[
        "Chela"
    ],
    "name:swe_x_preferred":[
        "Chela"
    ],
    "wof:name":"Chela",
    "wof:placetype":"locality"
},
  "geometry": {"coordinates":[-7.81185,12.79852],"type":"Point"}
}