{
  "type": "Feature",
  "properties": {
    "gn:admin1_code":"3.0",
    "gn:asciiname":"Tomadjalan",
    "gn:country_code":"ML",
    "gn:dem":350,
    "gn:feature_class":"P",
    "gn:feature_code":"PPL",
    "gn:name":"Tomadjalan",
    "gn:population":0,
    "gn:timezone":"Africa/Bamako",
    "iso:country":"ML",
    "wof:name":"Tomadjalan",
    "wof:placetype":"locality"
},
  "geometry": {"coordinates":[-9.1299,13.094],"type":"Point"}
}