{
  "type": "Feature",
  "properties": {
    "gn:admin1_code":"04",
    "gn:asciiname":"Sim",
    "gn:country_code":"ML",
    "gn:dem":289,
    "gn:feature_class":"P",
    "gn:feature_code":"PPL",
    "gn:name":"Sim",
    "gn:population":0,
    "gn:timezone":"Africa/Bamako",
    "iso:country":"ML",
    "name:und_x_variant":[
        "Simi",
        "Sini",
        "Sim"
    ],
    "wof:name":"Sim",
    "wof:placetype":"locality"
},
  "geometry": {"coordinates":[-3.88629,14.6974],"type":"Point"}
}