{
  "type": "Feature",
  "properties": {
    "gn:admin1_code":"03",
    "gn:asciiname":"Kolea",
    "gn:country_code":"ML",
    "gn:dem":224,
    "gn:feature_class":"P",
    "gn:feature_code":"PPL",
    "gn:name":"Kol\u00e9a",
    "gn:population":0,
    "gn:timezone":"Africa/Bamako",
    "iso:country":"ML",
    "wof:name":"Kolea",
    "wof:placetype":"locality"
},
  "geometry": {"coordinates":[-10.6676,13.9819],"type":"Point"}
}