{
  "type": "Feature",
  "properties": {
    "gn:admin1_code":"3.0",
    "gn:asciiname":"Bandiougoula",
    "gn:country_code":"ML",
    "gn:dem":114,
    "gn:feature_class":"P",
    "gn:feature_code":"PPL",
    "gn:name":"Bandiougoula",
    "gn:population":0,
    "gn:timezone":"Africa/Bamako",
    "iso:country":"ML",
    "name:und_x_variant":[
        "Badiougoula",
        "Bandiougoula"
    ],
    "wof:name":"Bandiougoula",
    "wof:placetype":"locality"
},
  "geometry": {"coordinates":[-10.50674,15.24687],"type":"Point"}
}