{
  "type": "Feature",
  "properties": {
    "gn:admin1_code":"03",
    "gn:asciiname":"Saboussire",
    "gn:country_code":"ML",
    "gn:dem":258,
    "gn:feature_class":"P",
    "gn:feature_code":"PPL",
    "gn:name":"Saboussir\u00e9",
    "gn:population":0,
    "gn:timezone":"Africa/Bamako",
    "iso:country":"ML",
    "name:und_x_variant":[
        "Saboucir\u00e9",
        "Saboussir\u00e9"
    ],
    "wof:name":"Saboussire",
    "wof:placetype":"locality"
},
  "geometry": {"coordinates":[-9.75479,14.47313],"type":"Point"}
}