{
  "type": "Feature",
  "properties": {
    "gn:admin1_code":"03",
    "gn:asciiname":"Moulane",
    "gn:country_code":"ML",
    "gn:dem":128,
    "gn:feature_class":"P",
    "gn:feature_code":"PPL",
    "gn:name":"Moulan\u00e9",
    "gn:population":0,
    "gn:timezone":"Africa/Bamako",
    "iso:country":"ML",
    "wof:name":"Moulane",
    "wof:placetype":"locality"
},
  "geometry": {"coordinates":[-10.7288,14.5335],"type":"Point"}
}