{
  "type": "Feature",
  "properties": {
    "gn:admin1_code":"3.0",
    "gn:asciiname":"Darsilami",
    "gn:country_code":"ML",
    "gn:dem":39,
    "gn:feature_class":"P",
    "gn:feature_code":"PPL",
    "gn:name":"Darsilami",
    "gn:population":0,
    "gn:timezone":"Africa/Bamako",
    "iso:country":"ML",
    "wof:name":"Darsilami",
    "wof:placetype":"locality"
},
  "geometry": {"coordinates":[-11.53981,14.48513],"type":"Point"}
}