{
  "type": "Feature",
  "properties": {
    "gn:admin1_code":"6.0",
    "gn:asciiname":"Ntorola",
    "gn:country_code":"ML",
    "gn:dem":335,
    "gn:feature_class":"P",
    "gn:feature_code":"PPL",
    "gn:name":"Ntorola",
    "gn:population":0,
    "gn:timezone":"Africa/Bamako",
    "iso:country":"ML",
    "wof:name":"Ntorola",
    "wof:placetype":"locality"
},
  "geometry": {"coordinates":[-5.7031,12.2874],"type":"Point"}
}