{
  "type": "Feature",
  "properties": {
    "gn:admin1_code":"00",
    "gn:asciiname":"Linnguekoto",
    "gn:country_code":"ML",
    "gn:dem":348,
    "gn:feature_class":"P",
    "gn:feature_code":"PPL",
    "gn:name":"Linngu\u00e9koto",
    "gn:population":0,
    "gn:timezone":"Africa/Bamako",
    "iso:country":"ML",
    "wof:name":"Linnguekoto",
    "wof:placetype":"locality"
},
  "geometry": {"coordinates":[-9.41667,13.31667],"type":"Point"}
}