{
  "type": "Feature",
  "properties": {
    "gn:admin1_code":"03",
    "gn:asciiname":"Sidiantinti",
    "gn:country_code":"ML",
    "gn:dem":328,
    "gn:feature_class":"P",
    "gn:feature_code":"PPL",
    "gn:name":"Sidiantinti",
    "gn:population":0,
    "gn:timezone":"Africa/Bamako",
    "iso:country":"ML",
    "wof:name":"Sidiantinti",
    "wof:placetype":"locality"
},
  "geometry": {"coordinates":[-10.2622,14.0649],"type":"Point"}
}