{
  "type": "Feature",
  "properties": {
    "gn:admin1_code":"7.0",
    "gn:asciiname":"Sodoba",
    "gn:country_code":"ML",
    "gn:dem":408,
    "gn:feature_class":"P",
    "gn:feature_code":"PPL",
    "gn:name":"Sodoba",
    "gn:population":0,
    "gn:timezone":"Africa/Bamako",
    "iso:country":"ML",
    "wof:name":"Sodoba",
    "wof:placetype":"locality"
},
  "geometry": {"coordinates":[-7.49467,13.53655],"type":"Point"}
}