{
  "type": "Feature",
  "properties": {
    "gn:admin1_code":"7.0",
    "gn:asciiname":"Kodanko",
    "gn:country_code":"ML",
    "gn:dem":373,
    "gn:feature_class":"P",
    "gn:feature_code":"PPL",
    "gn:name":"Kodanko",
    "gn:population":0,
    "gn:timezone":"Africa/Bamako",
    "iso:country":"ML",
    "wof:name":"Kodanko",
    "wof:placetype":"locality"
},
  "geometry": {"coordinates":[-8.49837,12.20759],"type":"Point"}
}