{
  "type": "Feature",
  "properties": {
    "gn:admin1_code":"00",
    "gn:asciiname":"Sebenekeli",
    "gn:country_code":"ML",
    "gn:dem":368,
    "gn:feature_class":"P",
    "gn:feature_code":"PPL",
    "gn:name":"S\u00e9b\u00e9n\u00e9k\u00e9li",
    "gn:population":0,
    "gn:timezone":"Africa/Bamako",
    "iso:country":"ML",
    "wof:name":"Sebenekeli",
    "wof:placetype":"locality"
},
  "geometry": {"coordinates":[-9.65,12.53333],"type":"Point"}
}