{
  "type": "Feature",
  "properties": {
    "gn:admin1_code":"07",
    "gn:asciiname":"Kanyema",
    "gn:country_code":"ML",
    "gn:dem":313,
    "gn:feature_class":"P",
    "gn:feature_code":"PPL",
    "gn:name":"Kany\u00e9ma",
    "gn:population":0,
    "gn:timezone":"Africa/Bamako",
    "iso:country":"ML",
    "name:fra_x_preferred":[
        "Kany\u00e9ma"
    ],
    "name:fra_x_variant":[
        "Kaniena"
    ],
    "wof:name":"Kanyema",
    "wof:placetype":"locality"
},
  "geometry": {"coordinates":[-6.0527,12.2513],"type":"Point"}
}