{
  "type": "Feature",
  "properties": {
    "gn:admin1_code":"03",
    "gn:asciiname":"Kassi-Kara",
    "gn:country_code":"ML",
    "gn:dem":290,
    "gn:feature_class":"P",
    "gn:feature_code":"PPL",
    "gn:name":"Kassi-Kara",
    "gn:population":0,
    "gn:timezone":"Africa/Bamako",
    "iso:country":"ML",
    "wof:name":"Kassi-Kara",
    "wof:placetype":"locality"
},
  "geometry": {"coordinates":[-9.2778,14.866],"type":"Point"}
}