{
  "type": "Feature",
  "properties": {
    "gn:admin1_code":"04",
    "gn:asciiname":"Yaso",
    "gn:country_code":"ML",
    "gn:dem":349,
    "gn:feature_class":"P",
    "gn:feature_code":"PPL",
    "gn:name":"Yaso",
    "gn:population":0,
    "gn:timezone":"Africa/Bamako",
    "iso:country":"ML",
    "name:und_x_variant":[
        "Yasso",
        "Yaso"
    ],
    "wof:name":"Yaso",
    "wof:placetype":"locality"
},
  "geometry": {"coordinates":[-3.67609,14.132],"type":"Point"}
}