{
  "type": "Feature",
  "properties": {
    "gn:admin1_code":"04",
    "gn:asciiname":"Tiambavel",
    "gn:country_code":"ML",
    "gn:dem":275,
    "gn:feature_class":"P",
    "gn:feature_code":"PPL",
    "gn:name":"Tiambavel",
    "gn:population":0,
    "gn:timezone":"Africa/Bamako",
    "iso:country":"ML",
    "name:und_x_variant":[
        "Tianbegel",
        "Tiambaouel",
        "Tiambavel"
    ],
    "wof:name":"Tiambavel",
    "wof:placetype":"locality"
},
  "geometry": {"coordinates":[-4.70137,14.96287],"type":"Point"}
}