{
  "type": "Feature",
  "properties": {
    "gn:admin1_code":"08",
    "gn:asciiname":"Garnati",
    "gn:country_code":"ML",
    "gn:dem":270,
    "gn:feature_class":"P",
    "gn:feature_code":"PPL",
    "gn:name":"Garnati",
    "gn:population":0,
    "gn:timezone":"Africa/Bamako",
    "iso:country":"ML",
    "name:und_x_variant":[
        "Gaman",
        "Garnati"
    ],
    "wof:name":"Garnati",
    "wof:placetype":"locality"
},
  "geometry": {"coordinates":[-3.5089,15.8247],"type":"Point"}
}