{
  "type": "Feature",
  "properties": {
    "gn:admin1_code":"00",
    "gn:asciiname":"Kondoroubougou",
    "gn:country_code":"ML",
    "gn:dem":170,
    "gn:feature_class":"P",
    "gn:feature_code":"PPL",
    "gn:name":"Kondoroubougou",
    "gn:population":0,
    "gn:timezone":"Africa/Bamako",
    "iso:country":"ML",
    "wof:name":"Kondoroubougou",
    "wof:placetype":"locality"
},
  "geometry": {"coordinates":[-11.03333,13.45],"type":"Point"}
}