{
  "type": "Feature",
  "properties": {
    "gn:admin1_code":"07",
    "gn:asciiname":"Sanankoro",
    "gn:country_code":"ML",
    "gn:dem":375,
    "gn:feature_class":"P",
    "gn:feature_code":"PPL",
    "gn:name":"Sanankoro",
    "gn:population":0,
    "gn:timezone":"Africa/Bamako",
    "iso:country":"ML",
    "name:und_x_variant":[
        "Sankoro",
        "Sanankoro"
    ],
    "wof:name":"Sanankoro",
    "wof:placetype":"locality"
},
  "geometry": {"coordinates":[-7.07024,12.95733],"type":"Point"}
}