{
  "type": "Feature",
  "properties": {
    "gn:admin1_code":"7.0",
    "gn:asciiname":"Kinndo",
    "gn:country_code":"ML",
    "gn:dem":438,
    "gn:feature_class":"P",
    "gn:feature_code":"PPL",
    "gn:name":"Kinndo",
    "gn:population":0,
    "gn:timezone":"Africa/Bamako",
    "iso:country":"ML",
    "wof:name":"Kinndo",
    "wof:placetype":"locality"
},
  "geometry": {"coordinates":[-8.1536,13.6345],"type":"Point"}
}