{
  "type": "Feature",
  "properties": {
    "gn:admin1_code":"1.0",
    "gn:asciiname":"Djelibougou",
    "gn:country_code":"ML",
    "gn:dem":362,
    "gn:feature_class":"P",
    "gn:feature_code":"PPL",
    "gn:name":"Djelibougou",
    "gn:population":0,
    "gn:timezone":"Africa/Bamako",
    "iso:country":"ML",
    "wof:name":"Djelibougou",
    "wof:placetype":"locality"
},
  "geometry": {"coordinates":[-7.95278,12.69417],"type":"Point"}
}