{
  "type": "Feature",
  "properties": {
    "gn:admin1_code":"05",
    "gn:asciiname":"Tetou",
    "gn:country_code":"ML",
    "gn:dem":385,
    "gn:feature_class":"P",
    "gn:feature_code":"PPL",
    "gn:name":"T\u00e9tou",
    "gn:population":0,
    "gn:timezone":"Africa/Bamako",
    "iso:country":"ML",
    "name:und_x_variant":[
        "Tetuu",
        "T\u00e9tou"
    ],
    "wof:name":"Tetou",
    "wof:placetype":"locality"
},
  "geometry": {"coordinates":[-4.3265,12.9575],"type":"Point"}
}