{
  "type": "Feature",
  "properties": {
    "gn:admin1_code":"05",
    "gn:asciiname":"Tyentyenbougou",
    "gn:country_code":"ML",
    "gn:dem":277,
    "gn:feature_class":"P",
    "gn:feature_code":"PPL",
    "gn:name":"Ty\u00e8nty\u00e8nbougou",
    "gn:population":0,
    "gn:timezone":"Africa/Bamako",
    "iso:country":"ML",
    "wof:name":"Tyentyenbougou",
    "wof:placetype":"locality"
},
  "geometry": {"coordinates":[-6.0247,14.7694],"type":"Point"}
}