{
  "type": "Feature",
  "properties": {
    "gn:admin1_code":"09",
    "gn:asciiname":"Seina Bela Forgandi",
    "gn:country_code":"ML",
    "gn:dem":246,
    "gn:feature_class":"P",
    "gn:feature_code":"PPL",
    "gn:name":"Se\u00efna Bela Forgandi",
    "gn:population":0,
    "gn:timezone":"Africa/Bamako",
    "iso:country":"ML",
    "wof:name":"Seina Bela Forgandi",
    "wof:placetype":"locality"
},
  "geometry": {"coordinates":[0.5036,15.6222],"type":"Point"}
}