{
  "type": "Feature",
  "properties": {
    "gn:admin1_code":"05",
    "gn:asciiname":"Missibougou",
    "gn:country_code":"ML",
    "gn:dem":281,
    "gn:feature_class":"P",
    "gn:feature_code":"PPL",
    "gn:name":"Missibougou",
    "gn:population":0,
    "gn:timezone":"Africa/Bamako",
    "iso:country":"ML",
    "wof:name":"Missibougou",
    "wof:placetype":"locality"
},
  "geometry": {"coordinates":[-5.6923,14.0802],"type":"Point"}
}