{
  "type": "Feature",
  "properties": {
    "gn:admin1_code":"4.0",
    "gn:asciiname":"Ologo",
    "gn:country_code":"ML",
    "gn:dem":510,
    "gn:feature_class":"P",
    "gn:feature_code":"PPL",
    "gn:name":"Ologo",
    "gn:population":0,
    "gn:timezone":"Africa/Bamako",
    "iso:country":"ML",
    "wof:name":"Ologo",
    "wof:placetype":"locality"
},
  "geometry": {"coordinates":[-3.47199,14.7141],"type":"Point"}
}