{
  "type": "Feature",
  "properties": {
    "gn:admin1_code":"7.0",
    "gn:asciiname":"Kouwanta",
    "gn:country_code":"ML",
    "gn:dem":281,
    "gn:feature_class":"P",
    "gn:feature_code":"PPL",
    "gn:name":"Kouwanta",
    "gn:population":0,
    "gn:timezone":"Africa/Bamako",
    "iso:country":"ML",
    "wof:name":"Kouwanta",
    "wof:placetype":"locality"
},
  "geometry": {"coordinates":[-6.8699,14.3175],"type":"Point"}
}