{
  "type": "Feature",
  "properties": {
    "gn:admin1_code":"04",
    "gn:asciiname":"Siratinti",
    "gn:country_code":"ML",
    "gn:dem":261,
    "gn:feature_class":"P",
    "gn:feature_code":"PPL",
    "gn:name":"Siratinti",
    "gn:population":0,
    "gn:timezone":"Africa/Bamako",
    "iso:country":"ML",
    "name:und_x_variant":[
        "Siratinnti",
        "Siratinti"
    ],
    "wof:name":"Siratinti",
    "wof:placetype":"locality"
},
  "geometry": {"coordinates":[-3.4814,13.7271],"type":"Point"}
}