{
  "type": "Feature",
  "properties": {
    "gn:admin1_code":"00",
    "gn:asciiname":"Naouena",
    "gn:cc2":"ML",
    "gn:country_code":"ML",
    "gn:dem":372,
    "gn:feature_class":"P",
    "gn:feature_code":"PPL",
    "gn:name":"Naou\u00e9na",
    "gn:population":0,
    "gn:timezone":"Africa/Bamako",
    "iso:country":"ML",
    "name:und_x_variant":[
        "Naw\u00e9na",
        "Naou\u00e9na"
    ],
    "wof:name":"Naouena",
    "wof:placetype":"locality"
},
  "geometry": {"coordinates":[-7.15,10.48333],"type":"Point"}
}