{
  "type": "Feature",
  "properties": {
    "gn:admin1_code":"3.0",
    "gn:asciiname":"Deide",
    "gn:country_code":"ML",
    "gn:dem":105,
    "gn:feature_class":"P",
    "gn:feature_code":"PPL",
    "gn:name":"D\u00e9\u00efd\u00e9",
    "gn:population":0,
    "gn:timezone":"Africa/Bamako",
    "iso:country":"ML",
    "wof:name":"Deide",
    "wof:placetype":"locality"
},
  "geometry": {"coordinates":[-11.44846,15.30306],"type":"Point"}
}