{
  "type": "Feature",
  "properties": {
    "gn:admin1_code":"6.0",
    "gn:asciiname":"Faboulabougou",
    "gn:country_code":"ML",
    "gn:dem":331,
    "gn:feature_class":"P",
    "gn:feature_code":"PPL",
    "gn:name":"Faboulabougou",
    "gn:population":0,
    "gn:timezone":"Africa/Bamako",
    "iso:country":"ML",
    "wof:name":"Faboulabougou",
    "wof:placetype":"locality"
},
  "geometry": {"coordinates":[-6.25032,11.32921],"type":"Point"}
}