{
  "type": "Feature",
  "properties": {
    "gn:admin1_code":"8.0",
    "gn:asciiname":"Bangadarya-Abadyouma",
    "gn:country_code":"ML",
    "gn:dem":265,
    "gn:feature_class":"P",
    "gn:feature_code":"PPL",
    "gn:name":"Bangadarya-Abadyouma",
    "gn:population":0,
    "gn:timezone":"Africa/Bamako",
    "iso:country":"ML",
    "wof:name":"Bangadarya-Abadyouma",
    "wof:placetype":"locality"
},
  "geometry": {"coordinates":[-3.56395,16.01297000000001],"type":"Point"}
}