{
  "type": "Feature",
  "properties": {
    "gn:admin1_code":"04",
    "gn:asciiname":"Ororo",
    "gn:country_code":"ML",
    "gn:dem":270,
    "gn:feature_class":"P",
    "gn:feature_code":"PPL",
    "gn:name":"Ororo",
    "gn:population":0,
    "gn:timezone":"Africa/Bamako",
    "iso:country":"ML",
    "name:und_x_variant":[
        "Ouero",
        "Ouoro",
        "Ororo"
    ],
    "wof:name":"Ororo",
    "wof:placetype":"locality"
},
  "geometry": {"coordinates":[-3.4249,15.4162],"type":"Point"}
}