{
  "type": "Feature",
  "properties": {
    "gn:admin1_code":"07",
    "gn:asciiname":"Siradou",
    "gn:country_code":"ML",
    "gn:dem":325,
    "gn:feature_class":"P",
    "gn:feature_code":"PPL",
    "gn:name":"Siradou",
    "gn:population":0,
    "gn:timezone":"Africa/Bamako",
    "iso:country":"ML",
    "name:und_x_variant":[
        "Sirado",
        "Siradou"
    ],
    "wof:name":"Siradou",
    "wof:placetype":"locality"
},
  "geometry": {"coordinates":[-8.1408,14.2512],"type":"Point"}
}