{
  "type": "Feature",
  "properties": {
    "gn:admin1_code":"00",
    "gn:asciiname":"Yorola",
    "gn:country_code":"ML",
    "gn:dem":389,
    "gn:feature_class":"P",
    "gn:feature_code":"PPL",
    "gn:name":"Yorola",
    "gn:population":0,
    "gn:timezone":"Africa/Bamako",
    "iso:country":"ML",
    "wof:name":"Yorola",
    "wof:placetype":"locality"
},
  "geometry": {"coordinates":[-8.23333,11.38333],"type":"Point"}
}