{
  "type": "Feature",
  "properties": {
    "gn:admin1_code":"05",
    "gn:asciiname":"Koba",
    "gn:country_code":"ML",
    "gn:dem":279,
    "gn:feature_class":"P",
    "gn:feature_code":"PPL",
    "gn:name":"Koba",
    "gn:population":0,
    "gn:timezone":"Africa/Bamako",
    "iso:country":"ML",
    "name:ceb_x_preferred":[
        "Koba"
    ],
    "name:deu_x_preferred":[
        "Koba"
    ],
    "name:fra_x_preferred":[
        "Koba"
    ],
    "name:ita_x_preferred":[
        "Koba"
    ],
    "name:nld_x_preferred":[
        "Koba"
    ],
    "name:rus_x_preferred":[
        "\u041a\u043e\u0431\u0430"
    ],
    "name:srp_x_preferred":[
        "\u041a\u043e\u0431\u0430"
    ],
    "name:swe_x_preferred":[
        "Koba"
    ],
    "wof:name":"Koba",
    "wof:placetype":"locality"
},
  "geometry": {"coordinates":[-5.45126,13.50119],"type":"Point"}
}