{
  "type": "Feature",
  "properties": {
    "gn:admin1_code":"4.0",
    "gn:asciiname":"Poha",
    "gn:country_code":"ML",
    "gn:dem":273,
    "gn:feature_class":"P",
    "gn:feature_code":"PPL",
    "gn:name":"Poha",
    "gn:population":0,
    "gn:timezone":"Africa/Bamako",
    "iso:country":"ML",
    "wof:name":"Poha",
    "wof:placetype":"locality"
},
  "geometry": {"coordinates":[-4.26947,14.31564],"type":"Point"}
}