{
  "type": "Feature",
  "properties": {
    "gn:admin1_code":"07",
    "gn:asciiname":"Soukourani",
    "gn:country_code":"ML",
    "gn:dem":336,
    "gn:feature_class":"P",
    "gn:feature_code":"PPL",
    "gn:name":"Soukourani",
    "gn:population":0,
    "gn:timezone":"Africa/Bamako",
    "iso:country":"ML",
    "name:fra_x_preferred":[
        "Soukourani"
    ],
    "wof:name":"Soukourani",
    "wof:placetype":"locality"
},
  "geometry": {"coordinates":[-6.9579,12.1538],"type":"Point"}
}