{
  "type": "Feature",
  "properties": {
    "gn:admin1_code":"05",
    "gn:asciiname":"Wendoubougou",
    "gn:country_code":"ML",
    "gn:dem":340,
    "gn:feature_class":"P",
    "gn:feature_code":"PPL",
    "gn:name":"Wendoubougou",
    "gn:population":0,
    "gn:timezone":"Africa/Bamako",
    "iso:country":"ML",
    "name:fra_x_preferred":[
        "Wendoubougou"
    ],
    "wof:name":"Wendoubougou",
    "wof:placetype":"locality"
},
  "geometry": {"coordinates":[-6.65,12.83333],"type":"Point"}
}