{
  "type": "Feature",
  "properties": {
    "gn:admin1_code":"7.0",
    "gn:asciiname":"Dialakorobougou",
    "gn:country_code":"ML",
    "gn:dem":304,
    "gn:feature_class":"P",
    "gn:feature_code":"PPL",
    "gn:name":"Dialakorobougou",
    "gn:population":0,
    "gn:timezone":"Africa/Bamako",
    "iso:country":"ML",
    "wof:name":"Dialakorobougou",
    "wof:placetype":"locality"
},
  "geometry": {"coordinates":[-7.65996,12.80849],"type":"Point"}
}