{
  "type": "Feature",
  "properties": {
    "gn:admin1_code":"07",
    "gn:asciiname":"Tiafahina",
    "gn:country_code":"ML",
    "gn:dem":352,
    "gn:feature_class":"P",
    "gn:feature_code":"PPL",
    "gn:name":"Tiafahina",
    "gn:population":0,
    "gn:timezone":"Africa/Bamako",
    "iso:country":"ML",
    "name:fra_x_preferred":[
        "Tiafahina"
    ],
    "name:fra_x_variant":[
        "Tiafina"
    ],
    "name:und_x_variant":[
        "Tiafina"
    ],
    "wof:name":"Tiafahina",
    "wof:placetype":"locality"
},
  "geometry": {"coordinates":[-8.2132,13.7039],"type":"Point"}
}