{
  "type": "Feature",
  "properties": {
    "gn:admin1_code":"04",
    "gn:asciiname":"Ouro-Ndia",
    "gn:country_code":"ML",
    "gn:dem":270,
    "gn:feature_class":"P",
    "gn:feature_code":"PPL",
    "gn:name":"Ouro-Ndia",
    "gn:population":0,
    "gn:timezone":"Africa/Bamako",
    "iso:country":"ML",
    "wof:name":"Ouro-Ndia",
    "wof:placetype":"locality"
},
  "geometry": {"coordinates":[-4.6049,15.0786],"type":"Point"}
}