{
  "type": "Feature",
  "properties": {
    "gn:admin1_code":"5.0",
    "gn:asciiname":"Koundiadaga",
    "gn:country_code":"ML",
    "gn:dem":291,
    "gn:feature_class":"P",
    "gn:feature_code":"PPL",
    "gn:name":"Koundiadaga",
    "gn:population":0,
    "gn:timezone":"Africa/Bamako",
    "iso:country":"ML",
    "wof:name":"Koundiadaga",
    "wof:placetype":"locality"
},
  "geometry": {"coordinates":[-4.1986,13.778],"type":"Point"}
}