{
  "type": "Feature",
  "properties": {
    "gn:admin1_code":"07",
    "gn:asciiname":"Dinan Marka",
    "gn:country_code":"ML",
    "gn:dem":299,
    "gn:feature_class":"P",
    "gn:feature_code":"PPL",
    "gn:name":"Dinan Marka",
    "gn:population":0,
    "gn:timezone":"Africa/Bamako",
    "iso:country":"ML",
    "name:und_x_variant":[
        "Dinan",
        "Dinan Marka"
    ],
    "wof:name":"Dinan Marka",
    "wof:placetype":"locality"
},
  "geometry": {"coordinates":[-7.34564,13.04243],"type":"Point"}
}