{
  "type": "Feature",
  "properties": {
    "gn:admin1_code":"03",
    "gn:asciiname":"Monsombougou",
    "gn:country_code":"ML",
    "gn:dem":256,
    "gn:feature_class":"P",
    "gn:feature_code":"PPL",
    "gn:name":"Monsombougou",
    "gn:population":0,
    "gn:timezone":"Africa/Bamako",
    "iso:country":"ML",
    "wof:name":"Monsombougou",
    "wof:placetype":"locality"
},
  "geometry": {"coordinates":[-10.0218,14.9805],"type":"Point"}
}