{
  "type": "Feature",
  "properties": {
    "gn:admin1_code":"07",
    "gn:asciiname":"Nianzana",
    "gn:country_code":"ML",
    "gn:dem":351,
    "gn:feature_class":"P",
    "gn:feature_code":"PPL",
    "gn:name":"Nianzana",
    "gn:population":0,
    "gn:timezone":"Africa/Bamako",
    "iso:country":"ML",
    "name:und_x_variant":[
        "Niansana",
        "Nyanzana",
        "Nianzana"
    ],
    "wof:name":"Nianzana",
    "wof:placetype":"locality"
},
  "geometry": {"coordinates":[-7.7377,12.2267],"type":"Point"}
}