{
  "type": "Feature",
  "properties": {
    "gn:admin1_code":"03",
    "gn:asciiname":"Diongui Diongui",
    "gn:country_code":"ML",
    "gn:dem":269,
    "gn:feature_class":"P",
    "gn:feature_code":"PPL",
    "gn:name":"Diongui Diongui",
    "gn:population":0,
    "gn:timezone":"Africa/Bamako",
    "iso:country":"ML",
    "wof:name":"Diongui Diongui",
    "wof:placetype":"locality"
},
  "geometry": {"coordinates":[-9.78773,15.05602],"type":"Point"}
}