{
  "type": "Feature",
  "properties": {
    "gn:admin1_code":"04",
    "gn:asciiname":"Tako",
    "gn:country_code":"ML",
    "gn:dem":274,
    "gn:feature_class":"P",
    "gn:feature_code":"PPL",
    "gn:name":"Tako",
    "gn:population":0,
    "gn:timezone":"Africa/Bamako",
    "iso:country":"ML",
    "name:ceb_x_preferred":[
        "Tako"
    ],
    "name:deu_x_preferred":[
        "Tako"
    ],
    "name:jpn_x_preferred":[
        "\u30bf\u30b3"
    ],
    "name:rus_x_preferred":[
        "\u0422\u0430\u043a\u043e"
    ],
    "name:swe_x_preferred":[
        "Tako"
    ],
    "name:ukr_x_preferred":[
        "\u0422\u0430\u043a\u043e"
    ],
    "wof:name":"Tako",
    "wof:placetype":"locality"
},
  "geometry": {"coordinates":[-4.5134,13.7611],"type":"Point"}
}