{
  "type": "Feature",
  "properties": {
    "gn:admin1_code":"06",
    "gn:asciiname":"Niomassala",
    "gn:country_code":"ML",
    "gn:dem":360,
    "gn:feature_class":"P",
    "gn:feature_code":"PPL",
    "gn:name":"Niomassala",
    "gn:population":0,
    "gn:timezone":"Africa/Bamako",
    "iso:country":"ML",
    "wof:name":"Niomassala",
    "wof:placetype":"locality"
},
  "geometry": {"coordinates":[-7.72956,11.0008],"type":"Point"}
}