{
  "type": "Feature",
  "properties": {
    "gn:admin1_code":"7.0",
    "gn:asciiname":"Niamakorola",
    "gn:country_code":"ML",
    "gn:dem":326,
    "gn:feature_class":"P",
    "gn:feature_code":"PPL",
    "gn:name":"Niamakorola",
    "gn:population":0,
    "gn:timezone":"Africa/Bamako",
    "iso:country":"ML",
    "wof:name":"Niamakorola",
    "wof:placetype":"locality"
},
  "geometry": {"coordinates":[-8.14537,12.29459],"type":"Point"}
}