{
  "type": "Feature",
  "properties": {
    "gn:admin1_code":"6.0",
    "gn:asciiname":"Kaniena",
    "gn:country_code":"ML",
    "gn:dem":421,
    "gn:feature_class":"P",
    "gn:feature_code":"PPL",
    "gn:name":"Kani\u00e9na",
    "gn:population":0,
    "gn:timezone":"Africa/Bamako",
    "iso:country":"ML",
    "wof:name":"Kaniena",
    "wof:placetype":"locality"
},
  "geometry": {"coordinates":[-5.90811,11.22121],"type":"Point"}
}