{
  "type": "Feature",
  "properties": {
    "gn:admin1_code":"04",
    "gn:asciiname":"Kersani",
    "gn:country_code":"ML",
    "gn:dem":269,
    "gn:feature_class":"P",
    "gn:feature_code":"PPL",
    "gn:name":"Kersani",
    "gn:population":0,
    "gn:timezone":"Africa/Bamako",
    "iso:country":"ML",
    "name:und_x_variant":[
        "Karsani",
        "Kersani"
    ],
    "wof:name":"Kersani",
    "wof:placetype":"locality"
},
  "geometry": {"coordinates":[-3.16064,15.47602],"type":"Point"}
}