{
  "type": "Feature",
  "properties": {
    "gn:admin1_code":"06",
    "gn:asciiname":"Kola",
    "gn:country_code":"ML",
    "gn:dem":351,
    "gn:feature_class":"P",
    "gn:feature_code":"PPL",
    "gn:name":"Kola",
    "gn:population":0,
    "gn:timezone":"Africa/Bamako",
    "iso:country":"ML",
    "name:aze_x_preferred":[
        "Kola"
    ],
    "name:bos_x_preferred":[
        "Kola"
    ],
    "name:bul_x_preferred":[
        "\u041a\u043e\u043b\u0430"
    ],
    "name:ceb_x_preferred":[
        "Kola"
    ],
    "name:ces_x_preferred":[
        "Kola"
    ],
    "name:chv_x_preferred":[
        "\u041a\u043e\u043b\u0430"
    ],
    "name:deu_x_preferred":[
        "Kola"
    ],
    "name:epo_x_preferred":[
        "Kola"
    ],
    "name:eus_x_preferred":[
        "Kola"
    ],
    "name:fin_x_preferred":[
        "Kola"
    ],
    "name:fra_x_preferred":[
        "Kola"
    ],
    "name:hrv_x_preferred":[
        "Kola"
    ],
    "name:hsb_x_preferred":[
        "Kola"
    ],
    "name:ita_x_preferred":[
        "Kola"
    ],
    "name:jpn_x_preferred":[
        "\u30b3\u30fc\u30e9"
    ],
    "name:kat_x_preferred":[
        "\u10d9\u10dd\u10da\u10d0"
    ],
    "name:kor_x_preferred":[
        "\ucf5c\ub77c"
    ],
    "name:lat_x_preferred":[
        "Kola"
    ],
    "name:lav_x_preferred":[
        "Kola"
    ],
    "name:lit_x_preferred":[
        "Kola"
    ],
    "name:ltz_x_preferred":[
        "Kola"
    ],
    "name:mkd_x_preferred":[
        "\u041a\u043e\u043b\u0430"
    ],
    "name:nld_x_preferred":[
        "Kola"
    ],
    "name:nor_x_preferred":[
        "Kola"
    ],
    "name:pol_x_preferred":[
        "Kola"
    ],
    "name:rus_x_preferred":[
        "\u041a\u043e\u043b\u0430"
    ],
    "name:slk_x_preferred":[
        "Kola"
    ],
    "name:spa_x_preferred":[
        "Kola"
    ],
    "name:srp_x_preferred":[
        "\u041a\u043e\u043b\u0430"
    ],
    "name:swe_x_preferred":[
        "Kola"
    ],
    "name:tgl_x_preferred":[
        "Kola"
    ],
    "name:ukr_x_preferred":[
        "\u041a\u043e\u043b\u0430"
    ],
    "wof:name":"Kola",
    "wof:placetype":"locality"
},
  "geometry": {"coordinates":[-5.79629,12.59973],"type":"Point"}
}