{
  "type": "Feature",
  "properties": {
    "gn:admin1_code":"05",
    "gn:asciiname":"Lanfiera",
    "gn:country_code":"ML",
    "gn:dem":324,
    "gn:feature_class":"P",
    "gn:feature_code":"PPL",
    "gn:name":"Lanfi\u00e9ra",
    "gn:population":0,
    "gn:timezone":"Africa/Bamako",
    "iso:country":"ML",
    "name:und_x_variant":[
        "Lanf\u00e9ria",
        "Lanfi\u00e9ra"
    ],
    "wof:name":"Lanfiera",
    "wof:placetype":"locality"
},
  "geometry": {"coordinates":[-4.1487,13.4939],"type":"Point"}
}