{
  "type": "Feature",
  "properties": {
    "gn:admin1_code":"5.0",
    "gn:asciiname":"Kambabakabougou",
    "gn:country_code":"ML",
    "gn:dem":314,
    "gn:feature_class":"P",
    "gn:feature_code":"PPL",
    "gn:name":"Kambabakabougou",
    "gn:population":0,
    "gn:timezone":"Africa/Bamako",
    "iso:country":"ML",
    "wof:name":"Kambabakabougou",
    "wof:placetype":"locality"
},
  "geometry": {"coordinates":[-6.93581,13.18092],"type":"Point"}
}