{
  "type": "Feature",
  "properties": {
    "gn:admin1_code":"05",
    "gn:asciiname":"Fadabougou",
    "gn:country_code":"ML",
    "gn:dem":324,
    "gn:feature_class":"P",
    "gn:feature_code":"PPL",
    "gn:name":"Fadabougou",
    "gn:population":0,
    "gn:timezone":"Africa/Bamako",
    "iso:country":"ML",
    "name:fra_x_preferred":[
        "Fadabougou"
    ],
    "wof:name":"Fadabougou",
    "wof:placetype":"locality"
},
  "geometry": {"coordinates":[-6.7098,12.92421],"type":"Point"}
}