{
  "type": "Feature",
  "properties": {
    "gn:admin1_code":"6.0",
    "gn:asciiname":"Pornonbougou",
    "gn:country_code":"ML",
    "gn:dem":407,
    "gn:feature_class":"P",
    "gn:feature_code":"PPL",
    "gn:name":"Pornonbougou",
    "gn:population":0,
    "gn:timezone":"Africa/Bamako",
    "iso:country":"ML",
    "wof:name":"Pornonbougou",
    "wof:placetype":"locality"
},
  "geometry": {"coordinates":[-5.48415,11.31875],"type":"Point"}
}