{
  "type": "Feature",
  "properties": {
    "gn:admin1_code":"7.0",
    "gn:asciiname":"Kelekabougou",
    "gn:country_code":"ML",
    "gn:dem":394,
    "gn:feature_class":"P",
    "gn:feature_code":"PPL",
    "gn:name":"K\u00e9l\u00e9kabougou",
    "gn:population":0,
    "gn:timezone":"Africa/Bamako",
    "iso:country":"ML",
    "wof:name":"Kelekabougou",
    "wof:placetype":"locality"
},
  "geometry": {"coordinates":[-7.93867,13.18546],"type":"Point"}
}