{
  "type": "Feature",
  "properties": {
    "gn:admin1_code":"09",
    "gn:asciiname":"Goutchoum Gargouna",
    "gn:country_code":"ML",
    "gn:dem":247,
    "gn:feature_class":"P",
    "gn:feature_code":"PPL",
    "gn:name":"Goutchoum Gargouna",
    "gn:population":0,
    "gn:timezone":"Africa/Bamako",
    "iso:country":"ML",
    "wof:name":"Goutchoum Gargouna",
    "wof:placetype":"locality"
},
  "geometry": {"coordinates":[0.2959,15.8282],"type":"Point"}
}