{
  "type": "Feature",
  "properties": {
    "gn:admin1_code":"03",
    "gn:asciiname":"Nienngue",
    "gn:country_code":"ML",
    "gn:dem":158,
    "gn:feature_class":"P",
    "gn:feature_code":"PPL",
    "gn:name":"Nienngu\u00e9",
    "gn:population":0,
    "gn:timezone":"Africa/Bamako",
    "iso:country":"ML",
    "wof:name":"Nienngue",
    "wof:placetype":"locality"
},
  "geometry": {"coordinates":[-11.57736,13.69371],"type":"Point"}
}