{
  "type": "Feature",
  "properties": {
    "gn:admin1_code":"7.0",
    "gn:asciiname":"Ouessebougouni",
    "gn:country_code":"ML",
    "gn:dem":339,
    "gn:feature_class":"P",
    "gn:feature_code":"PPL",
    "gn:name":"Ou\u00e9ss\u00e9bougouni",
    "gn:population":0,
    "gn:timezone":"Africa/Bamako",
    "iso:country":"ML",
    "wof:name":"Ouessebougouni",
    "wof:placetype":"locality"
},
  "geometry": {"coordinates":[-7.63021,13.09811],"type":"Point"}
}