{
  "type": "Feature",
  "properties": {
    "gn:admin1_code":"6.0",
    "gn:asciiname":"Farako",
    "gn:country_code":"ML",
    "gn:dem":312,
    "gn:feature_class":"P",
    "gn:feature_code":"PPL",
    "gn:name":"Farako",
    "gn:population":0,
    "gn:timezone":"Africa/Bamako",
    "iso:country":"ML",
    "name:fin_x_preferred":[
        "Farako"
    ],
    "name:fra_x_preferred":[
        "Farako"
    ],
    "name:ita_x_preferred":[
        "Farako"
    ],
    "name:nld_x_preferred":[
        "Farako"
    ],
    "name:spa_x_preferred":[
        "Farako"
    ],
    "wof:name":"Farako",
    "wof:placetype":"locality"
},
  "geometry": {"coordinates":[-6.57962,11.36217],"type":"Point"}
}