{
  "type": "Feature",
  "properties": {
    "gn:admin1_code":"03",
    "gn:asciiname":"Traorela Guimbala",
    "gn:country_code":"ML",
    "gn:dem":332,
    "gn:feature_class":"P",
    "gn:feature_code":"PPL",
    "gn:name":"Traor\u00e9la Guimbala",
    "gn:population":0,
    "gn:timezone":"Africa/Bamako",
    "iso:country":"ML",
    "name:und_x_variant":[
        "Traol\u00e9la Guimbala",
        "Traor\u00e9la Guimbala",
        "Traol\u00e9la-Guimmbala"
    ],
    "wof:name":"Traorela Guimbala",
    "wof:placetype":"locality"
},
  "geometry": {"coordinates":[-9.35622,13.38146],"type":"Point"}
}