{
  "type": "Feature",
  "properties": {
    "gn:admin1_code":"8.0",
    "gn:asciiname":"Amgoundji",
    "gn:country_code":"ML",
    "gn:dem":260,
    "gn:feature_class":"P",
    "gn:feature_code":"PPL",
    "gn:name":"Amgoundji",
    "gn:population":0,
    "gn:timezone":"Africa/Bamako",
    "iso:country":"ML",
    "name:und_x_variant":[
        "Hamgoudi\u00e9",
        "Hamgounbji",
        "Hamgoundji",
        "Amgoundji"
    ],
    "wof:name":"Amgoundji",
    "wof:placetype":"locality"
},
  "geometry": {"coordinates":[-1.1262,17.0506],"type":"Point"}
}