{
  "type": "Feature",
  "properties": {
    "gn:admin1_code":"05",
    "gn:asciiname":"Terimabougou",
    "gn:country_code":"ML",
    "gn:dem":294,
    "gn:feature_class":"P",
    "gn:feature_code":"PPL",
    "gn:name":"T\u00e9rimabougou",
    "gn:population":0,
    "gn:timezone":"Africa/Bamako",
    "iso:country":"ML",
    "name:und_x_variant":[
        "Tiembougou",
        "Termabougou",
        "T\u00e9rimabougou"
    ],
    "wof:name":"Terimabougou",
    "wof:placetype":"locality"
},
  "geometry": {"coordinates":[-6.78708,13.46551],"type":"Point"}
}