{
  "type": "Feature",
  "properties": {
    "gn:admin1_code":"07",
    "gn:asciiname":"Dakolobougou",
    "gn:country_code":"ML",
    "gn:dem":357,
    "gn:feature_class":"P",
    "gn:feature_code":"PPL",
    "gn:name":"Dakolobougou",
    "gn:population":0,
    "gn:timezone":"Africa/Bamako",
    "iso:country":"ML",
    "wof:name":"Dakolobougou",
    "wof:placetype":"locality"
},
  "geometry": {"coordinates":[-7.4592,14.0269],"type":"Point"}
}