{
  "type": "Feature",
  "properties": {
    "gn:admin1_code":"08",
    "gn:asciiname":"Kaia",
    "gn:country_code":"ML",
    "gn:dem":270,
    "gn:feature_class":"P",
    "gn:feature_code":"PPL",
    "gn:name":"Ka\u00efa",
    "gn:population":0,
    "gn:timezone":"Africa/Bamako",
    "iso:country":"ML",
    "name:und_x_variant":[
        "Kati",
        "Kali",
        "Ka\u00ef",
        "Kaya",
        "Ka\u00efa"
    ],
    "wof:name":"Kaia",
    "wof:placetype":"locality"
},
  "geometry": {"coordinates":[-3.5421,15.9071],"type":"Point"}
}