{
  "type": "Feature",
  "properties": {
    "gn:admin1_code":"4.0",
    "gn:asciiname":"Dondouli",
    "gn:country_code":"ML",
    "gn:dem":594,
    "gn:feature_class":"P",
    "gn:feature_code":"PPL",
    "gn:name":"Dondouli",
    "gn:population":0,
    "gn:timezone":"Africa/Bamako",
    "iso:country":"ML",
    "wof:name":"Dondouli",
    "wof:placetype":"locality"
},
  "geometry": {"coordinates":[-2.5005,15.19376],"type":"Point"}
}