{
  "type": "Feature",
  "properties": {
    "gn:admin1_code":"00",
    "gn:asciiname":"Daroussalam",
    "gn:country_code":"ML",
    "gn:dem":204,
    "gn:feature_class":"P",
    "gn:feature_code":"PPL",
    "gn:name":"Daroussalam",
    "gn:population":0,
    "gn:timezone":"Africa/Bamako",
    "iso:country":"ML",
    "wof:name":"Daroussalam",
    "wof:placetype":"locality"
},
  "geometry": {"coordinates":[-10.91667,12.41667],"type":"Point"}
}