{
  "type": "Feature",
  "properties": {
    "gn:admin1_code":"07",
    "gn:asciiname":"Zanga",
    "gn:country_code":"ML",
    "gn:dem":342,
    "gn:feature_class":"P",
    "gn:feature_code":"PPL",
    "gn:name":"Zanga",
    "gn:population":0,
    "gn:timezone":"Africa/Bamako",
    "iso:country":"ML",
    "wof:name":"Zanga",
    "wof:placetype":"locality"
},
  "geometry": {"coordinates":[-7.21915,13.69064],"type":"Point"}
}