{
  "type": "Feature",
  "properties": {
    "gn:admin1_code":"03",
    "gn:asciiname":"Mouthrar",
    "gn:country_code":"ML",
    "gn:dem":193,
    "gn:feature_class":"P",
    "gn:feature_code":"PPL",
    "gn:name":"Mouthrar",
    "gn:population":0,
    "gn:timezone":"Africa/Bamako",
    "iso:country":"ML",
    "wof:name":"Mouthrar",
    "wof:placetype":"locality"
},
  "geometry": {"coordinates":[-9.63826,15.4013],"type":"Point"}
}