{
  "type": "Feature",
  "properties": {
    "gn:admin1_code":"07",
    "gn:asciiname":"Sanankoro",
    "gn:country_code":"ML",
    "gn:dem":343,
    "gn:feature_class":"P",
    "gn:feature_code":"PPL",
    "gn:name":"Sanankoro",
    "gn:population":0,
    "gn:timezone":"Africa/Bamako",
    "iso:country":"ML",
    "name:fra_x_preferred":[
        "Sanankoro"
    ],
    "wof:name":"Sanankoro",
    "wof:placetype":"locality"
},
  "geometry": {"coordinates":[-8.21497,13.99457],"type":"Point"}
}