{
  "type": "Feature",
  "properties": {
    "gn:admin1_code":"07",
    "gn:asciiname":"Nkouraba",
    "gn:country_code":"ML",
    "gn:dem":341,
    "gn:feature_class":"P",
    "gn:feature_code":"PPL",
    "gn:name":"Nkouraba",
    "gn:population":0,
    "gn:timezone":"Africa/Bamako",
    "iso:country":"ML",
    "name:und_x_variant":[
        "Kourouba",
        "Kouraba",
        "Nkouraba"
    ],
    "wof:name":"Nkouraba",
    "wof:placetype":"locality"
},
  "geometry": {"coordinates":[-7.49132,12.42511],"type":"Point"}
}