{
  "type": "Feature",
  "properties": {
    "gn:admin1_code":"06",
    "gn:asciiname":"Diomana",
    "gn:country_code":"ML",
    "gn:dem":324,
    "gn:feature_class":"P",
    "gn:feature_code":"PPL",
    "gn:name":"Diomana",
    "gn:population":0,
    "gn:timezone":"Africa/Bamako",
    "iso:country":"ML",
    "name:fra_x_preferred":[
        "Diomana"
    ],
    "name:fra_x_variant":[
        "Dioumana"
    ],
    "wof:name":"Diomana",
    "wof:placetype":"locality"
},
  "geometry": {"coordinates":[-6.45662,11.33131],"type":"Point"}
}