{
  "type": "Feature",
  "properties": {
    "gn:admin1_code":"05",
    "gn:asciiname":"Sota",
    "gn:country_code":"ML",
    "gn:dem":277,
    "gn:feature_class":"P",
    "gn:feature_code":"PPL",
    "gn:name":"Sota",
    "gn:population":0,
    "gn:timezone":"Africa/Bamako",
    "iso:country":"ML",
    "name:ceb_x_preferred":[
        "Sota"
    ],
    "name:deu_x_preferred":[
        "Sota"
    ],
    "name:swe_x_preferred":[
        "Sota"
    ],
    "wof:name":"Sota",
    "wof:placetype":"locality"
},
  "geometry": {"coordinates":[-4.8285,13.6179],"type":"Point"}
}