{
  "type": "Feature",
  "properties": {
    "gn:admin1_code":"03",
    "gn:asciiname":"Segourme",
    "gn:country_code":"ML",
    "gn:dem":50,
    "gn:feature_class":"P",
    "gn:feature_code":"PPL",
    "gn:name":"S\u00e8gourm\u00e9",
    "gn:population":0,
    "gn:timezone":"Africa/Bamako",
    "iso:country":"ML",
    "wof:name":"Segourme",
    "wof:placetype":"locality"
},
  "geometry": {"coordinates":[-11.20777,14.40038],"type":"Point"}
}