{
  "type": "Feature",
  "properties": {
    "gn:admin1_code":"05",
    "gn:asciiname":"Maniabougou",
    "gn:country_code":"ML",
    "gn:dem":294,
    "gn:feature_class":"P",
    "gn:feature_code":"PPL",
    "gn:name":"Maniabougou",
    "gn:population":0,
    "gn:timezone":"Africa/Bamako",
    "iso:country":"ML",
    "name:und_x_variant":[
        "Mani\u00e9bougou",
        "Maniabougou"
    ],
    "wof:name":"Maniabougou",
    "wof:placetype":"locality"
},
  "geometry": {"coordinates":[-6.60318,13.46605],"type":"Point"}
}