{
  "type": "Feature",
  "properties": {
    "gn:admin1_code":"04",
    "gn:asciiname":"Didia",
    "gn:country_code":"ML",
    "gn:dem":269,
    "gn:feature_class":"P",
    "gn:feature_code":"PPL",
    "gn:name":"Didia",
    "gn:population":0,
    "gn:timezone":"Africa/Bamako",
    "iso:country":"ML",
    "name:hun_x_preferred":[
        "Didia"
    ],
    "name:ukr_x_preferred":[
        "\u0414\u0456\u0434\u0456\u0430"
    ],
    "wof:name":"Didia",
    "wof:placetype":"locality"
},
  "geometry": {"coordinates":[-2.72498,14.18379],"type":"Point"}
}