{
  "type": "Feature",
  "properties": {
    "gn:admin1_code":"06",
    "gn:asciiname":"Zougoumasso",
    "gn:country_code":"ML",
    "gn:dem":311,
    "gn:feature_class":"P",
    "gn:feature_code":"PPL",
    "gn:name":"Zougoumasso",
    "gn:population":0,
    "gn:timezone":"Africa/Bamako",
    "iso:country":"ML",
    "wof:name":"Zougoumasso",
    "wof:placetype":"locality"
},
  "geometry": {"coordinates":[-5.27483,12.475],"type":"Point"}
}