{
  "type": "Feature",
  "properties": {
    "gn:admin1_code":"05",
    "gn:asciiname":"Konokasi",
    "gn:country_code":"ML",
    "gn:dem":282,
    "gn:feature_class":"P",
    "gn:feature_code":"PPL",
    "gn:name":"Konokasi",
    "gn:population":0,
    "gn:timezone":"Africa/Bamako",
    "iso:country":"ML",
    "name:fra_x_preferred":[
        "Konokassi"
    ],
    "name:und_x_variant":[
        "Konokassi"
    ],
    "wof:name":"Konokasi",
    "wof:placetype":"locality"
},
  "geometry": {"coordinates":[-6.0241,14.3574],"type":"Point"}
}