{
  "type": "Feature",
  "properties": {
    "gn:admin1_code":"03",
    "gn:asciiname":"Takoutala",
    "gn:country_code":"ML",
    "gn:dem":112,
    "gn:feature_class":"P",
    "gn:feature_code":"PPL",
    "gn:name":"Takoutala",
    "gn:population":0,
    "gn:timezone":"Africa/Bamako",
    "iso:country":"ML",
    "wof:name":"Takoutala",
    "wof:placetype":"locality"
},
  "geometry": {"coordinates":[-10.66606,15.28966],"type":"Point"}
}