{
  "type": "Feature",
  "properties": {
    "gn:admin1_code":"03",
    "gn:asciiname":"Kaha",
    "gn:country_code":"ML",
    "gn:dem":434,
    "gn:feature_class":"P",
    "gn:feature_code":"PPL",
    "gn:name":"Kaha",
    "gn:population":0,
    "gn:timezone":"Africa/Bamako",
    "iso:country":"ML",
    "name:und_x_variant":[
        "Kana",
        "Kaha"
    ],
    "wof:name":"Kaha",
    "wof:placetype":"locality"
},
  "geometry": {"coordinates":[-11.14249,12.7767],"type":"Point"}
}