{
  "type": "Feature",
  "properties": {
    "gn:admin1_code":"7.0",
    "gn:asciiname":"Ndinkoro",
    "gn:country_code":"ML",
    "gn:dem":379,
    "gn:feature_class":"P",
    "gn:feature_code":"PPL",
    "gn:name":"Ndinkoro",
    "gn:population":0,
    "gn:timezone":"Africa/Bamako",
    "iso:country":"ML",
    "wof:name":"Ndinkoro",
    "wof:placetype":"locality"
},
  "geometry": {"coordinates":[-7.8414,12.80642],"type":"Point"}
}