{
  "type": "Feature",
  "properties": {
    "gn:admin1_code":"03",
    "gn:asciiname":"Lataraf",
    "gn:country_code":"ML",
    "gn:dem":243,
    "gn:feature_class":"P",
    "gn:feature_code":"PPL",
    "gn:name":"Lataraf",
    "gn:population":0,
    "gn:timezone":"Africa/Bamako",
    "iso:country":"ML",
    "wof:name":"Lataraf",
    "wof:placetype":"locality"
},
  "geometry": {"coordinates":[-9.7284,14.5314],"type":"Point"}
}