{
  "type": "Feature",
  "properties": {
    "gn:admin1_code":"03",
    "gn:asciiname":"Dinguira-Logo",
    "gn:country_code":"ML",
    "gn:dem":52,
    "gn:feature_class":"P",
    "gn:feature_code":"PPL",
    "gn:name":"Dinguira-Logo",
    "gn:population":0,
    "gn:timezone":"Africa/Bamako",
    "iso:country":"ML",
    "name:und_x_variant":[
        "Dinguira",
        "Dinguira-Logo"
    ],
    "wof:name":"Dinguira-Logo",
    "wof:placetype":"locality"
},
  "geometry": {"coordinates":[-11.2466,14.17559],"type":"Point"}
}