{
  "type": "Feature",
  "properties": {
    "gn:admin1_code":"06",
    "gn:asciiname":"Findiala",
    "gn:country_code":"ML",
    "gn:dem":328,
    "gn:feature_class":"P",
    "gn:feature_code":"PPL",
    "gn:name":"Findiala",
    "gn:population":0,
    "gn:timezone":"Africa/Bamako",
    "iso:country":"ML",
    "name:fra_x_preferred":[
        "Fandiala"
    ],
    "name:fra_x_variant":[
        "Fendiala"
    ],
    "name:und_x_variant":[
        "Findiala"
    ],
    "wof:name":"Findiala",
    "wof:placetype":"locality"
},
  "geometry": {"coordinates":[-6.73225,11.06181],"type":"Point"}
}