{
  "type": "Feature",
  "properties": {
    "gn:admin1_code":"7.0",
    "gn:asciiname":"Diamberebougou",
    "gn:country_code":"ML",
    "gn:dem":354,
    "gn:feature_class":"P",
    "gn:feature_code":"PPL",
    "gn:name":"Diamb\u00e8r\u00e8bougou",
    "gn:population":0,
    "gn:timezone":"Africa/Bamako",
    "iso:country":"ML",
    "wof:name":"Diamberebougou",
    "wof:placetype":"locality"
},
  "geometry": {"coordinates":[-7.61955,12.86786],"type":"Point"}
}