{
  "type": "Feature",
  "properties": {
    "gn:admin1_code":"05",
    "gn:asciiname":"Zokwe",
    "gn:country_code":"ML",
    "gn:dem":420,
    "gn:feature_class":"P",
    "gn:feature_code":"PPL",
    "gn:name":"Zokw\u00e9",
    "gn:population":0,
    "gn:timezone":"Africa/Bamako",
    "iso:country":"ML",
    "name:und_x_variant":[
        "Zogue",
        "Zogou\u00e9",
        "Zokw\u00e9"
    ],
    "wof:name":"Zokwe",
    "wof:placetype":"locality"
},
  "geometry": {"coordinates":[-4.3199,12.8788],"type":"Point"}
}