{
  "type": "Feature",
  "properties": {
    "gn:admin1_code":"7.0",
    "gn:asciiname":"Malikabougou",
    "gn:country_code":"ML",
    "gn:dem":321,
    "gn:feature_class":"P",
    "gn:feature_code":"PPL",
    "gn:name":"Malikabougou",
    "gn:population":0,
    "gn:timezone":"Africa/Bamako",
    "iso:country":"ML",
    "wof:name":"Malikabougou",
    "wof:placetype":"locality"
},
  "geometry": {"coordinates":[-7.7873,14.1748],"type":"Point"}
}