{
  "type": "Feature",
  "properties": {
    "gn:admin1_code":"05",
    "gn:asciiname":"Kalala",
    "gn:country_code":"ML",
    "gn:dem":280,
    "gn:feature_class":"P",
    "gn:feature_code":"PPL",
    "gn:name":"Kalala",
    "gn:population":0,
    "gn:timezone":"Africa/Bamako",
    "iso:country":"ML",
    "name:und_x_variant":[
        "Kakala",
        "Kalala"
    ],
    "wof:name":"Kalala",
    "wof:placetype":"locality"
},
  "geometry": {"coordinates":[-5.11192,13.75535],"type":"Point"}
}