{
  "type": "Feature",
  "properties": {
    "gn:admin1_code":"07",
    "gn:asciiname":"Ndjila",
    "gn:country_code":"ML",
    "gn:dem":368,
    "gn:feature_class":"P",
    "gn:feature_code":"PPL",
    "gn:name":"Ndjila",
    "gn:population":0,
    "gn:timezone":"Africa/Bamako",
    "iso:country":"ML",
    "name:fra_x_preferred":[
        "N\u2019Kila"
    ],
    "name:fra_x_variant":[
        "Ndjila"
    ],
    "wof:name":"Ndjila",
    "wof:placetype":"locality"
},
  "geometry": {"coordinates":[-8.0174,13.2517],"type":"Point"}
}