{
  "type": "Feature",
  "properties": {
    "gn:admin1_code":"07",
    "gn:asciiname":"Werekela",
    "gn:country_code":"ML",
    "gn:dem":338,
    "gn:feature_class":"P",
    "gn:feature_code":"PPL",
    "gn:name":"W\u00e9r\u00e9k\u00e9la",
    "gn:population":0,
    "gn:timezone":"Africa/Bamako",
    "iso:country":"ML",
    "name:fra_x_preferred":[
        "W\u00e9r\u00e9k\u00e9la"
    ],
    "name:fra_x_variant":[
        "Ourogour\u00e9li"
    ],
    "wof:name":"Werekela",
    "wof:placetype":"locality"
},
  "geometry": {"coordinates":[-6.92337,12.80944],"type":"Point"}
}