{
  "type": "Feature",
  "properties": {
    "gn:admin1_code":"7.0",
    "gn:asciiname":"Zana",
    "gn:country_code":"ML",
    "gn:dem":340,
    "gn:feature_class":"P",
    "gn:feature_code":"PPL",
    "gn:name":"Zana",
    "gn:population":0,
    "gn:timezone":"Africa/Bamako",
    "iso:country":"ML",
    "name:ceb_x_preferred":[
        "Zana"
    ],
    "name:deu_x_preferred":[
        "Zana"
    ],
    "name:fra_x_preferred":[
        "Zana"
    ],
    "name:heb_x_preferred":[
        "\u05d6\u05e0\u05d4"
    ],
    "name:hrv_x_preferred":[
        "Zana"
    ],
    "name:rus_x_preferred":[
        "\u0417\u0430\u043d\u0430"
    ],
    "name:slk_x_preferred":[
        "Zana"
    ],
    "name:sqi_x_preferred":[
        "Zana"
    ],
    "name:srp_x_preferred":[
        "\u0417\u0430\u043d\u0430"
    ],
    "name:swe_x_preferred":[
        "Zana"
    ],
    "wof:name":"Zana",
    "wof:placetype":"locality"
},
  "geometry": {"coordinates":[-6.60174,11.79985],"type":"Point"}
}