{
  "type": "Feature",
  "properties": {
    "gn:admin1_code":"10.0",
    "gn:asciiname":"Abeibara",
    "gn:country_code":"ML",
    "gn:dem":538,
    "gn:feature_class":"P",
    "gn:feature_code":"PPLA2",
    "gn:name":"Abe\u00efbara",
    "gn:population":0,
    "gn:timezone":"Africa/Bamako",
    "iso:country":"ML",
    "name:und_x_variant":[
        "Abe\u00efbara"
    ],
    "wof:name":"Abeibara",
    "wof:placetype":"locality"
},
  "geometry": {"coordinates":[1.75,19.11667000000001],"type":"Point"}
}