{
  "type": "Feature",
  "properties": {
    "gn:admin1_code":"10.0",
    "gn:asciiname":"Abeibara",
    "gn:country_code":"ML",
    "gn:dem":538,
    "gn:feature_class":"P",
    "gn:feature_code":"PPLA2",
    "gn:name":"Abe\u00efbara",
    "gn:population":0,
    "gn:timezone":"Africa/Bamako",
    "iso:country":"ML",
    "name:azb_x_preferred":[
        "\u0627\u0628\u06cc\u0628\u0627\u0631\u0627"
    ],
    "name:ell_x_preferred":[
        "\u0391\u03bc\u03c0\u03b5\u03ca\u03bc\u03c0\u03b1\u03c1\u03ac"
    ],
    "name:fas_x_preferred":[
        "\u0627\u0628\u06cc\u0628\u0627\u0631\u0627"
    ],
    "name:fin_x_preferred":[
        "Abe\u00efbara"
    ],
    "name:fra_x_preferred":[
        "Abe\u00efbara"
    ],
    "name:ita_x_preferred":[
        "Ab\u00e9\u00efbara"
    ],
    "name:nld_x_preferred":[
        "Ab\u00e9\u00efbara"
    ],
    "name:nor_x_preferred":[
        "Abe\u00efbara"
    ],
    "name:spa_x_preferred":[
        "Abe\u00efbara"
    ],
    "name:zho_x_preferred":[
        "\u963f\u8c9d\u5df4\u62c9"
    ],
    "wof:name":"Abeibara",
    "wof:placetype":"locality"
},
  "geometry": {"coordinates":[1.75,19.11667000000001],"type":"Point"}
}