{
  "type": "Feature",
  "properties": {
    "gn:admin1_code":"3.0",
    "gn:asciiname":"Sanbanara",
    "gn:country_code":"ML",
    "gn:dem":255,
    "gn:feature_class":"P",
    "gn:feature_code":"PPL",
    "gn:name":"Sanbanara",
    "gn:population":0,
    "gn:timezone":"Africa/Bamako",
    "iso:country":"ML",
    "wof:name":"Sanbanara",
    "wof:placetype":"locality"
},
  "geometry": {"coordinates":[-10.29473,15.29547],"type":"Point"}
}