{
  "type": "Feature",
  "properties": {
    "gn:admin1_code":"07",
    "gn:asciiname":"Monsona",
    "gn:country_code":"ML",
    "gn:dem":450,
    "gn:feature_class":"P",
    "gn:feature_code":"PPL",
    "gn:name":"Monsona",
    "gn:population":0,
    "gn:timezone":"Africa/Bamako",
    "iso:country":"ML",
    "name:fra_x_preferred":[
        "Monsona"
    ],
    "wof:name":"Monsona",
    "wof:placetype":"locality"
},
  "geometry": {"coordinates":[-8.0684,13.7976],"type":"Point"}
}