{
  "type": "Feature",
  "properties": {
    "gn:admin1_code":"04",
    "gn:asciiname":"Kossinn",
    "gn:country_code":"ML",
    "gn:dem":271,
    "gn:feature_class":"P",
    "gn:feature_code":"PPL",
    "gn:name":"Kossinn",
    "gn:population":0,
    "gn:timezone":"Africa/Bamako",
    "iso:country":"ML",
    "wof:name":"Kossinn",
    "wof:placetype":"locality"
},
  "geometry": {"coordinates":[-3.3726,15.6622],"type":"Point"}
}