{
  "type": "Feature",
  "properties": {
    "gn:admin1_code":"5.0",
    "gn:asciiname":"Amadou-Doso Ware",
    "gn:country_code":"ML",
    "gn:dem":283,
    "gn:feature_class":"P",
    "gn:feature_code":"PPL",
    "gn:name":"Amadou-Doso War\u00e9",
    "gn:population":0,
    "gn:timezone":"Africa/Bamako",
    "iso:country":"ML",
    "wof:name":"Amadou-Doso Ware",
    "wof:placetype":"locality"
},
  "geometry": {"coordinates":[-6.091,14.2392],"type":"Point"}
}