{
  "type": "Feature",
  "properties": {
    "gn:admin1_code":"4.0",
    "gn:asciiname":"Sarafere Merignan",
    "gn:country_code":"ML",
    "gn:dem":270,
    "gn:feature_class":"P",
    "gn:feature_code":"PPL",
    "gn:name":"Saraf\u00e9r\u00e9 Merignan",
    "gn:population":0,
    "gn:timezone":"Africa/Bamako",
    "iso:country":"ML",
    "wof:name":"Sarafere Merignan",
    "wof:placetype":"locality"
},
  "geometry": {"coordinates":[-3.4972,15.6409],"type":"Point"}
}