{
  "type": "Feature",
  "properties": {
    "gn:admin1_code":"7.0",
    "gn:asciiname":"Gouanzerebougou",
    "gn:country_code":"ML",
    "gn:dem":408,
    "gn:feature_class":"P",
    "gn:feature_code":"PPL",
    "gn:name":"Gouanz\u00e9r\u00e9bougou",
    "gn:population":0,
    "gn:timezone":"Africa/Bamako",
    "iso:country":"ML",
    "wof:name":"Gouanzerebougou",
    "wof:placetype":"locality"
},
  "geometry": {"coordinates":[-7.83711,13.33443],"type":"Point"}
}