{
  "type": "Feature",
  "properties": {
    "gn:admin1_code":"07",
    "gn:asciiname":"Bougouba",
    "gn:country_code":"ML",
    "gn:dem":334,
    "gn:feature_class":"P",
    "gn:feature_code":"PPL",
    "gn:name":"Bougouba",
    "gn:population":0,
    "gn:timezone":"Africa/Bamako",
    "iso:country":"ML",
    "wof:name":"Bougouba",
    "wof:placetype":"locality"
},
  "geometry": {"coordinates":[-7.47841,13.35448],"type":"Point"}
}