{
  "type": "Feature",
  "properties": {
    "gn:admin1_code":"5.0",
    "gn:asciiname":"Nansiguio",
    "gn:country_code":"ML",
    "gn:dem":279,
    "gn:feature_class":"P",
    "gn:feature_code":"PPL",
    "gn:name":"Nansiguio",
    "gn:population":0,
    "gn:timezone":"Africa/Bamako",
    "iso:country":"ML",
    "wof:name":"Nansiguio",
    "wof:placetype":"locality"
},
  "geometry": {"coordinates":[-5.61716,13.96789],"type":"Point"}
}