{
  "type": "Feature",
  "properties": {
    "gn:admin1_code":"03",
    "gn:asciiname":"Sobokou",
    "gn:country_code":"ML",
    "gn:dem":34,
    "gn:feature_class":"P",
    "gn:feature_code":"PPL",
    "gn:name":"Sobokou",
    "gn:population":0,
    "gn:timezone":"Africa/Bamako",
    "iso:country":"ML",
    "wof:name":"Sobokou",
    "wof:placetype":"locality"
},
  "geometry": {"coordinates":[-11.97851,14.65903],"type":"Point"}
}