{
  "type": "Feature",
  "properties": {
    "gn:admin1_code":"3.0",
    "gn:asciiname":"Moudere",
    "gn:country_code":"ML",
    "gn:dem":211,
    "gn:feature_class":"P",
    "gn:feature_code":"PPL",
    "gn:name":"Moud\u00e9r\u00e9",
    "gn:population":0,
    "gn:timezone":"Africa/Bamako",
    "iso:country":"ML",
    "wof:name":"Moudere",
    "wof:placetype":"locality"
},
  "geometry": {"coordinates":[-9.5484,15.33054],"type":"Point"}
}