{
  "type": "Feature",
  "properties": {
    "gn:admin1_code":"03",
    "gn:asciiname":"Komara",
    "gn:country_code":"ML",
    "gn:dem":280,
    "gn:feature_class":"P",
    "gn:feature_code":"PPL",
    "gn:name":"Komara",
    "gn:population":0,
    "gn:timezone":"Africa/Bamako",
    "iso:country":"ML",
    "name:bul_x_preferred":[
        "\u041a\u043e\u043c\u0430\u0440\u043b\u0438"
    ],
    "name:ceb_x_preferred":[
        "K\u00f3mara"
    ],
    "name:ell_x_preferred":[
        "\u039a\u03cc\u03bc\u03b1\u03c1\u03b1 \u0388\u03b2\u03c1\u03bf\u03c5"
    ],
    "name:ron_x_preferred":[
        "Komara"
    ],
    "name:swe_x_preferred":[
        "K\u00f3mara"
    ],
    "name:tur_x_preferred":[
        "Kumarl\u0131"
    ],
    "wof:name":"Komara",
    "wof:placetype":"locality"
},
  "geometry": {"coordinates":[-9.1524,14.6536],"type":"Point"}
}