{
  "type": "Feature",
  "properties": {
    "gn:admin1_code":"05",
    "gn:asciiname":"Ngabakoro",
    "gn:country_code":"ML",
    "gn:dem":315,
    "gn:feature_class":"P",
    "gn:feature_code":"PPL",
    "gn:name":"Ngabakoro",
    "gn:population":0,
    "gn:timezone":"Africa/Bamako",
    "iso:country":"ML",
    "name:fra_x_preferred":[
        "Ngabakoro"
    ],
    "wof:name":"Ngabakoro",
    "wof:placetype":"locality"
},
  "geometry": {"coordinates":[-6.6767,12.9833],"type":"Point"}
}