{
  "type": "Feature",
  "properties": {
    "gn:admin1_code":"06",
    "gn:asciiname":"Keremena",
    "gn:country_code":"ML",
    "gn:dem":346,
    "gn:feature_class":"P",
    "gn:feature_code":"PPL",
    "gn:name":"K\u00e9r\u00e9m\u00e9na",
    "gn:population":0,
    "gn:timezone":"Africa/Bamako",
    "iso:country":"ML",
    "name:fra_x_preferred":[
        "K\u00e9r\u00e9m\u00e9na"
    ],
    "wof:name":"Keremena",
    "wof:placetype":"locality"
},
  "geometry": {"coordinates":[-6.14613,11.49458],"type":"Point"}
}