{
  "type": "Feature",
  "properties": {
    "gn:admin1_code":"09",
    "gn:asciiname":"Elmaki Bentia",
    "gn:country_code":"ML",
    "gn:dem":238,
    "gn:feature_class":"P",
    "gn:feature_code":"PPL",
    "gn:name":"Elmaki Bentia",
    "gn:population":0,
    "gn:timezone":"Africa/Bamako",
    "iso:country":"ML",
    "wof:name":"Elmaki Bentia",
    "wof:placetype":"locality"
},
  "geometry": {"coordinates":[0.7526,15.3431],"type":"Point"}
}