{
  "type": "Feature",
  "properties": {
    "gn:admin1_code":"07",
    "gn:asciiname":"Nteguedo",
    "gn:country_code":"ML",
    "gn:dem":348,
    "gn:feature_class":"P",
    "gn:feature_code":"PPL",
    "gn:name":"Nt\u00e9gu\u00e9do",
    "gn:population":0,
    "gn:timezone":"Africa/Bamako",
    "iso:country":"ML",
    "name:fra_x_preferred":[
        "Nt\u00e9gu\u00e9do"
    ],
    "wof:name":"Nteguedo",
    "wof:placetype":"locality"
},
  "geometry": {"coordinates":[-8.3081,13.1314],"type":"Point"}
}