{
  "type": "Feature",
  "properties": {
    "gn:admin1_code":"07",
    "gn:asciiname":"Tota",
    "gn:country_code":"ML",
    "gn:dem":379,
    "gn:feature_class":"P",
    "gn:feature_code":"PPL",
    "gn:name":"Tota",
    "gn:population":0,
    "gn:timezone":"Africa/Bamako",
    "iso:country":"ML",
    "name:und_x_variant":[
        "Touta",
        "Touba",
        "Tota"
    ],
    "wof:name":"Tota",
    "wof:placetype":"locality"
},
  "geometry": {"coordinates":[-7.56499,13.69306],"type":"Point"}
}