{
  "type": "Feature",
  "properties": {
    "gn:admin1_code":"07",
    "gn:asciiname":"Panpala",
    "gn:country_code":"ML",
    "gn:dem":393,
    "gn:feature_class":"P",
    "gn:feature_code":"PPL",
    "gn:name":"Panpala",
    "gn:population":0,
    "gn:timezone":"Africa/Bamako",
    "iso:country":"ML",
    "name:und_x_variant":[
        "Pampala",
        "Panpala"
    ],
    "wof:name":"Panpala",
    "wof:placetype":"locality"
},
  "geometry": {"coordinates":[-7.9406,14.0886],"type":"Point"}
}