{
  "type": "Feature",
  "properties": {
    "gn:admin1_code":"4.0",
    "gn:asciiname":"Wara",
    "gn:country_code":"ML",
    "gn:dem":569,
    "gn:feature_class":"P",
    "gn:feature_code":"PPL",
    "gn:name":"Wara",
    "gn:population":0,
    "gn:timezone":"Africa/Bamako",
    "iso:country":"ML",
    "name:ceb_x_preferred":[
        "Wara"
    ],
    "name:deu_x_preferred":[
        "Wara"
    ],
    "name:fra_x_preferred":[
        "Wara"
    ],
    "name:swe_x_preferred":[
        "Wara"
    ],
    "wof:name":"Wara",
    "wof:placetype":"locality"
},
  "geometry": {"coordinates":[-3.36979,14.58808],"type":"Point"}
}