{
  "type": "Feature",
  "properties": {
    "gn:admin1_code":"03",
    "gn:asciiname":"Toukoto",
    "gn:country_code":"ML",
    "gn:dem":260,
    "gn:feature_class":"P",
    "gn:feature_code":"PPL",
    "gn:name":"Toukoto",
    "gn:population":0,
    "gn:timezone":"Africa/Bamako",
    "iso:country":"ML",
    "name:fin_x_preferred":[
        "Toukoto"
    ],
    "name:fra_x_preferred":[
        "Toukoto"
    ],
    "name:ita_x_preferred":[
        "Toukoto"
    ],
    "name:nld_x_preferred":[
        "Toukoto"
    ],
    "name:spa_x_preferred":[
        "Toukoto"
    ],
    "wof:name":"Toukoto",
    "wof:placetype":"locality"
},
  "geometry": {"coordinates":[-9.98053,15.06541],"type":"Point"}
}