{
  "type": "Feature",
  "properties": {
    "gn:admin1_code":"5.0",
    "gn:asciiname":"Diadaka",
    "gn:country_code":"ML",
    "gn:dem":271,
    "gn:feature_class":"P",
    "gn:feature_code":"PPL",
    "gn:name":"Diadaka",
    "gn:population":0,
    "gn:timezone":"Africa/Bamako",
    "iso:country":"ML",
    "wof:name":"Diadaka",
    "wof:placetype":"locality"
},
  "geometry": {"coordinates":[-5.02562,13.62062],"type":"Point"}
}