{
  "type": "Feature",
  "properties": {
    "gn:admin1_code":"00",
    "gn:asciiname":"Sessinie",
    "gn:cc2":"ML",
    "gn:country_code":"ML",
    "gn:dem":361,
    "gn:feature_class":"P",
    "gn:feature_code":"PPL",
    "gn:name":"Sessini\u00e9",
    "gn:population":0,
    "gn:timezone":"Africa/Bamako",
    "iso:country":"ML",
    "name:und_x_variant":[
        "Ciss\u00e9gu\u00e9",
        "Sessini\u00e9"
    ],
    "wof:name":"Sessinie",
    "wof:placetype":"locality"
},
  "geometry": {"coordinates":[-5.98333,10.66667],"type":"Point"}
}