{
  "type": "Feature",
  "properties": {
    "gn:admin1_code":"03",
    "gn:asciiname":"Kabaya",
    "gn:country_code":"ML",
    "gn:dem":256,
    "gn:feature_class":"P",
    "gn:feature_code":"PPL",
    "gn:name":"Kabaya",
    "gn:population":0,
    "gn:timezone":"Africa/Bamako",
    "iso:country":"ML",
    "name:jpn_x_preferred":[
        "\u30ab\u30d0\u30e4\u98df\u54c1"
    ],
    "name:kor_x_preferred":[
        "\uac00\ubc14\uc57c \uc2dd\ud488"
    ],
    "wof:name":"Kabaya",
    "wof:placetype":"locality"
},
  "geometry": {"coordinates":[-10.7502,14.3046],"type":"Point"}
}