{
  "type": "Feature",
  "properties": {
    "gn:admin1_code":"07",
    "gn:asciiname":"Dioria",
    "gn:country_code":"ML",
    "gn:dem":362,
    "gn:feature_class":"P",
    "gn:feature_code":"PPL",
    "gn:name":"Dioria",
    "gn:population":0,
    "gn:timezone":"Africa/Bamako",
    "iso:country":"ML",
    "name:und_x_variant":[
        "Dioriba",
        "Dioria"
    ],
    "wof:name":"Dioria",
    "wof:placetype":"locality"
},
  "geometry": {"coordinates":[-8.09088,12.10476],"type":"Point"}
}