{
  "type": "Feature",
  "properties": {
    "gn:admin1_code":"05",
    "gn:asciiname":"Bougoula",
    "gn:country_code":"ML",
    "gn:dem":299,
    "gn:feature_class":"P",
    "gn:feature_code":"PPL",
    "gn:name":"Bougoula",
    "gn:population":0,
    "gn:timezone":"Africa/Bamako",
    "iso:country":"ML",
    "name:fra_x_preferred":[
        "Bougoula"
    ],
    "name:ita_x_preferred":[
        "Bougoula"
    ],
    "name:nld_x_preferred":[
        "Bougoula"
    ],
    "name:por_x_preferred":[
        "Bugula"
    ],
    "name:und_x_variant":[
        "Bougouba",
        "Bougoula"
    ],
    "wof:name":"Bougoula",
    "wof:placetype":"locality"
},
  "geometry": {"coordinates":[-6.8316,13.3215],"type":"Point"}
}