{
  "type": "Feature",
  "properties": {
    "gn:admin1_code":"07",
    "gn:asciiname":"Yeredombougou",
    "gn:country_code":"ML",
    "gn:dem":305,
    "gn:feature_class":"P",
    "gn:feature_code":"PPL",
    "gn:name":"Y\u00e8r\u00e8dombougou",
    "gn:population":0,
    "gn:timezone":"Africa/Bamako",
    "iso:country":"ML",
    "name:und_x_variant":[
        "Y\u00e9r\u00e9donbougou",
        "Y\u00e8r\u00e8dombougou"
    ],
    "wof:name":"Yeredombougou",
    "wof:placetype":"locality"
},
  "geometry": {"coordinates":[-7.23271,13.35397],"type":"Point"}
}