{
  "type": "Feature",
  "properties": {
    "gn:admin1_code":"8.0",
    "gn:asciiname":"Tadjidjit",
    "gn:country_code":"ML",
    "gn:dem":258,
    "gn:feature_class":"P",
    "gn:feature_code":"PPL",
    "gn:name":"Tadjidjit",
    "gn:population":0,
    "gn:timezone":"Africa/Bamako",
    "iso:country":"ML",
    "wof:name":"Tadjidjit",
    "wof:placetype":"locality"
},
  "geometry": {"coordinates":[-4.31151,16.6178],"type":"Point"}
}