{
  "type": "Feature",
  "properties": {
    "gn:admin1_code":"6.0",
    "gn:asciiname":"Dyana",
    "gn:country_code":"ML",
    "gn:dem":313,
    "gn:feature_class":"P",
    "gn:feature_code":"PPL",
    "gn:name":"Dyana",
    "gn:population":0,
    "gn:timezone":"Africa/Bamako",
    "iso:country":"ML",
    "wof:name":"Dyana",
    "wof:placetype":"locality"
},
  "geometry": {"coordinates":[-6.1465,12.0092],"type":"Point"}
}