{
  "type": "Feature",
  "properties": {
    "gn:admin1_code":"03",
    "gn:asciiname":"Tourougoumbe",
    "gn:country_code":"ML",
    "gn:dem":306,
    "gn:feature_class":"P",
    "gn:feature_code":"PPL",
    "gn:name":"Tourougoumb\u00e9",
    "gn:population":0,
    "gn:timezone":"Africa/Bamako",
    "iso:country":"ML",
    "name:und_x_variant":[
        "Tourougomb\u00e9",
        "Tourougoumb\u00e9"
    ],
    "wof:name":"Tourougoumbe",
    "wof:placetype":"locality"
},
  "geometry": {"coordinates":[-9.2263,15.2647],"type":"Point"}
}