{
  "type": "Feature",
  "properties": {
    "gn:admin1_code":"4.0",
    "gn:asciiname":"Niongolo",
    "gn:country_code":"ML",
    "gn:dem":265,
    "gn:feature_class":"P",
    "gn:feature_code":"PPL",
    "gn:name":"Niongolo",
    "gn:population":0,
    "gn:timezone":"Africa/Bamako",
    "iso:country":"ML",
    "wof:name":"Niongolo",
    "wof:placetype":"locality"
},
  "geometry": {"coordinates":[-3.4449,15.1581],"type":"Point"}
}