{
  "type": "Feature",
  "properties": {
    "gn:admin1_code":"05",
    "gn:asciiname":"Sokola",
    "gn:country_code":"ML",
    "gn:dem":336,
    "gn:feature_class":"P",
    "gn:feature_code":"PPL",
    "gn:name":"Sokola",
    "gn:population":0,
    "gn:timezone":"Africa/Bamako",
    "iso:country":"ML",
    "name:ceb_x_preferred":[
        "Sokola"
    ],
    "name:fra_x_preferred":[
        "Sokola"
    ],
    "name:pol_x_preferred":[
        "Sokola"
    ],
    "name:swe_x_preferred":[
        "Sokola"
    ],
    "name:ukr_x_preferred":[
        "\u0421\u043e\u043a\u043e\u043b\u044f"
    ],
    "wof:name":"Sokola",
    "wof:placetype":"locality"
},
  "geometry": {"coordinates":[-6.8012,12.9232],"type":"Point"}
}