{
  "type": "Feature",
  "properties": {
    "gn:admin1_code":"3.0",
    "gn:asciiname":"Diabedebe",
    "gn:country_code":"ML",
    "gn:dem":77,
    "gn:feature_class":"P",
    "gn:feature_code":"PPL",
    "gn:name":"Diab\u00e9d\u00e9b\u00e9",
    "gn:population":0,
    "gn:timezone":"Africa/Bamako",
    "iso:country":"ML",
    "wof:name":"Diabedebe",
    "wof:placetype":"locality"
},
  "geometry": {"coordinates":[-10.87777,15.14255],"type":"Point"}
}