{
  "type": "Feature",
  "properties": {
    "gn:admin1_code":"05",
    "gn:asciiname":"Galaka",
    "gn:country_code":"ML",
    "gn:dem":302,
    "gn:feature_class":"P",
    "gn:feature_code":"PPL",
    "gn:name":"Galaka",
    "gn:population":0,
    "gn:timezone":"Africa/Bamako",
    "iso:country":"ML",
    "wof:name":"Galaka",
    "wof:placetype":"locality"
},
  "geometry": {"coordinates":[-5.96633,12.8816],"type":"Point"}
}