{
  "type": "Feature",
  "properties": {
    "gn:admin1_code":"9.0",
    "gn:asciiname":"Banlassi",
    "gn:country_code":"ML",
    "gn:dem":246,
    "gn:feature_class":"P",
    "gn:feature_code":"PPL",
    "gn:name":"Banlassi",
    "gn:population":0,
    "gn:timezone":"Africa/Bamako",
    "iso:country":"ML",
    "wof:name":"Banlassi",
    "wof:placetype":"locality"
},
  "geometry": {"coordinates":[0.7036,15.4811],"type":"Point"}
}