{
  "type": "Feature",
  "properties": {
    "gn:admin1_code":"03",
    "gn:asciiname":"Serne",
    "gn:country_code":"ML",
    "gn:dem":296,
    "gn:feature_class":"P",
    "gn:feature_code":"PPL",
    "gn:name":"Sern\u00e9",
    "gn:population":0,
    "gn:timezone":"Africa/Bamako",
    "iso:country":"ML",
    "wof:name":"Serne",
    "wof:placetype":"locality"
},
  "geometry": {"coordinates":[-9.3806,14.4873],"type":"Point"}
}