{
  "type": "Feature",
  "properties": {
    "gn:admin1_code":"08",
    "gn:asciiname":"Garbame",
    "gn:country_code":"ML",
    "gn:dem":273,
    "gn:feature_class":"P",
    "gn:feature_code":"PPL",
    "gn:name":"Garbam\u00e9",
    "gn:population":0,
    "gn:timezone":"Africa/Bamako",
    "iso:country":"ML",
    "name:und_x_variant":[
        "Garbane",
        "Gardan\u00e9",
        "Garbam\u00e9"
    ],
    "wof:name":"Garbame",
    "wof:placetype":"locality"
},
  "geometry": {"coordinates":[-1.21793,17.00718],"type":"Point"}
}