{
  "type": "Feature",
  "properties": {
    "gn:admin1_code":"7.0",
    "gn:asciiname":"Sougoulabougou",
    "gn:country_code":"ML",
    "gn:dem":382,
    "gn:feature_class":"P",
    "gn:feature_code":"PPL",
    "gn:name":"Sougoulabougou",
    "gn:population":0,
    "gn:timezone":"Africa/Bamako",
    "iso:country":"ML",
    "wof:name":"Sougoulabougou",
    "wof:placetype":"locality"
},
  "geometry": {"coordinates":[-7.75371,12.49492],"type":"Point"}
}