{
  "type": "Feature",
  "properties": {
    "gn:admin1_code":"6.0",
    "gn:asciiname":"Doumasso",
    "gn:country_code":"ML",
    "gn:dem":317,
    "gn:feature_class":"P",
    "gn:feature_code":"PPL",
    "gn:name":"Doumasso",
    "gn:population":0,
    "gn:timezone":"Africa/Bamako",
    "iso:country":"ML",
    "wof:name":"Doumasso",
    "wof:placetype":"locality"
},
  "geometry": {"coordinates":[-5.1935,12.0215],"type":"Point"}
}