{
  "type": "Feature",
  "properties": {
    "gn:admin1_code":"05",
    "gn:asciiname":"Tana",
    "gn:country_code":"ML",
    "gn:dem":286,
    "gn:feature_class":"P",
    "gn:feature_code":"PPL",
    "gn:name":"Tana",
    "gn:population":0,
    "gn:timezone":"Africa/Bamako",
    "iso:country":"ML",
    "name:bel_x_preferred":[
        "\u0422\u0430\u043d\u0430"
    ],
    "name:cat_x_preferred":[
        "Tana"
    ],
    "name:ceb_x_preferred":[
        "Tana"
    ],
    "name:ces_x_preferred":[
        "Tana"
    ],
    "name:deu_x_preferred":[
        "Tana"
    ],
    "name:est_x_preferred":[
        "Tana"
    ],
    "name:fin_x_preferred":[
        "Tana"
    ],
    "name:fra_x_preferred":[
        "Tana"
    ],
    "name:heb_x_preferred":[
        "\u05d8\u05d0\u05e0\u05d4"
    ],
    "name:heb_x_variant":[
        "\u05d8\u05e0\u05d4"
    ],
    "name:hrv_x_preferred":[
        "Tana"
    ],
    "name:hun_x_preferred":[
        "Tana"
    ],
    "name:ind_x_preferred":[
        "Tana"
    ],
    "name:ita_x_preferred":[
        "Tana"
    ],
    "name:kat_x_preferred":[
        "\u10e2\u10d0\u10dc\u10d0"
    ],
    "name:kor_x_preferred":[
        "\ud0c0\ub098"
    ],
    "name:lim_x_preferred":[
        "Tana"
    ],
    "name:lit_x_preferred":[
        "Tana"
    ],
    "name:nld_x_preferred":[
        "Tana"
    ],
    "name:pol_x_preferred":[
        "Tana"
    ],
    "name:por_x_preferred":[
        "Tana"
    ],
    "name:ron_x_preferred":[
        "Tana"
    ],
    "name:rus_x_preferred":[
        "\u0422\u0430\u043d\u0430"
    ],
    "name:spa_x_preferred":[
        "Tana"
    ],
    "name:srp_x_preferred":[
        "\u0422\u0430\u043d\u0430"
    ],
    "name:swa_x_preferred":[
        "Tana"
    ],
    "name:swe_x_preferred":[
        "Tana"
    ],
    "name:ukr_x_preferred":[
        "\u0422\u0430\u043d\u0430"
    ],
    "name:und_x_variant":[
        "Tama"
    ],
    "name:urd_x_preferred":[
        "\u062a\u0627\u0646\u0627"
    ],
    "name:uzb_x_preferred":[
        "Tana"
    ],
    "name:vie_x_preferred":[
        "S\u00f4ng Tana"
    ],
    "wof:name":"Tana",
    "wof:placetype":"locality"
},
  "geometry": {"coordinates":[-5.07958,13.23364],"type":"Point"}
}