{
  "type": "Feature",
  "properties": {
    "gn:admin1_code":"05",
    "gn:asciiname":"Tana",
    "gn:country_code":"ML",
    "gn:dem":286,
    "gn:feature_class":"P",
    "gn:feature_code":"PPL",
    "gn:name":"Tana",
    "gn:population":0,
    "gn:timezone":"Africa/Bamako",
    "iso:country":"ML",
    "name:und_x_variant":[
        "Tama",
        "Tana"
    ],
    "wof:name":"Tana",
    "wof:placetype":"locality"
},
  "geometry": {"coordinates":[-5.07958,13.23364],"type":"Point"}
}