{
  "type": "Feature",
  "properties": {
    "gn:admin1_code":"7.0",
    "gn:asciiname":"Tyenfala",
    "gn:country_code":"ML",
    "gn:dem":346,
    "gn:feature_class":"P",
    "gn:feature_code":"PPL",
    "gn:name":"Ty\u00e8nfala",
    "gn:population":0,
    "gn:timezone":"Africa/Bamako",
    "iso:country":"ML",
    "wof:name":"Tyenfala",
    "wof:placetype":"locality"
},
  "geometry": {"coordinates":[-7.41479,12.31879],"type":"Point"}
}