{
  "type": "Feature",
  "properties": {
    "gn:admin1_code":"06",
    "gn:asciiname":"Seyna",
    "gn:country_code":"ML",
    "gn:dem":300,
    "gn:feature_class":"P",
    "gn:feature_code":"PPL",
    "gn:name":"Seyna",
    "gn:population":0,
    "gn:timezone":"Africa/Bamako",
    "iso:country":"ML",
    "name:fra_x_preferred":[
        "Seyna"
    ],
    "name:fra_x_variant":[
        "Se\u00efna"
    ],
    "name:und_x_variant":[
        "Se\u00efna"
    ],
    "wof:name":"Seyna",
    "wof:placetype":"locality"
},
  "geometry": {"coordinates":[-6.2675,12.1005],"type":"Point"}
}