{
  "type": "Feature",
  "properties": {
    "gn:admin1_code":"03",
    "gn:asciiname":"Nantela",
    "gn:country_code":"ML",
    "gn:dem":166,
    "gn:feature_class":"P",
    "gn:feature_code":"PPL",
    "gn:name":"Nant\u00e9la",
    "gn:population":0,
    "gn:timezone":"Africa/Bamako",
    "iso:country":"ML",
    "name:und_x_variant":[
        "Nantella",
        "Natella",
        "Nant\u00e9la"
    ],
    "wof:name":"Nantela",
    "wof:placetype":"locality"
},
  "geometry": {"coordinates":[-10.4617,13.1975],"type":"Point"}
}