{
  "type": "Feature",
  "properties": {
    "gn:admin1_code":"4.0",
    "gn:asciiname":"Matanga",
    "gn:country_code":"ML",
    "gn:dem":625,
    "gn:feature_class":"P",
    "gn:feature_code":"PPL",
    "gn:name":"Matanga",
    "gn:population":0,
    "gn:timezone":"Africa/Bamako",
    "iso:country":"ML",
    "wof:name":"Matanga",
    "wof:placetype":"locality"
},
  "geometry": {"coordinates":[-3.17433,14.73837],"type":"Point"}
}