{
  "type": "Feature",
  "properties": {
    "gn:admin1_code":"7.0",
    "gn:asciiname":"Fouarobougou",
    "gn:country_code":"ML",
    "gn:dem":390,
    "gn:feature_class":"P",
    "gn:feature_code":"PPL",
    "gn:name":"Fouarobougou",
    "gn:population":0,
    "gn:timezone":"Africa/Bamako",
    "iso:country":"ML",
    "wof:name":"Fouarobougou",
    "wof:placetype":"locality"
},
  "geometry": {"coordinates":[-7.82982,13.37472],"type":"Point"}
}