{
  "type": "Feature",
  "properties": {
    "gn:admin1_code":"9.0",
    "gn:asciiname":"Batal",
    "gn:country_code":"ML",
    "gn:dem":255,
    "gn:feature_class":"P",
    "gn:feature_code":"PPL",
    "gn:name":"Batal",
    "gn:population":0,
    "gn:timezone":"Africa/Bamako",
    "iso:country":"ML",
    "wof:name":"Batal",
    "wof:placetype":"locality"
},
  "geometry": {"coordinates":[-0.04389,16.37972],"type":"Point"}
}