{
  "type": "Feature",
  "properties": {
    "gn:admin1_code":"4.0",
    "gn:asciiname":"Garou-Do",
    "gn:country_code":"ML",
    "gn:dem":505,
    "gn:feature_class":"P",
    "gn:feature_code":"PPL",
    "gn:name":"Garou-Do",
    "gn:population":0,
    "gn:timezone":"Africa/Bamako",
    "iso:country":"ML",
    "wof:name":"Garou-Do",
    "wof:placetype":"locality"
},
  "geometry": {"coordinates":[-3.7385,14.0426],"type":"Point"}
}