{
  "type": "Feature",
  "properties": {
    "gn:admin1_code":"7.0",
    "gn:asciiname":"Sissela",
    "gn:country_code":"ML",
    "gn:dem":329,
    "gn:feature_class":"P",
    "gn:feature_code":"PPL",
    "gn:name":"Siss\u00e9la",
    "gn:population":0,
    "gn:timezone":"Africa/Bamako",
    "iso:country":"ML",
    "name:fra_x_preferred":[
        "Siss\u00e9la"
    ],
    "name:und_x_variant":[
        "Sis\u00e9la",
        "Siss\u00e9la"
    ],
    "wof:name":"Sissela",
    "wof:placetype":"locality"
},
  "geometry": {"coordinates":[-6.91175,11.99498],"type":"Point"}
}