{
  "type": "Feature",
  "properties": {
    "gn:admin1_code":"07",
    "gn:asciiname":"Kwala",
    "gn:country_code":"ML",
    "gn:dem":376,
    "gn:feature_class":"P",
    "gn:feature_code":"PPL",
    "gn:name":"Kwala",
    "gn:population":0,
    "gn:timezone":"Africa/Bamako",
    "iso:country":"ML",
    "wof:name":"Kwala",
    "wof:placetype":"locality"
},
  "geometry": {"coordinates":[-8.0422,14.1506],"type":"Point"}
}