{
  "type": "Feature",
  "properties": {
    "gn:admin1_code":"03",
    "gn:asciiname":"Kobama",
    "gn:country_code":"ML",
    "gn:dem":230,
    "gn:feature_class":"P",
    "gn:feature_code":"PPL",
    "gn:name":"Kobama",
    "gn:population":0,
    "gn:timezone":"Africa/Bamako",
    "iso:country":"ML",
    "wof:name":"Kobama",
    "wof:placetype":"locality"
},
  "geometry": {"coordinates":[-10.6441,13.9831],"type":"Point"}
}