{
  "type": "Feature",
  "properties": {
    "gn:admin1_code":"04",
    "gn:asciiname":"Dagambe",
    "gn:country_code":"ML",
    "gn:dem":267,
    "gn:feature_class":"P",
    "gn:feature_code":"PPL",
    "gn:name":"Dagamb\u00e9",
    "gn:population":0,
    "gn:timezone":"Africa/Bamako",
    "iso:country":"ML",
    "name:und_x_variant":[
        "Dakombo",
        "Dakambo",
        "Dagumb\u00e9",
        "Dagamb\u00e9"
    ],
    "wof:name":"Dagambe",
    "wof:placetype":"locality"
},
  "geometry": {"coordinates":[-4.0698,15.494],"type":"Point"}
}