{
  "type": "Feature",
  "properties": {
    "gn:admin1_code":"07",
    "gn:asciiname":"Dyorone",
    "gn:country_code":"ML",
    "gn:dem":327,
    "gn:feature_class":"P",
    "gn:feature_code":"PPL",
    "gn:name":"Dyoron\u00e9",
    "gn:population":0,
    "gn:timezone":"Africa/Bamako",
    "iso:country":"ML",
    "wof:name":"Dyorone",
    "wof:placetype":"locality"
},
  "geometry": {"coordinates":[-7.7632,14.1648],"type":"Point"}
}