{
  "type": "Feature",
  "properties": {
    "gn:admin1_code":"03",
    "gn:asciiname":"Komberade",
    "gn:country_code":"ML",
    "gn:dem":337,
    "gn:feature_class":"P",
    "gn:feature_code":"PPL",
    "gn:name":"Komb\u00e9rad\u00e9",
    "gn:population":0,
    "gn:timezone":"Africa/Bamako",
    "iso:country":"ML",
    "name:und_x_variant":[
        "Konb\u00e9rad\u00e9",
        "Komb\u00e9rad\u00e9"
    ],
    "wof:name":"Komberade",
    "wof:placetype":"locality"
},
  "geometry": {"coordinates":[-11.36214,12.35033],"type":"Point"}
}