{
  "type": "Feature",
  "properties": {
    "gn:admin1_code":"4.0",
    "gn:asciiname":"Sare-Ma",
    "gn:country_code":"ML",
    "gn:dem":273,
    "gn:feature_class":"P",
    "gn:feature_code":"PPL",
    "gn:name":"Sar\u00e9-Ma",
    "gn:population":0,
    "gn:timezone":"Africa/Bamako",
    "iso:country":"ML",
    "wof:name":"Sare-Ma",
    "wof:placetype":"locality"
},
  "geometry": {"coordinates":[-4.06734,14.53722],"type":"Point"}
}