{
  "type": "Feature",
  "properties": {
    "gn:admin1_code":"5.0",
    "gn:asciiname":"Nonba",
    "gn:country_code":"ML",
    "gn:dem":287,
    "gn:feature_class":"P",
    "gn:feature_code":"PPL",
    "gn:name":"Nonba",
    "gn:population":0,
    "gn:timezone":"Africa/Bamako",
    "iso:country":"ML",
    "wof:name":"Nonba",
    "wof:placetype":"locality"
},
  "geometry": {"coordinates":[-6.28,12.9955],"type":"Point"}
}