{
  "type": "Feature",
  "properties": {
    "gn:admin1_code":"03",
    "gn:asciiname":"Foulanguedou",
    "gn:country_code":"ML",
    "gn:dem":213,
    "gn:feature_class":"P",
    "gn:feature_code":"PPL",
    "gn:name":"Foulangu\u00e9dou",
    "gn:population":0,
    "gn:timezone":"Africa/Bamako",
    "iso:country":"ML",
    "wof:name":"Foulanguedou",
    "wof:placetype":"locality"
},
  "geometry": {"coordinates":[-9.9526,14.4226],"type":"Point"}
}