{
  "type": "Feature",
  "properties": {
    "gn:admin1_code":"06",
    "gn:asciiname":"Zanina",
    "gn:country_code":"ML",
    "gn:dem":330,
    "gn:feature_class":"P",
    "gn:feature_code":"PPL",
    "gn:name":"Zanina",
    "gn:population":0,
    "gn:timezone":"Africa/Bamako",
    "iso:country":"ML",
    "name:fin_x_preferred":[
        "Zanina"
    ],
    "name:fra_x_preferred":[
        "Nzanina"
    ],
    "name:fra_x_variant":[
        "Zanina"
    ],
    "name:ita_x_preferred":[
        "Zanina"
    ],
    "name:nld_x_preferred":[
        "Zanina"
    ],
    "name:por_x_preferred":[
        "Zanina"
    ],
    "name:spa_x_preferred":[
        "Zanina"
    ],
    "name:zho_x_preferred":[
        "\u624e\u5c3c\u7d0d"
    ],
    "wof:name":"Zanina",
    "wof:placetype":"locality"
},
  "geometry": {"coordinates":[-6.62043,11.17757],"type":"Point"}
}