{
  "type": "Feature",
  "properties": {
    "gn:admin1_code":"06",
    "gn:asciiname":"Zanina",
    "gn:country_code":"ML",
    "gn:dem":330,
    "gn:feature_class":"P",
    "gn:feature_code":"PPL",
    "gn:name":"Zanina",
    "gn:population":0,
    "gn:timezone":"Africa/Bamako",
    "iso:country":"ML",
    "name:fra_x_preferred":[
        "Nzanina"
    ],
    "name:und_x_variant":[
        "Nzanina"
    ],
    "wof:name":"Zanina",
    "wof:placetype":"locality"
},
  "geometry": {"coordinates":[-6.62043,11.17757],"type":"Point"}
}