{
  "type": "Feature",
  "properties": {
    "gn:admin1_code":"07",
    "gn:asciiname":"Tyemba",
    "gn:country_code":"ML",
    "gn:dem":361,
    "gn:feature_class":"P",
    "gn:feature_code":"PPL",
    "gn:name":"Ty\u00e8mba",
    "gn:population":0,
    "gn:timezone":"Africa/Bamako",
    "iso:country":"ML",
    "wof:name":"Tyemba",
    "wof:placetype":"locality"
},
  "geometry": {"coordinates":[-7.7147,12.1246],"type":"Point"}
}