{
  "type": "Feature",
  "properties": {
    "gn:admin1_code":"7.0",
    "gn:asciiname":"Fendiebougou",
    "gn:country_code":"ML",
    "gn:dem":357,
    "gn:feature_class":"P",
    "gn:feature_code":"PPL",
    "gn:name":"F\u00e8ndi\u00e8bougou",
    "gn:population":0,
    "gn:timezone":"Africa/Bamako",
    "iso:country":"ML",
    "wof:name":"Fendiebougou",
    "wof:placetype":"locality"
},
  "geometry": {"coordinates":[-7.6486,13.39453],"type":"Point"}
}