{
  "type": "Feature",
  "properties": {
    "gn:admin1_code":"6.0",
    "gn:asciiname":"Kolonba",
    "gn:country_code":"ML",
    "gn:dem":374,
    "gn:feature_class":"P",
    "gn:feature_code":"PPL",
    "gn:name":"Kolonba",
    "gn:population":0,
    "gn:timezone":"Africa/Bamako",
    "iso:country":"ML",
    "wof:name":"Kolonba",
    "wof:placetype":"locality"
},
  "geometry": {"coordinates":[-7.08698,11.14835],"type":"Point"}
}