{
  "type": "Feature",
  "properties": {
    "gn:admin1_code":"07",
    "gn:asciiname":"Sola",
    "gn:country_code":"ML",
    "gn:dem":372,
    "gn:feature_class":"P",
    "gn:feature_code":"PPL",
    "gn:name":"Sola",
    "gn:population":0,
    "gn:timezone":"Africa/Bamako",
    "iso:country":"ML",
    "name:bpy_x_preferred":[
        "\u09b8\u09cb\u09b2\u09be"
    ],
    "name:cat_x_preferred":[
        "Sola"
    ],
    "name:ceb_x_preferred":[
        "Sola"
    ],
    "name:dan_x_preferred":[
        "Sola"
    ],
    "name:deu_x_preferred":[
        "Sola"
    ],
    "name:epo_x_preferred":[
        "Sola"
    ],
    "name:est_x_preferred":[
        "Sola vald"
    ],
    "name:eus_x_preferred":[
        "Sola"
    ],
    "name:fas_x_preferred":[
        "\u0633\u0648\u0644\u0627"
    ],
    "name:fin_x_preferred":[
        "Sola"
    ],
    "name:fra_x_preferred":[
        "Sola"
    ],
    "name:glg_x_preferred":[
        "Sola"
    ],
    "name:hun_x_preferred":[
        "Sola k\u00f6zs\u00e9g"
    ],
    "name:hye_x_preferred":[
        "\u054d\u0578\u056c\u0561"
    ],
    "name:ita_x_preferred":[
        "Sola"
    ],
    "name:jav_x_preferred":[
        "Sola"
    ],
    "name:kor_x_preferred":[
        "\uc194\ub77c"
    ],
    "name:lat_x_preferred":[
        "Sola"
    ],
    "name:lim_x_preferred":[
        "Sola"
    ],
    "name:msa_x_preferred":[
        "Sola"
    ],
    "name:nds_x_preferred":[
        "Kommun Sola"
    ],
    "name:nld_x_preferred":[
        "Sola"
    ],
    "name:nno_x_preferred":[
        "Sola kommune"
    ],
    "name:nor_x_preferred":[
        "Sola"
    ],
    "name:pol_x_preferred":[
        "Sola"
    ],
    "name:por_x_preferred":[
        "Sola"
    ],
    "name:ron_x_preferred":[
        "Sola"
    ],
    "name:rus_x_preferred":[
        "\u0421\u043e\u043b\u0430"
    ],
    "name:slv_x_preferred":[
        "Sola"
    ],
    "name:sme_x_preferred":[
        "Sola"
    ],
    "name:spa_x_preferred":[
        "Sola"
    ],
    "name:sqi_x_preferred":[
        "Sola"
    ],
    "name:swe_x_preferred":[
        "Sola kommun"
    ],
    "name:war_x_preferred":[
        "Sola"
    ],
    "name:zho_x_preferred":[
        "\u8607\u62c9"
    ],
    "wof:name":"Sola",
    "wof:placetype":"locality"
},
  "geometry": {"coordinates":[-8.14049,13.93484],"type":"Point"}
}