{
  "type": "Feature",
  "properties": {
    "gn:admin1_code":"7.0",
    "gn:asciiname":"Nkalamedo",
    "gn:country_code":"ML",
    "gn:dem":373,
    "gn:feature_class":"P",
    "gn:feature_code":"PPL",
    "gn:name":"Nkalam\u00e9do",
    "gn:population":0,
    "gn:timezone":"Africa/Bamako",
    "iso:country":"ML",
    "wof:name":"Nkalamedo",
    "wof:placetype":"locality"
},
  "geometry": {"coordinates":[-7.74711,12.13411],"type":"Point"}
}