{
  "type": "Feature",
  "properties": {
    "gn:admin1_code":"7.0",
    "gn:asciiname":"Sirikoro",
    "gn:country_code":"ML",
    "gn:dem":323,
    "gn:feature_class":"P",
    "gn:feature_code":"PPL",
    "gn:name":"Sirikoro",
    "gn:population":0,
    "gn:timezone":"Africa/Bamako",
    "iso:country":"ML",
    "wof:name":"Sirikoro",
    "wof:placetype":"locality"
},
  "geometry": {"coordinates":[-7.0987,12.04117],"type":"Point"}
}