{
  "type": "Feature",
  "properties": {
    "gn:admin1_code":"3.0",
    "gn:asciiname":"Baye",
    "gn:country_code":"ML",
    "gn:dem":312,
    "gn:feature_class":"P",
    "gn:feature_code":"PPL",
    "gn:name":"Bay\u00e9",
    "gn:population":0,
    "gn:timezone":"Africa/Bamako",
    "iso:country":"ML",
    "name:fin_x_preferred":[
        "Baye"
    ],
    "name:fra_x_preferred":[
        "Baye"
    ],
    "name:ind_x_preferred":[
        "Baye"
    ],
    "name:ita_x_preferred":[
        "Baye"
    ],
    "name:nld_x_preferred":[
        "Baye"
    ],
    "name:spa_x_preferred":[
        "Baye"
    ],
    "name:und_x_variant":[
        "Bah\u00e9",
        "Bay\u00e9"
    ],
    "wof:name":"Baye",
    "wof:placetype":"locality"
},
  "geometry": {"coordinates":[-9.9806,13.0836],"type":"Point"}
}