{
  "type": "Feature",
  "properties": {
    "gn:admin1_code":"6.0",
    "gn:asciiname":"Kongola",
    "gn:country_code":"ML",
    "gn:dem":327,
    "gn:feature_class":"P",
    "gn:feature_code":"PPL",
    "gn:name":"Kongola",
    "gn:population":0,
    "gn:timezone":"Africa/Bamako",
    "iso:country":"ML",
    "name:deu_x_preferred":[
        "Kongola"
    ],
    "wof:name":"Kongola",
    "wof:placetype":"locality"
},
  "geometry": {"coordinates":[-6.43476,11.60466],"type":"Point"}
}