{
  "type": "Feature",
  "properties": {
    "gn:admin1_code":"3.0",
    "gn:asciiname":"Tiguinyan",
    "gn:country_code":"ML",
    "gn:dem":309,
    "gn:feature_class":"P",
    "gn:feature_code":"PPL",
    "gn:name":"Tiguinyan",
    "gn:population":0,
    "gn:timezone":"Africa/Bamako",
    "iso:country":"ML",
    "name:und_x_variant":[
        "Tiginyan",
        "Tiguinyan"
    ],
    "wof:name":"Tiguinyan",
    "wof:placetype":"locality"
},
  "geometry": {"coordinates":[-8.396,14.3883],"type":"Point"}
}