{
  "type": "Feature",
  "properties": {
    "gn:admin1_code":"03",
    "gn:asciiname":"Daramboungala",
    "gn:country_code":"ML",
    "gn:dem":88,
    "gn:feature_class":"P",
    "gn:feature_code":"PPL",
    "gn:name":"Daramboungala",
    "gn:population":0,
    "gn:timezone":"Africa/Bamako",
    "iso:country":"ML",
    "name:und_x_variant":[
        "Darambougoula",
        "Daramboungala"
    ],
    "wof:name":"Daramboungala",
    "wof:placetype":"locality"
},
  "geometry": {"coordinates":[-10.932,14.421],"type":"Point"}
}