{
  "type": "Feature",
  "properties": {
    "gn:admin1_code":"04",
    "gn:asciiname":"Sare Dina",
    "gn:country_code":"ML",
    "gn:dem":272,
    "gn:feature_class":"P",
    "gn:feature_code":"PPL",
    "gn:name":"Sar\u00e9 Dina",
    "gn:population":0,
    "gn:timezone":"Africa/Bamako",
    "iso:country":"ML",
    "name:und_x_variant":[
        "Sardina",
        "Sar\u00e9 Dina"
    ],
    "wof:name":"Sare Dina",
    "wof:placetype":"locality"
},
  "geometry": {"coordinates":[-1.8399,14.76946],"type":"Point"}
}