{
  "type": "Feature",
  "properties": {
    "gn:admin1_code":"04",
    "gn:asciiname":"Wendiana",
    "gn:country_code":"ML",
    "gn:dem":284,
    "gn:feature_class":"P",
    "gn:feature_code":"PPL",
    "gn:name":"Wendiana",
    "gn:population":0,
    "gn:timezone":"Africa/Bamako",
    "iso:country":"ML",
    "name:und_x_variant":[
        "Wandiana",
        "Wendiana"
    ],
    "wof:name":"Wendiana",
    "wof:placetype":"locality"
},
  "geometry": {"coordinates":[-3.6582,13.7041],"type":"Point"}
}