{
  "type": "Feature",
  "properties": {
    "gn:admin1_code":"5.0",
    "gn:asciiname":"Fassongo Ouere",
    "gn:country_code":"ML",
    "gn:dem":291,
    "gn:feature_class":"P",
    "gn:feature_code":"PPL",
    "gn:name":"Fassongo Ou\u00e8r\u00e8",
    "gn:population":0,
    "gn:timezone":"Africa/Bamako",
    "iso:country":"ML",
    "wof:name":"Fassongo Ouere",
    "wof:placetype":"locality"
},
  "geometry": {"coordinates":[-6.60438,13.36515],"type":"Point"}
}