{
  "type": "Feature",
  "properties": {
    "gn:admin1_code":"07",
    "gn:asciiname":"Sirakoroni",
    "gn:country_code":"ML",
    "gn:dem":350,
    "gn:feature_class":"P",
    "gn:feature_code":"PPL",
    "gn:name":"Sirakoroni",
    "gn:population":0,
    "gn:timezone":"Africa/Bamako",
    "iso:country":"ML",
    "wof:name":"Sirakoroni",
    "wof:placetype":"locality"
},
  "geometry": {"coordinates":[-7.84896,12.87416],"type":"Point"}
}