{
  "type": "Feature",
  "properties": {
    "gn:admin1_code":"3.0",
    "gn:asciiname":"Bafaroto",
    "gn:country_code":"ML",
    "gn:dem":134,
    "gn:feature_class":"P",
    "gn:feature_code":"PPL",
    "gn:name":"Bafaroto",
    "gn:population":0,
    "gn:timezone":"Africa/Bamako",
    "iso:country":"ML",
    "name:und_x_variant":[
        "Barafoto",
        "Bafaroto"
    ],
    "wof:name":"Bafaroto",
    "wof:placetype":"locality"
},
  "geometry": {"coordinates":[-10.9012,13.9958],"type":"Point"}
}