{
  "type": "Feature",
  "properties": {
    "gn:admin1_code":"03",
    "gn:asciiname":"Touba",
    "gn:country_code":"ML",
    "gn:dem":74,
    "gn:feature_class":"P",
    "gn:feature_code":"PPL",
    "gn:name":"Touba",
    "gn:population":0,
    "gn:timezone":"Africa/Bamako",
    "iso:country":"ML",
    "wof:name":"Touba",
    "wof:placetype":"locality"
},
  "geometry": {"coordinates":[-10.9788,14.2996],"type":"Point"}
}