{
  "type": "Feature",
  "properties": {
    "gn:admin1_code":"9.0",
    "gn:asciiname":"Gougorgo",
    "gn:country_code":"ML",
    "gn:dem":243,
    "gn:feature_class":"P",
    "gn:feature_code":"PPL",
    "gn:name":"Gougorgo",
    "gn:population":0,
    "gn:timezone":"Africa/Bamako",
    "iso:country":"ML",
    "wof:name":"Gougorgo",
    "wof:placetype":"locality"
},
  "geometry": {"coordinates":[0.4752,15.5588],"type":"Point"}
}