{
  "type": "Feature",
  "properties": {
    "gn:admin1_code":"7.0",
    "gn:asciiname":"Boulkassoumbougou",
    "gn:country_code":"ML",
    "gn:dem":341,
    "gn:feature_class":"P",
    "gn:feature_code":"PPL",
    "gn:name":"Boulkassoumbougou",
    "gn:population":0,
    "gn:timezone":"Africa/Bamako",
    "iso:country":"ML",
    "name:und_x_variant":[
        "Boulkassonmbougou",
        "Boulkassoumbougou"
    ],
    "wof:name":"Boulkassoumbougou",
    "wof:placetype":"locality"
},
  "geometry": {"coordinates":[-7.9258,12.68487],"type":"Point"}
}