{
  "type": "Feature",
  "properties": {
    "gn:admin1_code":"07",
    "gn:asciiname":"Niamabikoni",
    "gn:country_code":"ML",
    "gn:dem":372,
    "gn:feature_class":"P",
    "gn:feature_code":"PPL",
    "gn:name":"Niamabikoni",
    "gn:population":0,
    "gn:timezone":"Africa/Bamako",
    "iso:country":"ML",
    "name:fra_x_preferred":[
        "Niamabikoni"
    ],
    "wof:name":"Niamabikoni",
    "wof:placetype":"locality"
},
  "geometry": {"coordinates":[-8.3183,13.6547],"type":"Point"}
}