{
  "type": "Feature",
  "properties": {
    "gn:admin1_code":"04",
    "gn:asciiname":"Tango",
    "gn:country_code":"ML",
    "gn:dem":266,
    "gn:feature_class":"P",
    "gn:feature_code":"PPL",
    "gn:name":"Tango",
    "gn:population":0,
    "gn:timezone":"Africa/Bamako",
    "iso:country":"ML",
    "name:und_x_variant":[
        "Tangon",
        "Tango"
    ],
    "wof:name":"Tango",
    "wof:placetype":"locality"
},
  "geometry": {"coordinates":[-3.9285,15.4104],"type":"Point"}
}