{
  "type": "Feature",
  "properties": {
    "gn:admin1_code":"06",
    "gn:asciiname":"Mizanso",
    "gn:country_code":"ML",
    "gn:dem":322,
    "gn:feature_class":"P",
    "gn:feature_code":"PPL",
    "gn:name":"Mizanso",
    "gn:population":0,
    "gn:timezone":"Africa/Bamako",
    "iso:country":"ML",
    "name:und_x_variant":[
        "Kimbela",
        "Mizanso"
    ],
    "wof:name":"Mizanso",
    "wof:placetype":"locality"
},
  "geometry": {"coordinates":[-5.30061,11.8778],"type":"Point"}
}