{
  "type": "Feature",
  "properties": {
    "gn:admin1_code":"4.0",
    "gn:asciiname":"Torokouma",
    "gn:country_code":"ML",
    "gn:dem":418,
    "gn:feature_class":"P",
    "gn:feature_code":"PPL",
    "gn:name":"Torokouma",
    "gn:population":0,
    "gn:timezone":"Africa/Bamako",
    "iso:country":"ML",
    "wof:name":"Torokouma",
    "wof:placetype":"locality"
},
  "geometry": {"coordinates":[-3.9426,13.7163],"type":"Point"}
}