{
  "type": "Feature",
  "properties": {
    "gn:admin1_code":"07",
    "gn:asciiname":"Djiblebougou",
    "gn:country_code":"ML",
    "gn:dem":421,
    "gn:feature_class":"P",
    "gn:feature_code":"PPL",
    "gn:name":"Djibl\u00e8bougou",
    "gn:population":0,
    "gn:timezone":"Africa/Bamako",
    "iso:country":"ML",
    "wof:name":"Djiblebougou",
    "wof:placetype":"locality"
},
  "geometry": {"coordinates":[-8.1456,13.0403],"type":"Point"}
}