{
  "type": "Feature",
  "properties": {
    "gn:admin1_code":"3.0",
    "gn:asciiname":"Gourel Mousse",
    "gn:country_code":"ML",
    "gn:dem":216,
    "gn:feature_class":"P",
    "gn:feature_code":"PPL",
    "gn:name":"Gourel Mousse",
    "gn:population":0,
    "gn:timezone":"Africa/Bamako",
    "iso:country":"ML",
    "wof:name":"Gourel Mousse",
    "wof:placetype":"locality"
},
  "geometry": {"coordinates":[-9.5266,15.29168],"type":"Point"}
}