{
  "type": "Feature",
  "properties": {
    "gn:admin1_code":"07",
    "gn:asciiname":"Sirable",
    "gn:country_code":"ML",
    "gn:dem":264,
    "gn:feature_class":"P",
    "gn:feature_code":"PPL",
    "gn:name":"Sirabl\u00e9",
    "gn:population":0,
    "gn:timezone":"Africa/Bamako",
    "iso:country":"ML",
    "wof:name":"Sirable",
    "wof:placetype":"locality"
},
  "geometry": {"coordinates":[-8.3861,14.8042],"type":"Point"}
}