{
  "type": "Feature",
  "properties": {
    "gn:admin1_code":"04",
    "gn:asciiname":"Fantina",
    "gn:country_code":"ML",
    "gn:dem":276,
    "gn:feature_class":"P",
    "gn:feature_code":"PPL",
    "gn:name":"Fantina",
    "gn:population":0,
    "gn:timezone":"Africa/Bamako",
    "iso:country":"ML",
    "name:ita_x_preferred":[
        "Fantina"
    ],
    "wof:name":"Fantina",
    "wof:placetype":"locality"
},
  "geometry": {"coordinates":[-5.1339,14.4181],"type":"Point"}
}