{
  "type": "Feature",
  "properties": {
    "gn:admin1_code":"03",
    "gn:asciiname":"Makadougou",
    "gn:country_code":"ML",
    "gn:dem":282,
    "gn:feature_class":"P",
    "gn:feature_code":"PPL",
    "gn:name":"Makadougou",
    "gn:population":0,
    "gn:timezone":"Africa/Bamako",
    "iso:country":"ML",
    "wof:name":"Makadougou",
    "wof:placetype":"locality"
},
  "geometry": {"coordinates":[-10.8013,14.2315],"type":"Point"}
}