{
  "type": "Feature",
  "properties": {
    "gn:admin1_code":"3.0",
    "gn:asciiname":"Boudou Kamara",
    "gn:country_code":"ML",
    "gn:dem":107,
    "gn:feature_class":"P",
    "gn:feature_code":"PPL",
    "gn:name":"Boudou Kamara",
    "gn:population":0,
    "gn:timezone":"Africa/Bamako",
    "iso:country":"ML",
    "wof:name":"Boudou Kamara",
    "wof:placetype":"locality"
},
  "geometry": {"coordinates":[-11.57424,15.20109],"type":"Point"}
}