{
  "type": "Feature",
  "properties": {
    "gn:admin1_code":"07",
    "gn:asciiname":"Dyaradjya Kamara",
    "gn:country_code":"ML",
    "gn:dem":280,
    "gn:feature_class":"P",
    "gn:feature_code":"PPL",
    "gn:name":"Dyaradjya Kamara",
    "gn:population":0,
    "gn:timezone":"Africa/Bamako",
    "iso:country":"ML",
    "wof:name":"Dyaradjya Kamara",
    "wof:placetype":"locality"
},
  "geometry": {"coordinates":[-8.82233,15.31472],"type":"Point"}
}