{
  "type": "Feature",
  "properties": {
    "gn:admin1_code":"03",
    "gn:asciiname":"Lenguema",
    "gn:country_code":"ML",
    "gn:dem":308,
    "gn:feature_class":"P",
    "gn:feature_code":"PPL",
    "gn:name":"Lengu\u00e8ma",
    "gn:population":0,
    "gn:timezone":"Africa/Bamako",
    "iso:country":"ML",
    "name:und_x_variant":[
        "Lingu\u00e8ma",
        "Lengu\u00e8ma"
    ],
    "wof:name":"Lenguema",
    "wof:placetype":"locality"
},
  "geometry": {"coordinates":[-9.5963,13.3778],"type":"Point"}
}