{
  "type": "Feature",
  "properties": {
    "gn:admin1_code":"4.0",
    "gn:asciiname":"Ambakele",
    "gn:country_code":"ML",
    "gn:dem":498,
    "gn:feature_class":"P",
    "gn:feature_code":"PPL",
    "gn:name":"Ambak\u00e9l\u00e9",
    "gn:population":0,
    "gn:timezone":"Africa/Bamako",
    "iso:country":"ML",
    "wof:name":"Ambakele",
    "wof:placetype":"locality"
},
  "geometry": {"coordinates":[-3.04933,14.90287],"type":"Point"}
}