{
  "type": "Feature",
  "properties": {
    "gn:admin1_code":"7.0",
    "gn:asciiname":"Mangola",
    "gn:country_code":"ML",
    "gn:dem":441,
    "gn:feature_class":"P",
    "gn:feature_code":"PPL",
    "gn:name":"Mangola",
    "gn:population":0,
    "gn:timezone":"Africa/Bamako",
    "iso:country":"ML",
    "wof:name":"Mangola",
    "wof:placetype":"locality"
},
  "geometry": {"coordinates":[-8.23561,12.98365],"type":"Point"}
}