{
  "type": "Feature",
  "properties": {
    "gn:admin1_code":"07",
    "gn:asciiname":"Masila",
    "gn:country_code":"ML",
    "gn:dem":307,
    "gn:feature_class":"P",
    "gn:feature_code":"PPL",
    "gn:name":"Masila",
    "gn:population":0,
    "gn:timezone":"Africa/Bamako",
    "iso:country":"ML",
    "name:und_x_variant":[
        "Massila",
        "Masila"
    ],
    "wof:name":"Masila",
    "wof:placetype":"locality"
},
  "geometry": {"coordinates":[-8.5111,15.17563],"type":"Point"}
}