{
  "type": "Feature",
  "properties": {
    "gn:admin1_code":"03",
    "gn:asciiname":"Dalaba",
    "gn:country_code":"ML",
    "gn:dem":144,
    "gn:feature_class":"P",
    "gn:feature_code":"PPL",
    "gn:name":"Dalaba",
    "gn:population":0,
    "gn:timezone":"Africa/Bamako",
    "iso:country":"ML",
    "name:bul_x_preferred":[
        "\u0414\u0430\u043b\u0430\u0431\u0430"
    ],
    "name:deu_x_preferred":[
        "Dalaba"
    ],
    "name:fin_x_preferred":[
        "Dalaba"
    ],
    "name:fra_x_preferred":[
        "Dalaba"
    ],
    "name:ita_x_preferred":[
        "Dalaba"
    ],
    "name:msa_x_preferred":[
        "Dalaba"
    ],
    "name:nld_x_preferred":[
        "Dalaba"
    ],
    "name:pol_x_preferred":[
        "Dalaba"
    ],
    "name:spa_x_preferred":[
        "Dalaba"
    ],
    "wof:name":"Dalaba",
    "wof:placetype":"locality"
},
  "geometry": {"coordinates":[-11.7096,14.11337],"type":"Point"}
}