{
  "type": "Feature",
  "properties": {
    "gn:admin1_code":"03",
    "gn:asciiname":"Dalaba",
    "gn:country_code":"ML",
    "gn:dem":144,
    "gn:feature_class":"P",
    "gn:feature_code":"PPL",
    "gn:name":"Dalaba",
    "gn:population":0,
    "gn:timezone":"Africa/Bamako",
    "iso:country":"ML",
    "name:ben_x_preferred":[
        "\u09a1\u09be\u09b2\u09be\u09ac\u09be"
    ],
    "name:bul_x_preferred":[
        "\u0414\u0430\u043b\u0430\u0431\u0430"
    ],
    "name:deu_x_preferred":[
        "Dalaba"
    ],
    "name:ell_x_preferred":[
        "\u039d\u03c4\u03b1\u03bb\u03ac\u03bc\u03c0\u03b1"
    ],
    "name:fas_x_preferred":[
        "\u062f\u0627\u0644\u0627\u0628\u0627"
    ],
    "name:fin_x_preferred":[
        "Dalaba"
    ],
    "name:fra_x_preferred":[
        "Dalaba"
    ],
    "name:heb_x_preferred":[
        "\u05d3\u05dc\u05d0\u05d1\u05d4"
    ],
    "name:hin_x_preferred":[
        "\u0921\u0932\u093e\u092c\u093e"
    ],
    "name:hun_x_preferred":[
        "Dalaba"
    ],
    "name:ind_x_preferred":[
        "Dalaba"
    ],
    "name:ita_x_preferred":[
        "Dalaba"
    ],
    "name:jpn_x_preferred":[
        "\u30c0\u30e9\u30d0"
    ],
    "name:kor_x_preferred":[
        "\ub2ec\ub77c\ubc14"
    ],
    "name:msa_x_preferred":[
        "Dalaba"
    ],
    "name:nld_x_preferred":[
        "Dalaba"
    ],
    "name:pol_x_preferred":[
        "Dalaba"
    ],
    "name:spa_x_preferred":[
        "Dalaba"
    ],
    "name:swe_x_preferred":[
        "Dalaba"
    ],
    "name:tur_x_preferred":[
        "Dalaba"
    ],
    "name:ukr_x_preferred":[
        "\u0414\u0430\u043b\u0430\u0431\u0430"
    ],
    "name:urd_x_preferred":[
        "\u0688\u0627\u0644\u0627\u0628\u0627"
    ],
    "name:vie_x_preferred":[
        "Dalaba"
    ],
    "wof:name":"Dalaba",
    "wof:placetype":"locality"
},
  "geometry": {"coordinates":[-11.7096,14.11337],"type":"Point"}
}