{
  "type": "Feature",
  "properties": {
    "gn:admin1_code":"07",
    "gn:asciiname":"Goumbou",
    "gn:country_code":"ML",
    "gn:dem":274,
    "gn:feature_class":"P",
    "gn:feature_code":"PPL",
    "gn:name":"Goumbou",
    "gn:population":0,
    "gn:timezone":"Africa/Bamako",
    "iso:country":"ML",
    "name:und_x_variant":[
        "Gumbu",
        "Goumbou"
    ],
    "wof:name":"Goumbou",
    "wof:placetype":"locality"
},
  "geometry": {"coordinates":[-7.454,14.9882],"type":"Point"}
}