{
  "type": "Feature",
  "properties": {
    "gn:admin1_code":"03",
    "gn:asciiname":"Keniekenieba",
    "gn:country_code":"ML",
    "gn:dem":71,
    "gn:feature_class":"P",
    "gn:feature_code":"PPL",
    "gn:name":"K\u00e9ni\u00e9k\u00e9ni\u00e9ba",
    "gn:population":0,
    "gn:timezone":"Africa/Bamako",
    "iso:country":"ML",
    "wof:name":"Keniekenieba",
    "wof:placetype":"locality"
},
  "geometry": {"coordinates":[-11.86741,13.37262],"type":"Point"}
}