{
  "type": "Feature",
  "properties": {
    "gn:admin1_code":"03",
    "gn:asciiname":"Melgue",
    "gn:country_code":"ML",
    "gn:dem":43,
    "gn:feature_class":"P",
    "gn:feature_code":"PPL",
    "gn:name":"Melgu\u00e9",
    "gn:population":0,
    "gn:timezone":"Africa/Bamako",
    "iso:country":"ML",
    "wof:name":"Melgue",
    "wof:placetype":"locality"
},
  "geometry": {"coordinates":[-11.79057,14.90163],"type":"Point"}
}