{
  "type": "Feature",
  "properties": {
    "gn:admin1_code":"07",
    "gn:asciiname":"Tenezana",
    "gn:country_code":"ML",
    "gn:dem":382,
    "gn:feature_class":"P",
    "gn:feature_code":"PPL",
    "gn:name":"T\u00e8n\u00e8zana",
    "gn:population":0,
    "gn:timezone":"Africa/Bamako",
    "iso:country":"ML",
    "name:und_x_variant":[
        "Tmezama",
        "T\u00e8n\u00e8zana"
    ],
    "wof:name":"Tenezana",
    "wof:placetype":"locality"
},
  "geometry": {"coordinates":[-7.98473,13.01095],"type":"Point"}
}