{
  "type": "Feature",
  "properties": {
    "gn:admin1_code":"05",
    "gn:asciiname":"Diagou",
    "gn:country_code":"ML",
    "gn:dem":332,
    "gn:feature_class":"P",
    "gn:feature_code":"PPL",
    "gn:name":"Diagou",
    "gn:population":0,
    "gn:timezone":"Africa/Bamako",
    "iso:country":"ML",
    "name:und_x_variant":[
        "Diago",
        "Diagou"
    ],
    "wof:name":"Diagou",
    "wof:placetype":"locality"
},
  "geometry": {"coordinates":[-7.00113,13.04459],"type":"Point"}
}