{
  "type": "Feature",
  "properties": {
    "gn:admin1_code":"7.0",
    "gn:asciiname":"Bamakolon",
    "gn:country_code":"ML",
    "gn:dem":335,
    "gn:feature_class":"P",
    "gn:feature_code":"PPL",
    "gn:name":"Bamakolon",
    "gn:population":0,
    "gn:timezone":"Africa/Bamako",
    "iso:country":"ML",
    "name:fra_x_preferred":[
        "Bamakolon"
    ],
    "wof:name":"Bamakolon",
    "wof:placetype":"locality"
},
  "geometry": {"coordinates":[-8.3451,13.7195],"type":"Point"}
}