{
  "type": "Feature",
  "properties": {
    "gn:admin1_code":"5.0",
    "gn:asciiname":"Lembe",
    "gn:country_code":"ML",
    "gn:dem":293,
    "gn:feature_class":"P",
    "gn:feature_code":"PPL",
    "gn:name":"L\u00e8mb\u00e8",
    "gn:population":0,
    "gn:timezone":"Africa/Bamako",
    "iso:country":"ML",
    "wof:name":"Lembe",
    "wof:placetype":"locality"
},
  "geometry": {"coordinates":[-6.6786,13.4897],"type":"Point"}
}