{
  "type": "Feature",
  "properties": {
    "gn:admin1_code":"6.0",
    "gn:asciiname":"Dialakoro",
    "gn:country_code":"ML",
    "gn:dem":347,
    "gn:feature_class":"P",
    "gn:feature_code":"PPL",
    "gn:name":"Dialakoro",
    "gn:population":0,
    "gn:timezone":"Africa/Bamako",
    "iso:country":"ML",
    "name:fra_x_preferred":[
        "Dialakoro"
    ],
    "name:ita_x_preferred":[
        "Dialakoro"
    ],
    "name:spa_x_preferred":[
        "Dialakoro"
    ],
    "wof:name":"Dialakoro",
    "wof:placetype":"locality"
},
  "geometry": {"coordinates":[-7.5267,11.3075],"type":"Point"}
}