{
  "type": "Feature",
  "properties": {
    "gn:admin1_code":"7.0",
    "gn:asciiname":"Serebougou",
    "gn:country_code":"ML",
    "gn:dem":327,
    "gn:feature_class":"P",
    "gn:feature_code":"PPL",
    "gn:name":"S\u00e9r\u00e9bougou",
    "gn:population":0,
    "gn:timezone":"Africa/Bamako",
    "iso:country":"ML",
    "wof:name":"Serebougou",
    "wof:placetype":"locality"
},
  "geometry": {"coordinates":[-7.64247,13.21015],"type":"Point"}
}