{
  "type": "Feature",
  "properties": {
    "gn:admin1_code":"7.0",
    "gn:asciiname":"Diokalani",
    "gn:country_code":"ML",
    "gn:dem":341,
    "gn:feature_class":"P",
    "gn:feature_code":"PPL",
    "gn:name":"Diokalani",
    "gn:population":0,
    "gn:timezone":"Africa/Bamako",
    "iso:country":"ML",
    "wof:name":"Diokalani",
    "wof:placetype":"locality"
},
  "geometry": {"coordinates":[-7.58402,12.36937],"type":"Point"}
}