{
  "type": "Feature",
  "properties": {
    "gn:admin1_code":"03",
    "gn:asciiname":"Lambidou",
    "gn:country_code":"ML",
    "gn:dem":280,
    "gn:feature_class":"P",
    "gn:feature_code":"PPL",
    "gn:name":"Lambidou",
    "gn:population":0,
    "gn:timezone":"Africa/Bamako",
    "iso:country":"ML",
    "name:fra_x_preferred":[
        "Lambidou"
    ],
    "name:ita_x_preferred":[
        "Lambidou"
    ],
    "name:nld_x_preferred":[
        "Lambidou"
    ],
    "name:spa_x_preferred":[
        "Lambidou"
    ],
    "name:urd_x_preferred":[
        "\u0644\u0627\u0645\u0628\u06cc\u0688\u0648"
    ],
    "name:zho_x_preferred":[
        "\u862d\u6bd4\u675c"
    ],
    "wof:name":"Lambidou",
    "wof:placetype":"locality"
},
  "geometry": {"coordinates":[-9.5509,14.3121],"type":"Point"}
}