{
  "type": "Feature",
  "properties": {
    "gn:admin1_code":"03",
    "gn:asciiname":"Gouriga",
    "gn:country_code":"ML",
    "gn:dem":258,
    "gn:feature_class":"P",
    "gn:feature_code":"PPL",
    "gn:name":"Gouriga",
    "gn:population":0,
    "gn:timezone":"Africa/Bamako",
    "iso:country":"ML",
    "wof:name":"Gouriga",
    "wof:placetype":"locality"
},
  "geometry": {"coordinates":[-9.6037,14.1966],"type":"Point"}
}