{
  "type": "Feature",
  "properties": {
    "gn:admin1_code":"07",
    "gn:asciiname":"Koronga",
    "gn:country_code":"ML",
    "gn:dem":255,
    "gn:feature_class":"P",
    "gn:feature_code":"PPL",
    "gn:name":"Koronga",
    "gn:population":0,
    "gn:timezone":"Africa/Bamako",
    "iso:country":"ML",
    "name:fin_x_preferred":[
        "Koronga"
    ],
    "name:fra_x_preferred":[
        "Koronga"
    ],
    "name:ita_x_preferred":[
        "Koronga"
    ],
    "name:nld_x_preferred":[
        "Koronga"
    ],
    "name:spa_x_preferred":[
        "Koronga"
    ],
    "name:und_x_variant":[
        "Karounga",
        "Koronga"
    ],
    "wof:name":"Koronga",
    "wof:placetype":"locality"
},
  "geometry": {"coordinates":[-7.60426,15.33189],"type":"Point"}
}