{
  "type": "Feature",
  "properties": {
    "gn:admin1_code":"7.0",
    "gn:asciiname":"Abaladougou Kenieba",
    "gn:country_code":"ML",
    "gn:dem":360,
    "gn:feature_class":"P",
    "gn:feature_code":"PPL",
    "gn:name":"Abaladougou K\u00e9ni\u00e9ba",
    "gn:population":0,
    "gn:timezone":"Africa/Bamako",
    "iso:country":"ML",
    "wof:name":"Abaladougou Kenieba",
    "wof:placetype":"locality"
},
  "geometry": {"coordinates":[-8.62907,12.04329],"type":"Point"}
}