{
  "type": "Feature",
  "properties": {
    "gn:admin1_code":"07",
    "gn:asciiname":"Niamabougou",
    "gn:country_code":"ML",
    "gn:dem":421,
    "gn:feature_class":"P",
    "gn:feature_code":"PPL",
    "gn:name":"Niamabougou",
    "gn:population":0,
    "gn:timezone":"Africa/Bamako",
    "iso:country":"ML",
    "name:fra_x_preferred":[
        "Niamabougou"
    ],
    "wof:name":"Niamabougou",
    "wof:placetype":"locality"
},
  "geometry": {"coordinates":[-8.0662,13.6756],"type":"Point"}
}