{
  "type": "Feature",
  "properties": {
    "gn:admin1_code":"03",
    "gn:asciiname":"Diounfara",
    "gn:country_code":"ML",
    "gn:dem":389,
    "gn:feature_class":"P",
    "gn:feature_code":"PPL",
    "gn:name":"Diounfara",
    "gn:population":0,
    "gn:timezone":"Africa/Bamako",
    "iso:country":"ML",
    "wof:name":"Diounfara",
    "wof:placetype":"locality"
},
  "geometry": {"coordinates":[-11.04558,13.03978],"type":"Point"}
}