{
  "type": "Feature",
  "properties": {
    "gn:admin1_code":"07",
    "gn:asciiname":"Sanambani",
    "gn:country_code":"ML",
    "gn:dem":344,
    "gn:feature_class":"P",
    "gn:feature_code":"PPL",
    "gn:name":"Sanambani",
    "gn:population":0,
    "gn:timezone":"Africa/Bamako",
    "iso:country":"ML",
    "name:und_x_variant":[
        "Sananbani",
        "Sanambani"
    ],
    "wof:name":"Sanambani",
    "wof:placetype":"locality"
},
  "geometry": {"coordinates":[-7.46308,13.40802],"type":"Point"}
}