{
  "type": "Feature",
  "properties": {
    "gn:admin1_code":"7.0",
    "gn:asciiname":"Tchitian",
    "gn:country_code":"ML",
    "gn:dem":387,
    "gn:feature_class":"P",
    "gn:feature_code":"PPL",
    "gn:name":"Tchitian",
    "gn:population":0,
    "gn:timezone":"Africa/Bamako",
    "iso:country":"ML",
    "wof:name":"Tchitian",
    "wof:placetype":"locality"
},
  "geometry": {"coordinates":[-7.85539,13.39839],"type":"Point"}
}