{
  "type": "Feature",
  "properties": {
    "gn:admin1_code":"03",
    "gn:asciiname":"Sansamba",
    "gn:country_code":"ML",
    "gn:dem":103,
    "gn:feature_class":"P",
    "gn:feature_code":"PPL",
    "gn:name":"Sansamba",
    "gn:population":0,
    "gn:timezone":"Africa/Bamako",
    "iso:country":"ML",
    "name:und_x_variant":[
        "Sansanba",
        "Sansamba"
    ],
    "wof:name":"Sansamba",
    "wof:placetype":"locality"
},
  "geometry": {"coordinates":[-11.36235,12.98669],"type":"Point"}
}