{
  "type": "Feature",
  "properties": {
    "gn:admin1_code":"07",
    "gn:asciiname":"Tyekourabougou",
    "gn:country_code":"ML",
    "gn:dem":374,
    "gn:feature_class":"P",
    "gn:feature_code":"PPL",
    "gn:name":"Ty\u00e9kourabougou",
    "gn:population":0,
    "gn:timezone":"Africa/Bamako",
    "iso:country":"ML",
    "wof:name":"Tyekourabougou",
    "wof:placetype":"locality"
},
  "geometry": {"coordinates":[-7.8469,14.0319],"type":"Point"}
}