{
  "type": "Feature",
  "properties": {
    "gn:admin1_code":"07",
    "gn:asciiname":"Touloukoro",
    "gn:country_code":"ML",
    "gn:dem":400,
    "gn:feature_class":"P",
    "gn:feature_code":"PPL",
    "gn:name":"Touloukoro",
    "gn:population":0,
    "gn:timezone":"Africa/Bamako",
    "iso:country":"ML",
    "name:und_x_variant":[
        "Tloucoro",
        "Touloukoro"
    ],
    "wof:name":"Touloukoro",
    "wof:placetype":"locality"
},
  "geometry": {"coordinates":[-7.91456,13.98445],"type":"Point"}
}