{
  "type": "Feature",
  "properties": {
    "gn:admin1_code":"07",
    "gn:asciiname":"Fabougou",
    "gn:country_code":"ML",
    "gn:dem":386,
    "gn:feature_class":"P",
    "gn:feature_code":"PPL",
    "gn:name":"Fabougou",
    "gn:population":0,
    "gn:timezone":"Africa/Bamako",
    "iso:country":"ML",
    "name:fra_x_preferred":[
        "Fabougou"
    ],
    "wof:name":"Fabougou",
    "wof:placetype":"locality"
},
  "geometry": {"coordinates":[-8.2204,13.6535],"type":"Point"}
}