{
  "type": "Feature",
  "properties": {
    "gn:admin1_code":"4.0",
    "gn:asciiname":"Dioni",
    "gn:country_code":"ML",
    "gn:dem":514,
    "gn:feature_class":"P",
    "gn:feature_code":"PPL",
    "gn:name":"Dioni",
    "gn:population":0,
    "gn:timezone":"Africa/Bamako",
    "iso:country":"ML",
    "name:ara_x_preferred":[
        "\u062f\u064a\u0648\u0646\u064a\u0633\u064a\u0648 \u0627\u064a\u0633\u0643\u0627\u0644\u0627\u0646\u062a\u064a"
    ],
    "name:pol_x_preferred":[
        "Dioni"
    ],
    "name:spa_x_preferred":[
        "Dioni Villalba"
    ],
    "name:tgk_x_preferred":[
        "\u0414\u0438\u043e\u043d\u0438"
    ],
    "name:tgl_x_preferred":[
        "Dioni"
    ],
    "wof:name":"Dioni",
    "wof:placetype":"locality"
},
  "geometry": {"coordinates":[-3.08843,14.94227],"type":"Point"}
}