{
  "type": "Feature",
  "properties": {
    "gn:admin1_code":"4.0",
    "gn:asciiname":"Dioni",
    "gn:country_code":"ML",
    "gn:dem":514,
    "gn:feature_class":"P",
    "gn:feature_code":"PPL",
    "gn:name":"Dioni",
    "gn:population":0,
    "gn:timezone":"Africa/Bamako",
    "iso:country":"ML",
    "wof:name":"Dioni",
    "wof:placetype":"locality"
},
  "geometry": {"coordinates":[-3.08843,14.94227],"type":"Point"}
}