{
  "type": "Feature",
  "properties": {
    "gn:admin1_code":"03",
    "gn:asciiname":"Djeli-Mahe",
    "gn:country_code":"ML",
    "gn:dem":145,
    "gn:feature_class":"P",
    "gn:feature_code":"PPL",
    "gn:name":"Dj\u00e9li-Mah\u00e9",
    "gn:population":0,
    "gn:timezone":"Africa/Bamako",
    "iso:country":"ML",
    "name:und_x_variant":[
        "Djel Mael",
        "Djeli Mael",
        "Dj\u00e9li-Mah\u00e9"
    ],
    "wof:name":"Djeli-Mahe",
    "wof:placetype":"locality"
},
  "geometry": {"coordinates":[-10.58666,15.40735],"type":"Point"}
}