{
  "type": "Feature",
  "properties": {
    "gn:admin1_code":"05",
    "gn:asciiname":"Tyenabougou",
    "gn:country_code":"ML",
    "gn:dem":328,
    "gn:feature_class":"P",
    "gn:feature_code":"PPL",
    "gn:name":"Ty\u00e9nabougou",
    "gn:population":0,
    "gn:timezone":"Africa/Bamako",
    "iso:country":"ML",
    "name:fra_x_preferred":[
        "Ty\u00e9nabougou"
    ],
    "name:fra_x_variant":[
        "Tienembougou",
        "Tiembougou"
    ],
    "wof:name":"Tyenabougou",
    "wof:placetype":"locality"
},
  "geometry": {"coordinates":[-6.3141,12.6844],"type":"Point"}
}