{
  "type": "Feature",
  "properties": {
    "gn:admin1_code":"03",
    "gn:asciiname":"Saboussire",
    "gn:country_code":"ML",
    "gn:dem":75,
    "gn:feature_class":"P",
    "gn:feature_code":"PPL",
    "gn:name":"Saboussir\u00e9",
    "gn:population":0,
    "gn:timezone":"Africa/Bamako",
    "iso:country":"ML",
    "wof:name":"Saboussire",
    "wof:placetype":"locality"
},
  "geometry": {"coordinates":[-10.9098,14.7126],"type":"Point"}
}