{
  "type": "Feature",
  "properties": {
    "gn:admin1_code":"03",
    "gn:asciiname":"Galoukone",
    "gn:country_code":"ML",
    "gn:dem":107,
    "gn:feature_class":"P",
    "gn:feature_code":"PPL",
    "gn:name":"Galoukon\u00e9",
    "gn:population":0,
    "gn:timezone":"Africa/Bamako",
    "iso:country":"ML",
    "name:und_x_variant":[
        "Galloukon\u00e9",
        "Galoukon\u00e9"
    ],
    "wof:name":"Galoukone",
    "wof:placetype":"locality"
},
  "geometry": {"coordinates":[-10.6638,13.7458],"type":"Point"}
}