{
  "type": "Feature",
  "properties": {
    "gn:admin1_code":"04",
    "gn:asciiname":"Doungoura",
    "gn:country_code":"ML",
    "gn:dem":265,
    "gn:feature_class":"P",
    "gn:feature_code":"PPL",
    "gn:name":"Doungoura",
    "gn:population":0,
    "gn:timezone":"Africa/Bamako",
    "iso:country":"ML",
    "wof:name":"Doungoura",
    "wof:placetype":"locality"
},
  "geometry": {"coordinates":[-4.7663,15.046],"type":"Point"}
}