{
  "type": "Feature",
  "properties": {
    "gn:admin1_code":"4.0",
    "gn:asciiname":"Tien",
    "gn:country_code":"ML",
    "gn:dem":276,
    "gn:feature_class":"P",
    "gn:feature_code":"PPL",
    "gn:name":"Tien",
    "gn:population":0,
    "gn:timezone":"Africa/Bamako",
    "iso:country":"ML",
    "name:deu_x_preferred":[
        "Tien"
    ],
    "name:fra_x_preferred":[
        "Tien"
    ],
    "name:lim_x_preferred":[
        "Tien"
    ],
    "name:nld_x_preferred":[
        "Tien"
    ],
    "name:rus_x_preferred":[
        "\u0422\u044c\u0435\u043d"
    ],
    "wof:name":"Tien",
    "wof:placetype":"locality"
},
  "geometry": {"coordinates":[-4.4219,13.772],"type":"Point"}
}