{
  "type": "Feature",
  "properties": {
    "gn:admin1_code":"4.0",
    "gn:asciiname":"Tien",
    "gn:country_code":"ML",
    "gn:dem":276,
    "gn:feature_class":"P",
    "gn:feature_code":"PPL",
    "gn:name":"Tien",
    "gn:population":0,
    "gn:timezone":"Africa/Bamako",
    "iso:country":"ML",
    "wof:name":"Tien",
    "wof:placetype":"locality"
},
  "geometry": {"coordinates":[-4.4219,13.772],"type":"Point"}
}