{
  "type": "Feature",
  "properties": {
    "gn:admin1_code":"5.0",
    "gn:asciiname":"Nema",
    "gn:country_code":"ML",
    "gn:dem":299,
    "gn:feature_class":"P",
    "gn:feature_code":"PPL",
    "gn:name":"N\u00e8ma",
    "gn:population":0,
    "gn:timezone":"Africa/Bamako",
    "iso:country":"ML",
    "name:ben_x_preferred":[
        "\u09a8\u09c7\u09ae\u09be"
    ],
    "name:ceb_x_preferred":[
        "Nema"
    ],
    "name:epo_x_preferred":[
        "Nema"
    ],
    "name:fra_x_preferred":[
        "Nema"
    ],
    "name:hin_x_preferred":[
        "\u0928\u0947\u092e\u093e"
    ],
    "name:ita_x_preferred":[
        "Nema"
    ],
    "name:swe_x_preferred":[
        "Nema"
    ],
    "name:tur_x_preferred":[
        "Nema"
    ],
    "wof:name":"Nema",
    "wof:placetype":"locality"
},
  "geometry": {"coordinates":[-6.8085,13.3171],"type":"Point"}
}