{
  "type": "Feature",
  "properties": {
    "gn:admin1_code":"03",
    "gn:asciiname":"Dialaka",
    "gn:country_code":"ML",
    "gn:dem":95,
    "gn:feature_class":"P",
    "gn:feature_code":"PPL",
    "gn:name":"Dialaka",
    "gn:population":0,
    "gn:timezone":"Africa/Bamako",
    "iso:country":"ML",
    "wof:name":"Dialaka",
    "wof:placetype":"locality"
},
  "geometry": {"coordinates":[-10.8113,14.6356],"type":"Point"}
}