{
  "type": "Feature",
  "properties": {
    "gn:admin1_code":"05",
    "gn:asciiname":"Debougou",
    "gn:country_code":"ML",
    "gn:dem":281,
    "gn:feature_class":"P",
    "gn:feature_code":"PPL",
    "gn:name":"D\u00e9bougou",
    "gn:population":0,
    "gn:timezone":"Africa/Bamako",
    "iso:country":"ML",
    "name:und_x_variant":[
        "Nd\u00e9bougou",
        "D\u00e9bougou"
    ],
    "wof:name":"Debougou",
    "wof:placetype":"locality"
},
  "geometry": {"coordinates":[-5.9771,14.3751],"type":"Point"}
}