{
  "type": "Feature",
  "properties": {
    "gn:admin1_code":"3.0",
    "gn:asciiname":"Bendougou",
    "gn:country_code":"ML",
    "gn:dem":311,
    "gn:feature_class":"P",
    "gn:feature_code":"PPL",
    "gn:name":"Bendougou",
    "gn:population":0,
    "gn:timezone":"Africa/Bamako",
    "iso:country":"ML",
    "name:und_x_variant":[
        "Bindougou",
        "Bendougou"
    ],
    "wof:name":"Bendougou",
    "wof:placetype":"locality"
},
  "geometry": {"coordinates":[-9.8552,13.0757],"type":"Point"}
}