{
  "type": "Feature",
  "properties": {
    "gn:admin1_code":"05",
    "gn:asciiname":"Kaminiankoro",
    "gn:country_code":"ML",
    "gn:dem":304,
    "gn:feature_class":"P",
    "gn:feature_code":"PPL",
    "gn:name":"Kaminiankoro",
    "gn:population":0,
    "gn:timezone":"Africa/Bamako",
    "iso:country":"ML",
    "wof:name":"Kaminiankoro",
    "wof:placetype":"locality"
},
  "geometry": {"coordinates":[-4.7002,13.3703],"type":"Point"}
}