{
  "type": "Feature",
  "properties": {
    "gn:admin1_code":"8.0",
    "gn:asciiname":"Bangao",
    "gn:country_code":"ML",
    "gn:dem":266,
    "gn:feature_class":"P",
    "gn:feature_code":"PPL",
    "gn:name":"Bangao",
    "gn:population":0,
    "gn:timezone":"Africa/Bamako",
    "iso:country":"ML",
    "wof:name":"Bangao",
    "wof:placetype":"locality"
},
  "geometry": {"coordinates":[-2.26724,16.78972000000001],"type":"Point"}
}