{
  "type": "Feature",
  "properties": {
    "gn:admin1_code":"03",
    "gn:asciiname":"Toudou Kidinnga",
    "gn:country_code":"ML",
    "gn:dem":294,
    "gn:feature_class":"P",
    "gn:feature_code":"PPL",
    "gn:name":"Toudou Kidinnga",
    "gn:population":0,
    "gn:timezone":"Africa/Bamako",
    "iso:country":"ML",
    "wof:name":"Toudou Kidinnga",
    "wof:placetype":"locality"
},
  "geometry": {"coordinates":[-9.1214,14.9375],"type":"Point"}
}