{
  "type": "Feature",
  "properties": {
    "gn:admin1_code":"03",
    "gn:asciiname":"Sepe",
    "gn:country_code":"ML",
    "gn:dem":224,
    "gn:feature_class":"P",
    "gn:feature_code":"PPL",
    "gn:name":"S\u00e9p\u00e9",
    "gn:population":0,
    "gn:timezone":"Africa/Bamako",
    "iso:country":"ML",
    "name:deu_x_preferred":[
        "Sepe"
    ],
    "name:ita_x_preferred":[
        "Sepe"
    ],
    "name:rus_x_preferred":[
        "\u0421\u0435\u043f\u0435"
    ],
    "name:spa_x_preferred":[
        "Sepe"
    ],
    "wof:name":"Sepe",
    "wof:placetype":"locality"
},
  "geometry": {"coordinates":[-10.519,14.5484],"type":"Point"}
}