{
  "type": "Feature",
  "properties": {
    "gn:admin1_code":"7.0",
    "gn:asciiname":"Kolenda",
    "gn:country_code":"ML",
    "gn:dem":342,
    "gn:feature_class":"P",
    "gn:feature_code":"PPL",
    "gn:name":"Kol\u00e8nda",
    "gn:population":0,
    "gn:timezone":"Africa/Bamako",
    "iso:country":"ML",
    "wof:name":"Kolenda",
    "wof:placetype":"locality"
},
  "geometry": {"coordinates":[-8.42778,12.00583],"type":"Point"}
}