{
  "type": "Feature",
  "properties": {
    "gn:admin1_code":"05",
    "gn:asciiname":"Tomoba",
    "gn:country_code":"ML",
    "gn:dem":288,
    "gn:feature_class":"P",
    "gn:feature_code":"PPL",
    "gn:name":"Tomoba",
    "gn:population":0,
    "gn:timezone":"Africa/Bamako",
    "iso:country":"ML",
    "wof:name":"Tomoba",
    "wof:placetype":"locality"
},
  "geometry": {"coordinates":[-5.99655,13.79317],"type":"Point"}
}