{
  "type": "Feature",
  "properties": {
    "gn:admin1_code":"03",
    "gn:asciiname":"Garangou",
    "gn:country_code":"ML",
    "gn:dem":300,
    "gn:feature_class":"P",
    "gn:feature_code":"PPL",
    "gn:name":"Garangou",
    "gn:population":0,
    "gn:timezone":"Africa/Bamako",
    "iso:country":"ML",
    "wof:name":"Garangou",
    "wof:placetype":"locality"
},
  "geometry": {"coordinates":[-9.4417,14.1571],"type":"Point"}
}