{
  "type": "Feature",
  "properties": {
    "gn:admin1_code":"03",
    "gn:asciiname":"Gueninnkoro",
    "gn:country_code":"ML",
    "gn:dem":424,
    "gn:feature_class":"P",
    "gn:feature_code":"PPL",
    "gn:name":"Gu\u00e8ninnkoro",
    "gn:population":0,
    "gn:timezone":"Africa/Bamako",
    "iso:country":"ML",
    "name:fra_x_preferred":[
        "Gu\u00e8ninnkoro"
    ],
    "name:fra_x_variant":[
        "Gu\u00e8ninkoro"
    ],
    "wof:name":"Gueninnkoro",
    "wof:placetype":"locality"
},
  "geometry": {"coordinates":[-8.831,13.1308],"type":"Point"}
}