{
  "type": "Feature",
  "properties": {
    "gn:admin1_code":"07",
    "gn:asciiname":"Sirakoro",
    "gn:country_code":"ML",
    "gn:dem":292,
    "gn:feature_class":"P",
    "gn:feature_code":"PPL",
    "gn:name":"Sirakoro",
    "gn:population":0,
    "gn:timezone":"Africa/Bamako",
    "iso:country":"ML",
    "wof:name":"Sirakoro",
    "wof:placetype":"locality"
},
  "geometry": {"coordinates":[-7.9297,14.3595],"type":"Point"}
}