{
  "type": "Feature",
  "properties": {
    "gn:admin1_code":"8.0",
    "gn:asciiname":"Tomi",
    "gn:country_code":"ML",
    "gn:dem":266,
    "gn:feature_class":"P",
    "gn:feature_code":"PPL",
    "gn:name":"Tomi",
    "gn:population":0,
    "gn:timezone":"Africa/Bamako",
    "iso:country":"ML",
    "name:ceb_x_preferred":[
        "Tomi"
    ],
    "name:deu_x_preferred":[
        "Tomi"
    ],
    "name:fra_x_preferred":[
        "Tomi"
    ],
    "name:ita_x_preferred":[
        "Tomi"
    ],
    "name:nld_x_preferred":[
        "Tomi"
    ],
    "name:pol_x_preferred":[
        "Tomi"
    ],
    "name:swe_x_preferred":[
        "Tomi"
    ],
    "wof:name":"Tomi",
    "wof:placetype":"locality"
},
  "geometry": {"coordinates":[-3.9552,15.9324],"type":"Point"}
}