{
  "type": "Feature",
  "properties": {
    "gn:admin1_code":"03",
    "gn:asciiname":"Marania",
    "gn:country_code":"ML",
    "gn:dem":62,
    "gn:feature_class":"P",
    "gn:feature_code":"PPL",
    "gn:name":"Marania",
    "gn:population":0,
    "gn:timezone":"Africa/Bamako",
    "iso:country":"ML",
    "wof:name":"Marania",
    "wof:placetype":"locality"
},
  "geometry": {"coordinates":[-11.19247,14.08187],"type":"Point"}
}