{
  "type": "Feature",
  "properties": {
    "gn:admin1_code":"06",
    "gn:asciiname":"Keleni",
    "gn:country_code":"ML",
    "gn:dem":304,
    "gn:feature_class":"P",
    "gn:feature_code":"PPL",
    "gn:name":"K\u00e9l\u00e9ni",
    "gn:population":0,
    "gn:timezone":"Africa/Bamako",
    "iso:country":"ML",
    "wof:name":"Keleni",
    "wof:placetype":"locality"
},
  "geometry": {"coordinates":[-5.78443,12.2211],"type":"Point"}
}