{
  "type": "Feature",
  "properties": {
    "gn:admin1_code":"03",
    "gn:asciiname":"Koranpo",
    "gn:country_code":"ML",
    "gn:dem":218,
    "gn:feature_class":"P",
    "gn:feature_code":"PPL",
    "gn:name":"Koranpo",
    "gn:population":0,
    "gn:timezone":"Africa/Bamako",
    "iso:country":"ML",
    "wof:name":"Koranpo",
    "wof:placetype":"locality"
},
  "geometry": {"coordinates":[-10.22485,15.32624],"type":"Point"}
}