{
  "type": "Feature",
  "properties": {
    "gn:population":2868,
    "iso:country":"ML",
    "name:ceb_x_preferred":[
        "M\u0121arr"
    ],
    "name:ces_x_preferred":[
        "M\u0121arr"
    ],
    "name:eng_x_preferred":[
        "Imjar"
    ],
    "name:eng_x_variant":[
        "M\u0121arr"
    ],
    "name:fra_x_preferred":[
        "M\u0121arr"
    ],
    "name:hun_x_preferred":[
        "M\u0121arr"
    ],
    "name:nld_x_preferred":[
        "M\u0121arr"
    ],
    "name:pol_x_preferred":[
        "M\u0121arr"
    ],
    "name:swe_x_preferred":[
        "M\u0121arr"
    ],
    "name:und_x_colloquial":[
        "L-Imgarr",
        "Mgarr"
    ],
    "name:und_x_variant":[
        "L-Im\u0121arr"
    ],
    "qs:gn_adm0_cc":"MT",
    "qs:gn_fcode":"PPL",
    "qs:gn_local":2562734,
    "qs:gn_nam_loc":"mgarr",
    "qs:gn_namadm1":"11",
    "qs:gn_name":"M\u0121arr",
    "qs:local_max":1,
    "qs:local_sum":1,
    "qs:localhoods":1,
    "qs:name":"M\u0121arr",
    "qs:name_adm0":"Malta",
    "qs:name_adm1":"Gozo",
    "qs:name_adm2":"G\u0127ajnsielem",
    "qs:name_en":"Imjar",
    "qs:name_local":"M\u0121arr",
    "qs:photo_max":1,
    "qs:photo_sum":1,
    "qs:placetype":"Town",
    "qs:quad_count":1,
    "qs:woe_adm0":23424897,
    "qs:woe_adm1":24549803,
    "qs:woe_adm2":24551363,
    "qs:woe_lau":0,
    "qs:woe_local":483433,
    "qs:woe_ver":"7.10.0",
    "wof:lang":[
        "unk"
    ],
    "wof:name":"M\u0121arr",
    "wof:placetype":"neighbourhood",
    "wof:population":2868
},
  "geometry": {"coordinates":[14.295959,36.02467],"type":"Point"}
}