{
  "type": "Feature",
  "properties": {
    "gn:admin1_code":"6.0",
    "gn:asciiname":"Niangasso",
    "gn:country_code":"ML",
    "gn:dem":375,
    "gn:feature_class":"P",
    "gn:feature_code":"PPL",
    "gn:name":"Niangasso",
    "gn:population":0,
    "gn:timezone":"Africa/Bamako",
    "iso:country":"ML",
    "wof:name":"Niangasso",
    "wof:placetype":"locality"
},
  "geometry": {"coordinates":[-5.78559,11.29048],"type":"Point"}
}