{
  "type": "Feature",
  "properties": {
    "gn:admin1_code":"06",
    "gn:admin2_code":"7670554.0",
    "gn:asciiname":"Ntossoni",
    "gn:country_code":"ML",
    "gn:dem":325,
    "gn:feature_class":"P",
    "gn:feature_code":"PPL",
    "gn:name":"Ntossoni",
    "gn:population":8700,
    "gn:timezone":"Africa/Bamako",
    "iso:country":"ML",
    "name:fin_x_preferred":[
        "N\u2019Tossoni"
    ],
    "name:fra_x_preferred":[
        "N'Tossoni"
    ],
    "name:ita_x_preferred":[
        "N'Tossoni"
    ],
    "name:nld_x_preferred":[
        "N'Tossoni"
    ],
    "name:por_x_preferred":[
        "Tossoni"
    ],
    "name:spa_x_preferred":[
        "N'Tossoni"
    ],
    "name:und_x_variant":[
        "Ntosoni",
        "Ntossoni"
    ],
    "name:zho_x_preferred":[
        "\u6069\u6258\u7d22\u5c3c"
    ],
    "wof:name":"Ntossoni",
    "wof:placetype":"locality",
    "wof:population":8700
},
  "geometry": {"coordinates":[-5.77003,12.5304],"type":"Point"}
}