{
  "type": "Feature",
  "properties": {
    "gn:admin1_code":"00",
    "gn:asciiname":"Sandougoula",
    "gn:cc2":"ML",
    "gn:country_code":"ML",
    "gn:dem":414,
    "gn:feature_class":"P",
    "gn:feature_code":"PPL",
    "gn:name":"Sandougoula",
    "gn:population":0,
    "gn:timezone":"Africa/Bamako",
    "iso:country":"ML",
    "name:und_x_variant":[
        "Sanangoula",
        "Sandougoula"
    ],
    "wof:name":"Sandougoula",
    "wof:placetype":"locality"
},
  "geometry": {"coordinates":[-7.85,10.25],"type":"Point"}
}