{
  "type": "Feature",
  "properties": {
    "gn:admin1_code":"03",
    "gn:asciiname":"Boulou Abaidate",
    "gn:country_code":"ML",
    "gn:dem":243,
    "gn:feature_class":"P",
    "gn:feature_code":"PPL",
    "gn:name":"Boulou Aba\u00efdate",
    "gn:population":0,
    "gn:timezone":"Africa/Bamako",
    "iso:country":"ML",
    "name:und_x_variant":[
        "Boulou",
        "Boulou Aba\u00efdate"
    ],
    "wof:name":"Boulou Abaidate",
    "wof:placetype":"locality"
},
  "geometry": {"coordinates":[-9.46255,15.20805],"type":"Point"}
}