{
  "type": "Feature",
  "properties": {
    "gn:admin1_code":"4.0",
    "gn:asciiname":"Dounoupa",
    "gn:country_code":"ML",
    "gn:dem":260,
    "gn:feature_class":"P",
    "gn:feature_code":"PPL",
    "gn:name":"Dounoupa",
    "gn:population":0,
    "gn:timezone":"Africa/Bamako",
    "iso:country":"ML",
    "wof:name":"Dounoupa",
    "wof:placetype":"locality"
},
  "geometry": {"coordinates":[-3.2243,13.8707],"type":"Point"}
}