{
  "type": "Feature",
  "properties": {
    "gn:admin1_code":"4.0",
    "gn:asciiname":"Diamangolo",
    "gn:country_code":"ML",
    "gn:dem":351,
    "gn:feature_class":"P",
    "gn:feature_code":"PPL",
    "gn:name":"Diamangolo",
    "gn:population":0,
    "gn:timezone":"Africa/Bamako",
    "iso:country":"ML",
    "wof:name":"Diamangolo",
    "wof:placetype":"locality"
},
  "geometry": {"coordinates":[-3.7091,14.6257],"type":"Point"}
}