{
  "type": "Feature",
  "properties": {
    "gn:admin1_code":"03",
    "gn:asciiname":"Dioka",
    "gn:country_code":"ML",
    "gn:dem":222,
    "gn:feature_class":"P",
    "gn:feature_code":"PPL",
    "gn:name":"Dioka",
    "gn:population":0,
    "gn:timezone":"Africa/Bamako",
    "iso:country":"ML",
    "wof:name":"Dioka",
    "wof:placetype":"locality"
},
  "geometry": {"coordinates":[-10.0964,14.8637],"type":"Point"}
}