{
  "type": "Feature",
  "properties": {
    "gn:admin1_code":"03",
    "gn:asciiname":"Ninangouha",
    "gn:country_code":"ML",
    "gn:dem":108,
    "gn:feature_class":"P",
    "gn:feature_code":"PPL",
    "gn:name":"Ninangouha",
    "gn:population":0,
    "gn:timezone":"Africa/Bamako",
    "iso:country":"ML",
    "wof:name":"Ninangouha",
    "wof:placetype":"locality"
},
  "geometry": {"coordinates":[-10.6517,14.8807],"type":"Point"}
}