{
  "type": "Feature",
  "properties": {
    "gn:admin1_code":"07",
    "gn:asciiname":"Lemourouzanzan",
    "gn:country_code":"ML",
    "gn:dem":369,
    "gn:feature_class":"P",
    "gn:feature_code":"PPL",
    "gn:name":"L\u00e9mourouzanzan",
    "gn:population":0,
    "gn:timezone":"Africa/Bamako",
    "iso:country":"ML",
    "name:und_x_variant":[
        "Lemrousanzan",
        "Lemouroufanfan",
        "Lamourousansan",
        "L\u00e9mourouzanzan"
    ],
    "wof:name":"Lemourouzanzan",
    "wof:placetype":"locality"
},
  "geometry": {"coordinates":[-8.50777,12.82229],"type":"Point"}
}