{
  "type": "Feature",
  "properties": {
    "gn:admin1_code":"8.0",
    "gn:asciiname":"Adyengo",
    "gn:country_code":"ML",
    "gn:dem":268,
    "gn:feature_class":"P",
    "gn:feature_code":"PPL",
    "gn:name":"Ady\u00e8ngo",
    "gn:population":0,
    "gn:timezone":"Africa/Bamako",
    "iso:country":"ML",
    "wof:name":"Adyengo",
    "wof:placetype":"locality"
},
  "geometry": {"coordinates":[-3.71657,16.10057999999999],"type":"Point"}
}