{
  "type": "Feature",
  "properties": {
    "gn:admin1_code":"6.0",
    "gn:asciiname":"Benian",
    "gn:country_code":"ML",
    "gn:dem":341,
    "gn:feature_class":"P",
    "gn:feature_code":"PPL",
    "gn:name":"B\u00e8nian",
    "gn:population":0,
    "gn:timezone":"Africa/Bamako",
    "iso:country":"ML",
    "name:und_x_variant":[
        "Binian",
        "B\u00e9nyan",
        "B\u00e8nian"
    ],
    "wof:name":"Benian",
    "wof:placetype":"locality"
},
  "geometry": {"coordinates":[-7.17176,12.12818],"type":"Point"}
}