{
  "type": "Feature",
  "properties": {
    "gn:admin1_code":"04",
    "gn:asciiname":"Nemende",
    "gn:country_code":"ML",
    "gn:dem":265,
    "gn:feature_class":"P",
    "gn:feature_code":"PPL",
    "gn:name":"N\u00e9mend\u00e9",
    "gn:population":0,
    "gn:timezone":"Africa/Bamako",
    "iso:country":"ML",
    "name:und_x_variant":[
        "N\u00e9mind\u00e9",
        "N\u00e9mend\u00e9"
    ],
    "wof:name":"Nemende",
    "wof:placetype":"locality"
},
  "geometry": {"coordinates":[-4.17418,14.66286],"type":"Point"}
}