{
  "type": "Feature",
  "properties": {
    "gn:admin1_code":"05",
    "gn:asciiname":"Tiessogo",
    "gn:country_code":"ML",
    "gn:dem":273,
    "gn:feature_class":"P",
    "gn:feature_code":"PPL",
    "gn:name":"Tiessogo",
    "gn:population":0,
    "gn:timezone":"Africa/Bamako",
    "iso:country":"ML",
    "wof:name":"Tiessogo",
    "wof:placetype":"locality"
},
  "geometry": {"coordinates":[-5.00981,13.63312],"type":"Point"}
}