{
  "type": "Feature",
  "properties": {
    "gn:admin1_code":"07",
    "gn:asciiname":"Tanganaga Tougoune",
    "gn:country_code":"ML",
    "gn:dem":268,
    "gn:feature_class":"P",
    "gn:feature_code":"PPL",
    "gn:name":"Tanganaga Tougoun\u00e9",
    "gn:population":0,
    "gn:timezone":"Africa/Bamako",
    "iso:country":"ML",
    "wof:name":"Tanganaga Tougoune",
    "wof:placetype":"locality"
},
  "geometry": {"coordinates":[-7.81361,15.13989],"type":"Point"}
}