{
  "type": "Feature",
  "properties": {
    "gn:admin1_code":"03",
    "gn:asciiname":"Kenienndi",
    "gn:country_code":"ML",
    "gn:dem":307,
    "gn:feature_class":"P",
    "gn:feature_code":"PPL",
    "gn:name":"K\u00e9nienndi",
    "gn:population":0,
    "gn:timezone":"Africa/Bamako",
    "iso:country":"ML",
    "wof:name":"Kenienndi",
    "wof:placetype":"locality"
},
  "geometry": {"coordinates":[-11.18148,13.36412],"type":"Point"}
}