{
  "type": "Feature",
  "properties": {
    "gn:admin1_code":"3.0",
    "gn:asciiname":"Segoubougouni",
    "gn:country_code":"ML",
    "gn:dem":482,
    "gn:feature_class":"P",
    "gn:feature_code":"PPL",
    "gn:name":"S\u00e9goubougouni",
    "gn:population":0,
    "gn:timezone":"Africa/Bamako",
    "iso:country":"ML",
    "wof:name":"Segoubougouni",
    "wof:placetype":"locality"
},
  "geometry": {"coordinates":[-8.86333,12.99041],"type":"Point"}
}