{
  "type": "Feature",
  "properties": {
    "gn:admin1_code":"3.0",
    "gn:asciiname":"Aite",
    "gn:country_code":"ML",
    "gn:dem":64,
    "gn:feature_class":"P",
    "gn:feature_code":"PPL",
    "gn:name":"A\u00eft\u00e9",
    "gn:population":0,
    "gn:timezone":"Africa/Bamako",
    "iso:country":"ML",
    "name:und_x_variant":[
        "A\u00eft\u00e9"
    ],
    "wof:name":"Aite",
    "wof:placetype":"locality"
},
  "geometry": {"coordinates":[-11.65122,15.08939],"type":"Point"}
}