{
  "type": "Feature",
  "properties": {
    "gn:admin1_code":"07",
    "gn:asciiname":"Zambougou",
    "gn:country_code":"ML",
    "gn:dem":308,
    "gn:feature_class":"P",
    "gn:feature_code":"PPL",
    "gn:name":"Zambougou",
    "gn:population":0,
    "gn:timezone":"Africa/Bamako",
    "iso:country":"ML",
    "wof:name":"Zambougou",
    "wof:placetype":"locality"
},
  "geometry": {"coordinates":[-8.46,14.2382],"type":"Point"}
}