{
  "type": "Feature",
  "properties": {
    "gn:admin1_code":"8.0",
    "gn:asciiname":"Goudiouguil",
    "gn:country_code":"ML",
    "gn:dem":264,
    "gn:feature_class":"P",
    "gn:feature_code":"PPL",
    "gn:name":"Goud\u00efouguil",
    "gn:population":0,
    "gn:timezone":"Africa/Bamako",
    "iso:country":"ML",
    "wof:name":"Goudiouguil",
    "wof:placetype":"locality"
},
  "geometry": {"coordinates":[-3.6809,15.857],"type":"Point"}
}