{
  "type": "Feature",
  "properties": {
    "gn:admin1_code":"7.0",
    "gn:asciiname":"Sourounara",
    "gn:country_code":"ML",
    "gn:dem":356,
    "gn:feature_class":"P",
    "gn:feature_code":"PPL",
    "gn:name":"Sourounara",
    "gn:population":0,
    "gn:timezone":"Africa/Bamako",
    "iso:country":"ML",
    "wof:name":"Sourounara",
    "wof:placetype":"locality"
},
  "geometry": {"coordinates":[-7.7535,12.33751],"type":"Point"}
}