{
  "type": "Feature",
  "properties": {
    "gn:admin1_code":"05",
    "gn:asciiname":"Fio",
    "gn:country_code":"ML",
    "gn:dem":295,
    "gn:feature_class":"P",
    "gn:feature_code":"PPL",
    "gn:name":"Fio",
    "gn:population":0,
    "gn:timezone":"Africa/Bamako",
    "iso:country":"ML",
    "name:por_x_preferred":[
        "Fio"
    ],
    "wof:name":"Fio",
    "wof:placetype":"locality"
},
  "geometry": {"coordinates":[-4.7194,13.4073],"type":"Point"}
}