{
  "type": "Feature",
  "properties": {
    "gn:admin1_code":"04",
    "gn:asciiname":"Ferendi",
    "gn:country_code":"ML",
    "gn:dem":281,
    "gn:feature_class":"P",
    "gn:feature_code":"PPL",
    "gn:name":"F\u00e9rendi",
    "gn:population":0,
    "gn:timezone":"Africa/Bamako",
    "iso:country":"ML",
    "name:und_x_variant":[
        "F\u00e9ridin",
        "F\u00e9rendi"
    ],
    "wof:name":"Ferendi",
    "wof:placetype":"locality"
},
  "geometry": {"coordinates":[-2.48581,15.24178],"type":"Point"}
}