{
  "type": "Feature",
  "properties": {
    "gn:admin1_code":"00",
    "gn:asciiname":"Yalea",
    "gn:country_code":"ML",
    "gn:dem":438,
    "gn:feature_class":"P",
    "gn:feature_code":"PPL",
    "gn:name":"Yal\u00e9a",
    "gn:population":0,
    "gn:timezone":"Africa/Bamako",
    "iso:country":"ML",
    "wof:name":"Yalea",
    "wof:placetype":"locality"
},
  "geometry": {"coordinates":[-10.71667,12.06667],"type":"Point"}
}