{
  "type": "Feature",
  "properties": {
    "gn:admin1_code":"6.0",
    "gn:asciiname":"Kossemena",
    "gn:country_code":"ML",
    "gn:dem":418,
    "gn:feature_class":"P",
    "gn:feature_code":"PPL",
    "gn:name":"Koss\u00e9m\u00e9na",
    "gn:population":0,
    "gn:timezone":"Africa/Bamako",
    "iso:country":"ML",
    "wof:name":"Kossemena",
    "wof:placetype":"locality"
},
  "geometry": {"coordinates":[-5.5748,11.1994],"type":"Point"}
}