{
  "type": "Feature",
  "properties": {
    "gn:admin1_code":"7.0",
    "gn:asciiname":"Neguebabougou",
    "gn:country_code":"ML",
    "gn:dem":383,
    "gn:feature_class":"P",
    "gn:feature_code":"PPL",
    "gn:name":"N\u00e8gu\u00e8babougou",
    "gn:population":0,
    "gn:timezone":"Africa/Bamako",
    "iso:country":"ML",
    "wof:name":"Neguebabougou",
    "wof:placetype":"locality"
},
  "geometry": {"coordinates":[-7.88285,13.56519],"type":"Point"}
}