{
  "type": "Feature",
  "properties": {
    "gn:admin1_code":"4.0",
    "gn:asciiname":"Abdourahmane",
    "gn:country_code":"ML",
    "gn:dem":266,
    "gn:feature_class":"P",
    "gn:feature_code":"PPL",
    "gn:name":"Abdourahmane",
    "gn:population":0,
    "gn:timezone":"Africa/Bamako",
    "iso:country":"ML",
    "name:und_x_variant":[
        "Abdouramane",
        "Abdourahmane"
    ],
    "wof:name":"Abdourahmane",
    "wof:placetype":"locality"
},
  "geometry": {"coordinates":[-4.22826,14.78589],"type":"Point"}
}