{
  "type": "Feature",
  "properties": {
    "gn:admin1_code":"3.0",
    "gn:asciiname":"Kouroukoto",
    "gn:country_code":"ML",
    "gn:dem":326,
    "gn:feature_class":"P",
    "gn:feature_code":"PPL",
    "gn:name":"Kouroukoto",
    "gn:population":0,
    "gn:timezone":"Africa/Bamako",
    "iso:country":"ML",
    "name:fin_x_preferred":[
        "Kroukoto"
    ],
    "name:fra_x_preferred":[
        "Kouroukoto"
    ],
    "name:ita_x_preferred":[
        "Kroukoto"
    ],
    "name:nld_x_preferred":[
        "Kroukoto"
    ],
    "name:spa_x_preferred":[
        "Kouroukoto"
    ],
    "wof:name":"Kouroukoto",
    "wof:placetype":"locality"
},
  "geometry": {"coordinates":[-9.3037,13.473],"type":"Point"}
}