{
  "type": "Feature",
  "properties": {
    "gn:admin1_code":"3.0",
    "gn:asciiname":"Binteguela",
    "gn:country_code":"ML",
    "gn:dem":98,
    "gn:feature_class":"P",
    "gn:feature_code":"PPL",
    "gn:name":"Bint\u00e9gu\u00e9la",
    "gn:population":0,
    "gn:timezone":"Africa/Bamako",
    "iso:country":"ML",
    "wof:name":"Binteguela",
    "wof:placetype":"locality"
},
  "geometry": {"coordinates":[-11.54935,14.30829],"type":"Point"}
}