{
  "type": "Feature",
  "properties": {
    "gn:admin1_code":"04",
    "gn:asciiname":"Kerano",
    "gn:country_code":"ML",
    "gn:dem":296,
    "gn:feature_class":"P",
    "gn:feature_code":"PPL",
    "gn:name":"K\u00e9rano",
    "gn:population":0,
    "gn:timezone":"Africa/Bamako",
    "iso:country":"ML",
    "name:und_x_variant":[
        "K\u00e9r\u00e9na",
        "K\u00e9rano"
    ],
    "wof:name":"Kerano",
    "wof:placetype":"locality"
},
  "geometry": {"coordinates":[-2.68632,15.03076],"type":"Point"}
}