{
  "type": "Feature",
  "properties": {
    "gn:admin1_code":"3.0",
    "gn:asciiname":"Ambidedi Rive Gauche",
    "gn:country_code":"ML",
    "gn:dem":32,
    "gn:feature_class":"P",
    "gn:feature_code":"PPL",
    "gn:name":"Ambid\u00e9di Rive Gauche",
    "gn:population":0,
    "gn:timezone":"Africa/Bamako",
    "iso:country":"ML",
    "wof:name":"Ambidedi Rive Gauche",
    "wof:placetype":"locality"
},
  "geometry": {"coordinates":[-11.76456,14.58309],"type":"Point"}
}