{
  "type": "Feature",
  "properties": {
    "gn:admin1_code":"04",
    "gn:asciiname":"Tie",
    "gn:country_code":"ML",
    "gn:dem":276,
    "gn:feature_class":"P",
    "gn:feature_code":"PPL",
    "gn:name":"Ti\u00e9",
    "gn:population":0,
    "gn:timezone":"Africa/Bamako",
    "iso:country":"ML",
    "name:und_x_variant":[
        "Pi\u00e9",
        "Ti\u00e9"
    ],
    "wof:name":"Tie",
    "wof:placetype":"locality"
},
  "geometry": {"coordinates":[-4.7456,13.7624],"type":"Point"}
}