{
  "type": "Feature",
  "properties": {
    "gn:admin1_code":"08",
    "gn:asciiname":"Orogoungou",
    "gn:country_code":"ML",
    "gn:dem":263,
    "gn:feature_class":"P",
    "gn:feature_code":"PPL",
    "gn:name":"Orogoungou",
    "gn:population":0,
    "gn:timezone":"Africa/Bamako",
    "iso:country":"ML",
    "name:und_x_variant":[
        "Ourogoungou",
        "Orogoungou"
    ],
    "wof:name":"Orogoungou",
    "wof:placetype":"locality"
},
  "geometry": {"coordinates":[-3.32075,16.45301],"type":"Point"}
}