{
  "type": "Feature",
  "properties": {
    "gn:admin1_code":"00",
    "gn:asciiname":"Ndiou",
    "gn:cc2":"ML",
    "gn:country_code":"ML",
    "gn:dem":344,
    "gn:feature_class":"P",
    "gn:feature_code":"PPL",
    "gn:name":"Ndiou",
    "gn:population":0,
    "gn:timezone":"Africa/Bamako",
    "iso:country":"ML",
    "name:und_x_variant":[
        "Jeu",
        "Dj\u00e9ou",
        "Ndiou"
    ],
    "wof:name":"Ndiou",
    "wof:placetype":"locality"
},
  "geometry": {"coordinates":[-6.03333,10.73333],"type":"Point"}
}