{
  "type": "Feature",
  "properties": {
    "gn:admin1_code":"03",
    "gn:asciiname":"Noma",
    "gn:country_code":"ML",
    "gn:dem":222,
    "gn:feature_class":"P",
    "gn:feature_code":"PPL",
    "gn:name":"Noma",
    "gn:population":0,
    "gn:timezone":"Africa/Bamako",
    "iso:country":"ML",
    "wof:name":"Noma",
    "wof:placetype":"locality"
},
  "geometry": {"coordinates":[-9.47777,15.25938],"type":"Point"}
}