{
  "type": "Feature",
  "properties": {
    "gn:admin1_code":"03",
    "gn:asciiname":"Noma",
    "gn:country_code":"ML",
    "gn:dem":222,
    "gn:feature_class":"P",
    "gn:feature_code":"PPL",
    "gn:name":"Noma",
    "gn:population":0,
    "gn:timezone":"Africa/Bamako",
    "iso:country":"ML",
    "name:cat_x_preferred":[
        "Noma"
    ],
    "name:ceb_x_preferred":[
        "Noma"
    ],
    "name:dan_x_preferred":[
        "Noma"
    ],
    "name:deu_x_preferred":[
        "Noma"
    ],
    "name:fin_x_preferred":[
        "Noma"
    ],
    "name:fra_x_preferred":[
        "Noma"
    ],
    "name:heb_x_preferred":[
        "\u05e0\u05d5\u05de\u05d4"
    ],
    "name:ita_x_preferred":[
        "Noma"
    ],
    "name:jpn_x_preferred":[
        "\u30ce\u30fc\u30de"
    ],
    "name:nld_x_preferred":[
        "Noma"
    ],
    "name:nor_x_preferred":[
        "Noma"
    ],
    "name:pol_x_preferred":[
        "Noma"
    ],
    "name:por_x_preferred":[
        "Noma"
    ],
    "name:rus_x_preferred":[
        "\u041d\u043e\u043c\u0430"
    ],
    "name:spa_x_preferred":[
        "Noma"
    ],
    "name:uzb_x_preferred":[
        "Noma"
    ],
    "wof:name":"Noma",
    "wof:placetype":"locality"
},
  "geometry": {"coordinates":[-9.47777,15.25938],"type":"Point"}
}