{
  "type": "Feature",
  "properties": {
    "gn:admin1_code":"03",
    "gn:asciiname":"Farabantourou",
    "gn:country_code":"ML",
    "gn:dem":105,
    "gn:feature_class":"P",
    "gn:feature_code":"PPL",
    "gn:name":"Farabantourou",
    "gn:population":0,
    "gn:timezone":"Africa/Bamako",
    "iso:country":"ML",
    "wof:name":"Farabantourou",
    "wof:placetype":"locality"
},
  "geometry": {"coordinates":[-11.63341,13.45404],"type":"Point"}
}