{
  "type": "Feature",
  "properties": {
    "gn:admin1_code":"06",
    "gn:asciiname":"Kemissala",
    "gn:country_code":"ML",
    "gn:dem":374,
    "gn:feature_class":"P",
    "gn:feature_code":"PPL",
    "gn:name":"K\u00e9missala",
    "gn:population":0,
    "gn:timezone":"Africa/Bamako",
    "iso:country":"ML",
    "wof:name":"Kemissala",
    "wof:placetype":"locality"
},
  "geometry": {"coordinates":[-7.82326,11.21827],"type":"Point"}
}