{
  "type": "Feature",
  "properties": {
    "gn:admin1_code":"6.0",
    "gn:asciiname":"Neguela",
    "gn:country_code":"ML",
    "gn:dem":347,
    "gn:feature_class":"P",
    "gn:feature_code":"PPL",
    "gn:name":"N\u00e9gu\u00e9la",
    "gn:population":0,
    "gn:timezone":"Africa/Bamako",
    "iso:country":"ML",
    "wof:name":"Neguela",
    "wof:placetype":"locality"
},
  "geometry": {"coordinates":[-7.30034,11.24908],"type":"Point"}
}