{
  "type": "Feature",
  "properties": {
    "gn:admin1_code":"07",
    "gn:asciiname":"Dokenbougou",
    "gn:country_code":"ML",
    "gn:dem":331,
    "gn:feature_class":"P",
    "gn:feature_code":"PPL",
    "gn:name":"Dokenbougou",
    "gn:population":0,
    "gn:timezone":"Africa/Bamako",
    "iso:country":"ML",
    "wof:name":"Dokenbougou",
    "wof:placetype":"locality"
},
  "geometry": {"coordinates":[-8.21997,14.1056],"type":"Point"}
}