{
  "type": "Feature",
  "properties": {
    "gn:admin1_code":"03",
    "gn:asciiname":"Galamakoro",
    "gn:country_code":"ML",
    "gn:dem":247,
    "gn:feature_class":"P",
    "gn:feature_code":"PPL",
    "gn:name":"Galamakoro",
    "gn:population":0,
    "gn:timezone":"Africa/Bamako",
    "iso:country":"ML",
    "wof:name":"Galamakoro",
    "wof:placetype":"locality"
},
  "geometry": {"coordinates":[-9.0457,14.4023],"type":"Point"}
}