{
  "type": "Feature",
  "properties": {
    "gn:admin1_code":"03",
    "gn:asciiname":"Kontala",
    "gn:country_code":"ML",
    "gn:dem":254,
    "gn:feature_class":"P",
    "gn:feature_code":"PPL",
    "gn:name":"Kontala",
    "gn:population":0,
    "gn:timezone":"Africa/Bamako",
    "iso:country":"ML",
    "wof:name":"Kontala",
    "wof:placetype":"locality"
},
  "geometry": {"coordinates":[-10.4212,14.5897],"type":"Point"}
}