{
  "type": "Feature",
  "properties": {
    "gn:admin1_code":"6.0",
    "gn:asciiname":"Zantiebougou",
    "gn:country_code":"ML",
    "gn:dem":341,
    "gn:feature_class":"P",
    "gn:feature_code":"PPL",
    "gn:name":"Zanti\u00e9bougou",
    "gn:population":0,
    "gn:timezone":"Africa/Bamako",
    "iso:country":"ML",
    "name:und_x_variant":[
        "Zanti\u00e9bougou"
    ],
    "wof:name":"Zantiebougou",
    "wof:placetype":"locality"
},
  "geometry": {"coordinates":[-7.34142,11.25107],"type":"Point"}
}