{
  "type": "Feature",
  "properties": {
    "gn:admin1_code":"07",
    "gn:asciiname":"Siele",
    "gn:country_code":"ML",
    "gn:dem":538,
    "gn:feature_class":"P",
    "gn:feature_code":"PPL",
    "gn:name":"Si\u00e9l\u00e9",
    "gn:population":0,
    "gn:timezone":"Africa/Bamako",
    "iso:country":"ML",
    "name:und_x_variant":[
        "Sy\u00e9l\u00e9",
        "Si\u00e9l\u00e9"
    ],
    "wof:name":"Siele",
    "wof:placetype":"locality"
},
  "geometry": {"coordinates":[-8.37997,12.66489],"type":"Point"}
}