{
  "type": "Feature",
  "properties": {
    "gn:admin1_code":"3.0",
    "gn:asciiname":"Bangassi",
    "gn:country_code":"ML",
    "gn:dem":297,
    "gn:feature_class":"P",
    "gn:feature_code":"PPL",
    "gn:name":"Bangassi",
    "gn:population":0,
    "gn:timezone":"Africa/Bamako",
    "iso:country":"ML",
    "name:fin_x_preferred":[
        "Bangassi"
    ],
    "name:fra_x_preferred":[
        "Bangassi"
    ],
    "name:ita_x_preferred":[
        "Bangassi"
    ],
    "name:nld_x_preferred":[
        "Bangassi"
    ],
    "name:spa_x_preferred":[
        "Bangassi"
    ],
    "wof:name":"Bangassi",
    "wof:placetype":"locality"
},
  "geometry": {"coordinates":[-10.2469,14.6886],"type":"Point"}
}