{
  "type": "Feature",
  "properties": {
    "gn:admin1_code":"07",
    "gn:asciiname":"Djibia",
    "gn:country_code":"ML",
    "gn:dem":360,
    "gn:feature_class":"P",
    "gn:feature_code":"PPL",
    "gn:name":"Djibia",
    "gn:population":0,
    "gn:timezone":"Africa/Bamako",
    "iso:country":"ML",
    "wof:name":"Djibia",
    "wof:placetype":"locality"
},
  "geometry": {"coordinates":[-7.69444,12.10629],"type":"Point"}
}