{
  "type": "Feature",
  "properties": {
    "gn:admin1_code":"5.0",
    "gn:asciiname":"Dyolewere",
    "gn:country_code":"ML",
    "gn:dem":319,
    "gn:feature_class":"P",
    "gn:feature_code":"PPL",
    "gn:name":"Dyol\u00e9w\u00e9r\u00e9",
    "gn:population":0,
    "gn:timezone":"Africa/Bamako",
    "iso:country":"ML",
    "wof:name":"Dyolewere",
    "wof:placetype":"locality"
},
  "geometry": {"coordinates":[-6.5625,12.937],"type":"Point"}
}