{
  "type": "Feature",
  "properties": {
    "gn:admin1_code":"03",
    "gn:asciiname":"Missidi",
    "gn:country_code":"ML",
    "gn:dem":230,
    "gn:feature_class":"P",
    "gn:feature_code":"PPL",
    "gn:name":"Missidi",
    "gn:population":0,
    "gn:timezone":"Africa/Bamako",
    "iso:country":"ML",
    "wof:name":"Missidi",
    "wof:placetype":"locality"
},
  "geometry": {"coordinates":[-10.4767,14.3431],"type":"Point"}
}