{
  "type": "Feature",
  "properties": {
    "gn:admin1_code":"00",
    "gn:asciiname":"Djeboute",
    "gn:country_code":"ML",
    "gn:dem":512,
    "gn:feature_class":"P",
    "gn:feature_code":"PPL",
    "gn:name":"Dj\u00e9bout\u00e9",
    "gn:population":0,
    "gn:timezone":"Africa/Bamako",
    "iso:country":"ML",
    "wof:name":"Djeboute",
    "wof:placetype":"locality"
},
  "geometry": {"coordinates":[-10.28333,12.26667],"type":"Point"}
}