{
  "type": "Feature",
  "properties": {
    "gn:admin1_code":"4.0",
    "gn:asciiname":"Dedougou",
    "gn:country_code":"ML",
    "gn:dem":270,
    "gn:feature_class":"P",
    "gn:feature_code":"PPL",
    "gn:name":"D\u00e9dougou",
    "gn:population":0,
    "gn:timezone":"Africa/Bamako",
    "iso:country":"ML",
    "wof:name":"Dedougou",
    "wof:placetype":"locality"
},
  "geometry": {"coordinates":[-4.12982,14.15104],"type":"Point"}
}