{
  "type": "Feature",
  "properties": {
    "gn:admin1_code":"7.0",
    "gn:asciiname":"Kouni",
    "gn:country_code":"ML",
    "gn:dem":332,
    "gn:feature_class":"P",
    "gn:feature_code":"PPL",
    "gn:name":"Kouni",
    "gn:population":0,
    "gn:timezone":"Africa/Bamako",
    "iso:country":"ML",
    "name:ceb_x_preferred":[
        "Kouni"
    ],
    "name:fra_x_preferred":[
        "Kouni"
    ],
    "wof:name":"Kouni",
    "wof:placetype":"locality"
},
  "geometry": {"coordinates":[-7.12143,12.65241],"type":"Point"}
}