{
  "type": "Feature",
  "properties": {
    "gn:admin1_code":"06",
    "gn:asciiname":"Diebe",
    "gn:country_code":"ML",
    "gn:dem":328,
    "gn:feature_class":"P",
    "gn:feature_code":"PPL",
    "gn:name":"Di\u00e9b\u00e9",
    "gn:population":0,
    "gn:timezone":"Africa/Bamako",
    "iso:country":"ML",
    "name:und_x_variant":[
        "Di\u00e9b\u00e9"
    ],
    "wof:name":"Diebe",
    "wof:placetype":"locality"
},
  "geometry": {"coordinates":[-4.97004,12.61993],"type":"Point"}
}