{
  "type": "Feature",
  "properties": {
    "gn:admin1_code":"03",
    "gn:asciiname":"Goumera",
    "gn:country_code":"ML",
    "gn:dem":56,
    "gn:feature_class":"P",
    "gn:feature_code":"PPL",
    "gn:name":"Goum\u00e9ra",
    "gn:population":0,
    "gn:timezone":"Africa/Bamako",
    "iso:country":"ML",
    "name:fin_x_preferred":[
        "Goum\u00e9ra"
    ],
    "name:fra_x_preferred":[
        "Goum\u00e9ra"
    ],
    "name:ita_x_preferred":[
        "Goum\u00e9ra"
    ],
    "name:nld_x_preferred":[
        "Goum\u00e9ra"
    ],
    "name:spa_x_preferred":[
        "Goum\u00e9ra"
    ],
    "wof:name":"Goumera",
    "wof:placetype":"locality"
},
  "geometry": {"coordinates":[-11.29875,14.55751],"type":"Point"}
}