{
  "type": "Feature",
  "properties": {
    "gn:admin1_code":"7.0",
    "gn:asciiname":"Grinkoumbe",
    "gn:country_code":"ML",
    "gn:dem":450,
    "gn:feature_class":"P",
    "gn:feature_code":"PPL",
    "gn:name":"Grinkoumb\u00e9",
    "gn:population":0,
    "gn:timezone":"Africa/Bamako",
    "iso:country":"ML",
    "wof:name":"Grinkoumbe",
    "wof:placetype":"locality"
},
  "geometry": {"coordinates":[-8.09741,12.65245],"type":"Point"}
}