{
  "type": "Feature",
  "properties": {
    "gn:admin1_code":"4.0",
    "gn:asciiname":"Belanguel",
    "gn:country_code":"ML",
    "gn:dem":263,
    "gn:feature_class":"P",
    "gn:feature_code":"PPL",
    "gn:name":"B\u00e9languel",
    "gn:population":0,
    "gn:timezone":"Africa/Bamako",
    "iso:country":"ML",
    "wof:name":"Belanguel",
    "wof:placetype":"locality"
},
  "geometry": {"coordinates":[-4.55133,14.47324],"type":"Point"}
}