{
  "type": "Feature",
  "properties": {
    "gn:admin1_code":"3.0",
    "gn:asciiname":"Banamba",
    "gn:country_code":"ML",
    "gn:dem":329,
    "gn:feature_class":"P",
    "gn:feature_code":"PPL",
    "gn:name":"Banamba",
    "gn:population":0,
    "gn:timezone":"Africa/Bamako",
    "iso:country":"ML",
    "name:ceb_x_preferred":[
        "Banamba"
    ],
    "name:epo_x_preferred":[
        "Banamba"
    ],
    "name:est_x_preferred":[
        "Banamba"
    ],
    "name:fin_x_preferred":[
        "Banamba"
    ],
    "name:fra_x_preferred":[
        "Banamba"
    ],
    "name:hun_x_preferred":[
        "Banamba"
    ],
    "name:ita_x_preferred":[
        "Banamba"
    ],
    "name:nld_x_preferred":[
        "Banamba"
    ],
    "name:pol_x_preferred":[
        "Banamba"
    ],
    "name:rus_x_preferred":[
        "\u0411\u0430\u043d\u0430\u043c\u0431\u0430"
    ],
    "name:spa_x_preferred":[
        "Banamba"
    ],
    "name:swe_x_preferred":[
        "Banamba"
    ],
    "name:zho_x_preferred":[
        "\u5df4\u5357\u5df4"
    ],
    "wof:name":"Banamba",
    "wof:placetype":"locality"
},
  "geometry": {"coordinates":[-9.1224,13.3696],"type":"Point"}
}