{
  "type": "Feature",
  "properties": {
    "gn:admin1_code":"03",
    "gn:asciiname":"Guimini",
    "gn:country_code":"ML",
    "gn:dem":306,
    "gn:feature_class":"P",
    "gn:feature_code":"PPL",
    "gn:name":"Guimini",
    "gn:population":0,
    "gn:timezone":"Africa/Bamako",
    "iso:country":"ML",
    "name:ceb_x_preferred":[
        "Guimini"
    ],
    "name:swe_x_preferred":[
        "Guimini"
    ],
    "wof:name":"Guimini",
    "wof:placetype":"locality"
},
  "geometry": {"coordinates":[-11.22109,13.34335],"type":"Point"}
}