{
  "type": "Feature",
  "properties": {
    "gn:admin1_code":"5.0",
    "gn:asciiname":"Binbene Nobougou",
    "gn:country_code":"ML",
    "gn:dem":277,
    "gn:feature_class":"P",
    "gn:feature_code":"PPL",
    "gn:name":"Binb\u00e9n\u00e9 Nobougou",
    "gn:population":0,
    "gn:timezone":"Africa/Bamako",
    "iso:country":"ML",
    "wof:name":"Binbene Nobougou",
    "wof:placetype":"locality"
},
  "geometry": {"coordinates":[-5.18904,13.69556],"type":"Point"}
}