{
  "type": "Feature",
  "properties": {
    "gn:admin1_code":"4.0",
    "gn:asciiname":"Kougodiegue",
    "gn:country_code":"ML",
    "gn:dem":477,
    "gn:feature_class":"P",
    "gn:feature_code":"PPL",
    "gn:name":"Kougodi\u00e9gu\u00e9",
    "gn:population":0,
    "gn:timezone":"Africa/Bamako",
    "iso:country":"ML",
    "wof:name":"Kougodiegue",
    "wof:placetype":"locality"
},
  "geometry": {"coordinates":[-3.8118,13.9118],"type":"Point"}
}