{
  "type": "Feature",
  "properties": {
    "gn:admin1_code":"05",
    "gn:asciiname":"Dioronkoura",
    "gn:country_code":"ML",
    "gn:dem":286,
    "gn:feature_class":"P",
    "gn:feature_code":"PPL",
    "gn:name":"Dioronkoura",
    "gn:population":0,
    "gn:timezone":"Africa/Bamako",
    "iso:country":"ML",
    "wof:name":"Dioronkoura",
    "wof:placetype":"locality"
},
  "geometry": {"coordinates":[-5.66282,13.91507],"type":"Point"}
}