{
  "type": "Feature",
  "properties": {
    "gn:admin1_code":"06",
    "gn:asciiname":"Ouarana",
    "gn:country_code":"ML",
    "gn:dem":309,
    "gn:feature_class":"P",
    "gn:feature_code":"PPL",
    "gn:name":"Ouarana",
    "gn:population":0,
    "gn:timezone":"Africa/Bamako",
    "iso:country":"ML",
    "name:fra_x_preferred":[
        "Warana"
    ],
    "wof:name":"Ouarana",
    "wof:placetype":"locality"
},
  "geometry": {"coordinates":[-6.43731,11.21784],"type":"Point"}
}