{
  "type": "Feature",
  "properties": {
    "gn:admin1_code":"03",
    "gn:asciiname":"Kouroukotodji",
    "gn:country_code":"ML",
    "gn:dem":150,
    "gn:feature_class":"P",
    "gn:feature_code":"PPL",
    "gn:name":"Kouroukotodji",
    "gn:population":0,
    "gn:timezone":"Africa/Bamako",
    "iso:country":"ML",
    "wof:name":"Kouroukotodji",
    "wof:placetype":"locality"
},
  "geometry": {"coordinates":[-10.1121,13.7713],"type":"Point"}
}