{
  "type": "Feature",
  "properties": {
    "gn:admin1_code":"03",
    "gn:asciiname":"Marena",
    "gn:country_code":"ML",
    "gn:dem":366,
    "gn:feature_class":"P",
    "gn:feature_code":"PPL",
    "gn:name":"Mar\u00e9na",
    "gn:population":0,
    "gn:timezone":"Africa/Bamako",
    "iso:country":"ML",
    "wof:name":"Marena",
    "wof:placetype":"locality"
},
  "geometry": {"coordinates":[-10.2296,14.0047],"type":"Point"}
}