{
  "type": "Feature",
  "properties": {
    "gn:admin1_code":"00",
    "gn:asciiname":"Gueleninkoro",
    "gn:cc2":"ML",
    "gn:country_code":"ML",
    "gn:dem":394,
    "gn:feature_class":"P",
    "gn:feature_code":"PPL",
    "gn:name":"Gu\u00e9l\u00e9ninkoro",
    "gn:population":0,
    "gn:timezone":"Africa/Bamako",
    "iso:country":"ML",
    "name:und_x_variant":[
        "Bol\u00e9nikoro",
        "Gou\u00e9l\u00e9ninkoro",
        "Gu\u00e9l\u00e9ninkoro"
    ],
    "wof:name":"Gueleninkoro",
    "wof:placetype":"locality"
},
  "geometry": {"coordinates":[-8.51667,11.15],"type":"Point"}
}