{
  "type": "Feature",
  "properties": {
    "gn:admin1_code":"05",
    "gn:asciiname":"Siranikoro",
    "gn:country_code":"ML",
    "gn:dem":280,
    "gn:feature_class":"P",
    "gn:feature_code":"PPL",
    "gn:name":"Siranikoro",
    "gn:population":0,
    "gn:timezone":"Africa/Bamako",
    "iso:country":"ML",
    "name:fra_x_preferred":[
        "Siranikoro"
    ],
    "wof:name":"Siranikoro",
    "wof:placetype":"locality"
},
  "geometry": {"coordinates":[-6.2162,14.2769],"type":"Point"}
}