{
  "type": "Feature",
  "properties": {
    "gn:admin1_code":"4.0",
    "gn:asciiname":"Koumbel-Alfa",
    "gn:country_code":"ML",
    "gn:dem":270,
    "gn:feature_class":"P",
    "gn:feature_code":"PPL",
    "gn:name":"Koumbel-Alfa",
    "gn:population":0,
    "gn:timezone":"Africa/Bamako",
    "iso:country":"ML",
    "wof:name":"Koumbel-Alfa",
    "wof:placetype":"locality"
},
  "geometry": {"coordinates":[-4.93532,14.55055],"type":"Point"}
}