{
  "type": "Feature",
  "properties": {
    "gn:admin1_code":"9.0",
    "gn:asciiname":"Guidara",
    "gn:country_code":"ML",
    "gn:dem":248,
    "gn:feature_class":"P",
    "gn:feature_code":"PPL",
    "gn:name":"Guidara",
    "gn:population":0,
    "gn:timezone":"Africa/Bamako",
    "iso:country":"ML",
    "wof:name":"Guidara",
    "wof:placetype":"locality"
},
  "geometry": {"coordinates":[0.3979,15.7672],"type":"Point"}
}