{
  "type": "Feature",
  "properties": {
    "gn:admin1_code":"07",
    "gn:asciiname":"Namarana",
    "gn:country_code":"ML",
    "gn:dem":326,
    "gn:feature_class":"P",
    "gn:feature_code":"PPL",
    "gn:name":"Namarana",
    "gn:population":0,
    "gn:timezone":"Africa/Bamako",
    "iso:country":"ML",
    "wof:name":"Namarana",
    "wof:placetype":"locality"
},
  "geometry": {"coordinates":[-8.90345,12.21882],"type":"Point"}
}