{
  "type": "Feature",
  "properties": {
    "gn:admin1_code":"07",
    "gn:asciiname":"Boula",
    "gn:country_code":"ML",
    "gn:dem":281,
    "gn:feature_class":"P",
    "gn:feature_code":"PPL",
    "gn:name":"Boula",
    "gn:population":0,
    "gn:timezone":"Africa/Bamako",
    "iso:country":"ML",
    "name:und_x_variant":[
        "Boullal",
        "Boulal",
        "Boula"
    ],
    "wof:name":"Boula",
    "wof:placetype":"locality"
},
  "geometry": {"coordinates":[-8.42809,15.07713],"type":"Point"}
}