{
  "type": "Feature",
  "properties": {
    "gn:admin1_code":"7.0",
    "gn:asciiname":"Ngabakoro",
    "gn:country_code":"ML",
    "gn:dem":295,
    "gn:feature_class":"P",
    "gn:feature_code":"PPL",
    "gn:name":"Ngabakoro",
    "gn:population":0,
    "gn:timezone":"Africa/Bamako",
    "iso:country":"ML",
    "wof:name":"Ngabakoro",
    "wof:placetype":"locality"
},
  "geometry": {"coordinates":[-6.90184,13.43166],"type":"Point"}
}