{
  "type": "Feature",
  "properties": {
    "gn:admin1_code":"5.0",
    "gn:asciiname":"Koko",
    "gn:country_code":"ML",
    "gn:dem":341,
    "gn:feature_class":"P",
    "gn:feature_code":"PPL",
    "gn:name":"Koko",
    "gn:population":0,
    "gn:timezone":"Africa/Bamako",
    "iso:country":"ML",
    "wof:name":"Koko",
    "wof:placetype":"locality"
},
  "geometry": {"coordinates":[-6.9722,12.97],"type":"Point"}
}