{
  "type": "Feature",
  "properties": {
    "gn:admin1_code":"09",
    "gn:asciiname":"Koygoro",
    "gn:country_code":"ML",
    "gn:dem":257,
    "gn:feature_class":"P",
    "gn:feature_code":"PPL",
    "gn:name":"Koygoro",
    "gn:population":0,
    "gn:timezone":"Africa/Bamako",
    "iso:country":"ML",
    "wof:name":"Koygoro",
    "wof:placetype":"locality"
},
  "geometry": {"coordinates":[0.06111,16.04111],"type":"Point"}
}