{
  "type": "Feature",
  "properties": {
    "gn:admin1_code":"03",
    "gn:asciiname":"Dakassenou",
    "gn:country_code":"ML",
    "gn:dem":54,
    "gn:feature_class":"P",
    "gn:feature_code":"PPL",
    "gn:name":"Dakass\u00e9nou",
    "gn:population":0,
    "gn:timezone":"Africa/Bamako",
    "iso:country":"ML",
    "name:und_x_variant":[
        "Dakass\u00e9mou",
        "Dakass\u00e9nou"
    ],
    "wof:name":"Dakassenou",
    "wof:placetype":"locality"
},
  "geometry": {"coordinates":[-12.0142,14.28715],"type":"Point"}
}