{
  "type": "Feature",
  "properties": {
    "gn:admin1_code":"4.0",
    "gn:asciiname":"Venndeguele",
    "gn:country_code":"ML",
    "gn:dem":447,
    "gn:feature_class":"P",
    "gn:feature_code":"PPL",
    "gn:name":"Vennd\u00e9gu\u00e9l\u00e9",
    "gn:population":0,
    "gn:timezone":"Africa/Bamako",
    "iso:country":"ML",
    "wof:name":"Venndeguele",
    "wof:placetype":"locality"
},
  "geometry": {"coordinates":[-3.5359,14.3611],"type":"Point"}
}