{
  "type": "Feature",
  "properties": {
    "gn:admin1_code":"05",
    "gn:asciiname":"Siguidoulou",
    "gn:country_code":"ML",
    "gn:dem":341,
    "gn:feature_class":"P",
    "gn:feature_code":"PPL",
    "gn:name":"Siguidoulou",
    "gn:population":0,
    "gn:timezone":"Africa/Bamako",
    "iso:country":"ML",
    "name:fra_x_preferred":[
        "Siguidoulou"
    ],
    "name:fra_x_variant":[
        "Siguidolo",
        "Sigidoulou"
    ],
    "wof:name":"Siguidoulou",
    "wof:placetype":"locality"
},
  "geometry": {"coordinates":[-6.8076,12.8969],"type":"Point"}
}