{
  "type": "Feature",
  "properties": {
    "gn:admin1_code":"4.0",
    "gn:asciiname":"Kala-Segui",
    "gn:country_code":"ML",
    "gn:dem":267,
    "gn:feature_class":"P",
    "gn:feature_code":"PPL",
    "gn:name":"Kala-S\u00e9gui",
    "gn:population":0,
    "gn:timezone":"Africa/Bamako",
    "iso:country":"ML",
    "wof:name":"Kala-Segui",
    "wof:placetype":"locality"
},
  "geometry": {"coordinates":[-4.5815,15.4727],"type":"Point"}
}