{
  "type": "Feature",
  "properties": {
    "gn:admin1_code":"3.0",
    "gn:asciiname":"Bambaran",
    "gn:country_code":"ML",
    "gn:dem":265,
    "gn:feature_class":"P",
    "gn:feature_code":"PPL",
    "gn:name":"Bambaran",
    "gn:population":0,
    "gn:timezone":"Africa/Bamako",
    "iso:country":"ML",
    "name:rus_x_preferred":[
        "\u0411\u0430\u043d\u0430\u043c\u0431\u0430"
    ],
    "name:und_x_variant":[
        "Banbaran",
        "Bambaran"
    ],
    "wof:name":"Bambaran",
    "wof:placetype":"locality"
},
  "geometry": {"coordinates":[-9.10869,13.74872],"type":"Point"}
}