{
  "type": "Feature",
  "properties": {
    "gn:admin1_code":"03",
    "gn:asciiname":"Niaragui",
    "gn:country_code":"ML",
    "gn:dem":141,
    "gn:feature_class":"P",
    "gn:feature_code":"PPL",
    "gn:name":"Niaragui",
    "gn:population":0,
    "gn:timezone":"Africa/Bamako",
    "iso:country":"ML",
    "wof:name":"Niaragui",
    "wof:placetype":"locality"
},
  "geometry": {"coordinates":[-11.48706,13.5643],"type":"Point"}
}