{
  "type": "Feature",
  "properties": {
    "gn:admin1_code":"00",
    "gn:asciiname":"Makana",
    "gn:country_code":"ML",
    "gn:dem":384,
    "gn:feature_class":"P",
    "gn:feature_code":"PPL",
    "gn:name":"Makana",
    "gn:population":0,
    "gn:timezone":"Africa/Bamako",
    "iso:country":"ML",
    "name:ceb_x_preferred":[
        "Makana"
    ],
    "wof:name":"Makana",
    "wof:placetype":"locality"
},
  "geometry": {"coordinates":[-9.35,12.93333],"type":"Point"}
}