{
  "type": "Feature",
  "properties": {
    "gn:admin1_code":"4.0",
    "gn:asciiname":"Bargoumou",
    "gn:country_code":"ML",
    "gn:dem":486,
    "gn:feature_class":"P",
    "gn:feature_code":"PPL",
    "gn:name":"Bargoumou",
    "gn:population":0,
    "gn:timezone":"Africa/Bamako",
    "iso:country":"ML",
    "wof:name":"Bargoumou",
    "wof:placetype":"locality"
},
  "geometry": {"coordinates":[-3.5642,14.2708],"type":"Point"}
}