{
  "type": "Feature",
  "properties": {
    "gn:admin1_code":"07",
    "gn:asciiname":"Seloubale",
    "gn:country_code":"ML",
    "gn:dem":358,
    "gn:feature_class":"P",
    "gn:feature_code":"PPL",
    "gn:name":"S\u00e9loubal\u00e9",
    "gn:population":0,
    "gn:timezone":"Africa/Bamako",
    "iso:country":"ML",
    "wof:name":"Seloubale",
    "wof:placetype":"locality"
},
  "geometry": {"coordinates":[-8.56772,12.05642],"type":"Point"}
}