{
  "type": "Feature",
  "properties": {
    "gn:admin1_code":"09",
    "gn:asciiname":"Gouhi Gouni",
    "gn:country_code":"ML",
    "gn:dem":244,
    "gn:feature_class":"P",
    "gn:feature_code":"PPL",
    "gn:name":"Gouhi Gouni",
    "gn:population":0,
    "gn:timezone":"Africa/Bamako",
    "iso:country":"ML",
    "wof:name":"Gouhi Gouni",
    "wof:placetype":"locality"
},
  "geometry": {"coordinates":[0.5873,15.4963],"type":"Point"}
}