{
  "type": "Feature",
  "properties": {
    "gn:admin1_code":"07",
    "gn:asciiname":"Kolombala",
    "gn:country_code":"ML",
    "gn:dem":316,
    "gn:feature_class":"P",
    "gn:feature_code":"PPL",
    "gn:name":"Kolombala",
    "gn:population":0,
    "gn:timezone":"Africa/Bamako",
    "iso:country":"ML",
    "name:und_x_variant":[
        "Kolomba",
        "Kolonbala",
        "Kolombala"
    ],
    "wof:name":"Kolombala",
    "wof:placetype":"locality"
},
  "geometry": {"coordinates":[-7.08852,13.47737],"type":"Point"}
}