{
  "type": "Feature",
  "properties": {
    "gn:admin1_code":"03",
    "gn:asciiname":"Loulo",
    "gn:country_code":"ML",
    "gn:dem":125,
    "gn:feature_class":"P",
    "gn:feature_code":"PPL",
    "gn:name":"Loulo",
    "gn:population":0,
    "gn:timezone":"Africa/Bamako",
    "iso:country":"ML",
    "wof:name":"Loulo",
    "wof:placetype":"locality"
},
  "geometry": {"coordinates":[-11.37218,13.06715],"type":"Point"}
}