{
  "type": "Feature",
  "properties": {
    "gn:admin1_code":"00",
    "gn:asciiname":"Mbassa",
    "gn:cc2":"ML",
    "gn:country_code":"ML",
    "gn:dem":362,
    "gn:feature_class":"P",
    "gn:feature_code":"PPL",
    "gn:name":"Mbassa",
    "gn:population":0,
    "gn:timezone":"Africa/Bamako",
    "iso:country":"ML",
    "name:und_x_variant":[
        "Mbasa",
        "Mbassa"
    ],
    "wof:name":"Mbassa",
    "wof:placetype":"locality"
},
  "geometry": {"coordinates":[-7.85,12.23333],"type":"Point"}
}