{
  "type": "Feature",
  "properties": {
    "gn:admin1_code":"07",
    "gn:asciiname":"Tafala",
    "gn:country_code":"ML",
    "gn:dem":303,
    "gn:feature_class":"P",
    "gn:feature_code":"PPL",
    "gn:name":"Tafala",
    "gn:population":0,
    "gn:timezone":"Africa/Bamako",
    "iso:country":"ML",
    "name:und_x_variant":[
        "Taffala",
        "Tafala"
    ],
    "wof:name":"Tafala",
    "wof:placetype":"locality"
},
  "geometry": {"coordinates":[-7.35181,13.09766],"type":"Point"}
}