{
  "type": "Feature",
  "properties": {
    "gn:admin1_code":"05",
    "gn:asciiname":"Diesso",
    "gn:country_code":"ML",
    "gn:dem":294,
    "gn:feature_class":"P",
    "gn:feature_code":"PPL",
    "gn:name":"Diesso",
    "gn:population":0,
    "gn:timezone":"Africa/Bamako",
    "iso:country":"ML",
    "name:und_x_variant":[
        "Itiankui",
        "Diesso"
    ],
    "wof:name":"Diesso",
    "wof:placetype":"locality"
},
  "geometry": {"coordinates":[-4.3841,13.5246],"type":"Point"}
}