{
  "type": "Feature",
  "properties": {
    "gn:admin1_code":"07",
    "gn:asciiname":"Bouraba",
    "gn:country_code":"ML",
    "gn:dem":337,
    "gn:feature_class":"P",
    "gn:feature_code":"PPL",
    "gn:name":"Bouraba",
    "gn:population":0,
    "gn:timezone":"Africa/Bamako",
    "iso:country":"ML",
    "wof:name":"Bouraba",
    "wof:placetype":"locality"
},
  "geometry": {"coordinates":[-7.03398,12.06942],"type":"Point"}
}