{
  "type": "Feature",
  "properties": {
    "gn:admin1_code":"07",
    "gn:asciiname":"Koursale Koro",
    "gn:country_code":"ML",
    "gn:dem":335,
    "gn:feature_class":"P",
    "gn:feature_code":"PPL",
    "gn:name":"Koursal\u00e9 Koro",
    "gn:population":0,
    "gn:timezone":"Africa/Bamako",
    "iso:country":"ML",
    "name:und_x_variant":[
        "Kroussalekoura",
        "Koursal\u00e9 Koro"
    ],
    "wof:name":"Koursale Koro",
    "wof:placetype":"locality"
},
  "geometry": {"coordinates":[-8.16747,12.27829],"type":"Point"}
}