{
  "type": "Feature",
  "properties": {
    "gn:admin1_code":"3.0",
    "gn:asciiname":"Ore",
    "gn:country_code":"ML",
    "gn:dem":229,
    "gn:feature_class":"P",
    "gn:feature_code":"PPL",
    "gn:name":"Or\u00e9",
    "gn:population":0,
    "gn:timezone":"Africa/Bamako",
    "iso:country":"ML",
    "wof:name":"Ore",
    "wof:placetype":"locality"
},
  "geometry": {"coordinates":[-10.4379,14.5144],"type":"Point"}
}