{
  "type": "Feature",
  "properties": {
    "gn:admin1_code":"07",
    "gn:asciiname":"Siribila",
    "gn:country_code":"ML",
    "gn:dem":288,
    "gn:feature_class":"P",
    "gn:feature_code":"PPL",
    "gn:name":"Siribila",
    "gn:population":0,
    "gn:timezone":"Africa/Bamako",
    "iso:country":"ML",
    "name:fra_x_preferred":[
        "Siribila"
    ],
    "wof:name":"Siribila",
    "wof:placetype":"locality"
},
  "geometry": {"coordinates":[-6.8656,14.272],"type":"Point"}
}