{
  "type": "Feature",
  "properties": {
    "gn:admin1_code":"4.0",
    "gn:asciiname":"Kourmi",
    "gn:country_code":"ML",
    "gn:dem":320,
    "gn:feature_class":"P",
    "gn:feature_code":"PPL",
    "gn:name":"Kourmi",
    "gn:population":0,
    "gn:timezone":"Africa/Bamako",
    "iso:country":"ML",
    "wof:name":"Kourmi",
    "wof:placetype":"locality"
},
  "geometry": {"coordinates":[-1.83349,15.38103],"type":"Point"}
}