{
  "type": "Feature",
  "properties": {
    "gn:admin1_code":"00",
    "gn:asciiname":"Soubala",
    "gn:country_code":"ML",
    "gn:dem":304,
    "gn:feature_class":"P",
    "gn:feature_code":"PPL",
    "gn:name":"Soubala",
    "gn:population":0,
    "gn:timezone":"Africa/Bamako",
    "iso:country":"ML",
    "wof:name":"Soubala",
    "wof:placetype":"locality"
},
  "geometry": {"coordinates":[-9.93333,12.78333],"type":"Point"}
}