{
  "type": "Feature",
  "properties": {
    "gn:admin1_code":"00",
    "gn:asciiname":"Foulaboula",
    "gn:country_code":"ML",
    "gn:dem":395,
    "gn:feature_class":"P",
    "gn:feature_code":"PPL",
    "gn:name":"Foulaboula",
    "gn:population":0,
    "gn:timezone":"Africa/Bamako",
    "iso:country":"ML",
    "wof:name":"Foulaboula",
    "wof:placetype":"locality"
},
  "geometry": {"coordinates":[-8.11667,10.96667],"type":"Point"}
}