{
  "type": "Feature",
  "properties": {
    "gn:admin1_code":"7.0",
    "gn:asciiname":"Bankouma",
    "gn:country_code":"ML",
    "gn:dem":397,
    "gn:feature_class":"P",
    "gn:feature_code":"PPL",
    "gn:name":"Bankouma",
    "gn:population":0,
    "gn:timezone":"Africa/Bamako",
    "iso:country":"ML",
    "name:fra_x_preferred":[
        "Bankouma"
    ],
    "wof:name":"Bankouma",
    "wof:placetype":"locality"
},
  "geometry": {"coordinates":[-8.25042,13.17687],"type":"Point"}
}