{
  "type": "Feature",
  "properties": {
    "gn:admin1_code":"03",
    "gn:asciiname":"Madiari",
    "gn:country_code":"ML",
    "gn:dem":313,
    "gn:feature_class":"P",
    "gn:feature_code":"PPL",
    "gn:name":"Madiari",
    "gn:population":0,
    "gn:timezone":"Africa/Bamako",
    "iso:country":"ML",
    "name:und_x_variant":[
        "Madiani",
        "Madiari"
    ],
    "wof:name":"Madiari",
    "wof:placetype":"locality"
},
  "geometry": {"coordinates":[-9.51406,13.14672],"type":"Point"}
}