{
  "type": "Feature",
  "properties": {
    "gn:admin1_code":"05",
    "gn:asciiname":"Bossoni",
    "gn:country_code":"ML",
    "gn:dem":284,
    "gn:feature_class":"P",
    "gn:feature_code":"PPL",
    "gn:name":"Bosson\u00ef",
    "gn:population":0,
    "gn:timezone":"Africa/Bamako",
    "iso:country":"ML",
    "wof:name":"Bossoni",
    "wof:placetype":"locality"
},
  "geometry": {"coordinates":[-4.6482,13.3145],"type":"Point"}
}