{
  "type": "Feature",
  "properties": {
    "gn:admin1_code":"04",
    "gn:asciiname":"Kassanga",
    "gn:country_code":"ML",
    "gn:dem":275,
    "gn:feature_class":"P",
    "gn:feature_code":"PPL",
    "gn:name":"Kassanga",
    "gn:population":0,
    "gn:timezone":"Africa/Bamako",
    "iso:country":"ML",
    "name:und_x_variant":[
        "Kasanga",
        "Kassanga"
    ],
    "wof:name":"Kassanga",
    "wof:placetype":"locality"
},
  "geometry": {"coordinates":[-2.12998,14.50761],"type":"Point"}
}