{
  "type": "Feature",
  "properties": {
    "gn:admin1_code":"05",
    "gn:asciiname":"Wouna",
    "gn:country_code":"ML",
    "gn:dem":305,
    "gn:feature_class":"P",
    "gn:feature_code":"PPL",
    "gn:name":"Wouna",
    "gn:population":0,
    "gn:timezone":"Africa/Bamako",
    "iso:country":"ML",
    "wof:name":"Wouna",
    "wof:placetype":"locality"
},
  "geometry": {"coordinates":[-5.97133,12.8124],"type":"Point"}
}