{
  "type": "Feature",
  "properties": {
    "gn:admin1_code":"0.0",
    "gn:asciiname":"Baranian",
    "gn:country_code":"ML",
    "gn:dem":300,
    "gn:feature_class":"P",
    "gn:feature_code":"PPL",
    "gn:name":"Baranian",
    "gn:population":0,
    "gn:timezone":"Africa/Bamako",
    "iso:country":"ML",
    "wof:name":"Baranian",
    "wof:placetype":"locality"
},
  "geometry": {"coordinates":[-9.58333,12.96667],"type":"Point"}
}