{
  "type": "Feature",
  "properties": {
    "gn:admin1_code":"5.0",
    "gn:asciiname":"Barebougou",
    "gn:country_code":"ML",
    "gn:dem":286,
    "gn:feature_class":"P",
    "gn:feature_code":"PPL",
    "gn:name":"Bar\u00e9bougou",
    "gn:population":0,
    "gn:timezone":"Africa/Bamako",
    "iso:country":"ML",
    "name:fra_x_preferred":[
        "Bar\u00e9bougou"
    ],
    "wof:name":"Barebougou",
    "wof:placetype":"locality"
},
  "geometry": {"coordinates":[-6.0771,14.1267],"type":"Point"}
}