{
  "type": "Feature",
  "properties": {
    "gn:admin1_code":"08",
    "gn:asciiname":"Margou",
    "gn:country_code":"ML",
    "gn:dem":264,
    "gn:feature_class":"P",
    "gn:feature_code":"PPL",
    "gn:name":"Margou",
    "gn:population":0,
    "gn:timezone":"Africa/Bamako",
    "iso:country":"ML",
    "name:und_x_variant":[
        "Mangou",
        "Margou"
    ],
    "wof:name":"Margou",
    "wof:placetype":"locality"
},
  "geometry": {"coordinates":[-4.063,15.7434],"type":"Point"}
}