{
  "type": "Feature",
  "properties": {
    "gn:admin1_code":"03",
    "gn:asciiname":"Fidiko",
    "gn:country_code":"ML",
    "gn:dem":608,
    "gn:feature_class":"P",
    "gn:feature_code":"PPL",
    "gn:name":"Fidiko",
    "gn:population":0,
    "gn:timezone":"Africa/Bamako",
    "iso:country":"ML",
    "wof:name":"Fidiko",
    "wof:placetype":"locality"
},
  "geometry": {"coordinates":[-11.40628,12.16937],"type":"Point"}
}