{
  "type": "Feature",
  "properties": {
    "gn:admin1_code":"04",
    "gn:asciiname":"Daka Amadou Dyale",
    "gn:country_code":"ML",
    "gn:dem":269,
    "gn:feature_class":"P",
    "gn:feature_code":"PPL",
    "gn:name":"Daka Amadou Dyal\u00e9",
    "gn:population":0,
    "gn:timezone":"Africa/Bamako",
    "iso:country":"ML",
    "wof:name":"Daka Amadou Dyale",
    "wof:placetype":"locality"
},
  "geometry": {"coordinates":[-2.8488,15.8039],"type":"Point"}
}