{
  "type": "Feature",
  "properties": {
    "gn:admin1_code":"06",
    "gn:asciiname":"Fanterila",
    "gn:country_code":"ML",
    "gn:dem":480,
    "gn:feature_class":"P",
    "gn:feature_code":"PPL",
    "gn:name":"Fant\u00e9rila",
    "gn:population":0,
    "gn:timezone":"Africa/Bamako",
    "iso:country":"ML",
    "name:fra_x_preferred":[
        "Fant\u00e9rila"
    ],
    "name:fra_x_variant":[
        "Fant\u00e9rita"
    ],
    "wof:name":"Fanterila",
    "wof:placetype":"locality"
},
  "geometry": {"coordinates":[-6.04504,11.37023],"type":"Point"}
}