{
  "type": "Feature",
  "properties": {
    "gn:admin1_code":"06",
    "gn:asciiname":"Soron",
    "gn:country_code":"ML",
    "gn:dem":347,
    "gn:feature_class":"P",
    "gn:feature_code":"PPL",
    "gn:name":"Soron",
    "gn:population":0,
    "gn:timezone":"Africa/Bamako",
    "iso:country":"ML",
    "name:bpy_x_preferred":[
        "\u09b8\u09cb\u09b0\u09cb\u09a8"
    ],
    "name:ceb_x_preferred":[
        "Soron"
    ],
    "name:hif_x_preferred":[
        "Soron"
    ],
    "name:hin_x_preferred":[
        "\u0938\u094b\u0930\u094b\u0902"
    ],
    "name:ita_x_preferred":[
        "Soron"
    ],
    "name:mlg_x_preferred":[
        "Soron"
    ],
    "name:msa_x_preferred":[
        "Soron"
    ],
    "name:nld_x_preferred":[
        "Soron"
    ],
    "name:ori_x_preferred":[
        "\u0b38\u0b4b\u0b30\u0b4b\u0b28"
    ],
    "name:pnb_x_preferred":[
        "\u0633\u0648\u0631\u0648\u0646"
    ],
    "name:pol_x_preferred":[
        "Soron"
    ],
    "name:por_x_preferred":[
        "Soron"
    ],
    "name:swe_x_preferred":[
        "Soron"
    ],
    "name:urd_x_preferred":[
        "\u0633\u0648\u0631\u0648\u0646"
    ],
    "name:vie_x_preferred":[
        "Soron"
    ],
    "name:zho_x_preferred":[
        "\u7d22\u9f8d"
    ],
    "wof:name":"Soron",
    "wof:placetype":"locality"
},
  "geometry": {"coordinates":[-7.36299,11.21696],"type":"Point"}
}