{
  "type": "Feature",
  "properties": {
    "gn:admin1_code":"09",
    "gn:asciiname":"Dangaberi",
    "gn:country_code":"ML",
    "gn:dem":249,
    "gn:feature_class":"P",
    "gn:feature_code":"PPL",
    "gn:name":"Dangaberi",
    "gn:population":0,
    "gn:timezone":"Africa/Bamako",
    "iso:country":"ML",
    "name:und_x_variant":[
        "Barab\u00e9ri",
        "Dangaberi"
    ],
    "wof:name":"Dangaberi",
    "wof:placetype":"locality"
},
  "geometry": {"coordinates":[0.2599,15.8206],"type":"Point"}
}