{
  "type": "Feature",
  "properties": {
    "gn:admin1_code":"7.0",
    "gn:asciiname":"Zirado",
    "gn:country_code":"ML",
    "gn:dem":360,
    "gn:feature_class":"P",
    "gn:feature_code":"PPL",
    "gn:name":"Zirado",
    "gn:population":0,
    "gn:timezone":"Africa/Bamako",
    "iso:country":"ML",
    "wof:name":"Zirado",
    "wof:placetype":"locality"
},
  "geometry": {"coordinates":[-7.84106,13.27763],"type":"Point"}
}