{
  "type": "Feature",
  "properties": {
    "gn:admin1_code":"03",
    "gn:asciiname":"Bougouya",
    "gn:country_code":"ML",
    "gn:dem":196,
    "gn:feature_class":"P",
    "gn:feature_code":"PPL",
    "gn:name":"Bougouya",
    "gn:population":0,
    "gn:timezone":"Africa/Bamako",
    "iso:country":"ML",
    "wof:name":"Bougouya",
    "wof:placetype":"locality"
},
  "geometry": {"coordinates":[-11.05748,13.60937],"type":"Point"}
}