{
  "type": "Feature",
  "properties": {
    "gn:admin1_code":"7.0",
    "gn:asciiname":"Siraninkeling",
    "gn:country_code":"ML",
    "gn:dem":293,
    "gn:feature_class":"P",
    "gn:feature_code":"PPL",
    "gn:name":"Siranink\u00e9ling",
    "gn:population":0,
    "gn:timezone":"Africa/Bamako",
    "iso:country":"ML",
    "wof:name":"Siraninkeling",
    "wof:placetype":"locality"
},
  "geometry": {"coordinates":[-7.03773,13.2741],"type":"Point"}
}