{
  "type": "Feature",
  "properties": {
    "gn:admin1_code":"09",
    "gn:asciiname":"Cheoui",
    "gn:country_code":"ML",
    "gn:dem":262,
    "gn:feature_class":"P",
    "gn:feature_code":"PPL",
    "gn:name":"Ch\u00e9oui",
    "gn:population":0,
    "gn:timezone":"Africa/Bamako",
    "iso:country":"ML",
    "wof:name":"Cheoui",
    "wof:placetype":"locality"
},
  "geometry": {"coordinates":[-0.98212,16.95511],"type":"Point"}
}