{
  "type": "Feature",
  "properties": {
    "gn:admin1_code":"03",
    "gn:asciiname":"Samina",
    "gn:country_code":"ML",
    "gn:dem":203,
    "gn:feature_class":"P",
    "gn:feature_code":"PPL",
    "gn:name":"Samina",
    "gn:population":0,
    "gn:timezone":"Africa/Bamako",
    "iso:country":"ML",
    "name:arg_x_preferred":[
        "Samina"
    ],
    "name:ceb_x_preferred":[
        "Samina"
    ],
    "name:nds_x_preferred":[
        "Samina"
    ],
    "name:pol_x_preferred":[
        "Samina"
    ],
    "name:swe_x_preferred":[
        "Samina"
    ],
    "name:und_x_variant":[
        "Saomina"
    ],
    "wof:name":"Samina",
    "wof:placetype":"locality"
},
  "geometry": {"coordinates":[-10.1224,14.0666],"type":"Point"}
}