{
  "type": "Feature",
  "properties": {
    "gn:admin1_code":"7.0",
    "gn:asciiname":"Kamamba",
    "gn:country_code":"ML",
    "gn:dem":425,
    "gn:feature_class":"P",
    "gn:feature_code":"PPL",
    "gn:name":"Kamamba",
    "gn:population":0,
    "gn:timezone":"Africa/Bamako",
    "iso:country":"ML",
    "wof:name":"Kamamba",
    "wof:placetype":"locality"
},
  "geometry": {"coordinates":[-8.27393,12.81761],"type":"Point"}
}