{
  "type": "Feature",
  "properties": {
    "gn:admin1_code":"03",
    "gn:asciiname":"Kourou",
    "gn:country_code":"ML",
    "gn:dem":392,
    "gn:feature_class":"P",
    "gn:feature_code":"PPL",
    "gn:name":"Kourou",
    "gn:population":0,
    "gn:timezone":"Africa/Bamako",
    "iso:country":"ML",
    "wof:name":"Kourou",
    "wof:placetype":"locality"
},
  "geometry": {"coordinates":[-11.28505,12.20694],"type":"Point"}
}