{
  "type": "Feature",
  "properties": {
    "gn:admin1_code":"00",
    "gn:asciiname":"Saint-Isidore",
    "gn:country_code":"ML",
    "gn:dem":316,
    "gn:feature_class":"P",
    "gn:feature_code":"PPL",
    "gn:name":"Saint-Isidore",
    "gn:population":0,
    "gn:timezone":"Africa/Bamako",
    "iso:country":"ML",
    "wof:name":"Saint-Isidore",
    "wof:placetype":"locality"
},
  "geometry": {"coordinates":[-9.48333,12.91667],"type":"Point"}
}