{
  "type": "Feature",
  "properties": {
    "gn:admin1_code":"8.0",
    "gn:asciiname":"El Barka",
    "gn:country_code":"ML",
    "gn:dem":265,
    "gn:feature_class":"P",
    "gn:feature_code":"PPL",
    "gn:name":"El Barka",
    "gn:population":0,
    "gn:timezone":"Africa/Bamako",
    "iso:country":"ML",
    "name:por_x_preferred":[
        "El Barka"
    ],
    "wof:name":"El Barka",
    "wof:placetype":"locality"
},
  "geometry": {"coordinates":[-5.4465,15.5538],"type":"Point"}
}