{
  "type": "Feature",
  "properties": {
    "gn:admin1_code":"7.0",
    "gn:asciiname":"Ntyola",
    "gn:country_code":"ML",
    "gn:dem":329,
    "gn:feature_class":"P",
    "gn:feature_code":"PPL",
    "gn:name":"Ntyola",
    "gn:population":0,
    "gn:timezone":"Africa/Bamako",
    "iso:country":"ML",
    "wof:name":"Ntyola",
    "wof:placetype":"locality"
},
  "geometry": {"coordinates":[-6.8756,12.0177],"type":"Point"}
}