{
  "type": "Feature",
  "properties": {
    "gn:admin1_code":"03",
    "gn:asciiname":"Guerbetiou",
    "gn:country_code":"ML",
    "gn:dem":51,
    "gn:feature_class":"P",
    "gn:feature_code":"PPL",
    "gn:name":"Guerb\u00e9tiou",
    "gn:population":0,
    "gn:timezone":"Africa/Bamako",
    "iso:country":"ML",
    "wof:name":"Guerbetiou",
    "wof:placetype":"locality"
},
  "geometry": {"coordinates":[-11.21386,14.13524],"type":"Point"}
}