{
  "type": "Feature",
  "properties": {
    "gn:admin1_code":"4.0",
    "gn:asciiname":"Souma",
    "gn:country_code":"ML",
    "gn:dem":273,
    "gn:feature_class":"P",
    "gn:feature_code":"PPL",
    "gn:name":"Souma",
    "gn:population":0,
    "gn:timezone":"Africa/Bamako",
    "iso:country":"ML",
    "name:ceb_x_preferred":[
        "Souma"
    ],
    "name:fra_x_preferred":[
        "Souma"
    ],
    "name:swe_x_preferred":[
        "Souma"
    ],
    "wof:name":"Souma",
    "wof:placetype":"locality"
},
  "geometry": {"coordinates":[-4.02914,14.6367],"type":"Point"}
}