{
  "type": "Feature",
  "properties": {
    "gn:admin1_code":"04",
    "gn:asciiname":"Sene-Banbara",
    "gn:country_code":"ML",
    "gn:dem":279,
    "gn:feature_class":"P",
    "gn:feature_code":"PPL",
    "gn:name":"S\u00e9n\u00e9-Banbara",
    "gn:population":0,
    "gn:timezone":"Africa/Bamako",
    "iso:country":"ML",
    "name:und_x_variant":[
        "S\u00e9n\u00e9 Bambara",
        "S\u00e9n\u00e9-Banbara"
    ],
    "wof:name":"Sene-Banbara",
    "wof:placetype":"locality"
},
  "geometry": {"coordinates":[-5.1745,14.1947],"type":"Point"}
}