{
  "type": "Feature",
  "properties": {
    "gn:admin1_code":"05",
    "gn:asciiname":"Wema",
    "gn:country_code":"ML",
    "gn:dem":279,
    "gn:feature_class":"P",
    "gn:feature_code":"PPL",
    "gn:name":"W\u00e8ma",
    "gn:population":0,
    "gn:timezone":"Africa/Bamako",
    "iso:country":"ML",
    "name:und_x_variant":[
        "Ou\u00efama",
        "W\u00e8ma"
    ],
    "wof:name":"Wema",
    "wof:placetype":"locality"
},
  "geometry": {"coordinates":[-4.8926,13.4005],"type":"Point"}
}