{
  "type": "Feature",
  "properties": {
    "gn:admin1_code":"3.0",
    "gn:asciiname":"Laglala",
    "gn:country_code":"ML",
    "gn:dem":211,
    "gn:feature_class":"P",
    "gn:feature_code":"PPL",
    "gn:name":"Laglala",
    "gn:population":0,
    "gn:timezone":"Africa/Bamako",
    "iso:country":"ML",
    "wof:name":"Laglala",
    "wof:placetype":"locality"
},
  "geometry": {"coordinates":[-9.84817,15.41471],"type":"Point"}
}