{
  "type": "Feature",
  "properties": {
    "gn:admin1_code":"05",
    "gn:asciiname":"Tassilima",
    "gn:country_code":"ML",
    "gn:dem":311,
    "gn:feature_class":"P",
    "gn:feature_code":"PPL",
    "gn:name":"Tassilima",
    "gn:population":0,
    "gn:timezone":"Africa/Bamako",
    "iso:country":"ML",
    "wof:name":"Tassilima",
    "wof:placetype":"locality"
},
  "geometry": {"coordinates":[-4.0877,13.6189],"type":"Point"}
}