{
  "type": "Feature",
  "properties": {
    "gn:admin1_code":"04",
    "gn:asciiname":"Mandio",
    "gn:country_code":"ML",
    "gn:dem":276,
    "gn:feature_class":"P",
    "gn:feature_code":"PPL",
    "gn:name":"Mandio",
    "gn:population":0,
    "gn:timezone":"Africa/Bamako",
    "iso:country":"ML",
    "wof:name":"Mandio",
    "wof:placetype":"locality"
},
  "geometry": {"coordinates":[-4.06879,14.2414],"type":"Point"}
}