{
  "type": "Feature",
  "properties": {
    "gn:admin1_code":"9.0",
    "gn:asciiname":"Badji Haoussa",
    "gn:country_code":"ML",
    "gn:dem":251,
    "gn:feature_class":"P",
    "gn:feature_code":"PPL",
    "gn:name":"Badji Haoussa",
    "gn:population":0,
    "gn:timezone":"Africa/Bamako",
    "iso:country":"ML",
    "wof:name":"Badji Haoussa",
    "wof:placetype":"locality"
},
  "geometry": {"coordinates":[0.5012,15.6829],"type":"Point"}
}