{
  "type": "Feature",
  "properties": {
    "gn:admin1_code":"5.0",
    "gn:asciiname":"Babadika",
    "gn:country_code":"ML",
    "gn:dem":278,
    "gn:feature_class":"P",
    "gn:feature_code":"PPL",
    "gn:name":"Babadika",
    "gn:population":0,
    "gn:timezone":"Africa/Bamako",
    "iso:country":"ML",
    "wof:name":"Babadika",
    "wof:placetype":"locality"
},
  "geometry": {"coordinates":[-5.315,13.51259],"type":"Point"}
}