{
  "type": "Feature",
  "properties": {
    "gn:admin1_code":"00",
    "gn:asciiname":"Dougueba",
    "gn:cc2":"ML",
    "gn:country_code":"ML",
    "gn:dem":282,
    "gn:feature_class":"P",
    "gn:feature_code":"PPL",
    "gn:name":"Dougu\u00e9ba",
    "gn:population":0,
    "gn:timezone":"Africa/Bamako",
    "iso:country":"ML",
    "name:und_x_variant":[
        "Donguiba",
        "Dougu\u00e9ba"
    ],
    "wof:name":"Dougueba",
    "wof:placetype":"locality"
},
  "geometry": {"coordinates":[-6.13333,13.81667],"type":"Point"}
}