{
  "type": "Feature",
  "properties": {
    "gn:admin1_code":"3.0",
    "gn:asciiname":"Bakoye",
    "gn:country_code":"ML",
    "gn:dem":105,
    "gn:feature_class":"P",
    "gn:feature_code":"PPL",
    "gn:name":"Bakoye",
    "gn:population":0,
    "gn:timezone":"Africa/Bamako",
    "iso:country":"ML",
    "wof:name":"Bakoye",
    "wof:placetype":"locality"
},
  "geometry": {"coordinates":[-10.8099,13.8117],"type":"Point"}
}