{
  "type": "Feature",
  "properties": {
    "gn:admin1_code":"03",
    "gn:asciiname":"Sanbakanou",
    "gn:country_code":"ML",
    "gn:dem":87,
    "gn:feature_class":"P",
    "gn:feature_code":"PPL",
    "gn:name":"Sanbakanou",
    "gn:population":0,
    "gn:timezone":"Africa/Bamako",
    "iso:country":"ML",
    "name:und_x_variant":[
        "Sambakar\u00e9",
        "Sambakan\u00e9",
        "Sambakanou",
        "Sanbakanou"
    ],
    "wof:name":"Sanbakanou",
    "wof:placetype":"locality"
},
  "geometry": {"coordinates":[-10.70112,15.1214],"type":"Point"}
}