{
  "type": "Feature",
  "properties": {
    "gn:admin1_code":"08",
    "gn:asciiname":"Guindegata-Nari",
    "gn:country_code":"ML",
    "gn:dem":269,
    "gn:feature_class":"P",
    "gn:feature_code":"PPL",
    "gn:name":"Guind\u00e9gata-Nari",
    "gn:population":0,
    "gn:timezone":"Africa/Bamako",
    "iso:country":"ML",
    "name:und_x_variant":[
        "Guindegatamar",
        "Guind\u00e9gata-Nari"
    ],
    "wof:name":"Guindegata-Nari",
    "wof:placetype":"locality"
},
  "geometry": {"coordinates":[-3.68887,16.09981],"type":"Point"}
}