{
  "type": "Feature",
  "properties": {
    "gn:admin1_code":"00",
    "gn:asciiname":"Sekoto",
    "gn:country_code":"ML",
    "gn:dem":380,
    "gn:feature_class":"P",
    "gn:feature_code":"PPL",
    "gn:name":"S\u00e9koto",
    "gn:population":0,
    "gn:timezone":"Africa/Bamako",
    "iso:country":"ML",
    "wof:name":"Sekoto",
    "wof:placetype":"locality"
},
  "geometry": {"coordinates":[-9.75,12.58333],"type":"Point"}
}