{
  "type": "Feature",
  "properties": {
    "gn:admin1_code":"07",
    "gn:asciiname":"Fatoma",
    "gn:country_code":"ML",
    "gn:dem":364,
    "gn:feature_class":"P",
    "gn:feature_code":"PPL",
    "gn:name":"Fatoma",
    "gn:population":0,
    "gn:timezone":"Africa/Bamako",
    "iso:country":"ML",
    "name:fin_x_preferred":[
        "Fatoma"
    ],
    "name:fra_x_preferred":[
        "Fatoma"
    ],
    "name:ita_x_preferred":[
        "Fatoma"
    ],
    "name:nld_x_preferred":[
        "Fatoma"
    ],
    "name:spa_x_preferred":[
        "Fatoma"
    ],
    "name:zho_x_preferred":[
        "\u6cd5\u6258\u99ac"
    ],
    "wof:name":"Fatoma",
    "wof:placetype":"locality"
},
  "geometry": {"coordinates":[-7.4106,14.1253],"type":"Point"}
}