{
  "type": "Feature",
  "properties": {
    "gn:admin1_code":"07",
    "gn:asciiname":"Kida",
    "gn:country_code":"ML",
    "gn:dem":368,
    "gn:feature_class":"P",
    "gn:feature_code":"PPL",
    "gn:name":"Kid\u00e2",
    "gn:population":0,
    "gn:timezone":"Africa/Bamako",
    "iso:country":"ML",
    "name:und_x_variant":[
        "Gou\u00e8na",
        "Gu\u00e9na",
        "Kid\u00e2"
    ],
    "wof:name":"Kida",
    "wof:placetype":"locality"
},
  "geometry": {"coordinates":[-8.37871,12.30973],"type":"Point"}
}