{
  "type": "Feature",
  "properties": {
    "gn:admin1_code":"4.0",
    "gn:asciiname":"Digari",
    "gn:country_code":"ML",
    "gn:dem":320,
    "gn:feature_class":"P",
    "gn:feature_code":"PPL",
    "gn:name":"Digari",
    "gn:population":0,
    "gn:timezone":"Africa/Bamako",
    "iso:country":"ML",
    "wof:name":"Digari",
    "wof:placetype":"locality"
},
  "geometry": {"coordinates":[-3.7805,14.794],"type":"Point"}
}