{
  "type": "Feature",
  "properties": {
    "gn:admin1_code":"07",
    "gn:asciiname":"Sabougou",
    "gn:country_code":"ML",
    "gn:dem":268,
    "gn:feature_class":"P",
    "gn:feature_code":"PPL",
    "gn:name":"Sabougou",
    "gn:population":0,
    "gn:timezone":"Africa/Bamako",
    "iso:country":"ML",
    "name:und_x_variant":[
        "Sobougou",
        "Sabougou"
    ],
    "wof:name":"Sabougou",
    "wof:placetype":"locality"
},
  "geometry": {"coordinates":[-7.549,14.977],"type":"Point"}
}