{
  "type": "Feature",
  "properties": {
    "gn:admin1_code":"04",
    "gn:asciiname":"Kombo-Ogourou",
    "gn:country_code":"ML",
    "gn:dem":273,
    "gn:feature_class":"P",
    "gn:feature_code":"PPL",
    "gn:name":"Kombo-Ogourou",
    "gn:population":0,
    "gn:timezone":"Africa/Bamako",
    "iso:country":"ML",
    "name:und_x_variant":[
        "Kombo-guru",
        "Kombogourou",
        "Kombo-Ogourou"
    ],
    "wof:name":"Kombo-Ogourou",
    "wof:placetype":"locality"
},
  "geometry": {"coordinates":[-3.24519,14.2392],"type":"Point"}
}