{
  "type": "Feature",
  "properties": {
    "gn:admin1_code":"7.0",
    "gn:asciiname":"Kolomana",
    "gn:country_code":"ML",
    "gn:dem":377,
    "gn:feature_class":"P",
    "gn:feature_code":"PPL",
    "gn:name":"Kolomana",
    "gn:population":0,
    "gn:timezone":"Africa/Bamako",
    "iso:country":"ML",
    "wof:name":"Kolomana",
    "wof:placetype":"locality"
},
  "geometry": {"coordinates":[-7.83626,13.19321],"type":"Point"}
}