{
  "type": "Feature",
  "properties": {
    "gn:admin1_code":"04",
    "gn:asciiname":"Sama",
    "gn:country_code":"ML",
    "gn:dem":269,
    "gn:feature_class":"P",
    "gn:feature_code":"PPL",
    "gn:name":"Sama",
    "gn:population":0,
    "gn:timezone":"Africa/Bamako",
    "iso:country":"ML",
    "name:ast_x_preferred":[
        "Sama"
    ],
    "name:ceb_x_preferred":[
        "Sama"
    ],
    "name:deu_x_preferred":[
        "Sama"
    ],
    "name:fin_x_preferred":[
        "Sama"
    ],
    "name:fra_x_preferred":[
        "Sama"
    ],
    "name:ind_x_preferred":[
        "Sama"
    ],
    "name:ita_x_preferred":[
        "Sama"
    ],
    "name:por_x_preferred":[
        "Sama"
    ],
    "name:spa_x_preferred":[
        "Sama"
    ],
    "name:swe_x_preferred":[
        "Sama"
    ],
    "name:und_x_variant":[
        "Sana",
        "Sanabougou",
        "Sama"
    ],
    "name:urd_x_preferred":[
        "\u0633\u0627\u0645\u0627"
    ],
    "wof:name":"Sama",
    "wof:placetype":"locality"
},
  "geometry": {"coordinates":[-3.89677,14.92525],"type":"Point"}
}