{
  "type": "Feature",
  "properties": {
    "gn:admin1_code":"06",
    "gn:asciiname":"Sokara",
    "gn:country_code":"ML",
    "gn:dem":326,
    "gn:feature_class":"P",
    "gn:feature_code":"PPL",
    "gn:name":"Sokara",
    "gn:population":0,
    "gn:timezone":"Africa/Bamako",
    "iso:country":"ML",
    "name:und_x_variant":[
        "Sala",
        "Sokara"
    ],
    "wof:name":"Sokara",
    "wof:placetype":"locality"
},
  "geometry": {"coordinates":[-7.31181,11.57954],"type":"Point"}
}