{
  "type": "Feature",
  "properties": {
    "gn:admin1_code":"03",
    "gn:asciiname":"Guinbane",
    "gn:country_code":"ML",
    "gn:dem":285,
    "gn:feature_class":"P",
    "gn:feature_code":"PPL",
    "gn:name":"Guinban\u00e9",
    "gn:population":0,
    "gn:timezone":"Africa/Bamako",
    "iso:country":"ML",
    "name:und_x_variant":[
        "Guimbana",
        "Guimban\u00e9",
        "Guinban\u00e9"
    ],
    "wof:name":"Guinbane",
    "wof:placetype":"locality"
},
  "geometry": {"coordinates":[-9.50612,15.08714],"type":"Point"}
}