{
  "type": "Feature",
  "properties": {
    "gn:admin1_code":"07",
    "gn:asciiname":"Niare",
    "gn:country_code":"ML",
    "gn:dem":305,
    "gn:feature_class":"P",
    "gn:feature_code":"PPL",
    "gn:name":"Niar\u00e9",
    "gn:population":0,
    "gn:timezone":"Africa/Bamako",
    "iso:country":"ML",
    "wof:name":"Niare",
    "wof:placetype":"locality"
},
  "geometry": {"coordinates":[-7.31545,13.85128],"type":"Point"}
}