{
  "type": "Feature",
  "properties": {
    "gn:admin1_code":"07",
    "gn:asciiname":"Mouse Ouloueli",
    "gn:country_code":"ML",
    "gn:dem":299,
    "gn:feature_class":"P",
    "gn:feature_code":"PPL",
    "gn:name":"Mous\u00e9 Oulou\u00e9li",
    "gn:population":0,
    "gn:timezone":"Africa/Bamako",
    "iso:country":"ML",
    "name:und_x_variant":[
        "Mouss\u00e9 Oulou\u00e9li",
        "Mous\u00e9 Oulou\u00e9li"
    ],
    "wof:name":"Mouse Ouloueli",
    "wof:placetype":"locality"
},
  "geometry": {"coordinates":[-8.3416,15.37284],"type":"Point"}
}