{
  "type": "Feature",
  "properties": {
    "gn:admin1_code":"7.0",
    "gn:asciiname":"Dotyena",
    "gn:country_code":"ML",
    "gn:dem":352,
    "gn:feature_class":"P",
    "gn:feature_code":"PPL",
    "gn:name":"Doty\u00e8na",
    "gn:population":0,
    "gn:timezone":"Africa/Bamako",
    "iso:country":"ML",
    "wof:name":"Dotyena",
    "wof:placetype":"locality"
},
  "geometry": {"coordinates":[-8.02941,12.89685],"type":"Point"}
}