{
  "type": "Feature",
  "properties": {
    "gn:admin1_code":"7.0",
    "gn:asciiname":"Koninkounkourou",
    "gn:country_code":"ML",
    "gn:dem":440,
    "gn:feature_class":"P",
    "gn:feature_code":"PPL",
    "gn:name":"Koninkounkourou",
    "gn:population":0,
    "gn:timezone":"Africa/Bamako",
    "iso:country":"ML",
    "wof:name":"Koninkounkourou",
    "wof:placetype":"locality"
},
  "geometry": {"coordinates":[-8.34847,12.70919],"type":"Point"}
}