{
  "type": "Feature",
  "properties": {
    "gn:admin1_code":"05",
    "gn:asciiname":"Dougoubala",
    "gn:country_code":"ML",
    "gn:dem":277,
    "gn:feature_class":"P",
    "gn:feature_code":"PPL",
    "gn:name":"Dougoubala",
    "gn:population":0,
    "gn:timezone":"Africa/Bamako",
    "iso:country":"ML",
    "wof:name":"Dougoubala",
    "wof:placetype":"locality"
},
  "geometry": {"coordinates":[-5.2063,13.49008],"type":"Point"}
}