{
  "type": "Feature",
  "properties": {
    "gn:admin1_code":"3.0",
    "gn:asciiname":"Tourougoumbou",
    "gn:country_code":"ML",
    "gn:dem":312,
    "gn:feature_class":"P",
    "gn:feature_code":"PPL",
    "gn:name":"Tourougoumbou",
    "gn:population":0,
    "gn:timezone":"Africa/Bamako",
    "iso:country":"ML",
    "wof:name":"Tourougoumbou",
    "wof:placetype":"locality"
},
  "geometry": {"coordinates":[-9.0469,14.9355],"type":"Point"}
}