{
  "type": "Feature",
  "properties": {
    "gn:admin1_code":"3.0",
    "gn:asciiname":"Naniela",
    "gn:country_code":"ML",
    "gn:dem":72,
    "gn:feature_class":"P",
    "gn:feature_code":"PPL",
    "gn:name":"Nani\u00e8la",
    "gn:population":0,
    "gn:timezone":"Africa/Bamako",
    "iso:country":"ML",
    "wof:name":"Naniela",
    "wof:placetype":"locality"
},
  "geometry": {"coordinates":[-10.8723,15.08627],"type":"Point"}
}