{
  "type": "Feature",
  "properties": {
    "gn:admin1_code":"07",
    "gn:asciiname":"Satlela",
    "gn:country_code":"ML",
    "gn:dem":329,
    "gn:feature_class":"P",
    "gn:feature_code":"PPL",
    "gn:name":"Satl\u00e9la",
    "gn:population":0,
    "gn:timezone":"Africa/Bamako",
    "iso:country":"ML",
    "wof:name":"Satlela",
    "wof:placetype":"locality"
},
  "geometry": {"coordinates":[-8.2631,14.2368],"type":"Point"}
}