{
  "type": "Feature",
  "properties": {
    "gn:admin1_code":"7.0",
    "gn:asciiname":"Konina",
    "gn:country_code":"ML",
    "gn:dem":329,
    "gn:feature_class":"P",
    "gn:feature_code":"PPL",
    "gn:name":"Konina",
    "gn:population":0,
    "gn:timezone":"Africa/Bamako",
    "iso:country":"ML",
    "name:nld_x_preferred":[
        "Konina"
    ],
    "name:pol_x_preferred":[
        "Konina"
    ],
    "wof:name":"Konina",
    "wof:placetype":"locality"
},
  "geometry": {"coordinates":[-7.00437,12.37384],"type":"Point"}
}