{
  "type": "Feature",
  "properties": {
    "gn:admin1_code":"5.0",
    "gn:asciiname":"Koulenze",
    "gn:country_code":"ML",
    "gn:dem":294,
    "gn:feature_class":"P",
    "gn:feature_code":"PPL",
    "gn:name":"Koulenz\u00e9",
    "gn:population":0,
    "gn:timezone":"Africa/Bamako",
    "iso:country":"ML",
    "wof:name":"Koulenze",
    "wof:placetype":"locality"
},
  "geometry": {"coordinates":[-6.63282,13.35507],"type":"Point"}
}