{
  "type": "Feature",
  "properties": {
    "gn:admin1_code":"4.0",
    "gn:asciiname":"Daga",
    "gn:country_code":"ML",
    "gn:dem":465,
    "gn:feature_class":"P",
    "gn:feature_code":"PPL",
    "gn:name":"Daga",
    "gn:population":0,
    "gn:timezone":"Africa/Bamako",
    "iso:country":"ML",
    "wof:name":"Daga",
    "wof:placetype":"locality"
},
  "geometry": {"coordinates":[-3.5762,14.2429],"type":"Point"}
}