{
  "type": "Feature",
  "properties": {
    "gn:admin1_code":"4.0",
    "gn:asciiname":"Daga",
    "gn:country_code":"ML",
    "gn:dem":465,
    "gn:feature_class":"P",
    "gn:feature_code":"PPL",
    "gn:name":"Daga",
    "gn:population":0,
    "gn:timezone":"Africa/Bamako",
    "iso:country":"ML",
    "name:ara_x_preferred":[
        "\u062f\u0627\u063a\u0627"
    ],
    "name:ceb_x_preferred":[
        "Daga"
    ],
    "name:ell_x_preferred":[
        "\u039d\u03c4\u03ac\u03b3\u03ba\u03b1"
    ],
    "name:fra_x_preferred":[
        "Daga"
    ],
    "name:heb_x_preferred":[
        "\u05d3\u05d2\u05d4"
    ],
    "name:hin_x_preferred":[
        "\u0921\u093e\u0917\u093e"
    ],
    "name:ita_x_preferred":[
        "Daga"
    ],
    "name:swe_x_preferred":[
        "Daga"
    ],
    "name:tgl_x_preferred":[
        "Daga"
    ],
    "name:tur_x_preferred":[
        "Daga"
    ],
    "name:vie_x_preferred":[
        "Daga"
    ],
    "wof:name":"Daga",
    "wof:placetype":"locality"
},
  "geometry": {"coordinates":[-3.5762,14.2429],"type":"Point"}
}