{
  "type": "Feature",
  "properties": {
    "gn:admin1_code":"7.0",
    "gn:asciiname":"Dissan",
    "gn:country_code":"ML",
    "gn:dem":409,
    "gn:feature_class":"P",
    "gn:feature_code":"PPL",
    "gn:name":"Dissan",
    "gn:population":0,
    "gn:timezone":"Africa/Bamako",
    "iso:country":"ML",
    "wof:name":"Dissan",
    "wof:placetype":"locality"
},
  "geometry": {"coordinates":[-7.55734,13.52733],"type":"Point"}
}