{
  "type": "Feature",
  "properties": {
    "gn:admin1_code":"06",
    "gn:asciiname":"Dogo",
    "gn:country_code":"ML",
    "gn:dem":372,
    "gn:feature_class":"P",
    "gn:feature_code":"PPL",
    "gn:name":"Dogo",
    "gn:population":0,
    "gn:timezone":"Africa/Bamako",
    "iso:country":"ML",
    "name:fin_x_preferred":[
        "Dogo"
    ],
    "name:fra_x_preferred":[
        "Dogo"
    ],
    "name:ita_x_preferred":[
        "Dogo"
    ],
    "name:nld_x_preferred":[
        "Dogo"
    ],
    "name:spa_x_preferred":[
        "Dogo"
    ],
    "wof:name":"Dogo",
    "wof:placetype":"locality"
},
  "geometry": {"coordinates":[-7.32968,11.89036],"type":"Point"}
}