{
  "type": "Feature",
  "properties": {
    "gn:admin1_code":"3.0",
    "gn:asciiname":"Dienguere",
    "gn:country_code":"ML",
    "gn:dem":99,
    "gn:feature_class":"P",
    "gn:feature_code":"PPL",
    "gn:name":"Diengu\u00e9r\u00e9",
    "gn:population":0,
    "gn:timezone":"Africa/Bamako",
    "iso:country":"ML",
    "wof:name":"Dienguere",
    "wof:placetype":"locality"
},
  "geometry": {"coordinates":[-10.4325,15.02283],"type":"Point"}
}