{
  "type": "Feature",
  "properties": {
    "gn:admin1_code":"03",
    "gn:asciiname":"Moussala",
    "gn:country_code":"ML",
    "gn:dem":76,
    "gn:feature_class":"P",
    "gn:feature_code":"PPL",
    "gn:name":"Moussala",
    "gn:population":0,
    "gn:timezone":"Africa/Bamako",
    "iso:country":"ML",
    "wof:name":"Moussala",
    "wof:placetype":"locality"
},
  "geometry": {"coordinates":[-10.9524,14.2911],"type":"Point"}
}