{
  "type": "Feature",
  "properties": {
    "gn:admin1_code":"07",
    "gn:asciiname":"Ngara",
    "gn:country_code":"ML",
    "gn:dem":340,
    "gn:feature_class":"P",
    "gn:feature_code":"PPL",
    "gn:name":"Ngara",
    "gn:population":0,
    "gn:timezone":"Africa/Bamako",
    "iso:country":"ML",
    "name:ceb_x_preferred":[
        "Ngara"
    ],
    "name:fra_x_preferred":[
        "Ngara"
    ],
    "name:fra_x_variant":[
        "Gara"
    ],
    "name:nor_x_preferred":[
        "Ngara"
    ],
    "name:ron_x_preferred":[
        "Ngara"
    ],
    "name:rus_x_preferred":[
        "\u041d\u0433\u0430\u0440\u0430"
    ],
    "name:tur_x_preferred":[
        "Ngara"
    ],
    "wof:name":"Ngara",
    "wof:placetype":"locality"
},
  "geometry": {"coordinates":[-6.8721,12.3743],"type":"Point"}
}