{
  "type": "Feature",
  "properties": {
    "gn:admin1_code":"07",
    "gn:asciiname":"Kerwane",
    "gn:country_code":"ML",
    "gn:dem":300,
    "gn:feature_class":"P",
    "gn:feature_code":"PPL",
    "gn:name":"K\u00e9rwan\u00e9",
    "gn:population":0,
    "gn:timezone":"Africa/Bamako",
    "iso:country":"ML",
    "name:und_x_variant":[
        "K\u00e9rouan\u00e9",
        "K\u00e9rwan\u00e9"
    ],
    "wof:name":"Kerwane",
    "wof:placetype":"locality"
},
  "geometry": {"coordinates":[-8.73417,15.16775],"type":"Point"}
}