{
  "type": "Feature",
  "properties": {
    "gn:admin1_code":"04",
    "gn:asciiname":"Kenta Foulbe",
    "gn:country_code":"ML",
    "gn:dem":269,
    "gn:feature_class":"P",
    "gn:feature_code":"PPL",
    "gn:name":"Kenta Foulb\u00e9",
    "gn:population":0,
    "gn:timezone":"Africa/Bamako",
    "iso:country":"ML",
    "name:und_x_variant":[
        "Kinta-Foulb\u00e9",
        "Kenta Foulb\u00e9"
    ],
    "wof:name":"Kenta Foulbe",
    "wof:placetype":"locality"
},
  "geometry": {"coordinates":[-4.8219,14.62398],"type":"Point"}
}