{
  "type": "Feature",
  "properties": {
    "gn:admin1_code":"05",
    "gn:asciiname":"No Ouere",
    "gn:country_code":"ML",
    "gn:dem":286,
    "gn:feature_class":"P",
    "gn:feature_code":"PPL",
    "gn:name":"No Ou\u00e8r\u00e8",
    "gn:population":0,
    "gn:timezone":"Africa/Bamako",
    "iso:country":"ML",
    "name:und_x_variant":[
        "Now\u00e9r\u00e9",
        "No Ou\u00e8r\u00e8"
    ],
    "wof:name":"No Ouere",
    "wof:placetype":"locality"
},
  "geometry": {"coordinates":[-6.0596,13.5905],"type":"Point"}
}