{
  "type": "Feature",
  "properties": {
    "gn:admin1_code":"7.0",
    "gn:asciiname":"Bandyougoubougou",
    "gn:country_code":"ML",
    "gn:dem":303,
    "gn:feature_class":"P",
    "gn:feature_code":"PPL",
    "gn:name":"Bandyougoubougou",
    "gn:population":0,
    "gn:timezone":"Africa/Bamako",
    "iso:country":"ML",
    "wof:name":"Bandyougoubougou",
    "wof:placetype":"locality"
},
  "geometry": {"coordinates":[-8.71134,15.20725],"type":"Point"}
}