{
  "type": "Feature",
  "properties": {
    "gn:admin1_code":"5.0",
    "gn:asciiname":"Massadougou",
    "gn:country_code":"ML",
    "gn:dem":282,
    "gn:feature_class":"P",
    "gn:feature_code":"PPL",
    "gn:name":"Massadougou",
    "gn:population":0,
    "gn:timezone":"Africa/Bamako",
    "iso:country":"ML",
    "name:fra_x_preferred":[
        "Massadougou"
    ],
    "name:msa_x_preferred":[
        "Massadougou"
    ],
    "wof:name":"Massadougou",
    "wof:placetype":"locality"
},
  "geometry": {"coordinates":[-5.5339,13.98368],"type":"Point"}
}