{
  "type": "Feature",
  "properties": {
    "gn:admin1_code":"00",
    "gn:asciiname":"Dionbougou",
    "gn:country_code":"ML",
    "gn:dem":344,
    "gn:feature_class":"P",
    "gn:feature_code":"PPL",
    "gn:name":"Dionbougou",
    "gn:population":0,
    "gn:timezone":"Africa/Bamako",
    "iso:country":"ML",
    "wof:name":"Dionbougou",
    "wof:placetype":"locality"
},
  "geometry": {"coordinates":[-6.58333,10.65],"type":"Point"}
}