{
  "type": "Feature",
  "properties": {
    "gn:admin1_code":"06",
    "gn:asciiname":"Kalaka",
    "gn:country_code":"ML",
    "gn:dem":329,
    "gn:feature_class":"P",
    "gn:feature_code":"PPL",
    "gn:name":"Kalaka",
    "gn:population":0,
    "gn:timezone":"Africa/Bamako",
    "iso:country":"ML",
    "name:fra_x_preferred":[
        "Kalaka"
    ],
    "wof:name":"Kalaka",
    "wof:placetype":"locality"
},
  "geometry": {"coordinates":[-6.79372,11.16178],"type":"Point"}
}