{
  "type": "Feature",
  "properties": {
    "gn:admin1_code":"6.0",
    "gn:asciiname":"Titiena",
    "gn:country_code":"ML",
    "gn:dem":310,
    "gn:feature_class":"P",
    "gn:feature_code":"PPL",
    "gn:name":"Titi\u00e9na",
    "gn:population":0,
    "gn:timezone":"Africa/Bamako",
    "iso:country":"ML",
    "wof:name":"Titiena",
    "wof:placetype":"locality"
},
  "geometry": {"coordinates":[-6.57222,11.28509],"type":"Point"}
}