{
  "type": "Feature",
  "properties": {
    "gn:admin1_code":"06",
    "gn:asciiname":"Kore",
    "gn:country_code":"ML",
    "gn:dem":306,
    "gn:feature_class":"P",
    "gn:feature_code":"PPL",
    "gn:name":"Kor\u00e9",
    "gn:population":0,
    "gn:timezone":"Africa/Bamako",
    "iso:country":"ML",
    "name:und_x_variant":[
        "Kori",
        "Kor\u00e9"
    ],
    "wof:name":"Kore",
    "wof:placetype":"locality"
},
  "geometry": {"coordinates":[-5.32443,12.6672],"type":"Point"}
}