{
  "type": "Feature",
  "properties": {
    "gn:admin1_code":"03",
    "gn:asciiname":"Sitakourou",
    "gn:country_code":"ML",
    "gn:dem":226,
    "gn:feature_class":"P",
    "gn:feature_code":"PPL",
    "gn:name":"Sitakourou",
    "gn:population":0,
    "gn:timezone":"Africa/Bamako",
    "iso:country":"ML",
    "wof:name":"Sitakourou",
    "wof:placetype":"locality"
},
  "geometry": {"coordinates":[-10.513,14.34803],"type":"Point"}
}