{
  "type": "Feature",
  "properties": {
    "gn:admin1_code":"00",
    "gn:asciiname":"Tenintoumanina",
    "gn:country_code":"ML",
    "gn:dem":381,
    "gn:feature_class":"P",
    "gn:feature_code":"PPL",
    "gn:name":"T\u00e9nintoumanina",
    "gn:population":0,
    "gn:timezone":"Africa/Bamako",
    "iso:country":"ML",
    "wof:name":"Tenintoumanina",
    "wof:placetype":"locality"
},
  "geometry": {"coordinates":[-8.11667,10.66667],"type":"Point"}
}