{
  "type": "Feature",
  "properties": {
    "gn:admin1_code":"5.0",
    "gn:asciiname":"Mele Ouere",
    "gn:country_code":"ML",
    "gn:dem":294,
    "gn:feature_class":"P",
    "gn:feature_code":"PPL",
    "gn:name":"M\u00e8l\u00e8 Ou\u00e8r\u00e8",
    "gn:population":0,
    "gn:timezone":"Africa/Bamako",
    "iso:country":"ML",
    "wof:name":"Mele Ouere",
    "wof:placetype":"locality"
},
  "geometry": {"coordinates":[-6.3507,13.36521],"type":"Point"}
}