{
  "type": "Feature",
  "properties": {
    "gn:admin1_code":"5.0",
    "gn:asciiname":"Foulakoungo",
    "gn:country_code":"ML",
    "gn:dem":370,
    "gn:feature_class":"P",
    "gn:feature_code":"PPL",
    "gn:name":"Foulakoungo",
    "gn:population":0,
    "gn:timezone":"Africa/Bamako",
    "iso:country":"ML",
    "wof:name":"Foulakoungo",
    "wof:placetype":"locality"
},
  "geometry": {"coordinates":[-7.039,12.9746],"type":"Point"}
}