{
  "type": "Feature",
  "properties": {
    "gn:admin1_code":"5.0",
    "gn:asciiname":"Fitekelasso",
    "gn:country_code":"ML",
    "gn:dem":285,
    "gn:feature_class":"P",
    "gn:feature_code":"PPL",
    "gn:name":"Fit\u00e9k\u00e9lasso",
    "gn:population":0,
    "gn:timezone":"Africa/Bamako",
    "iso:country":"ML",
    "wof:name":"Fitekelasso",
    "wof:placetype":"locality"
},
  "geometry": {"coordinates":[-5.2355,12.9757],"type":"Point"}
}