{
  "type": "Feature",
  "properties": {
    "gn:admin1_code":"03",
    "gn:asciiname":"Sarabalani",
    "gn:country_code":"ML",
    "gn:dem":252,
    "gn:feature_class":"P",
    "gn:feature_code":"PPL",
    "gn:name":"Sarabalani",
    "gn:population":0,
    "gn:timezone":"Africa/Bamako",
    "iso:country":"ML",
    "wof:name":"Sarabalani",
    "wof:placetype":"locality"
},
  "geometry": {"coordinates":[-9.1014,14.3025],"type":"Point"}
}