{
  "type": "Feature",
  "properties": {
    "gn:admin1_code":"7.0",
    "gn:asciiname":"Sarafara",
    "gn:country_code":"ML",
    "gn:dem":370,
    "gn:feature_class":"P",
    "gn:feature_code":"PPL",
    "gn:name":"Sarafara",
    "gn:population":0,
    "gn:timezone":"Africa/Bamako",
    "iso:country":"ML",
    "wof:name":"Sarafara",
    "wof:placetype":"locality"
},
  "geometry": {"coordinates":[-8.50937,12.32919],"type":"Point"}
}