{
  "type": "Feature",
  "properties": {
    "gn:admin1_code":"07",
    "gn:asciiname":"Dyorone",
    "gn:country_code":"ML",
    "gn:dem":295,
    "gn:feature_class":"P",
    "gn:feature_code":"PPL",
    "gn:name":"Dyoron\u00e9",
    "gn:population":0,
    "gn:timezone":"Africa/Bamako",
    "iso:country":"ML",
    "name:und_x_variant":[
        "Dioron\u00e9",
        "Hasal\u00e9",
        "Dyoron\u00e9"
    ],
    "wof:name":"Dyorone",
    "wof:placetype":"locality"
},
  "geometry": {"coordinates":[-8.73663,15.07053],"type":"Point"}
}