{
  "type": "Feature",
  "properties": {
    "gn:admin1_code":"03",
    "gn:asciiname":"Tanboko",
    "gn:country_code":"ML",
    "gn:dem":251,
    "gn:feature_class":"P",
    "gn:feature_code":"PPL",
    "gn:name":"Tanboko",
    "gn:population":0,
    "gn:timezone":"Africa/Bamako",
    "iso:country":"ML",
    "wof:name":"Tanboko",
    "wof:placetype":"locality"
},
  "geometry": {"coordinates":[-11.29518,13.55604],"type":"Point"}
}