{
  "type": "Feature",
  "properties": {
    "gn:admin1_code":"00",
    "gn:asciiname":"Nyanfala",
    "gn:country_code":"ML",
    "gn:dem":373,
    "gn:feature_class":"P",
    "gn:feature_code":"PPL",
    "gn:name":"Nyanfala",
    "gn:population":0,
    "gn:timezone":"Africa/Bamako",
    "iso:country":"ML",
    "wof:name":"Nyanfala",
    "wof:placetype":"locality"
},
  "geometry": {"coordinates":[-7.91667,12.46667],"type":"Point"}
}