{
  "type": "Feature",
  "properties": {
    "gn:admin1_code":"00",
    "gn:asciiname":"Dienndo",
    "gn:cc2":"ML",
    "gn:country_code":"ML",
    "gn:dem":344,
    "gn:feature_class":"P",
    "gn:feature_code":"PPL",
    "gn:name":"Dienndo",
    "gn:population":0,
    "gn:timezone":"Africa/Bamako",
    "iso:country":"ML",
    "name:und_x_variant":[
        "Dienndio",
        "Dienndo"
    ],
    "wof:name":"Dienndo",
    "wof:placetype":"locality"
},
  "geometry": {"coordinates":[-6.61667,10.73333],"type":"Point"}
}