{
  "type": "Feature",
  "properties": {
    "gn:admin1_code":"04",
    "gn:asciiname":"Ti-n-Dialali",
    "gn:country_code":"ML",
    "gn:dem":271,
    "gn:feature_class":"P",
    "gn:feature_code":"PPL",
    "gn:name":"Ti-n-Dialali",
    "gn:population":0,
    "gn:timezone":"Africa/Bamako",
    "iso:country":"ML",
    "name:und_x_variant":[
        "Tin Dialali",
        "Ti-n-Dialali"
    ],
    "wof:name":"Ti-n-Dialali",
    "wof:placetype":"locality"
},
  "geometry": {"coordinates":[-1.29313,15.05801],"type":"Point"}
}