{
  "type": "Feature",
  "properties": {
    "gn:admin1_code":"7.0",
    "gn:asciiname":"Biba",
    "gn:country_code":"ML",
    "gn:dem":356,
    "gn:feature_class":"P",
    "gn:feature_code":"PPL",
    "gn:name":"Biba",
    "gn:population":0,
    "gn:timezone":"Africa/Bamako",
    "iso:country":"ML",
    "wof:name":"Biba",
    "wof:placetype":"locality"
},
  "geometry": {"coordinates":[-6.69038,11.8738],"type":"Point"}
}