{
  "type": "Feature",
  "properties": {
    "gn:admin1_code":"7.0",
    "gn:asciiname":"Bertela",
    "gn:country_code":"ML",
    "gn:dem":340,
    "gn:feature_class":"P",
    "gn:feature_code":"PPL",
    "gn:name":"Bert\u00e9la",
    "gn:population":0,
    "gn:timezone":"Africa/Bamako",
    "iso:country":"ML",
    "name:fra_x_preferred":[
        "Bert\u00e9la"
    ],
    "wof:name":"Bertela",
    "wof:placetype":"locality"
},
  "geometry": {"coordinates":[-6.8682,12.7826],"type":"Point"}
}