{
  "type": "Feature",
  "properties": {
    "gn:admin1_code":"05",
    "gn:asciiname":"Morobougou Banbara",
    "gn:country_code":"ML",
    "gn:dem":280,
    "gn:feature_class":"P",
    "gn:feature_code":"PPL",
    "gn:name":"Morobougou Banbara",
    "gn:population":0,
    "gn:timezone":"Africa/Bamako",
    "iso:country":"ML",
    "name:und_x_variant":[
        "Morobougou",
        "Morobougou Banbara"
    ],
    "wof:name":"Morobougou Banbara",
    "wof:placetype":"locality"
},
  "geometry": {"coordinates":[-5.41664,13.60971],"type":"Point"}
}