{
  "type": "Feature",
  "properties": {
    "gn:admin1_code":"3.0",
    "gn:asciiname":"Kodiarana",
    "gn:country_code":"ML",
    "gn:dem":317,
    "gn:feature_class":"P",
    "gn:feature_code":"PPL",
    "gn:name":"Kodiarana",
    "gn:population":0,
    "gn:timezone":"Africa/Bamako",
    "iso:country":"ML",
    "wof:name":"Kodiarana",
    "wof:placetype":"locality"
},
  "geometry": {"coordinates":[-9.5923,13.123],"type":"Point"}
}