{
  "type": "Feature",
  "properties": {
    "gn:admin1_code":"4.0",
    "gn:asciiname":"Logo",
    "gn:country_code":"ML",
    "gn:dem":302,
    "gn:feature_class":"P",
    "gn:feature_code":"PPL",
    "gn:name":"Logo",
    "gn:population":0,
    "gn:timezone":"Africa/Bamako",
    "iso:country":"ML",
    "wof:name":"Logo",
    "wof:placetype":"locality"
},
  "geometry": {"coordinates":[-3.6333,14.0237],"type":"Point"}
}