{
  "type": "Feature",
  "properties": {
    "gn:admin1_code":"07",
    "gn:asciiname":"Tourela",
    "gn:country_code":"ML",
    "gn:dem":335,
    "gn:feature_class":"P",
    "gn:feature_code":"PPL",
    "gn:name":"Tour\u00e9la",
    "gn:population":0,
    "gn:timezone":"Africa/Bamako",
    "iso:country":"ML",
    "wof:name":"Tourela",
    "wof:placetype":"locality"
},
  "geometry": {"coordinates":[-8.07977,12.35396],"type":"Point"}
}