{
  "type": "Feature",
  "properties": {
    "gn:admin1_code":"7.0",
    "gn:asciiname":"Forokobougou",
    "gn:country_code":"ML",
    "gn:dem":417,
    "gn:feature_class":"P",
    "gn:feature_code":"PPL",
    "gn:name":"Forokobougou",
    "gn:population":0,
    "gn:timezone":"Africa/Bamako",
    "iso:country":"ML",
    "wof:name":"Forokobougou",
    "wof:placetype":"locality"
},
  "geometry": {"coordinates":[-8.00092,13.11951],"type":"Point"}
}