{
  "type": "Feature",
  "properties": {
    "gn:admin1_code":"5.0",
    "gn:asciiname":"Bougouni",
    "gn:country_code":"ML",
    "gn:dem":297,
    "gn:feature_class":"P",
    "gn:feature_code":"PPL",
    "gn:name":"Bougouni",
    "gn:population":0,
    "gn:timezone":"Africa/Bamako",
    "iso:country":"ML",
    "wof:name":"Bougouni",
    "wof:placetype":"locality"
},
  "geometry": {"coordinates":[-6.7792,13.1689],"type":"Point"}
}