{
  "type": "Feature",
  "properties": {
    "gn:admin1_code":"5.0",
    "gn:asciiname":"Bougouni",
    "gn:country_code":"ML",
    "gn:dem":297,
    "gn:feature_class":"P",
    "gn:feature_code":"PPL",
    "gn:name":"Bougouni",
    "gn:population":0,
    "gn:timezone":"Africa/Bamako",
    "iso:country":"ML",
    "name:ben_x_preferred":[
        "\u09ac\u09cc\u0997\u09cc\u09a8\u09bf"
    ],
    "name:deu_x_preferred":[
        "Bougouni"
    ],
    "name:heb_x_preferred":[
        "\u05d1\u05d5\u05d2\u05d5\u05e0\u05d9"
    ],
    "name:hin_x_preferred":[
        "\u092c\u0942\u0917\u093e\u0909\u0928\u0940"
    ],
    "name:ind_x_preferred":[
        "Bougouni"
    ],
    "name:kor_x_preferred":[
        "\ubd80\uace0\ub2c8"
    ],
    "name:tur_x_preferred":[
        "Bougouni"
    ],
    "name:ukr_x_preferred":[
        "\u0411\u0443\u0433\u0443\u043d\u0456"
    ],
    "name:urd_x_preferred":[
        "\u0628\u0648\u06af\u0648\u0646\u06cc"
    ],
    "name:vie_x_preferred":[
        "Bougouni"
    ],
    "wof:name":"Bougouni",
    "wof:placetype":"locality"
},
  "geometry": {"coordinates":[-6.7792,13.1689],"type":"Point"}
}