{
  "type": "Feature",
  "properties": {
    "gn:admin1_code":"07",
    "gn:asciiname":"Lbeurd",
    "gn:country_code":"ML",
    "gn:dem":268,
    "gn:feature_class":"P",
    "gn:feature_code":"PPL",
    "gn:name":"Lbeurd",
    "gn:population":0,
    "gn:timezone":"Africa/Bamako",
    "iso:country":"ML",
    "wof:name":"Lbeurd",
    "wof:placetype":"locality"
},
  "geometry": {"coordinates":[-7.22503,15.29842],"type":"Point"}
}