{
  "type": "Feature",
  "properties": {
    "gn:admin1_code":"7.0",
    "gn:asciiname":"Kondo",
    "gn:country_code":"ML",
    "gn:dem":341,
    "gn:feature_class":"P",
    "gn:feature_code":"PPL",
    "gn:name":"Kondo",
    "gn:population":0,
    "gn:timezone":"Africa/Bamako",
    "iso:country":"ML",
    "wof:name":"Kondo",
    "wof:placetype":"locality"
},
  "geometry": {"coordinates":[-8.43057,12.01729],"type":"Point"}
}