{
  "type": "Feature",
  "properties": {
    "gn:admin1_code":"04",
    "gn:asciiname":"Sevare",
    "gn:country_code":"ML",
    "gn:dem":273,
    "gn:feature_class":"P",
    "gn:feature_code":"PPL",
    "gn:name":"S\u00e9var\u00e9",
    "gn:population":0,
    "gn:timezone":"Africa/Bamako",
    "iso:country":"ML",
    "name:cat_x_preferred":[
        "S\u00e9var\u00e9"
    ],
    "name:deu_x_preferred":[
        "S\u00e9var\u00e9"
    ],
    "name:epo_x_preferred":[
        "S\u00e9var\u00e9"
    ],
    "name:eus_x_preferred":[
        "S\u00e9var\u00e9"
    ],
    "name:fin_x_preferred":[
        "S\u00e9var\u00e9"
    ],
    "name:fra_x_preferred":[
        "S\u00e9var\u00e9"
    ],
    "name:rus_x_preferred":[
        "\u0421\u0435\u0432\u0430\u0440\u044d"
    ],
    "name:ukr_x_preferred":[
        "\u0421\u0435\u0432\u0430\u0440\u0435"
    ],
    "name:zho_x_preferred":[
        "\u585e\u74e6\u96f7"
    ],
    "wof:name":"Sevare",
    "wof:placetype":"locality"
},
  "geometry": {"coordinates":[-4.09344,14.52742],"type":"Point"}
}