{
  "type": "Feature",
  "properties": {
    "gn:admin1_code":"07",
    "gn:asciiname":"Diono",
    "gn:country_code":"ML",
    "gn:dem":353,
    "gn:feature_class":"P",
    "gn:feature_code":"PPL",
    "gn:name":"Diono",
    "gn:population":0,
    "gn:timezone":"Africa/Bamako",
    "iso:country":"ML",
    "name:und_x_variant":[
        "Djono",
        "Diono"
    ],
    "wof:name":"Diono",
    "wof:placetype":"locality"
},
  "geometry": {"coordinates":[-7.5359,12.4437],"type":"Point"}
}