{
  "type": "Feature",
  "properties": {
    "gn:admin1_code":"07",
    "gn:asciiname":"Wenia",
    "gn:country_code":"ML",
    "gn:dem":352,
    "gn:feature_class":"P",
    "gn:feature_code":"PPL",
    "gn:name":"W\u00e9nia",
    "gn:population":0,
    "gn:timezone":"Africa/Bamako",
    "iso:country":"ML",
    "name:fra_x_preferred":[
        "W\u00e9nia"
    ],
    "wof:name":"Wenia",
    "wof:placetype":"locality"
},
  "geometry": {"coordinates":[-8.309,13.9414],"type":"Point"}
}