{
  "type": "Feature",
  "properties": {
    "gn:admin1_code":"07",
    "gn:asciiname":"Nababougou",
    "gn:country_code":"ML",
    "gn:dem":329,
    "gn:feature_class":"P",
    "gn:feature_code":"PPL",
    "gn:name":"Nababougou",
    "gn:population":0,
    "gn:timezone":"Africa/Bamako",
    "iso:country":"ML",
    "name:fra_x_preferred":[
        "Nababougou"
    ],
    "wof:name":"Nababougou",
    "wof:placetype":"locality"
},
  "geometry": {"coordinates":[-8.2941,13.7557],"type":"Point"}
}