{
  "type": "Feature",
  "properties": {
    "gn:admin1_code":"03",
    "gn:asciiname":"Tourida",
    "gn:country_code":"ML",
    "gn:dem":250,
    "gn:feature_class":"P",
    "gn:feature_code":"PPL",
    "gn:name":"Tourida",
    "gn:population":0,
    "gn:timezone":"Africa/Bamako",
    "iso:country":"ML",
    "name:und_x_variant":[
        "Tourido",
        "Tourida"
    ],
    "wof:name":"Tourida",
    "wof:placetype":"locality"
},
  "geometry": {"coordinates":[-9.68296,15.00233],"type":"Point"}
}