{
  "type": "Feature",
  "properties": {
    "gn:admin1_code":"3.0",
    "gn:asciiname":"Bangassi",
    "gn:country_code":"ML",
    "gn:dem":49,
    "gn:feature_class":"P",
    "gn:feature_code":"PPL",
    "gn:name":"Bangassi",
    "gn:population":0,
    "gn:timezone":"Africa/Bamako",
    "iso:country":"ML",
    "wof:name":"Bangassi",
    "wof:placetype":"locality"
},
  "geometry": {"coordinates":[-11.35113,14.34802],"type":"Point"}
}