{
  "type": "Feature",
  "properties": {
    "gn:admin1_code":"7.0",
    "gn:asciiname":"Falani",
    "gn:country_code":"ML",
    "gn:dem":306,
    "gn:feature_class":"P",
    "gn:feature_code":"PPL",
    "gn:name":"Falani",
    "gn:population":0,
    "gn:timezone":"Africa/Bamako",
    "iso:country":"ML",
    "wof:name":"Falani",
    "wof:placetype":"locality"
},
  "geometry": {"coordinates":[-6.3063,12.4199],"type":"Point"}
}