{
  "type": "Feature",
  "properties": {
    "gn:admin1_code":"07",
    "gn:asciiname":"Sanga",
    "gn:country_code":"ML",
    "gn:dem":325,
    "gn:feature_class":"P",
    "gn:feature_code":"PPL",
    "gn:name":"Sanga",
    "gn:population":0,
    "gn:timezone":"Africa/Bamako",
    "iso:country":"ML",
    "wof:name":"Sanga",
    "wof:placetype":"locality"
},
  "geometry": {"coordinates":[-6.9732,13.8553],"type":"Point"}
}