{
  "type": "Feature",
  "properties": {
    "gn:admin1_code":"04",
    "gn:asciiname":"Tantoumo",
    "gn:country_code":"ML",
    "gn:dem":276,
    "gn:feature_class":"P",
    "gn:feature_code":"PPL",
    "gn:name":"Tantoumo",
    "gn:population":0,
    "gn:timezone":"Africa/Bamako",
    "iso:country":"ML",
    "wof:name":"Tantoumo",
    "wof:placetype":"locality"
},
  "geometry": {"coordinates":[-2.99866,14.31476],"type":"Point"}
}