{
  "type": "Feature",
  "properties": {
    "gn:admin1_code":"04",
    "gn:asciiname":"Gouni",
    "gn:country_code":"ML",
    "gn:dem":358,
    "gn:feature_class":"P",
    "gn:feature_code":"PPL",
    "gn:name":"Gouni",
    "gn:population":0,
    "gn:timezone":"Africa/Bamako",
    "iso:country":"ML",
    "wof:name":"Gouni",
    "wof:placetype":"locality"
},
  "geometry": {"coordinates":[-3.97539,14.1145],"type":"Point"}
}