{
  "type": "Feature",
  "properties": {
    "gn:admin1_code":"3.0",
    "gn:asciiname":"Bobougou",
    "gn:country_code":"ML",
    "gn:dem":300,
    "gn:feature_class":"P",
    "gn:feature_code":"PPL",
    "gn:name":"Bobougou",
    "gn:population":0,
    "gn:timezone":"Africa/Bamako",
    "iso:country":"ML",
    "wof:name":"Bobougou",
    "wof:placetype":"locality"
},
  "geometry": {"coordinates":[-9.3997,14.7457],"type":"Point"}
}