{
  "type": "Feature",
  "properties": {
    "gn:admin1_code":"05",
    "gn:asciiname":"Ndogona",
    "gn:country_code":"ML",
    "gn:dem":333,
    "gn:feature_class":"P",
    "gn:feature_code":"PPL",
    "gn:name":"Ndogona",
    "gn:population":0,
    "gn:timezone":"Africa/Bamako",
    "iso:country":"ML",
    "name:und_x_variant":[
        "Dogona",
        "Ndogona"
    ],
    "wof:name":"Ndogona",
    "wof:placetype":"locality"
},
  "geometry": {"coordinates":[-7.09438,13.0468],"type":"Point"}
}