{
  "type": "Feature",
  "properties": {
    "gn:admin1_code":"5.0",
    "gn:asciiname":"Bankouma",
    "gn:country_code":"ML",
    "gn:dem":348,
    "gn:feature_class":"P",
    "gn:feature_code":"PPL",
    "gn:name":"Bankouma",
    "gn:population":0,
    "gn:timezone":"Africa/Bamako",
    "iso:country":"ML",
    "wof:name":"Bankouma",
    "wof:placetype":"locality"
},
  "geometry": {"coordinates":[-4.35224,13.07709],"type":"Point"}
}