{
  "type": "Feature",
  "properties": {
    "gn:admin1_code":"5.0",
    "gn:asciiname":"Bankouma",
    "gn:country_code":"ML",
    "gn:dem":348,
    "gn:feature_class":"P",
    "gn:feature_code":"PPL",
    "gn:name":"Bankouma",
    "gn:population":0,
    "gn:timezone":"Africa/Bamako",
    "iso:country":"ML",
    "name:azb_x_preferred":[
        "\u0628\u0627\u0646\u06a9\u0648\u0645\u0627"
    ],
    "name:ceb_x_preferred":[
        "Bankouma"
    ],
    "name:fas_x_preferred":[
        "\u0628\u0627\u0646\u06a9\u0648\u0645\u0627"
    ],
    "name:fra_x_preferred":[
        "Bankouma"
    ],
    "name:swe_x_preferred":[
        "Bankouma"
    ],
    "name:zho_x_preferred":[
        "\u90a6\u5eab\u99ac"
    ],
    "wof:name":"Bankouma",
    "wof:placetype":"locality"
},
  "geometry": {"coordinates":[-4.35224,13.07709],"type":"Point"}
}