{
  "type": "Feature",
  "properties": {
    "gn:admin1_code":"7.0",
    "gn:asciiname":"Kossouma",
    "gn:country_code":"ML",
    "gn:dem":367,
    "gn:feature_class":"P",
    "gn:feature_code":"PPL",
    "gn:name":"Kossouma",
    "gn:population":0,
    "gn:timezone":"Africa/Bamako",
    "iso:country":"ML",
    "wof:name":"Kossouma",
    "wof:placetype":"locality"
},
  "geometry": {"coordinates":[-8.58927,12.21089],"type":"Point"}
}