{
  "type": "Feature",
  "properties": {
    "gn:admin1_code":"06",
    "gn:asciiname":"Mpiebougoula",
    "gn:country_code":"ML",
    "gn:dem":324,
    "gn:feature_class":"P",
    "gn:feature_code":"PPL",
    "gn:name":"Mpi\u00e9bougoula",
    "gn:population":0,
    "gn:timezone":"Africa/Bamako",
    "iso:country":"ML",
    "name:fra_x_preferred":[
        "Mp\u00e9bougoula"
    ],
    "name:und_x_variant":[
        "Mpi\u00e9bougoula"
    ],
    "wof:name":"Mpiebougoula",
    "wof:placetype":"locality"
},
  "geometry": {"coordinates":[-6.84345,11.60828],"type":"Point"}
}