{
  "type": "Feature",
  "properties": {
    "gn:admin1_code":"04",
    "gn:asciiname":"Pergue",
    "gn:country_code":"ML",
    "gn:dem":426,
    "gn:feature_class":"P",
    "gn:feature_code":"PPL",
    "gn:name":"P\u00e8rgu\u00e9",
    "gn:population":0,
    "gn:timezone":"Africa/Bamako",
    "iso:country":"ML",
    "name:und_x_variant":[
        "Perg\u00e9",
        "P\u00e8rgu\u00e9"
    ],
    "wof:name":"Pergue",
    "wof:placetype":"locality"
},
  "geometry": {"coordinates":[-2.97627,14.8019],"type":"Point"}
}