{
  "type": "Feature",
  "properties": {
    "gn:admin1_code":"05",
    "gn:asciiname":"Bounoumbougoula",
    "gn:country_code":"ML",
    "gn:dem":295,
    "gn:feature_class":"P",
    "gn:feature_code":"PPL",
    "gn:name":"Bounoumbougoula",
    "gn:population":0,
    "gn:timezone":"Africa/Bamako",
    "iso:country":"ML",
    "name:und_x_variant":[
        "Bonoubougoula",
        "Bounounbougoula",
        "Bounoumbougoula"
    ],
    "wof:name":"Bounoumbougoula",
    "wof:placetype":"locality"
},
  "geometry": {"coordinates":[-6.383,13.225],"type":"Point"}
}