{
  "type": "Feature",
  "properties": {
    "gn:admin1_code":"04",
    "gn:asciiname":"Yolo",
    "gn:country_code":"ML",
    "gn:dem":363,
    "gn:feature_class":"P",
    "gn:feature_code":"PPL",
    "gn:name":"Yolo",
    "gn:population":0,
    "gn:timezone":"Africa/Bamako",
    "iso:country":"ML",
    "name:und_x_variant":[
        "Golo",
        "Yolo"
    ],
    "wof:name":"Yolo",
    "wof:placetype":"locality"
},
  "geometry": {"coordinates":[-3.7452,13.9016],"type":"Point"}
}