{
  "type": "Feature",
  "properties": {
    "gn:admin1_code":"07",
    "gn:asciiname":"Djila-Finyana",
    "gn:country_code":"ML",
    "gn:dem":305,
    "gn:feature_class":"P",
    "gn:feature_code":"PPL",
    "gn:name":"Djila-Finyana",
    "gn:population":0,
    "gn:timezone":"Africa/Bamako",
    "iso:country":"ML",
    "name:fra_x_preferred":[
        "N\u2019Djila"
    ],
    "wof:name":"Djila-Finyana",
    "wof:placetype":"locality"
},
  "geometry": {"coordinates":[-6.9275,12.5102],"type":"Point"}
}