{
  "type": "Feature",
  "properties": {
    "gn:admin1_code":"07",
    "gn:asciiname":"Ide",
    "gn:country_code":"ML",
    "gn:dem":256,
    "gn:feature_class":"P",
    "gn:feature_code":"PPL",
    "gn:name":"Id\u00e9",
    "gn:population":0,
    "gn:timezone":"Africa/Bamako",
    "iso:country":"ML",
    "wof:name":"Ide",
    "wof:placetype":"locality"
},
  "geometry": {"coordinates":[-7.7752,14.9579],"type":"Point"}
}