{
  "type": "Feature",
  "properties": {
    "gn:admin1_code":"05",
    "gn:asciiname":"Tegueredjira",
    "gn:country_code":"ML",
    "gn:dem":280,
    "gn:feature_class":"P",
    "gn:feature_code":"PPL",
    "gn:name":"T\u00e9gu\u00e9r\u00e9djira",
    "gn:population":0,
    "gn:timezone":"Africa/Bamako",
    "iso:country":"ML",
    "wof:name":"Tegueredjira",
    "wof:placetype":"locality"
},
  "geometry": {"coordinates":[-5.01037,13.87895],"type":"Point"}
}