{
  "type": "Feature",
  "properties": {
    "gn:admin1_code":"6.0",
    "gn:asciiname":"Ngoloperebougou",
    "gn:country_code":"ML",
    "gn:dem":442,
    "gn:feature_class":"P",
    "gn:feature_code":"PPL",
    "gn:name":"Ngolop\u00e9r\u00e9bougou",
    "gn:population":0,
    "gn:timezone":"Africa/Bamako",
    "iso:country":"ML",
    "wof:name":"Ngoloperebougou",
    "wof:placetype":"locality"
},
  "geometry": {"coordinates":[-6.07309,11.3399],"type":"Point"}
}