{
  "type": "Feature",
  "properties": {
    "gn:admin1_code":"7.0",
    "gn:asciiname":"Bodiebougou",
    "gn:country_code":"ML",
    "gn:dem":349,
    "gn:feature_class":"P",
    "gn:feature_code":"PPL",
    "gn:name":"Bodi\u00e9bougou",
    "gn:population":0,
    "gn:timezone":"Africa/Bamako",
    "iso:country":"ML",
    "name:fra_x_preferred":[
        "Bodi\u00e9bougou"
    ],
    "wof:name":"Bodiebougou",
    "wof:placetype":"locality"
},
  "geometry": {"coordinates":[-8.2936,13.9433],"type":"Point"}
}