{
  "type": "Feature",
  "properties": {
    "gn:admin1_code":"4.0",
    "gn:asciiname":"Ngourema Faya",
    "gn:country_code":"ML",
    "gn:dem":267,
    "gn:feature_class":"P",
    "gn:feature_code":"PPL",
    "gn:name":"Ngour\u00e9ma Faya",
    "gn:population":0,
    "gn:timezone":"Africa/Bamako",
    "iso:country":"ML",
    "wof:name":"Ngourema Faya",
    "wof:placetype":"locality"
},
  "geometry": {"coordinates":[-4.54425,14.41582],"type":"Point"}
}