{
  "type": "Feature",
  "properties": {
    "gn:admin1_code":"07",
    "gn:asciiname":"Fissaba",
    "gn:country_code":"ML",
    "gn:dem":365,
    "gn:feature_class":"P",
    "gn:feature_code":"PPL",
    "gn:name":"Fissaba",
    "gn:population":0,
    "gn:timezone":"Africa/Bamako",
    "iso:country":"ML",
    "name:fra_x_preferred":[
        "Foussaba"
    ],
    "name:und_x_variant":[
        "Foussaba"
    ],
    "wof:name":"Fissaba",
    "wof:placetype":"locality"
},
  "geometry": {"coordinates":[-6.70035,11.922],"type":"Point"}
}