{
  "type": "Feature",
  "properties": {
    "gn:admin1_code":"5.0",
    "gn:asciiname":"Kiran",
    "gn:country_code":"ML",
    "gn:dem":278,
    "gn:feature_class":"P",
    "gn:feature_code":"PPL",
    "gn:name":"Kiran",
    "gn:population":0,
    "gn:timezone":"Africa/Bamako",
    "iso:country":"ML",
    "name:ceb_x_preferred":[
        "Kiran"
    ],
    "name:deu_x_preferred":[
        "Kiran"
    ],
    "name:hin_x_preferred":[
        "\u0915\u093f\u0930\u0923"
    ],
    "wof:name":"Kiran",
    "wof:placetype":"locality"
},
  "geometry": {"coordinates":[-5.38274,13.67127],"type":"Point"}
}