{
  "type": "Feature",
  "properties": {
    "gn:admin1_code":"04",
    "gn:asciiname":"Manga Sonolie",
    "gn:country_code":"ML",
    "gn:dem":267,
    "gn:feature_class":"P",
    "gn:feature_code":"PPL",
    "gn:name":"Manga Sonoli\u00e9",
    "gn:population":0,
    "gn:timezone":"Africa/Bamako",
    "iso:country":"ML",
    "name:und_x_variant":[
        "Manga-Sonali\u00e9",
        "Manga Sonoli\u00e9"
    ],
    "wof:name":"Manga Sonolie",
    "wof:placetype":"locality"
},
  "geometry": {"coordinates":[-4.76318,14.90822],"type":"Point"}
}