{
  "type": "Feature",
  "properties": {
    "gn:admin1_code":"00",
    "gn:asciiname":"Selingue",
    "gn:country_code":"ML",
    "gn:dem":351,
    "gn:feature_class":"P",
    "gn:feature_code":"PPL",
    "gn:name":"S\u00e9lingu\u00e9",
    "gn:population":0,
    "gn:timezone":"Africa/Bamako",
    "iso:country":"ML",
    "name:und_x_variant":[
        "S\u00e9lingu\u00e9"
    ],
    "wof:name":"Selingue",
    "wof:placetype":"locality"
},
  "geometry": {"coordinates":[-8.23333,11.61667],"type":"Point"}
}