{
  "type": "Feature",
  "properties": {
    "gn:admin1_code":"5.0",
    "gn:asciiname":"Sara",
    "gn:country_code":"ML",
    "gn:dem":285,
    "gn:feature_class":"P",
    "gn:feature_code":"PPL",
    "gn:name":"Sara",
    "gn:population":0,
    "gn:timezone":"Africa/Bamako",
    "iso:country":"ML",
    "wof:name":"Sara",
    "wof:placetype":"locality"
},
  "geometry": {"coordinates":[-4.4849,13.3694],"type":"Point"}
}