{
  "type": "Feature",
  "properties": {
    "gn:admin1_code":"06",
    "gn:asciiname":"Yeni",
    "gn:country_code":"ML",
    "gn:dem":327,
    "gn:feature_class":"P",
    "gn:feature_code":"PPL",
    "gn:name":"Y\u00e9ni",
    "gn:population":0,
    "gn:timezone":"Africa/Bamako",
    "iso:country":"ML",
    "name:fra_x_preferred":[
        "Y\u00e9ni"
    ],
    "wof:name":"Yeni",
    "wof:placetype":"locality"
},
  "geometry": {"coordinates":[-6.92896,11.72187],"type":"Point"}
}