{
  "type": "Feature",
  "properties": {
    "gn:admin1_code":"6.0",
    "gn:asciiname":"Daouda",
    "gn:country_code":"ML",
    "gn:dem":342,
    "gn:feature_class":"P",
    "gn:feature_code":"PPL",
    "gn:name":"Daouda",
    "gn:population":0,
    "gn:timezone":"Africa/Bamako",
    "iso:country":"ML",
    "wof:name":"Daouda",
    "wof:placetype":"locality"
},
  "geometry": {"coordinates":[-5.57848,11.44549],"type":"Point"}
}