{
  "type": "Feature",
  "properties": {
    "gn:admin1_code":"07",
    "gn:asciiname":"Madina",
    "gn:country_code":"ML",
    "gn:dem":262,
    "gn:feature_class":"P",
    "gn:feature_code":"PPL",
    "gn:name":"Madina",
    "gn:population":0,
    "gn:timezone":"Africa/Bamako",
    "iso:country":"ML",
    "wof:name":"Madina",
    "wof:placetype":"locality"
},
  "geometry": {"coordinates":[-8.94897,15.37041],"type":"Point"}
}