{
  "type": "Feature",
  "properties": {
    "gn:admin1_code":"4.0",
    "gn:asciiname":"Dio",
    "gn:country_code":"ML",
    "gn:dem":270,
    "gn:feature_class":"P",
    "gn:feature_code":"PPL",
    "gn:name":"Dio",
    "gn:population":0,
    "gn:timezone":"Africa/Bamako",
    "iso:country":"ML",
    "name:cat_x_preferred":[
        "Dio"
    ],
    "name:ceb_x_preferred":[
        "Dio"
    ],
    "name:deu_x_preferred":[
        "Dio"
    ],
    "name:est_x_preferred":[
        "Dio"
    ],
    "name:fas_x_preferred":[
        "\u062f\u06cc\u0648"
    ],
    "name:fin_x_preferred":[
        "Dio"
    ],
    "name:fra_x_preferred":[
        "Dio"
    ],
    "name:heb_x_preferred":[
        "\u05d3\u05d9\u05d5"
    ],
    "name:jpn_x_preferred":[
        "\u30c7\u30a3\u30aa"
    ],
    "name:nld_x_preferred":[
        "Dio"
    ],
    "name:por_x_preferred":[
        "Dio"
    ],
    "name:rus_x_preferred":[
        "\u0414\u0438\u043e"
    ],
    "name:swe_x_preferred":[
        "Dio"
    ],
    "name:ukr_x_preferred":[
        "\u0414\u0456\u043e"
    ],
    "name:zho_x_preferred":[
        "\u8fea\u5967"
    ],
    "wof:name":"Dio",
    "wof:placetype":"locality"
},
  "geometry": {"coordinates":[-4.10195,14.30412],"type":"Point"}
}