{
  "type": "Feature",
  "properties": {
    "gn:admin1_code":"06",
    "gn:asciiname":"Sikoro",
    "gn:country_code":"ML",
    "gn:dem":320,
    "gn:feature_class":"P",
    "gn:feature_code":"PPL",
    "gn:name":"Sikoro",
    "gn:population":0,
    "gn:timezone":"Africa/Bamako",
    "iso:country":"ML",
    "name:fra_x_preferred":[
        "Sikoro"
    ],
    "wof:name":"Sikoro",
    "wof:placetype":"locality"
},
  "geometry": {"coordinates":[-6.28676,11.0713],"type":"Point"}
}