{
  "type": "Feature",
  "properties": {
    "gn:admin1_code":"07",
    "gn:asciiname":"Mpebougou",
    "gn:country_code":"ML",
    "gn:dem":302,
    "gn:feature_class":"P",
    "gn:feature_code":"PPL",
    "gn:name":"Mp\u00e8bougou",
    "gn:population":0,
    "gn:timezone":"Africa/Bamako",
    "iso:country":"ML",
    "name:und_x_variant":[
        "Piebougou",
        "Nb\u00e9bougou",
        "Mp\u00e8bougou"
    ],
    "wof:name":"Mpebougou",
    "wof:placetype":"locality"
},
  "geometry": {"coordinates":[-7.23848,13.89993],"type":"Point"}
}