{
  "type": "Feature",
  "properties": {
    "gn:admin1_code":"7.0",
    "gn:asciiname":"Soma",
    "gn:country_code":"ML",
    "gn:dem":402,
    "gn:feature_class":"P",
    "gn:feature_code":"PPL",
    "gn:name":"Soma",
    "gn:population":0,
    "gn:timezone":"Africa/Bamako",
    "iso:country":"ML",
    "wof:name":"Soma",
    "wof:placetype":"locality"
},
  "geometry": {"coordinates":[-7.85499,13.62999],"type":"Point"}
}