{
  "type": "Feature",
  "properties": {
    "gn:admin1_code":"03",
    "gn:asciiname":"Tamarina",
    "gn:country_code":"ML",
    "gn:dem":119,
    "gn:feature_class":"P",
    "gn:feature_code":"PPL",
    "gn:name":"Tamarina",
    "gn:population":0,
    "gn:timezone":"Africa/Bamako",
    "iso:country":"ML",
    "name:und_x_variant":[
        "Tamar\u00e9na",
        "Tam\u00e9r\u00e9na",
        "Tamarina"
    ],
    "wof:name":"Tamarina",
    "wof:placetype":"locality"
},
  "geometry": {"coordinates":[-10.8074,13.36],"type":"Point"}
}