{
  "type": "Feature",
  "properties": {
    "gn:admin1_code":"6.0",
    "gn:asciiname":"Bagani",
    "gn:country_code":"ML",
    "gn:dem":367,
    "gn:feature_class":"P",
    "gn:feature_code":"PPL",
    "gn:name":"Bagani",
    "gn:population":0,
    "gn:timezone":"Africa/Bamako",
    "iso:country":"ML",
    "name:und_x_variant":[
        "Barani",
        "Bagani"
    ],
    "wof:name":"Bagani",
    "wof:placetype":"locality"
},
  "geometry": {"coordinates":[-7.84019,11.3937],"type":"Point"}
}