{
  "type": "Feature",
  "properties": {
    "gn:admin1_code":"6.0",
    "gn:asciiname":"Meribougou",
    "gn:country_code":"ML",
    "gn:dem":337,
    "gn:feature_class":"P",
    "gn:feature_code":"PPL",
    "gn:name":"M\u00e9ribougou",
    "gn:population":0,
    "gn:timezone":"Africa/Bamako",
    "iso:country":"ML",
    "wof:name":"Meribougou",
    "wof:placetype":"locality"
},
  "geometry": {"coordinates":[-7.27448,11.80068],"type":"Point"}
}