{
  "type": "Feature",
  "properties": {
    "gn:admin1_code":"7.0",
    "gn:asciiname":"Koumabougou",
    "gn:country_code":"ML",
    "gn:dem":363,
    "gn:feature_class":"P",
    "gn:feature_code":"PPL",
    "gn:name":"Koumabougou",
    "gn:population":0,
    "gn:timezone":"Africa/Bamako",
    "iso:country":"ML",
    "wof:name":"Koumabougou",
    "wof:placetype":"locality"
},
  "geometry": {"coordinates":[-6.75002,11.95337],"type":"Point"}
}