{
  "type": "Feature",
  "properties": {
    "gn:admin1_code":"04",
    "gn:asciiname":"Gande Tama",
    "gn:country_code":"ML",
    "gn:dem":263,
    "gn:feature_class":"P",
    "gn:feature_code":"PPL",
    "gn:name":"Gand\u00e9 Tama",
    "gn:population":0,
    "gn:timezone":"Africa/Bamako",
    "iso:country":"ML",
    "name:und_x_variant":[
        "Gand\u00e9toma",
        "Gand\u00e9 Tama"
    ],
    "wof:name":"Gande Tama",
    "wof:placetype":"locality"
},
  "geometry": {"coordinates":[-4.43041,14.99838],"type":"Point"}
}