{
  "type": "Feature",
  "properties": {
    "gn:admin1_code":"03",
    "gn:asciiname":"Sidian",
    "gn:country_code":"ML",
    "gn:dem":317,
    "gn:feature_class":"P",
    "gn:feature_code":"PPL",
    "gn:name":"Sidian",
    "gn:population":0,
    "gn:timezone":"Africa/Bamako",
    "iso:country":"ML",
    "name:fra_x_preferred":[
        "Sidian"
    ],
    "wof:name":"Sidian",
    "wof:placetype":"locality"
},
  "geometry": {"coordinates":[-8.8344,13.5972],"type":"Point"}
}