{
  "type": "Feature",
  "properties": {
    "gn:admin1_code":"03",
    "gn:asciiname":"Dialeani",
    "gn:country_code":"ML",
    "gn:dem":324,
    "gn:feature_class":"P",
    "gn:feature_code":"PPL",
    "gn:name":"Dial\u00e9ani",
    "gn:population":0,
    "gn:timezone":"Africa/Bamako",
    "iso:country":"ML",
    "name:und_x_variant":[
        "Dialaya",
        "Dial\u00e9ani"
    ],
    "wof:name":"Dialeani",
    "wof:placetype":"locality"
},
  "geometry": {"coordinates":[-9.47263,13.13873],"type":"Point"}
}