{
  "type": "Feature",
  "properties": {
    "gn:admin1_code":"00",
    "gn:asciiname":"Paraol",
    "gn:country_code":"ML",
    "gn:dem":612,
    "gn:feature_class":"P",
    "gn:feature_code":"PPL",
    "gn:name":"Paraol",
    "gn:population":0,
    "gn:timezone":"Africa/Bamako",
    "iso:country":"ML",
    "wof:name":"Paraol",
    "wof:placetype":"locality"
},
  "geometry": {"coordinates":[-10.53333,12.26667],"type":"Point"}
}