{
  "type": "Feature",
  "properties": {
    "gn:admin1_code":"03",
    "gn:asciiname":"Harangui",
    "gn:country_code":"ML",
    "gn:dem":480,
    "gn:feature_class":"P",
    "gn:feature_code":"PPL",
    "gn:name":"Harangui",
    "gn:population":0,
    "gn:timezone":"Africa/Bamako",
    "iso:country":"ML",
    "wof:name":"Harangui",
    "wof:placetype":"locality"
},
  "geometry": {"coordinates":[-11.29352,12.02704],"type":"Point"}
}