{
  "type": "Feature",
  "properties": {
    "gn:admin1_code":"7.0",
    "gn:asciiname":"Massiminabougou",
    "gn:country_code":"ML",
    "gn:dem":310,
    "gn:feature_class":"P",
    "gn:feature_code":"PPL",
    "gn:name":"Massiminabougou",
    "gn:population":0,
    "gn:timezone":"Africa/Bamako",
    "iso:country":"ML",
    "wof:name":"Massiminabougou",
    "wof:placetype":"locality"
},
  "geometry": {"coordinates":[-7.30969,13.34421],"type":"Point"}
}