{
  "type": "Feature",
  "properties": {
    "gn:admin1_code":"4.0",
    "gn:asciiname":"Damada",
    "gn:country_code":"ML",
    "gn:dem":631,
    "gn:feature_class":"P",
    "gn:feature_code":"PPL",
    "gn:name":"Damada",
    "gn:population":0,
    "gn:timezone":"Africa/Bamako",
    "iso:country":"ML",
    "wof:name":"Damada",
    "wof:placetype":"locality"
},
  "geometry": {"coordinates":[-3.17613,14.73287],"type":"Point"}
}