{
  "type": "Feature",
  "properties": {
    "gn:admin1_code":"03",
    "gn:asciiname":"Katabaya",
    "gn:country_code":"ML",
    "gn:dem":446,
    "gn:feature_class":"P",
    "gn:feature_code":"PPL",
    "gn:name":"Katabaya",
    "gn:population":0,
    "gn:timezone":"Africa/Bamako",
    "iso:country":"ML",
    "name:und_x_variant":[
        "Kataba\u00efa",
        "Katabaya"
    ],
    "wof:name":"Katabaya",
    "wof:placetype":"locality"
},
  "geometry": {"coordinates":[-11.38184,12.23562],"type":"Point"}
}