{
  "type": "Feature",
  "properties": {
    "gn:admin1_code":"3.0",
    "gn:asciiname":"Babala",
    "gn:country_code":"ML",
    "gn:dem":230,
    "gn:feature_class":"P",
    "gn:feature_code":"PPL",
    "gn:name":"Babala",
    "gn:population":0,
    "gn:timezone":"Africa/Bamako",
    "iso:country":"ML",
    "name:bih_x_preferred":[
        "\u092c\u093e\u092c\u0932\u093e"
    ],
    "name:ceb_x_preferred":[
        "Babala"
    ],
    "name:fra_x_preferred":[
        "Babala"
    ],
    "name:hin_x_preferred":[
        "\u092c\u093e\u0930\u0932\u093e"
    ],
    "name:mai_x_preferred":[
        "\u092c\u093e\u092c\u0932\u093e"
    ],
    "name:msa_x_preferred":[
        "Babala"
    ],
    "name:nep_x_preferred":[
        "\u092c\u093e\u092c\u0932\u093e"
    ],
    "name:new_x_preferred":[
        "\u092c\u093e\u092c\u0932\u093e"
    ],
    "name:pol_x_preferred":[
        "Babala"
    ],
    "wof:name":"Babala",
    "wof:placetype":"locality"
},
  "geometry": {"coordinates":[-10.5344,14.7234],"type":"Point"}
}