{
  "type": "Feature",
  "properties": {
    "gn:admin1_code":"05",
    "gn:asciiname":"Dagadougou",
    "gn:country_code":"ML",
    "gn:dem":275,
    "gn:feature_class":"P",
    "gn:feature_code":"PPL",
    "gn:name":"Dagadougou",
    "gn:population":0,
    "gn:timezone":"Africa/Bamako",
    "iso:country":"ML",
    "name:und_x_variant":[
        "Ti\u00e9rakui",
        "Dagadougou"
    ],
    "wof:name":"Dagadougou",
    "wof:placetype":"locality"
},
  "geometry": {"coordinates":[-4.3189,13.723],"type":"Point"}
}