{
  "type": "Feature",
  "properties": {
    "gn:admin1_code":"03",
    "gn:asciiname":"Yilimalo",
    "gn:country_code":"ML",
    "gn:dem":274,
    "gn:feature_class":"P",
    "gn:feature_code":"PPL",
    "gn:name":"Yilimalo",
    "gn:population":0,
    "gn:timezone":"Africa/Bamako",
    "iso:country":"ML",
    "wof:name":"Yilimalo",
    "wof:placetype":"locality"
},
  "geometry": {"coordinates":[-11.16572,13.50213],"type":"Point"}
}