{
  "type": "Feature",
  "properties": {
    "gn:admin1_code":"04",
    "gn:asciiname":"Yogoro",
    "gn:country_code":"ML",
    "gn:dem":262,
    "gn:feature_class":"P",
    "gn:feature_code":"PPL",
    "gn:name":"Yogoro",
    "gn:population":0,
    "gn:timezone":"Africa/Bamako",
    "iso:country":"ML",
    "wof:name":"Yogoro",
    "wof:placetype":"locality"
},
  "geometry": {"coordinates":[-4.3212,15.44],"type":"Point"}
}