{
  "type": "Feature",
  "properties": {
    "gn:admin1_code":"03",
    "gn:asciiname":"Soukoutali",
    "gn:country_code":"ML",
    "gn:dem":207,
    "gn:feature_class":"P",
    "gn:feature_code":"PPL",
    "gn:name":"Soukoutali",
    "gn:population":0,
    "gn:timezone":"Africa/Bamako",
    "iso:country":"ML",
    "wof:name":"Soukoutali",
    "wof:placetype":"locality"
},
  "geometry": {"coordinates":[-10.4251,13.202],"type":"Point"}
}