{
  "type": "Feature",
  "properties": {
    "gn:admin1_code":"6.0",
    "gn:asciiname":"Galamina",
    "gn:country_code":"ML",
    "gn:dem":389,
    "gn:feature_class":"P",
    "gn:feature_code":"PPL",
    "gn:name":"Galamina",
    "gn:population":0,
    "gn:timezone":"Africa/Bamako",
    "iso:country":"ML",
    "wof:name":"Galamina",
    "wof:placetype":"locality"
},
  "geometry": {"coordinates":[-7.96377,11.36233],"type":"Point"}
}