{
  "type": "Feature",
  "properties": {
    "gn:admin1_code":"7.0",
    "gn:asciiname":"Deniekoro",
    "gn:country_code":"ML",
    "gn:dem":361,
    "gn:feature_class":"P",
    "gn:feature_code":"PPL",
    "gn:name":"D\u00e9ni\u00e9koro",
    "gn:population":0,
    "gn:timezone":"Africa/Bamako",
    "iso:country":"ML",
    "wof:name":"Deniekoro",
    "wof:placetype":"locality"
},
  "geometry": {"coordinates":[-6.68565,11.90709],"type":"Point"}
}