{
  "type": "Feature",
  "properties": {
    "gn:admin1_code":"00",
    "gn:asciiname":"Siradiouba",
    "gn:cc2":"ML",
    "gn:country_code":"ML",
    "gn:dem":353,
    "gn:feature_class":"P",
    "gn:feature_code":"PPL",
    "gn:name":"Siradiouba",
    "gn:population":0,
    "gn:timezone":"Africa/Bamako",
    "iso:country":"ML",
    "name:und_x_variant":[
        "Diradiola",
        "Siradoubia",
        "Siradiouba"
    ],
    "wof:name":"Siradiouba",
    "wof:placetype":"locality"
},
  "geometry": {"coordinates":[-8.66667,10.96667],"type":"Point"}
}