{
  "type": "Feature",
  "properties": {
    "gn:admin1_code":"0.0",
    "gn:asciiname":"Balandougou",
    "gn:country_code":"ML",
    "gn:dem":349,
    "gn:feature_class":"P",
    "gn:feature_code":"PPL",
    "gn:name":"Balandougou",
    "gn:population":0,
    "gn:timezone":"Africa/Bamako",
    "iso:country":"ML",
    "name:bul_x_preferred":[
        "\u0411\u0430\u043b\u0430\u043d\u0434\u0443\u0433\u0443"
    ],
    "name:ceb_x_preferred":[
        "Balandougou"
    ],
    "name:spa_x_preferred":[
        "Balandougou"
    ],
    "name:swe_x_preferred":[
        "Balandougou"
    ],
    "wof:name":"Balandougou",
    "wof:placetype":"locality"
},
  "geometry": {"coordinates":[-9.46667,12.58333],"type":"Point"}
}