{
  "type": "Feature",
  "properties": {
    "gn:admin1_code":"05",
    "gn:asciiname":"Danfa",
    "gn:country_code":"ML",
    "gn:dem":313,
    "gn:feature_class":"P",
    "gn:feature_code":"PPL",
    "gn:name":"Danfa",
    "gn:population":0,
    "gn:timezone":"Africa/Bamako",
    "iso:country":"ML",
    "name:fra_x_preferred":[
        "Danfa"
    ],
    "name:fra_x_variant":[
        "Sanabougou",
        "Denfa"
    ],
    "name:und_x_variant":[
        "Sanabougou",
        "Denfa"
    ],
    "wof:name":"Danfa",
    "wof:placetype":"locality"
},
  "geometry": {"coordinates":[-6.0836,12.689],"type":"Point"}
}