{
  "type": "Feature",
  "properties": {
    "gn:admin1_code":"07",
    "gn:asciiname":"Sikorobougou",
    "gn:country_code":"ML",
    "gn:dem":380,
    "gn:feature_class":"P",
    "gn:feature_code":"PPL",
    "gn:name":"Sikorobougou",
    "gn:population":0,
    "gn:timezone":"Africa/Bamako",
    "iso:country":"ML",
    "wof:name":"Sikorobougou",
    "wof:placetype":"locality"
},
  "geometry": {"coordinates":[-8.03217,12.84889],"type":"Point"}
}