{
  "type": "Feature",
  "properties": {
    "gn:admin1_code":"03",
    "gn:asciiname":"Mbarkefal",
    "gn:country_code":"ML",
    "gn:dem":284,
    "gn:feature_class":"P",
    "gn:feature_code":"PPL",
    "gn:name":"Mbark\u00e9fal",
    "gn:population":0,
    "gn:timezone":"Africa/Bamako",
    "iso:country":"ML",
    "wof:name":"Mbarkefal",
    "wof:placetype":"locality"
},
  "geometry": {"coordinates":[-8.5352,14.42147],"type":"Point"}
}