{
  "type": "Feature",
  "properties": {
    "gn:admin1_code":"06",
    "gn:asciiname":"Nirouani",
    "gn:country_code":"ML",
    "gn:dem":446,
    "gn:feature_class":"P",
    "gn:feature_code":"PPL",
    "gn:name":"Nirouani",
    "gn:population":0,
    "gn:timezone":"Africa/Bamako",
    "iso:country":"ML",
    "name:fra_x_preferred":[
        "Nirouana"
    ],
    "name:und_x_variant":[
        "Nirouana"
    ],
    "wof:name":"Nirouani",
    "wof:placetype":"locality"
},
  "geometry": {"coordinates":[-6.00442,11.41281],"type":"Point"}
}