{
  "type": "Feature",
  "properties": {
    "gn:admin1_code":"07",
    "gn:asciiname":"Moribougou Tiguira",
    "gn:country_code":"ML",
    "gn:dem":307,
    "gn:feature_class":"P",
    "gn:feature_code":"PPL",
    "gn:name":"Moribougou Tiguira",
    "gn:population":0,
    "gn:timezone":"Africa/Bamako",
    "iso:country":"ML",
    "name:und_x_variant":[
        "Moribougou",
        "Moribougou Tiguira"
    ],
    "wof:name":"Moribougou Tiguira",
    "wof:placetype":"locality"
},
  "geometry": {"coordinates":[-7.33591,13.83799],"type":"Point"}
}