{
  "type": "Feature",
  "properties": {
    "gn:admin1_code":"6.0",
    "gn:asciiname":"Kolontabale",
    "gn:country_code":"ML",
    "gn:dem":312,
    "gn:feature_class":"P",
    "gn:feature_code":"PPL",
    "gn:name":"Kolontabal\u00e9",
    "gn:population":0,
    "gn:timezone":"Africa/Bamako",
    "iso:country":"ML",
    "wof:name":"Kolontabale",
    "wof:placetype":"locality"
},
  "geometry": {"coordinates":[-6.14579,11.94957],"type":"Point"}
}