{
  "type": "Feature",
  "properties": {
    "gn:admin1_code":"4.0",
    "gn:asciiname":"Gani-Le",
    "gn:country_code":"ML",
    "gn:dem":349,
    "gn:feature_class":"P",
    "gn:feature_code":"PPL",
    "gn:name":"Gani-L\u00e9",
    "gn:population":0,
    "gn:timezone":"Africa/Bamako",
    "iso:country":"ML",
    "wof:name":"Gani-Le",
    "wof:placetype":"locality"
},
  "geometry": {"coordinates":[-3.789,14.0198],"type":"Point"}
}