{
  "type": "Feature",
  "properties": {
    "gn:admin1_code":"5.0",
    "gn:asciiname":"Wakala",
    "gn:country_code":"ML",
    "gn:dem":284,
    "gn:feature_class":"P",
    "gn:feature_code":"PPL",
    "gn:name":"Wakala",
    "gn:population":0,
    "gn:timezone":"Africa/Bamako",
    "iso:country":"ML",
    "wof:name":"Wakala",
    "wof:placetype":"locality"
},
  "geometry": {"coordinates":[-5.94,13.4474],"type":"Point"}
}