{
  "type": "Feature",
  "properties": {
    "gn:admin1_code":"03",
    "gn:asciiname":"Oussouki",
    "gn:country_code":"ML",
    "gn:dem":86,
    "gn:feature_class":"P",
    "gn:feature_code":"PPL",
    "gn:name":"Oussouki",
    "gn:population":0,
    "gn:timezone":"Africa/Bamako",
    "iso:country":"ML",
    "wof:name":"Oussouki",
    "wof:placetype":"locality"
},
  "geometry": {"coordinates":[-11.05978,13.9045],"type":"Point"}
}