{
  "type": "Feature",
  "properties": {
    "gn:admin1_code":"00",
    "gn:asciiname":"Oula",
    "gn:country_code":"ML",
    "gn:dem":525,
    "gn:feature_class":"P",
    "gn:feature_code":"PPL",
    "gn:name":"Oula",
    "gn:population":0,
    "gn:timezone":"Africa/Bamako",
    "iso:country":"ML",
    "wof:name":"Oula",
    "wof:placetype":"locality"
},
  "geometry": {"coordinates":[-10.16667,12.33333],"type":"Point"}
}