{
  "type": "Feature",
  "properties": {
    "gn:admin1_code":"04",
    "gn:asciiname":"Madougou",
    "gn:country_code":"ML",
    "gn:dem":269,
    "gn:feature_class":"P",
    "gn:feature_code":"PPL",
    "gn:name":"Madougou",
    "gn:population":0,
    "gn:timezone":"Africa/Bamako",
    "iso:country":"ML",
    "name:fin_x_preferred":[
        "Madougou"
    ],
    "name:fra_x_preferred":[
        "Madougou"
    ],
    "name:ita_x_preferred":[
        "Madougou"
    ],
    "name:nld_x_preferred":[
        "Madougou"
    ],
    "name:spa_x_preferred":[
        "Madougou"
    ],
    "name:urd_x_preferred":[
        "\u0645\u06cc\u0688\u0648\u06af\u0648"
    ],
    "name:zho_x_preferred":[
        "\u9a6c\u675c\u53e4"
    ],
    "wof:name":"Madougou",
    "wof:placetype":"locality"
},
  "geometry": {"coordinates":[-3.2638,15.3258],"type":"Point"}
}