{
  "type": "Feature",
  "properties": {
    "gn:admin1_code":"03",
    "gn:asciiname":"Lani Modi",
    "gn:country_code":"ML",
    "gn:dem":32,
    "gn:feature_class":"P",
    "gn:feature_code":"PPL",
    "gn:name":"Lani Modi",
    "gn:population":0,
    "gn:timezone":"Africa/Bamako",
    "iso:country":"ML",
    "wof:name":"Lani Modi",
    "wof:placetype":"locality"
},
  "geometry": {"coordinates":[-12.05496,14.71475],"type":"Point"}
}