{
  "type": "Feature",
  "properties": {
    "gn:admin1_code":"00",
    "gn:asciiname":"Diou",
    "gn:country_code":"ML",
    "gn:dem":348,
    "gn:feature_class":"P",
    "gn:feature_code":"PPL",
    "gn:name":"Diou",
    "gn:population":0,
    "gn:timezone":"Africa/Bamako",
    "iso:country":"ML",
    "name:fin_x_preferred":[
        "Diou"
    ],
    "name:fra_x_preferred":[
        "Diou"
    ],
    "name:ita_x_preferred":[
        "Diou"
    ],
    "name:nld_x_preferred":[
        "Diou"
    ],
    "name:por_x_preferred":[
        "Diu"
    ],
    "name:spa_x_preferred":[
        "Diou"
    ],
    "name:zho_x_preferred":[
        "\u8fea\u70cf"
    ],
    "wof:name":"Diou",
    "wof:placetype":"locality"
},
  "geometry": {"coordinates":[-5.96667,10.58333],"type":"Point"}
}