{
  "type": "Feature",
  "properties": {
    "gn:admin1_code":"00",
    "gn:asciiname":"Diou",
    "gn:country_code":"ML",
    "gn:dem":348,
    "gn:feature_class":"P",
    "gn:feature_code":"PPL",
    "gn:name":"Diou",
    "gn:population":0,
    "gn:timezone":"Africa/Bamako",
    "iso:country":"ML",
    "wof:name":"Diou",
    "wof:placetype":"locality"
},
  "geometry": {"coordinates":[-5.96667,10.58333],"type":"Point"}
}