{
  "type": "Feature",
  "properties": {
    "gn:admin1_code":"7.0",
    "gn:asciiname":"Bafotiguibougou",
    "gn:country_code":"ML",
    "gn:dem":325,
    "gn:feature_class":"P",
    "gn:feature_code":"PPL",
    "gn:name":"Bafotiguibougou",
    "gn:population":0,
    "gn:timezone":"Africa/Bamako",
    "iso:country":"ML",
    "wof:name":"Bafotiguibougou",
    "wof:placetype":"locality"
},
  "geometry": {"coordinates":[-7.15733,13.02652],"type":"Point"}
}