{
  "type": "Feature",
  "properties": {
    "gn:admin1_code":"7.0",
    "gn:asciiname":"Ngoma",
    "gn:country_code":"ML",
    "gn:dem":414,
    "gn:feature_class":"P",
    "gn:feature_code":"PPL",
    "gn:name":"Ngoma",
    "gn:population":0,
    "gn:timezone":"Africa/Bamako",
    "iso:country":"ML",
    "name:bar_x_preferred":[
        "Ngoma"
    ],
    "name:ceb_x_preferred":[
        "Ngoma"
    ],
    "name:deu_x_preferred":[
        "Ngoma"
    ],
    "name:est_x_preferred":[
        "Ngoma"
    ],
    "name:fra_x_preferred":[
        "Ngoma"
    ],
    "name:ita_x_preferred":[
        "Ngoma"
    ],
    "name:pol_x_preferred":[
        "Ngoma"
    ],
    "name:swa_x_preferred":[
        "Ngoma"
    ],
    "name:swe_x_preferred":[
        "Ngoma"
    ],
    "wof:name":"Ngoma",
    "wof:placetype":"locality"
},
  "geometry": {"coordinates":[-7.8881,13.84494],"type":"Point"}
}