{
  "type": "Feature",
  "properties": {
    "gn:admin1_code":"09",
    "gn:asciiname":"Zaguia",
    "gn:country_code":"ML",
    "gn:dem":261,
    "gn:feature_class":"P",
    "gn:feature_code":"PPL",
    "gn:name":"Zaguia",
    "gn:population":0,
    "gn:timezone":"Africa/Bamako",
    "iso:country":"ML",
    "wof:name":"Zaguia",
    "wof:placetype":"locality"
},
  "geometry": {"coordinates":[-1.41945,17.0197],"type":"Point"}
}