{
  "type": "Feature",
  "properties": {
    "gn:admin1_code":"7.0",
    "gn:asciiname":"Seloule Makandiana",
    "gn:country_code":"ML",
    "gn:dem":513,
    "gn:feature_class":"P",
    "gn:feature_code":"PPL",
    "gn:name":"S\u00e9loul\u00e9 Makandiana",
    "gn:population":0,
    "gn:timezone":"Africa/Bamako",
    "iso:country":"ML",
    "wof:name":"Seloule Makandiana",
    "wof:placetype":"locality"
},
  "geometry": {"coordinates":[-8.81467,12.44999],"type":"Point"}
}