{
  "type": "Feature",
  "properties": {
    "gn:admin1_code":"05",
    "gn:asciiname":"Bousse",
    "gn:country_code":"ML",
    "gn:dem":282,
    "gn:feature_class":"P",
    "gn:feature_code":"PPL",
    "gn:name":"Bouss\u00e9",
    "gn:population":0,
    "gn:timezone":"Africa/Bamako",
    "iso:country":"ML",
    "name:ceb_x_preferred":[
        "Bousse"
    ],
    "name:deu_x_preferred":[
        "Bousse"
    ],
    "name:fra_x_preferred":[
        "Bousse"
    ],
    "name:ita_x_preferred":[
        "Bousse"
    ],
    "name:nds_x_preferred":[
        "Bousse"
    ],
    "name:nld_x_preferred":[
        "Bousse"
    ],
    "name:oci_x_preferred":[
        "Bousse"
    ],
    "name:pol_x_preferred":[
        "Bousse"
    ],
    "name:por_x_preferred":[
        "Bousse"
    ],
    "name:ron_x_preferred":[
        "Bousse"
    ],
    "name:slk_x_preferred":[
        "Bousse"
    ],
    "name:spa_x_preferred":[
        "Bousse"
    ],
    "name:swe_x_preferred":[
        "Bousse"
    ],
    "name:ukr_x_preferred":[
        "\u0411\u0443\u0441\u0441"
    ],
    "name:und_x_variant":[
        "Busse",
        "Bouss\u00e9"
    ],
    "wof:name":"Bousse",
    "wof:placetype":"locality"
},
  "geometry": {"coordinates":[-5.93628,13.50594],"type":"Point"}
}