{
  "type": "Feature",
  "properties": {
    "gn:admin1_code":"00",
    "gn:asciiname":"Faraguele",
    "gn:country_code":"ML",
    "gn:dem":400,
    "gn:feature_class":"P",
    "gn:feature_code":"PPL",
    "gn:name":"Faragu\u00e9l\u00e9",
    "gn:population":0,
    "gn:timezone":"Africa/Bamako",
    "iso:country":"ML",
    "wof:name":"Faraguele",
    "wof:placetype":"locality"
},
  "geometry": {"coordinates":[-8.21667,10.63333],"type":"Point"}
}