{
  "type": "Feature",
  "properties": {
    "gn:admin1_code":"4.0",
    "gn:asciiname":"Doumbougou",
    "gn:country_code":"ML",
    "gn:dem":463,
    "gn:feature_class":"P",
    "gn:feature_code":"PPL",
    "gn:name":"Doumbougou",
    "gn:population":0,
    "gn:timezone":"Africa/Bamako",
    "iso:country":"ML",
    "wof:name":"Doumbougou",
    "wof:placetype":"locality"
},
  "geometry": {"coordinates":[-3.44463,14.43397],"type":"Point"}
}