{
  "type": "Feature",
  "properties": {
    "gn:admin1_code":"03",
    "gn:asciiname":"Samankidi",
    "gn:country_code":"ML",
    "gn:dem":43,
    "gn:feature_class":"P",
    "gn:feature_code":"PPL",
    "gn:name":"Samankidi",
    "gn:population":0,
    "gn:timezone":"Africa/Bamako",
    "iso:country":"ML",
    "wof:name":"Samankidi",
    "wof:placetype":"locality"
},
  "geometry": {"coordinates":[-11.60785,14.54674],"type":"Point"}
}