{
  "type": "Feature",
  "properties": {
    "gn:admin1_code":"06",
    "gn:asciiname":"Kian",
    "gn:country_code":"ML",
    "gn:dem":479,
    "gn:feature_class":"P",
    "gn:feature_code":"PPL",
    "gn:name":"Kian",
    "gn:population":0,
    "gn:timezone":"Africa/Bamako",
    "iso:country":"ML",
    "wof:name":"Kian",
    "wof:placetype":"locality"
},
  "geometry": {"coordinates":[-4.4211,12.3396],"type":"Point"}
}