{
  "type": "Feature",
  "properties": {
    "gn:admin1_code":"06",
    "gn:asciiname":"Kian",
    "gn:country_code":"ML",
    "gn:dem":479,
    "gn:feature_class":"P",
    "gn:feature_code":"PPL",
    "gn:name":"Kian",
    "gn:population":0,
    "gn:timezone":"Africa/Bamako",
    "iso:country":"ML",
    "name:ara_x_preferred":[
        "\u0645\u062f\u064a\u0646\u0629 \u0643\u064a\u0627\u0646"
    ],
    "name:aze_x_preferred":[
        "Kiyan"
    ],
    "name:fas_x_preferred":[
        "\u06a9\u06cc\u0627\u0646"
    ],
    "name:ita_x_preferred":[
        "Kian"
    ],
    "name:mlg_x_preferred":[
        "Kian"
    ],
    "name:msa_x_preferred":[
        "Shahr-e K\u012b\u0101n"
    ],
    "name:rus_x_preferred":[
        "\u041a\u0438\u0430\u043d"
    ],
    "name:tur_x_preferred":[
        "Kiyan"
    ],
    "name:urd_x_preferred":[
        "\u0634\u06c1\u0631 \u06a9\u06cc\u0627\u0646"
    ],
    "wof:name":"Kian",
    "wof:placetype":"locality"
},
  "geometry": {"coordinates":[-4.4211,12.3396],"type":"Point"}
}