{
  "type": "Feature",
  "properties": {
    "gn:admin1_code":"07",
    "gn:asciiname":"Ouassada",
    "gn:cc2":"ML",
    "gn:country_code":"ML",
    "gn:dem":345,
    "gn:feature_class":"P",
    "gn:feature_code":"PPL",
    "gn:name":"Ouassada",
    "gn:population":0,
    "gn:timezone":"Africa/Bamako",
    "iso:country":"ML",
    "name:und_x_variant":[
        "Wasada",
        "Ouassada"
    ],
    "wof:name":"Ouassada",
    "wof:placetype":"locality"
},
  "geometry": {"coordinates":[-8.36139,12.20806],"type":"Point"}
}