{
  "type": "Feature",
  "properties": {
    "gn:admin1_code":"04",
    "gn:asciiname":"Sare-Male",
    "gn:country_code":"ML",
    "gn:dem":272,
    "gn:feature_class":"P",
    "gn:feature_code":"PPL",
    "gn:name":"Sar\u00e9-Mal\u00e9",
    "gn:population":0,
    "gn:timezone":"Africa/Bamako",
    "iso:country":"ML",
    "name:und_x_variant":[
        "Sar\u00e9-Mar\u00e9",
        "Sar\u00e9-Mal\u00e9"
    ],
    "wof:name":"Sare-Male",
    "wof:placetype":"locality"
},
  "geometry": {"coordinates":[-4.42891,14.08757],"type":"Point"}
}