{
  "type": "Feature",
  "properties": {
    "gn:admin1_code":"07",
    "gn:asciiname":"Saranfouga",
    "gn:country_code":"ML",
    "gn:dem":361,
    "gn:feature_class":"P",
    "gn:feature_code":"PPL",
    "gn:name":"Saranfouga",
    "gn:population":0,
    "gn:timezone":"Africa/Bamako",
    "iso:country":"ML",
    "name:und_x_variant":[
        "Siranvoga",
        "Saranfouga"
    ],
    "wof:name":"Saranfouga",
    "wof:placetype":"locality"
},
  "geometry": {"coordinates":[-7.16448,13.55674],"type":"Point"}
}