{
  "type": "Feature",
  "properties": {
    "gn:admin1_code":"06",
    "gn:asciiname":"Zielabougou",
    "gn:country_code":"ML",
    "gn:dem":345,
    "gn:feature_class":"P",
    "gn:feature_code":"PPL",
    "gn:name":"Zi\u00e9labougou",
    "gn:population":0,
    "gn:timezone":"Africa/Bamako",
    "iso:country":"ML",
    "wof:name":"Zielabougou",
    "wof:placetype":"locality"
},
  "geometry": {"coordinates":[-7.79649,11.90861],"type":"Point"}
}