{
  "type": "Feature",
  "properties": {
    "gn:admin1_code":"03",
    "gn:asciiname":"Kanamakounou",
    "gn:country_code":"ML",
    "gn:dem":52,
    "gn:feature_class":"P",
    "gn:feature_code":"PPL",
    "gn:name":"Kanamakounou",
    "gn:population":0,
    "gn:timezone":"Africa/Bamako",
    "iso:country":"ML",
    "wof:name":"Kanamakounou",
    "wof:placetype":"locality"
},
  "geometry": {"coordinates":[-11.198,14.44791],"type":"Point"}
}