{
  "type": "Feature",
  "properties": {
    "gn:admin1_code":"06",
    "gn:asciiname":"Kongolikouo",
    "gn:country_code":"ML",
    "gn:dem":349,
    "gn:feature_class":"P",
    "gn:feature_code":"PPL",
    "gn:name":"Kongolikouo",
    "gn:population":0,
    "gn:timezone":"Africa/Bamako",
    "iso:country":"ML",
    "name:fra_x_preferred":[
        "Kougoulikoro"
    ],
    "name:und_x_variant":[
        "Kougoulikoro"
    ],
    "wof:name":"Kongolikouo",
    "wof:placetype":"locality"
},
  "geometry": {"coordinates":[-6.38649,11.6294],"type":"Point"}
}