{
  "type": "Feature",
  "properties": {
    "gn:admin1_code":"07",
    "gn:asciiname":"Falakono",
    "gn:country_code":"ML",
    "gn:dem":330,
    "gn:feature_class":"P",
    "gn:feature_code":"PPL",
    "gn:name":"Falakono",
    "gn:population":0,
    "gn:timezone":"Africa/Bamako",
    "iso:country":"ML",
    "name:und_x_variant":[
        "Talakoro",
        "Fala Koho",
        "Falakono"
    ],
    "wof:name":"Falakono",
    "wof:placetype":"locality"
},
  "geometry": {"coordinates":[-7.04693,12.38502],"type":"Point"}
}