{
  "type": "Feature",
  "properties": {
    "gn:admin1_code":"07",
    "gn:asciiname":"Tomekoro",
    "gn:country_code":"ML",
    "gn:dem":417,
    "gn:feature_class":"P",
    "gn:feature_code":"PPL",
    "gn:name":"Tom\u00e9koro",
    "gn:population":0,
    "gn:timezone":"Africa/Bamako",
    "iso:country":"ML",
    "name:fra_x_preferred":[
        "Tom\u00e9koro"
    ],
    "wof:name":"Tomekoro",
    "wof:placetype":"locality"
},
  "geometry": {"coordinates":[-8.1878,13.5888],"type":"Point"}
}