{
  "type": "Feature",
  "properties": {
    "gn:admin1_code":"03",
    "gn:asciiname":"Koriga",
    "gn:country_code":"ML",
    "gn:dem":231,
    "gn:feature_class":"P",
    "gn:feature_code":"PPL",
    "gn:name":"Koriga",
    "gn:population":0,
    "gn:timezone":"Africa/Bamako",
    "iso:country":"ML",
    "wof:name":"Koriga",
    "wof:placetype":"locality"
},
  "geometry": {"coordinates":[-9.92213,15.37454],"type":"Point"}
}