{
  "type": "Feature",
  "properties": {
    "gn:admin1_code":"7.0",
    "gn:asciiname":"Makonobougou",
    "gn:country_code":"ML",
    "gn:dem":334,
    "gn:feature_class":"P",
    "gn:feature_code":"PPL",
    "gn:name":"Makonobougou",
    "gn:population":0,
    "gn:timezone":"Africa/Bamako",
    "iso:country":"ML",
    "wof:name":"Makonobougou",
    "wof:placetype":"locality"
},
  "geometry": {"coordinates":[-7.19487,12.51238],"type":"Point"}
}