{
  "type": "Feature",
  "properties": {
    "gn:admin1_code":"06",
    "gn:asciiname":"Nimmsila",
    "gn:country_code":"ML",
    "gn:dem":367,
    "gn:feature_class":"P",
    "gn:feature_code":"PPL",
    "gn:name":"Nimmsila",
    "gn:population":0,
    "gn:timezone":"Africa/Bamako",
    "iso:country":"ML",
    "name:und_x_variant":[
        "Nimssila",
        "Nimsila",
        "Nimmsila"
    ],
    "wof:name":"Nimmsila",
    "wof:placetype":"locality"
},
  "geometry": {"coordinates":[-7.57336,11.17237],"type":"Point"}
}