{
  "type": "Feature",
  "properties": {
    "gn:admin1_code":"07",
    "gn:asciiname":"Nyinyan-Dyawara",
    "gn:country_code":"ML",
    "gn:dem":274,
    "gn:feature_class":"P",
    "gn:feature_code":"PPL",
    "gn:name":"Nyinyan-Dyawara",
    "gn:population":0,
    "gn:timezone":"Africa/Bamako",
    "iso:country":"ML",
    "wof:name":"Nyinyan-Dyawara",
    "wof:placetype":"locality"
},
  "geometry": {"coordinates":[-8.442,14.8944],"type":"Point"}
}