{
  "type": "Feature",
  "properties": {
    "gn:admin1_code":"5.0",
    "gn:asciiname":"Makerela",
    "gn:country_code":"ML",
    "gn:dem":286,
    "gn:feature_class":"P",
    "gn:feature_code":"PPL",
    "gn:name":"Mak\u00e9r\u00e9la",
    "gn:population":0,
    "gn:timezone":"Africa/Bamako",
    "iso:country":"ML",
    "name:und_x_variant":[
        "Famaga",
        "Mak\u00e9r\u00e9la"
    ],
    "wof:name":"Makerela",
    "wof:placetype":"locality"
},
  "geometry": {"coordinates":[-5.84073,13.84055],"type":"Point"}
}