{
  "type": "Feature",
  "properties": {
    "gn:admin1_code":"03",
    "gn:asciiname":"Mamba",
    "gn:country_code":"ML",
    "gn:dem":530,
    "gn:feature_class":"P",
    "gn:feature_code":"PPL",
    "gn:name":"Mamba",
    "gn:population":0,
    "gn:timezone":"Africa/Bamako",
    "iso:country":"ML",
    "name:und_x_variant":[
        "Manba",
        "Mamba"
    ],
    "wof:name":"Mamba",
    "wof:placetype":"locality"
},
  "geometry": {"coordinates":[-11.15463,12.73127],"type":"Point"}
}