{
  "type": "Feature",
  "properties": {
    "gn:admin1_code":"03",
    "gn:asciiname":"Mamba",
    "gn:country_code":"ML",
    "gn:dem":530,
    "gn:feature_class":"P",
    "gn:feature_code":"PPL",
    "gn:name":"Mamba",
    "gn:population":0,
    "gn:timezone":"Africa/Bamako",
    "iso:country":"ML",
    "name:afr_x_preferred":[
        "Mamba"
    ],
    "name:ara_x_preferred":[
        "\u0645\u0627\u0645\u0628\u0627"
    ],
    "name:ast_x_preferred":[
        "Dendroaspis"
    ],
    "name:bul_x_preferred":[
        "\u041c\u0430\u043c\u0431\u0438"
    ],
    "name:cat_x_preferred":[
        "Mamba"
    ],
    "name:ceb_x_preferred":[
        "Dendroaspis"
    ],
    "name:ces_x_preferred":[
        "Mamba"
    ],
    "name:dan_x_preferred":[
        "Mamba"
    ],
    "name:deu_x_preferred":[
        "Mambas"
    ],
    "name:est_x_preferred":[
        "Mamba"
    ],
    "name:eus_x_preferred":[
        "Dendroaspis"
    ],
    "name:fas_x_preferred":[
        "\u0645\u0627\u0645\u0628\u0627"
    ],
    "name:fin_x_preferred":[
        "Mambat"
    ],
    "name:fra_x_preferred":[
        "Dendroaspis"
    ],
    "name:heb_x_preferred":[
        "\u05de\u05de\u05d1\u05d4"
    ],
    "name:hin_x_preferred":[
        "\u092e\u093e\u092e\u094d\u092c\u093e"
    ],
    "name:hrv_x_preferred":[
        "Mambe"
    ],
    "name:ind_x_preferred":[
        "Mamba"
    ],
    "name:ita_x_preferred":[
        "Dendroaspis"
    ],
    "name:jpn_x_preferred":[
        "\u30de\u30f3\u30d0\u5c5e"
    ],
    "name:kan_x_preferred":[
        "\u0cae\u0cbe\u0c82\u0cac\u0cbe"
    ],
    "name:kat_x_preferred":[
        "\u10db\u10d0\u10db\u10d1\u10d0"
    ],
    "name:kaz_x_preferred":[
        "\u041c\u0430\u043c\u0431\u0430\u043b\u0430\u0440"
    ],
    "name:kir_x_preferred":[
        "\u041c\u0430\u043c\u0431\u0430\u043b\u0430\u0440"
    ],
    "name:lit_x_preferred":[
        "Mambos"
    ],
    "name:nld_x_preferred":[
        "Mamba's"
    ],
    "name:nor_x_preferred":[
        "Mambaer"
    ],
    "name:pol_x_preferred":[
        "Dendroaspis"
    ],
    "name:por_x_preferred":[
        "Mamba"
    ],
    "name:ron_x_preferred":[
        "Mamba"
    ],
    "name:rus_x_preferred":[
        "\u041c\u0430\u043c\u0431\u044b"
    ],
    "name:slk_x_preferred":[
        "Mamba"
    ],
    "name:spa_x_preferred":[
        "Dendroaspis"
    ],
    "name:srp_x_preferred":[
        "Mamba"
    ],
    "name:swa_x_preferred":[
        "Hongo"
    ],
    "name:swe_x_preferred":[
        "Mambor"
    ],
    "name:tam_x_preferred":[
        "\u0bae\u0bbe\u0bae\u0bcd\u0baa\u0bbe"
    ],
    "name:tha_x_preferred":[
        "\u0e07\u0e39\u0e41\u0e21\u0e21\u0e1a\u0e32"
    ],
    "name:ukr_x_preferred":[
        "\u041c\u0430\u043c\u0431\u0430"
    ],
    "name:und_x_variant":[
        "Manba"
    ],
    "name:vie_x_preferred":[
        "R\u1eafn mamba"
    ],
    "name:war_x_preferred":[
        "Dendroaspis"
    ],
    "name:zho_x_preferred":[
        "\u66fc\u5df4\u86c7\u5c6c"
    ],
    "wof:name":"Mamba",
    "wof:placetype":"locality"
},
  "geometry": {"coordinates":[-11.15463,12.73127],"type":"Point"}
}