{
  "type": "Feature",
  "properties": {
    "gn:admin1_code":"5.0",
    "gn:asciiname":"Ngosso",
    "gn:country_code":"ML",
    "gn:dem":294,
    "gn:feature_class":"P",
    "gn:feature_code":"PPL",
    "gn:name":"Ngosso",
    "gn:population":0,
    "gn:timezone":"Africa/Bamako",
    "iso:country":"ML",
    "wof:name":"Ngosso",
    "wof:placetype":"locality"
},
  "geometry": {"coordinates":[-5.10986,13.05072],"type":"Point"}
}