{
  "type": "Feature",
  "properties": {
    "gn:admin1_code":"7.0",
    "gn:asciiname":"Kamalo",
    "gn:country_code":"ML",
    "gn:dem":378,
    "gn:feature_class":"P",
    "gn:feature_code":"PPL",
    "gn:name":"Kamalo",
    "gn:population":0,
    "gn:timezone":"Africa/Bamako",
    "iso:country":"ML",
    "wof:name":"Kamalo",
    "wof:placetype":"locality"
},
  "geometry": {"coordinates":[-8.47687,12.22549],"type":"Point"}
}