{
  "type": "Feature",
  "properties": {
    "gn:admin1_code":"06",
    "gn:asciiname":"Sirakoroba",
    "gn:country_code":"ML",
    "gn:dem":336,
    "gn:feature_class":"P",
    "gn:feature_code":"PPL",
    "gn:name":"Sirakoroba",
    "gn:population":0,
    "gn:timezone":"Africa/Bamako",
    "iso:country":"ML",
    "name:fra_x_preferred":[
        "Sirakoroba"
    ],
    "name:fra_x_variant":[
        "Sirakoro",
        "Sikoro"
    ],
    "name:und_x_variant":[
        "Sirakoro",
        "Sikoro"
    ],
    "wof:name":"Sirakoroba",
    "wof:placetype":"locality"
},
  "geometry": {"coordinates":[-6.22694,11.30756],"type":"Point"}
}