{
  "type": "Feature",
  "properties": {
    "gn:admin1_code":"05",
    "gn:asciiname":"Misala",
    "gn:country_code":"ML",
    "gn:dem":319,
    "gn:feature_class":"P",
    "gn:feature_code":"PPL",
    "gn:name":"Misala",
    "gn:population":0,
    "gn:timezone":"Africa/Bamako",
    "iso:country":"ML",
    "name:fra_x_preferred":[
        "Missala"
    ],
    "name:fra_x_variant":[
        "Messala"
    ],
    "name:und_x_variant":[
        "Misala"
    ],
    "wof:name":"Misala",
    "wof:placetype":"locality"
},
  "geometry": {"coordinates":[-6.11914,12.82356],"type":"Point"}
}