{
  "type": "Feature",
  "properties": {
    "gn:admin1_code":"06",
    "gn:asciiname":"Diero",
    "gn:country_code":"ML",
    "gn:dem":336,
    "gn:feature_class":"P",
    "gn:feature_code":"PPL",
    "gn:name":"Di\u00e9ro",
    "gn:population":0,
    "gn:timezone":"Africa/Bamako",
    "iso:country":"ML",
    "wof:name":"Diero",
    "wof:placetype":"locality"
},
  "geometry": {"coordinates":[-7.04396,11.94811],"type":"Point"}
}