{
  "type": "Feature",
  "properties": {
    "gn:admin1_code":"06",
    "gn:asciiname":"Koumala",
    "gn:country_code":"ML",
    "gn:dem":317,
    "gn:feature_class":"P",
    "gn:feature_code":"PPL",
    "gn:name":"Koumala",
    "gn:population":0,
    "gn:timezone":"Africa/Bamako",
    "iso:country":"ML",
    "name:und_x_variant":[
        "Koumbala",
        "Koumala"
    ],
    "wof:name":"Koumala",
    "wof:placetype":"locality"
},
  "geometry": {"coordinates":[-5.42244,11.70984],"type":"Point"}
}