{
  "type": "Feature",
  "properties": {
    "gn:admin1_code":"03",
    "gn:asciiname":"Yilimalo",
    "gn:country_code":"ML",
    "gn:dem":170,
    "gn:feature_class":"P",
    "gn:feature_code":"PPL",
    "gn:name":"Yilimalo",
    "gn:population":0,
    "gn:timezone":"Africa/Bamako",
    "iso:country":"ML",
    "name:und_x_variant":[
        "Ilimalo",
        "Yilimalo"
    ],
    "wof:name":"Yilimalo",
    "wof:placetype":"locality"
},
  "geometry": {"coordinates":[-11.43847,12.35288],"type":"Point"}
}