{
  "type": "Feature",
  "properties": {
    "gn:admin1_code":"08",
    "gn:asciiname":"Nyambourgou",
    "gn:country_code":"ML",
    "gn:dem":265,
    "gn:feature_class":"P",
    "gn:feature_code":"PPL",
    "gn:name":"Nyambourgou",
    "gn:population":0,
    "gn:timezone":"Africa/Bamako",
    "iso:country":"ML",
    "name:und_x_variant":[
        "Niambougou",
        "Nyambourgou"
    ],
    "wof:name":"Nyambourgou",
    "wof:placetype":"locality"
},
  "geometry": {"coordinates":[-3.44903,16.53834],"type":"Point"}
}