{
  "type": "Feature",
  "properties": {
    "gn:admin1_code":"6.0",
    "gn:asciiname":"Zorona",
    "gn:country_code":"ML",
    "gn:dem":323,
    "gn:feature_class":"P",
    "gn:feature_code":"PPL",
    "gn:name":"Zorona",
    "gn:population":0,
    "gn:timezone":"Africa/Bamako",
    "iso:country":"ML",
    "wof:name":"Zorona",
    "wof:placetype":"locality"
},
  "geometry": {"coordinates":[-6.66332,11.08323],"type":"Point"}
}