{
  "type": "Feature",
  "properties": {
    "gn:admin1_code":"03",
    "gn:asciiname":"Sitahoro",
    "gn:country_code":"ML",
    "gn:dem":82,
    "gn:feature_class":"P",
    "gn:feature_code":"PPL",
    "gn:name":"Sitahoro",
    "gn:population":0,
    "gn:timezone":"Africa/Bamako",
    "iso:country":"ML",
    "wof:name":"Sitahoro",
    "wof:placetype":"locality"
},
  "geometry": {"coordinates":[-11.34994,14.24573],"type":"Point"}
}