{
  "type": "Feature",
  "properties": {
    "gn:admin1_code":"06",
    "gn:asciiname":"Faradiele",
    "gn:country_code":"ML",
    "gn:dem":346,
    "gn:feature_class":"P",
    "gn:feature_code":"PPL",
    "gn:name":"Faradi\u00e9l\u00e9",
    "gn:population":0,
    "gn:timezone":"Africa/Bamako",
    "iso:country":"ML",
    "name:fin_x_preferred":[
        "Faradi\u00e9l\u00e9"
    ],
    "name:fra_x_preferred":[
        "Faradi\u00e9l\u00e9"
    ],
    "name:ita_x_preferred":[
        "Faradi\u00e9l\u00e9"
    ],
    "name:nld_x_preferred":[
        "Faradi\u00e9l\u00e9"
    ],
    "name:spa_x_preferred":[
        "Faradiele"
    ],
    "name:und_x_variant":[
        "Faradi\u00e9l\u00e9"
    ],
    "wof:name":"Faradiele",
    "wof:placetype":"locality"
},
  "geometry": {"coordinates":[-7.63622,11.34786],"type":"Point"}
}