{
  "type": "Feature",
  "properties": {
    "gn:admin1_code":"08",
    "gn:asciiname":"Kessou-Indyar",
    "gn:country_code":"ML",
    "gn:dem":269,
    "gn:feature_class":"P",
    "gn:feature_code":"PPL",
    "gn:name":"Kessou-Indyar",
    "gn:population":0,
    "gn:timezone":"Africa/Bamako",
    "iso:country":"ML",
    "wof:name":"Kessou-Indyar",
    "wof:placetype":"locality"
},
  "geometry": {"coordinates":[-3.2688,16.51161],"type":"Point"}
}