{
  "type": "Feature",
  "properties": {
    "gn:admin1_code":"03",
    "gn:asciiname":"Savane",
    "gn:country_code":"ML",
    "gn:dem":205,
    "gn:feature_class":"P",
    "gn:feature_code":"PPL",
    "gn:name":"Savan\u00e9",
    "gn:population":0,
    "gn:timezone":"Africa/Bamako",
    "iso:country":"ML",
    "name:ceb_x_preferred":[
        "Savane"
    ],
    "name:fra_x_preferred":[
        "Savane"
    ],
    "name:spa_x_preferred":[
        "Savane"
    ],
    "name:swe_x_preferred":[
        "Savane"
    ],
    "wof:name":"Savane",
    "wof:placetype":"locality"
},
  "geometry": {"coordinates":[-10.0288,14.2529],"type":"Point"}
}