{
  "type": "Feature",
  "properties": {
    "gn:admin1_code":"8.0",
    "gn:asciiname":"Agaminan-Taoussa",
    "gn:country_code":"ML",
    "gn:dem":264,
    "gn:feature_class":"P",
    "gn:feature_code":"PPL",
    "gn:name":"Agaminan-Taoussa",
    "gn:population":0,
    "gn:timezone":"Africa/Bamako",
    "iso:country":"ML",
    "name:und_x_variant":[
        "Taoussa",
        "Agaminan-Taoussa"
    ],
    "wof:name":"Agaminan-Taoussa",
    "wof:placetype":"locality"
},
  "geometry": {"coordinates":[-3.18158,16.4123],"type":"Point"}
}