{
  "type": "Feature",
  "properties": {
    "gn:admin1_code":"03",
    "gn:asciiname":"Toumboundala",
    "gn:country_code":"ML",
    "gn:dem":348,
    "gn:feature_class":"P",
    "gn:feature_code":"PPL",
    "gn:name":"Toumboundala",
    "gn:population":0,
    "gn:timezone":"Africa/Bamako",
    "iso:country":"ML",
    "name:und_x_variant":[
        "Toumoundala",
        "Toumboundala"
    ],
    "wof:name":"Toumboundala",
    "wof:placetype":"locality"
},
  "geometry": {"coordinates":[-9.48635,13.06849],"type":"Point"}
}