{
  "type": "Feature",
  "properties": {
    "gn:admin1_code":"03",
    "gn:asciiname":"Kougola",
    "gn:country_code":"ML",
    "gn:dem":145,
    "gn:feature_class":"P",
    "gn:feature_code":"PPL",
    "gn:name":"Kougola",
    "gn:population":0,
    "gn:timezone":"Africa/Bamako",
    "iso:country":"ML",
    "wof:name":"Kougola",
    "wof:placetype":"locality"
},
  "geometry": {"coordinates":[-11.19699,12.88306],"type":"Point"}
}