{
  "type": "Feature",
  "properties": {
    "gn:admin1_code":"04",
    "gn:asciiname":"Kende",
    "gn:country_code":"ML",
    "gn:dem":267,
    "gn:feature_class":"P",
    "gn:feature_code":"PPL",
    "gn:name":"Kend\u00e9",
    "gn:population":0,
    "gn:timezone":"Africa/Bamako",
    "iso:country":"ML",
    "name:fin_x_preferred":[
        "Kend\u00e9"
    ],
    "name:fra_x_preferred":[
        "Kend\u00e9"
    ],
    "name:ita_x_preferred":[
        "Kend\u00e9"
    ],
    "name:nld_x_preferred":[
        "Kend\u00e9"
    ],
    "name:spa_x_preferred":[
        "Kend\u00e9"
    ],
    "wof:name":"Kende",
    "wof:placetype":"locality"
},
  "geometry": {"coordinates":[-4.13767,14.72621],"type":"Point"}
}