{
  "type": "Feature",
  "properties": {
    "gn:admin1_code":"00",
    "gn:asciiname":"Foroko",
    "gn:country_code":"ML",
    "gn:dem":390,
    "gn:feature_class":"P",
    "gn:feature_code":"PPL",
    "gn:name":"Foroko",
    "gn:population":0,
    "gn:timezone":"Africa/Bamako",
    "iso:country":"ML",
    "wof:name":"Foroko",
    "wof:placetype":"locality"
},
  "geometry": {"coordinates":[-8.56667,11.66667],"type":"Point"}
}