{
  "type": "Feature",
  "properties": {
    "gn:admin1_code":"03",
    "gn:asciiname":"Somone",
    "gn:country_code":"ML",
    "gn:dem":34,
    "gn:feature_class":"P",
    "gn:feature_code":"PPL",
    "gn:name":"Somon\u00e9",
    "gn:population":0,
    "gn:timezone":"Africa/Bamako",
    "iso:country":"ML",
    "wof:name":"Somone",
    "wof:placetype":"locality"
},
  "geometry": {"coordinates":[-11.86251,14.60796],"type":"Point"}
}