{
  "type": "Feature",
  "properties": {
    "gn:admin1_code":"06",
    "gn:asciiname":"Tieoulena",
    "gn:country_code":"ML",
    "gn:dem":373,
    "gn:feature_class":"P",
    "gn:feature_code":"PPL",
    "gn:name":"Ti\u00e9oul\u00e9na",
    "gn:population":0,
    "gn:timezone":"Africa/Bamako",
    "iso:country":"ML",
    "wof:name":"Tieoulena",
    "wof:placetype":"locality"
},
  "geometry": {"coordinates":[-7.95252,11.13084],"type":"Point"}
}