{
  "type": "Feature",
  "properties": {
    "gn:admin1_code":"06",
    "gn:asciiname":"Tiondougou Konlondie",
    "gn:country_code":"ML",
    "gn:dem":355,
    "gn:feature_class":"P",
    "gn:feature_code":"PPL",
    "gn:name":"Tiondougou Konlondi\u00e9",
    "gn:population":0,
    "gn:timezone":"Africa/Bamako",
    "iso:country":"ML",
    "name:und_x_variant":[
        "Tiondougou Kolondi\u00e9",
        "Tiondougou Konlondi\u00e9"
    ],
    "wof:name":"Tiondougou Konlondie",
    "wof:placetype":"locality"
},
  "geometry": {"coordinates":[-7.27666,11.22284],"type":"Point"}
}