{
  "type": "Feature",
  "properties": {
    "gn:admin1_code":"07",
    "gn:asciiname":"Gueleba",
    "gn:country_code":"ML",
    "gn:dem":340,
    "gn:feature_class":"P",
    "gn:feature_code":"PPL",
    "gn:name":"Gu\u00e9l\u00e9ba",
    "gn:population":0,
    "gn:timezone":"Africa/Bamako",
    "iso:country":"ML",
    "name:und_x_variant":[
        "G\u00e9l\u00e9ba",
        "Gu\u00e9l\u00e9ba"
    ],
    "wof:name":"Gueleba",
    "wof:placetype":"locality"
},
  "geometry": {"coordinates":[-8.29167,12.08525],"type":"Point"}
}