{
  "type": "Feature",
  "properties": {
    "gn:admin1_code":"07",
    "gn:asciiname":"Disila",
    "gn:country_code":"ML",
    "gn:dem":336,
    "gn:feature_class":"P",
    "gn:feature_code":"PPL",
    "gn:name":"Disila",
    "gn:population":0,
    "gn:timezone":"Africa/Bamako",
    "iso:country":"ML",
    "name:und_x_variant":[
        "Dissila",
        "Disila"
    ],
    "wof:name":"Disila",
    "wof:placetype":"locality"
},
  "geometry": {"coordinates":[-8.3572,14.3117],"type":"Point"}
}