{
  "type": "Feature",
  "properties": {
    "gn:admin1_code":"05",
    "gn:asciiname":"Korola",
    "gn:country_code":"ML",
    "gn:dem":279,
    "gn:feature_class":"P",
    "gn:feature_code":"PPL",
    "gn:name":"Korola",
    "gn:population":0,
    "gn:timezone":"Africa/Bamako",
    "iso:country":"ML",
    "name:und_x_variant":[
        "Kouroro",
        "Kourourou",
        "Korola"
    ],
    "wof:name":"Korola",
    "wof:placetype":"locality"
},
  "geometry": {"coordinates":[-4.5191,13.4522],"type":"Point"}
}