{
  "type": "Feature",
  "properties": {
    "gn:admin1_code":"07",
    "gn:asciiname":"Iraghoule",
    "gn:country_code":"ML",
    "gn:dem":314,
    "gn:feature_class":"P",
    "gn:feature_code":"PPL",
    "gn:name":"Iraghoul\u00e9",
    "gn:population":0,
    "gn:timezone":"Africa/Bamako",
    "iso:country":"ML",
    "name:und_x_variant":[
        "Irarhoul\u00e9",
        "Iraghoul\u00e9"
    ],
    "wof:name":"Iraghoule",
    "wof:placetype":"locality"
},
  "geometry": {"coordinates":[-7.4114,14.5249],"type":"Point"}
}