{
  "type": "Feature",
  "properties": {
    "gn:admin1_code":"07",
    "gn:asciiname":"Bougoula",
    "gn:country_code":"ML",
    "gn:dem":313,
    "gn:feature_class":"P",
    "gn:feature_code":"PPL",
    "gn:name":"Bougoula",
    "gn:population":0,
    "gn:timezone":"Africa/Bamako",
    "iso:country":"ML",
    "name:fra_x_preferred":[
        "Bougoula"
    ],
    "name:ita_x_preferred":[
        "Bougoula"
    ],
    "name:nld_x_preferred":[
        "Bougoula"
    ],
    "name:por_x_preferred":[
        "Bugula"
    ],
    "wof:name":"Bougoula",
    "wof:placetype":"locality"
},
  "geometry": {"coordinates":[-6.1737,12.34],"type":"Point"}
}