{
  "type": "Feature",
  "properties": {
    "gn:admin1_code":"03",
    "gn:asciiname":"Nembere",
    "gn:country_code":"ML",
    "gn:dem":301,
    "gn:feature_class":"P",
    "gn:feature_code":"PPL",
    "gn:name":"Nemb\u00e8r\u00e8",
    "gn:population":0,
    "gn:timezone":"Africa/Bamako",
    "iso:country":"ML",
    "name:und_x_variant":[
        "Ninb\u00e9r\u00e9",
        "Nemb\u00e8r\u00e8"
    ],
    "wof:name":"Nembere",
    "wof:placetype":"locality"
},
  "geometry": {"coordinates":[-9.9402,13.0798],"type":"Point"}
}