{
  "type": "Feature",
  "properties": {
    "gn:admin1_code":"9.0",
    "gn:asciiname":"Bandiende",
    "gn:country_code":"ML",
    "gn:dem":268,
    "gn:feature_class":"P",
    "gn:feature_code":"PPL",
    "gn:name":"Bandi\u00e8nd\u00e9",
    "gn:population":0,
    "gn:timezone":"Africa/Bamako",
    "iso:country":"ML",
    "wof:name":"Bandiende",
    "wof:placetype":"locality"
},
  "geometry": {"coordinates":[-0.24028,16.59167],"type":"Point"}
}