{
  "type": "Feature",
  "properties": {
    "gn:admin1_code":"6.0",
    "gn:asciiname":"Kokala",
    "gn:country_code":"ML",
    "gn:dem":319,
    "gn:feature_class":"P",
    "gn:feature_code":"PPL",
    "gn:name":"Kokala",
    "gn:population":0,
    "gn:timezone":"Africa/Bamako",
    "iso:country":"ML",
    "wof:name":"Kokala",
    "wof:placetype":"locality"
},
  "geometry": {"coordinates":[-7.17372,12.0715],"type":"Point"}
}