{
  "type": "Feature",
  "properties": {
    "gn:admin1_code":"05",
    "gn:asciiname":"Sola",
    "gn:country_code":"ML",
    "gn:dem":309,
    "gn:feature_class":"P",
    "gn:feature_code":"PPL",
    "gn:name":"Sola",
    "gn:population":0,
    "gn:timezone":"Africa/Bamako",
    "iso:country":"ML",
    "name:fra_x_preferred":[
        "Sola"
    ],
    "name:fra_x_variant":[
        "Siola",
        "Sala"
    ],
    "name:und_x_variant":[
        "Sala",
        "Siola"
    ],
    "wof:name":"Sola",
    "wof:placetype":"locality"
},
  "geometry": {"coordinates":[-6.21243,12.95316],"type":"Point"}
}