{
  "type": "Feature",
  "properties": {
    "gn:admin1_code":"6.0",
    "gn:asciiname":"Miabougou",
    "gn:country_code":"ML",
    "gn:dem":318,
    "gn:feature_class":"P",
    "gn:feature_code":"PPL",
    "gn:name":"Miabougou",
    "gn:population":0,
    "gn:timezone":"Africa/Bamako",
    "iso:country":"ML",
    "wof:name":"Miabougou",
    "wof:placetype":"locality"
},
  "geometry": {"coordinates":[-6.50147,11.36168],"type":"Point"}
}