{
  "type": "Feature",
  "properties": {
    "gn:admin1_code":"05",
    "gn:asciiname":"Somasso",
    "gn:country_code":"ML",
    "gn:dem":289,
    "gn:feature_class":"P",
    "gn:feature_code":"PPL",
    "gn:name":"Somasso",
    "gn:population":0,
    "gn:timezone":"Africa/Bamako",
    "iso:country":"ML",
    "name:fin_x_preferred":[
        "Somasso"
    ],
    "name:fra_x_preferred":[
        "Somasso"
    ],
    "name:ita_x_preferred":[
        "Somasso"
    ],
    "name:nld_x_preferred":[
        "Somasso"
    ],
    "name:spa_x_preferred":[
        "Somasso"
    ],
    "name:und_x_variant":[
        "Samasso"
    ],
    "wof:name":"Somasso",
    "wof:placetype":"locality"
},
  "geometry": {"coordinates":[-5.60319,12.87291],"type":"Point"}
}