{
  "type": "Feature",
  "properties": {
    "gn:admin1_code":"00",
    "gn:asciiname":"Sitakoto",
    "gn:country_code":"ML",
    "gn:dem":410,
    "gn:feature_class":"P",
    "gn:feature_code":"PPL",
    "gn:name":"Sitakoto",
    "gn:population":0,
    "gn:timezone":"Africa/Bamako",
    "iso:country":"ML",
    "wof:name":"Sitakoto",
    "wof:placetype":"locality"
},
  "geometry": {"coordinates":[-9.71667,12.56667],"type":"Point"}
}