{
  "type": "Feature",
  "properties": {
    "gn:admin1_code":"07",
    "gn:asciiname":"Tchekon",
    "gn:country_code":"ML",
    "gn:dem":318,
    "gn:feature_class":"P",
    "gn:feature_code":"PPL",
    "gn:name":"Tch\u00e9kon",
    "gn:population":0,
    "gn:timezone":"Africa/Bamako",
    "iso:country":"ML",
    "wof:name":"Tchekon",
    "wof:placetype":"locality"
},
  "geometry": {"coordinates":[-7.798,14.1963],"type":"Point"}
}