{
  "type": "Feature",
  "properties": {
    "gn:admin1_code":"07",
    "gn:asciiname":"Seribougou",
    "gn:country_code":"ML",
    "gn:dem":337,
    "gn:feature_class":"P",
    "gn:feature_code":"PPL",
    "gn:name":"S\u00e9ribougou",
    "gn:population":0,
    "gn:timezone":"Africa/Bamako",
    "iso:country":"ML",
    "name:fra_x_preferred":[
        "S\u00e9ribougou"
    ],
    "wof:name":"Seribougou",
    "wof:placetype":"locality"
},
  "geometry": {"coordinates":[-8.1903,13.7609],"type":"Point"}
}