{
  "type": "Feature",
  "properties": {
    "gn:admin1_code":"06",
    "gn:asciiname":"Tabakoro",
    "gn:country_code":"ML",
    "gn:dem":334,
    "gn:feature_class":"P",
    "gn:feature_code":"PPL",
    "gn:name":"Tabakoro",
    "gn:population":0,
    "gn:timezone":"Africa/Bamako",
    "iso:country":"ML",
    "name:fra_x_preferred":[
        "Tabakoro"
    ],
    "wof:name":"Tabakoro",
    "wof:placetype":"locality"
},
  "geometry": {"coordinates":[-6.78621,11.42822],"type":"Point"}
}