{
  "type": "Feature",
  "properties": {
    "gn:admin1_code":"5.0",
    "gn:asciiname":"Noumousa",
    "gn:country_code":"ML",
    "gn:dem":317,
    "gn:feature_class":"P",
    "gn:feature_code":"PPL",
    "gn:name":"Noumousa",
    "gn:population":0,
    "gn:timezone":"Africa/Bamako",
    "iso:country":"ML",
    "wof:name":"Noumousa",
    "wof:placetype":"locality"
},
  "geometry": {"coordinates":[-6.7007,12.953],"type":"Point"}
}