{
  "type": "Feature",
  "properties": {
    "gn:admin1_code":"05",
    "gn:asciiname":"Saaba",
    "gn:country_code":"ML",
    "gn:dem":354,
    "gn:feature_class":"P",
    "gn:feature_code":"PPL",
    "gn:name":"Saaba",
    "gn:population":0,
    "gn:timezone":"Africa/Bamako",
    "iso:country":"ML",
    "wof:name":"Saaba",
    "wof:placetype":"locality"
},
  "geometry": {"coordinates":[-4.2298,13.5806],"type":"Point"}
}