{
  "type": "Feature",
  "properties": {
    "gn:admin1_code":"05",
    "gn:asciiname":"Woniongosso",
    "gn:country_code":"ML",
    "gn:dem":296,
    "gn:feature_class":"P",
    "gn:feature_code":"PPL",
    "gn:name":"Woniongosso",
    "gn:population":0,
    "gn:timezone":"Africa/Bamako",
    "iso:country":"ML",
    "wof:name":"Woniongosso",
    "wof:placetype":"locality"
},
  "geometry": {"coordinates":[-4.9497,13.0417],"type":"Point"}
}