{
  "type": "Feature",
  "properties": {
    "gn:admin1_code":"3.0",
    "gn:asciiname":"Bleinti",
    "gn:country_code":"ML",
    "gn:dem":290,
    "gn:feature_class":"P",
    "gn:feature_code":"PPL",
    "gn:name":"Ble\u00efnti",
    "gn:population":0,
    "gn:timezone":"Africa/Bamako",
    "iso:country":"ML",
    "wof:name":"Bleinti",
    "wof:placetype":"locality"
},
  "geometry": {"coordinates":[-9.2724,14.8724],"type":"Point"}
}