{
  "type": "Feature",
  "properties": {
    "gn:admin1_code":"7.0",
    "gn:asciiname":"Bamarobougou",
    "gn:country_code":"ML",
    "gn:dem":397,
    "gn:feature_class":"P",
    "gn:feature_code":"PPL",
    "gn:name":"Bamarobougou",
    "gn:population":0,
    "gn:timezone":"Africa/Bamako",
    "iso:country":"ML",
    "wof:name":"Bamarobougou",
    "wof:placetype":"locality"
},
  "geometry": {"coordinates":[-7.58776,13.48392],"type":"Point"}
}