{
  "type": "Feature",
  "properties": {
    "gn:admin1_code":"05",
    "gn:asciiname":"Kamona",
    "gn:country_code":"ML",
    "gn:dem":297,
    "gn:feature_class":"P",
    "gn:feature_code":"PPL",
    "gn:name":"Kamona",
    "gn:population":0,
    "gn:timezone":"Africa/Bamako",
    "iso:country":"ML",
    "name:ben_x_preferred":[
        "\u0995\u09be\u09ae\u09a8\u09be"
    ],
    "name:und_x_variant":[
        "Kamouna",
        "Kamona"
    ],
    "wof:name":"Kamona",
    "wof:placetype":"locality"
},
  "geometry": {"coordinates":[-5.70962,12.87356],"type":"Point"}
}