{
  "type": "Feature",
  "properties": {
    "gn:admin1_code":"03",
    "gn:asciiname":"Diabessamou",
    "gn:country_code":"ML",
    "gn:dem":135,
    "gn:feature_class":"P",
    "gn:feature_code":"PPL",
    "gn:name":"Diabessamou",
    "gn:population":0,
    "gn:timezone":"Africa/Bamako",
    "iso:country":"ML",
    "name:und_x_variant":[
        "Diab\u00e9samou",
        "Diabessamou"
    ],
    "wof:name":"Diabessamou",
    "wof:placetype":"locality"
},
  "geometry": {"coordinates":[-10.7401,13.9702],"type":"Point"}
}