{
  "type": "Feature",
  "properties": {
    "gn:admin1_code":"06",
    "gn:asciiname":"Fingola",
    "gn:country_code":"ML",
    "gn:dem":317,
    "gn:feature_class":"P",
    "gn:feature_code":"PPL",
    "gn:name":"Fingola",
    "gn:population":0,
    "gn:timezone":"Africa/Bamako",
    "iso:country":"ML",
    "name:fra_x_preferred":[
        "Fengola"
    ],
    "wof:name":"Fingola",
    "wof:placetype":"locality"
},
  "geometry": {"coordinates":[-6.8299,11.63758],"type":"Point"}
}