{
  "type": "Feature",
  "properties": {
    "gn:admin1_code":"5.0",
    "gn:asciiname":"Sobedaga",
    "gn:country_code":"ML",
    "gn:dem":335,
    "gn:feature_class":"P",
    "gn:feature_code":"PPL",
    "gn:name":"Sob\u00e9daga",
    "gn:population":0,
    "gn:timezone":"Africa/Bamako",
    "iso:country":"ML",
    "wof:name":"Sobedaga",
    "wof:placetype":"locality"
},
  "geometry": {"coordinates":[-4.1054,13.6086],"type":"Point"}
}