{
  "type": "Feature",
  "properties": {
    "gn:admin1_code":"09",
    "gn:asciiname":"Todyel Gargouna",
    "gn:country_code":"ML",
    "gn:dem":257,
    "gn:feature_class":"P",
    "gn:feature_code":"PPL",
    "gn:name":"Todyel Gargouna",
    "gn:population":0,
    "gn:timezone":"Africa/Bamako",
    "iso:country":"ML",
    "wof:name":"Todyel Gargouna",
    "wof:placetype":"locality"
},
  "geometry": {"coordinates":[0.1775,15.9679],"type":"Point"}
}