{
  "type": "Feature",
  "properties": {
    "gn:admin1_code":"03",
    "gn:asciiname":"Guiamayo",
    "gn:country_code":"ML",
    "gn:dem":233,
    "gn:feature_class":"P",
    "gn:feature_code":"PPL",
    "gn:name":"Guiamayo",
    "gn:population":0,
    "gn:timezone":"Africa/Bamako",
    "iso:country":"ML",
    "name:und_x_variant":[
        "Gu\u00e9m\u00e9a",
        "Guiamayo"
    ],
    "wof:name":"Guiamayo",
    "wof:placetype":"locality"
},
  "geometry": {"coordinates":[-11.06591,12.22346],"type":"Point"}
}