{
  "type": "Feature",
  "properties": {
    "gn:admin1_code":"7.0",
    "gn:asciiname":"Beleko-Soba",
    "gn:country_code":"ML",
    "gn:dem":305,
    "gn:feature_class":"P",
    "gn:feature_code":"PPL",
    "gn:name":"B\u00e9l\u00e9ko-Soba",
    "gn:population":0,
    "gn:timezone":"Africa/Bamako",
    "iso:country":"ML",
    "name:fra_x_preferred":[
        "Benkou"
    ],
    "name:fra_x_variant":[
        "Belekou",
        "B\u00e9l\u00e9koro",
        "B\u00e9l\u00e9ko"
    ],
    "name:und_x_variant":[
        "Benkou",
        "B\u00e9l\u00e9koro",
        "Belekou",
        "B\u00e9l\u00e9ko",
        "B\u00e9l\u00e9ko-Soba",
        "Belekosoba"
    ],
    "wof:name":"Beleko-Soba",
    "wof:placetype":"locality"
},
  "geometry": {"coordinates":[-6.409,12.4814],"type":"Point"}
}