{
  "type": "Feature",
  "properties": {
    "gn:admin1_code":"03",
    "gn:asciiname":"Djigouma",
    "gn:country_code":"ML",
    "gn:dem":319,
    "gn:feature_class":"P",
    "gn:feature_code":"PPL",
    "gn:name":"Djigouma",
    "gn:population":0,
    "gn:timezone":"Africa/Bamako",
    "iso:country":"ML",
    "name:fra_x_preferred":[
        "Djigouma"
    ],
    "wof:name":"Djigouma",
    "wof:placetype":"locality"
},
  "geometry": {"coordinates":[-8.973,13.5308],"type":"Point"}
}