{
  "type": "Feature",
  "properties": {
    "gn:admin1_code":"03",
    "gn:asciiname":"Hafia",
    "gn:country_code":"ML",
    "gn:dem":189,
    "gn:feature_class":"P",
    "gn:feature_code":"PPL",
    "gn:name":"Hafia",
    "gn:population":0,
    "gn:timezone":"Africa/Bamako",
    "iso:country":"ML",
    "name:ita_x_preferred":[
        "Hafia"
    ],
    "name:msa_x_preferred":[
        "Hafia"
    ],
    "name:spa_x_preferred":[
        "Hafia"
    ],
    "wof:name":"Hafia",
    "wof:placetype":"locality"
},
  "geometry": {"coordinates":[-11.01705,12.30987],"type":"Point"}
}