{
  "type": "Feature",
  "properties": {
    "gn:admin1_code":"00",
    "gn:asciiname":"Guessekole",
    "gn:country_code":"ML",
    "gn:dem":333,
    "gn:feature_class":"P",
    "gn:feature_code":"PPL",
    "gn:name":"Gu\u00e9ss\u00e9kole",
    "gn:population":0,
    "gn:timezone":"Africa/Bamako",
    "iso:country":"ML",
    "wof:name":"Guessekole",
    "wof:placetype":"locality"
},
  "geometry": {"coordinates":[-9.53333,12.51667],"type":"Point"}
}