{
  "type": "Feature",
  "properties": {
    "gn:admin1_code":"00",
    "gn:asciiname":"Daka Saidou",
    "gn:country_code":"ML",
    "gn:dem":415,
    "gn:feature_class":"P",
    "gn:feature_code":"PPL",
    "gn:name":"Daka Sa\u00efdou",
    "gn:population":0,
    "gn:timezone":"Africa/Bamako",
    "iso:country":"ML",
    "wof:name":"Daka Saidou",
    "wof:placetype":"locality"
},
  "geometry": {"coordinates":[-10.66667,11.95],"type":"Point"}
}