{
  "type": "Feature",
  "properties": {
    "gn:admin1_code":"03",
    "gn:asciiname":"Kiniedito",
    "gn:country_code":"ML",
    "gn:dem":161,
    "gn:feature_class":"P",
    "gn:feature_code":"PPL",
    "gn:name":"Kini\u00e9dito",
    "gn:population":0,
    "gn:timezone":"Africa/Bamako",
    "iso:country":"ML",
    "wof:name":"Kiniedito",
    "wof:placetype":"locality"
},
  "geometry": {"coordinates":[-10.0793,13.8949],"type":"Point"}
}