{
  "type": "Feature",
  "properties": {
    "gn:admin1_code":"8.0",
    "gn:asciiname":"Filenza Bakou",
    "gn:country_code":"ML",
    "gn:dem":269,
    "gn:feature_class":"P",
    "gn:feature_code":"PPL",
    "gn:name":"Filenza Bakou",
    "gn:population":0,
    "gn:timezone":"Africa/Bamako",
    "iso:country":"ML",
    "wof:name":"Filenza Bakou",
    "wof:placetype":"locality"
},
  "geometry": {"coordinates":[-3.7806,15.7886],"type":"Point"}
}