{
  "type": "Feature",
  "properties": {
    "gn:admin1_code":"04",
    "gn:asciiname":"Sougouba",
    "gn:country_code":"ML",
    "gn:dem":275,
    "gn:feature_class":"P",
    "gn:feature_code":"PPL",
    "gn:name":"Sougouba",
    "gn:population":0,
    "gn:timezone":"Africa/Bamako",
    "iso:country":"ML",
    "wof:name":"Sougouba",
    "wof:placetype":"locality"
},
  "geometry": {"coordinates":[-4.88843,13.72617],"type":"Point"}
}