{
  "type": "Feature",
  "properties": {
    "gn:admin1_code":"00",
    "gn:asciiname":"Makono",
    "gn:cc2":"ML",
    "gn:country_code":"ML",
    "gn:dem":390,
    "gn:feature_class":"P",
    "gn:feature_code":"PPL",
    "gn:name":"Makono",
    "gn:population":0,
    "gn:timezone":"Africa/Bamako",
    "iso:country":"ML",
    "name:und_x_variant":[
        "Mamakono",
        "Makono"
    ],
    "wof:name":"Makono",
    "wof:placetype":"locality"
},
  "geometry": {"coordinates":[-9.05,12.68333],"type":"Point"}
}