{
  "type": "Feature",
  "properties": {
    "gn:admin1_code":"5.0",
    "gn:asciiname":"Foko",
    "gn:country_code":"ML",
    "gn:dem":281,
    "gn:feature_class":"P",
    "gn:feature_code":"PPL",
    "gn:name":"Foko",
    "gn:population":0,
    "gn:timezone":"Africa/Bamako",
    "iso:country":"ML",
    "wof:name":"Foko",
    "wof:placetype":"locality"
},
  "geometry": {"coordinates":[-5.6074,13.6734],"type":"Point"}
}