{
  "type": "Feature",
  "properties": {
    "gn:admin1_code":"03",
    "gn:asciiname":"Gouka",
    "gn:country_code":"ML",
    "gn:dem":81,
    "gn:feature_class":"P",
    "gn:feature_code":"PPL",
    "gn:name":"Gouka",
    "gn:population":0,
    "gn:timezone":"Africa/Bamako",
    "iso:country":"ML",
    "wof:name":"Gouka",
    "wof:placetype":"locality"
},
  "geometry": {"coordinates":[-11.81114,14.33409],"type":"Point"}
}