{
  "type": "Feature",
  "properties": {
    "gn:admin1_code":"7.0",
    "gn:asciiname":"Folonda",
    "gn:country_code":"ML",
    "gn:dem":386,
    "gn:feature_class":"P",
    "gn:feature_code":"PPL",
    "gn:name":"Folonda",
    "gn:population":0,
    "gn:timezone":"Africa/Bamako",
    "iso:country":"ML",
    "wof:name":"Folonda",
    "wof:placetype":"locality"
},
  "geometry": {"coordinates":[-7.88308,13.27399],"type":"Point"}
}