{
  "type": "Feature",
  "properties": {
    "gn:admin1_code":"07",
    "gn:asciiname":"Sirakorola",
    "gn:country_code":"ML",
    "gn:dem":351,
    "gn:feature_class":"P",
    "gn:feature_code":"PPL",
    "gn:name":"Sirakorola",
    "gn:population":0,
    "gn:timezone":"Africa/Bamako",
    "iso:country":"ML",
    "name:und_x_variant":[
        "Siracorola",
        "Sirakorola"
    ],
    "wof:name":"Sirakorola",
    "wof:placetype":"locality"
},
  "geometry": {"coordinates":[-7.56982,13.28671],"type":"Point"}
}