{
  "type": "Feature",
  "properties": {
    "gn:admin1_code":"03",
    "gn:asciiname":"Serora",
    "gn:country_code":"ML",
    "gn:dem":66,
    "gn:feature_class":"P",
    "gn:feature_code":"PPL",
    "gn:name":"S\u00e9rora",
    "gn:population":0,
    "gn:timezone":"Africa/Bamako",
    "iso:country":"ML",
    "wof:name":"Serora",
    "wof:placetype":"locality"
},
  "geometry": {"coordinates":[-11.01871,14.49521],"type":"Point"}
}