{
  "type": "Feature",
  "properties": {
    "gn:admin1_code":"06",
    "gn:asciiname":"Niamassanbougou",
    "gn:country_code":"ML",
    "gn:dem":322,
    "gn:feature_class":"P",
    "gn:feature_code":"PPL",
    "gn:name":"Niamassanbougou",
    "gn:population":0,
    "gn:timezone":"Africa/Bamako",
    "iso:country":"ML",
    "wof:name":"Niamassanbougou",
    "wof:placetype":"locality"
},
  "geometry": {"coordinates":[-5.83681,11.99411],"type":"Point"}
}