{
  "type": "Feature",
  "properties": {
    "gn:admin1_code":"06",
    "gn:asciiname":"Ifola",
    "gn:country_code":"ML",
    "gn:dem":429,
    "gn:feature_class":"P",
    "gn:feature_code":"PPL",
    "gn:name":"Ifola",
    "gn:population":0,
    "gn:timezone":"Africa/Bamako",
    "iso:country":"ML",
    "name:und_x_variant":[
        "Yiola",
        "Ifola"
    ],
    "wof:name":"Ifola",
    "wof:placetype":"locality"
},
  "geometry": {"coordinates":[-5.97102,11.37641],"type":"Point"}
}