{
  "type": "Feature",
  "properties": {
    "gn:admin1_code":"5.0",
    "gn:asciiname":"Kitiola",
    "gn:country_code":"ML",
    "gn:dem":293,
    "gn:feature_class":"P",
    "gn:feature_code":"PPL",
    "gn:name":"Kitiola",
    "gn:population":0,
    "gn:timezone":"Africa/Bamako",
    "iso:country":"ML",
    "wof:name":"Kitiola",
    "wof:placetype":"locality"
},
  "geometry": {"coordinates":[-6.1601,13.306],"type":"Point"}
}