{
  "type": "Feature",
  "properties": {
    "gn:admin1_code":"7.0",
    "gn:asciiname":"Tioribougou",
    "gn:country_code":"ML",
    "gn:dem":407,
    "gn:feature_class":"P",
    "gn:feature_code":"PPL",
    "gn:name":"Tioribougou",
    "gn:population":0,
    "gn:timezone":"Africa/Bamako",
    "iso:country":"ML",
    "wof:name":"Tioribougou",
    "wof:placetype":"locality"
},
  "geometry": {"coordinates":[-7.60788,13.45864],"type":"Point"}
}