{
  "type": "Feature",
  "properties": {
    "gn:admin1_code":"07",
    "gn:asciiname":"Boro",
    "gn:country_code":"ML",
    "gn:dem":420,
    "gn:feature_class":"P",
    "gn:feature_code":"PPL",
    "gn:name":"Boro",
    "gn:population":0,
    "gn:timezone":"Africa/Bamako",
    "iso:country":"ML",
    "name:fra_x_preferred":[
        "Boro"
    ],
    "wof:name":"Boro",
    "wof:placetype":"locality"
},
  "geometry": {"coordinates":[-8.3065,13.0128],"type":"Point"}
}