{
  "type": "Feature",
  "properties": {
    "gn:admin1_code":"05",
    "gn:asciiname":"Boulel",
    "gn:country_code":"ML",
    "gn:dem":270,
    "gn:feature_class":"P",
    "gn:feature_code":"PPL",
    "gn:name":"Boulel",
    "gn:population":0,
    "gn:timezone":"Africa/Bamako",
    "iso:country":"ML",
    "wof:name":"Boulel",
    "wof:placetype":"locality"
},
  "geometry": {"coordinates":[-5.2806,15.1155],"type":"Point"}
}