{
  "type": "Feature",
  "properties": {
    "gn:admin1_code":"4.0",
    "gn:asciiname":"Bente",
    "gn:country_code":"ML",
    "gn:dem":266,
    "gn:feature_class":"P",
    "gn:feature_code":"PPL",
    "gn:name":"Bent\u00e9",
    "gn:population":0,
    "gn:timezone":"Africa/Bamako",
    "iso:country":"ML",
    "wof:name":"Bente",
    "wof:placetype":"locality"
},
  "geometry": {"coordinates":[-4.18583,14.71781],"type":"Point"}
}