{
  "type": "Feature",
  "properties": {
    "gn:admin1_code":"07",
    "gn:asciiname":"Kodiala",
    "gn:country_code":"ML",
    "gn:dem":461,
    "gn:feature_class":"P",
    "gn:feature_code":"PPL",
    "gn:name":"Kodiala",
    "gn:population":0,
    "gn:timezone":"Africa/Bamako",
    "iso:country":"ML",
    "wof:name":"Kodiala",
    "wof:placetype":"locality"
},
  "geometry": {"coordinates":[-8.25707,12.64439],"type":"Point"}
}