{
  "type": "Feature",
  "properties": {
    "gn:admin1_code":"08",
    "gn:asciiname":"Ouro-Fatouma",
    "gn:country_code":"ML",
    "gn:dem":267,
    "gn:feature_class":"P",
    "gn:feature_code":"PPL",
    "gn:name":"Ouro-Fatouma",
    "gn:population":0,
    "gn:timezone":"Africa/Bamako",
    "iso:country":"ML",
    "wof:name":"Ouro-Fatouma",
    "wof:placetype":"locality"
},
  "geometry": {"coordinates":[-3.32133,16.02662999999999],"type":"Point"}
}