{
  "type": "Feature",
  "properties": {
    "gn:admin1_code":"6.0",
    "gn:asciiname":"Tenebougou",
    "gn:country_code":"ML",
    "gn:dem":332,
    "gn:feature_class":"P",
    "gn:feature_code":"PPL",
    "gn:name":"T\u00e9n\u00e9bougou",
    "gn:population":0,
    "gn:timezone":"Africa/Bamako",
    "iso:country":"ML",
    "wof:name":"Tenebougou",
    "wof:placetype":"locality"
},
  "geometry": {"coordinates":[-5.57028,11.4245],"type":"Point"}
}