{
  "type": "Feature",
  "properties": {
    "gn:admin1_code":"07",
    "gn:asciiname":"Medina Koura",
    "gn:country_code":"ML",
    "gn:dem":262,
    "gn:feature_class":"P",
    "gn:feature_code":"PPL",
    "gn:name":"M\u00e9dina Koura",
    "gn:population":0,
    "gn:timezone":"Africa/Bamako",
    "iso:country":"ML",
    "wof:name":"Medina Koura",
    "wof:placetype":"locality"
},
  "geometry": {"coordinates":[-7.08794,15.07227],"type":"Point"}
}