{
  "type": "Feature",
  "properties": {
    "gn:admin1_code":"0.0",
    "gn:asciiname":"Bindougou",
    "gn:country_code":"ML",
    "gn:dem":326,
    "gn:feature_class":"P",
    "gn:feature_code":"PPL",
    "gn:name":"Bindougou",
    "gn:population":0,
    "gn:timezone":"Africa/Bamako",
    "iso:country":"ML",
    "wof:name":"Bindougou",
    "wof:placetype":"locality"
},
  "geometry": {"coordinates":[-10.06667,12.48333],"type":"Point"}
}