{
  "type": "Feature",
  "properties": {
    "gn:admin1_code":"07",
    "gn:asciiname":"Diago",
    "gn:country_code":"ML",
    "gn:dem":415,
    "gn:feature_class":"P",
    "gn:feature_code":"PPL",
    "gn:name":"Diago",
    "gn:population":0,
    "gn:timezone":"Africa/Bamako",
    "iso:country":"ML",
    "name:fin_x_preferred":[
        "Diago"
    ],
    "name:fra_x_preferred":[
        "Diago"
    ],
    "name:ita_x_preferred":[
        "Diago"
    ],
    "name:nld_x_preferred":[
        "Diago"
    ],
    "name:spa_x_preferred":[
        "Diago"
    ],
    "name:und_x_variant":[
        "Niago",
        "Dyago"
    ],
    "name:zho_x_preferred":[
        "\u8fea\u4e9e\u6208"
    ],
    "wof:name":"Diago",
    "wof:placetype":"locality"
},
  "geometry": {"coordinates":[-8.15657,12.77799],"type":"Point"}
}