{
  "type": "Feature",
  "properties": {
    "gn:admin1_code":"07",
    "gn:asciiname":"Fougala",
    "gn:country_code":"ML",
    "gn:dem":326,
    "gn:feature_class":"P",
    "gn:feature_code":"PPL",
    "gn:name":"Fougala",
    "gn:population":0,
    "gn:timezone":"Africa/Bamako",
    "iso:country":"ML",
    "name:fra_x_preferred":[
        "Fougala"
    ],
    "wof:name":"Fougala",
    "wof:placetype":"locality"
},
  "geometry": {"coordinates":[-6.9937,12.066],"type":"Point"}
}