{
  "type": "Feature",
  "properties": {
    "gn:admin1_code":"08",
    "gn:asciiname":"Mankalagoungou",
    "gn:country_code":"ML",
    "gn:dem":266,
    "gn:feature_class":"P",
    "gn:feature_code":"PPL",
    "gn:name":"Mankalagoungou",
    "gn:population":0,
    "gn:timezone":"Africa/Bamako",
    "iso:country":"ML",
    "name:und_x_variant":[
        "Makoulagoungou",
        "Mankalagoungou"
    ],
    "wof:name":"Mankalagoungou",
    "wof:placetype":"locality"
},
  "geometry": {"coordinates":[-3.16637,16.57867],"type":"Point"}
}