{
  "type": "Feature",
  "properties": {
    "gn:admin1_code":"05",
    "gn:asciiname":"Siradoba",
    "gn:country_code":"ML",
    "gn:dem":291,
    "gn:feature_class":"P",
    "gn:feature_code":"PPL",
    "gn:name":"Siradoba",
    "gn:population":0,
    "gn:timezone":"Africa/Bamako",
    "iso:country":"ML",
    "wof:name":"Siradoba",
    "wof:placetype":"locality"
},
  "geometry": {"coordinates":[-6.29626,13.25723],"type":"Point"}
}