{
  "type": "Feature",
  "properties": {
    "gn:admin1_code":"06",
    "gn:asciiname":"Diemeno",
    "gn:country_code":"ML",
    "gn:dem":366,
    "gn:feature_class":"P",
    "gn:feature_code":"PPL",
    "gn:name":"Di\u00e9m\u00e9no",
    "gn:population":0,
    "gn:timezone":"Africa/Bamako",
    "iso:country":"ML",
    "wof:name":"Diemeno",
    "wof:placetype":"locality"
},
  "geometry": {"coordinates":[-7.93477,11.84875],"type":"Point"}
}