{
  "type": "Feature",
  "properties": {
    "gn:country":"ML",
    "gn:fcode":"PPLX",
    "gn:population":0,
    "iso:country":"ML",
    "name:fra_x_colloquial":[
        "Medina Koura"
    ],
    "name:fra_x_preferred":[
        "M\u00e9dina Koura"
    ],
    "qs:gn_adm0_cc":"ML",
    "qs:gn_fcode":"PPLX",
    "qs:gn_local":2460596,
    "qs:gn_nam_loc":"Bamako, Bamako, Bamako, ML",
    "qs:gn_namadm1":"00",
    "qs:gn_name":"M\u00e9dina Koura",
    "qs:local_max":278,
    "qs:local_sum":581,
    "qs:localhoods":4,
    "qs:name":"M\u00e9dina Koura",
    "qs:name_adm0":"Mali",
    "qs:name_adm1":"Bamako",
    "qs:name_adm2":"Bamako",
    "qs:name_local":"Bamako",
    "qs:photo_max":125,
    "qs:photo_sum":278,
    "qs:placetype":"Suburb",
    "qs:quad_count":16,
    "qs:woe_adm0":23424891,
    "qs:woe_adm1":2346180,
    "qs:woe_adm2":55999998,
    "qs:woe_lau":0,
    "qs:woe_local":1369729,
    "qs:woe_ver":"7.10.0",
    "qs_pg:aaroncc":"ML",
    "qs_pg:gn_country":"ML",
    "qs_pg:gn_fcode":"PPLX",
    "qs_pg:gn_pop":0,
    "qs_pg:name":"M\u00e9dina Koura",
    "qs_pg:name_adm0":"Mali",
    "qs_pg:name_adm1":"Bamako",
    "qs_pg:photos":269,
    "qs_pg:photos_1k":55,
    "qs_pg:photos_9k":1,
    "qs_pg:photos_9r":4,
    "qs_pg:photos_all":269,
    "qs_pg:photos_sr":5,
    "qs_pg:pop_sr":0,
    "qs_pg:qs_pg_placetype":"neighbourhood",
    "qs_pg:qs_pg_placetype_gp":"Suburb",
    "qs_pg:woe_adm0":23424891,
    "wof:lang":[
        "fre"
    ],
    "wof:name":"M\u00e9dina Koura",
    "wof:placetype":"neighbourhood"
},
  "geometry": {"coordinates":[-7.99071,12.649799],"type":"Point"}
}