{
  "type": "Feature",
  "properties": {
    "gn:admin1_code":"07",
    "gn:asciiname":"Bozibougou",
    "gn:country_code":"ML",
    "gn:dem":298,
    "gn:feature_class":"P",
    "gn:feature_code":"PPL",
    "gn:name":"Bozibougou",
    "gn:population":0,
    "gn:timezone":"Africa/Bamako",
    "iso:country":"ML",
    "name:fra_x_preferred":[
        "Bozibougou"
    ],
    "name:fra_x_variant":[
        "Bonsibougou"
    ],
    "wof:name":"Bozibougou",
    "wof:placetype":"locality"
},
  "geometry": {"coordinates":[-6.556,12.3414],"type":"Point"}
}