{
  "type": "Feature",
  "properties": {
    "gn:admin1_code":"6.0",
    "gn:asciiname":"Fonsebougou",
    "gn:country_code":"ML",
    "gn:dem":314,
    "gn:feature_class":"P",
    "gn:feature_code":"PPL",
    "gn:name":"Fons\u00e9bougou",
    "gn:population":0,
    "gn:timezone":"Africa/Bamako",
    "iso:country":"ML",
    "wof:name":"Fonsebougou",
    "wof:placetype":"locality"
},
  "geometry": {"coordinates":[-6.15597,11.88179],"type":"Point"}
}