{
  "type": "Feature",
  "properties": {
    "gn:admin1_code":"03",
    "gn:asciiname":"Inetiebougou",
    "gn:country_code":"ML",
    "gn:dem":72,
    "gn:feature_class":"P",
    "gn:feature_code":"PPL",
    "gn:name":"In\u00e9ti\u00e9bougou",
    "gn:population":0,
    "gn:timezone":"Africa/Bamako",
    "iso:country":"ML",
    "wof:name":"Inetiebougou",
    "wof:placetype":"locality"
},
  "geometry": {"coordinates":[-11.76525,14.40173],"type":"Point"}
}