{
  "type": "Feature",
  "properties": {
    "gn:admin1_code":"4.0",
    "gn:asciiname":"Kaguila",
    "gn:country_code":"ML",
    "gn:dem":266,
    "gn:feature_class":"P",
    "gn:feature_code":"PPL",
    "gn:name":"Kaguila",
    "gn:population":0,
    "gn:timezone":"Africa/Bamako",
    "iso:country":"ML",
    "wof:name":"Kaguila",
    "wof:placetype":"locality"
},
  "geometry": {"coordinates":[-4.04393,14.75957],"type":"Point"}
}