{
  "type": "Feature",
  "properties": {
    "gn:admin1_code":"03",
    "gn:asciiname":"Manndakoto",
    "gn:country_code":"ML",
    "gn:dem":131,
    "gn:feature_class":"P",
    "gn:feature_code":"PPL",
    "gn:name":"Manndakoto",
    "gn:population":0,
    "gn:timezone":"Africa/Bamako",
    "iso:country":"ML",
    "wof:name":"Manndakoto",
    "wof:placetype":"locality"
},
  "geometry": {"coordinates":[-11.58957,13.76047],"type":"Point"}
}