{
  "type": "Feature",
  "properties": {
    "gn:admin1_code":"9.0",
    "gn:asciiname":"Onda",
    "gn:country_code":"ML",
    "gn:dem":242,
    "gn:feature_class":"P",
    "gn:feature_code":"PPL",
    "gn:name":"Onda",
    "gn:population":0,
    "gn:timezone":"Africa/Bamako",
    "iso:country":"ML",
    "wof:name":"Onda",
    "wof:placetype":"locality"
},
  "geometry": {"coordinates":[0.6961,15.4667],"type":"Point"}
}