{
  "type": "Feature",
  "properties": {
    "gn:admin1_code":"9.0",
    "gn:asciiname":"Onda",
    "gn:country_code":"ML",
    "gn:dem":242,
    "gn:feature_class":"P",
    "gn:feature_code":"PPL",
    "gn:name":"Onda",
    "gn:population":0,
    "gn:timezone":"Africa/Bamako",
    "iso:country":"ML",
    "name:arg_x_preferred":[
        "Onda"
    ],
    "name:ceb_x_preferred":[
        "Onda"
    ],
    "name:deu_x_preferred":[
        "Onda"
    ],
    "name:epo_x_preferred":[
        "Onda"
    ],
    "name:glg_x_preferred":[
        "Onda"
    ],
    "name:ita_x_preferred":[
        "Onda"
    ],
    "name:mlg_x_preferred":[
        "Onda"
    ],
    "name:nld_x_preferred":[
        "Onda"
    ],
    "name:oci_x_preferred":[
        "Onda"
    ],
    "name:por_x_preferred":[
        "Onda"
    ],
    "name:rus_x_preferred":[
        "\u041e\u043d\u0434\u0430"
    ],
    "name:spa_x_preferred":[
        "Onda"
    ],
    "name:swe_x_preferred":[
        "Onda"
    ],
    "name:ukr_x_preferred":[
        "\u041e\u043d\u0434\u0430"
    ],
    "wof:name":"Onda",
    "wof:placetype":"locality"
},
  "geometry": {"coordinates":[0.6961,15.4667],"type":"Point"}
}