{
  "type": "Feature",
  "properties": {
    "gn:admin1_code":"04",
    "gn:asciiname":"Ouro-Boubou",
    "gn:country_code":"ML",
    "gn:dem":265,
    "gn:feature_class":"P",
    "gn:feature_code":"PPL",
    "gn:name":"Ouro-Boubou",
    "gn:population":0,
    "gn:timezone":"Africa/Bamako",
    "iso:country":"ML",
    "wof:name":"Ouro-Boubou",
    "wof:placetype":"locality"
},
  "geometry": {"coordinates":[-4.74116,14.64953],"type":"Point"}
}