{
  "type": "Feature",
  "properties": {
    "gn:admin1_code":"03",
    "gn:asciiname":"Saniaga",
    "gn:country_code":"ML",
    "gn:dem":305,
    "gn:feature_class":"P",
    "gn:feature_code":"PPL",
    "gn:name":"Saniaga",
    "gn:population":0,
    "gn:timezone":"Africa/Bamako",
    "iso:country":"ML",
    "wof:name":"Saniaga",
    "wof:placetype":"locality"
},
  "geometry": {"coordinates":[-9.05684,15.07097],"type":"Point"}
}