{
  "type": "Feature",
  "properties": {
    "gn:admin1_code":"07",
    "gn:asciiname":"Serouala",
    "gn:country_code":"ML",
    "gn:dem":367,
    "gn:feature_class":"P",
    "gn:feature_code":"PPL",
    "gn:name":"S\u00e9rouala",
    "gn:population":0,
    "gn:timezone":"Africa/Bamako",
    "iso:country":"ML",
    "name:und_x_variant":[
        "S\u00e9rwala",
        "S\u00e9ronala",
        "S\u00e9riouala",
        "S\u00e9rouala"
    ],
    "wof:name":"Serouala",
    "wof:placetype":"locality"
},
  "geometry": {"coordinates":[-7.90947,12.839],"type":"Point"}
}