{
  "type": "Feature",
  "properties": {
    "gn:admin1_code":"7.0",
    "gn:asciiname":"Bagoeni",
    "gn:country_code":"ML",
    "gn:dem":298,
    "gn:feature_class":"P",
    "gn:feature_code":"PPL",
    "gn:name":"Bago\u00e9ni",
    "gn:population":0,
    "gn:timezone":"Africa/Bamako",
    "iso:country":"ML",
    "name:und_x_variant":[
        "Bagou\u00e9ni",
        "Bago\u00e9ni"
    ],
    "wof:name":"Bagoeni",
    "wof:placetype":"locality"
},
  "geometry": {"coordinates":[-8.63652,15.17216],"type":"Point"}
}