{
  "type": "Feature",
  "properties": {
    "gn:admin1_code":"3.0",
    "gn:asciiname":"Sangarela",
    "gn:country_code":"ML",
    "gn:dem":217,
    "gn:feature_class":"P",
    "gn:feature_code":"PPL",
    "gn:name":"Sangar\u00e9la",
    "gn:population":0,
    "gn:timezone":"Africa/Bamako",
    "iso:country":"ML",
    "wof:name":"Sangarela",
    "wof:placetype":"locality"
},
  "geometry": {"coordinates":[-10.5652,14.3324],"type":"Point"}
}