{
  "type": "Feature",
  "properties": {
    "gn:admin1_code":"7.0",
    "gn:asciiname":"Bandiougoubougou",
    "gn:country_code":"ML",
    "gn:dem":328,
    "gn:feature_class":"P",
    "gn:feature_code":"PPL",
    "gn:name":"Bandiougoubougou",
    "gn:population":0,
    "gn:timezone":"Africa/Bamako",
    "iso:country":"ML",
    "wof:name":"Bandiougoubougou",
    "wof:placetype":"locality"
},
  "geometry": {"coordinates":[-7.00629,12.76648],"type":"Point"}
}