{
  "type": "Feature",
  "properties": {
    "gn:admin1_code":"4.0",
    "gn:asciiname":"Loro Habe",
    "gn:country_code":"ML",
    "gn:dem":404,
    "gn:feature_class":"P",
    "gn:feature_code":"PPL",
    "gn:name":"Loro Habe",
    "gn:population":0,
    "gn:timezone":"Africa/Bamako",
    "iso:country":"ML",
    "wof:name":"Loro Habe",
    "wof:placetype":"locality"
},
  "geometry": {"coordinates":[-2.17699,15.08453],"type":"Point"}
}