{
  "type": "Feature",
  "properties": {
    "gn:admin1_code":"04",
    "gn:asciiname":"Dani-Sare",
    "gn:country_code":"ML",
    "gn:dem":299,
    "gn:feature_class":"P",
    "gn:feature_code":"PPL",
    "gn:name":"Dani-Sar\u00e9",
    "gn:population":0,
    "gn:timezone":"Africa/Bamako",
    "iso:country":"ML",
    "wof:name":"Dani-Sare",
    "wof:placetype":"locality"
},
  "geometry": {"coordinates":[-3.80709,14.8354],"type":"Point"}
}