{
  "type": "Feature",
  "properties": {
    "gn:admin1_code":"07",
    "gn:asciiname":"Falababe",
    "gn:country_code":"ML",
    "gn:dem":318,
    "gn:feature_class":"P",
    "gn:feature_code":"PPL",
    "gn:name":"Falababe",
    "gn:population":0,
    "gn:timezone":"Africa/Bamako",
    "iso:country":"ML",
    "name:und_x_variant":[
        "Falaba",
        "Falababe"
    ],
    "wof:name":"Falababe",
    "wof:placetype":"locality"
},
  "geometry": {"coordinates":[-8.3254,14.0495],"type":"Point"}
}