{
  "type": "Feature",
  "properties": {
    "gn:admin1_code":"03",
    "gn:asciiname":"Madiga",
    "gn:country_code":"ML",
    "gn:dem":318,
    "gn:feature_class":"P",
    "gn:feature_code":"PPL",
    "gn:name":"Madiga",
    "gn:population":0,
    "gn:timezone":"Africa/Bamako",
    "iso:country":"ML",
    "name:kan_x_preferred":[
        "\u0cae\u0cbe\u0ca6\u0cbf\u0c97"
    ],
    "name:tel_x_preferred":[
        "\u0c2e\u0c3e\u0c26\u0c3f\u0c17"
    ],
    "wof:name":"Madiga",
    "wof:placetype":"locality"
},
  "geometry": {"coordinates":[-9.5917,14.531],"type":"Point"}
}