{
  "type": "Feature",
  "properties": {
    "gn:admin1_code":"03",
    "gn:asciiname":"Toumbou",
    "gn:country_code":"ML",
    "gn:dem":542,
    "gn:feature_class":"P",
    "gn:feature_code":"PPL",
    "gn:name":"Toumbou",
    "gn:population":0,
    "gn:timezone":"Africa/Bamako",
    "iso:country":"ML",
    "name:und_x_variant":[
        "Tonbou",
        "Toumbou"
    ],
    "wof:name":"Toumbou",
    "wof:placetype":"locality"
},
  "geometry": {"coordinates":[-11.05363,12.71427],"type":"Point"}
}