{
  "type": "Feature",
  "properties": {
    "gn:admin1_code":"03",
    "gn:asciiname":"Tambafoulou",
    "gn:country_code":"ML",
    "gn:dem":230,
    "gn:feature_class":"P",
    "gn:feature_code":"PPL",
    "gn:name":"Tambafoulou",
    "gn:population":0,
    "gn:timezone":"Africa/Bamako",
    "iso:country":"ML",
    "wof:name":"Tambafoulou",
    "wof:placetype":"locality"
},
  "geometry": {"coordinates":[-9.9119,14.5241],"type":"Point"}
}