{
  "type": "Feature",
  "properties": {
    "gn:admin1_code":"7.0",
    "gn:asciiname":"Farako Darani",
    "gn:country_code":"ML",
    "gn:dem":357,
    "gn:feature_class":"P",
    "gn:feature_code":"PPL",
    "gn:name":"Farako Darani",
    "gn:population":0,
    "gn:timezone":"Africa/Bamako",
    "iso:country":"ML",
    "wof:name":"Farako Darani",
    "wof:placetype":"locality"
},
  "geometry": {"coordinates":[-7.77239,12.43088],"type":"Point"}
}