{
  "type": "Feature",
  "properties": {
    "gn:admin1_code":"06",
    "gn:asciiname":"Kapala",
    "gn:country_code":"ML",
    "gn:dem":355,
    "gn:feature_class":"P",
    "gn:feature_code":"PPL",
    "gn:name":"Kapala",
    "gn:population":0,
    "gn:timezone":"Africa/Bamako",
    "iso:country":"ML",
    "name:fra_x_preferred":[
        "Kapala"
    ],
    "name:pol_x_preferred":[
        "Kapala"
    ],
    "name:rus_x_preferred":[
        "\u041a\u0430\u043f\u0430\u043b\u0430"
    ],
    "name:spa_x_preferred":[
        "Kapala"
    ],
    "name:swe_x_preferred":[
        "Kapala"
    ],
    "name:tur_x_preferred":[
        "Kapala"
    ],
    "name:ukr_x_preferred":[
        "\u041a\u0430\u043f\u0430\u043b\u0430"
    ],
    "name:zho_x_preferred":[
        "\u560e\u5df4\u62c9\u7897"
    ],
    "wof:name":"Kapala",
    "wof:placetype":"locality"
},
  "geometry": {"coordinates":[-5.45923,12.2146],"type":"Point"}
}