{
  "type": "Feature",
  "properties": {
    "gn:admin1_code":"04",
    "gn:asciiname":"Tiboki",
    "gn:country_code":"ML",
    "gn:dem":459,
    "gn:feature_class":"P",
    "gn:feature_code":"PPL",
    "gn:name":"Tiboki",
    "gn:population":0,
    "gn:timezone":"Africa/Bamako",
    "iso:country":"ML",
    "wof:name":"Tiboki",
    "wof:placetype":"locality"
},
  "geometry": {"coordinates":[-3.46157,15.03603],"type":"Point"}
}