{
  "type": "Feature",
  "properties": {
    "gn:admin1_code":"03",
    "gn:asciiname":"Yahiro",
    "gn:country_code":"ML",
    "gn:dem":216,
    "gn:feature_class":"P",
    "gn:feature_code":"PPL",
    "gn:name":"Yahiro",
    "gn:population":0,
    "gn:timezone":"Africa/Bamako",
    "iso:country":"ML",
    "wof:name":"Yahiro",
    "wof:placetype":"locality"
},
  "geometry": {"coordinates":[-10.1783,14.8571],"type":"Point"}
}