{
  "type": "Feature",
  "properties": {
    "gn:admin1_code":"09",
    "gn:asciiname":"Tana Onda",
    "gn:country_code":"ML",
    "gn:dem":246,
    "gn:feature_class":"P",
    "gn:feature_code":"PPL",
    "gn:name":"Tana Onda",
    "gn:population":0,
    "gn:timezone":"Africa/Bamako",
    "iso:country":"ML",
    "wof:name":"Tana Onda",
    "wof:placetype":"locality"
},
  "geometry": {"coordinates":[0.7132,15.4721],"type":"Point"}
}