{
  "type": "Feature",
  "properties": {
    "gn:admin1_code":"3.0",
    "gn:asciiname":"Bakouroufata",
    "gn:country_code":"ML",
    "gn:dem":124,
    "gn:feature_class":"P",
    "gn:feature_code":"PPL",
    "gn:name":"Bakouroufata",
    "gn:population":0,
    "gn:timezone":"Africa/Bamako",
    "iso:country":"ML",
    "wof:name":"Bakouroufata",
    "wof:placetype":"locality"
},
  "geometry": {"coordinates":[-10.6995,13.4326],"type":"Point"}
}