{
  "type": "Feature",
  "properties": {
    "gn:admin1_code":"00",
    "gn:asciiname":"Konotaye",
    "gn:cc2":"ML",
    "gn:country_code":"ML",
    "gn:dem":339,
    "gn:feature_class":"P",
    "gn:feature_code":"PPL",
    "gn:name":"Konotaye",
    "gn:population":0,
    "gn:timezone":"Africa/Bamako",
    "iso:country":"ML",
    "name:und_x_variant":[
        "Konofaye",
        "Konofoy",
        "Konofa\u00ef",
        "Konotaye"
    ],
    "wof:name":"Konotaye",
    "wof:placetype":"locality"
},
  "geometry": {"coordinates":[-9.21667,12.75],"type":"Point"}
}