{
  "type": "Feature",
  "properties": {
    "gn:admin1_code":"3.0",
    "gn:asciiname":"Konbournavel",
    "gn:country_code":"ML",
    "gn:dem":204,
    "gn:feature_class":"P",
    "gn:feature_code":"PPL",
    "gn:name":"Konbournavel",
    "gn:population":0,
    "gn:timezone":"Africa/Bamako",
    "iso:country":"ML",
    "wof:name":"Konbournavel",
    "wof:placetype":"locality"
},
  "geometry": {"coordinates":[-9.52805,15.35522],"type":"Point"}
}