{
  "type": "Feature",
  "properties": {
    "gn:admin1_code":"6.0",
    "gn:asciiname":"Faneme",
    "gn:country_code":"ML",
    "gn:dem":340,
    "gn:feature_class":"P",
    "gn:feature_code":"PPL",
    "gn:name":"Fan\u00e9m\u00e9",
    "gn:population":0,
    "gn:timezone":"Africa/Bamako",
    "iso:country":"ML",
    "wof:name":"Faneme",
    "wof:placetype":"locality"
},
  "geometry": {"coordinates":[-7.24442,11.3787],"type":"Point"}
}