{
  "type": "Feature",
  "properties": {
    "gn:admin1_code":"03",
    "gn:asciiname":"Saboussere",
    "gn:country_code":"ML",
    "gn:dem":115,
    "gn:feature_class":"P",
    "gn:feature_code":"PPL",
    "gn:name":"Sabouss\u00e9r\u00e9",
    "gn:population":0,
    "gn:timezone":"Africa/Bamako",
    "iso:country":"ML",
    "wof:name":"Saboussere",
    "wof:placetype":"locality"
},
  "geometry": {"coordinates":[-10.71406,15.26853],"type":"Point"}
}