{
  "type": "Feature",
  "properties": {
    "gn:admin1_code":"00",
    "gn:asciiname":"Dinde",
    "gn:country_code":"ML",
    "gn:dem":279,
    "gn:feature_class":"P",
    "gn:feature_code":"PPL",
    "gn:name":"Dind\u00e9",
    "gn:population":0,
    "gn:timezone":"Africa/Bamako",
    "iso:country":"ML",
    "wof:name":"Dinde",
    "wof:placetype":"locality"
},
  "geometry": {"coordinates":[-0.48333,15.63333],"type":"Point"}
}