{
  "type": "Feature",
  "properties": {
    "gn:admin1_code":"03",
    "gn:asciiname":"Daribera",
    "gn:country_code":"ML",
    "gn:dem":245,
    "gn:feature_class":"P",
    "gn:feature_code":"PPL",
    "gn:name":"Darib\u00e9ra",
    "gn:population":0,
    "gn:timezone":"Africa/Bamako",
    "iso:country":"ML",
    "name:und_x_variant":[
        "Dalib\u00e9ra",
        "Darib\u00e9ra"
    ],
    "wof:name":"Daribera",
    "wof:placetype":"locality"
},
  "geometry": {"coordinates":[-9.7231,14.5093],"type":"Point"}
}