{
  "type": "Feature",
  "properties": {
    "gn:admin1_code":"07",
    "gn:asciiname":"Hasi el Barke",
    "gn:country_code":"ML",
    "gn:dem":304,
    "gn:feature_class":"P",
    "gn:feature_code":"PPL",
    "gn:name":"H\u00e2s\u00ee el Bark\u00e9",
    "gn:population":0,
    "gn:timezone":"Africa/Bamako",
    "iso:country":"ML",
    "name:und_x_variant":[
        "Hassi el Bark\u00e9",
        "H\u00e2s\u00ee el Bark\u00e9"
    ],
    "wof:name":"Hasi el Barke",
    "wof:placetype":"locality"
},
  "geometry": {"coordinates":[-8.048,15.4747],"type":"Point"}
}