{
  "type": "Feature",
  "properties": {
    "gn:admin1_code":"06",
    "gn:asciiname":"Sende",
    "gn:country_code":"ML",
    "gn:dem":361,
    "gn:feature_class":"P",
    "gn:feature_code":"PPL",
    "gn:name":"Send\u00e9",
    "gn:population":0,
    "gn:timezone":"Africa/Bamako",
    "iso:country":"ML",
    "wof:name":"Sende",
    "wof:placetype":"locality"
},
  "geometry": {"coordinates":[-4.6672,12.5382],"type":"Point"}
}