{
  "type": "Feature",
  "properties": {
    "gn:admin1_code":"05",
    "gn:asciiname":"Dianebougou",
    "gn:country_code":"ML",
    "gn:dem":285,
    "gn:feature_class":"P",
    "gn:feature_code":"PPL",
    "gn:name":"Dian\u00e9bougou",
    "gn:population":0,
    "gn:timezone":"Africa/Bamako",
    "iso:country":"ML",
    "name:und_x_variant":[
        "Dj\u00e9n\u00e9bougou",
        "Dian\u00e9bougou"
    ],
    "wof:name":"Dianebougou",
    "wof:placetype":"locality"
},
  "geometry": {"coordinates":[-6.1636,13.9194],"type":"Point"}
}