{
  "type": "Feature",
  "properties": {
    "gn:admin1_code":"07",
    "gn:asciiname":"Dili",
    "gn:country_code":"ML",
    "gn:dem":260,
    "gn:feature_class":"P",
    "gn:feature_code":"PPL",
    "gn:name":"Dili",
    "gn:population":0,
    "gn:timezone":"Africa/Bamako",
    "iso:country":"ML",
    "name:fin_x_preferred":[
        "Dilly"
    ],
    "name:fra_x_preferred":[
        "Dilly"
    ],
    "name:ita_x_preferred":[
        "Dilly"
    ],
    "name:nld_x_preferred":[
        "Dilly"
    ],
    "name:spa_x_preferred":[
        "Dilly"
    ],
    "name:und_x_variant":[
        "Dili"
    ],
    "wof:name":"Dili",
    "wof:placetype":"locality"
},
  "geometry": {"coordinates":[-7.66836,14.99556],"type":"Point"}
}