{
  "type": "Feature",
  "properties": {
    "gn:admin1_code":"5.0",
    "gn:asciiname":"Babougou",
    "gn:country_code":"ML",
    "gn:dem":275,
    "gn:feature_class":"P",
    "gn:feature_code":"PPL",
    "gn:name":"Babougou",
    "gn:population":0,
    "gn:timezone":"Africa/Bamako",
    "iso:country":"ML",
    "wof:name":"Babougou",
    "wof:placetype":"locality"
},
  "geometry": {"coordinates":[-5.24957,13.65359],"type":"Point"}
}