{
  "type": "Feature",
  "properties": {
    "gn:admin1_code":"03",
    "gn:asciiname":"Gamaye",
    "gn:country_code":"ML",
    "gn:dem":124,
    "gn:feature_class":"P",
    "gn:feature_code":"PPL",
    "gn:name":"Gamaye",
    "gn:population":0,
    "gn:timezone":"Africa/Bamako",
    "iso:country":"ML",
    "wof:name":"Gamaye",
    "wof:placetype":"locality"
},
  "geometry": {"coordinates":[-11.37604,12.6159],"type":"Point"}
}