{
  "type": "Feature",
  "properties": {
    "gn:admin1_code":"07",
    "gn:asciiname":"Korona",
    "gn:country_code":"ML",
    "gn:dem":363,
    "gn:feature_class":"P",
    "gn:feature_code":"PPL",
    "gn:name":"Korona",
    "gn:population":0,
    "gn:timezone":"Africa/Bamako",
    "iso:country":"ML",
    "name:bul_x_preferred":[
        "\u041a\u043e\u0440\u043e\u043d\u0430"
    ],
    "name:ceb_x_preferred":[
        "Korona"
    ],
    "name:ces_x_preferred":[
        "Kor\u00f3na"
    ],
    "name:deu_x_preferred":[
        "Korona"
    ],
    "name:ell_x_preferred":[
        "\u039a\u03bf\u03c1\u03cc\u03bd\u03b1"
    ],
    "name:epo_x_preferred":[
        "Korona"
    ],
    "name:fin_x_preferred":[
        "Korona"
    ],
    "name:fra_x_preferred":[
        "Korona"
    ],
    "name:heb_x_preferred":[
        "\u05e7\u05d5\u05e8\u05d5\u05e0\u05d4"
    ],
    "name:hun_x_preferred":[
        "Korona"
    ],
    "name:jpn_x_preferred":[
        "\u30b3\u30ed\u30ca"
    ],
    "name:lav_x_preferred":[
        "Korona"
    ],
    "name:nno_x_preferred":[
        "Korona"
    ],
    "name:pol_x_preferred":[
        "Korona"
    ],
    "name:rus_x_preferred":[
        "\u041a\u043e\u0440\u043e\u043d\u0430"
    ],
    "name:sqi_x_preferred":[
        "Korona"
    ],
    "name:srp_x_preferred":[
        "\u041a\u043e\u0440\u043e\u043d\u0430"
    ],
    "name:swe_x_preferred":[
        "Korona"
    ],
    "name:tgl_x_preferred":[
        "Korona"
    ],
    "name:ukr_x_preferred":[
        "\u041a\u043e\u0440\u043e\u043d\u0430"
    ],
    "wof:name":"Korona",
    "wof:placetype":"locality"
},
  "geometry": {"coordinates":[-7.9247,12.1625],"type":"Point"}
}