{
  "type": "Feature",
  "properties": {
    "gn:admin1_code":"05",
    "gn:asciiname":"Samango",
    "gn:country_code":"ML",
    "gn:dem":288,
    "gn:feature_class":"P",
    "gn:feature_code":"PPL",
    "gn:name":"Samango",
    "gn:population":0,
    "gn:timezone":"Africa/Bamako",
    "iso:country":"ML",
    "name:fra_x_preferred":[
        "Samango"
    ],
    "name:ita_x_preferred":[
        "Samango"
    ],
    "name:msa_x_preferred":[
        "Samango"
    ],
    "name:ron_x_preferred":[
        "Samango"
    ],
    "name:und_x_variant":[
        "Samankou"
    ],
    "wof:name":"Samango",
    "wof:placetype":"locality"
},
  "geometry": {"coordinates":[-6.37506,13.70275],"type":"Point"}
}