{
  "type": "Feature",
  "properties": {
    "gn:admin1_code":"04",
    "gn:asciiname":"Gore",
    "gn:country_code":"ML",
    "gn:dem":265,
    "gn:feature_class":"P",
    "gn:feature_code":"PPL",
    "gn:name":"Gor\u00e9",
    "gn:population":0,
    "gn:timezone":"Africa/Bamako",
    "iso:country":"ML",
    "name:bos_x_preferred":[
        "Gore"
    ],
    "name:cat_x_preferred":[
        "Gore"
    ],
    "name:ceb_x_preferred":[
        "Gore"
    ],
    "name:ces_x_preferred":[
        "Gore"
    ],
    "name:deu_x_preferred":[
        "Gore"
    ],
    "name:fas_x_preferred":[
        "\u06af\u0648\u0631"
    ],
    "name:fin_x_preferred":[
        "Gore"
    ],
    "name:fra_x_preferred":[
        "Gore"
    ],
    "name:heb_x_preferred":[
        "\u05d2\u05d5\u05e8\u05d4"
    ],
    "name:heb_x_variant":[
        "\u05d2\u05d5\u05e8"
    ],
    "name:hin_x_preferred":[
        "\u0917\u094b\u0930\u0947"
    ],
    "name:hun_x_preferred":[
        "Gore"
    ],
    "name:ind_x_preferred":[
        "Gore"
    ],
    "name:ita_x_preferred":[
        "Gore"
    ],
    "name:kor_x_preferred":[
        "\uace0\ub9ac"
    ],
    "name:lit_x_preferred":[
        "Gore"
    ],
    "name:nld_x_preferred":[
        "Gore"
    ],
    "name:pol_x_preferred":[
        "Gore"
    ],
    "name:por_x_preferred":[
        "Gore"
    ],
    "name:rus_x_preferred":[
        "\u0413\u043e\u0440\u0435"
    ],
    "name:slv_x_preferred":[
        "Gore"
    ],
    "name:spa_x_preferred":[
        "Gore"
    ],
    "name:srp_x_preferred":[
        "\u0413\u043e\u0440\u0435"
    ],
    "name:swe_x_preferred":[
        "Gore"
    ],
    "name:tur_x_preferred":[
        "Gore"
    ],
    "name:ukr_x_preferred":[
        "\u0413\u043e\u0440\u0435"
    ],
    "name:urd_x_preferred":[
        "\u06af\u0648\u0631\u06d2"
    ],
    "name:vie_x_preferred":[
        "Gore"
    ],
    "name:vol_x_preferred":[
        "Gore"
    ],
    "name:zho_cn_x_preferred":[
        "\u6208\u5c14"
    ],
    "name:zho_tw_x_preferred":[
        "\u6208\u723e"
    ],
    "wof:name":"Gore",
    "wof:placetype":"locality"
},
  "geometry": {"coordinates":[-4.1443,15.5872],"type":"Point"}
}