{
  "type": "Feature",
  "properties": {
    "gn:admin1_code":"04",
    "gn:asciiname":"Bouta",
    "gn:country_code":"ML",
    "gn:dem":264,
    "gn:feature_class":"P",
    "gn:feature_code":"PPL",
    "gn:name":"Bouta",
    "gn:population":0,
    "gn:timezone":"Africa/Bamako",
    "iso:country":"ML",
    "wof:name":"Bouta",
    "wof:placetype":"locality"
},
  "geometry": {"coordinates":[-4.5335,15.5376],"type":"Point"}
}