{
  "type": "Feature",
  "properties": {
    "gn:admin1_code":"06",
    "gn:asciiname":"Kokodio",
    "gn:country_code":"ML",
    "gn:dem":336,
    "gn:feature_class":"P",
    "gn:feature_code":"PPL",
    "gn:name":"Kokodio",
    "gn:population":0,
    "gn:timezone":"Africa/Bamako",
    "iso:country":"ML",
    "name:fra_x_preferred":[
        "Kokodio"
    ],
    "name:fra_x_variant":[
        "Korodiou"
    ],
    "name:und_x_variant":[
        "Korodiou"
    ],
    "wof:name":"Kokodio",
    "wof:placetype":"locality"
},
  "geometry": {"coordinates":[-6.87034,11.44356],"type":"Point"}
}