{
  "type": "Feature",
  "properties": {
    "gn:admin1_code":"06",
    "gn:asciiname":"Tiarakassedougou",
    "gn:country_code":"ML",
    "gn:dem":326,
    "gn:feature_class":"P",
    "gn:feature_code":"PPL",
    "gn:name":"Tiarakass\u00e9dougou",
    "gn:population":0,
    "gn:timezone":"Africa/Bamako",
    "iso:country":"ML",
    "wof:name":"Tiarakassedougou",
    "wof:placetype":"locality"
},
  "geometry": {"coordinates":[-5.70043,12.2578],"type":"Point"}
}