{
  "type": "Feature",
  "properties": {
    "gn:admin1_code":"5.0",
    "gn:asciiname":"Ouondo",
    "gn:country_code":"ML",
    "gn:dem":330,
    "gn:feature_class":"P",
    "gn:feature_code":"PPL",
    "gn:name":"Ouondo",
    "gn:population":0,
    "gn:timezone":"Africa/Bamako",
    "iso:country":"ML",
    "wof:name":"Ouondo",
    "wof:placetype":"locality"
},
  "geometry": {"coordinates":[-6.76966,13.03091],"type":"Point"}
}