{
  "type": "Feature",
  "properties": {
    "gn:admin1_code":"5.0",
    "gn:asciiname":"Bolokounou",
    "gn:country_code":"ML",
    "gn:dem":292,
    "gn:feature_class":"P",
    "gn:feature_code":"PPL",
    "gn:name":"Bolokounou",
    "gn:population":0,
    "gn:timezone":"Africa/Bamako",
    "iso:country":"ML",
    "wof:name":"Bolokounou",
    "wof:placetype":"locality"
},
  "geometry": {"coordinates":[-4.66266,13.02847],"type":"Point"}
}