{
  "type": "Feature",
  "properties": {
    "gn:admin1_code":"04",
    "gn:asciiname":"Were",
    "gn:country_code":"ML",
    "gn:dem":359,
    "gn:feature_class":"P",
    "gn:feature_code":"PPL",
    "gn:name":"W\u00e9r\u00e9",
    "gn:population":0,
    "gn:timezone":"Africa/Bamako",
    "iso:country":"ML",
    "name:und_x_variant":[
        "Ou\u00e9r\u00e9",
        "V\u00e9r\u00e9",
        "W\u00e9r\u00e9"
    ],
    "wof:name":"Were",
    "wof:placetype":"locality"
},
  "geometry": {"coordinates":[-3.19859,14.6006],"type":"Point"}
}