{
  "type": "Feature",
  "properties": {
    "gn:admin1_code":"07",
    "gn:asciiname":"Foinye",
    "gn:country_code":"ML",
    "gn:dem":256,
    "gn:feature_class":"P",
    "gn:feature_code":"PPL",
    "gn:name":"Foiny\u00e9",
    "gn:population":0,
    "gn:timezone":"Africa/Bamako",
    "iso:country":"ML",
    "name:und_x_variant":[
        "Fo\u00efniat",
        "Fo\u00efni\u00e9",
        "Foiny\u00e9"
    ],
    "wof:name":"Foinye",
    "wof:placetype":"locality"
},
  "geometry": {"coordinates":[-8.70129,15.48303],"type":"Point"}
}