{
  "type": "Feature",
  "properties": {
    "gn:admin1_code":"04",
    "gn:asciiname":"Kamba-Bandie",
    "gn:country_code":"ML",
    "gn:dem":531,
    "gn:feature_class":"P",
    "gn:feature_code":"PPL",
    "gn:name":"Kamba-Bandi\u00e9",
    "gn:population":0,
    "gn:timezone":"Africa/Bamako",
    "iso:country":"ML",
    "wof:name":"Kamba-Bandie",
    "wof:placetype":"locality"
},
  "geometry": {"coordinates":[-3.39908,14.42717],"type":"Point"}
}