{
  "type": "Feature",
  "properties": {
    "gn:admin1_code":"07",
    "gn:asciiname":"Sanmbe",
    "gn:country_code":"ML",
    "gn:dem":282,
    "gn:feature_class":"P",
    "gn:feature_code":"PPL",
    "gn:name":"Sanmb\u00e9",
    "gn:population":0,
    "gn:timezone":"Africa/Bamako",
    "iso:country":"ML",
    "name:und_x_variant":[
        "Samb\u00e9",
        "Sanmb\u00e9"
    ],
    "wof:name":"Sanmbe",
    "wof:placetype":"locality"
},
  "geometry": {"coordinates":[-7.9817,15.1126],"type":"Point"}
}