{
  "type": "Feature",
  "properties": {
    "gn:admin1_code":"06",
    "gn:asciiname":"Kaniko",
    "gn:country_code":"ML",
    "gn:dem":352,
    "gn:feature_class":"P",
    "gn:feature_code":"PPL",
    "gn:name":"Kaniko",
    "gn:population":0,
    "gn:timezone":"Africa/Bamako",
    "iso:country":"ML",
    "wof:name":"Kaniko",
    "wof:placetype":"locality"
},
  "geometry": {"coordinates":[-5.36429,12.32112],"type":"Point"}
}