{
  "type": "Feature",
  "properties": {
    "gn:admin1_code":"00",
    "gn:asciiname":"Siboro Tounbo",
    "gn:country_code":"ML",
    "gn:dem":317,
    "gn:feature_class":"P",
    "gn:feature_code":"PPL",
    "gn:name":"Siboro Tounbo",
    "gn:population":0,
    "gn:timezone":"Africa/Bamako",
    "iso:country":"ML",
    "wof:name":"Siboro Tounbo",
    "wof:placetype":"locality"
},
  "geometry": {"coordinates":[-10.38333,12.23333],"type":"Point"}
}