{
  "type": "Feature",
  "properties": {
    "gn:admin1_code":"8.0",
    "gn:asciiname":"Banikane",
    "gn:country_code":"ML",
    "gn:dem":258,
    "gn:feature_class":"P",
    "gn:feature_code":"PPL",
    "gn:name":"Banikane",
    "gn:population":0,
    "gn:timezone":"Africa/Bamako",
    "iso:country":"ML",
    "name:fin_x_preferred":[
        "Banikane"
    ],
    "name:fra_x_preferred":[
        "Banikane"
    ],
    "name:ita_x_preferred":[
        "Banikane"
    ],
    "name:nld_x_preferred":[
        "Banikane"
    ],
    "name:spa_x_preferred":[
        "Banikane"
    ],
    "name:und_x_variant":[
        "Banekane",
        "Banikan",
        "Banikane"
    ],
    "name:zho_x_preferred":[
        "\u5df4\u5167\u5361\u5167"
    ],
    "wof:name":"Banikane",
    "wof:placetype":"locality"
},
  "geometry": {"coordinates":[-1.74806,16.94944],"type":"Point"}
}