{
  "type": "Feature",
  "properties": {
    "gn:admin1_code":"03",
    "gn:asciiname":"Dambala",
    "gn:country_code":"ML",
    "gn:dem":371,
    "gn:feature_class":"P",
    "gn:feature_code":"PPL",
    "gn:name":"Dambala",
    "gn:population":0,
    "gn:timezone":"Africa/Bamako",
    "iso:country":"ML",
    "name:und_x_variant":[
        "Danbala",
        "Dambala"
    ],
    "wof:name":"Dambala",
    "wof:placetype":"locality"
},
  "geometry": {"coordinates":[-11.39324,12.19501],"type":"Point"}
}