{
  "type": "Feature",
  "properties": {
    "gn:admin1_code":"7.0",
    "gn:asciiname":"Fara",
    "gn:country_code":"ML",
    "gn:dem":415,
    "gn:feature_class":"P",
    "gn:feature_code":"PPL",
    "gn:name":"Fara",
    "gn:population":0,
    "gn:timezone":"Africa/Bamako",
    "iso:country":"ML",
    "wof:name":"Fara",
    "wof:placetype":"locality"
},
  "geometry": {"coordinates":[-7.93859,13.43523],"type":"Point"}
}