{
  "type": "Feature",
  "properties": {
    "gn:admin1_code":"06",
    "gn:asciiname":"Klela",
    "gn:country_code":"ML",
    "gn:dem":327,
    "gn:feature_class":"P",
    "gn:feature_code":"PPL",
    "gn:name":"Kl\u00e9la",
    "gn:population":0,
    "gn:timezone":"Africa/Bamako",
    "iso:country":"ML",
    "name:fin_x_preferred":[
        "Kl\u00e9la"
    ],
    "name:fra_x_preferred":[
        "Kl\u00e9la"
    ],
    "name:ita_x_preferred":[
        "Kl\u00e9la"
    ],
    "name:nld_x_preferred":[
        "Kl\u00e9la"
    ],
    "name:por_x_preferred":[
        "Clela"
    ],
    "name:spa_x_preferred":[
        "Kl\u00e9la"
    ],
    "name:und_x_variant":[
        "K\u00e9l\u00e9la",
        "Ki\u00e9la"
    ],
    "name:zho_x_preferred":[
        "\u514b\u840a\u62c9"
    ],
    "wof:name":"Klela",
    "wof:placetype":"locality"
},
  "geometry": {"coordinates":[-5.66409,11.68749],"type":"Point"}
}