{
  "type": "Feature",
  "properties": {
    "gn:admin1_code":"07",
    "gn:asciiname":"Djidie",
    "gn:country_code":"ML",
    "gn:dem":381,
    "gn:feature_class":"P",
    "gn:feature_code":"PPL",
    "gn:name":"Djidi\u00e9",
    "gn:population":0,
    "gn:timezone":"Africa/Bamako",
    "iso:country":"ML",
    "name:fra_x_preferred":[
        "Dyidy\u00e9"
    ],
    "name:fra_x_variant":[
        "Guidi\u00e9ni"
    ],
    "name:und_x_variant":[
        "Guidi\u00e9ni",
        "Djidi\u00e9",
        "Dyidy\u00e9"
    ],
    "wof:name":"Djidie",
    "wof:placetype":"locality"
},
  "geometry": {"coordinates":[-8.2712,13.038],"type":"Point"}
}