{
  "type": "Feature",
  "properties": {
    "gn:admin1_code":"05",
    "gn:asciiname":"Dangougouni",
    "gn:country_code":"ML",
    "gn:dem":283,
    "gn:feature_class":"P",
    "gn:feature_code":"PPL",
    "gn:name":"Dangougouni",
    "gn:population":0,
    "gn:timezone":"Africa/Bamako",
    "iso:country":"ML",
    "name:und_x_variant":[
        "Tofini",
        "Dangougouni"
    ],
    "wof:name":"Dangougouni",
    "wof:placetype":"locality"
},
  "geometry": {"coordinates":[-4.2753,13.8579],"type":"Point"}
}