{
  "type": "Feature",
  "properties": {
    "gn:admin1_code":"06",
    "gn:asciiname":"Niantanso",
    "gn:country_code":"ML",
    "gn:dem":389,
    "gn:feature_class":"P",
    "gn:feature_code":"PPL",
    "gn:name":"Niantanso",
    "gn:population":0,
    "gn:timezone":"Africa/Bamako",
    "iso:country":"ML",
    "name:fin_x_preferred":[
        "Niantanso"
    ],
    "name:fra_x_preferred":[
        "Nadinso"
    ],
    "name:fra_x_variant":[
        "Niantanso"
    ],
    "name:ita_x_preferred":[
        "Niantanso"
    ],
    "name:nld_x_preferred":[
        "Niantanso"
    ],
    "name:spa_x_preferred":[
        "Niantanso"
    ],
    "wof:name":"Niantanso",
    "wof:placetype":"locality"
},
  "geometry": {"coordinates":[-6.00696,11.26851],"type":"Point"}
}