{
  "type": "Feature",
  "properties": {
    "gn:admin1_code":"07",
    "gn:asciiname":"Samakorola",
    "gn:country_code":"ML",
    "gn:dem":375,
    "gn:feature_class":"P",
    "gn:feature_code":"PPL",
    "gn:name":"Samakorola",
    "gn:population":0,
    "gn:timezone":"Africa/Bamako",
    "iso:country":"ML",
    "name:fra_x_preferred":[
        "Samakorola"
    ],
    "wof:name":"Samakorola",
    "wof:placetype":"locality"
},
  "geometry": {"coordinates":[-8.0703,13.9576],"type":"Point"}
}