{
  "type": "Feature",
  "properties": {
    "gn:admin1_code":"03",
    "gn:asciiname":"Guetema",
    "gn:country_code":"ML",
    "gn:dem":308,
    "gn:feature_class":"P",
    "gn:feature_code":"PPL",
    "gn:name":"Gu\u00e9t\u00e9ma",
    "gn:population":0,
    "gn:timezone":"Africa/Bamako",
    "iso:country":"ML",
    "name:fra_x_preferred":[
        "Gu\u00e9t\u00e9ma"
    ],
    "name:ita_x_preferred":[
        "Gu\u00e9t\u00e9ma"
    ],
    "name:nld_x_preferred":[
        "Gu\u00e9t\u00e9ma"
    ],
    "name:spa_x_preferred":[
        "Gu\u00e9t\u00e9ma"
    ],
    "wof:name":"Guetema",
    "wof:placetype":"locality"
},
  "geometry": {"coordinates":[-9.58306,15.12075],"type":"Point"}
}