{
  "type": "Feature",
  "properties": {
    "gn:admin1_code":"00",
    "gn:asciiname":"Tyeba",
    "gn:country_code":"ML",
    "gn:dem":356,
    "gn:feature_class":"P",
    "gn:feature_code":"PPL",
    "gn:name":"Ty\u00e9ba",
    "gn:population":0,
    "gn:timezone":"Africa/Bamako",
    "iso:country":"ML",
    "wof:name":"Tyeba",
    "wof:placetype":"locality"
},
  "geometry": {"coordinates":[-8.73333,12.85],"type":"Point"}
}