{
  "type": "Feature",
  "properties": {
    "gn:admin1_code":"00",
    "gn:asciiname":"Kona",
    "gn:country_code":"ML",
    "gn:dem":357,
    "gn:feature_class":"P",
    "gn:feature_code":"PPL",
    "gn:name":"Kona",
    "gn:population":0,
    "gn:timezone":"Africa/Bamako",
    "iso:country":"ML",
    "name:cat_x_preferred":[
        "Kona"
    ],
    "name:ceb_x_preferred":[
        "Kona"
    ],
    "name:dan_x_preferred":[
        "Kona"
    ],
    "name:deu_x_preferred":[
        "Kona"
    ],
    "name:fin_x_preferred":[
        "Kona"
    ],
    "name:fra_x_preferred":[
        "Kona"
    ],
    "name:nno_x_preferred":[
        "Kona"
    ],
    "name:spa_x_preferred":[
        "Kona"
    ],
    "name:swe_x_preferred":[
        "Kona"
    ],
    "wof:name":"Kona",
    "wof:placetype":"locality"
},
  "geometry": {"coordinates":[-8.35,11.25],"type":"Point"}
}