{
  "type": "Feature",
  "properties": {
    "gn:admin1_code":"00",
    "gn:asciiname":"Zeguere",
    "gn:cc2":"ML",
    "gn:country_code":"ML",
    "gn:dem":361,
    "gn:feature_class":"P",
    "gn:feature_code":"PPL",
    "gn:name":"Z\u00e9gu\u00e9r\u00e9",
    "gn:population":0,
    "gn:timezone":"Africa/Bamako",
    "iso:country":"ML",
    "name:und_x_variant":[
        "Nz\u00e9gu\u00e9r\u00e9",
        "Z\u00e9gu\u00e9r\u00e9"
    ],
    "wof:name":"Zeguere",
    "wof:placetype":"locality"
},
  "geometry": {"coordinates":[-6.73333,10.58333],"type":"Point"}
}