{
  "type": "Feature",
  "properties": {
    "gn:admin1_code":"05",
    "gn:asciiname":"Goudjikoro",
    "gn:country_code":"ML",
    "gn:dem":266,
    "gn:feature_class":"P",
    "gn:feature_code":"PPL",
    "gn:name":"Goudjikoro",
    "gn:population":0,
    "gn:timezone":"Africa/Bamako",
    "iso:country":"ML",
    "name:fra_x_preferred":[
        "Goudjikoro"
    ],
    "name:fra_x_variant":[
        "Kodji",
        "Kodii"
    ],
    "wof:name":"Goudjikoro",
    "wof:placetype":"locality"
},
  "geometry": {"coordinates":[-6.5592,14.31972],"type":"Point"}
}