{
  "type": "Feature",
  "properties": {
    "gn:admin1_code":"3.0",
    "gn:asciiname":"Balabougou",
    "gn:country_code":"ML",
    "gn:dem":394,
    "gn:feature_class":"P",
    "gn:feature_code":"PPL",
    "gn:name":"Balabougou",
    "gn:population":0,
    "gn:timezone":"Africa/Bamako",
    "iso:country":"ML",
    "wof:name":"Balabougou",
    "wof:placetype":"locality"
},
  "geometry": {"coordinates":[-8.82353,12.87501],"type":"Point"}
}