{
  "type": "Feature",
  "properties": {
    "gn:admin1_code":"06",
    "gn:asciiname":"Diati",
    "gn:country_code":"ML",
    "gn:dem":308,
    "gn:feature_class":"P",
    "gn:feature_code":"PPL",
    "gn:name":"Diati",
    "gn:population":0,
    "gn:timezone":"Africa/Bamako",
    "iso:country":"ML",
    "name:und_x_variant":[
        "Datien",
        "Diati"
    ],
    "wof:name":"Diati",
    "wof:placetype":"locality"
},
  "geometry": {"coordinates":[-5.29583,12.5586],"type":"Point"}
}