{
  "type": "Feature",
  "properties": {
    "gn:admin1_code":"0.0",
    "gn:asciiname":"Batanga",
    "gn:country_code":"ML",
    "gn:dem":264,
    "gn:feature_class":"P",
    "gn:feature_code":"PPL",
    "gn:name":"Batanga",
    "gn:population":0,
    "gn:timezone":"Africa/Bamako",
    "iso:country":"ML",
    "name:ceb_x_preferred":[
        "Batanga"
    ],
    "name:fra_x_preferred":[
        "Batanga"
    ],
    "name:swe_x_preferred":[
        "Batanga"
    ],
    "wof:name":"Batanga",
    "wof:placetype":"locality"
},
  "geometry": {"coordinates":[-0.77579,17.00368],"type":"Point"}
}