{
  "type": "Feature",
  "properties": {
    "gn:admin1_code":"7.0",
    "gn:asciiname":"Sananfalani",
    "gn:country_code":"ML",
    "gn:dem":407,
    "gn:feature_class":"P",
    "gn:feature_code":"PPL",
    "gn:name":"Sananfalani",
    "gn:population":0,
    "gn:timezone":"Africa/Bamako",
    "iso:country":"ML",
    "wof:name":"Sananfalani",
    "wof:placetype":"locality"
},
  "geometry": {"coordinates":[-8.18001,12.88315],"type":"Point"}
}