{
  "type": "Feature",
  "properties": {
    "gn:admin1_code":"04",
    "gn:asciiname":"Nimitogo",
    "gn:country_code":"ML",
    "gn:dem":268,
    "gn:feature_class":"P",
    "gn:feature_code":"PPL",
    "gn:name":"Nimitogo",
    "gn:population":0,
    "gn:timezone":"Africa/Bamako",
    "iso:country":"ML",
    "name:und_x_variant":[
        "Nimitongo",
        "Nimitogo"
    ],
    "wof:name":"Nimitogo",
    "wof:placetype":"locality"
},
  "geometry": {"coordinates":[-4.17759,14.59467],"type":"Point"}
}