{
  "type": "Feature",
  "properties": {
    "gn:admin1_code":"7.0",
    "gn:asciiname":"Banankoro",
    "gn:country_code":"ML",
    "gn:dem":312,
    "gn:feature_class":"P",
    "gn:feature_code":"PPL",
    "gn:name":"Banankoro",
    "gn:population":0,
    "gn:timezone":"Africa/Bamako",
    "iso:country":"ML",
    "name:ceb_x_preferred":[
        "Banankoro"
    ],
    "name:swe_x_preferred":[
        "Banankoro"
    ],
    "wof:name":"Banankoro",
    "wof:placetype":"locality"
},
  "geometry": {"coordinates":[-7.14705,13.08605],"type":"Point"}
}