{
  "type": "Feature",
  "properties": {
    "gn:admin1_code":"06",
    "gn:asciiname":"Diensobala",
    "gn:country_code":"ML",
    "gn:dem":359,
    "gn:feature_class":"P",
    "gn:feature_code":"PPL",
    "gn:name":"Di\u00e8nsobala",
    "gn:population":0,
    "gn:timezone":"Africa/Bamako",
    "iso:country":"ML",
    "name:und_x_variant":[
        "Dyensobala",
        "Di\u00e8nsobala"
    ],
    "wof:name":"Diensobala",
    "wof:placetype":"locality"
},
  "geometry": {"coordinates":[-7.33981,12.03524],"type":"Point"}
}