{
  "type": "Feature",
  "properties": {
    "gn:admin1_code":"3.0",
    "gn:asciiname":"Boli Bana",
    "gn:country_code":"ML",
    "gn:dem":38,
    "gn:feature_class":"P",
    "gn:feature_code":"PPL",
    "gn:name":"Boli Bana",
    "gn:population":0,
    "gn:timezone":"Africa/Bamako",
    "iso:country":"ML",
    "wof:name":"Boli Bana",
    "wof:placetype":"locality"
},
  "geometry": {"coordinates":[-12.19554,14.47914],"type":"Point"}
}