{
  "type": "Feature",
  "properties": {
    "gn:admin1_code":"4.0",
    "gn:asciiname":"Dougo",
    "gn:country_code":"ML",
    "gn:dem":527,
    "gn:feature_class":"P",
    "gn:feature_code":"PPL",
    "gn:name":"Dougo",
    "gn:population":0,
    "gn:timezone":"Africa/Bamako",
    "iso:country":"ML",
    "wof:name":"Dougo",
    "wof:placetype":"locality"
},
  "geometry": {"coordinates":[-3.6972,14.8048],"type":"Point"}
}