{
  "type": "Feature",
  "properties": {
    "gn:admin1_code":"04",
    "gn:asciiname":"Kouna",
    "gn:country_code":"ML",
    "gn:dem":268,
    "gn:feature_class":"P",
    "gn:feature_code":"PPL",
    "gn:name":"Kouna",
    "gn:population":0,
    "gn:timezone":"Africa/Bamako",
    "iso:country":"ML",
    "wof:name":"Kouna",
    "wof:placetype":"locality"
},
  "geometry": {"coordinates":[-4.6784,14.45183],"type":"Point"}
}