{
  "type": "Feature",
  "properties": {
    "gn:admin1_code":"4.0",
    "gn:asciiname":"Sego",
    "gn:country_code":"ML",
    "gn:dem":581,
    "gn:feature_class":"P",
    "gn:feature_code":"PPL",
    "gn:name":"S\u00e9go",
    "gn:population":0,
    "gn:timezone":"Africa/Bamako",
    "iso:country":"ML",
    "wof:name":"Sego",
    "wof:placetype":"locality"
},
  "geometry": {"coordinates":[-3.50289,14.8322],"type":"Point"}
}