{
  "type": "Feature",
  "properties": {
    "gn:admin1_code":"08",
    "gn:asciiname":"Dabara",
    "gn:country_code":"ML",
    "gn:dem":273,
    "gn:feature_class":"P",
    "gn:feature_code":"PPL",
    "gn:name":"Dabara",
    "gn:population":0,
    "gn:timezone":"Africa/Bamako",
    "iso:country":"ML",
    "name:fas_x_preferred":[
        "\u062f\u0627\u0628\u0627\u0631\u0627"
    ],
    "name:urd_x_preferred":[
        "\u062f\u0627\u0628\u0627\u0631\u0627"
    ],
    "wof:name":"Dabara",
    "wof:placetype":"locality"
},
  "geometry": {"coordinates":[-3.5602,15.7024],"type":"Point"}
}