{
  "type": "Feature",
  "properties": {
    "gn:admin1_code":"6.0",
    "gn:asciiname":"Waibera",
    "gn:country_code":"ML",
    "gn:dem":523,
    "gn:feature_class":"P",
    "gn:feature_code":"PPL",
    "gn:name":"Wa\u00efb\u00e9ra",
    "gn:population":0,
    "gn:timezone":"Africa/Bamako",
    "iso:country":"ML",
    "wof:name":"Waibera",
    "wof:placetype":"locality"
},
  "geometry": {"coordinates":[-5.67335,11.06664],"type":"Point"}
}