{
  "type": "Feature",
  "properties": {
    "gn:admin1_code":"04",
    "gn:asciiname":"Tirere",
    "gn:country_code":"ML",
    "gn:dem":263,
    "gn:feature_class":"P",
    "gn:feature_code":"PPL",
    "gn:name":"Tirer\u00e9",
    "gn:population":0,
    "gn:timezone":"Africa/Bamako",
    "iso:country":"ML",
    "name:und_x_variant":[
        "Till\u00e9r\u00e9",
        "Tirer\u00e9"
    ],
    "wof:name":"Tirere",
    "wof:placetype":"locality"
},
  "geometry": {"coordinates":[-3.2643,15.2243],"type":"Point"}
}