{
  "type": "Feature",
  "properties": {
    "gn:admin1_code":"00",
    "gn:asciiname":"Gouanso",
    "gn:cc2":"ML",
    "gn:country_code":"ML",
    "gn:dem":345,
    "gn:feature_class":"P",
    "gn:feature_code":"PPL",
    "gn:name":"Gouanso",
    "gn:population":0,
    "gn:timezone":"Africa/Bamako",
    "iso:country":"ML",
    "name:und_x_variant":[
        "Gouansso",
        "Guenso",
        "Gouanso"
    ],
    "wof:name":"Gouanso",
    "wof:placetype":"locality"
},
  "geometry": {"coordinates":[-8.13333,11.28333],"type":"Point"}
}