{
  "type": "Feature",
  "properties": {
    "gn:admin1_code":"07",
    "gn:asciiname":"Dienindie",
    "gn:country_code":"ML",
    "gn:dem":321,
    "gn:feature_class":"P",
    "gn:feature_code":"PPL",
    "gn:name":"Di\u00e8nindi\u00e8",
    "gn:population":0,
    "gn:timezone":"Africa/Bamako",
    "iso:country":"ML",
    "name:und_x_variant":[
        "Dj\u00e9nindi\u00e9",
        "Guininndi\u00e9",
        "Di\u00e8nindi\u00e8"
    ],
    "wof:name":"Dienindie",
    "wof:placetype":"locality"
},
  "geometry": {"coordinates":[-7.38514,13.37783],"type":"Point"}
}