{
  "type": "Feature",
  "properties": {
    "gn:admin1_code":"06",
    "gn:asciiname":"Nenerebougou",
    "gn:country_code":"ML",
    "gn:dem":362,
    "gn:feature_class":"P",
    "gn:feature_code":"PPL",
    "gn:name":"N\u00e8n\u00e8r\u00e8bougou",
    "gn:population":0,
    "gn:timezone":"Africa/Bamako",
    "iso:country":"ML",
    "name:fra_x_preferred":[
        "N\u00e8n\u00e8r\u00e8bougou"
    ],
    "wof:name":"Nenerebougou",
    "wof:placetype":"locality"
},
  "geometry": {"coordinates":[-6.0281,12.0488],"type":"Point"}
}