{
  "type": "Feature",
  "properties": {
    "gn:admin1_code":"05",
    "gn:asciiname":"Marakabougou",
    "gn:country_code":"ML",
    "gn:dem":286,
    "gn:feature_class":"P",
    "gn:feature_code":"PPL",
    "gn:name":"Marakabougou",
    "gn:population":0,
    "gn:timezone":"Africa/Bamako",
    "iso:country":"ML",
    "name:und_x_variant":[
        "Markadougou",
        "Markan\u00e9bougou",
        "Markabougou",
        "Marakabougou"
    ],
    "wof:name":"Marakabougou",
    "wof:placetype":"locality"
},
  "geometry": {"coordinates":[-6.34736,13.91394],"type":"Point"}
}