{
  "type": "Feature",
  "properties": {
    "gn:admin1_code":"3.0",
    "gn:asciiname":"Sebefe",
    "gn:country_code":"ML",
    "gn:dem":342,
    "gn:feature_class":"P",
    "gn:feature_code":"PPL",
    "gn:name":"S\u00e9b\u00e9f\u00e9",
    "gn:population":0,
    "gn:timezone":"Africa/Bamako",
    "iso:country":"ML",
    "wof:name":"Sebefe",
    "wof:placetype":"locality"
},
  "geometry": {"coordinates":[-9.2435,13.0052],"type":"Point"}
}