{
  "type": "Feature",
  "properties": {
    "gn:admin1_code":"06",
    "gn:asciiname":"Koloni",
    "gn:country_code":"ML",
    "gn:dem":446,
    "gn:feature_class":"P",
    "gn:feature_code":"PPL",
    "gn:name":"Koloni",
    "gn:population":0,
    "gn:timezone":"Africa/Bamako",
    "iso:country":"ML",
    "name:hye_x_preferred":[
        "\u053f\u0578\u056c\u0578\u0576\u056b"
    ],
    "name:por_x_preferred":[
        "Coloni"
    ],
    "wof:name":"Koloni",
    "wof:placetype":"locality"
},
  "geometry": {"coordinates":[-4.5842,12.3604],"type":"Point"}
}