{
  "type": "Feature",
  "properties": {
    "gn:admin1_code":"06",
    "gn:asciiname":"Fonfana",
    "gn:country_code":"ML",
    "gn:dem":295,
    "gn:feature_class":"P",
    "gn:feature_code":"PPL",
    "gn:name":"Fonfana",
    "gn:population":0,
    "gn:timezone":"Africa/Bamako",
    "iso:country":"ML",
    "wof:name":"Fonfana",
    "wof:placetype":"locality"
},
  "geometry": {"coordinates":[-5.61623,12.6743],"type":"Point"}
}