{
  "type": "Feature",
  "properties": {
    "gn:admin1_code":"0.0",
    "gn:asciiname":"Banbafara",
    "gn:country_code":"ML",
    "gn:dem":286,
    "gn:feature_class":"P",
    "gn:feature_code":"PPL",
    "gn:name":"Banbafara",
    "gn:population":0,
    "gn:timezone":"Africa/Bamako",
    "iso:country":"ML",
    "wof:name":"Banbafara",
    "wof:placetype":"locality"
},
  "geometry": {"coordinates":[-9.53333,12.83333],"type":"Point"}
}