{
  "type": "Feature",
  "properties": {
    "gn:admin1_code":"4.0",
    "gn:asciiname":"Sobodi",
    "gn:country_code":"ML",
    "gn:dem":574,
    "gn:feature_class":"P",
    "gn:feature_code":"PPL",
    "gn:name":"Sobodi",
    "gn:population":0,
    "gn:timezone":"Africa/Bamako",
    "iso:country":"ML",
    "wof:name":"Sobodi",
    "wof:placetype":"locality"
},
  "geometry": {"coordinates":[-3.21743,14.62107],"type":"Point"}
}