{
  "type": "Feature",
  "properties": {
    "gn:admin1_code":"7.0",
    "gn:asciiname":"Tchitcherela",
    "gn:country_code":"ML",
    "gn:dem":356,
    "gn:feature_class":"P",
    "gn:feature_code":"PPL",
    "gn:name":"Tchitch\u00e9r\u00e9la",
    "gn:population":0,
    "gn:timezone":"Africa/Bamako",
    "iso:country":"ML",
    "wof:name":"Tchitcherela",
    "wof:placetype":"locality"
},
  "geometry": {"coordinates":[-7.68988,13.42435],"type":"Point"}
}