{
  "type": "Feature",
  "properties": {
    "gn:admin1_code":"4.0",
    "gn:asciiname":"San",
    "gn:country_code":"ML",
    "gn:dem":292,
    "gn:feature_class":"P",
    "gn:feature_code":"PPL",
    "gn:name":"San",
    "gn:population":0,
    "gn:timezone":"Africa/Bamako",
    "iso:country":"ML",
    "name:ben_x_preferred":[
        "\u09b8\u09be\u09a8"
    ],
    "name:ell_x_preferred":[
        "\u03a3\u03b1\u03bd"
    ],
    "name:heb_x_preferred":[
        "\u05e1\u05d0\u05df"
    ],
    "name:hin_x_preferred":[
        "\u0938\u0948\u0928"
    ],
    "name:hun_x_preferred":[
        "San"
    ],
    "name:ind_x_preferred":[
        "San"
    ],
    "name:kor_x_preferred":[
        "\uc0b0"
    ],
    "name:tur_x_preferred":[
        "San"
    ],
    "name:ukr_x_preferred":[
        "\u0421\u0430\u043d"
    ],
    "name:urd_x_preferred":[
        "\u0633\u0627\u0646"
    ],
    "name:vie_x_preferred":[
        "San"
    ],
    "wof:name":"San",
    "wof:placetype":"locality"
},
  "geometry": {"coordinates":[-2.11567,14.35787],"type":"Point"}
}