{
  "type": "Feature",
  "properties": {
    "gn:admin1_code":"04",
    "gn:asciiname":"Ngoro",
    "gn:country_code":"ML",
    "gn:dem":426,
    "gn:feature_class":"P",
    "gn:feature_code":"PPL",
    "gn:name":"Ngoro",
    "gn:population":0,
    "gn:timezone":"Africa/Bamako",
    "iso:country":"ML",
    "name:und_x_variant":[
        "Koro",
        "Ngoro"
    ],
    "wof:name":"Ngoro",
    "wof:placetype":"locality"
},
  "geometry": {"coordinates":[-3.77679,14.3246],"type":"Point"}
}