{
  "type": "Feature",
  "properties": {
    "gn:admin1_code":"9.0",
    "gn:asciiname":"Gougouma Koina",
    "gn:country_code":"ML",
    "gn:dem":254,
    "gn:feature_class":"P",
    "gn:feature_code":"PPL",
    "gn:name":"Gougouma Ko\u00efna",
    "gn:population":0,
    "gn:timezone":"Africa/Bamako",
    "iso:country":"ML",
    "wof:name":"Gougouma Koina",
    "wof:placetype":"locality"
},
  "geometry": {"coordinates":[0.6808,15.457],"type":"Point"}
}