{
  "type": "Feature",
  "properties": {
    "gn:admin1_code":"4.0",
    "gn:asciiname":"Kori-Maounde",
    "gn:country_code":"ML",
    "gn:dem":364,
    "gn:feature_class":"P",
    "gn:feature_code":"PPL",
    "gn:name":"Kori-Maound\u00e9",
    "gn:population":0,
    "gn:timezone":"Africa/Bamako",
    "iso:country":"ML",
    "wof:name":"Kori-Maounde",
    "wof:placetype":"locality"
},
  "geometry": {"coordinates":[-3.7762,14.4521],"type":"Point"}
}