{
  "type": "Feature",
  "properties": {
    "gn:admin1_code":"05",
    "gn:asciiname":"Diongonibougou",
    "gn:country_code":"ML",
    "gn:dem":281,
    "gn:feature_class":"P",
    "gn:feature_code":"PPL",
    "gn:name":"Diongonibougou",
    "gn:population":0,
    "gn:timezone":"Africa/Bamako",
    "iso:country":"ML",
    "wof:name":"Diongonibougou",
    "wof:placetype":"locality"
},
  "geometry": {"coordinates":[-5.5526,13.49413],"type":"Point"}
}