{
  "type": "Feature",
  "properties": {
    "gn:admin1_code":"5.0",
    "gn:asciiname":"Bassiembougou",
    "gn:country_code":"ML",
    "gn:dem":286,
    "gn:feature_class":"P",
    "gn:feature_code":"PPL",
    "gn:name":"Bassiembougou",
    "gn:population":0,
    "gn:timezone":"Africa/Bamako",
    "iso:country":"ML",
    "name:und_x_variant":[
        "Batiembougou",
        "Bassiembougou"
    ],
    "wof:name":"Bassiembougou",
    "wof:placetype":"locality"
},
  "geometry": {"coordinates":[-6.0454,13.437],"type":"Point"}
}