{
  "type": "Feature",
  "properties": {
    "gn:admin1_code":"6.0",
    "gn:asciiname":"Diadoulaba",
    "gn:country_code":"ML",
    "gn:dem":369,
    "gn:feature_class":"P",
    "gn:feature_code":"PPL",
    "gn:name":"Diadoulaba",
    "gn:population":0,
    "gn:timezone":"Africa/Bamako",
    "iso:country":"ML",
    "wof:name":"Diadoulaba",
    "wof:placetype":"locality"
},
  "geometry": {"coordinates":[-7.95312,11.44094],"type":"Point"}
}