{
  "type": "Feature",
  "properties": {
    "gn:admin1_code":"07",
    "gn:asciiname":"Fana",
    "gn:country_code":"ML",
    "gn:dem":333,
    "gn:feature_class":"P",
    "gn:feature_code":"PPL",
    "gn:name":"Fana",
    "gn:population":0,
    "gn:timezone":"Africa/Bamako",
    "iso:country":"ML",
    "name:fra_x_preferred":[
        "Fana"
    ],
    "wof:name":"Fana",
    "wof:placetype":"locality"
},
  "geometry": {"coordinates":[-6.9564,12.7787],"type":"Point"}
}