{
  "type": "Feature",
  "properties": {
    "gn:admin1_code":"00",
    "gn:asciiname":"Lena",
    "gn:country_code":"ML",
    "gn:dem":378,
    "gn:feature_class":"P",
    "gn:feature_code":"PPL",
    "gn:name":"L\u00e9na",
    "gn:population":0,
    "gn:timezone":"Africa/Bamako",
    "iso:country":"ML",
    "wof:name":"Lena",
    "wof:placetype":"locality"
},
  "geometry": {"coordinates":[-8.08333,11.63333],"type":"Point"}
}