{
  "type": "Feature",
  "properties": {
    "gn:admin1_code":"00",
    "gn:asciiname":"Lena",
    "gn:country_code":"ML",
    "gn:dem":378,
    "gn:feature_class":"P",
    "gn:feature_code":"PPL",
    "gn:name":"L\u00e9na",
    "gn:population":0,
    "gn:timezone":"Africa/Bamako",
    "iso:country":"ML",
    "name:als_x_preferred":[
        "Lena"
    ],
    "name:aze_x_preferred":[
        "Lena"
    ],
    "name:bak_x_preferred":[
        "\u041b\u0435\u043d\u0430"
    ],
    "name:bre_x_preferred":[
        "Lena"
    ],
    "name:ceb_x_preferred":[
        "Lena"
    ],
    "name:dan_x_preferred":[
        "Lena"
    ],
    "name:deu_x_preferred":[
        "Lena"
    ],
    "name:fin_x_preferred":[
        "Lena"
    ],
    "name:fra_x_preferred":[
        "L\u00e9na"
    ],
    "name:glg_x_preferred":[
        "Lena"
    ],
    "name:hrv_x_preferred":[
        "Lena"
    ],
    "name:ita_x_preferred":[
        "Lena"
    ],
    "name:ltz_x_preferred":[
        "Lena"
    ],
    "name:nds_x_preferred":[
        "Lena"
    ],
    "name:nld_x_preferred":[
        "Lena"
    ],
    "name:nno_x_preferred":[
        "Lena"
    ],
    "name:nor_x_preferred":[
        "Lena"
    ],
    "name:oci_x_preferred":[
        "Lena"
    ],
    "name:pol_x_preferred":[
        "Lena"
    ],
    "name:por_x_preferred":[
        "Lena"
    ],
    "name:ron_x_preferred":[
        "Lena"
    ],
    "name:rus_x_preferred":[
        "\u041b\u0435\u043d\u0430"
    ],
    "name:slk_x_preferred":[
        "Lena"
    ],
    "name:spa_x_preferred":[
        "Lena"
    ],
    "name:srp_x_preferred":[
        "\u041b\u0435\u043d\u0430"
    ],
    "name:swe_x_preferred":[
        "Lena"
    ],
    "name:tur_x_preferred":[
        "Lena"
    ],
    "name:ukr_x_preferred":[
        "\u041b\u0435\u043d\u0430"
    ],
    "name:vie_x_preferred":[
        "Lena"
    ],
    "name:vol_x_preferred":[
        "Lena"
    ],
    "wof:name":"Lena",
    "wof:placetype":"locality"
},
  "geometry": {"coordinates":[-8.08333,11.63333],"type":"Point"}
}