{
  "type": "Feature",
  "properties": {
    "gn:admin1_code":"7.0",
    "gn:asciiname":"Badinye",
    "gn:country_code":"ML",
    "gn:dem":332,
    "gn:feature_class":"P",
    "gn:feature_code":"PPL",
    "gn:name":"Badiny\u00e9",
    "gn:population":0,
    "gn:timezone":"Africa/Bamako",
    "iso:country":"ML",
    "name:fra_x_preferred":[
        "Badiny\u00e9"
    ],
    "name:fra_x_variant":[
        "Badigue"
    ],
    "wof:name":"Badinye",
    "wof:placetype":"locality"
},
  "geometry": {"coordinates":[-6.9174,12.3509],"type":"Point"}
}