{
  "type": "Feature",
  "properties": {
    "gn:admin1_code":"5.0",
    "gn:asciiname":"Banantomo",
    "gn:country_code":"ML",
    "gn:dem":296,
    "gn:feature_class":"P",
    "gn:feature_code":"PPL",
    "gn:name":"Banantomo",
    "gn:population":0,
    "gn:timezone":"Africa/Bamako",
    "iso:country":"ML",
    "name:und_x_variant":[
        "Banandomo",
        "Banantomo"
    ],
    "wof:name":"Banantomo",
    "wof:placetype":"locality"
},
  "geometry": {"coordinates":[-6.32339,13.21282],"type":"Point"}
}