{
  "type": "Feature",
  "properties": {
    "gn:admin1_code":"03",
    "gn:asciiname":"Boutissigare",
    "gn:country_code":"ML",
    "gn:dem":305,
    "gn:feature_class":"P",
    "gn:feature_code":"PPL",
    "gn:name":"Boutissigar\u00e9",
    "gn:population":0,
    "gn:timezone":"Africa/Bamako",
    "iso:country":"ML",
    "wof:name":"Boutissigare",
    "wof:placetype":"locality"
},
  "geometry": {"coordinates":[-9.0632,14.7081],"type":"Point"}
}