{
  "type": "Feature",
  "properties": {
    "gn:admin1_code":"7.0",
    "gn:asciiname":"Kabana",
    "gn:country_code":"ML",
    "gn:dem":344,
    "gn:feature_class":"P",
    "gn:feature_code":"PPL",
    "gn:name":"Kabana",
    "gn:population":0,
    "gn:timezone":"Africa/Bamako",
    "iso:country":"ML",
    "wof:name":"Kabana",
    "wof:placetype":"locality"
},
  "geometry": {"coordinates":[-7.86321,13.03098],"type":"Point"}
}