{
  "type": "Feature",
  "properties": {
    "gn:admin1_code":"09",
    "gn:asciiname":"Taoussa",
    "gn:country_code":"ML",
    "gn:dem":259,
    "gn:feature_class":"P",
    "gn:feature_code":"PPL",
    "gn:name":"Taoussa",
    "gn:population":0,
    "gn:timezone":"Africa/Bamako",
    "iso:country":"ML",
    "wof:name":"Taoussa",
    "wof:placetype":"locality"
},
  "geometry": {"coordinates":[-0.55098,16.97207],"type":"Point"}
}