{
  "type": "Feature",
  "properties": {
    "gn:admin1_code":"4.0",
    "gn:asciiname":"Oussoua",
    "gn:country_code":"ML",
    "gn:dem":274,
    "gn:feature_class":"P",
    "gn:feature_code":"PPL",
    "gn:name":"Oussoua",
    "gn:population":0,
    "gn:timezone":"Africa/Bamako",
    "iso:country":"ML",
    "wof:name":"Oussoua",
    "wof:placetype":"locality"
},
  "geometry": {"coordinates":[-1.75047,15.01272],"type":"Point"}
}