{
  "type": "Feature",
  "properties": {
    "gn:admin1_code":"04",
    "gn:asciiname":"Goueley",
    "gn:country_code":"ML",
    "gn:dem":324,
    "gn:feature_class":"P",
    "gn:feature_code":"PPL",
    "gn:name":"Gou\u00e9l\u00e8y",
    "gn:population":0,
    "gn:timezone":"Africa/Bamako",
    "iso:country":"ML",
    "name:und_x_variant":[
        "Gw\u00e9ley",
        "Gou\u00e9l\u00e8y"
    ],
    "wof:name":"Goueley",
    "wof:placetype":"locality"
},
  "geometry": {"coordinates":[-1.92672,15.32207],"type":"Point"}
}