{
  "type": "Feature",
  "properties": {
    "gn:admin1_code":"00",
    "gn:asciiname":"Pabi",
    "gn:country_code":"ML",
    "gn:dem":685,
    "gn:feature_class":"P",
    "gn:feature_code":"PPL",
    "gn:name":"Pabi",
    "gn:population":0,
    "gn:timezone":"Africa/Bamako",
    "iso:country":"ML",
    "wof:name":"Pabi",
    "wof:placetype":"locality"
},
  "geometry": {"coordinates":[-10.78333,12.01667],"type":"Point"}
}