{
  "type": "Feature",
  "properties": {
    "gn:admin1_code":"7.0",
    "gn:asciiname":"Sirifibougou",
    "gn:country_code":"ML",
    "gn:dem":345,
    "gn:feature_class":"P",
    "gn:feature_code":"PPL",
    "gn:name":"Sirifibougou",
    "gn:population":0,
    "gn:timezone":"Africa/Bamako",
    "iso:country":"ML",
    "wof:name":"Sirifibougou",
    "wof:placetype":"locality"
},
  "geometry": {"coordinates":[-7.2346,12.9702],"type":"Point"}
}