{
  "type": "Feature",
  "properties": {
    "gn:admin1_code":"04",
    "gn:asciiname":"Sogoussi",
    "gn:country_code":"ML",
    "gn:dem":271,
    "gn:feature_class":"P",
    "gn:feature_code":"PPL",
    "gn:name":"Sogoussi",
    "gn:population":0,
    "gn:timezone":"Africa/Bamako",
    "iso:country":"ML",
    "wof:name":"Sogoussi",
    "wof:placetype":"locality"
},
  "geometry": {"coordinates":[-3.5157,13.8009],"type":"Point"}
}