{
  "type": "Feature",
  "properties": {
    "gn:admin1_code":"4.0",
    "gn:asciiname":"Bazogou Kanda",
    "gn:country_code":"ML",
    "gn:dem":279,
    "gn:feature_class":"P",
    "gn:feature_code":"PPL",
    "gn:name":"Bazogou Kanda",
    "gn:population":0,
    "gn:timezone":"Africa/Bamako",
    "iso:country":"ML",
    "wof:name":"Bazogou Kanda",
    "wof:placetype":"locality"
},
  "geometry": {"coordinates":[-3.5706,13.7698],"type":"Point"}
}