{
  "type": "Feature",
  "properties": {
    "gn:admin1_code":"4.0",
    "gn:asciiname":"Bormon",
    "gn:country_code":"ML",
    "gn:dem":299,
    "gn:feature_class":"P",
    "gn:feature_code":"PPL",
    "gn:name":"Bormon",
    "gn:population":0,
    "gn:timezone":"Africa/Bamako",
    "iso:country":"ML",
    "wof:name":"Bormon",
    "wof:placetype":"locality"
},
  "geometry": {"coordinates":[-3.20593,14.40927],"type":"Point"}
}