{
  "type": "Feature",
  "properties": {
    "gn:admin1_code":"07",
    "gn:asciiname":"Komana Kouta",
    "gn:country_code":"ML",
    "gn:dem":337,
    "gn:feature_class":"P",
    "gn:feature_code":"PPL",
    "gn:name":"Komana Kouta",
    "gn:population":0,
    "gn:timezone":"Africa/Bamako",
    "iso:country":"ML",
    "name:und_x_variant":[
        "Kommakana",
        "Koumakana",
        "Komana Kouta"
    ],
    "wof:name":"Komana Kouta",
    "wof:placetype":"locality"
},
  "geometry": {"coordinates":[-8.94668,12.28308],"type":"Point"}
}