{
  "type": "Feature",
  "properties": {
    "gn:admin1_code":"03",
    "gn:asciiname":"Diadia",
    "gn:country_code":"ML",
    "gn:dem":82,
    "gn:feature_class":"P",
    "gn:feature_code":"PPL",
    "gn:name":"Diadia",
    "gn:population":0,
    "gn:timezone":"Africa/Bamako",
    "iso:country":"ML",
    "name:und_x_variant":[
        "Dadia",
        "Diadia"
    ],
    "wof:name":"Diadia",
    "wof:placetype":"locality"
},
  "geometry": {"coordinates":[-11.05477,14.25372],"type":"Point"}
}