{
  "type": "Feature",
  "properties": {
    "gn:admin1_code":"05",
    "gn:asciiname":"Doundedaga",
    "gn:country_code":"ML",
    "gn:dem":286,
    "gn:feature_class":"P",
    "gn:feature_code":"PPL",
    "gn:name":"Dound\u00e9daga",
    "gn:population":0,
    "gn:timezone":"Africa/Bamako",
    "iso:country":"ML",
    "wof:name":"Doundedaga",
    "wof:placetype":"locality"
},
  "geometry": {"coordinates":[-4.21729,13.79894],"type":"Point"}
}