{
  "type": "Feature",
  "properties": {
    "gn:admin1_code":"07",
    "gn:asciiname":"Bougoukorola",
    "gn:country_code":"ML",
    "gn:dem":424,
    "gn:feature_class":"P",
    "gn:feature_code":"PPL",
    "gn:name":"Bougoukorola",
    "gn:population":0,
    "gn:timezone":"Africa/Bamako",
    "iso:country":"ML",
    "name:fra_x_preferred":[
        "Bougoukorola"
    ],
    "wof:name":"Bougoukorola",
    "wof:placetype":"locality"
},
  "geometry": {"coordinates":[-8.0244,13.647],"type":"Point"}
}