{
  "type": "Feature",
  "properties": {
    "gn:admin1_code":"00",
    "gn:asciiname":"Galama",
    "gn:country_code":"ML",
    "gn:dem":312,
    "gn:feature_class":"P",
    "gn:feature_code":"PPL",
    "gn:name":"Galama",
    "gn:population":0,
    "gn:timezone":"Africa/Bamako",
    "iso:country":"ML",
    "wof:name":"Galama",
    "wof:placetype":"locality"
},
  "geometry": {"coordinates":[-10.58333,11.98333],"type":"Point"}
}