{
  "type": "Feature",
  "properties": {
    "gn:admin1_code":"7.0",
    "gn:asciiname":"Banankoro",
    "gn:country_code":"ML",
    "gn:dem":360,
    "gn:feature_class":"P",
    "gn:feature_code":"PPL",
    "gn:name":"Banankoro",
    "gn:population":0,
    "gn:timezone":"Africa/Bamako",
    "iso:country":"ML",
    "wof:name":"Banankoro",
    "wof:placetype":"locality"
},
  "geometry": {"coordinates":[-8.16807,12.05579],"type":"Point"}
}