{
  "type": "Feature",
  "properties": {
    "gn:admin1_code":"03",
    "gn:asciiname":"Gola",
    "gn:country_code":"ML",
    "gn:dem":100,
    "gn:feature_class":"P",
    "gn:feature_code":"PPL",
    "gn:name":"Gola",
    "gn:population":0,
    "gn:timezone":"Africa/Bamako",
    "iso:country":"ML",
    "wof:name":"Gola",
    "wof:placetype":"locality"
},
  "geometry": {"coordinates":[-10.7702,13.7869],"type":"Point"}
}