{
  "type": "Feature",
  "properties": {
    "gn:admin1_code":"07",
    "gn:asciiname":"Ndomono",
    "gn:country_code":"ML",
    "gn:dem":303,
    "gn:feature_class":"P",
    "gn:feature_code":"PPL",
    "gn:name":"Ndomono",
    "gn:population":0,
    "gn:timezone":"Africa/Bamako",
    "iso:country":"ML",
    "wof:name":"Ndomono",
    "wof:placetype":"locality"
},
  "geometry": {"coordinates":[-7.62187,14.30145],"type":"Point"}
}