{
  "type": "Feature",
  "properties": {
    "gn:admin1_code":"04",
    "gn:asciiname":"Kobo",
    "gn:country_code":"ML",
    "gn:dem":370,
    "gn:feature_class":"P",
    "gn:feature_code":"PPL",
    "gn:name":"Kobo",
    "gn:population":0,
    "gn:timezone":"Africa/Bamako",
    "iso:country":"ML",
    "wof:name":"Kobo",
    "wof:placetype":"locality"
},
  "geometry": {"coordinates":[-3.77264,13.95249],"type":"Point"}
}