{
  "type": "Feature",
  "properties": {
    "gn:admin1_code":"7.0",
    "gn:asciiname":"Singouela",
    "gn:country_code":"ML",
    "gn:dem":371,
    "gn:feature_class":"P",
    "gn:feature_code":"PPL",
    "gn:name":"Singou\u00e9la",
    "gn:population":0,
    "gn:timezone":"Africa/Bamako",
    "iso:country":"ML",
    "wof:name":"Singouela",
    "wof:placetype":"locality"
},
  "geometry": {"coordinates":[-8.46767,12.15859],"type":"Point"}
}