{
  "type": "Feature",
  "properties": {
    "gn:admin1_code":"06",
    "gn:asciiname":"Niaradougou",
    "gn:country_code":"ML",
    "gn:dem":403,
    "gn:feature_class":"P",
    "gn:feature_code":"PPL",
    "gn:name":"Niaradougou",
    "gn:population":0,
    "gn:timezone":"Africa/Bamako",
    "iso:country":"ML",
    "name:und_x_variant":[
        "Ni\u00e9z\u00e9dougou",
        "Niaradougou"
    ],
    "wof:name":"Niaradougou",
    "wof:placetype":"locality"
},
  "geometry": {"coordinates":[-5.96015,11.56029],"type":"Point"}
}