{
  "type": "Feature",
  "properties": {
    "gn:admin1_code":"03",
    "gn:asciiname":"Sangafara",
    "gn:country_code":"ML",
    "gn:dem":149,
    "gn:feature_class":"P",
    "gn:feature_code":"PPL",
    "gn:name":"Sangafara",
    "gn:population":0,
    "gn:timezone":"Africa/Bamako",
    "iso:country":"ML",
    "wof:name":"Sangafara",
    "wof:placetype":"locality"
},
  "geometry": {"coordinates":[-11.6716,14.09082],"type":"Point"}
}