{
  "type": "Feature",
  "properties": {
    "gn:admin1_code":"00",
    "gn:asciiname":"Dossola",
    "gn:cc2":"ML",
    "gn:country_code":"ML",
    "gn:dem":372,
    "gn:feature_class":"P",
    "gn:feature_code":"PPL",
    "gn:name":"Dossola",
    "gn:population":0,
    "gn:timezone":"Africa/Bamako",
    "iso:country":"ML",
    "name:und_x_variant":[
        "Dossela",
        "Dossola"
    ],
    "wof:name":"Dossola",
    "wof:placetype":"locality"
},
  "geometry": {"coordinates":[-8.08333,11.53333],"type":"Point"}
}