{
  "type": "Feature",
  "properties": {
    "gn:admin1_code":"07",
    "gn:asciiname":"Samambougou",
    "gn:country_code":"ML",
    "gn:dem":407,
    "gn:feature_class":"P",
    "gn:feature_code":"PPL",
    "gn:name":"Samambougou",
    "gn:population":0,
    "gn:timezone":"Africa/Bamako",
    "iso:country":"ML",
    "wof:name":"Samambougou",
    "wof:placetype":"locality"
},
  "geometry": {"coordinates":[-8.43469,12.7466],"type":"Point"}
}