{
  "type": "Feature",
  "properties": {
    "gn:admin1_code":"5.0",
    "gn:asciiname":"Niamassourouma",
    "gn:country_code":"ML",
    "gn:dem":283,
    "gn:feature_class":"P",
    "gn:feature_code":"PPL",
    "gn:name":"Niamassourouma",
    "gn:population":0,
    "gn:timezone":"Africa/Bamako",
    "iso:country":"ML",
    "wof:name":"Niamassourouma",
    "wof:placetype":"locality"
},
  "geometry": {"coordinates":[-5.87659,13.49166],"type":"Point"}
}