{
  "type": "Feature",
  "properties": {
    "gn:admin1_code":"03",
    "gn:asciiname":"Fadougou",
    "gn:country_code":"ML",
    "gn:dem":134,
    "gn:feature_class":"P",
    "gn:feature_code":"PPL",
    "gn:name":"Fadougou",
    "gn:population":0,
    "gn:timezone":"Africa/Bamako",
    "iso:country":"ML",
    "wof:name":"Fadougou",
    "wof:placetype":"locality"
},
  "geometry": {"coordinates":[-11.37014,12.5379],"type":"Point"}
}