{
  "type": "Feature",
  "properties": {
    "gn:admin1_code":"06",
    "gn:asciiname":"Kodiougouni",
    "gn:country_code":"ML",
    "gn:dem":348,
    "gn:feature_class":"P",
    "gn:feature_code":"PPL",
    "gn:name":"Kodiougouni",
    "gn:population":0,
    "gn:timezone":"Africa/Bamako",
    "iso:country":"ML",
    "wof:name":"Kodiougouni",
    "wof:placetype":"locality"
},
  "geometry": {"coordinates":[-7.38487,11.70919],"type":"Point"}
}