{
  "type": "Feature",
  "properties": {
    "gn:admin1_code":"8.0",
    "gn:asciiname":"Banikan",
    "gn:country_code":"ML",
    "gn:dem":274,
    "gn:feature_class":"P",
    "gn:feature_code":"PPL",
    "gn:name":"Banikan",
    "gn:population":0,
    "gn:timezone":"Africa/Bamako",
    "iso:country":"ML",
    "name:und_x_variant":[
        "Banikane",
        "Banikan"
    ],
    "wof:name":"Banikan",
    "wof:placetype":"locality"
},
  "geometry": {"coordinates":[-3.60039,16.04038],"type":"Point"}
}