{
  "type": "Feature",
  "properties": {
    "gn:admin1_code":"04",
    "gn:asciiname":"Dana",
    "gn:country_code":"ML",
    "gn:dem":264,
    "gn:feature_class":"P",
    "gn:feature_code":"PPL",
    "gn:name":"Dana",
    "gn:population":0,
    "gn:timezone":"Africa/Bamako",
    "iso:country":"ML",
    "name:ara_x_preferred":[
        "\u062f\u0627\u0646\u0627"
    ],
    "name:ceb_x_preferred":[
        "Dana"
    ],
    "name:ces_x_preferred":[
        "Dana"
    ],
    "name:dan_x_preferred":[
        "Dana"
    ],
    "name:deu_x_preferred":[
        "Dana"
    ],
    "name:epo_x_preferred":[
        "Dana"
    ],
    "name:est_x_preferred":[
        "Dana"
    ],
    "name:fas_x_preferred":[
        "\u062f\u0627\u0646\u0627"
    ],
    "name:fin_x_preferred":[
        "Dana"
    ],
    "name:fra_x_preferred":[
        "Dana"
    ],
    "name:heb_x_preferred":[
        "\u05d3\u05d9\u05d9\u05e0\u05d4"
    ],
    "name:ita_x_preferred":[
        "Dana"
    ],
    "name:kor_x_preferred":[
        "\ub370\uc774\ub098"
    ],
    "name:lav_x_preferred":[
        "Dana"
    ],
    "name:nld_x_preferred":[
        "Dana"
    ],
    "name:nor_x_preferred":[
        "Dana"
    ],
    "name:pol_x_preferred":[
        "Dana"
    ],
    "name:por_x_preferred":[
        "Dana"
    ],
    "name:ron_x_preferred":[
        "Dana"
    ],
    "name:rus_x_preferred":[
        "\u0414\u0430\u043d\u0430"
    ],
    "name:slk_x_preferred":[
        "Dana"
    ],
    "name:spa_x_preferred":[
        "Dana"
    ],
    "name:srp_x_preferred":[
        "\u0414\u0435\u0458\u043d\u0430"
    ],
    "name:swe_x_preferred":[
        "Dana"
    ],
    "name:vol_x_preferred":[
        "Dana"
    ],
    "wof:name":"Dana",
    "wof:placetype":"locality"
},
  "geometry": {"coordinates":[-3.04499,14.17565],"type":"Point"}
}