{
  "type": "Feature",
  "properties": {
    "gn:admin1_code":"5.0",
    "gn:asciiname":"Kammpena",
    "gn:country_code":"ML",
    "gn:dem":289,
    "gn:feature_class":"P",
    "gn:feature_code":"PPL",
    "gn:name":"Kammp\u00e9na",
    "gn:population":0,
    "gn:timezone":"Africa/Bamako",
    "iso:country":"ML",
    "wof:name":"Kammpena",
    "wof:placetype":"locality"
},
  "geometry": {"coordinates":[-4.23,13.7238],"type":"Point"}
}