{
  "type": "Feature",
  "properties": {
    "gn:admin1_code":"03",
    "gn:asciiname":"Tinaga",
    "gn:country_code":"ML",
    "gn:dem":246,
    "gn:feature_class":"P",
    "gn:feature_code":"PPL",
    "gn:name":"Tinaga",
    "gn:population":0,
    "gn:timezone":"Africa/Bamako",
    "iso:country":"ML",
    "wof:name":"Tinaga",
    "wof:placetype":"locality"
},
  "geometry": {"coordinates":[-9.97724,15.36804],"type":"Point"}
}