{
  "type": "Feature",
  "properties": {
    "gn:admin1_code":"7.0",
    "gn:asciiname":"Kolonda",
    "gn:country_code":"ML",
    "gn:dem":420,
    "gn:feature_class":"P",
    "gn:feature_code":"PPL",
    "gn:name":"Kolonda",
    "gn:population":0,
    "gn:timezone":"Africa/Bamako",
    "iso:country":"ML",
    "wof:name":"Kolonda",
    "wof:placetype":"locality"
},
  "geometry": {"coordinates":[-8.1024,12.63925],"type":"Point"}
}