{
  "type": "Feature",
  "properties": {
    "gn:admin1_code":"10.0",
    "gn:asciiname":"In Khalil",
    "gn:country_code":"ML",
    "gn:dem":421,
    "gn:feature_class":"P",
    "gn:feature_code":"PPL",
    "gn:name":"In Khalil",
    "gn:population":0,
    "gn:timezone":"Africa/Bamako",
    "iso:country":"ML",
    "name:und_x_variant":[
        "El-Khalil",
        "Inhalid",
        "In-Khalil",
        "al-Khalil",
        "I-n-Khalil"
    ],
    "wof:name":"In Khalil",
    "wof:placetype":"locality"
},
  "geometry": {"coordinates":[1.04303,21.19006],"type":"Point"}
}