{
  "type": "Feature",
  "properties": {
    "gn:admin1_code":"03",
    "gn:asciiname":"Nanifara",
    "gn:country_code":"ML",
    "gn:dem":158,
    "gn:feature_class":"P",
    "gn:feature_code":"PPL",
    "gn:name":"Nanifara",
    "gn:population":0,
    "gn:timezone":"Africa/Bamako",
    "iso:country":"ML",
    "wof:name":"Nanifara",
    "wof:placetype":"locality"
},
  "geometry": {"coordinates":[-10.82,13.1012],"type":"Point"}
}