{
  "type": "Feature",
  "properties": {
    "gn:admin1_code":"08",
    "gn:asciiname":"Daka-Bonyokou",
    "gn:country_code":"ML",
    "gn:dem":275,
    "gn:feature_class":"P",
    "gn:feature_code":"PPL",
    "gn:name":"Daka-Bonyokou",
    "gn:population":0,
    "gn:timezone":"Africa/Bamako",
    "iso:country":"ML",
    "wof:name":"Daka-Bonyokou",
    "wof:placetype":"locality"
},
  "geometry": {"coordinates":[-2.85159,15.89549],"type":"Point"}
}