{
  "type": "Feature",
  "properties": {
    "gn:admin1_code":"6.0",
    "gn:asciiname":"Djissan",
    "gn:country_code":"ML",
    "gn:dem":334,
    "gn:feature_class":"P",
    "gn:feature_code":"PPL",
    "gn:name":"Djissan",
    "gn:population":0,
    "gn:timezone":"Africa/Bamako",
    "iso:country":"ML",
    "wof:name":"Djissan",
    "wof:placetype":"locality"
},
  "geometry": {"coordinates":[-6.6789,11.31841],"type":"Point"}
}