{
  "type": "Feature",
  "properties": {
    "gn:admin1_code":"07",
    "gn:asciiname":"Fani",
    "gn:country_code":"ML",
    "gn:dem":294,
    "gn:feature_class":"P",
    "gn:feature_code":"PPL",
    "gn:name":"Fani",
    "gn:population":0,
    "gn:timezone":"Africa/Bamako",
    "iso:country":"ML",
    "name:ceb_x_preferred":[
        "Fani"
    ],
    "name:deu_x_preferred":[
        "Fani"
    ],
    "name:fra_x_preferred":[
        "Fani"
    ],
    "name:ita_x_preferred":[
        "Fani"
    ],
    "name:nld_x_preferred":[
        "Fani"
    ],
    "name:por_x_preferred":[
        "Fani"
    ],
    "name:swe_x_preferred":[
        "Fani"
    ],
    "wof:name":"Fani",
    "wof:placetype":"locality"
},
  "geometry": {"coordinates":[-7.09528,13.24048],"type":"Point"}
}