{
  "type": "Feature",
  "properties": {
    "gn:admin1_code":"03",
    "gn:asciiname":"Mbeidi",
    "gn:country_code":"ML",
    "gn:dem":258,
    "gn:feature_class":"P",
    "gn:feature_code":"PPL",
    "gn:name":"Mb\u00e9\u00efdi",
    "gn:population":0,
    "gn:timezone":"Africa/Bamako",
    "iso:country":"ML",
    "wof:name":"Mbeidi",
    "wof:placetype":"locality"
},
  "geometry": {"coordinates":[-9.0117,14.5629],"type":"Point"}
}