{
  "type": "Feature",
  "properties": {
    "gn:admin1_code":"6.0",
    "gn:asciiname":"Noubasso",
    "gn:country_code":"ML",
    "gn:dem":391,
    "gn:feature_class":"P",
    "gn:feature_code":"PPL",
    "gn:name":"Noubasso",
    "gn:population":0,
    "gn:timezone":"Africa/Bamako",
    "iso:country":"ML",
    "wof:name":"Noubasso",
    "wof:placetype":"locality"
},
  "geometry": {"coordinates":[-5.5447,12.3891],"type":"Point"}
}