{
  "type": "Feature",
  "properties": {
    "gn:admin1_code":"03",
    "gn:asciiname":"Koussouko",
    "gn:country_code":"ML",
    "gn:dem":271,
    "gn:feature_class":"P",
    "gn:feature_code":"PPL",
    "gn:name":"Koussouko",
    "gn:population":0,
    "gn:timezone":"Africa/Bamako",
    "iso:country":"ML",
    "wof:name":"Koussouko",
    "wof:placetype":"locality"
},
  "geometry": {"coordinates":[-9.7158,14.4656],"type":"Point"}
}