{
  "type": "Feature",
  "properties": {
    "gn:admin1_code":"07",
    "gn:asciiname":"Boulougou",
    "gn:country_code":"ML",
    "gn:dem":340,
    "gn:feature_class":"P",
    "gn:feature_code":"PPL",
    "gn:name":"Boulougou",
    "gn:population":0,
    "gn:timezone":"Africa/Bamako",
    "iso:country":"ML",
    "name:azb_x_preferred":[
        "\u0628\u0648\u0644\u0648\u0642\u0648"
    ],
    "name:ceb_x_preferred":[
        "Boulougou"
    ],
    "name:fas_x_preferred":[
        "\u0628\u0648\u0644\u0648\u06af\u0648"
    ],
    "name:fra_x_preferred":[
        "Boulougou"
    ],
    "name:fra_x_variant":[
        "Bouboukou"
    ],
    "name:und_x_variant":[
        "Bouboukou"
    ],
    "wof:name":"Boulougou",
    "wof:placetype":"locality"
},
  "geometry": {"coordinates":[-8.3878,13.2711],"type":"Point"}
}