{
  "type": "Feature",
  "properties": {
    "gn:admin1_code":"08",
    "gn:asciiname":"Kora Goundia",
    "gn:country_code":"ML",
    "gn:dem":259,
    "gn:feature_class":"P",
    "gn:feature_code":"PPL",
    "gn:name":"Kora Goundia",
    "gn:population":0,
    "gn:timezone":"Africa/Bamako",
    "iso:country":"ML",
    "name:und_x_variant":[
        "Kora Gounda",
        "Kora Goundia"
    ],
    "wof:name":"Kora Goundia",
    "wof:placetype":"locality"
},
  "geometry": {"coordinates":[-1.01252,16.96861],"type":"Point"}
}