{
  "type": "Feature",
  "properties": {
    "gn:admin1_code":"07",
    "gn:asciiname":"Dyemenekoura",
    "gn:country_code":"ML",
    "gn:dem":326,
    "gn:feature_class":"P",
    "gn:feature_code":"PPL",
    "gn:name":"Dy\u00e9m\u00e9n\u00e9koura",
    "gn:population":0,
    "gn:timezone":"Africa/Bamako",
    "iso:country":"ML",
    "name:und_x_variant":[
        "Di\u00e9men\u00e9koura",
        "Dy\u00e9m\u00e9n\u00e9koura"
    ],
    "wof:name":"Dyemenekoura",
    "wof:placetype":"locality"
},
  "geometry": {"coordinates":[-8.1684,14.1477],"type":"Point"}
}