{
  "type": "Feature",
  "properties": {
    "gn:admin1_code":"7.0",
    "gn:asciiname":"Bassabougou",
    "gn:country_code":"ML",
    "gn:dem":358,
    "gn:feature_class":"P",
    "gn:feature_code":"PPL",
    "gn:name":"Bassabougou",
    "gn:population":0,
    "gn:timezone":"Africa/Bamako",
    "iso:country":"ML",
    "name:fra_x_preferred":[
        "Bassabougou"
    ],
    "wof:name":"Bassabougou",
    "wof:placetype":"locality"
},
  "geometry": {"coordinates":[-8.2952,13.0618],"type":"Point"}
}