{
  "type": "Feature",
  "properties": {
    "gn:admin1_code":"5.0",
    "gn:asciiname":"Koumantou",
    "gn:country_code":"ML",
    "gn:dem":327,
    "gn:feature_class":"P",
    "gn:feature_code":"PPL",
    "gn:name":"Koumantou",
    "gn:population":0,
    "gn:timezone":"Africa/Bamako",
    "iso:country":"ML",
    "name:fin_x_preferred":[
        "Koumantou"
    ],
    "name:fra_x_preferred":[
        "Koumantou"
    ],
    "name:ita_x_preferred":[
        "Koumantou"
    ],
    "name:nld_x_preferred":[
        "Koumantou"
    ],
    "name:spa_x_preferred":[
        "Koumantou"
    ],
    "name:zho_x_preferred":[
        "\u5eab\u8292\u5716"
    ],
    "wof:name":"Koumantou",
    "wof:placetype":"locality"
},
  "geometry": {"coordinates":[-6.18592,12.87286],"type":"Point"}
}