{
  "type": "Feature",
  "properties": {
    "gn:admin1_code":"03",
    "gn:asciiname":"Oumourou",
    "gn:country_code":"ML",
    "gn:dem":241,
    "gn:feature_class":"P",
    "gn:feature_code":"PPL",
    "gn:name":"Oumourou",
    "gn:population":0,
    "gn:timezone":"Africa/Bamako",
    "iso:country":"ML",
    "wof:name":"Oumourou",
    "wof:placetype":"locality"
},
  "geometry": {"coordinates":[-10.4201,14.4902],"type":"Point"}
}