{
  "type": "Feature",
  "properties": {
    "gn:admin1_code":"7.0",
    "gn:asciiname":"Mpieba",
    "gn:country_code":"ML",
    "gn:dem":411,
    "gn:feature_class":"P",
    "gn:feature_code":"PPL",
    "gn:name":"Mpi\u00e9ba",
    "gn:population":0,
    "gn:timezone":"Africa/Bamako",
    "iso:country":"ML",
    "wof:name":"Mpieba",
    "wof:placetype":"locality"
},
  "geometry": {"coordinates":[-7.93675,13.37399],"type":"Point"}
}