{
  "type": "Feature",
  "properties": {
    "gn:admin1_code":"7.0",
    "gn:asciiname":"Koflatye",
    "gn:country_code":"ML",
    "gn:dem":447,
    "gn:feature_class":"P",
    "gn:feature_code":"PPL",
    "gn:name":"Koflaty\u00e8",
    "gn:population":0,
    "gn:timezone":"Africa/Bamako",
    "iso:country":"ML",
    "wof:name":"Koflatye",
    "wof:placetype":"locality"
},
  "geometry": {"coordinates":[-8.2041,12.64844],"type":"Point"}
}