{
  "type": "Feature",
  "properties": {
    "gn:admin1_code":"7.0",
    "gn:asciiname":"Bala",
    "gn:country_code":"ML",
    "gn:dem":338,
    "gn:feature_class":"P",
    "gn:feature_code":"PPL",
    "gn:name":"Bala",
    "gn:population":0,
    "gn:timezone":"Africa/Bamako",
    "iso:country":"ML",
    "name:und_x_variant":[
        "Balala",
        "Bala"
    ],
    "wof:name":"Bala",
    "wof:placetype":"locality"
},
  "geometry": {"coordinates":[-8.13367,12.22609],"type":"Point"}
}