{
  "type": "Feature",
  "properties": {
    "gn:admin1_code":"4.0",
    "gn:asciiname":"Bamguel",
    "gn:country_code":"ML",
    "gn:dem":301,
    "gn:feature_class":"P",
    "gn:feature_code":"PPL",
    "gn:name":"Bamguel",
    "gn:population":0,
    "gn:timezone":"Africa/Bamako",
    "iso:country":"ML",
    "wof:name":"Bamguel",
    "wof:placetype":"locality"
},
  "geometry": {"coordinates":[-2.58241,15.10717],"type":"Point"}
}