{
  "type": "Feature",
  "properties": {
    "gn:admin1_code":"03",
    "gn:asciiname":"Kamarifara",
    "gn:country_code":"ML",
    "gn:dem":295,
    "gn:feature_class":"P",
    "gn:feature_code":"PPL",
    "gn:name":"Kamarifara",
    "gn:population":0,
    "gn:timezone":"Africa/Bamako",
    "iso:country":"ML",
    "wof:name":"Kamarifara",
    "wof:placetype":"locality"
},
  "geometry": {"coordinates":[-9.4868,14.6307],"type":"Point"}
}