{
  "type": "Feature",
  "properties": {
    "gn:admin1_code":"6.0",
    "gn:asciiname":"Zankorabougou",
    "gn:country_code":"ML",
    "gn:dem":307,
    "gn:feature_class":"P",
    "gn:feature_code":"PPL",
    "gn:name":"Zankorabougou",
    "gn:population":0,
    "gn:timezone":"Africa/Bamako",
    "iso:country":"ML",
    "wof:name":"Zankorabougou",
    "wof:placetype":"locality"
},
  "geometry": {"coordinates":[-5.9513,12.7353],"type":"Point"}
}