{
  "type": "Feature",
  "properties": {
    "gn:admin1_code":"06",
    "gn:asciiname":"Sodioula",
    "gn:country_code":"ML",
    "gn:dem":316,
    "gn:feature_class":"P",
    "gn:feature_code":"PPL",
    "gn:name":"Sodioula",
    "gn:population":0,
    "gn:timezone":"Africa/Bamako",
    "iso:country":"ML",
    "name:fra_x_preferred":[
        "Sodioula"
    ],
    "wof:name":"Sodioula",
    "wof:placetype":"locality"
},
  "geometry": {"coordinates":[-6.71755,11.31812],"type":"Point"}
}