{
  "type": "Feature",
  "properties": {
    "gn:admin1_code":"3.0",
    "gn:asciiname":"El Guenib",
    "gn:country_code":"ML",
    "gn:dem":138,
    "gn:feature_class":"P",
    "gn:feature_code":"PPL",
    "gn:name":"El Gu\u00e9nib",
    "gn:population":0,
    "gn:timezone":"Africa/Bamako",
    "iso:country":"ML",
    "wof:name":"El Guenib",
    "wof:placetype":"locality"
},
  "geometry": {"coordinates":[-11.20049,15.2986],"type":"Point"}
}