{
  "type": "Feature",
  "properties": {
    "gn:admin1_code":"03",
    "gn:asciiname":"Fello Bawo",
    "gn:country_code":"ML",
    "gn:dem":388,
    "gn:feature_class":"P",
    "gn:feature_code":"PPL",
    "gn:name":"F\u00e9llo Bawo",
    "gn:population":0,
    "gn:timezone":"Africa/Bamako",
    "iso:country":"ML",
    "name:und_x_variant":[
        "F\u00e9lo Bao",
        "F\u00e9llo Bawo"
    ],
    "wof:name":"Fello Bawo",
    "wof:placetype":"locality"
},
  "geometry": {"coordinates":[-11.4772,12.21312],"type":"Point"}
}