{
  "type": "Feature",
  "properties": {
    "gn:admin1_code":"7.0",
    "gn:asciiname":"Laghwat",
    "gn:country_code":"ML",
    "gn:dem":272,
    "gn:feature_class":"P",
    "gn:feature_code":"PPL",
    "gn:name":"Laghwat",
    "gn:population":0,
    "gn:timezone":"Africa/Bamako",
    "iso:country":"ML",
    "name:und_x_variant":[
        "Larhwat",
        "Laghwat"
    ],
    "wof:name":"Laghwat",
    "wof:placetype":"locality"
},
  "geometry": {"coordinates":[-7.16973,15.16841],"type":"Point"}
}