{
  "type": "Feature",
  "properties": {
    "gn:admin1_code":"5.0",
    "gn:asciiname":"Wolokouna",
    "gn:country_code":"ML",
    "gn:dem":279,
    "gn:feature_class":"P",
    "gn:feature_code":"PPL",
    "gn:name":"Wolokouna",
    "gn:population":0,
    "gn:timezone":"Africa/Bamako",
    "iso:country":"ML",
    "wof:name":"Wolokouna",
    "wof:placetype":"locality"
},
  "geometry": {"coordinates":[-5.42211,13.74223],"type":"Point"}
}