{
  "type": "Feature",
  "properties": {
    "gn:admin1_code":"7.0",
    "gn:asciiname":"Merelakhe",
    "gn:country_code":"ML",
    "gn:dem":330,
    "gn:feature_class":"P",
    "gn:feature_code":"PPL",
    "gn:name":"M\u00e9r\u00e9lakh\u00e9",
    "gn:population":0,
    "gn:timezone":"Africa/Bamako",
    "iso:country":"ML",
    "wof:name":"Merelakhe",
    "wof:placetype":"locality"
},
  "geometry": {"coordinates":[-7.46172,13.36729],"type":"Point"}
}