{
  "type": "Feature",
  "properties": {
    "gn:admin1_code":"00",
    "gn:asciiname":"Dialakoro",
    "gn:country_code":"ML",
    "gn:dem":373,
    "gn:feature_class":"P",
    "gn:feature_code":"PPL",
    "gn:name":"Dialakoro",
    "gn:population":0,
    "gn:timezone":"Africa/Bamako",
    "iso:country":"ML",
    "wof:name":"Dialakoro",
    "wof:placetype":"locality"
},
  "geometry": {"coordinates":[-8.05,11.55],"type":"Point"}
}