{
  "type": "Feature",
  "properties": {
    "gn:admin1_code":"4.0",
    "gn:asciiname":"Gondodie",
    "gn:country_code":"ML",
    "gn:dem":496,
    "gn:feature_class":"P",
    "gn:feature_code":"PPL",
    "gn:name":"Gondodi\u00e9",
    "gn:population":0,
    "gn:timezone":"Africa/Bamako",
    "iso:country":"ML",
    "wof:name":"Gondodie",
    "wof:placetype":"locality"
},
  "geometry": {"coordinates":[-3.40013,14.45927],"type":"Point"}
}