{
  "type": "Feature",
  "properties": {
    "gn:admin1_code":"03",
    "gn:asciiname":"Tangadonga",
    "gn:country_code":"ML",
    "gn:dem":108,
    "gn:feature_class":"P",
    "gn:feature_code":"PPL",
    "gn:name":"Tangadonga",
    "gn:population":0,
    "gn:timezone":"Africa/Bamako",
    "iso:country":"ML",
    "name:und_x_variant":[
        "Tangadouga",
        "Tangadougou",
        "Tangadonga"
    ],
    "wof:name":"Tangadonga",
    "wof:placetype":"locality"
},
  "geometry": {"coordinates":[-10.46397,15.0057],"type":"Point"}
}