{
  "type": "Feature",
  "properties": {
    "gn:admin1_code":"08",
    "gn:asciiname":"El Oualadji",
    "gn:country_code":"ML",
    "gn:dem":262,
    "gn:feature_class":"P",
    "gn:feature_code":"PPL",
    "gn:name":"El Oualadji",
    "gn:population":0,
    "gn:timezone":"Africa/Bamako",
    "iso:country":"ML",
    "name:und_x_variant":[
        "El Oualedji",
        "El Oualadji"
    ],
    "wof:name":"El Oualadji",
    "wof:placetype":"locality"
},
  "geometry": {"coordinates":[-3.44827,16.18727],"type":"Point"}
}