{
  "type": "Feature",
  "properties": {
    "gn:admin1_code":"05",
    "gn:asciiname":"Kanzangasso",
    "gn:country_code":"ML",
    "gn:dem":292,
    "gn:feature_class":"P",
    "gn:feature_code":"PPL",
    "gn:name":"Kanzangasso",
    "gn:population":0,
    "gn:timezone":"Africa/Bamako",
    "iso:country":"ML",
    "wof:name":"Kanzangasso",
    "wof:placetype":"locality"
},
  "geometry": {"coordinates":[-5.56792,13.04694],"type":"Point"}
}