{
  "type": "Feature",
  "properties": {
    "gn:admin1_code":"07",
    "gn:asciiname":"Koloni",
    "gn:country_code":"ML",
    "gn:dem":304,
    "gn:feature_class":"P",
    "gn:feature_code":"PPL",
    "gn:name":"Koloni",
    "gn:population":0,
    "gn:timezone":"Africa/Bamako",
    "iso:country":"ML",
    "name:fra_x_preferred":[
        "Koloni"
    ],
    "name:fra_x_variant":[
        "Kolonia"
    ],
    "name:hye_x_preferred":[
        "\u053f\u0578\u056c\u0578\u0576\u056b"
    ],
    "name:por_x_preferred":[
        "Coloni"
    ],
    "name:und_x_variant":[
        "Kolonia"
    ],
    "wof:name":"Koloni",
    "wof:placetype":"locality"
},
  "geometry": {"coordinates":[-6.4802,12.4677],"type":"Point"}
}