{
  "type": "Feature",
  "properties": {
    "gn:admin1_code":"00",
    "gn:asciiname":"Kenieto",
    "gn:country_code":"ML",
    "gn:dem":381,
    "gn:feature_class":"P",
    "gn:feature_code":"PPL",
    "gn:name":"K\u00e9ni\u00e9to",
    "gn:population":0,
    "gn:timezone":"Africa/Bamako",
    "iso:country":"ML",
    "wof:name":"Kenieto",
    "wof:placetype":"locality"
},
  "geometry": {"coordinates":[-9.85,12.53333],"type":"Point"}
}