{
  "type": "Feature",
  "properties": {
    "gn:admin1_code":"06",
    "gn:asciiname":"Kignan",
    "gn:country_code":"ML",
    "gn:dem":347,
    "gn:feature_class":"P",
    "gn:feature_code":"PPL",
    "gn:name":"Kignan",
    "gn:population":0,
    "gn:timezone":"Africa/Bamako",
    "iso:country":"ML",
    "name:fra_x_preferred":[
        "Kinyan"
    ],
    "name:fra_x_variant":[
        "Kinian"
    ],
    "name:und_x_variant":[
        "Kinian",
        "Kignan",
        "Kinyan"
    ],
    "wof:name":"Kignan",
    "wof:placetype":"locality"
},
  "geometry": {"coordinates":[-6.01398,11.85194],"type":"Point"}
}