{
  "type": "Feature",
  "properties": {
    "gn:admin1_code":"06",
    "gn:asciiname":"Kignan",
    "gn:country_code":"ML",
    "gn:dem":347,
    "gn:feature_class":"P",
    "gn:feature_code":"PPL",
    "gn:name":"Kignan",
    "gn:population":0,
    "gn:timezone":"Africa/Bamako",
    "iso:country":"ML",
    "name:fin_x_preferred":[
        "Kignan"
    ],
    "name:fra_x_preferred":[
        "Kinyan"
    ],
    "name:fra_x_variant":[
        "Kinian",
        "Kignan"
    ],
    "name:ita_x_preferred":[
        "Kignan"
    ],
    "name:nld_x_preferred":[
        "Kignan"
    ],
    "name:por_x_preferred":[
        "Quiniam"
    ],
    "name:spa_x_preferred":[
        "Kignan"
    ],
    "name:zho_x_preferred":[
        "\u57fa\u683c\u5357"
    ],
    "wof:name":"Kignan",
    "wof:placetype":"locality"
},
  "geometry": {"coordinates":[-6.01398,11.85194],"type":"Point"}
}