{
  "type": "Feature",
  "properties": {
    "gn:admin1_code":"7.0",
    "gn:asciiname":"Djidianda",
    "gn:country_code":"ML",
    "gn:dem":468,
    "gn:feature_class":"P",
    "gn:feature_code":"PPL",
    "gn:name":"Djidianda",
    "gn:population":0,
    "gn:timezone":"Africa/Bamako",
    "iso:country":"ML",
    "wof:name":"Djidianda",
    "wof:placetype":"locality"
},
  "geometry": {"coordinates":[-8.19471,12.64085],"type":"Point"}
}