{
  "type": "Feature",
  "properties": {
    "gn:admin1_code":"5.0",
    "gn:asciiname":"Tiyo",
    "gn:country_code":"ML",
    "gn:dem":288,
    "gn:feature_class":"P",
    "gn:feature_code":"PPL",
    "gn:name":"Tiyo",
    "gn:population":0,
    "gn:timezone":"Africa/Bamako",
    "iso:country":"ML",
    "name:ara_x_preferred":[
        "\u0637\u064a\u0639\u0648\u0627"
    ],
    "name:jpn_x_preferred":[
        "\u30c6\u30a3\u30e8"
    ],
    "name:nor_x_preferred":[
        "Ti'o"
    ],
    "name:ukr_x_preferred":[
        "\u0422\u0456\u0439\u043e"
    ],
    "wof:name":"Tiyo",
    "wof:placetype":"locality"
},
  "geometry": {"coordinates":[-6.0343,13.7183],"type":"Point"}
}