{
  "type": "Feature",
  "properties": {
    "gn:admin1_code":"06",
    "gn:asciiname":"Sinkolo",
    "gn:country_code":"ML",
    "gn:dem":310,
    "gn:feature_class":"P",
    "gn:feature_code":"PPL",
    "gn:name":"Sinkolo",
    "gn:population":0,
    "gn:timezone":"Africa/Bamako",
    "iso:country":"ML",
    "wof:name":"Sinkolo",
    "wof:placetype":"locality"
},
  "geometry": {"coordinates":[-5.55265,12.08499],"type":"Point"}
}