{
  "type": "Feature",
  "properties": {
    "gn:admin1_code":"00",
    "gn:asciiname":"Djiblebougou",
    "gn:country_code":"ML",
    "gn:dem":340,
    "gn:feature_class":"P",
    "gn:feature_code":"PPL",
    "gn:name":"Djibl\u00e9bougou",
    "gn:population":0,
    "gn:timezone":"Africa/Bamako",
    "iso:country":"ML",
    "wof:name":"Djiblebougou",
    "wof:placetype":"locality"
},
  "geometry": {"coordinates":[-8.45,12.93333],"type":"Point"}
}