{
  "type": "Feature",
  "properties": {
    "gn:admin1_code":"7.0",
    "gn:asciiname":"Arichsi",
    "gn:country_code":"ML",
    "gn:dem":267,
    "gn:feature_class":"P",
    "gn:feature_code":"PPL",
    "gn:name":"Arichsi",
    "gn:population":0,
    "gn:timezone":"Africa/Bamako",
    "iso:country":"ML",
    "wof:name":"Arichsi",
    "wof:placetype":"locality"
},
  "geometry": {"coordinates":[-7.70131,15.30411],"type":"Point"}
}