{
  "type": "Feature",
  "properties": {
    "gn:admin1_code":"7.0",
    "gn:asciiname":"Bengo",
    "gn:country_code":"ML",
    "gn:dem":272,
    "gn:feature_class":"P",
    "gn:feature_code":"PPL",
    "gn:name":"B\u00e8ngo",
    "gn:population":0,
    "gn:timezone":"Africa/Bamako",
    "iso:country":"ML",
    "name:ceb_x_preferred":[
        "Bengo"
    ],
    "name:deu_x_preferred":[
        "Bengo"
    ],
    "name:fra_x_preferred":[
        "B\u00e8ngo"
    ],
    "name:ita_x_preferred":[
        "Bengo"
    ],
    "name:swe_x_preferred":[
        "Bengo"
    ],
    "wof:name":"Bengo",
    "wof:placetype":"locality"
},
  "geometry": {"coordinates":[-6.8918,14.6053],"type":"Point"}
}