{
  "type": "Feature",
  "properties": {
    "gn:admin1_code":"06",
    "gn:asciiname":"Sogoba",
    "gn:country_code":"ML",
    "gn:dem":413,
    "gn:feature_class":"P",
    "gn:feature_code":"PPL",
    "gn:name":"Sogoba",
    "gn:population":0,
    "gn:timezone":"Africa/Bamako",
    "iso:country":"ML",
    "name:und_x_variant":[
        "Sokoba",
        "Sogoba"
    ],
    "wof:name":"Sogoba",
    "wof:placetype":"locality"
},
  "geometry": {"coordinates":[-4.6419,12.4737],"type":"Point"}
}