{
  "type": "Feature",
  "properties": {
    "gn:admin1_code":"5.0",
    "gn:asciiname":"Kouintikika",
    "gn:country_code":"ML",
    "gn:dem":280,
    "gn:feature_class":"P",
    "gn:feature_code":"PPL",
    "gn:name":"Kouintikika",
    "gn:population":0,
    "gn:timezone":"Africa/Bamako",
    "iso:country":"ML",
    "wof:name":"Kouintikika",
    "wof:placetype":"locality"
},
  "geometry": {"coordinates":[-5.88236,13.47605],"type":"Point"}
}