{
  "type": "Feature",
  "properties": {
    "gn:admin1_code":"03",
    "gn:asciiname":"Dialakoto",
    "gn:country_code":"ML",
    "gn:dem":406,
    "gn:feature_class":"P",
    "gn:feature_code":"PPL",
    "gn:name":"Dialakoto",
    "gn:population":0,
    "gn:timezone":"Africa/Bamako",
    "iso:country":"ML",
    "wof:name":"Dialakoto",
    "wof:placetype":"locality"
},
  "geometry": {"coordinates":[-11.0405,12.81312],"type":"Point"}
}