{
  "type": "Feature",
  "properties": {
    "gn:admin1_code":"07",
    "gn:asciiname":"Chebougoula",
    "gn:country_code":"ML",
    "gn:dem":328,
    "gn:feature_class":"P",
    "gn:feature_code":"PPL",
    "gn:name":"Chebougoula",
    "gn:population":0,
    "gn:timezone":"Africa/Bamako",
    "iso:country":"ML",
    "name:fra_x_preferred":[
        "Chebougoula"
    ],
    "wof:name":"Chebougoula",
    "wof:placetype":"locality"
},
  "geometry": {"coordinates":[-6.7689,12.0716],"type":"Point"}
}