{
  "type": "Feature",
  "properties": {
    "gn:admin1_code":"07",
    "gn:asciiname":"Diera",
    "gn:country_code":"ML",
    "gn:dem":344,
    "gn:feature_class":"P",
    "gn:feature_code":"PPL",
    "gn:name":"Di\u00e9ra",
    "gn:population":0,
    "gn:timezone":"Africa/Bamako",
    "iso:country":"ML",
    "name:und_x_variant":[
        "Dy\u00e9ra",
        "Di\u00e9ra"
    ],
    "wof:name":"Diera",
    "wof:placetype":"locality"
},
  "geometry": {"coordinates":[-7.6189,12.0946],"type":"Point"}
}