{
  "type": "Feature",
  "properties": {
    "gn:admin1_code":"04",
    "gn:asciiname":"Soban",
    "gn:country_code":"ML",
    "gn:dem":313,
    "gn:feature_class":"P",
    "gn:feature_code":"PPL",
    "gn:name":"Soban",
    "gn:population":0,
    "gn:timezone":"Africa/Bamako",
    "iso:country":"ML",
    "name:und_x_variant":[
        "Saban",
        "Soban"
    ],
    "wof:name":"Soban",
    "wof:placetype":"locality"
},
  "geometry": {"coordinates":[-3.6527,13.8543],"type":"Point"}
}