{
  "type": "Feature",
  "properties": {
    "gn:admin1_code":"5.0",
    "gn:asciiname":"Markala",
    "gn:country_code":"ML",
    "gn:dem":282,
    "gn:feature_class":"P",
    "gn:feature_code":"PPL",
    "gn:name":"Markala",
    "gn:population":0,
    "gn:timezone":"Africa/Bamako",
    "iso:country":"ML",
    "name:ara_x_preferred":[
        "\u0645\u0627\u0631\u0643\u0627\u0644\u0627"
    ],
    "name:cat_x_preferred":[
        "Markala"
    ],
    "name:ceb_x_preferred":[
        "Markala"
    ],
    "name:epo_x_preferred":[
        "Markala"
    ],
    "name:fin_x_preferred":[
        "Markala"
    ],
    "name:fra_x_preferred":[
        "Markala"
    ],
    "name:hun_x_preferred":[
        "Markala"
    ],
    "name:ita_x_preferred":[
        "Markala"
    ],
    "name:nld_x_preferred":[
        "Markala"
    ],
    "name:pol_x_preferred":[
        "Markala"
    ],
    "name:rus_x_preferred":[
        "\u041c\u0430\u0440\u043a\u0430\u043b\u0430"
    ],
    "name:spa_x_preferred":[
        "Markala"
    ],
    "name:swe_x_preferred":[
        "Markala"
    ],
    "name:zho_x_preferred":[
        "\u99ac\u723e\u5361\u62c9"
    ],
    "wof:name":"Markala",
    "wof:placetype":"locality"
},
  "geometry": {"coordinates":[-5.72334,13.91602],"type":"Point"}
}