{
  "type": "Feature",
  "properties": {
    "gn:admin1_code":"5.0",
    "gn:asciiname":"Markala",
    "gn:country_code":"ML",
    "gn:dem":282,
    "gn:feature_class":"P",
    "gn:feature_code":"PPL",
    "gn:name":"Markala",
    "gn:population":0,
    "gn:timezone":"Africa/Bamako",
    "iso:country":"ML",
    "name:ara_x_preferred":[
        "\u0645\u0627\u0631\u0643\u0627\u0644\u0627"
    ],
    "name:ben_x_preferred":[
        "\u09ae\u09be\u09b0\u0995\u09be\u09b2\u09be"
    ],
    "name:cat_x_preferred":[
        "Markala"
    ],
    "name:ceb_x_preferred":[
        "Markala"
    ],
    "name:deu_x_preferred":[
        "Markala"
    ],
    "name:epo_x_preferred":[
        "Markala"
    ],
    "name:fas_x_preferred":[
        "\u0645\u0627\u0631\u06a9\u0627\u0644\u0627"
    ],
    "name:fin_x_preferred":[
        "Markala"
    ],
    "name:fra_x_preferred":[
        "Markala"
    ],
    "name:heb_x_preferred":[
        "\u05de\u05e8\u05e7\u05dc\u05d4"
    ],
    "name:hin_x_preferred":[
        "\u092e\u093e\u0930\u094d\u0915\u0932\u093e"
    ],
    "name:hun_x_preferred":[
        "Markala"
    ],
    "name:ind_x_preferred":[
        "Markala"
    ],
    "name:ita_x_preferred":[
        "Markala"
    ],
    "name:kor_x_preferred":[
        "\ub9c8\ub974\uce7c\ub77c"
    ],
    "name:nld_x_preferred":[
        "Markala"
    ],
    "name:pol_x_preferred":[
        "Markala"
    ],
    "name:rus_x_preferred":[
        "\u041c\u0430\u0440\u043a\u0430\u043b\u0430"
    ],
    "name:spa_x_preferred":[
        "Markala"
    ],
    "name:swe_x_preferred":[
        "Markala"
    ],
    "name:tur_x_preferred":[
        "Markala"
    ],
    "name:ukr_x_preferred":[
        "\u041c\u0430\u0440\u043a\u0430\u043b\u0430"
    ],
    "name:urd_x_preferred":[
        "\u0645\u0627\u0631\u06a9\u0627\u0644\u0627"
    ],
    "name:vie_x_preferred":[
        "Markala"
    ],
    "name:zho_x_preferred":[
        "\u99ac\u723e\u5361\u62c9"
    ],
    "wof:name":"Markala",
    "wof:placetype":"locality"
},
  "geometry": {"coordinates":[-5.72334,13.91602],"type":"Point"}
}