{
  "type": "Feature",
  "properties": {
    "gn:admin1_code":"7.0",
    "gn:asciiname":"Bouloukouma",
    "gn:country_code":"ML",
    "gn:dem":409,
    "gn:feature_class":"P",
    "gn:feature_code":"PPL",
    "gn:name":"Bouloukouma",
    "gn:population":0,
    "gn:timezone":"Africa/Bamako",
    "iso:country":"ML",
    "wof:name":"Bouloukouma",
    "wof:placetype":"locality"
},
  "geometry": {"coordinates":[-7.92209,13.26304],"type":"Point"}
}