{
  "type": "Feature",
  "properties": {
    "gn:admin1_code":"7.0",
    "gn:asciiname":"Kolebabougou",
    "gn:country_code":"ML",
    "gn:dem":436,
    "gn:feature_class":"P",
    "gn:feature_code":"PPL",
    "gn:name":"Kol\u00e9babougou",
    "gn:population":0,
    "gn:timezone":"Africa/Bamako",
    "iso:country":"ML",
    "wof:name":"Kolebabougou",
    "wof:placetype":"locality"
},
  "geometry": {"coordinates":[-8.01951,12.74945],"type":"Point"}
}