{
  "type": "Feature",
  "properties": {
    "gn:admin1_code":"9.0",
    "gn:asciiname":"Akabar",
    "gn:country_code":"ML",
    "gn:dem":283,
    "gn:feature_class":"P",
    "gn:feature_code":"PPL",
    "gn:name":"Akabar",
    "gn:population":0,
    "gn:timezone":"Africa/Bamako",
    "iso:country":"ML",
    "wof:name":"Akabar",
    "wof:placetype":"locality"
},
  "geometry": {"coordinates":[2.0319,15.3717],"type":"Point"}
}