{
  "type": "Feature",
  "properties": {
    "gn:admin1_code":"5.0",
    "gn:asciiname":"Gassin",
    "gn:country_code":"ML",
    "gn:dem":285,
    "gn:feature_class":"P",
    "gn:feature_code":"PPL",
    "gn:name":"Gassin",
    "gn:population":0,
    "gn:timezone":"Africa/Bamako",
    "iso:country":"ML",
    "name:cat_x_preferred":[
        "Gassin"
    ],
    "name:ceb_x_preferred":[
        "Gassin"
    ],
    "name:deu_x_preferred":[
        "Gassin"
    ],
    "name:epo_x_preferred":[
        "Gassin"
    ],
    "name:eus_x_preferred":[
        "Gassin"
    ],
    "name:fas_x_preferred":[
        "\u06af\u0627\u0633\u0646"
    ],
    "name:fin_x_preferred":[
        "Gassin"
    ],
    "name:fra_x_preferred":[
        "Gassin"
    ],
    "name:hun_x_preferred":[
        "Gassin"
    ],
    "name:ita_x_preferred":[
        "Gassin"
    ],
    "name:jpn_x_preferred":[
        "\u30ac\u30c3\u30b5\u30f3"
    ],
    "name:lmo_x_preferred":[
        "Gassin"
    ],
    "name:msa_x_preferred":[
        "Gassin"
    ],
    "name:nld_x_preferred":[
        "Gassin"
    ],
    "name:oci_x_preferred":[
        "Gassin"
    ],
    "name:pms_x_preferred":[
        "Gassin"
    ],
    "name:pol_x_preferred":[
        "Gassin"
    ],
    "name:por_x_preferred":[
        "Gassin"
    ],
    "name:ron_x_preferred":[
        "Gassin"
    ],
    "name:rus_x_preferred":[
        "\u0413\u0430\u0441\u0435\u043d"
    ],
    "name:slk_x_preferred":[
        "Gassin"
    ],
    "name:spa_x_preferred":[
        "Gassin"
    ],
    "name:swe_x_preferred":[
        "Gassin"
    ],
    "name:ukr_x_preferred":[
        "\u0413\u0430\u0441\u0441\u0435\u043d"
    ],
    "name:vie_x_preferred":[
        "Gassin"
    ],
    "name:vol_x_preferred":[
        "Gassin"
    ],
    "name:war_x_preferred":[
        "Gassin"
    ],
    "wof:name":"Gassin",
    "wof:placetype":"locality"
},
  "geometry": {"coordinates":[-5.99522,13.54116],"type":"Point"}
}