{
  "type": "Feature",
  "properties": {
    "gn:admin1_code":"06",
    "gn:asciiname":"Feretou",
    "gn:country_code":"ML",
    "gn:dem":346,
    "gn:feature_class":"P",
    "gn:feature_code":"PPL",
    "gn:name":"F\u00e9r\u00e9tou",
    "gn:population":0,
    "gn:timezone":"Africa/Bamako",
    "iso:country":"ML",
    "wof:name":"Feretou",
    "wof:placetype":"locality"
},
  "geometry": {"coordinates":[-7.2709,11.91828],"type":"Point"}
}