{
  "type": "Feature",
  "properties": {
    "gn:admin1_code":"5.0",
    "gn:asciiname":"Nara",
    "gn:country_code":"ML",
    "gn:dem":283,
    "gn:feature_class":"P",
    "gn:feature_code":"PPL",
    "gn:name":"Nara",
    "gn:population":0,
    "gn:timezone":"Africa/Bamako",
    "iso:country":"ML",
    "wof:name":"Nara",
    "wof:placetype":"locality"
},
  "geometry": {"coordinates":[-5.53076,13.95359],"type":"Point"}
}