{
  "type": "Feature",
  "properties": {
    "gn:admin1_code":"05",
    "gn:asciiname":"Tanan-Zokolo",
    "gn:country_code":"ML",
    "gn:dem":280,
    "gn:feature_class":"P",
    "gn:feature_code":"PPL",
    "gn:name":"Tanan-Zokolo",
    "gn:population":0,
    "gn:timezone":"Africa/Bamako",
    "iso:country":"ML",
    "wof:name":"Tanan-Zokolo",
    "wof:placetype":"locality"
},
  "geometry": {"coordinates":[-5.6028,13.86267],"type":"Point"}
}