{
  "type": "Feature",
  "properties": {
    "gn:admin1_code":"3.0",
    "gn:asciiname":"Bala",
    "gn:country_code":"ML",
    "gn:dem":379,
    "gn:feature_class":"P",
    "gn:feature_code":"PPL",
    "gn:name":"Bala",
    "gn:population":0,
    "gn:timezone":"Africa/Bamako",
    "iso:country":"ML",
    "wof:name":"Bala",
    "wof:placetype":"locality"
},
  "geometry": {"coordinates":[-11.28482,12.22308],"type":"Point"}
}