{
  "type": "Feature",
  "properties": {
    "gn:admin1_code":"07",
    "gn:asciiname":"Ngalabougou",
    "gn:country_code":"ML",
    "gn:dem":399,
    "gn:feature_class":"P",
    "gn:feature_code":"PPL",
    "gn:name":"Ngalabougou",
    "gn:population":0,
    "gn:timezone":"Africa/Bamako",
    "iso:country":"ML",
    "name:und_x_variant":[
        "Galabougou",
        "Ngalabougou"
    ],
    "wof:name":"Ngalabougou",
    "wof:placetype":"locality"
},
  "geometry": {"coordinates":[-7.74218,13.85459],"type":"Point"}
}