{
  "type": "Feature",
  "properties": {
    "gn:admin1_code":"05",
    "gn:asciiname":"Niamina",
    "gn:country_code":"ML",
    "gn:dem":276,
    "gn:feature_class":"P",
    "gn:feature_code":"PPL",
    "gn:name":"Niamina",
    "gn:population":0,
    "gn:timezone":"Africa/Bamako",
    "iso:country":"ML",
    "name:und_x_variant":[
        "Nyamina",
        "Niamina"
    ],
    "wof:name":"Niamina",
    "wof:placetype":"locality"
},
  "geometry": {"coordinates":[-4.8458,13.4882],"type":"Point"}
}