{
  "type": "Feature",
  "properties": {
    "gn:admin1_code":"3.0",
    "gn:asciiname":"Bandoma",
    "gn:country_code":"ML",
    "gn:dem":364,
    "gn:feature_class":"P",
    "gn:feature_code":"PPL",
    "gn:name":"Bandoma",
    "gn:population":0,
    "gn:timezone":"Africa/Bamako",
    "iso:country":"ML",
    "wof:name":"Bandoma",
    "wof:placetype":"locality"
},
  "geometry": {"coordinates":[-9.42369,13.16011],"type":"Point"}
}