{
  "type": "Feature",
  "properties": {
    "gn:admin1_code":"04",
    "gn:asciiname":"Koumbe Niasso",
    "gn:country_code":"ML",
    "gn:dem":270,
    "gn:feature_class":"P",
    "gn:feature_code":"PPL",
    "gn:name":"Koumb\u00e9 Niasso",
    "gn:population":0,
    "gn:timezone":"Africa/Bamako",
    "iso:country":"ML",
    "wof:name":"Koumbe Niasso",
    "wof:placetype":"locality"
},
  "geometry": {"coordinates":[-4.68424,14.70881],"type":"Point"}
}