{
  "type": "Feature",
  "properties": {
    "gn:admin1_code":"04",
    "gn:asciiname":"Time",
    "gn:country_code":"ML",
    "gn:dem":272,
    "gn:feature_class":"P",
    "gn:feature_code":"PPL",
    "gn:name":"Tim\u00e9",
    "gn:population":0,
    "gn:timezone":"Africa/Bamako",
    "iso:country":"ML",
    "wof:name":"Time",
    "wof:placetype":"locality"
},
  "geometry": {"coordinates":[-3.86069,14.9701],"type":"Point"}
}