{
  "type": "Feature",
  "properties": {
    "gn:admin1_code":"05",
    "gn:asciiname":"Yolo",
    "gn:country_code":"ML",
    "gn:dem":283,
    "gn:feature_class":"P",
    "gn:feature_code":"PPL",
    "gn:name":"Yolo",
    "gn:population":0,
    "gn:timezone":"Africa/Bamako",
    "iso:country":"ML",
    "name:ceb_x_preferred":[
        "Yolo"
    ],
    "name:deu_x_preferred":[
        "Yolo"
    ],
    "name:fra_x_preferred":[
        "Yolo"
    ],
    "name:ita_x_preferred":[
        "Yolo"
    ],
    "name:nld_x_preferred":[
        "Yolo"
    ],
    "name:rus_x_preferred":[
        "\u0419\u043e\u043b\u043e"
    ],
    "name:spa_x_preferred":[
        "Yolo"
    ],
    "name:swe_x_preferred":[
        "Yolo"
    ],
    "wof:name":"Yolo",
    "wof:placetype":"locality"
},
  "geometry": {"coordinates":[-5.62843,13.63866],"type":"Point"}
}