{
  "type": "Feature",
  "properties": {
    "gn:admin1_code":"03",
    "gn:asciiname":"Walila",
    "gn:country_code":"ML",
    "gn:dem":78,
    "gn:feature_class":"P",
    "gn:feature_code":"PPL",
    "gn:name":"Walila",
    "gn:population":0,
    "gn:timezone":"Africa/Bamako",
    "iso:country":"ML",
    "wof:name":"Walila",
    "wof:placetype":"locality"
},
  "geometry": {"coordinates":[-10.824,14.5743],"type":"Point"}
}