{
  "type": "Feature",
  "properties": {
    "gn:admin1_code":"3.0",
    "gn:asciiname":"Banzana",
    "gn:country_code":"ML",
    "gn:dem":49,
    "gn:feature_class":"P",
    "gn:feature_code":"PPL",
    "gn:name":"Banzana",
    "gn:population":0,
    "gn:timezone":"Africa/Bamako",
    "iso:country":"ML",
    "wof:name":"Banzana",
    "wof:placetype":"locality"
},
  "geometry": {"coordinates":[-11.49644,14.42358],"type":"Point"}
}