{
  "type": "Feature",
  "properties": {
    "gn:admin1_code":"07",
    "gn:asciiname":"Sirakorobougou",
    "gn:country_code":"ML",
    "gn:dem":298,
    "gn:feature_class":"P",
    "gn:feature_code":"PPL",
    "gn:name":"Sirakorobougou",
    "gn:population":0,
    "gn:timezone":"Africa/Bamako",
    "iso:country":"ML",
    "wof:name":"Sirakorobougou",
    "wof:placetype":"locality"
},
  "geometry": {"coordinates":[-7.1402,13.37722],"type":"Point"}
}