{
  "type": "Feature",
  "properties": {
    "gn:admin1_code":"4.0",
    "gn:asciiname":"Temmbodie",
    "gn:country_code":"ML",
    "gn:dem":524,
    "gn:feature_class":"P",
    "gn:feature_code":"PPL",
    "gn:name":"Temmbodi\u00e9",
    "gn:population":0,
    "gn:timezone":"Africa/Bamako",
    "iso:country":"ML",
    "wof:name":"Temmbodie",
    "wof:placetype":"locality"
},
  "geometry": {"coordinates":[-3.10823,14.71507],"type":"Point"}
}