{
  "type": "Feature",
  "properties": {
    "gn:admin1_code":"06",
    "gn:asciiname":"Kala",
    "gn:country_code":"ML",
    "gn:dem":341,
    "gn:feature_class":"P",
    "gn:feature_code":"PPL",
    "gn:name":"Kala",
    "gn:population":0,
    "gn:timezone":"Africa/Bamako",
    "iso:country":"ML",
    "wof:name":"Kala",
    "wof:placetype":"locality"
},
  "geometry": {"coordinates":[-7.53061,11.93265],"type":"Point"}
}