{
  "type": "Feature",
  "properties": {
    "gn:admin1_code":"03",
    "gn:asciiname":"Toumana",
    "gn:country_code":"ML",
    "gn:dem":418,
    "gn:feature_class":"P",
    "gn:feature_code":"PPL",
    "gn:name":"Toumana",
    "gn:population":0,
    "gn:timezone":"Africa/Bamako",
    "iso:country":"ML",
    "wof:name":"Toumana",
    "wof:placetype":"locality"
},
  "geometry": {"coordinates":[-8.8461,12.62981],"type":"Point"}
}