{
  "type": "Feature",
  "properties": {
    "gn:admin1_code":"6.0",
    "gn:asciiname":"Tomiela",
    "gn:country_code":"ML",
    "gn:dem":344,
    "gn:feature_class":"P",
    "gn:feature_code":"PPL",
    "gn:name":"Tomi\u00e9la",
    "gn:population":0,
    "gn:timezone":"Africa/Bamako",
    "iso:country":"ML",
    "wof:name":"Tomiela",
    "wof:placetype":"locality"
},
  "geometry": {"coordinates":[-7.41501,11.65505],"type":"Point"}
}