{
  "type": "Feature",
  "properties": {
    "gn:admin1_code":"5.0",
    "gn:asciiname":"Souroukoubougou",
    "gn:country_code":"ML",
    "gn:dem":283,
    "gn:feature_class":"P",
    "gn:feature_code":"PPL",
    "gn:name":"Souroukoubougou",
    "gn:population":0,
    "gn:timezone":"Africa/Bamako",
    "iso:country":"ML",
    "wof:name":"Souroukoubougou",
    "wof:placetype":"locality"
},
  "geometry": {"coordinates":[-6.23663,13.93152],"type":"Point"}
}