{
  "type": "Feature",
  "properties": {
    "gn:admin1_code":"4.0",
    "gn:asciiname":"Ambavel",
    "gn:country_code":"ML",
    "gn:dem":588,
    "gn:feature_class":"P",
    "gn:feature_code":"PPL",
    "gn:name":"Ambavel",
    "gn:population":0,
    "gn:timezone":"Africa/Bamako",
    "iso:country":"ML",
    "wof:name":"Ambavel",
    "wof:placetype":"locality"
},
  "geometry": {"coordinates":[-3.55769,14.8135],"type":"Point"}
}