{
  "type": "Feature",
  "properties": {
    "gn:admin1_code":"03",
    "gn:asciiname":"Mahina",
    "gn:country_code":"ML",
    "gn:dem":176,
    "gn:feature_class":"P",
    "gn:feature_code":"PPL",
    "gn:name":"Mahina",
    "gn:population":0,
    "gn:timezone":"Africa/Bamako",
    "iso:country":"ML",
    "name:ceb_x_preferred":[
        "Mahina"
    ],
    "name:deu_x_preferred":[
        "Mahina"
    ],
    "name:fra_x_preferred":[
        "Mahina"
    ],
    "name:ita_x_preferred":[
        "Mahina"
    ],
    "name:spa_x_preferred":[
        "Mahina"
    ],
    "name:swe_x_preferred":[
        "Mahina"
    ],
    "wof:name":"Mahina",
    "wof:placetype":"locality"
},
  "geometry": {"coordinates":[-10.649,13.2965],"type":"Point"}
}