{
  "type": "Feature",
  "properties": {
    "gn:admin1_code":"05",
    "gn:asciiname":"Sanakui",
    "gn:country_code":"ML",
    "gn:dem":306,
    "gn:feature_class":"P",
    "gn:feature_code":"PPL",
    "gn:name":"Sanakui",
    "gn:population":0,
    "gn:timezone":"Africa/Bamako",
    "iso:country":"ML",
    "name:fin_x_preferred":[
        "San\u00e9kuy"
    ],
    "name:fra_x_preferred":[
        "San\u00e9kuy"
    ],
    "name:ita_x_preferred":[
        "San\u00e9kuy"
    ],
    "name:nld_x_preferred":[
        "San\u00e9kuy"
    ],
    "name:spa_x_preferred":[
        "Sanekuy"
    ],
    "name:und_x_variant":[
        "San\u00e9kui",
        "Sanakui"
    ],
    "wof:name":"Sanakui",
    "wof:placetype":"locality"
},
  "geometry": {"coordinates":[-4.6145,13.0715],"type":"Point"}
}