{
  "type": "Feature",
  "properties": {
    "gn:admin1_code":"08",
    "gn:asciiname":"Koukourou",
    "gn:country_code":"ML",
    "gn:dem":263,
    "gn:feature_class":"P",
    "gn:feature_code":"PPL",
    "gn:name":"Koukourou",
    "gn:population":0,
    "gn:timezone":"Africa/Bamako",
    "iso:country":"ML",
    "name:ara_x_preferred":[
        "\u0643\u0648\u0643\u0648\u0631\u0648"
    ],
    "name:ben_x_preferred":[
        "\u0995\u09cc\u0995\u09cc\u09b0\u09cc"
    ],
    "name:deu_x_preferred":[
        "Koukourou"
    ],
    "name:ell_x_preferred":[
        "\u039a\u03bf\u03cd\u03ba\u03bf\u03c5\u03c1\u03bf\u03c5"
    ],
    "name:eng_x_preferred":[
        "Koukourou"
    ],
    "name:fas_x_preferred":[
        "\u06a9\u0648\u06a9\u0648\u0631\u0648"
    ],
    "name:fra_x_preferred":[
        "Koukourou"
    ],
    "name:heb_x_preferred":[
        "\u05e7\u05d5\u05e7\u05d5\u05e8\u05d5"
    ],
    "name:hin_x_preferred":[
        "\u0915\u094c\u0915\u094c\u0930\u094c"
    ],
    "name:hun_x_preferred":[
        "Koukourou"
    ],
    "name:ind_x_preferred":[
        "Koukourou"
    ],
    "name:ita_x_preferred":[
        "Koukourou"
    ],
    "name:jpn_x_preferred":[
        "\u30b3\u30a6\u30af\u30ed\u30a6"
    ],
    "name:kor_x_preferred":[
        "\ucf54\uc6b0\ucf54\ub85c"
    ],
    "name:nld_x_preferred":[
        "Koukourou"
    ],
    "name:pol_x_preferred":[
        "Koukourou"
    ],
    "name:por_x_preferred":[
        "Koukourou"
    ],
    "name:spa_x_preferred":[
        "Koukourou"
    ],
    "name:tur_x_preferred":[
        "Koukourou"
    ],
    "name:ukr_x_preferred":[
        "\u041a\u043e\u0443\u043a\u043e\u0443\u0440\u043e\u0443"
    ],
    "name:urd_x_preferred":[
        "\u06a9\u0648\u06a9\u0648\u0631\u0648"
    ],
    "name:vie_x_preferred":[
        "S\u00f4ng Koukourou"
    ],
    "name:zho_cn_x_preferred":[
        "\u5e93\u5e93\u9c81\u6cb3"
    ],
    "name:zho_tw_x_preferred":[
        "\u5eab\u5eab\u9b6f\u6cb3"
    ],
    "wof:name":"Koukourou",
    "wof:placetype":"locality"
},
  "geometry": {"coordinates":[-3.8995,15.7359],"type":"Point"}
}