{
  "type": "Feature",
  "properties": {
    "gn:admin1_code":"08",
    "gn:asciiname":"Koukourou",
    "gn:country_code":"ML",
    "gn:dem":263,
    "gn:feature_class":"P",
    "gn:feature_code":"PPL",
    "gn:name":"Koukourou",
    "gn:population":0,
    "gn:timezone":"Africa/Bamako",
    "iso:country":"ML",
    "wof:name":"Koukourou",
    "wof:placetype":"locality"
},
  "geometry": {"coordinates":[-3.8995,15.7359],"type":"Point"}
}