{
  "type": "Feature",
  "properties": {
    "gn:admin1_code":"03",
    "gn:asciiname":"Djikoye",
    "gn:country_code":"ML",
    "gn:dem":157,
    "gn:feature_class":"P",
    "gn:feature_code":"PPL",
    "gn:name":"Djikoy\u00e9",
    "gn:population":0,
    "gn:timezone":"Africa/Bamako",
    "iso:country":"ML",
    "wof:name":"Djikoye",
    "wof:placetype":"locality"
},
  "geometry": {"coordinates":[-10.8702,14.0968],"type":"Point"}
}