{
  "type": "Feature",
  "properties": {
    "gn:admin1_code":"07",
    "gn:asciiname":"Yarangabougou",
    "gn:country_code":"ML",
    "gn:dem":388,
    "gn:feature_class":"P",
    "gn:feature_code":"PPL",
    "gn:name":"Yarangabougou",
    "gn:population":0,
    "gn:timezone":"Africa/Bamako",
    "iso:country":"ML",
    "name:fra_x_preferred":[
        "Yarangabougou"
    ],
    "wof:name":"Yarangabougou",
    "wof:placetype":"locality"
},
  "geometry": {"coordinates":[-8.244,13.6349],"type":"Point"}
}