{
  "type": "Feature",
  "properties": {
    "gn:admin1_code":"6.0",
    "gn:asciiname":"Bale Diassa",
    "gn:country_code":"ML",
    "gn:dem":512,
    "gn:feature_class":"P",
    "gn:feature_code":"PPL",
    "gn:name":"Bal\u00e9 Diassa",
    "gn:population":0,
    "gn:timezone":"Africa/Bamako",
    "iso:country":"ML",
    "name:und_x_variant":[
        "Diassa",
        "Bal\u00e9 Diassa"
    ],
    "wof:name":"Bale Diassa",
    "wof:placetype":"locality"
},
  "geometry": {"coordinates":[-5.61463,11.06152],"type":"Point"}
}