{
  "type": "Feature",
  "properties": {
    "gn:admin1_code":"7.0",
    "gn:asciiname":"Meniourou",
    "gn:country_code":"ML",
    "gn:dem":464,
    "gn:feature_class":"P",
    "gn:feature_code":"PPL",
    "gn:name":"M\u00e8niourou",
    "gn:population":0,
    "gn:timezone":"Africa/Bamako",
    "iso:country":"ML",
    "wof:name":"Meniourou",
    "wof:placetype":"locality"
},
  "geometry": {"coordinates":[-8.22754,12.95068],"type":"Point"}
}