{
  "type": "Feature",
  "properties": {
    "gn:admin1_code":"04",
    "gn:asciiname":"Tenda",
    "gn:country_code":"ML",
    "gn:dem":266,
    "gn:feature_class":"P",
    "gn:feature_code":"PPL",
    "gn:name":"Tenda",
    "gn:population":0,
    "gn:timezone":"Africa/Bamako",
    "iso:country":"ML",
    "name:ceb_x_preferred":[
        "Tenda"
    ],
    "name:deu_x_preferred":[
        "Tenda"
    ],
    "name:fra_x_preferred":[
        "Tenda"
    ],
    "name:ita_x_preferred":[
        "Tenda"
    ],
    "name:swe_x_preferred":[
        "Tenda"
    ],
    "name:und_x_variant":[
        "Tanda"
    ],
    "name:zho_x_preferred":[
        "Tenda"
    ],
    "wof:name":"Tenda",
    "wof:placetype":"locality"
},
  "geometry": {"coordinates":[-4.55538,14.752],"type":"Point"}
}