{
  "type": "Feature",
  "properties": {
    "gn:admin1_code":"0.0",
    "gn:asciiname":"Diokobougou",
    "gn:country_code":"ML",
    "gn:dem":359,
    "gn:feature_class":"P",
    "gn:feature_code":"PPL",
    "gn:name":"Diokobougou",
    "gn:population":0,
    "gn:timezone":"Africa/Bamako",
    "iso:country":"ML",
    "name:und_x_variant":[
        "Dioko",
        "Diokobougou"
    ],
    "wof:name":"Diokobougou",
    "wof:placetype":"locality"
},
  "geometry": {"coordinates":[-7.80411,13.00261],"type":"Point"}
}