{
  "type": "Feature",
  "properties": {
    "gn:admin1_code":"6.0",
    "gn:asciiname":"Touroumadie",
    "gn:country_code":"ML",
    "gn:dem":316,
    "gn:feature_class":"P",
    "gn:feature_code":"PPL",
    "gn:name":"Touroumadi\u00e9",
    "gn:population":0,
    "gn:timezone":"Africa/Bamako",
    "iso:country":"ML",
    "wof:name":"Touroumadie",
    "wof:placetype":"locality"
},
  "geometry": {"coordinates":[-5.60623,11.60497],"type":"Point"}
}