{
  "type": "Feature",
  "properties": {
    "gn:admin1_code":"07",
    "gn:asciiname":"Metela",
    "gn:country_code":"ML",
    "gn:dem":306,
    "gn:feature_class":"P",
    "gn:feature_code":"PPL",
    "gn:name":"M\u00e9t\u00e9la",
    "gn:population":0,
    "gn:timezone":"Africa/Bamako",
    "iso:country":"ML",
    "name:fra_x_preferred":[
        "M\u00e9t\u00e9la"
    ],
    "wof:name":"Metela",
    "wof:placetype":"locality"
},
  "geometry": {"coordinates":[-6.40129,11.92824],"type":"Point"}
}