{
  "type": "Feature",
  "properties": {
    "gn:admin1_code":"05",
    "gn:asciiname":"Wela",
    "gn:country_code":"ML",
    "gn:dem":284,
    "gn:feature_class":"P",
    "gn:feature_code":"PPL",
    "gn:name":"W\u00e9la",
    "gn:population":0,
    "gn:timezone":"Africa/Bamako",
    "iso:country":"ML",
    "name:und_x_variant":[
        "Ou\u00e9la",
        "W\u00e9la"
    ],
    "wof:name":"Wela",
    "wof:placetype":"locality"
},
  "geometry": {"coordinates":[-5.64522,13.94798],"type":"Point"}
}