{
  "type": "Feature",
  "properties": {
    "gn:admin1_code":"04",
    "gn:asciiname":"Tou",
    "gn:country_code":"ML",
    "gn:dem":272,
    "gn:feature_class":"P",
    "gn:feature_code":"PPL",
    "gn:name":"Tou",
    "gn:population":0,
    "gn:timezone":"Africa/Bamako",
    "iso:country":"ML",
    "wof:name":"Tou",
    "wof:placetype":"locality"
},
  "geometry": {"coordinates":[-4.52594,14.13215],"type":"Point"}
}