{
  "type": "Feature",
  "properties": {
    "gn:admin1_code":"04",
    "gn:asciiname":"Sokarel",
    "gn:country_code":"ML",
    "gn:dem":269,
    "gn:feature_class":"P",
    "gn:feature_code":"PPL",
    "gn:name":"Sokarel",
    "gn:population":0,
    "gn:timezone":"Africa/Bamako",
    "iso:country":"ML",
    "name:und_x_variant":[
        "Sakaral",
        "Sakarel",
        "Sokarel"
    ],
    "wof:name":"Sokarel",
    "wof:placetype":"locality"
},
  "geometry": {"coordinates":[-4.10847,14.56485],"type":"Point"}
}