{
  "type": "Feature",
  "properties": {
    "gn:admin1_code":"06",
    "gn:asciiname":"Diele",
    "gn:country_code":"ML",
    "gn:dem":320,
    "gn:feature_class":"P",
    "gn:feature_code":"PPL",
    "gn:name":"Di\u00e9l\u00e9",
    "gn:population":0,
    "gn:timezone":"Africa/Bamako",
    "iso:country":"ML",
    "name:fra_x_preferred":[
        "Di\u00e9l\u00e9"
    ],
    "wof:name":"Diele",
    "wof:placetype":"locality"
},
  "geometry": {"coordinates":[-6.57792,11.74732],"type":"Point"}
}