{
  "type": "Feature",
  "properties": {
    "gn:admin1_code":"07",
    "gn:asciiname":"Sidiankoro",
    "gn:country_code":"ML",
    "gn:dem":440,
    "gn:feature_class":"P",
    "gn:feature_code":"PPL",
    "gn:name":"Sidiankoro",
    "gn:population":0,
    "gn:timezone":"Africa/Bamako",
    "iso:country":"ML",
    "name:und_x_variant":[
        "Ziranikoro",
        "Siraninkoro",
        "Sidiankoro"
    ],
    "wof:name":"Sidiankoro",
    "wof:placetype":"locality"
},
  "geometry": {"coordinates":[-8.15227,12.62489],"type":"Point"}
}