{
  "type": "Feature",
  "properties": {
    "gn:admin1_code":"03",
    "gn:asciiname":"Niarekoto",
    "gn:country_code":"ML",
    "gn:dem":249,
    "gn:feature_class":"P",
    "gn:feature_code":"PPL",
    "gn:name":"Niar\u00e8koto",
    "gn:population":0,
    "gn:timezone":"Africa/Bamako",
    "iso:country":"ML",
    "wof:name":"Niarekoto",
    "wof:placetype":"locality"
},
  "geometry": {"coordinates":[-11.16996,13.22774],"type":"Point"}
}