{
  "type": "Feature",
  "properties": {
    "gn:admin1_code":"08",
    "gn:asciiname":"Sibo",
    "gn:country_code":"ML",
    "gn:dem":269,
    "gn:feature_class":"P",
    "gn:feature_code":"PPL",
    "gn:name":"Sibo",
    "gn:population":0,
    "gn:timezone":"Africa/Bamako",
    "iso:country":"ML",
    "name:ceb_x_preferred":[
        "Sibo"
    ],
    "name:ita_x_preferred":[
        "Sibo"
    ],
    "name:nld_x_preferred":[
        "Sibo"
    ],
    "name:nno_x_preferred":[
        "Sibo"
    ],
    "name:nor_x_preferred":[
        "Sibo"
    ],
    "name:swe_x_preferred":[
        "Sibo"
    ],
    "wof:name":"Sibo",
    "wof:placetype":"locality"
},
  "geometry": {"coordinates":[-4.0445,15.8642],"type":"Point"}
}