{
  "type": "Feature",
  "properties": {
    "gn:admin1_code":"07",
    "gn:asciiname":"Ntyebougou",
    "gn:country_code":"ML",
    "gn:dem":280,
    "gn:feature_class":"P",
    "gn:feature_code":"PPL",
    "gn:name":"Nty\u00e9bougou",
    "gn:population":0,
    "gn:timezone":"Africa/Bamako",
    "iso:country":"ML",
    "name:fra_x_preferred":[
        "Nty\u00e9bougou"
    ],
    "name:fra_x_variant":[
        "Nti\u00e9bougou"
    ],
    "wof:name":"Ntyebougou",
    "wof:placetype":"locality"
},
  "geometry": {"coordinates":[-6.86349,14.45028],"type":"Point"}
}