{
  "type": "Feature",
  "properties": {
    "gn:admin1_code":"1.0",
    "gn:asciiname":"Quartier Mali",
    "gn:country_code":"ML",
    "gn:dem":331,
    "gn:feature_class":"P",
    "gn:feature_code":"PPL",
    "gn:name":"Quartier Mali",
    "gn:population":0,
    "gn:timezone":"Africa/Bamako",
    "iso:country":"ML",
    "wof:name":"Quartier Mali",
    "wof:placetype":"locality"
},
  "geometry": {"coordinates":[-7.99959,12.61046],"type":"Point"}
}