{
  "type": "Feature",
  "properties": {
    "gn:admin1_code":"7.0",
    "gn:asciiname":"Dogoni",
    "gn:country_code":"ML",
    "gn:dem":353,
    "gn:feature_class":"P",
    "gn:feature_code":"PPL",
    "gn:name":"Dogoni",
    "gn:population":0,
    "gn:timezone":"Africa/Bamako",
    "iso:country":"ML",
    "name:fin_x_preferred":[
        "Dogoni"
    ],
    "name:fra_x_preferred":[
        "Dogoni"
    ],
    "name:ita_x_preferred":[
        "Dogoni"
    ],
    "name:nld_x_preferred":[
        "Dogoni"
    ],
    "name:por_x_preferred":[
        "Dogoni"
    ],
    "name:spa_x_preferred":[
        "Dogoni"
    ],
    "name:zho_x_preferred":[
        "\u591a\u6208\u5c3c"
    ],
    "wof:name":"Dogoni",
    "wof:placetype":"locality"
},
  "geometry": {"coordinates":[-7.3168,12.81447],"type":"Point"}
}