{
  "type": "Feature",
  "properties": {
    "gn:admin1_code":"00",
    "gn:asciiname":"Minirodougou",
    "gn:country_code":"ML",
    "gn:dem":536,
    "gn:feature_class":"P",
    "gn:feature_code":"PPL",
    "gn:name":"Minirodougou",
    "gn:population":0,
    "gn:timezone":"Africa/Bamako",
    "iso:country":"ML",
    "wof:name":"Minirodougou",
    "wof:placetype":"locality"
},
  "geometry": {"coordinates":[-9.76667,12.18333],"type":"Point"}
}