{
  "type": "Feature",
  "properties": {
    "gn:admin1_code":"00",
    "gn:asciiname":"Ogana",
    "gn:country_code":"ML",
    "gn:dem":405,
    "gn:feature_class":"P",
    "gn:feature_code":"PPL",
    "gn:name":"Ogana",
    "gn:population":0,
    "gn:timezone":"Africa/Bamako",
    "iso:country":"ML",
    "wof:name":"Ogana",
    "wof:placetype":"locality"
},
  "geometry": {"coordinates":[-7.31667,10.33333],"type":"Point"}
}