{
  "type": "Feature",
  "properties": {
    "gn:admin1_code":"05",
    "gn:asciiname":"Soumouni",
    "gn:country_code":"ML",
    "gn:dem":282,
    "gn:feature_class":"P",
    "gn:feature_code":"PPL",
    "gn:name":"Soumouni",
    "gn:population":0,
    "gn:timezone":"Africa/Bamako",
    "iso:country":"ML",
    "name:und_x_variant":[
        "Soumani",
        "Soumouni"
    ],
    "wof:name":"Soumouni",
    "wof:placetype":"locality"
},
  "geometry": {"coordinates":[-5.2356,14.1373],"type":"Point"}
}