{
  "type": "Feature",
  "properties": {
    "gn:admin1_code":"07",
    "gn:asciiname":"Moke",
    "gn:country_code":"ML",
    "gn:dem":354,
    "gn:feature_class":"P",
    "gn:feature_code":"PPL",
    "gn:name":"M\u00f4k\u00e9",
    "gn:population":0,
    "gn:timezone":"Africa/Bamako",
    "iso:country":"ML",
    "name:ceb_x_preferred":[
        "Moke"
    ],
    "name:fra_x_preferred":[
        "Moke"
    ],
    "name:swe_x_preferred":[
        "Moke"
    ],
    "wof:name":"Moke",
    "wof:placetype":"locality"
},
  "geometry": {"coordinates":[-6.8126,12.1073],"type":"Point"}
}