{
  "type": "Feature",
  "properties": {
    "gn:admin1_code":"05",
    "gn:asciiname":"Siratiguibougou",
    "gn:country_code":"ML",
    "gn:dem":298,
    "gn:feature_class":"P",
    "gn:feature_code":"PPL",
    "gn:name":"Siratiguibougou",
    "gn:population":0,
    "gn:timezone":"Africa/Bamako",
    "iso:country":"ML",
    "name:und_x_variant":[
        "Saratiguibougou",
        "Siratiguibougou"
    ],
    "wof:name":"Siratiguibougou",
    "wof:placetype":"locality"
},
  "geometry": {"coordinates":[-6.58005,13.45157],"type":"Point"}
}