{
  "type": "Feature",
  "properties": {
    "gn:admin1_code":"05",
    "gn:asciiname":"Dyourdako",
    "gn:country_code":"ML",
    "gn:dem":269,
    "gn:feature_class":"P",
    "gn:feature_code":"PPL",
    "gn:name":"Dyourdako",
    "gn:population":0,
    "gn:timezone":"Africa/Bamako",
    "iso:country":"ML",
    "name:fra_x_preferred":[
        "Dyourdako"
    ],
    "wof:name":"Dyourdako",
    "wof:placetype":"locality"
},
  "geometry": {"coordinates":[-6.2247,14.7663],"type":"Point"}
}