{
  "type": "Feature",
  "properties": {
    "gn:admin1_code":"03",
    "gn:asciiname":"Sangafe",
    "gn:country_code":"ML",
    "gn:dem":257,
    "gn:feature_class":"P",
    "gn:feature_code":"PPL",
    "gn:name":"Sangaf\u00e9",
    "gn:population":0,
    "gn:timezone":"Africa/Bamako",
    "iso:country":"ML",
    "wof:name":"Sangafe",
    "wof:placetype":"locality"
},
  "geometry": {"coordinates":[-10.3744,14.5921],"type":"Point"}
}