{
  "type": "Feature",
  "properties": {
    "gn:admin1_code":"03",
    "gn:asciiname":"Faraba",
    "gn:country_code":"ML",
    "gn:dem":216,
    "gn:feature_class":"P",
    "gn:feature_code":"PPL",
    "gn:name":"Faraba",
    "gn:population":0,
    "gn:timezone":"Africa/Bamako",
    "iso:country":"ML",
    "wof:name":"Faraba",
    "wof:placetype":"locality"
},
  "geometry": {"coordinates":[-9.9928,14.0391],"type":"Point"}
}