{
  "type": "Feature",
  "properties": {
    "gn:admin1_code":"06",
    "gn:asciiname":"Ntienina",
    "gn:country_code":"ML",
    "gn:dem":327,
    "gn:feature_class":"P",
    "gn:feature_code":"PPL",
    "gn:name":"Nti\u00e9nina",
    "gn:population":0,
    "gn:timezone":"Africa/Bamako",
    "iso:country":"ML",
    "name:fra_x_preferred":[
        "Nti\u00e9nina"
    ],
    "wof:name":"Ntienina",
    "wof:placetype":"locality"
},
  "geometry": {"coordinates":[-6.72507,11.16578],"type":"Point"}
}