{
  "type": "Feature",
  "properties": {
    "gn:admin1_code":"03",
    "gn:asciiname":"Kamidala",
    "gn:country_code":"ML",
    "gn:dem":283,
    "gn:feature_class":"P",
    "gn:feature_code":"PPL",
    "gn:name":"Kamidala",
    "gn:population":0,
    "gn:timezone":"Africa/Bamako",
    "iso:country":"ML",
    "name:und_x_variant":[
        "Kamindalah",
        "Kamidala"
    ],
    "wof:name":"Kamidala",
    "wof:placetype":"locality"
},
  "geometry": {"coordinates":[-9.2699,14.9177],"type":"Point"}
}