{
  "type": "Feature",
  "properties": {
    "gn:admin1_code":"7.0",
    "gn:asciiname":"Yayabougou",
    "gn:country_code":"ML",
    "gn:dem":357,
    "gn:feature_class":"P",
    "gn:feature_code":"PPL",
    "gn:name":"Yayabougou",
    "gn:population":0,
    "gn:timezone":"Africa/Bamako",
    "iso:country":"ML",
    "name:und_x_variant":[
        "Nioniakoro",
        "Yayabougou"
    ],
    "wof:name":"Yayabougou",
    "wof:placetype":"locality"
},
  "geometry": {"coordinates":[-7.6982,12.585],"type":"Point"}
}