{
  "type": "Feature",
  "properties": {
    "gn:admin1_code":"03",
    "gn:asciiname":"Mbadialala Sandiambougou",
    "gn:country_code":"ML",
    "gn:dem":366,
    "gn:feature_class":"P",
    "gn:feature_code":"PPL",
    "gn:name":"Mbadialala Sandiambougou",
    "gn:population":0,
    "gn:timezone":"Africa/Bamako",
    "iso:country":"ML",
    "name:und_x_variant":[
        "Mbadialala Sandianbougou",
        "Mbadialala Sandiambougou"
    ],
    "wof:name":"Mbadialala Sandiambougou",
    "wof:placetype":"locality"
},
  "geometry": {"coordinates":[-9.39202,13.29601],"type":"Point"}
}