{
  "type": "Feature",
  "properties": {
    "gn:admin1_code":"00",
    "gn:asciiname":"Kolikourounda",
    "gn:cc2":"ML",
    "gn:country_code":"ML",
    "gn:dem":339,
    "gn:feature_class":"P",
    "gn:feature_code":"PPL",
    "gn:name":"Kolikourounda",
    "gn:population":0,
    "gn:timezone":"Africa/Bamako",
    "iso:country":"ML",
    "name:und_x_variant":[
        "Kol\u00e9kouroundala",
        "Kolikourounda"
    ],
    "wof:name":"Kolikourounda",
    "wof:placetype":"locality"
},
  "geometry": {"coordinates":[-9.21667,12.76667],"type":"Point"}
}