{
  "type": "Feature",
  "properties": {
    "gn:admin1_code":"04",
    "gn:asciiname":"Koumelobogan",
    "gn:country_code":"ML",
    "gn:dem":327,
    "gn:feature_class":"P",
    "gn:feature_code":"PPL",
    "gn:name":"Koum\u00e9lobogan",
    "gn:population":0,
    "gn:timezone":"Africa/Bamako",
    "iso:country":"ML",
    "wof:name":"Koumelobogan",
    "wof:placetype":"locality"
},
  "geometry": {"coordinates":[-3.6617,13.9287],"type":"Point"}
}