{
  "type": "Feature",
  "properties": {
    "gn:admin1_code":"05",
    "gn:asciiname":"Tlike",
    "gn:country_code":"ML",
    "gn:dem":278,
    "gn:feature_class":"P",
    "gn:feature_code":"PPL",
    "gn:name":"Tlik\u00e9",
    "gn:population":0,
    "gn:timezone":"Africa/Bamako",
    "iso:country":"ML",
    "wof:name":"Tlike",
    "wof:placetype":"locality"
},
  "geometry": {"coordinates":[-5.16092,13.40545],"type":"Point"}
}