{
  "type": "Feature",
  "properties": {
    "gn:admin1_code":"04",
    "gn:asciiname":"Pene",
    "gn:country_code":"ML",
    "gn:dem":270,
    "gn:feature_class":"P",
    "gn:feature_code":"PPL",
    "gn:name":"P\u00e9n\u00e9",
    "gn:population":0,
    "gn:timezone":"Africa/Bamako",
    "iso:country":"ML",
    "name:ceb_x_preferred":[
        "Pene"
    ],
    "name:fra_x_preferred":[
        "Pene"
    ],
    "name:ita_x_preferred":[
        "Pene"
    ],
    "wof:name":"Pene",
    "wof:placetype":"locality"
},
  "geometry": {"coordinates":[-3.12219,14.1429],"type":"Point"}
}