{
  "type": "Feature",
  "properties": {
    "gn:admin1_code":"09",
    "gn:asciiname":"Kamagoundiame",
    "gn:country_code":"ML",
    "gn:dem":256,
    "gn:feature_class":"P",
    "gn:feature_code":"PPL",
    "gn:name":"Kamagoundiam\u00e9",
    "gn:population":0,
    "gn:timezone":"Africa/Bamako",
    "iso:country":"ML",
    "wof:name":"Kamagoundiame",
    "wof:placetype":"locality"
},
  "geometry": {"coordinates":[-0.01389,16.39194],"type":"Point"}
}