{
  "type": "Feature",
  "properties": {
    "gn:admin1_code":"8.0",
    "gn:asciiname":"Babi",
    "gn:country_code":"ML",
    "gn:dem":269,
    "gn:feature_class":"P",
    "gn:feature_code":"PPL",
    "gn:name":"Babi",
    "gn:population":0,
    "gn:timezone":"Africa/Bamako",
    "iso:country":"ML",
    "name:cat_x_preferred":[
        "Babi"
    ],
    "name:ceb_x_preferred":[
        "Babi"
    ],
    "name:deu_x_preferred":[
        "Babi"
    ],
    "name:ind_x_preferred":[
        "Babi"
    ],
    "name:ita_x_preferred":[
        "Babi"
    ],
    "name:por_x_preferred":[
        "Babi"
    ],
    "name:spa_x_preferred":[
        "Babi"
    ],
    "name:swe_x_preferred":[
        "Babi"
    ],
    "wof:name":"Babi",
    "wof:placetype":"locality"
},
  "geometry": {"coordinates":[-4.0451,15.8083],"type":"Point"}
}