{
  "type": "Feature",
  "properties": {
    "gn:admin1_code":"06",
    "gn:asciiname":"Faniena",
    "gn:country_code":"ML",
    "gn:dem":384,
    "gn:feature_class":"P",
    "gn:feature_code":"PPL",
    "gn:name":"Fani\u00e9na",
    "gn:population":0,
    "gn:timezone":"Africa/Bamako",
    "iso:country":"ML",
    "name:fra_x_preferred":[
        "Fani\u00e9na"
    ],
    "wof:name":"Faniena",
    "wof:placetype":"locality"
},
  "geometry": {"coordinates":[-6.01048,11.6362],"type":"Point"}
}