{
  "type": "Feature",
  "properties": {
    "gn:admin1_code":"03",
    "gn:asciiname":"Sanbala",
    "gn:country_code":"ML",
    "gn:dem":162,
    "gn:feature_class":"P",
    "gn:feature_code":"PPL",
    "gn:name":"Sanbala",
    "gn:population":0,
    "gn:timezone":"Africa/Bamako",
    "iso:country":"ML",
    "wof:name":"Sanbala",
    "wof:placetype":"locality"
},
  "geometry": {"coordinates":[-11.60495,14.26458],"type":"Point"}
}