{
  "type": "Feature",
  "properties": {
    "gn:admin1_code":"6.0",
    "gn:asciiname":"Zanadougou",
    "gn:country_code":"ML",
    "gn:dem":388,
    "gn:feature_class":"P",
    "gn:feature_code":"PPL",
    "gn:name":"Zanadougou",
    "gn:population":0,
    "gn:timezone":"Africa/Bamako",
    "iso:country":"ML",
    "wof:name":"Zanadougou",
    "wof:placetype":"locality"
},
  "geometry": {"coordinates":[-5.93649,11.23084],"type":"Point"}
}