{
  "type": "Feature",
  "properties": {
    "gn:admin1_code":"00",
    "gn:asciiname":"Farabale",
    "gn:country_code":"ML",
    "gn:dem":376,
    "gn:feature_class":"P",
    "gn:feature_code":"PPL",
    "gn:name":"Farabal\u00e9",
    "gn:population":0,
    "gn:timezone":"Africa/Bamako",
    "iso:country":"ML",
    "wof:name":"Farabale",
    "wof:placetype":"locality"
},
  "geometry": {"coordinates":[-7.28333,10.75],"type":"Point"}
}