{
  "type": "Feature",
  "properties": {
    "gn:admin1_code":"03",
    "gn:asciiname":"Jourala",
    "gn:country_code":"ML",
    "gn:dem":57,
    "gn:feature_class":"P",
    "gn:feature_code":"PPL",
    "gn:name":"Jourala",
    "gn:population":0,
    "gn:timezone":"Africa/Bamako",
    "iso:country":"ML",
    "wof:name":"Jourala",
    "wof:placetype":"locality"
},
  "geometry": {"coordinates":[-11.46146,14.3904],"type":"Point"}
}