{
  "type": "Feature",
  "properties": {
    "gn:admin1_code":"4.0",
    "gn:asciiname":"Lamordi",
    "gn:country_code":"ML",
    "gn:dem":418,
    "gn:feature_class":"P",
    "gn:feature_code":"PPL",
    "gn:name":"Lamordi",
    "gn:population":0,
    "gn:timezone":"Africa/Bamako",
    "iso:country":"ML",
    "wof:name":"Lamordi",
    "wof:placetype":"locality"
},
  "geometry": {"coordinates":[-3.09693,14.96167],"type":"Point"}
}