{
  "type": "Feature",
  "properties": {
    "gn:admin1_code":"7.0",
    "gn:asciiname":"Siradobougou",
    "gn:country_code":"ML",
    "gn:dem":353,
    "gn:feature_class":"P",
    "gn:feature_code":"PPL",
    "gn:name":"Siradobougou",
    "gn:population":0,
    "gn:timezone":"Africa/Bamako",
    "iso:country":"ML",
    "wof:name":"Siradobougou",
    "wof:placetype":"locality"
},
  "geometry": {"coordinates":[-7.60513,13.74884],"type":"Point"}
}