{
  "type": "Feature",
  "properties": {
    "gn:admin1_code":"3.0",
    "gn:asciiname":"Dabo",
    "gn:country_code":"ML",
    "gn:dem":74,
    "gn:feature_class":"P",
    "gn:feature_code":"PPL",
    "gn:name":"Dabo",
    "gn:population":0,
    "gn:timezone":"Africa/Bamako",
    "iso:country":"ML",
    "wof:name":"Dabo",
    "wof:placetype":"locality"
},
  "geometry": {"coordinates":[-11.63501,15.37798],"type":"Point"}
}