{
  "type": "Feature",
  "properties": {
    "gn:admin1_code":"03",
    "gn:asciiname":"Diboli",
    "gn:country_code":"ML",
    "gn:dem":37,
    "gn:feature_class":"P",
    "gn:feature_code":"PPL",
    "gn:name":"Diboli",
    "gn:population":0,
    "gn:timezone":"Africa/Bamako",
    "iso:country":"ML",
    "wof:name":"Diboli",
    "wof:placetype":"locality"
},
  "geometry": {"coordinates":[-12.19945,14.45511],"type":"Point"}
}