{
  "type": "Feature",
  "properties": {
    "gn:admin1_code":"03",
    "gn:asciiname":"Kamiko",
    "gn:country_code":"ML",
    "gn:dem":275,
    "gn:feature_class":"P",
    "gn:feature_code":"PPL",
    "gn:name":"Kamiko",
    "gn:population":0,
    "gn:timezone":"Africa/Bamako",
    "iso:country":"ML",
    "name:deu_x_preferred":[
        "Kamiko"
    ],
    "name:fra_x_preferred":[
        "Kamiko"
    ],
    "name:jpn_x_preferred":[
        "\u795e\u5deb\u5973 -\u30ab\u30df\u30b3-"
    ],
    "wof:name":"Kamiko",
    "wof:placetype":"locality"
},
  "geometry": {"coordinates":[-9.1687,14.773],"type":"Point"}
}