{
  "type": "Feature",
  "properties": {
    "gn:admin1_code":"4.0",
    "gn:asciiname":"Barkoussi",
    "gn:country_code":"ML",
    "gn:dem":442,
    "gn:feature_class":"P",
    "gn:feature_code":"PPL",
    "gn:name":"Barkoussi",
    "gn:population":0,
    "gn:timezone":"Africa/Bamako",
    "iso:country":"ML",
    "wof:name":"Barkoussi",
    "wof:placetype":"locality"
},
  "geometry": {"coordinates":[-1.73899,15.27341],"type":"Point"}
}