{
  "type": "Feature",
  "properties": {
    "gn:admin1_code":"00",
    "gn:asciiname":"Languekoto",
    "gn:country_code":"ML",
    "gn:dem":315,
    "gn:feature_class":"P",
    "gn:feature_code":"PPL",
    "gn:name":"Langu\u00e9koto",
    "gn:population":0,
    "gn:timezone":"Africa/Bamako",
    "iso:country":"ML",
    "wof:name":"Languekoto",
    "wof:placetype":"locality"
},
  "geometry": {"coordinates":[-9.93333,12.46667],"type":"Point"}
}