{
  "type": "Feature",
  "properties": {
    "gn:admin1_code":"8.0",
    "gn:asciiname":"Tiekoural Fagoume",
    "gn:country_code":"ML",
    "gn:dem":269,
    "gn:feature_class":"P",
    "gn:feature_code":"PPL",
    "gn:name":"Ti\u00e9koural Fagoume",
    "gn:population":0,
    "gn:timezone":"Africa/Bamako",
    "iso:country":"ML",
    "wof:name":"Tiekoural Fagoume",
    "wof:placetype":"locality"
},
  "geometry": {"coordinates":[-3.4033,15.7674],"type":"Point"}
}