{
  "type": "Feature",
  "properties": {
    "gn:admin1_code":"03",
    "gn:asciiname":"Diongaga",
    "gn:country_code":"ML",
    "gn:dem":69,
    "gn:feature_class":"P",
    "gn:feature_code":"PPL",
    "gn:name":"Diongaga",
    "gn:population":0,
    "gn:timezone":"Africa/Bamako",
    "iso:country":"ML",
    "name:und_x_variant":[
        "Diongoga",
        "Diongaga"
    ],
    "wof:name":"Diongaga",
    "wof:placetype":"locality"
},
  "geometry": {"coordinates":[-10.88489,15.07632],"type":"Point"}
}