{
  "type": "Feature",
  "properties": {
    "gn:admin1_code":"5.0",
    "gn:asciiname":"Kawesso",
    "gn:country_code":"ML",
    "gn:dem":291,
    "gn:feature_class":"P",
    "gn:feature_code":"PPL",
    "gn:name":"Kawesso",
    "gn:population":0,
    "gn:timezone":"Africa/Bamako",
    "iso:country":"ML",
    "wof:name":"Kawesso",
    "wof:placetype":"locality"
},
  "geometry": {"coordinates":[-5.03516,13.10628],"type":"Point"}
}