{
  "type": "Feature",
  "properties": {
    "gn:admin1_code":"4.0",
    "gn:asciiname":"Emmbari",
    "gn:country_code":"ML",
    "gn:dem":472,
    "gn:feature_class":"P",
    "gn:feature_code":"PPL",
    "gn:name":"Emmbari",
    "gn:population":0,
    "gn:timezone":"Africa/Bamako",
    "iso:country":"ML",
    "wof:name":"Emmbari",
    "wof:placetype":"locality"
},
  "geometry": {"coordinates":[-3.7292,14.6956],"type":"Point"}
}