{
  "type": "Feature",
  "properties": {
    "gn:admin1_code":"4.0",
    "gn:asciiname":"Patia",
    "gn:country_code":"ML",
    "gn:dem":274,
    "gn:feature_class":"P",
    "gn:feature_code":"PPL",
    "gn:name":"Patia",
    "gn:population":0,
    "gn:timezone":"Africa/Bamako",
    "iso:country":"ML",
    "name:ast_x_preferred":[
        "Patia"
    ],
    "name:ceb_x_preferred":[
        "Patia"
    ],
    "name:fra_x_preferred":[
        "Patia"
    ],
    "name:lat_x_preferred":[
        "Patia"
    ],
    "name:nld_x_preferred":[
        "Patia"
    ],
    "name:nor_x_preferred":[
        "Patia"
    ],
    "name:rus_x_preferred":[
        "Patia"
    ],
    "name:spa_x_preferred":[
        "Patia"
    ],
    "name:swe_x_preferred":[
        "Patia"
    ],
    "name:vie_x_preferred":[
        "Patia"
    ],
    "name:war_x_preferred":[
        "Patia"
    ],
    "name:zho_x_preferred":[
        "\u676f\u7c89\u8776\u5c6c"
    ],
    "wof:name":"Patia",
    "wof:placetype":"locality"
},
  "geometry": {"coordinates":[-4.02922,14.68384],"type":"Point"}
}