{
  "type": "Feature",
  "properties": {
    "gn:admin1_code":"06",
    "gn:asciiname":"Katiolo",
    "gn:country_code":"ML",
    "gn:dem":351,
    "gn:feature_class":"P",
    "gn:feature_code":"PPL",
    "gn:name":"Katiolo",
    "gn:population":0,
    "gn:timezone":"Africa/Bamako",
    "iso:country":"ML",
    "name:und_x_variant":[
        "Kadiolo",
        "Katiolo"
    ],
    "wof:name":"Katiolo",
    "wof:placetype":"locality"
},
  "geometry": {"coordinates":[-5.94331,11.1016],"type":"Point"}
}