{
  "type": "Feature",
  "properties": {
    "gn:admin1_code":"05",
    "gn:asciiname":"Sotlobougou",
    "gn:country_code":"ML",
    "gn:dem":287,
    "gn:feature_class":"P",
    "gn:feature_code":"PPL",
    "gn:name":"Sotlobougou",
    "gn:population":0,
    "gn:timezone":"Africa/Bamako",
    "iso:country":"ML",
    "name:und_x_variant":[
        "Sofl\u00e9bougou",
        "Sotlobougou"
    ],
    "wof:name":"Sotlobougou",
    "wof:placetype":"locality"
},
  "geometry": {"coordinates":[-6.23782,13.61099],"type":"Point"}
}