{
  "type": "Feature",
  "properties": {
    "gn:admin1_code":"06",
    "gn:asciiname":"Kadiandougou",
    "gn:country_code":"ML",
    "gn:dem":444,
    "gn:feature_class":"P",
    "gn:feature_code":"PPL",
    "gn:name":"Kadiandougou",
    "gn:population":0,
    "gn:timezone":"Africa/Bamako",
    "iso:country":"ML",
    "name:und_x_variant":[
        "Kouandougou",
        "Kadiandougou"
    ],
    "wof:name":"Kadiandougou",
    "wof:placetype":"locality"
},
  "geometry": {"coordinates":[-5.95081,11.31263],"type":"Point"}
}