{
  "type": "Feature",
  "properties": {
    "gn:admin1_code":"3.0",
    "gn:asciiname":"Diamoukata",
    "gn:country_code":"ML",
    "gn:dem":222,
    "gn:feature_class":"P",
    "gn:feature_code":"PPL",
    "gn:name":"Diamoukata",
    "gn:population":0,
    "gn:timezone":"Africa/Bamako",
    "iso:country":"ML",
    "wof:name":"Diamoukata",
    "wof:placetype":"locality"
},
  "geometry": {"coordinates":[-9.87643,15.36425],"type":"Point"}
}