{
  "type": "Feature",
  "properties": {
    "gn:admin1_code":"7.0",
    "gn:asciiname":"Ngoumel Marad",
    "gn:country_code":"ML",
    "gn:dem":267,
    "gn:feature_class":"P",
    "gn:feature_code":"PPL",
    "gn:name":"Ngoum\u00e9l Marad",
    "gn:population":0,
    "gn:timezone":"Africa/Bamako",
    "iso:country":"ML",
    "wof:name":"Ngoumel Marad",
    "wof:placetype":"locality"
},
  "geometry": {"coordinates":[-7.37135,15.36907],"type":"Point"}
}