{
  "type": "Feature",
  "properties": {
    "gn:admin1_code":"05",
    "gn:asciiname":"Kanabougou",
    "gn:country_code":"ML",
    "gn:dem":288,
    "gn:feature_class":"P",
    "gn:feature_code":"PPL",
    "gn:name":"Kanabougou",
    "gn:population":0,
    "gn:timezone":"Africa/Bamako",
    "iso:country":"ML",
    "wof:name":"Kanabougou",
    "wof:placetype":"locality"
},
  "geometry": {"coordinates":[-6.2761,13.5393],"type":"Point"}
}