{
  "type": "Feature",
  "properties": {
    "gn:admin1_code":"08",
    "gn:asciiname":"I-n-Tadeine",
    "gn:country_code":"ML",
    "gn:dem":289,
    "gn:feature_class":"P",
    "gn:feature_code":"PPL",
    "gn:name":"I-n-Tade\u00efn\u00e9",
    "gn:population":0,
    "gn:timezone":"Africa/Bamako",
    "iso:country":"ML",
    "wof:name":"I-n-Tadeine",
    "wof:placetype":"locality"
},
  "geometry": {"coordinates":[-1.07778,16.8775],"type":"Point"}
}