{
  "type": "Feature",
  "properties": {
    "gn:admin1_code":"05",
    "gn:asciiname":"Kalankorolo",
    "gn:country_code":"ML",
    "gn:dem":282,
    "gn:feature_class":"P",
    "gn:feature_code":"PPL",
    "gn:name":"Kalankorolo",
    "gn:population":0,
    "gn:timezone":"Africa/Bamako",
    "iso:country":"ML",
    "name:und_x_variant":[
        "Kalankorla",
        "Kalankola",
        "Kalankorolo"
    ],
    "wof:name":"Kalankorolo",
    "wof:placetype":"locality"
},
  "geometry": {"coordinates":[-5.97878,13.93049],"type":"Point"}
}