{
  "type": "Feature",
  "properties": {
    "gn:admin1_code":"03",
    "gn:asciiname":"Kourounouna",
    "gn:country_code":"ML",
    "gn:dem":314,
    "gn:feature_class":"P",
    "gn:feature_code":"PPL",
    "gn:name":"Kourounouna",
    "gn:population":0,
    "gn:timezone":"Africa/Bamako",
    "iso:country":"ML",
    "wof:name":"Kourounouna",
    "wof:placetype":"locality"
},
  "geometry": {"coordinates":[-9.8101,13.1237],"type":"Point"}
}