{
  "type": "Feature",
  "properties": {
    "gn:admin1_code":"06",
    "gn:asciiname":"Bougoudirani",
    "gn:country_code":"ML",
    "gn:dem":300,
    "gn:feature_class":"P",
    "gn:feature_code":"PPL",
    "gn:name":"Bougoudirani",
    "gn:population":0,
    "gn:timezone":"Africa/Bamako",
    "iso:country":"ML",
    "wof:name":"Bougoudirani",
    "wof:placetype":"locality"
},
  "geometry": {"coordinates":[-5.22389,12.63882],"type":"Point"}
}