{
  "type": "Feature",
  "properties": {
    "gn:admin1_code":"04",
    "gn:asciiname":"So",
    "gn:country_code":"ML",
    "gn:dem":448,
    "gn:feature_class":"P",
    "gn:feature_code":"PPL",
    "gn:name":"So",
    "gn:population":0,
    "gn:timezone":"Africa/Bamako",
    "iso:country":"ML",
    "wof:name":"So",
    "wof:placetype":"locality"
},
  "geometry": {"coordinates":[-3.83239,14.0121],"type":"Point"}
}