{
  "type": "Feature",
  "properties": {
    "gn:admin1_code":"6.0",
    "gn:asciiname":"Timpola",
    "gn:country_code":"ML",
    "gn:dem":315,
    "gn:feature_class":"P",
    "gn:feature_code":"PPL",
    "gn:name":"Timpola",
    "gn:population":0,
    "gn:timezone":"Africa/Bamako",
    "iso:country":"ML",
    "wof:name":"Timpola",
    "wof:placetype":"locality"
},
  "geometry": {"coordinates":[-6.31154,11.27609],"type":"Point"}
}