{
  "type": "Feature",
  "properties": {
    "gn:admin1_code":"4.0",
    "gn:asciiname":"Dari-Selouma",
    "gn:country_code":"ML",
    "gn:dem":267,
    "gn:feature_class":"P",
    "gn:feature_code":"PPL",
    "gn:name":"Dari-S\u00e9louma",
    "gn:population":0,
    "gn:timezone":"Africa/Bamako",
    "iso:country":"ML",
    "wof:name":"Dari-Selouma",
    "wof:placetype":"locality"
},
  "geometry": {"coordinates":[-3.9243,15.6125],"type":"Point"}
}