{
  "type": "Feature",
  "properties": {
    "gn:admin1_code":"5.0",
    "gn:asciiname":"Boundo Ouere",
    "gn:country_code":"ML",
    "gn:dem":293,
    "gn:feature_class":"P",
    "gn:feature_code":"PPL",
    "gn:name":"Boundo Ou\u00e8r\u00e8",
    "gn:population":0,
    "gn:timezone":"Africa/Bamako",
    "iso:country":"ML",
    "wof:name":"Boundo Ouere",
    "wof:placetype":"locality"
},
  "geometry": {"coordinates":[-6.5469,13.2914],"type":"Point"}
}