{
  "type": "Feature",
  "properties": {
    "gn:admin1_code":"7.0",
    "gn:asciiname":"Koreba Kabona",
    "gn:country_code":"ML",
    "gn:dem":343,
    "gn:feature_class":"P",
    "gn:feature_code":"PPL",
    "gn:name":"Kor\u00e9ba Kabona",
    "gn:population":0,
    "gn:timezone":"Africa/Bamako",
    "iso:country":"ML",
    "wof:name":"Koreba Kabona",
    "wof:placetype":"locality"
},
  "geometry": {"coordinates":[-7.62921,13.13251],"type":"Point"}
}