{
  "type": "Feature",
  "properties": {
    "gn:admin1_code":"04",
    "gn:asciiname":"Orossogou",
    "gn:country_code":"ML",
    "gn:dem":292,
    "gn:feature_class":"P",
    "gn:feature_code":"PPL",
    "gn:name":"Orossogou",
    "gn:population":0,
    "gn:timezone":"Africa/Bamako",
    "iso:country":"ML",
    "wof:name":"Orossogou",
    "wof:placetype":"locality"
},
  "geometry": {"coordinates":[-3.568,13.9551],"type":"Point"}
}