{
  "type": "Feature",
  "properties": {
    "gn:admin1_code":"06",
    "gn:asciiname":"Kelekele",
    "gn:country_code":"ML",
    "gn:dem":332,
    "gn:feature_class":"P",
    "gn:feature_code":"PPL",
    "gn:name":"K\u00e9l\u00e9k\u00e9l\u00e9",
    "gn:population":0,
    "gn:timezone":"Africa/Bamako",
    "iso:country":"ML",
    "name:fra_x_preferred":[
        "K\u00e9l\u00e9k\u00e9l\u00e9"
    ],
    "wof:name":"Kelekele",
    "wof:placetype":"locality"
},
  "geometry": {"coordinates":[-6.68831,11.05282],"type":"Point"}
}