{
  "type": "Feature",
  "properties": {
    "gn:admin1_code":"8.0",
    "gn:asciiname":"Bokoko",
    "gn:country_code":"ML",
    "gn:dem":266,
    "gn:feature_class":"P",
    "gn:feature_code":"PPL",
    "gn:name":"Bokoko",
    "gn:population":0,
    "gn:timezone":"Africa/Bamako",
    "iso:country":"ML",
    "wof:name":"Bokoko",
    "wof:placetype":"locality"
},
  "geometry": {"coordinates":[-3.39791,15.87474],"type":"Point"}
}