{
  "type": "Feature",
  "properties": {
    "gn:admin1_code":"5.0",
    "gn:asciiname":"Niadara",
    "gn:country_code":"ML",
    "gn:dem":329,
    "gn:feature_class":"P",
    "gn:feature_code":"PPL",
    "gn:name":"Niadara",
    "gn:population":0,
    "gn:timezone":"Africa/Bamako",
    "iso:country":"ML",
    "wof:name":"Niadara",
    "wof:placetype":"locality"
},
  "geometry": {"coordinates":[-4.1695,13.4572],"type":"Point"}
}