{
  "type": "Feature",
  "properties": {
    "gn:admin1_code":"5.0",
    "gn:asciiname":"Ohosso",
    "gn:country_code":"ML",
    "gn:dem":379,
    "gn:feature_class":"P",
    "gn:feature_code":"PPL",
    "gn:name":"Ohosso",
    "gn:population":0,
    "gn:timezone":"Africa/Bamako",
    "iso:country":"ML",
    "wof:name":"Ohosso",
    "wof:placetype":"locality"
},
  "geometry": {"coordinates":[-4.119,13.4268],"type":"Point"}
}