{
  "type": "Feature",
  "properties": {
    "gn:admin1_code":"06",
    "gn:asciiname":"Bougoro",
    "gn:country_code":"ML",
    "gn:dem":303,
    "gn:feature_class":"P",
    "gn:feature_code":"PPL",
    "gn:name":"Bougoro",
    "gn:population":0,
    "gn:timezone":"Africa/Bamako",
    "iso:country":"ML",
    "name:und_x_variant":[
        "Nkito",
        "Bougoro"
    ],
    "wof:name":"Bougoro",
    "wof:placetype":"locality"
},
  "geometry": {"coordinates":[-5.4141,11.9285],"type":"Point"}
}