{
  "type": "Feature",
  "properties": {
    "gn:admin1_code":"7.0",
    "gn:asciiname":"Ouolodiedo",
    "gn:country_code":"ML",
    "gn:dem":355,
    "gn:feature_class":"P",
    "gn:feature_code":"PPL",
    "gn:name":"Ouolodi\u00e8do",
    "gn:population":0,
    "gn:timezone":"Africa/Bamako",
    "iso:country":"ML",
    "wof:name":"Ouolodiedo",
    "wof:placetype":"locality"
},
  "geometry": {"coordinates":[-7.6724,12.5177],"type":"Point"}
}