{
  "type": "Feature",
  "properties": {
    "gn:admin1_code":"4.0",
    "gn:asciiname":"Wimbondou",
    "gn:country_code":"ML",
    "gn:dem":393,
    "gn:feature_class":"P",
    "gn:feature_code":"PPL",
    "gn:name":"Wimbondou",
    "gn:population":0,
    "gn:timezone":"Africa/Bamako",
    "iso:country":"ML",
    "wof:name":"Wimbondou",
    "wof:placetype":"locality"
},
  "geometry": {"coordinates":[-3.9135,14.0613],"type":"Point"}
}