{
  "type": "Feature",
  "properties": {
    "gn:admin1_code":"05",
    "gn:asciiname":"Niempiena",
    "gn:country_code":"ML",
    "gn:dem":286,
    "gn:feature_class":"P",
    "gn:feature_code":"PPL",
    "gn:name":"Niempi\u00e9na",
    "gn:population":0,
    "gn:timezone":"Africa/Bamako",
    "iso:country":"ML",
    "name:und_x_variant":[
        "Niemp\u00e9na",
        "Niempi\u00e9na"
    ],
    "wof:name":"Niempiena",
    "wof:placetype":"locality"
},
  "geometry": {"coordinates":[-6.23253,13.85165],"type":"Point"}
}