{
  "type": "Feature",
  "properties": {
    "gn:admin1_code":"4.0",
    "gn:asciiname":"Nere",
    "gn:country_code":"ML",
    "gn:dem":385,
    "gn:feature_class":"P",
    "gn:feature_code":"PPL",
    "gn:name":"N\u00e9r\u00e9",
    "gn:population":0,
    "gn:timezone":"Africa/Bamako",
    "iso:country":"ML",
    "name:ceb_x_preferred":[
        "Nere"
    ],
    "name:ita_x_preferred":[
        "Nere"
    ],
    "name:swe_x_preferred":[
        "Nere"
    ],
    "wof:name":"Nere",
    "wof:placetype":"locality"
},
  "geometry": {"coordinates":[-3.11853,14.94957],"type":"Point"}
}