{
  "type": "Feature",
  "properties": {
    "gn:admin1_code":"06",
    "gn:asciiname":"Sozana",
    "gn:country_code":"ML",
    "gn:dem":377,
    "gn:feature_class":"P",
    "gn:feature_code":"PPL",
    "gn:name":"Sozana",
    "gn:population":0,
    "gn:timezone":"Africa/Bamako",
    "iso:country":"ML",
    "wof:name":"Sozana",
    "wof:placetype":"locality"
},
  "geometry": {"coordinates":[-7.26048,11.15821],"type":"Point"}
}