{
  "type": "Feature",
  "properties": {
    "gn:admin1_code":"03",
    "gn:asciiname":"Tian",
    "gn:country_code":"ML",
    "gn:dem":440,
    "gn:feature_class":"P",
    "gn:feature_code":"PPL",
    "gn:name":"Tian",
    "gn:population":0,
    "gn:timezone":"Africa/Bamako",
    "iso:country":"ML",
    "name:fra_x_preferred":[
        "Tian"
    ],
    "wof:name":"Tian",
    "wof:placetype":"locality"
},
  "geometry": {"coordinates":[-8.78354,13.14594],"type":"Point"}
}