{
  "type": "Feature",
  "properties": {
    "gn:admin1_code":"03",
    "gn:asciiname":"Tian",
    "gn:country_code":"ML",
    "gn:dem":440,
    "gn:feature_class":"P",
    "gn:feature_code":"PPL",
    "gn:name":"Tian",
    "gn:population":0,
    "gn:timezone":"Africa/Bamako",
    "iso:country":"ML",
    "name:cat_x_preferred":[
        "Tian"
    ],
    "name:ces_x_preferred":[
        "Nebesa"
    ],
    "name:fas_x_preferred":[
        "\u062a\u06cc\u0627\u0646"
    ],
    "name:fin_x_preferred":[
        "Tian"
    ],
    "name:fra_x_preferred":[
        "Tian"
    ],
    "name:hun_x_preferred":[
        "Tien"
    ],
    "name:ind_x_preferred":[
        "Tian"
    ],
    "name:kor_x_preferred":[
        "\ucc9c"
    ],
    "name:nor_x_preferred":[
        "Tian"
    ],
    "name:pol_x_preferred":[
        "Tian"
    ],
    "name:por_x_preferred":[
        "Tian"
    ],
    "name:spa_x_preferred":[
        "Tian"
    ],
    "name:swe_x_preferred":[
        "Tian"
    ],
    "name:tur_x_preferred":[
        "Tian"
    ],
    "name:vie_x_preferred":[
        "Thi\u00ean"
    ],
    "wof:name":"Tian",
    "wof:placetype":"locality"
},
  "geometry": {"coordinates":[-8.78354,13.14594],"type":"Point"}
}