{
  "type": "Feature",
  "properties": {
    "gn:admin1_code":"00",
    "gn:asciiname":"Zantoumala",
    "gn:cc2":"ML",
    "gn:country_code":"ML",
    "gn:dem":355,
    "gn:feature_class":"P",
    "gn:feature_code":"PPL",
    "gn:name":"Zantoumala",
    "gn:population":0,
    "gn:timezone":"Africa/Bamako",
    "iso:country":"ML",
    "name:und_x_variant":[
        "Zantoumana",
        "Zantoumala"
    ],
    "wof:name":"Zantoumala",
    "wof:placetype":"locality"
},
  "geometry": {"coordinates":[-6.88333,10.81667],"type":"Point"}
}