{
  "type": "Feature",
  "properties": {
    "gn:admin1_code":"3.0",
    "gn:asciiname":"Toumane Konpo",
    "gn:country_code":"ML",
    "gn:dem":252,
    "gn:feature_class":"P",
    "gn:feature_code":"PPL",
    "gn:name":"Touman\u00e9 Konpo",
    "gn:population":0,
    "gn:timezone":"Africa/Bamako",
    "iso:country":"ML",
    "wof:name":"Toumane Konpo",
    "wof:placetype":"locality"
},
  "geometry": {"coordinates":[-10.23904,15.28341],"type":"Point"}
}