{
  "type": "Feature",
  "properties": {
    "gn:admin1_code":"06",
    "gn:asciiname":"Sala",
    "gn:country_code":"ML",
    "gn:dem":314,
    "gn:feature_class":"P",
    "gn:feature_code":"PPL",
    "gn:name":"Sala",
    "gn:population":0,
    "gn:timezone":"Africa/Bamako",
    "iso:country":"ML",
    "wof:name":"Sala",
    "wof:placetype":"locality"
},
  "geometry": {"coordinates":[-4.9036,12.0303],"type":"Point"}
}