{
  "type": "Feature",
  "properties": {
    "gn:admin1_code":"00",
    "gn:asciiname":"Daouna Bere",
    "gn:country_code":"ML",
    "gn:dem":385,
    "gn:feature_class":"P",
    "gn:feature_code":"PPL",
    "gn:name":"Daouna B\u00e9r\u00e9",
    "gn:population":0,
    "gn:timezone":"Africa/Bamako",
    "iso:country":"ML",
    "wof:name":"Daouna Bere",
    "wof:placetype":"locality"
},
  "geometry": {"coordinates":[-8.01667,10.55],"type":"Point"}
}