{
  "type": "Feature",
  "properties": {
    "gn:admin1_code":"7.0",
    "gn:asciiname":"Sido",
    "gn:country_code":"ML",
    "gn:dem":384,
    "gn:feature_class":"P",
    "gn:feature_code":"PPL",
    "gn:name":"Sido",
    "gn:population":0,
    "gn:timezone":"Africa/Bamako",
    "iso:country":"ML",
    "name:ceb_x_preferred":[
        "Sido"
    ],
    "name:deu_x_preferred":[
        "Sido"
    ],
    "name:fra_x_preferred":[
        "Sido"
    ],
    "name:swe_x_preferred":[
        "Sido"
    ],
    "wof:name":"Sido",
    "wof:placetype":"locality"
},
  "geometry": {"coordinates":[-7.42261,12.76151],"type":"Point"}
}