{
  "type": "Feature",
  "properties": {
    "gn:admin1_code":"07",
    "gn:asciiname":"Koumara",
    "gn:country_code":"ML",
    "gn:dem":298,
    "gn:feature_class":"P",
    "gn:feature_code":"PPL",
    "gn:name":"Koumara",
    "gn:population":0,
    "gn:timezone":"Africa/Bamako",
    "iso:country":"ML",
    "name:fra_x_preferred":[
        "Koumara"
    ],
    "wof:name":"Koumara",
    "wof:placetype":"locality"
},
  "geometry": {"coordinates":[-6.5318,12.6076],"type":"Point"}
}