{
  "type": "Feature",
  "properties": {
    "gn:admin1_code":"07",
    "gn:asciiname":"Dielibani",
    "gn:country_code":"ML",
    "gn:dem":380,
    "gn:feature_class":"P",
    "gn:feature_code":"PPL",
    "gn:name":"Di\u00e9libani",
    "gn:population":0,
    "gn:timezone":"Africa/Bamako",
    "iso:country":"ML",
    "wof:name":"Dielibani",
    "wof:placetype":"locality"
},
  "geometry": {"coordinates":[-8.42607,12.35419],"type":"Point"}
}