{
  "type": "Feature",
  "properties": {
    "gn:admin1_code":"7.0",
    "gn:asciiname":"Kolossebougou",
    "gn:country_code":"ML",
    "gn:dem":355,
    "gn:feature_class":"P",
    "gn:feature_code":"PPL",
    "gn:name":"Koloss\u00e9bougou",
    "gn:population":0,
    "gn:timezone":"Africa/Bamako",
    "iso:country":"ML",
    "wof:name":"Kolossebougou",
    "wof:placetype":"locality"
},
  "geometry": {"coordinates":[-7.67475,12.09479],"type":"Point"}
}