{
  "type": "Feature",
  "properties": {
    "gn:admin1_code":"5.0",
    "gn:asciiname":"Tiebela",
    "gn:country_code":"ML",
    "gn:dem":285,
    "gn:feature_class":"P",
    "gn:feature_code":"PPL",
    "gn:name":"Ti\u00e8b\u00e8la",
    "gn:population":0,
    "gn:timezone":"Africa/Bamako",
    "iso:country":"ML",
    "wof:name":"Tiebela",
    "wof:placetype":"locality"
},
  "geometry": {"coordinates":[-6.1067,13.7621],"type":"Point"}
}