{
  "type": "Feature",
  "properties": {
    "gn:admin1_code":"00",
    "gn:asciiname":"Sabere",
    "gn:country_code":"ML",
    "gn:dem":450,
    "gn:feature_class":"P",
    "gn:feature_code":"PPL",
    "gn:name":"Sab\u00e9r\u00e9",
    "gn:population":0,
    "gn:timezone":"Africa/Bamako",
    "iso:country":"ML",
    "wof:name":"Sabere",
    "wof:placetype":"locality"
},
  "geometry": {"coordinates":[-10.56667,12.21667],"type":"Point"}
}