{
  "type": "Feature",
  "properties": {
    "gn:admin1_code":"5.0",
    "gn:asciiname":"Bouka",
    "gn:country_code":"ML",
    "gn:dem":278,
    "gn:feature_class":"P",
    "gn:feature_code":"PPL",
    "gn:name":"Bouka",
    "gn:population":0,
    "gn:timezone":"Africa/Bamako",
    "iso:country":"ML",
    "name:ceb_x_preferred":[
        "Bouka"
    ],
    "name:swe_x_preferred":[
        "Bouka"
    ],
    "wof:name":"Bouka",
    "wof:placetype":"locality"
},
  "geometry": {"coordinates":[-5.34568,13.56432],"type":"Point"}
}