{
  "type": "Feature",
  "properties": {
    "gn:admin1_code":"3.0",
    "gn:asciiname":"Barsahe",
    "gn:country_code":"ML",
    "gn:dem":72,
    "gn:feature_class":"P",
    "gn:feature_code":"PPL",
    "gn:name":"Barsah\u00e9",
    "gn:population":0,
    "gn:timezone":"Africa/Bamako",
    "iso:country":"ML",
    "wof:name":"Barsahe",
    "wof:placetype":"locality"
},
  "geometry": {"coordinates":[-10.93912,15.04593],"type":"Point"}
}