{
  "type": "Feature",
  "properties": {
    "gn:admin1_code":"03",
    "gn:asciiname":"Hasi Adrami",
    "gn:country_code":"ML",
    "gn:dem":265,
    "gn:feature_class":"P",
    "gn:feature_code":"PPL",
    "gn:name":"H\u00e2si Adrami",
    "gn:population":0,
    "gn:timezone":"Africa/Bamako",
    "iso:country":"ML",
    "name:und_x_variant":[
        "Hassi Adrami",
        "H\u00e2si Adrami"
    ],
    "wof:name":"Hasi Adrami",
    "wof:placetype":"locality"
},
  "geometry": {"coordinates":[-8.8715,14.602],"type":"Point"}
}