{
  "type": "Feature",
  "properties": {
    "gn:admin1_code":"04",
    "gn:asciiname":"Soye",
    "gn:country_code":"ML",
    "gn:dem":271,
    "gn:feature_class":"P",
    "gn:feature_code":"PPL",
    "gn:name":"Soye",
    "gn:population":0,
    "gn:timezone":"Africa/Bamako",
    "iso:country":"ML",
    "name:und_x_variant":[
        "So\u00ef",
        "Soye"
    ],
    "wof:name":"Soye",
    "wof:placetype":"locality"
},
  "geometry": {"coordinates":[-4.27839,14.22813],"type":"Point"}
}