{
  "type": "Feature",
  "properties": {
    "gn:admin1_code":"04",
    "gn:asciiname":"Soye",
    "gn:country_code":"ML",
    "gn:dem":271,
    "gn:feature_class":"P",
    "gn:feature_code":"PPL",
    "gn:name":"Soye",
    "gn:population":0,
    "gn:timezone":"Africa/Bamako",
    "iso:country":"ML",
    "name:fin_x_preferred":[
        "Soye"
    ],
    "name:fra_x_preferred":[
        "Soye"
    ],
    "name:ita_x_preferred":[
        "Soye"
    ],
    "name:nld_x_preferred":[
        "Soye"
    ],
    "name:spa_x_preferred":[
        "Soye"
    ],
    "name:und_x_variant":[
        "So\u00ef"
    ],
    "name:zho_x_preferred":[
        "\u7d22\u8036"
    ],
    "wof:name":"Soye",
    "wof:placetype":"locality"
},
  "geometry": {"coordinates":[-4.27839,14.22813],"type":"Point"}
}