{
  "type": "Feature",
  "properties": {
    "gn:admin1_code":"00",
    "gn:asciiname":"Doichi",
    "gn:country_code":"ML",
    "gn:dem":259,
    "gn:feature_class":"P",
    "gn:feature_code":"PPL",
    "gn:name":"Doichi",
    "gn:population":0,
    "gn:timezone":"Africa/Bamako",
    "iso:country":"ML",
    "wof:name":"Doichi",
    "wof:placetype":"locality"
},
  "geometry": {"coordinates":[-8.4561,14.6715],"type":"Point"}
}