{
  "type": "Feature",
  "properties": {
    "gn:admin1_code":"00",
    "gn:asciiname":"Sikoro",
    "gn:country_code":"ML",
    "gn:dem":325,
    "gn:feature_class":"P",
    "gn:feature_code":"PPL",
    "gn:name":"Sikoro",
    "gn:population":0,
    "gn:timezone":"Africa/Bamako",
    "iso:country":"ML",
    "wof:name":"Sikoro",
    "wof:placetype":"locality"
},
  "geometry": {"coordinates":[-6.66667,10.55],"type":"Point"}
}