{
  "type": "Feature",
  "properties": {
    "gn:admin1_code":"03",
    "gn:asciiname":"Kambaya",
    "gn:country_code":"ML",
    "gn:dem":265,
    "gn:feature_class":"P",
    "gn:feature_code":"PPL",
    "gn:name":"Kambaya",
    "gn:population":0,
    "gn:timezone":"Africa/Bamako",
    "iso:country":"ML",
    "name:und_x_variant":[
        "Kamba\u00efa",
        "Kanbaya",
        "Kambaya"
    ],
    "wof:name":"Kambaya",
    "wof:placetype":"locality"
},
  "geometry": {"coordinates":[-11.33721,12.35368],"type":"Point"}
}