{
  "type": "Feature",
  "properties": {
    "gn:admin1_code":"07",
    "gn:asciiname":"Dogoro",
    "gn:country_code":"ML",
    "gn:dem":440,
    "gn:feature_class":"P",
    "gn:feature_code":"PPL",
    "gn:name":"Dogoro",
    "gn:population":0,
    "gn:timezone":"Africa/Bamako",
    "iso:country":"ML",
    "wof:name":"Dogoro",
    "wof:placetype":"locality"
},
  "geometry": {"coordinates":[-8.42817,12.42699],"type":"Point"}
}