{
  "type": "Feature",
  "properties": {
    "gn:admin1_code":"0.0",
    "gn:asciiname":"Bamba",
    "gn:cc2":"ML",
    "gn:country_code":"ML",
    "gn:dem":367,
    "gn:feature_class":"P",
    "gn:feature_code":"PPL",
    "gn:name":"Bamba",
    "gn:population":0,
    "gn:timezone":"Africa/Bamako",
    "iso:country":"ML",
    "name:ceb_x_preferred":[
        "Bamba"
    ],
    "name:deu_x_preferred":[
        "Bamba"
    ],
    "name:fra_x_preferred":[
        "Bamba"
    ],
    "name:heb_x_preferred":[
        "\u05d1\u05de\u05d1\u05d4"
    ],
    "name:ita_x_preferred":[
        "Bamba"
    ],
    "name:jpn_x_preferred":[
        "\u30d0\u30f3\u30d0"
    ],
    "name:pol_x_preferred":[
        "Bamba"
    ],
    "name:por_x_preferred":[
        "Bamba"
    ],
    "name:rus_x_preferred":[
        "\u0411\u0430\u043c\u0431\u0430"
    ],
    "name:swe_x_preferred":[
        "Bamba"
    ],
    "name:ukr_x_preferred":[
        "\u0411\u0430\u043c\u0431\u0430"
    ],
    "name:und_x_variant":[
        "Banba",
        "Bamba"
    ],
    "wof:name":"Bamba",
    "wof:placetype":"locality"
},
  "geometry": {"coordinates":[-7.15,10.38333],"type":"Point"}
}