{
  "type": "Feature",
  "properties": {
    "gn:admin1_code":"07",
    "gn:asciiname":"Seribougou",
    "gn:country_code":"ML",
    "gn:dem":434,
    "gn:feature_class":"P",
    "gn:feature_code":"PPL",
    "gn:name":"S\u00e8ribougou",
    "gn:population":0,
    "gn:timezone":"Africa/Bamako",
    "iso:country":"ML",
    "name:fra_x_preferred":[
        "S\u00e8ribougou"
    ],
    "wof:name":"Seribougou",
    "wof:placetype":"locality"
},
  "geometry": {"coordinates":[-8.0066,13.8362],"type":"Point"}
}