{
  "type": "Feature",
  "properties": {
    "gn:admin1_code":"00",
    "gn:asciiname":"Sanyimale",
    "gn:cc2":"ML",
    "gn:country_code":"ML",
    "gn:dem":345,
    "gn:feature_class":"P",
    "gn:feature_code":"PPL",
    "gn:name":"Sanyimal\u00e9",
    "gn:population":0,
    "gn:timezone":"Africa/Bamako",
    "iso:country":"ML",
    "name:und_x_variant":[
        "Sagnimal\u00e9",
        "Sanyimal\u00e9"
    ],
    "wof:name":"Sanyimale",
    "wof:placetype":"locality"
},
  "geometry": {"coordinates":[-8.38333,11.36667],"type":"Point"}
}