{
  "type": "Feature",
  "properties": {
    "gn:admin1_code":"3.0",
    "gn:asciiname":"Bessebougou",
    "gn:country_code":"ML",
    "gn:dem":94,
    "gn:feature_class":"P",
    "gn:feature_code":"PPL",
    "gn:name":"Bess\u00e9bougou",
    "gn:population":0,
    "gn:timezone":"Africa/Bamako",
    "iso:country":"ML",
    "wof:name":"Bessebougou",
    "wof:placetype":"locality"
},
  "geometry": {"coordinates":[-11.49711,14.33992],"type":"Point"}
}