{
  "type": "Feature",
  "properties": {
    "gn:admin1_code":"4.0",
    "gn:asciiname":"Sangui",
    "gn:country_code":"ML",
    "gn:dem":517,
    "gn:feature_class":"P",
    "gn:feature_code":"PPL",
    "gn:name":"Sangui",
    "gn:population":0,
    "gn:timezone":"Africa/Bamako",
    "iso:country":"ML",
    "wof:name":"Sangui",
    "wof:placetype":"locality"
},
  "geometry": {"coordinates":[-3.30763,14.47657],"type":"Point"}
}