{
  "type": "Feature",
  "properties": {
    "gn:admin1_code":"05",
    "gn:asciiname":"Ngolofanasso",
    "gn:country_code":"ML",
    "gn:dem":306,
    "gn:feature_class":"P",
    "gn:feature_code":"PPL",
    "gn:name":"Ngolofanasso",
    "gn:population":0,
    "gn:timezone":"Africa/Bamako",
    "iso:country":"ML",
    "name:und_x_variant":[
        "Ouolofanasso",
        "Ngolofanasso"
    ],
    "wof:name":"Ngolofanasso",
    "wof:placetype":"locality"
},
  "geometry": {"coordinates":[-4.9528,13.1964],"type":"Point"}
}