{
  "type": "Feature",
  "properties": {
    "gn:admin1_code":"3.0",
    "gn:asciiname":"Guilaba",
    "gn:country_code":"ML",
    "gn:dem":365,
    "gn:feature_class":"P",
    "gn:feature_code":"PPL",
    "gn:name":"Guilaba",
    "gn:population":0,
    "gn:timezone":"Africa/Bamako",
    "iso:country":"ML",
    "wof:name":"Guilaba",
    "wof:placetype":"locality"
},
  "geometry": {"coordinates":[-9.0006,13.0806],"type":"Point"}
}