{
  "type": "Feature",
  "properties": {
    "gn:admin1_code":"4.0",
    "gn:asciiname":"Kindi",
    "gn:country_code":"ML",
    "gn:dem":313,
    "gn:feature_class":"P",
    "gn:feature_code":"PPL",
    "gn:name":"Kindi",
    "gn:population":0,
    "gn:timezone":"Africa/Bamako",
    "iso:country":"ML",
    "name:ceb_x_preferred":[
        "Kindi"
    ],
    "name:deu_x_preferred":[
        "Kindi"
    ],
    "name:fra_x_preferred":[
        "Kindi"
    ],
    "name:swe_x_preferred":[
        "Kindi"
    ],
    "wof:name":"Kindi",
    "wof:placetype":"locality"
},
  "geometry": {"coordinates":[-2.16474,14.22188],"type":"Point"}
}