{
  "type": "Feature",
  "properties": {
    "gn:admin1_code":"5.0",
    "gn:asciiname":"Zana",
    "gn:country_code":"ML",
    "gn:dem":305,
    "gn:feature_class":"P",
    "gn:feature_code":"PPL",
    "gn:name":"Zana",
    "gn:population":0,
    "gn:timezone":"Africa/Bamako",
    "iso:country":"ML",
    "wof:name":"Zana",
    "wof:placetype":"locality"
},
  "geometry": {"coordinates":[-4.9728,13.0989],"type":"Point"}
}