{
  "type": "Feature",
  "properties": {
    "gn:admin1_code":"5.0",
    "gn:asciiname":"Mwabougou",
    "gn:country_code":"ML",
    "gn:dem":307,
    "gn:feature_class":"P",
    "gn:feature_code":"PPL",
    "gn:name":"Mwabougou",
    "gn:population":0,
    "gn:timezone":"Africa/Bamako",
    "iso:country":"ML",
    "wof:name":"Mwabougou",
    "wof:placetype":"locality"
},
  "geometry": {"coordinates":[-6.5771,12.9877],"type":"Point"}
}