{
  "type": "Feature",
  "properties": {
    "gn:admin1_code":"07",
    "gn:asciiname":"Nasela",
    "gn:country_code":"ML",
    "gn:dem":333,
    "gn:feature_class":"P",
    "gn:feature_code":"PPL",
    "gn:name":"Nas\u00e9la",
    "gn:population":0,
    "gn:timezone":"Africa/Bamako",
    "iso:country":"ML",
    "name:fra_x_preferred":[
        "Nass\u00e9la"
    ],
    "name:fra_x_variant":[
        "Nassila"
    ],
    "name:und_x_variant":[
        "Nas\u00e9la"
    ],
    "wof:name":"Nasela",
    "wof:placetype":"locality"
},
  "geometry": {"coordinates":[-6.858,12.3386],"type":"Point"}
}