{
  "type": "Feature",
  "properties": {
    "gn:admin1_code":"08",
    "gn:asciiname":"Famakouma",
    "gn:country_code":"ML",
    "gn:dem":270,
    "gn:feature_class":"P",
    "gn:feature_code":"PPL",
    "gn:name":"Famakouma",
    "gn:population":0,
    "gn:timezone":"Africa/Bamako",
    "iso:country":"ML",
    "wof:name":"Famakouma",
    "wof:placetype":"locality"
},
  "geometry": {"coordinates":[-3.5644,15.7496],"type":"Point"}
}