{
  "type": "Feature",
  "properties": {
    "gn:admin1_code":"08",
    "gn:asciiname":"Bori",
    "gn:country_code":"ML",
    "gn:dem":267,
    "gn:feature_class":"P",
    "gn:feature_code":"PPL",
    "gn:name":"Bori",
    "gn:population":0,
    "gn:timezone":"Africa/Bamako",
    "iso:country":"ML",
    "name:ceb_x_preferred":[
        "Bori"
    ],
    "name:deu_x_preferred":[
        "Bori"
    ],
    "name:fra_x_preferred":[
        "Bori"
    ],
    "name:hun_x_preferred":[
        "Bori"
    ],
    "name:ita_x_preferred":[
        "Bori"
    ],
    "name:kor_x_preferred":[
        "\ubcf4\ub9ac"
    ],
    "name:por_x_preferred":[
        "Bori"
    ],
    "name:swe_x_preferred":[
        "Bori"
    ],
    "name:vie_x_preferred":[
        "Bori"
    ],
    "wof:name":"Bori",
    "wof:placetype":"locality"
},
  "geometry": {"coordinates":[-2.76742,16.69489],"type":"Point"}
}