{
  "type": "Feature",
  "properties": {
    "gn:admin1_code":"06",
    "gn:asciiname":"Nerekoro",
    "gn:country_code":"ML",
    "gn:dem":339,
    "gn:feature_class":"P",
    "gn:feature_code":"PPL",
    "gn:name":"N\u00e8r\u00e8koro",
    "gn:population":0,
    "gn:timezone":"Africa/Bamako",
    "iso:country":"ML",
    "wof:name":"Nerekoro",
    "wof:placetype":"locality"
},
  "geometry": {"coordinates":[-7.31071,12.11532],"type":"Point"}
}