{
  "type": "Feature",
  "properties": {
    "gn:admin1_code":"07",
    "gn:asciiname":"Ndjifina",
    "gn:country_code":"ML",
    "gn:dem":305,
    "gn:feature_class":"P",
    "gn:feature_code":"PPL",
    "gn:name":"Ndjifina",
    "gn:population":0,
    "gn:timezone":"Africa/Bamako",
    "iso:country":"ML",
    "name:fra_x_preferred":[
        "N\u2019Tchifina"
    ],
    "name:fra_x_variant":[
        "Ndjifina"
    ],
    "wof:name":"Ndjifina",
    "wof:placetype":"locality"
},
  "geometry": {"coordinates":[-6.7225,12.678],"type":"Point"}
}