{
  "type": "Feature",
  "properties": {
    "gn:admin1_code":"5.0",
    "gn:asciiname":"Siriki Ouere",
    "gn:country_code":"ML",
    "gn:dem":291,
    "gn:feature_class":"P",
    "gn:feature_code":"PPL",
    "gn:name":"Siriki Ou\u00e8r\u00e8",
    "gn:population":0,
    "gn:timezone":"Africa/Bamako",
    "iso:country":"ML",
    "wof:name":"Siriki Ouere",
    "wof:placetype":"locality"
},
  "geometry": {"coordinates":[-6.13321,13.64833],"type":"Point"}
}