{
  "type": "Feature",
  "properties": {
    "gn:admin1_code":"7.0",
    "gn:asciiname":"Ndeguedo",
    "gn:country_code":"ML",
    "gn:dem":368,
    "gn:feature_class":"P",
    "gn:feature_code":"PPL",
    "gn:name":"Nd\u00e9gu\u00e9do",
    "gn:population":0,
    "gn:timezone":"Africa/Bamako",
    "iso:country":"ML",
    "wof:name":"Ndeguedo",
    "wof:placetype":"locality"
},
  "geometry": {"coordinates":[-7.73202,13.67477],"type":"Point"}
}