{
  "type": "Feature",
  "properties": {
    "gn:admin1_code":"07",
    "gn:asciiname":"Diakoni",
    "gn:country_code":"ML",
    "gn:dem":419,
    "gn:feature_class":"P",
    "gn:feature_code":"PPL",
    "gn:name":"Diakoni",
    "gn:population":0,
    "gn:timezone":"Africa/Bamako",
    "iso:country":"ML",
    "name:fra_x_preferred":[
        "Diakoni"
    ],
    "wof:name":"Diakoni",
    "wof:placetype":"locality"
},
  "geometry": {"coordinates":[-8.139,13.6802],"type":"Point"}
}