{
  "type": "Feature",
  "properties": {
    "gn:admin1_code":"07",
    "gn:asciiname":"Djikoungoni",
    "gn:country_code":"ML",
    "gn:dem":368,
    "gn:feature_class":"P",
    "gn:feature_code":"PPL",
    "gn:name":"Djikoungoni",
    "gn:population":0,
    "gn:timezone":"Africa/Bamako",
    "iso:country":"ML",
    "name:und_x_variant":[
        "Djikongoni",
        "Djikoungoni"
    ],
    "wof:name":"Djikoungoni",
    "wof:placetype":"locality"
},
  "geometry": {"coordinates":[-7.06232,12.93302],"type":"Point"}
}