{
  "type": "Feature",
  "properties": {
    "gn:admin1_code":"03",
    "gn:asciiname":"Gandega",
    "gn:country_code":"ML",
    "gn:dem":62,
    "gn:feature_class":"P",
    "gn:feature_code":"PPL",
    "gn:name":"Gand\u00e9ga",
    "gn:population":0,
    "gn:timezone":"Africa/Bamako",
    "iso:country":"ML",
    "wof:name":"Gandega",
    "wof:placetype":"locality"
},
  "geometry": {"coordinates":[-11.11429,14.79021],"type":"Point"}
}