{
  "type": "Feature",
  "properties": {
    "gn:admin1_code":"7.0",
    "gn:asciiname":"Noko",
    "gn:country_code":"ML",
    "gn:dem":360,
    "gn:feature_class":"P",
    "gn:feature_code":"PPL",
    "gn:name":"Noko",
    "gn:population":0,
    "gn:timezone":"Africa/Bamako",
    "iso:country":"ML",
    "name:spa_x_preferred":[
        "Noko"
    ],
    "wof:name":"Noko",
    "wof:placetype":"locality"
},
  "geometry": {"coordinates":[-7.79825,13.23046],"type":"Point"}
}