{
  "type": "Feature",
  "properties": {
    "gn:admin1_code":"03",
    "gn:asciiname":"Menayereka",
    "gn:country_code":"ML",
    "gn:dem":44,
    "gn:feature_class":"P",
    "gn:feature_code":"PPL",
    "gn:name":"M\u00e9nay\u00e9r\u00e9ka",
    "gn:population":0,
    "gn:timezone":"Africa/Bamako",
    "iso:country":"ML",
    "wof:name":"Menayereka",
    "wof:placetype":"locality"
},
  "geometry": {"coordinates":[-11.53607,14.44845],"type":"Point"}
}