{
  "type": "Feature",
  "properties": {
    "gn:admin1_code":"07",
    "gn:asciiname":"Galo",
    "gn:country_code":"ML",
    "gn:dem":309,
    "gn:feature_class":"P",
    "gn:feature_code":"PPL",
    "gn:name":"Galo",
    "gn:population":0,
    "gn:timezone":"Africa/Bamako",
    "iso:country":"ML",
    "name:ceb_x_preferred":[
        "Galo"
    ],
    "name:fra_x_preferred":[
        "Galo"
    ],
    "name:glg_x_preferred":[
        "Galo"
    ],
    "name:ita_x_preferred":[
        "Galo"
    ],
    "name:por_x_preferred":[
        "Galo"
    ],
    "name:spa_x_preferred":[
        "Galo"
    ],
    "name:swe_x_preferred":[
        "Galo"
    ],
    "name:und_x_variant":[
        "Gallo",
        "Galo"
    ],
    "wof:name":"Galo",
    "wof:placetype":"locality"
},
  "geometry": {"coordinates":[-7.5995,14.313],"type":"Point"}
}