{
  "type": "Feature",
  "properties": {
    "gn:admin1_code":"0.0",
    "gn:asciiname":"Bendorobougou",
    "gn:cc2":"ML",
    "gn:country_code":"ML",
    "gn:dem":328,
    "gn:feature_class":"P",
    "gn:feature_code":"PPL",
    "gn:name":"Bendorobougou",
    "gn:population":0,
    "gn:timezone":"Africa/Bamako",
    "iso:country":"ML",
    "name:und_x_variant":[
        "Bindorobougou",
        "Bendorobougou"
    ],
    "wof:name":"Bendorobougou",
    "wof:placetype":"locality"
},
  "geometry": {"coordinates":[-6.56667,11.18333],"type":"Point"}
}