{
  "type": "Feature",
  "properties": {
    "gn:admin1_code":"5.0",
    "gn:asciiname":"Bobola",
    "gn:country_code":"ML",
    "gn:dem":290,
    "gn:feature_class":"P",
    "gn:feature_code":"PPL",
    "gn:name":"Bobola",
    "gn:population":0,
    "gn:timezone":"Africa/Bamako",
    "iso:country":"ML",
    "name:und_x_variant":[
        "Babala",
        "Bobola"
    ],
    "wof:name":"Bobola",
    "wof:placetype":"locality"
},
  "geometry": {"coordinates":[-6.0823,13.5379],"type":"Point"}
}