{
  "type": "Feature",
  "properties": {
    "gn:admin1_code":"6.0",
    "gn:asciiname":"Ble",
    "gn:country_code":"ML",
    "gn:dem":352,
    "gn:feature_class":"P",
    "gn:feature_code":"PPL",
    "gn:name":"Bl\u00e9",
    "gn:population":0,
    "gn:timezone":"Africa/Bamako",
    "iso:country":"ML",
    "wof:name":"Ble",
    "wof:placetype":"locality"
},
  "geometry": {"coordinates":[-6.93153,11.85337],"type":"Point"}
}