{
  "type": "Feature",
  "properties": {
    "gn:admin1_code":"00",
    "gn:asciiname":"Sorona",
    "gn:country_code":"ML",
    "gn:dem":378,
    "gn:feature_class":"P",
    "gn:feature_code":"PPL",
    "gn:name":"Sorona",
    "gn:population":0,
    "gn:timezone":"Africa/Bamako",
    "iso:country":"ML",
    "name:epo_x_preferred":[
        "Sorona"
    ],
    "name:spa_x_preferred":[
        "Sorona"
    ],
    "wof:name":"Sorona",
    "wof:placetype":"locality"
},
  "geometry": {"coordinates":[-7.46667,10.88333],"type":"Point"}
}