{
  "type": "Feature",
  "properties": {
    "gn:admin1_code":"09",
    "gn:asciiname":"Gaina",
    "gn:country_code":"ML",
    "gn:dem":250,
    "gn:feature_class":"P",
    "gn:feature_code":"PPL",
    "gn:name":"Ga\u00efna",
    "gn:population":0,
    "gn:timezone":"Africa/Bamako",
    "iso:country":"ML",
    "name:ceb_x_preferred":[
        "Gaina"
    ],
    "name:swe_x_preferred":[
        "Gaina"
    ],
    "wof:name":"Gaina",
    "wof:placetype":"locality"
},
  "geometry": {"coordinates":[-0.06306,16.47332999999999],"type":"Point"}
}