{
  "type": "Feature",
  "properties": {
    "gn:admin1_code":"03",
    "gn:asciiname":"Taya Malea",
    "gn:country_code":"ML",
    "gn:dem":230,
    "gn:feature_class":"P",
    "gn:feature_code":"PPL",
    "gn:name":"Taya Mal\u00e9a",
    "gn:population":0,
    "gn:timezone":"Africa/Bamako",
    "iso:country":"ML",
    "name:und_x_variant":[
        "Mal\u00e9\u00efa Ta\u00efa",
        "Ta\u00efa-Mal\u00e9a",
        "Taya Mal\u00e9a"
    ],
    "wof:name":"Taya Malea",
    "wof:placetype":"locality"
},
  "geometry": {"coordinates":[-11.16117,12.28448],"type":"Point"}
}