{
  "type": "Feature",
  "properties": {
    "gn:admin1_code":"07",
    "gn:asciiname":"Kole",
    "gn:country_code":"ML",
    "gn:dem":337,
    "gn:feature_class":"P",
    "gn:feature_code":"PPL",
    "gn:name":"Kol\u00e9",
    "gn:population":0,
    "gn:timezone":"Africa/Bamako",
    "iso:country":"ML",
    "name:fra_x_preferred":[
        "Kole Weathers"
    ],
    "name:ron_x_preferred":[
        "Kole"
    ],
    "name:spa_x_preferred":[
        "Kole"
    ],
    "wof:name":"Kole",
    "wof:placetype":"locality"
},
  "geometry": {"coordinates":[-8.24357,12.23469],"type":"Point"}
}