{
  "type": "Feature",
  "properties": {
    "gn:admin1_code":"5.0",
    "gn:asciiname":"Boidiguendou",
    "gn:country_code":"ML",
    "gn:dem":351,
    "gn:feature_class":"P",
    "gn:feature_code":"PPL",
    "gn:name":"Bo\u00efdiguendou",
    "gn:population":0,
    "gn:timezone":"Africa/Bamako",
    "iso:country":"ML",
    "name:fra_x_preferred":[
        "Bo\u00efdiguendou"
    ],
    "name:fra_x_variant":[
        "Boidigendou"
    ],
    "wof:name":"Boidiguendou",
    "wof:placetype":"locality"
},
  "geometry": {"coordinates":[-6.7763,12.8395],"type":"Point"}
}