{
  "type": "Feature",
  "properties": {
    "gn:admin1_code":"5.0",
    "gn:asciiname":"Dabielabougou",
    "gn:country_code":"ML",
    "gn:dem":315,
    "gn:feature_class":"P",
    "gn:feature_code":"PPL",
    "gn:name":"Dabi\u00e9labougou",
    "gn:population":0,
    "gn:timezone":"Africa/Bamako",
    "iso:country":"ML",
    "wof:name":"Dabielabougou",
    "wof:placetype":"locality"
},
  "geometry": {"coordinates":[-6.0764,12.7005],"type":"Point"}
}