{
  "type": "Feature",
  "properties": {
    "iso:country":"ML",
    "name:ita_x_preferred":[
        "Palazzo Cassoli - Tirelli"
    ],
    "qs:gn_country":"ML",
    "qs:gn_fcode":"PPL",
    "qs:gn_pop":0,
    "qs:name":"Tirelli",
    "qs:name_adm0":"Mali",
    "qs:name_adm1":"Mopti",
    "qs:photos":260,
    "qs:photos_1k":53,
    "qs:photos_9k":1,
    "qs:photos_9r":4,
    "qs:photos_all":260,
    "qs:photos_sr":5,
    "qs:placetype":"Town",
    "qs:pop_sr":"0",
    "qs:woe_adm0":23424891,
    "wof:name":"Tirelli",
    "wof:placetype":"locality"
},
  "geometry": {"coordinates":[-3.34629,14.3803],"type":"Point"}
}