{
  "type": "Feature",
  "properties": {
    "gn:admin1_code":"7.0",
    "gn:asciiname":"Bassabougou",
    "gn:country_code":"ML",
    "gn:dem":389,
    "gn:feature_class":"P",
    "gn:feature_code":"PPL",
    "gn:name":"Bassabougou",
    "gn:population":0,
    "gn:timezone":"Africa/Bamako",
    "iso:country":"ML",
    "wof:name":"Bassabougou",
    "wof:placetype":"locality"
},
  "geometry": {"coordinates":[-7.8278,13.10465],"type":"Point"}
}