{
  "type": "Feature",
  "properties": {
    "gn:admin1_code":"4.0",
    "gn:asciiname":"Tolo",
    "gn:country_code":"ML",
    "gn:dem":606,
    "gn:feature_class":"P",
    "gn:feature_code":"PPL",
    "gn:name":"Tolo",
    "gn:population":0,
    "gn:timezone":"Africa/Bamako",
    "iso:country":"ML",
    "wof:name":"Tolo",
    "wof:placetype":"locality"
},
  "geometry": {"coordinates":[-3.08173,14.81247],"type":"Point"}
}