{
  "type": "Feature",
  "properties": {
    "gn:admin1_code":"4.0",
    "gn:asciiname":"Tolo",
    "gn:country_code":"ML",
    "gn:dem":606,
    "gn:feature_class":"P",
    "gn:feature_code":"PPL",
    "gn:name":"Tolo",
    "gn:population":0,
    "gn:timezone":"Africa/Bamako",
    "iso:country":"ML",
    "name:ceb_x_preferred":[
        "Tolo"
    ],
    "name:deu_x_preferred":[
        "Tolo"
    ],
    "name:fin_x_preferred":[
        "Tolo"
    ],
    "name:fra_x_preferred":[
        "Tolo"
    ],
    "name:ita_x_preferred":[
        "Tolo"
    ],
    "name:por_x_preferred":[
        "Tolo"
    ],
    "name:srp_x_preferred":[
        "Tolo"
    ],
    "name:swe_x_preferred":[
        "Tolo"
    ],
    "wof:name":"Tolo",
    "wof:placetype":"locality"
},
  "geometry": {"coordinates":[-3.08173,14.81247],"type":"Point"}
}