{
  "type": "Feature",
  "properties": {
    "gn:admin1_code":"5.0",
    "gn:asciiname":"Mokoulo",
    "gn:country_code":"ML",
    "gn:dem":319,
    "gn:feature_class":"P",
    "gn:feature_code":"PPL",
    "gn:name":"Mokoulo",
    "gn:population":0,
    "gn:timezone":"Africa/Bamako",
    "iso:country":"ML",
    "wof:name":"Mokoulo",
    "wof:placetype":"locality"
},
  "geometry": {"coordinates":[-6.7916,12.9563],"type":"Point"}
}