{
  "type": "Feature",
  "properties": {
    "gn:admin1_code":"06",
    "gn:asciiname":"Wolobougou",
    "gn:country_code":"ML",
    "gn:dem":355,
    "gn:feature_class":"P",
    "gn:feature_code":"PPL",
    "gn:name":"Wolobougou",
    "gn:population":0,
    "gn:timezone":"Africa/Bamako",
    "iso:country":"ML",
    "wof:name":"Wolobougou",
    "wof:placetype":"locality"
},
  "geometry": {"coordinates":[-5.48909,12.45659],"type":"Point"}
}