{
  "type": "Feature",
  "properties": {
    "gn:admin1_code":"05",
    "gn:asciiname":"Zammlara",
    "gn:country_code":"ML",
    "gn:dem":305,
    "gn:feature_class":"P",
    "gn:feature_code":"PPL",
    "gn:name":"Zammlara",
    "gn:population":0,
    "gn:timezone":"Africa/Bamako",
    "iso:country":"ML",
    "name:und_x_variant":[
        "Zamb\u00e9l\u00e9la",
        "Zamblana",
        "Zamlara",
        "Zammlara"
    ],
    "wof:name":"Zammlara",
    "wof:placetype":"locality"
},
  "geometry": {"coordinates":[-4.9041,12.6575],"type":"Point"}
}