{
  "type": "Feature",
  "properties": {
    "gn:admin1_code":"7.0",
    "gn:asciiname":"Guessebougou",
    "gn:country_code":"ML",
    "gn:dem":396,
    "gn:feature_class":"P",
    "gn:feature_code":"PPL",
    "gn:name":"Gu\u00e9ss\u00e9bougou",
    "gn:population":0,
    "gn:timezone":"Africa/Bamako",
    "iso:country":"ML",
    "wof:name":"Guessebougou",
    "wof:placetype":"locality"
},
  "geometry": {"coordinates":[-7.9634,13.09092],"type":"Point"}
}