{
  "type": "Feature",
  "properties": {
    "gn:admin1_code":"06",
    "gn:asciiname":"Kiana",
    "gn:country_code":"ML",
    "gn:dem":341,
    "gn:feature_class":"P",
    "gn:feature_code":"PPL",
    "gn:name":"Kiana",
    "gn:population":0,
    "gn:timezone":"Africa/Bamako",
    "iso:country":"ML",
    "name:ceb_x_preferred":[
        "Kiana"
    ],
    "name:fra_x_preferred":[
        "Kiana"
    ],
    "name:nld_x_preferred":[
        "Kiana"
    ],
    "name:swe_x_preferred":[
        "Kiana"
    ],
    "wof:name":"Kiana",
    "wof:placetype":"locality"
},
  "geometry": {"coordinates":[-5.96153,12.4928],"type":"Point"}
}