{
  "type": "Feature",
  "properties": {
    "gn:admin1_code":"07",
    "gn:asciiname":"Konga",
    "gn:country_code":"ML",
    "gn:dem":384,
    "gn:feature_class":"P",
    "gn:feature_code":"PPL",
    "gn:name":"Konga",
    "gn:population":0,
    "gn:timezone":"Africa/Bamako",
    "iso:country":"ML",
    "name:ceb_x_preferred":[
        "Konga"
    ],
    "name:ita_x_preferred":[
        "Konga"
    ],
    "name:nld_x_preferred":[
        "Konga"
    ],
    "name:nno_x_preferred":[
        "Konga"
    ],
    "name:nor_x_preferred":[
        "Konga"
    ],
    "name:sme_x_preferred":[
        "Konga"
    ],
    "name:swe_x_preferred":[
        "Konga"
    ],
    "name:und_x_variant":[
        "Konka",
        "Konga"
    ],
    "wof:name":"Konga",
    "wof:placetype":"locality"
},
  "geometry": {"coordinates":[-7.91044,13.57338],"type":"Point"}
}