{
  "type": "Feature",
  "properties": {
    "gn:admin1_code":"4.0",
    "gn:asciiname":"Komoguene",
    "gn:country_code":"ML",
    "gn:dem":583,
    "gn:feature_class":"P",
    "gn:feature_code":"PPL",
    "gn:name":"Komogu\u00e9n\u00e9",
    "gn:population":0,
    "gn:timezone":"Africa/Bamako",
    "iso:country":"ML",
    "wof:name":"Komoguene",
    "wof:placetype":"locality"
},
  "geometry": {"coordinates":[-3.26873,14.66897],"type":"Point"}
}