{
  "type": "Feature",
  "properties": {
    "gn:admin1_code":"07",
    "gn:asciiname":"Kouroutibia",
    "gn:country_code":"ML",
    "gn:dem":398,
    "gn:feature_class":"P",
    "gn:feature_code":"PPL",
    "gn:name":"Kouroutibia",
    "gn:population":0,
    "gn:timezone":"Africa/Bamako",
    "iso:country":"ML",
    "name:fra_x_preferred":[
        "Kouroutibia"
    ],
    "wof:name":"Kouroutibia",
    "wof:placetype":"locality"
},
  "geometry": {"coordinates":[-8.107,13.4348],"type":"Point"}
}