{
  "type": "Feature",
  "properties": {
    "gn:admin1_code":"8.0",
    "gn:asciiname":"Souli",
    "gn:country_code":"ML",
    "gn:dem":264,
    "gn:feature_class":"P",
    "gn:feature_code":"PPL",
    "gn:name":"Souli",
    "gn:population":0,
    "gn:timezone":"Africa/Bamako",
    "iso:country":"ML",
    "name:bul_x_preferred":[
        "\u0421\u0443\u043b\u0438"
    ],
    "name:ceb_x_preferred":[
        "Dimos Souli"
    ],
    "name:deu_x_preferred":[
        "Souli"
    ],
    "name:ell_x_preferred":[
        "\u0394\u03ae\u03bc\u03bf\u03c2 \u03a3\u03bf\u03c5\u03bb\u03af\u03bf\u03c5"
    ],
    "name:fin_x_preferred":[
        "So\u00fali"
    ],
    "name:ita_x_preferred":[
        "Suli"
    ],
    "name:nld_x_preferred":[
        "Souli"
    ],
    "name:nno_x_preferred":[
        "So\u00fali"
    ],
    "name:pol_x_preferred":[
        "Suli"
    ],
    "name:spa_x_preferred":[
        "Souli"
    ],
    "name:sqi_x_preferred":[
        "Suli"
    ],
    "name:swe_x_preferred":[
        "Dimos Souli"
    ],
    "name:tur_x_preferred":[
        "Suli"
    ],
    "name:vie_x_preferred":[
        "Souli"
    ],
    "wof:name":"Souli",
    "wof:placetype":"locality"
},
  "geometry": {"coordinates":[-3.7433,15.5287],"type":"Point"}
}