{
  "type": "Feature",
  "properties": {
    "gn:admin1_code":"3.0",
    "gn:asciiname":"Dini",
    "gn:country_code":"ML",
    "gn:dem":234,
    "gn:feature_class":"P",
    "gn:feature_code":"PPL",
    "gn:name":"Dini",
    "gn:population":0,
    "gn:timezone":"Africa/Bamako",
    "iso:country":"ML",
    "name:deu_x_preferred":[
        "Dini"
    ],
    "name:fra_x_preferred":[
        "Dini"
    ],
    "name:ita_x_preferred":[
        "Dini"
    ],
    "wof:name":"Dini",
    "wof:placetype":"locality"
},
  "geometry": {"coordinates":[-10.08851,15.36412],"type":"Point"}
}