{
  "type": "Feature",
  "properties": {
    "gn:admin1_code":"03",
    "gn:asciiname":"Bountou",
    "gn:country_code":"ML",
    "gn:dem":59,
    "gn:feature_class":"P",
    "gn:feature_code":"PPL",
    "gn:name":"Bountou",
    "gn:population":0,
    "gn:timezone":"Africa/Bamako",
    "iso:country":"ML",
    "name:und_x_variant":[
        "Boutou",
        "Bountou Malinke",
        "Bontou",
        "Bountou"
    ],
    "wof:name":"Bountou",
    "wof:placetype":"locality"
},
  "geometry": {"coordinates":[-12.03241,13.64661],"type":"Point"}
}