{
  "type": "Feature",
  "properties": {
    "gn:admin1_code":"4.0",
    "gn:asciiname":"Ama",
    "gn:country_code":"ML",
    "gn:dem":459,
    "gn:feature_class":"P",
    "gn:feature_code":"PPL",
    "gn:name":"Ama",
    "gn:population":0,
    "gn:timezone":"Africa/Bamako",
    "iso:country":"ML",
    "name:ceb_x_preferred":[
        "Ama"
    ],
    "name:eus_x_preferred":[
        "Ama"
    ],
    "name:glg_x_preferred":[
        "Ama"
    ],
    "name:heb_x_preferred":[
        "\u05d0\u05de\u05d4"
    ],
    "name:hye_x_preferred":[
        "\u0531\u0574\u0561"
    ],
    "name:nld_x_preferred":[
        "Ama"
    ],
    "name:ron_x_preferred":[
        "Ama"
    ],
    "name:spa_x_preferred":[
        "Ama"
    ],
    "name:tgl_x_preferred":[
        "Ama"
    ],
    "name:und_x_variant":[
        "Amo"
    ],
    "name:vol_x_preferred":[
        "Ama"
    ],
    "wof:name":"Ama",
    "wof:placetype":"locality"
},
  "geometry": {"coordinates":[-3.74729,14.0896],"type":"Point"}
}