{
  "type": "Feature",
  "properties": {
    "gn:admin1_code":"4.0",
    "gn:asciiname":"Ama",
    "gn:country_code":"ML",
    "gn:dem":459,
    "gn:feature_class":"P",
    "gn:feature_code":"PPL",
    "gn:name":"Ama",
    "gn:population":0,
    "gn:timezone":"Africa/Bamako",
    "iso:country":"ML",
    "name:und_x_variant":[
        "Amo",
        "Ama"
    ],
    "wof:name":"Ama",
    "wof:placetype":"locality"
},
  "geometry": {"coordinates":[-3.74729,14.0896],"type":"Point"}
}