{
  "type": "Feature",
  "properties": {
    "gn:admin1_code":"07",
    "gn:asciiname":"Ngouloumfala",
    "gn:country_code":"ML",
    "gn:dem":430,
    "gn:feature_class":"P",
    "gn:feature_code":"PPL",
    "gn:name":"Ngouloumfala",
    "gn:population":0,
    "gn:timezone":"Africa/Bamako",
    "iso:country":"ML",
    "name:fra_x_preferred":[
        "Ngouloumfala"
    ],
    "wof:name":"Ngouloumfala",
    "wof:placetype":"locality"
},
  "geometry": {"coordinates":[-8.0606,13.0063],"type":"Point"}
}