{
  "type": "Feature",
  "properties": {
    "gn:admin1_code":"5.0",
    "gn:asciiname":"Nyola",
    "gn:country_code":"ML",
    "gn:dem":354,
    "gn:feature_class":"P",
    "gn:feature_code":"PPL",
    "gn:name":"Nyola",
    "gn:population":0,
    "gn:timezone":"Africa/Bamako",
    "iso:country":"ML",
    "wof:name":"Nyola",
    "wof:placetype":"locality"
},
  "geometry": {"coordinates":[-6.97471,12.93746],"type":"Point"}
}