{
  "type": "Feature",
  "properties": {
    "gn:admin1_code":"06",
    "gn:asciiname":"Doniena",
    "gn:country_code":"ML",
    "gn:dem":421,
    "gn:feature_class":"P",
    "gn:feature_code":"PPL",
    "gn:name":"Doni\u00e9na",
    "gn:population":0,
    "gn:timezone":"Africa/Bamako",
    "iso:country":"ML",
    "name:und_x_variant":[
        "Dom\u00e9na",
        "Doni\u00e9na"
    ],
    "wof:name":"Doniena",
    "wof:placetype":"locality"
},
  "geometry": {"coordinates":[-5.62615,11.17238],"type":"Point"}
}