{
  "type": "Feature",
  "properties": {
    "gn:admin1_code":"03",
    "gn:asciiname":"Vindirodie",
    "gn:country_code":"ML",
    "gn:dem":203,
    "gn:feature_class":"P",
    "gn:feature_code":"PPL",
    "gn:name":"Vindirodie",
    "gn:population":0,
    "gn:timezone":"Africa/Bamako",
    "iso:country":"ML",
    "wof:name":"Vindirodie",
    "wof:placetype":"locality"
},
  "geometry": {"coordinates":[-9.49707,15.37281],"type":"Point"}
}