{
  "type": "Feature",
  "properties": {
    "gn:admin1_code":"4.0",
    "gn:asciiname":"Dagama",
    "gn:country_code":"ML",
    "gn:dem":500,
    "gn:feature_class":"P",
    "gn:feature_code":"PPL",
    "gn:name":"Dagama",
    "gn:population":0,
    "gn:timezone":"Africa/Bamako",
    "iso:country":"ML",
    "wof:name":"Dagama",
    "wof:placetype":"locality"
},
  "geometry": {"coordinates":[-2.05607,15.10573],"type":"Point"}
}