{
  "type": "Feature",
  "properties": {
    "gn:admin1_code":"04",
    "gn:asciiname":"Dogani",
    "gn:country_code":"ML",
    "gn:dem":634,
    "gn:feature_class":"P",
    "gn:feature_code":"PPL",
    "gn:name":"Dogani",
    "gn:population":0,
    "gn:timezone":"Africa/Bamako",
    "iso:country":"ML",
    "name:und_x_variant":[
        "Dagani",
        "Dangani",
        "Dogani"
    ],
    "wof:name":"Dogani",
    "wof:placetype":"locality"
},
  "geometry": {"coordinates":[-3.42359,14.8989],"type":"Point"}
}