{
  "type": "Feature",
  "properties": {
    "gn:admin1_code":"04",
    "gn:asciiname":"Segue",
    "gn:country_code":"ML",
    "gn:dem":264,
    "gn:feature_class":"P",
    "gn:feature_code":"PPL",
    "gn:name":"Segu\u00e9",
    "gn:population":0,
    "gn:timezone":"Africa/Bamako",
    "iso:country":"ML",
    "name:fra_x_preferred":[
        "Segue"
    ],
    "name:ron_x_preferred":[
        "Segue"
    ],
    "wof:name":"Segue",
    "wof:placetype":"locality"
},
  "geometry": {"coordinates":[-2.96494,13.81517],"type":"Point"}
}