{
  "type": "Feature",
  "properties": {
    "gn:admin1_code":"07",
    "gn:asciiname":"Kerela",
    "gn:country_code":"ML",
    "gn:dem":362,
    "gn:feature_class":"P",
    "gn:feature_code":"PPL",
    "gn:name":"K\u00e9r\u00e9la",
    "gn:population":0,
    "gn:timezone":"Africa/Bamako",
    "iso:country":"ML",
    "wof:name":"Kerela",
    "wof:placetype":"locality"
},
  "geometry": {"coordinates":[-7.66275,13.88945],"type":"Point"}
}