{
  "type": "Feature",
  "properties": {
    "gn:admin1_code":"00",
    "gn:asciiname":"Figuirakoura",
    "gn:cc2":"ML",
    "gn:country_code":"ML",
    "gn:dem":339,
    "gn:feature_class":"P",
    "gn:feature_code":"PPL",
    "gn:name":"Figuirakoura",
    "gn:population":0,
    "gn:timezone":"Africa/Bamako",
    "iso:country":"ML",
    "name:und_x_variant":[
        "Figuira",
        "Figuirakoura"
    ],
    "wof:name":"Figuirakoura",
    "wof:placetype":"locality"
},
  "geometry": {"coordinates":[-8.36667,11.91667],"type":"Point"}
}