{
  "type": "Feature",
  "properties": {
    "gn:admin1_code":"7.0",
    "gn:asciiname":"Soutarabougou",
    "gn:country_code":"ML",
    "gn:dem":332,
    "gn:feature_class":"P",
    "gn:feature_code":"PPL",
    "gn:name":"Soutarabougou",
    "gn:population":0,
    "gn:timezone":"Africa/Bamako",
    "iso:country":"ML",
    "wof:name":"Soutarabougou",
    "wof:placetype":"locality"
},
  "geometry": {"coordinates":[-7.8399,12.5478],"type":"Point"}
}