{
  "type": "Feature",
  "properties": {
    "gn:admin1_code":"4.0",
    "gn:asciiname":"Toua",
    "gn:country_code":"ML",
    "gn:dem":283,
    "gn:feature_class":"P",
    "gn:feature_code":"PPL",
    "gn:name":"Toua",
    "gn:population":0,
    "gn:timezone":"Africa/Bamako",
    "iso:country":"ML",
    "name:ceb_x_preferred":[
        "Toua"
    ],
    "name:deu_x_preferred":[
        "Toua"
    ],
    "name:swe_x_preferred":[
        "Toua"
    ],
    "wof:name":"Toua",
    "wof:placetype":"locality"
},
  "geometry": {"coordinates":[-2.50777,15.22091],"type":"Point"}
}