{
  "type": "Feature",
  "properties": {
    "gn:admin1_code":"06",
    "gn:asciiname":"Ntarla",
    "gn:country_code":"ML",
    "gn:dem":321,
    "gn:feature_class":"P",
    "gn:feature_code":"PPL",
    "gn:name":"Ntarla",
    "gn:population":0,
    "gn:timezone":"Africa/Bamako",
    "iso:country":"ML",
    "wof:name":"Ntarla",
    "wof:placetype":"locality"
},
  "geometry": {"coordinates":[-5.70341,12.55225],"type":"Point"}
}