{
  "type": "Feature",
  "properties": {
    "gn:admin1_code":"09",
    "gn:asciiname":"Bourem Guindou",
    "gn:country_code":"ML",
    "gn:dem":259,
    "gn:feature_class":"P",
    "gn:feature_code":"PPL",
    "gn:name":"Bour\u00e8m Guindou",
    "gn:population":0,
    "gn:timezone":"Africa/Bamako",
    "iso:country":"ML",
    "name:und_x_variant":[
        "Bourem",
        "Bour\u00e8m Guindou"
    ],
    "wof:name":"Bourem Guindou",
    "wof:placetype":"locality"
},
  "geometry": {"coordinates":[-0.35667,16.90889],"type":"Point"}
}