{
  "type": "Feature",
  "properties": {
    "gn:admin1_code":"06",
    "gn:asciiname":"Faradie",
    "gn:country_code":"ML",
    "gn:dem":363,
    "gn:feature_class":"P",
    "gn:feature_code":"PPL",
    "gn:name":"Faradi\u00e9",
    "gn:population":0,
    "gn:timezone":"Africa/Bamako",
    "iso:country":"ML",
    "wof:name":"Faradie",
    "wof:placetype":"locality"
},
  "geometry": {"coordinates":[-7.5483,11.2616],"type":"Point"}
}