{
  "type": "Feature",
  "properties": {
    "gn:admin1_code":"00",
    "gn:asciiname":"Sitabolon",
    "gn:country_code":"ML",
    "gn:dem":329,
    "gn:feature_class":"P",
    "gn:feature_code":"PPL",
    "gn:name":"Sitabolon",
    "gn:population":0,
    "gn:timezone":"Africa/Bamako",
    "iso:country":"ML",
    "wof:name":"Sitabolon",
    "wof:placetype":"locality"
},
  "geometry": {"coordinates":[-9.26667,12.61667],"type":"Point"}
}