{
  "type": "Feature",
  "properties": {
    "gn:admin1_code":"7.0",
    "gn:asciiname":"Tyekourabougou",
    "gn:country_code":"ML",
    "gn:dem":354,
    "gn:feature_class":"P",
    "gn:feature_code":"PPL",
    "gn:name":"Ty\u00e8kourabougou",
    "gn:population":0,
    "gn:timezone":"Africa/Bamako",
    "iso:country":"ML",
    "wof:name":"Tyekourabougou",
    "wof:placetype":"locality"
},
  "geometry": {"coordinates":[-7.25886,12.62936],"type":"Point"}
}