{
  "type": "Feature",
  "properties": {
    "gn:admin1_code":"4.0",
    "gn:asciiname":"Nenabe",
    "gn:country_code":"ML",
    "gn:dem":267,
    "gn:feature_class":"P",
    "gn:feature_code":"PPL",
    "gn:name":"N\u00e9nab\u00e9",
    "gn:population":0,
    "gn:timezone":"Africa/Bamako",
    "iso:country":"ML",
    "wof:name":"Nenabe",
    "wof:placetype":"locality"
},
  "geometry": {"coordinates":[-4.91677,14.31917],"type":"Point"}
}