{
  "type": "Feature",
  "properties": {
    "gn:admin1_code":"00",
    "gn:asciiname":"Tingone",
    "gn:country_code":"ML",
    "gn:dem":352,
    "gn:feature_class":"P",
    "gn:feature_code":"PPL",
    "gn:name":"Tingon\u00e9",
    "gn:population":0,
    "gn:timezone":"Africa/Bamako",
    "iso:country":"ML",
    "wof:name":"Tingone",
    "wof:placetype":"locality"
},
  "geometry": {"coordinates":[-7.03333,12.03333],"type":"Point"}
}