{
  "type": "Feature",
  "properties": {
    "gn:admin1_code":"06",
    "gn:asciiname":"Toupourla",
    "gn:country_code":"ML",
    "gn:dem":307,
    "gn:feature_class":"P",
    "gn:feature_code":"PPL",
    "gn:name":"Toupourla",
    "gn:population":0,
    "gn:timezone":"Africa/Bamako",
    "iso:country":"ML",
    "wof:name":"Toupourla",
    "wof:placetype":"locality"
},
  "geometry": {"coordinates":[-5.92665,12.31976],"type":"Point"}
}