{
  "type": "Feature",
  "properties": {
    "gn:admin1_code":"06",
    "gn:asciiname":"Neresso",
    "gn:country_code":"ML",
    "gn:dem":381,
    "gn:feature_class":"P",
    "gn:feature_code":"PPL",
    "gn:name":"N\u00e9resso",
    "gn:population":0,
    "gn:timezone":"Africa/Bamako",
    "iso:country":"ML",
    "wof:name":"Neresso",
    "wof:placetype":"locality"
},
  "geometry": {"coordinates":[-4.7288,12.2916],"type":"Point"}
}