{
  "type": "Feature",
  "properties": {
    "gn:admin1_code":"07",
    "gn:asciiname":"Ngabakoro Tiessouen",
    "gn:country_code":"ML",
    "gn:dem":382,
    "gn:feature_class":"P",
    "gn:feature_code":"PPL",
    "gn:name":"Ngabakoro Ti\u00e8ssouen",
    "gn:population":0,
    "gn:timezone":"Africa/Bamako",
    "iso:country":"ML",
    "name:und_x_variant":[
        "N\u2019Kabakoro",
        "Gabakoro",
        "Ngabakoro Ti\u00e8ssouen"
    ],
    "wof:name":"Ngabakoro Tiessouen",
    "wof:placetype":"locality"
},
  "geometry": {"coordinates":[-7.99012,13.2315],"type":"Point"}
}