{
  "type": "Feature",
  "properties": {
    "gn:admin1_code":"3.0",
    "gn:asciiname":"Barama",
    "gn:country_code":"ML",
    "gn:dem":212,
    "gn:feature_class":"P",
    "gn:feature_code":"PPL",
    "gn:name":"Barama",
    "gn:population":0,
    "gn:timezone":"Africa/Bamako",
    "iso:country":"ML",
    "wof:name":"Barama",
    "wof:placetype":"locality"
},
  "geometry": {"coordinates":[-9.932,14.3243],"type":"Point"}
}