{
  "type": "Feature",
  "properties": {
    "gn:admin1_code":"04",
    "gn:asciiname":"Dia",
    "gn:country_code":"ML",
    "gn:dem":285,
    "gn:feature_class":"P",
    "gn:feature_code":"PPL",
    "gn:name":"Dia",
    "gn:population":0,
    "gn:timezone":"Africa/Bamako",
    "iso:country":"ML",
    "name:cat_x_preferred":[
        "Dia"
    ],
    "name:ceb_x_preferred":[
        "Dia"
    ],
    "name:deu_x_preferred":[
        "Dia"
    ],
    "name:fas_x_preferred":[
        "\u062f\u06cc\u0627"
    ],
    "name:fin_x_preferred":[
        "Dia"
    ],
    "name:fra_x_preferred":[
        "Dia"
    ],
    "name:ind_x_preferred":[
        "Dia"
    ],
    "name:nld_x_preferred":[
        "Dia"
    ],
    "name:oci_x_preferred":[
        "Di\u00e1"
    ],
    "name:pol_x_preferred":[
        "Dia"
    ],
    "name:por_x_preferred":[
        "Dia"
    ],
    "name:rus_x_preferred":[
        "\u0414\u0438\u044f"
    ],
    "name:slk_x_preferred":[
        "Dia"
    ],
    "name:spa_x_preferred":[
        "Dia"
    ],
    "name:swe_x_preferred":[
        "Dia"
    ],
    "name:und_x_variant":[
        "Dianga"
    ],
    "name:vie_x_preferred":[
        "D\u0129a"
    ],
    "name:zho_x_preferred":[
        "Dia"
    ],
    "wof:name":"Dia",
    "wof:placetype":"locality"
},
  "geometry": {"coordinates":[-3.6372,13.7632],"type":"Point"}
}