{
  "type": "Feature",
  "properties": {
    "gn:admin1_code":"04",
    "gn:asciiname":"Dia",
    "gn:country_code":"ML",
    "gn:dem":285,
    "gn:feature_class":"P",
    "gn:feature_code":"PPL",
    "gn:name":"Dia",
    "gn:population":0,
    "gn:timezone":"Africa/Bamako",
    "iso:country":"ML",
    "name:und_x_variant":[
        "Dianga",
        "Dia"
    ],
    "wof:name":"Dia",
    "wof:placetype":"locality"
},
  "geometry": {"coordinates":[-3.6372,13.7632],"type":"Point"}
}