{
  "type": "Feature",
  "properties": {
    "gn:admin1_code":"03",
    "gn:asciiname":"Moussoume",
    "gn:country_code":"ML",
    "gn:dem":180,
    "gn:feature_class":"P",
    "gn:feature_code":"PPL",
    "gn:name":"Moussoum\u00e9",
    "gn:population":0,
    "gn:timezone":"Africa/Bamako",
    "iso:country":"ML",
    "wof:name":"Moussoume",
    "wof:placetype":"locality"
},
  "geometry": {"coordinates":[-10.8801,14.1563],"type":"Point"}
}