{
  "type": "Feature",
  "properties": {
    "gn:admin1_code":"8.0",
    "gn:asciiname":"Nanbi",
    "gn:country_code":"ML",
    "gn:dem":267,
    "gn:feature_class":"P",
    "gn:feature_code":"PPL",
    "gn:name":"Nanbi",
    "gn:population":0,
    "gn:timezone":"Africa/Bamako",
    "iso:country":"ML",
    "wof:name":"Nanbi",
    "wof:placetype":"locality"
},
  "geometry": {"coordinates":[-4.5367,15.6305],"type":"Point"}
}