{
  "type": "Feature",
  "properties": {
    "gn:admin1_code":"03",
    "gn:asciiname":"Guemou",
    "gn:country_code":"ML",
    "gn:dem":40,
    "gn:feature_class":"P",
    "gn:feature_code":"PPL",
    "gn:name":"Gu\u00e9mou",
    "gn:population":0,
    "gn:timezone":"Africa/Bamako",
    "iso:country":"ML",
    "wof:name":"Guemou",
    "wof:placetype":"locality"
},
  "geometry": {"coordinates":[-11.85154,14.51104],"type":"Point"}
}