{
  "type": "Feature",
  "properties": {
    "gn:admin1_code":"4.0",
    "gn:asciiname":"Beni",
    "gn:country_code":"ML",
    "gn:dem":398,
    "gn:feature_class":"P",
    "gn:feature_code":"PPL",
    "gn:name":"B\u00e9ni",
    "gn:population":0,
    "gn:timezone":"Africa/Bamako",
    "iso:country":"ML",
    "wof:name":"Beni",
    "wof:placetype":"locality"
},
  "geometry": {"coordinates":[-2.94713,14.85388],"type":"Point"}
}