{
  "type": "Feature",
  "properties": {
    "gn:admin1_code":"4.0",
    "gn:asciiname":"Beni",
    "gn:country_code":"ML",
    "gn:dem":398,
    "gn:feature_class":"P",
    "gn:feature_code":"PPL",
    "gn:name":"B\u00e9ni",
    "gn:population":0,
    "gn:timezone":"Africa/Bamako",
    "iso:country":"ML",
    "name:ara_x_preferred":[
        "\u0628\u064a\u0646\u064a"
    ],
    "name:ben_x_preferred":[
        "\u09ac\u09c7\u09a8\u09bf"
    ],
    "name:ceb_x_preferred":[
        "Beni"
    ],
    "name:deu_x_preferred":[
        "Beni"
    ],
    "name:ell_x_preferred":[
        "\u039c\u03c0\u03ad\u03bd\u03b9"
    ],
    "name:est_x_preferred":[
        "Beni"
    ],
    "name:fin_x_preferred":[
        "Beni"
    ],
    "name:fra_x_preferred":[
        "Beni"
    ],
    "name:heb_x_preferred":[
        "\u05d1\u05e0\u05d9"
    ],
    "name:hin_x_preferred":[
        "\u092c\u0947\u0928\u0940"
    ],
    "name:hrv_x_preferred":[
        "Beni"
    ],
    "name:hun_x_preferred":[
        "Beni"
    ],
    "name:ind_x_preferred":[
        "Beni"
    ],
    "name:ita_x_preferred":[
        "Beni"
    ],
    "name:kat_x_preferred":[
        "\u10d1\u10d4\u10dc\u10d8"
    ],
    "name:kor_x_preferred":[
        "\ubca0\ub2c8"
    ],
    "name:nld_x_preferred":[
        "Beni"
    ],
    "name:nor_x_preferred":[
        "Beni"
    ],
    "name:pol_x_preferred":[
        "Beni"
    ],
    "name:por_x_preferred":[
        "Beni"
    ],
    "name:rus_x_preferred":[
        "\u0411\u0435\u043d\u0438"
    ],
    "name:scn_x_preferred":[
        "Beni"
    ],
    "name:slv_x_preferred":[
        "Beni"
    ],
    "name:spa_x_preferred":[
        "Beni"
    ],
    "name:srp_x_preferred":[
        "\u0411\u0435\u043d\u0438"
    ],
    "name:swe_x_preferred":[
        "Beni"
    ],
    "name:tur_x_preferred":[
        "Beni"
    ],
    "name:ukr_x_preferred":[
        "\u0411\u0435\u043d\u0456"
    ],
    "name:urd_x_preferred":[
        "\u0628\u06cc\u0646\u06cc"
    ],
    "wof:name":"Beni",
    "wof:placetype":"locality"
},
  "geometry": {"coordinates":[-2.94713,14.85388],"type":"Point"}
}