{
  "type": "Feature",
  "properties": {
    "gn:admin1_code":"06",
    "gn:asciiname":"Gouanale",
    "gn:country_code":"ML",
    "gn:dem":347,
    "gn:feature_class":"P",
    "gn:feature_code":"PPL",
    "gn:name":"Gouanal\u00e9",
    "gn:population":0,
    "gn:timezone":"Africa/Bamako",
    "iso:country":"ML",
    "wof:name":"Gouanale",
    "wof:placetype":"locality"
},
  "geometry": {"coordinates":[-7.6652,11.91187],"type":"Point"}
}