{
  "type": "Feature",
  "properties": {
    "gn:admin1_code":"04",
    "gn:asciiname":"Makadie",
    "gn:country_code":"ML",
    "gn:dem":269,
    "gn:feature_class":"P",
    "gn:feature_code":"PPL",
    "gn:name":"Makadi\u00e9",
    "gn:population":0,
    "gn:timezone":"Africa/Bamako",
    "iso:country":"ML",
    "name:und_x_variant":[
        "Markadie",
        "Makadji\u00e9",
        "Makadi\u00e9"
    ],
    "wof:name":"Makadie",
    "wof:placetype":"locality"
},
  "geometry": {"coordinates":[-4.4972,14.28782],"type":"Point"}
}