{
  "type": "Feature",
  "properties": {
    "gn:admin1_code":"6.0",
    "gn:asciiname":"Dyalanyena",
    "gn:country_code":"ML",
    "gn:dem":343,
    "gn:feature_class":"P",
    "gn:feature_code":"PPL",
    "gn:name":"Dyalany\u00e9na",
    "gn:population":0,
    "gn:timezone":"Africa/Bamako",
    "iso:country":"ML",
    "wof:name":"Dyalanyena",
    "wof:placetype":"locality"
},
  "geometry": {"coordinates":[-6.0909,12.6262],"type":"Point"}
}