{
  "type": "Feature",
  "properties": {
    "gn:admin1_code":"3.0",
    "gn:asciiname":"Banntako",
    "gn:country_code":"ML",
    "gn:dem":321,
    "gn:feature_class":"P",
    "gn:feature_code":"PPL",
    "gn:name":"Banntako",
    "gn:population":0,
    "gn:timezone":"Africa/Bamako",
    "iso:country":"ML",
    "wof:name":"Banntako",
    "wof:placetype":"locality"
},
  "geometry": {"coordinates":[-11.10786,13.19852],"type":"Point"}
}