{
  "type": "Feature",
  "properties": {
    "gn:admin1_code":"04",
    "gn:asciiname":"Toumoura",
    "gn:country_code":"ML",
    "gn:dem":270,
    "gn:feature_class":"P",
    "gn:feature_code":"PPL",
    "gn:name":"Toumoura",
    "gn:population":0,
    "gn:timezone":"Africa/Bamako",
    "iso:country":"ML",
    "wof:name":"Toumoura",
    "wof:placetype":"locality"
},
  "geometry": {"coordinates":[-4.31374,14.41638],"type":"Point"}
}