{
  "type": "Feature",
  "properties": {
    "gn:admin1_code":"03",
    "gn:asciiname":"Trantimou",
    "gn:country_code":"ML",
    "gn:dem":295,
    "gn:feature_class":"P",
    "gn:feature_code":"PPL",
    "gn:name":"Trantimou",
    "gn:population":0,
    "gn:timezone":"Africa/Bamako",
    "iso:country":"ML",
    "name:und_x_variant":[
        "Tarentimou",
        "Trantimou"
    ],
    "wof:name":"Trantimou",
    "wof:placetype":"locality"
},
  "geometry": {"coordinates":[-10.1927,14.4805],"type":"Point"}
}