{
  "type": "Feature",
  "properties": {
    "gn:admin1_code":"05",
    "gn:asciiname":"Diessourouna",
    "gn:country_code":"ML",
    "gn:dem":318,
    "gn:feature_class":"P",
    "gn:feature_code":"PPL",
    "gn:name":"Di\u00e9ssourouna",
    "gn:population":0,
    "gn:timezone":"Africa/Bamako",
    "iso:country":"ML",
    "wof:name":"Diessourouna",
    "wof:placetype":"locality"
},
  "geometry": {"coordinates":[-6.6701,13.8848],"type":"Point"}
}