{
  "type": "Feature",
  "properties": {
    "gn:admin1_code":"07",
    "gn:asciiname":"Misira Kroa",
    "gn:country_code":"ML",
    "gn:dem":259,
    "gn:feature_class":"P",
    "gn:feature_code":"PPL",
    "gn:name":"Misira Kroa",
    "gn:population":0,
    "gn:timezone":"Africa/Bamako",
    "iso:country":"ML",
    "name:und_x_variant":[
        "Missira Kroa",
        "Misira Kroa"
    ],
    "wof:name":"Misira Kroa",
    "wof:placetype":"locality"
},
  "geometry": {"coordinates":[-8.87001,15.4824],"type":"Point"}
}