{
  "type": "Feature",
  "properties": {
    "gn:admin1_code":"03",
    "gn:asciiname":"Sanba Gone",
    "gn:country_code":"ML",
    "gn:dem":238,
    "gn:feature_class":"P",
    "gn:feature_code":"PPL",
    "gn:name":"Sanba Gon\u00e9",
    "gn:population":0,
    "gn:timezone":"Africa/Bamako",
    "iso:country":"ML",
    "wof:name":"Sanba Gone",
    "wof:placetype":"locality"
},
  "geometry": {"coordinates":[-9.74607,15.22674],"type":"Point"}
}