{
  "type": "Feature",
  "properties": {
    "gn:admin1_code":"05",
    "gn:asciiname":"Djenina",
    "gn:country_code":"ML",
    "gn:dem":331,
    "gn:feature_class":"P",
    "gn:feature_code":"PPL",
    "gn:name":"Dj\u00e9nina",
    "gn:population":0,
    "gn:timezone":"Africa/Bamako",
    "iso:country":"ML",
    "name:fra_x_preferred":[
        "Dj\u00e9nina"
    ],
    "wof:name":"Djenina",
    "wof:placetype":"locality"
},
  "geometry": {"coordinates":[-6.7205,12.897],"type":"Point"}
}