{
  "type": "Feature",
  "properties": {
    "gn:admin1_code":"03",
    "gn:asciiname":"Mouriba Toumoni",
    "gn:country_code":"ML",
    "gn:dem":336,
    "gn:feature_class":"P",
    "gn:feature_code":"PPL",
    "gn:name":"Mouriba Toumoni",
    "gn:population":0,
    "gn:timezone":"Africa/Bamako",
    "iso:country":"ML",
    "name:fra_x_preferred":[
        "Mouriba Toumoni"
    ],
    "wof:name":"Mouriba Toumoni",
    "wof:placetype":"locality"
},
  "geometry": {"coordinates":[-8.9301,13.4489],"type":"Point"}
}