{
  "type": "Feature",
  "properties": {
    "gn:admin1_code":"4.0",
    "gn:asciiname":"Gamra",
    "gn:country_code":"ML",
    "gn:dem":611,
    "gn:feature_class":"P",
    "gn:feature_code":"PPL",
    "gn:name":"Gamra",
    "gn:population":0,
    "gn:timezone":"Africa/Bamako",
    "iso:country":"ML",
    "wof:name":"Gamra",
    "wof:placetype":"locality"
},
  "geometry": {"coordinates":[-2.42651,15.18611],"type":"Point"}
}