{
  "type": "Feature",
  "properties": {
    "gn:admin1_code":"04",
    "gn:asciiname":"Para",
    "gn:country_code":"ML",
    "gn:dem":256,
    "gn:feature_class":"P",
    "gn:feature_code":"PPL",
    "gn:name":"Para",
    "gn:population":0,
    "gn:timezone":"Africa/Bamako",
    "iso:country":"ML",
    "wof:name":"Para",
    "wof:placetype":"locality"
},
  "geometry": {"coordinates":[-3.4437,13.4201],"type":"Point"}
}