{
  "type": "Feature",
  "properties": {
    "gn:admin1_code":"06",
    "gn:asciiname":"Zoumayere",
    "gn:country_code":"ML",
    "gn:dem":333,
    "gn:feature_class":"P",
    "gn:feature_code":"PPL",
    "gn:name":"Zoumay\u00e9r\u00e9",
    "gn:population":0,
    "gn:timezone":"Africa/Bamako",
    "iso:country":"ML",
    "wof:name":"Zoumayere",
    "wof:placetype":"locality"
},
  "geometry": {"coordinates":[-5.54824,11.50089],"type":"Point"}
}