{
  "type": "Feature",
  "properties": {
    "gn:admin1_code":"3.0",
    "gn:asciiname":"Siramadji",
    "gn:country_code":"ML",
    "gn:dem":343,
    "gn:feature_class":"P",
    "gn:feature_code":"PPL",
    "gn:name":"Siramadji",
    "gn:population":0,
    "gn:timezone":"Africa/Bamako",
    "iso:country":"ML",
    "wof:name":"Siramadji",
    "wof:placetype":"locality"
},
  "geometry": {"coordinates":[-9.0263,13.3017],"type":"Point"}
}