{
  "type": "Feature",
  "properties": {
    "gn:admin1_code":"07",
    "gn:asciiname":"Niandjila",
    "gn:country_code":"ML",
    "gn:dem":350,
    "gn:feature_class":"P",
    "gn:feature_code":"PPL",
    "gn:name":"Niandjila",
    "gn:population":0,
    "gn:timezone":"Africa/Bamako",
    "iso:country":"ML",
    "name:fin_x_preferred":[
        "Niantjila"
    ],
    "name:fra_x_preferred":[
        "Niendjila"
    ],
    "name:fra_x_variant":[
        "Niantjila"
    ],
    "name:ita_x_preferred":[
        "Niantjila"
    ],
    "name:nld_x_preferred":[
        "Niantjila"
    ],
    "name:spa_x_preferred":[
        "Niantjila"
    ],
    "name:zho_x_preferred":[
        "\u5c3c\u5b89\u7279\u5409\u62c9"
    ],
    "wof:name":"Niandjila",
    "wof:placetype":"locality"
},
  "geometry": {"coordinates":[-6.54915,11.79772],"type":"Point"}
}