{
  "type": "Feature",
  "properties": {
    "gn:admin1_code":"5.0",
    "gn:asciiname":"Djinebougou",
    "gn:country_code":"ML",
    "gn:dem":285,
    "gn:feature_class":"P",
    "gn:feature_code":"PPL",
    "gn:name":"Djin\u00e8bougou",
    "gn:population":0,
    "gn:timezone":"Africa/Bamako",
    "iso:country":"ML",
    "wof:name":"Djinebougou",
    "wof:placetype":"locality"
},
  "geometry": {"coordinates":[-6.3075,13.1432],"type":"Point"}
}