{
  "type": "Feature",
  "properties": {
    "gn:admin1_code":"3.0",
    "gn:asciiname":"Tourinnguide",
    "gn:country_code":"ML",
    "gn:dem":321,
    "gn:feature_class":"P",
    "gn:feature_code":"PPL",
    "gn:name":"Tourinnguid\u00e9",
    "gn:population":0,
    "gn:timezone":"Africa/Bamako",
    "iso:country":"ML",
    "wof:name":"Tourinnguide",
    "wof:placetype":"locality"
},
  "geometry": {"coordinates":[-10.1923,14.3599],"type":"Point"}
}