{
  "type": "Feature",
  "properties": {
    "gn:admin1_code":"03",
    "gn:asciiname":"Dulokou",
    "gn:country_code":"ML",
    "gn:dem":222,
    "gn:feature_class":"P",
    "gn:feature_code":"PPL",
    "gn:name":"Dulokou",
    "gn:population":0,
    "gn:timezone":"Africa/Bamako",
    "iso:country":"ML",
    "wof:name":"Dulokou",
    "wof:placetype":"locality"
},
  "geometry": {"coordinates":[-10.6889,14.0244],"type":"Point"}
}