{
  "type": "Feature",
  "properties": {
    "gn:admin1_code":"4.0",
    "gn:asciiname":"Boure",
    "gn:country_code":"ML",
    "gn:dem":255,
    "gn:feature_class":"P",
    "gn:feature_code":"PPL",
    "gn:name":"Bour\u00e9",
    "gn:population":0,
    "gn:timezone":"Africa/Bamako",
    "iso:country":"ML",
    "wof:name":"Boure",
    "wof:placetype":"locality"
},
  "geometry": {"coordinates":[-3.3282,13.7494],"type":"Point"}
}