{
  "type": "Feature",
  "properties": {
    "gn:admin1_code":"06",
    "gn:asciiname":"Lanpasso",
    "gn:country_code":"ML",
    "gn:dem":297,
    "gn:feature_class":"P",
    "gn:feature_code":"PPL",
    "gn:name":"Lanpasso",
    "gn:population":0,
    "gn:timezone":"Africa/Bamako",
    "iso:country":"ML",
    "name:und_x_variant":[
        "Lampasso",
        "Lanpasso"
    ],
    "wof:name":"Lanpasso",
    "wof:placetype":"locality"
},
  "geometry": {"coordinates":[-5.76742,12.16643],"type":"Point"}
}