{
  "type": "Feature",
  "properties": {
    "gn:admin1_code":"03",
    "gn:asciiname":"Salabougou",
    "gn:country_code":"ML",
    "gn:dem":61,
    "gn:feature_class":"P",
    "gn:feature_code":"PPL",
    "gn:name":"Salabougou",
    "gn:population":0,
    "gn:timezone":"Africa/Bamako",
    "iso:country":"ML",
    "wof:name":"Salabougou",
    "wof:placetype":"locality"
},
  "geometry": {"coordinates":[-11.51436,14.39814],"type":"Point"}
}