{
  "type": "Feature",
  "properties": {
    "gn:admin1_code":"03",
    "gn:asciiname":"Daloma",
    "gn:country_code":"ML",
    "gn:dem":118,
    "gn:feature_class":"P",
    "gn:feature_code":"PPL",
    "gn:name":"Daloma",
    "gn:population":0,
    "gn:timezone":"Africa/Bamako",
    "iso:country":"ML",
    "wof:name":"Daloma",
    "wof:placetype":"locality"
},
  "geometry": {"coordinates":[-10.7432,13.5448],"type":"Point"}
}