{
  "type": "Feature",
  "properties": {
    "gn:admin1_code":"07",
    "gn:asciiname":"Songoria",
    "gn:country_code":"ML",
    "gn:dem":353,
    "gn:feature_class":"P",
    "gn:feature_code":"PPL",
    "gn:name":"Songoria",
    "gn:population":0,
    "gn:timezone":"Africa/Bamako",
    "iso:country":"ML",
    "wof:name":"Songoria",
    "wof:placetype":"locality"
},
  "geometry": {"coordinates":[-8.08477,12.21419],"type":"Point"}
}