{
  "type": "Feature",
  "properties": {
    "gn:admin1_code":"5.0",
    "gn:asciiname":"Blanbougou",
    "gn:country_code":"ML",
    "gn:dem":282,
    "gn:feature_class":"P",
    "gn:feature_code":"PPL",
    "gn:name":"Blanbougou",
    "gn:population":0,
    "gn:timezone":"Africa/Bamako",
    "iso:country":"ML",
    "wof:name":"Blanbougou",
    "wof:placetype":"locality"
},
  "geometry": {"coordinates":[-4.263,13.7675],"type":"Point"}
}