{
  "type": "Feature",
  "properties": {
    "gn:admin1_code":"6.0",
    "gn:asciiname":"Kokouna",
    "gn:country_code":"ML",
    "gn:dem":364,
    "gn:feature_class":"P",
    "gn:feature_code":"PPL",
    "gn:name":"Kokouna",
    "gn:population":0,
    "gn:timezone":"Africa/Bamako",
    "iso:country":"ML",
    "wof:name":"Kokouna",
    "wof:placetype":"locality"
},
  "geometry": {"coordinates":[-7.01477,11.5815],"type":"Point"}
}