{
  "type": "Feature",
  "properties": {
    "gn:admin1_code":"03",
    "gn:asciiname":"Konokourou",
    "gn:country_code":"ML",
    "gn:dem":258,
    "gn:feature_class":"P",
    "gn:feature_code":"PPL",
    "gn:name":"Konokourou",
    "gn:population":0,
    "gn:timezone":"Africa/Bamako",
    "iso:country":"ML",
    "wof:name":"Konokourou",
    "wof:placetype":"locality"
},
  "geometry": {"coordinates":[-9.7066,14.0323],"type":"Point"}
}