{
  "type": "Feature",
  "properties": {
    "gn:admin1_code":"05",
    "gn:asciiname":"Segoukoro",
    "gn:country_code":"ML",
    "gn:dem":294,
    "gn:feature_class":"P",
    "gn:feature_code":"PPL",
    "gn:name":"S\u00e9goukoro",
    "gn:population":0,
    "gn:timezone":"Africa/Bamako",
    "iso:country":"ML",
    "name:und_x_variant":[
        "Siekoro",
        "S\u00e9goukoro"
    ],
    "wof:name":"Segoukoro",
    "wof:placetype":"locality"
},
  "geometry": {"coordinates":[-6.3494,13.3972],"type":"Point"}
}