{
  "type": "Feature",
  "properties": {
    "gn:admin1_code":"04",
    "gn:asciiname":"Saale",
    "gn:country_code":"ML",
    "gn:dem":265,
    "gn:feature_class":"P",
    "gn:feature_code":"PPL",
    "gn:name":"Saal\u00e9",
    "gn:population":0,
    "gn:timezone":"Africa/Bamako",
    "iso:country":"ML",
    "name:afr_x_preferred":[
        "Saale"
    ],
    "name:ara_x_preferred":[
        "\u0632\u0627\u0644\u0647"
    ],
    "name:arg_x_preferred":[
        "R\u00edo Saale"
    ],
    "name:azb_x_preferred":[
        "\u0632\u0627\u0644\u0647 \u0686\u0627\u06cc\u06cc"
    ],
    "name:bel_x_preferred":[
        "\u0417\u0430\u0430\u043b\u0435"
    ],
    "name:bre_x_preferred":[
        "Saale"
    ],
    "name:bul_x_preferred":[
        "\u0417\u0430\u043b\u0435"
    ],
    "name:cat_x_preferred":[
        "Saale"
    ],
    "name:ces_x_preferred":[
        "S\u00e1la"
    ],
    "name:chv_x_preferred":[
        "\u0417\u0430\u043b\u0435"
    ],
    "name:dan_x_preferred":[
        "Saale"
    ],
    "name:deu_x_preferred":[
        "Saale"
    ],
    "name:dsb_x_preferred":[
        "Solawa"
    ],
    "name:epo_x_preferred":[
        "Saale"
    ],
    "name:est_x_preferred":[
        "Saale"
    ],
    "name:eus_x_preferred":[
        "Saale"
    ],
    "name:fas_x_preferred":[
        "\u0632\u0627\u0644\u0647"
    ],
    "name:fin_x_preferred":[
        "Saale"
    ],
    "name:fra_x_preferred":[
        "Saale"
    ],
    "name:fry_x_preferred":[
        "Saale"
    ],
    "name:gle_x_preferred":[
        "An tSaale"
    ],
    "name:hsb_x_preferred":[
        "Solawa"
    ],
    "name:hye_x_preferred":[
        "\u0536\u0561\u056c\u0565"
    ],
    "name:ina_x_preferred":[
        "Saale"
    ],
    "name:ita_x_preferred":[
        "Saale"
    ],
    "name:jpn_x_preferred":[
        "\u30b6\u30fc\u30ec\u5ddd"
    ],
    "name:kor_x_preferred":[
        "\uc798\ub808\uac15"
    ],
    "name:lat_x_preferred":[
        "Sala"
    ],
    "name:lav_x_preferred":[
        "Z\u0101le"
    ],
    "name:lit_x_preferred":[
        "Zal\u0117"
    ],
    "name:mkd_x_preferred":[
        "\u0417\u0430\u043b\u0435"
    ],
    "name:nld_x_preferred":[
        "Saale"
    ],
    "name:nno_x_preferred":[
        "Saale"
    ],
    "name:nor_x_preferred":[
        "Saale"
    ],
    "name:pol_x_preferred":[
        "So\u0142awa"
    ],
    "name:por_x_preferred":[
        "Rio Saale"
    ],
    "name:ron_x_preferred":[
        "Saale"
    ],
    "name:rus_x_preferred":[
        "\u0417\u0430\u043b\u0435"
    ],
    "name:sco_x_preferred":[
        "Saale"
    ],
    "name:slk_x_preferred":[
        "S\u00e1la"
    ],
    "name:spa_x_preferred":[
        "Saale"
    ],
    "name:sqi_x_preferred":[
        "Lumi Saale"
    ],
    "name:srp_x_preferred":[
        "\u0417\u0430\u043b\u0435"
    ],
    "name:swe_x_preferred":[
        "Saale"
    ],
    "name:ukr_x_preferred":[
        "\u0417\u0430\u0430\u043b\u0435"
    ],
    "name:vie_x_preferred":[
        "S\u00f4ng Saale"
    ],
    "name:zho_x_preferred":[
        "\u85a9\u52d2\u6cb3"
    ],
    "wof:name":"Saale",
    "wof:placetype":"locality"
},
  "geometry": {"coordinates":[-3.3307,13.9359],"type":"Point"}
}