{
  "type": "Feature",
  "properties": {
    "gn:admin1_code":"04",
    "gn:asciiname":"Saale",
    "gn:country_code":"ML",
    "gn:dem":265,
    "gn:feature_class":"P",
    "gn:feature_code":"PPL",
    "gn:name":"Saal\u00e9",
    "gn:population":0,
    "gn:timezone":"Africa/Bamako",
    "iso:country":"ML",
    "wof:name":"Saale",
    "wof:placetype":"locality"
},
  "geometry": {"coordinates":[-3.3307,13.9359],"type":"Point"}
}