{
  "type": "Feature",
  "properties": {
    "gn:admin1_code":"04",
    "gn:asciiname":"Karakinde",
    "gn:country_code":"ML",
    "gn:dem":272,
    "gn:feature_class":"P",
    "gn:feature_code":"PPL",
    "gn:name":"Karakind\u00e9",
    "gn:population":0,
    "gn:timezone":"Africa/Bamako",
    "iso:country":"ML",
    "name:und_x_variant":[
        "Karakindj\u00e9",
        "Karakind\u00e9"
    ],
    "wof:name":"Karakinde",
    "wof:placetype":"locality"
},
  "geometry": {"coordinates":[-2.90506,14.41107],"type":"Point"}
}