{
  "type": "Feature",
  "properties": {
    "gn:admin1_code":"7.0",
    "gn:asciiname":"Djirimassigui",
    "gn:country_code":"ML",
    "gn:dem":353,
    "gn:feature_class":"P",
    "gn:feature_code":"PPL",
    "gn:name":"Djirimassigui",
    "gn:population":0,
    "gn:timezone":"Africa/Bamako",
    "iso:country":"ML",
    "wof:name":"Djirimassigui",
    "wof:placetype":"locality"
},
  "geometry": {"coordinates":[-7.18206,12.79049],"type":"Point"}
}