{
  "type": "Feature",
  "properties": {
    "gn:admin1_code":"4.0",
    "gn:asciiname":"Saya",
    "gn:country_code":"ML",
    "gn:dem":266,
    "gn:feature_class":"P",
    "gn:feature_code":"PPL",
    "gn:name":"Saya",
    "gn:population":0,
    "gn:timezone":"Africa/Bamako",
    "iso:country":"ML",
    "name:ceb_x_preferred":[
        "Saya"
    ],
    "name:deu_x_preferred":[
        "Saya"
    ],
    "name:fra_x_preferred":[
        "Saya"
    ],
    "name:ind_x_preferred":[
        "Saya"
    ],
    "name:spa_x_preferred":[
        "Saya"
    ],
    "name:swe_x_preferred":[
        "Saya"
    ],
    "wof:name":"Saya",
    "wof:placetype":"locality"
},
  "geometry": {"coordinates":[-4.09047,14.74838],"type":"Point"}
}