{
  "type": "Feature",
  "properties": {
    "gn:admin1_code":"07",
    "gn:asciiname":"Doumba",
    "gn:country_code":"ML",
    "gn:dem":336,
    "gn:feature_class":"P",
    "gn:feature_code":"PPL",
    "gn:name":"Doumba",
    "gn:population":0,
    "gn:timezone":"Africa/Bamako",
    "iso:country":"ML",
    "name:fin_x_preferred":[
        "Doumba"
    ],
    "name:fra_x_preferred":[
        "Doumba"
    ],
    "name:ita_x_preferred":[
        "Doumba"
    ],
    "name:nld_x_preferred":[
        "Doumba"
    ],
    "name:spa_x_preferred":[
        "Doumba"
    ],
    "name:zho_x_preferred":[
        "\u6771\u5df4"
    ],
    "wof:name":"Doumba",
    "wof:placetype":"locality"
},
  "geometry": {"coordinates":[-7.61121,13.1042],"type":"Point"}
}