{
  "type": "Feature",
  "properties": {
    "gn:admin1_code":"00",
    "gn:asciiname":"Kenieba",
    "gn:country_code":"ML",
    "gn:dem":365,
    "gn:feature_class":"P",
    "gn:feature_code":"PPL",
    "gn:name":"K\u00e9ni\u00e9ba",
    "gn:population":0,
    "gn:timezone":"Africa/Bamako",
    "iso:country":"ML",
    "wof:name":"Kenieba",
    "wof:placetype":"locality"
},
  "geometry": {"coordinates":[-8.43333,11.26667],"type":"Point"}
}