{
  "type": "Feature",
  "properties": {
    "gn:admin1_code":"03",
    "gn:asciiname":"Tantoudji",
    "gn:country_code":"ML",
    "gn:dem":111,
    "gn:feature_class":"P",
    "gn:feature_code":"PPL",
    "gn:name":"Tantoudji",
    "gn:population":0,
    "gn:timezone":"Africa/Bamako",
    "iso:country":"ML",
    "wof:name":"Tantoudji",
    "wof:placetype":"locality"
},
  "geometry": {"coordinates":[-10.907,13.7254],"type":"Point"}
}