{
  "type": "Feature",
  "properties": {
    "gn:admin1_code":"3.0",
    "gn:asciiname":"Moussobani",
    "gn:country_code":"ML",
    "gn:dem":426,
    "gn:feature_class":"P",
    "gn:feature_code":"PPL",
    "gn:name":"Moussobani",
    "gn:population":0,
    "gn:timezone":"Africa/Bamako",
    "iso:country":"ML",
    "wof:name":"Moussobani",
    "wof:placetype":"locality"
},
  "geometry": {"coordinates":[-8.84323,12.96701],"type":"Point"}
}