{
  "type": "Feature",
  "properties": {
    "gn:admin1_code":"05",
    "gn:asciiname":"Mendola",
    "gn:country_code":"ML",
    "gn:dem":324,
    "gn:feature_class":"P",
    "gn:feature_code":"PPL",
    "gn:name":"Mendola",
    "gn:population":0,
    "gn:timezone":"Africa/Bamako",
    "iso:country":"ML",
    "name:und_x_variant":[
        "Mentola",
        "Mantala",
        "Mantola",
        "Mendola"
    ],
    "wof:name":"Mendola",
    "wof:placetype":"locality"
},
  "geometry": {"coordinates":[-6.91315,13.10464],"type":"Point"}
}