{
  "type": "Feature",
  "properties": {
    "gn:admin1_code":"07",
    "gn:asciiname":"Wela",
    "gn:country_code":"ML",
    "gn:dem":302,
    "gn:feature_class":"P",
    "gn:feature_code":"PPL",
    "gn:name":"W\u00e9la",
    "gn:population":0,
    "gn:timezone":"Africa/Bamako",
    "iso:country":"ML",
    "name:fra_x_preferred":[
        "Ou\u00e9la"
    ],
    "name:und_x_variant":[
        "W\u00e9la"
    ],
    "wof:name":"Wela",
    "wof:placetype":"locality"
},
  "geometry": {"coordinates":[-6.6253,12.7253],"type":"Point"}
}