{
  "type": "Feature",
  "properties": {
    "gn:admin1_code":"7.0",
    "gn:asciiname":"Beleninko",
    "gn:country_code":"ML",
    "gn:dem":401,
    "gn:feature_class":"P",
    "gn:feature_code":"PPL",
    "gn:name":"B\u00e9l\u00e9ninko",
    "gn:population":0,
    "gn:timezone":"Africa/Bamako",
    "iso:country":"ML",
    "wof:name":"Beleninko",
    "wof:placetype":"locality"
},
  "geometry": {"coordinates":[-7.88709,13.64231],"type":"Point"}
}