{
  "type": "Feature",
  "properties": {
    "gn:admin1_code":"03",
    "gn:asciiname":"Diko",
    "gn:country_code":"ML",
    "gn:dem":369,
    "gn:feature_class":"P",
    "gn:feature_code":"PPL",
    "gn:name":"Diko",
    "gn:population":0,
    "gn:timezone":"Africa/Bamako",
    "iso:country":"ML",
    "wof:name":"Diko",
    "wof:placetype":"locality"
},
  "geometry": {"coordinates":[-10.2779,14.1944],"type":"Point"}
}