{
  "type": "Feature",
  "properties": {
    "gn:admin1_code":"03",
    "gn:asciiname":"Kouka",
    "gn:country_code":"ML",
    "gn:dem":363,
    "gn:feature_class":"P",
    "gn:feature_code":"PPL",
    "gn:name":"Kouka",
    "gn:population":0,
    "gn:timezone":"Africa/Bamako",
    "iso:country":"ML",
    "name:ceb_x_preferred":[
        "Kouka"
    ],
    "name:fra_x_preferred":[
        "Kouka"
    ],
    "name:swe_x_preferred":[
        "Kouka"
    ],
    "wof:name":"Kouka",
    "wof:placetype":"locality"
},
  "geometry": {"coordinates":[-11.13334,12.74146],"type":"Point"}
}