{
  "type": "Feature",
  "properties": {
    "gn:admin1_code":"7.0",
    "gn:asciiname":"Djiguila",
    "gn:country_code":"ML",
    "gn:dem":321,
    "gn:feature_class":"P",
    "gn:feature_code":"PPL",
    "gn:name":"Djiguila",
    "gn:population":0,
    "gn:timezone":"Africa/Bamako",
    "iso:country":"ML",
    "name:fra_x_preferred":[
        "Djigila"
    ],
    "wof:name":"Djiguila",
    "wof:placetype":"locality"
},
  "geometry": {"coordinates":[-6.6906,12.1873],"type":"Point"}
}