{
  "type": "Feature",
  "properties": {
    "gn:admin1_code":"06",
    "gn:asciiname":"Niaradougou",
    "gn:country_code":"ML",
    "gn:dem":338,
    "gn:feature_class":"P",
    "gn:feature_code":"PPL",
    "gn:name":"Niaradougou",
    "gn:population":0,
    "gn:timezone":"Africa/Bamako",
    "iso:country":"ML",
    "wof:name":"Niaradougou",
    "wof:placetype":"locality"
},
  "geometry": {"coordinates":[-5.54623,11.44939],"type":"Point"}
}