{
  "type": "Feature",
  "properties": {
    "gn:admin1_code":"7.0",
    "gn:asciiname":"Bolibanabougou",
    "gn:country_code":"ML",
    "gn:dem":365,
    "gn:feature_class":"P",
    "gn:feature_code":"PPL",
    "gn:name":"Bolibanabougou",
    "gn:population":0,
    "gn:timezone":"Africa/Bamako",
    "iso:country":"ML",
    "wof:name":"Bolibanabougou",
    "wof:placetype":"locality"
},
  "geometry": {"coordinates":[-8.54893,12.77711],"type":"Point"}
}