{
  "type": "Feature",
  "properties": {
    "gn:admin1_code":"7.0",
    "gn:asciiname":"Niamassana",
    "gn:country_code":"ML",
    "gn:dem":333,
    "gn:feature_class":"P",
    "gn:feature_code":"PPL",
    "gn:name":"Niamassana",
    "gn:population":0,
    "gn:timezone":"Africa/Bamako",
    "iso:country":"ML",
    "wof:name":"Niamassana",
    "wof:placetype":"locality"
},
  "geometry": {"coordinates":[-6.96098,11.98054],"type":"Point"}
}