{
  "type": "Feature",
  "properties": {
    "gn:admin1_code":"04",
    "gn:asciiname":"Tanga",
    "gn:country_code":"ML",
    "gn:dem":569,
    "gn:feature_class":"P",
    "gn:feature_code":"PPL",
    "gn:name":"Tanga",
    "gn:population":0,
    "gn:timezone":"Africa/Bamako",
    "iso:country":"ML",
    "name:als_x_preferred":[
        "Tanga"
    ],
    "name:cat_x_preferred":[
        "Tanga"
    ],
    "name:ceb_x_preferred":[
        "Tanga"
    ],
    "name:deu_x_preferred":[
        "Tanga"
    ],
    "name:eus_x_preferred":[
        "Tanga"
    ],
    "name:fra_x_preferred":[
        "Tanga"
    ],
    "name:heb_x_preferred":[
        "\u05d8\u05e0\u05d2\u05d4"
    ],
    "name:hun_x_preferred":[
        "Tanga"
    ],
    "name:ita_x_preferred":[
        "Tanga"
    ],
    "name:nds_x_preferred":[
        "Tanga"
    ],
    "name:nld_x_preferred":[
        "Tanga"
    ],
    "name:nor_x_preferred":[
        "Tanga"
    ],
    "name:por_x_preferred":[
        "Tanga"
    ],
    "name:ron_x_preferred":[
        "Tanga"
    ],
    "name:rus_x_preferred":[
        "\u0422\u0430\u043d\u0433\u0430"
    ],
    "name:spa_x_preferred":[
        "Tanga"
    ],
    "name:srp_x_preferred":[
        "\u0422\u0430\u043d\u0433\u0430"
    ],
    "name:swa_x_preferred":[
        "Tanga"
    ],
    "name:swe_x_preferred":[
        "Tanga"
    ],
    "name:tgl_x_preferred":[
        "Tanga"
    ],
    "name:ukr_x_preferred":[
        "\u0422\u0430\u043d\u0433\u0430"
    ],
    "name:vie_x_preferred":[
        "Tanga"
    ],
    "wof:name":"Tanga",
    "wof:placetype":"locality"
},
  "geometry": {"coordinates":[-3.64539,14.809],"type":"Point"}
}