{
  "type": "Feature",
  "properties": {
    "gn:admin1_code":"03",
    "gn:asciiname":"Kakadian",
    "gn:country_code":"ML",
    "gn:dem":124,
    "gn:feature_class":"P",
    "gn:feature_code":"PPL",
    "gn:name":"Kakadian",
    "gn:population":0,
    "gn:timezone":"Africa/Bamako",
    "iso:country":"ML",
    "wof:name":"Kakadian",
    "wof:placetype":"locality"
},
  "geometry": {"coordinates":[-11.84349,13.83207],"type":"Point"}
}