{
  "type": "Feature",
  "properties": {
    "gn:admin1_code":"7.0",
    "gn:asciiname":"Kanfara-Foulala",
    "gn:country_code":"ML",
    "gn:dem":351,
    "gn:feature_class":"P",
    "gn:feature_code":"PPL",
    "gn:name":"Kanfara-Foulala",
    "gn:population":0,
    "gn:timezone":"Africa/Bamako",
    "iso:country":"ML",
    "wof:name":"Kanfara-Foulala",
    "wof:placetype":"locality"
},
  "geometry": {"coordinates":[-6.8713,12.1489],"type":"Point"}
}