{
  "type": "Feature",
  "properties": {
    "gn:admin1_code":"06",
    "gn:asciiname":"Konbere",
    "gn:country_code":"ML",
    "gn:dem":328,
    "gn:feature_class":"P",
    "gn:feature_code":"PPL",
    "gn:name":"Konb\u00e9r\u00e9",
    "gn:population":0,
    "gn:timezone":"Africa/Bamako",
    "iso:country":"ML",
    "name:und_x_variant":[
        "Koumb\u00e9ri",
        "Koumb\u00e9r\u00e9",
        "Komb\u00e9r\u00e9",
        "Konb\u00e9r\u00e9"
    ],
    "wof:name":"Konbere",
    "wof:placetype":"locality"
},
  "geometry": {"coordinates":[-5.82683,12.7495],"type":"Point"}
}