{
  "type": "Feature",
  "properties": {
    "gn:admin1_code":"6.0",
    "gn:asciiname":"Sanankoro",
    "gn:country_code":"ML",
    "gn:dem":444,
    "gn:feature_class":"P",
    "gn:feature_code":"PPL",
    "gn:name":"Sanankoro",
    "gn:population":0,
    "gn:timezone":"Africa/Bamako",
    "iso:country":"ML",
    "wof:name":"Sanankoro",
    "wof:placetype":"locality"
},
  "geometry": {"coordinates":[-5.31589,11.25083],"type":"Point"}
}