{
  "type": "Feature",
  "properties": {
    "gn:admin1_code":"05",
    "gn:asciiname":"Noubougou",
    "gn:country_code":"ML",
    "gn:dem":282,
    "gn:feature_class":"P",
    "gn:feature_code":"PPL",
    "gn:name":"Noubougou",
    "gn:population":0,
    "gn:timezone":"Africa/Bamako",
    "iso:country":"ML",
    "name:fra_x_preferred":[
        "Noubougou"
    ],
    "wof:name":"Noubougou",
    "wof:placetype":"locality"
},
  "geometry": {"coordinates":[-6.01543,14.33858],"type":"Point"}
}