{
  "type": "Feature",
  "properties": {
    "gn:admin1_code":"07",
    "gn:asciiname":"Dono",
    "gn:country_code":"ML",
    "gn:dem":424,
    "gn:feature_class":"P",
    "gn:feature_code":"PPL",
    "gn:name":"Dono",
    "gn:population":0,
    "gn:timezone":"Africa/Bamako",
    "iso:country":"ML",
    "name:und_x_variant":[
        "Douno",
        "Dono"
    ],
    "wof:name":"Dono",
    "wof:placetype":"locality"
},
  "geometry": {"coordinates":[-7.90875,13.80735],"type":"Point"}
}