{
  "type": "Feature",
  "properties": {
    "gn:admin1_code":"07",
    "gn:asciiname":"Niamina",
    "gn:country_code":"ML",
    "gn:dem":294,
    "gn:feature_class":"P",
    "gn:feature_code":"PPL",
    "gn:name":"Niamina",
    "gn:population":0,
    "gn:timezone":"Africa/Bamako",
    "iso:country":"ML",
    "name:und_x_variant":[
        "Niaming",
        "Nyamina",
        "Niamina"
    ],
    "wof:name":"Niamina",
    "wof:placetype":"locality"
},
  "geometry": {"coordinates":[-6.983,13.3131],"type":"Point"}
}