{
  "type": "Feature",
  "properties": {
    "gn:admin1_code":"03",
    "gn:asciiname":"Dougouibarakaia",
    "gn:country_code":"ML",
    "gn:dem":397,
    "gn:feature_class":"P",
    "gn:feature_code":"PPL",
    "gn:name":"Dougouibaraka\u00efa",
    "gn:population":0,
    "gn:timezone":"Africa/Bamako",
    "iso:country":"ML",
    "name:fra_x_preferred":[
        "Dougouibarakaya"
    ],
    "name:und_x_variant":[
        "Dougouibaraka\u00efa",
        "Dougouibarakaya"
    ],
    "wof:name":"Dougouibarakaia",
    "wof:placetype":"locality"
},
  "geometry": {"coordinates":[-8.8571,13.2607],"type":"Point"}
}