{
  "type": "Feature",
  "properties": {
    "gn:admin1_code":"07",
    "gn:asciiname":"Zouargo",
    "gn:country_code":"ML",
    "gn:dem":277,
    "gn:feature_class":"P",
    "gn:feature_code":"PPL",
    "gn:name":"Zouargo",
    "gn:population":0,
    "gn:timezone":"Africa/Bamako",
    "iso:country":"ML",
    "wof:name":"Zouargo",
    "wof:placetype":"locality"
},
  "geometry": {"coordinates":[-6.88077,15.40136],"type":"Point"}
}