{
  "type": "Feature",
  "properties": {
    "gn:admin1_code":"04",
    "gn:asciiname":"Inguem",
    "gn:country_code":"ML",
    "gn:dem":269,
    "gn:feature_class":"P",
    "gn:feature_code":"PPL",
    "gn:name":"Inguem",
    "gn:population":0,
    "gn:timezone":"Africa/Bamako",
    "iso:country":"ML",
    "name:und_x_variant":[
        "Enguem",
        "Enghem",
        "Inguem"
    ],
    "wof:name":"Inguem",
    "wof:placetype":"locality"
},
  "geometry": {"coordinates":[-4.2871,15.4792],"type":"Point"}
}