{
  "type": "Feature",
  "properties": {
    "gn:admin1_code":"7.0",
    "gn:asciiname":"Bouadiougoubougou",
    "gn:country_code":"ML",
    "gn:dem":420,
    "gn:feature_class":"P",
    "gn:feature_code":"PPL",
    "gn:name":"Bouadiougoubougou",
    "gn:population":0,
    "gn:timezone":"Africa/Bamako",
    "iso:country":"ML",
    "wof:name":"Bouadiougoubougou",
    "wof:placetype":"locality"
},
  "geometry": {"coordinates":[-8.18611,12.98945],"type":"Point"}
}