{
  "type": "Feature",
  "properties": {
    "gn:admin1_code":"05",
    "gn:asciiname":"Sele",
    "gn:country_code":"ML",
    "gn:dem":278,
    "gn:feature_class":"P",
    "gn:feature_code":"PPL",
    "gn:name":"S\u00e9l\u00e9",
    "gn:population":0,
    "gn:timezone":"Africa/Bamako",
    "iso:country":"ML",
    "name:bos_x_preferred":[
        "Sele"
    ],
    "name:ceb_x_preferred":[
        "Sele"
    ],
    "name:dan_x_preferred":[
        "Sele"
    ],
    "name:deu_x_preferred":[
        "Sele"
    ],
    "name:hrv_x_preferred":[
        "Sele"
    ],
    "name:nld_x_preferred":[
        "Sele"
    ],
    "name:nor_x_preferred":[
        "Sele"
    ],
    "name:pms_x_preferred":[
        "Sele"
    ],
    "name:pol_x_preferred":[
        "Sele"
    ],
    "name:rus_x_preferred":[
        "\u0421\u0435\u043b\u0435"
    ],
    "name:slv_x_preferred":[
        "Sele"
    ],
    "name:srp_x_preferred":[
        "\u0421\u0435\u043b\u0435"
    ],
    "name:swe_x_preferred":[
        "Sele"
    ],
    "wof:name":"Sele",
    "wof:placetype":"locality"
},
  "geometry": {"coordinates":[-5.21707,13.69713],"type":"Point"}
}