{
  "type": "Feature",
  "properties": {
    "gn:admin1_code":"03",
    "gn:asciiname":"Keniefe",
    "gn:country_code":"ML",
    "gn:dem":259,
    "gn:feature_class":"P",
    "gn:feature_code":"PPL",
    "gn:name":"K\u00e9ni\u00e9f\u00e9",
    "gn:population":0,
    "gn:timezone":"Africa/Bamako",
    "iso:country":"ML",
    "wof:name":"Keniefe",
    "wof:placetype":"locality"
},
  "geometry": {"coordinates":[-10.6234,14.1077],"type":"Point"}
}