{
  "type": "Feature",
  "properties": {
    "gn:admin1_code":"00",
    "gn:asciiname":"Nemerandi",
    "gn:country_code":"ML",
    "gn:dem":325,
    "gn:feature_class":"P",
    "gn:feature_code":"PPL",
    "gn:name":"N\u00e9m\u00e9randi",
    "gn:population":0,
    "gn:timezone":"Africa/Bamako",
    "iso:country":"ML",
    "wof:name":"Nemerandi",
    "wof:placetype":"locality"
},
  "geometry": {"coordinates":[-9.63333,13.01667],"type":"Point"}
}