{
  "type": "Feature",
  "properties": {
    "gn:admin1_code":"4.0",
    "gn:asciiname":"Damakana",
    "gn:country_code":"ML",
    "gn:dem":309,
    "gn:feature_class":"P",
    "gn:feature_code":"PPL",
    "gn:name":"Damakana",
    "gn:population":0,
    "gn:timezone":"Africa/Bamako",
    "iso:country":"ML",
    "wof:name":"Damakana",
    "wof:placetype":"locality"
},
  "geometry": {"coordinates":[-3.6668,14.0093],"type":"Point"}
}