{
  "type": "Feature",
  "properties": {
    "gn:admin1_code":"00",
    "gn:asciiname":"Djirikoro",
    "gn:country_code":"ML",
    "gn:dem":338,
    "gn:feature_class":"P",
    "gn:feature_code":"PPL",
    "gn:name":"Djirikoro",
    "gn:population":0,
    "gn:timezone":"Africa/Bamako",
    "iso:country":"ML",
    "wof:name":"Djirikoro",
    "wof:placetype":"locality"
},
  "geometry": {"coordinates":[-9.26667,12.68333],"type":"Point"}
}