{
  "type": "Feature",
  "properties": {
    "gn:admin1_code":"00",
    "gn:asciiname":"Gakouroukoto",
    "gn:country_code":"ML",
    "gn:dem":382,
    "gn:feature_class":"P",
    "gn:feature_code":"PPL",
    "gn:name":"Gakouroukoto",
    "gn:population":0,
    "gn:timezone":"Africa/Bamako",
    "iso:country":"ML",
    "wof:name":"Gakouroukoto",
    "wof:placetype":"locality"
},
  "geometry": {"coordinates":[-9.76667,12.66667],"type":"Point"}
}