{
  "type": "Feature",
  "properties": {
    "gn:admin1_code":"5.0",
    "gn:asciiname":"Tanbana",
    "gn:country_code":"ML",
    "gn:dem":287,
    "gn:feature_class":"P",
    "gn:feature_code":"PPL",
    "gn:name":"Tanbana",
    "gn:population":0,
    "gn:timezone":"Africa/Bamako",
    "iso:country":"ML",
    "wof:name":"Tanbana",
    "wof:placetype":"locality"
},
  "geometry": {"coordinates":[-5.88779,13.89737],"type":"Point"}
}