{
  "type": "Feature",
  "properties": {
    "gn:admin1_code":"5.0",
    "gn:asciiname":"Bougounina",
    "gn:country_code":"ML",
    "gn:dem":301,
    "gn:feature_class":"P",
    "gn:feature_code":"PPL",
    "gn:name":"Bougounina",
    "gn:population":0,
    "gn:timezone":"Africa/Bamako",
    "iso:country":"ML",
    "wof:name":"Bougounina",
    "wof:placetype":"locality"
},
  "geometry": {"coordinates":[-6.326,13.2621],"type":"Point"}
}