{
  "type": "Feature",
  "properties": {
    "gn:admin1_code":"3.0",
    "gn:asciiname":"Makankoro",
    "gn:country_code":"ML",
    "gn:dem":303,
    "gn:feature_class":"P",
    "gn:feature_code":"PPL",
    "gn:name":"Makankoro",
    "gn:population":0,
    "gn:timezone":"Africa/Bamako",
    "iso:country":"ML",
    "wof:name":"Makankoro",
    "wof:placetype":"locality"
},
  "geometry": {"coordinates":[-9.107,13.5187],"type":"Point"}
}