{
  "type": "Feature",
  "properties": {
    "gn:admin1_code":"07",
    "gn:asciiname":"Darsalam",
    "gn:country_code":"ML",
    "gn:dem":261,
    "gn:feature_class":"P",
    "gn:feature_code":"PPL",
    "gn:name":"Darsalam",
    "gn:population":0,
    "gn:timezone":"Africa/Bamako",
    "iso:country":"ML",
    "wof:name":"Darsalam",
    "wof:placetype":"locality"
},
  "geometry": {"coordinates":[-7.3767,14.9451],"type":"Point"}
}