{
  "type": "Feature",
  "properties": {
    "gn:admin1_code":"00",
    "gn:asciiname":"Kounbe",
    "gn:country_code":"ML",
    "gn:dem":288,
    "gn:feature_class":"P",
    "gn:feature_code":"PPL",
    "gn:name":"Kounb\u00e9",
    "gn:population":0,
    "gn:timezone":"Africa/Bamako",
    "iso:country":"ML",
    "wof:name":"Kounbe",
    "wof:placetype":"locality"
},
  "geometry": {"coordinates":[-9.75,13.15],"type":"Point"}
}