{
  "type": "Feature",
  "properties": {
    "gn:admin1_code":"4.0",
    "gn:asciiname":"Djinassogou",
    "gn:country_code":"ML",
    "gn:dem":362,
    "gn:feature_class":"P",
    "gn:feature_code":"PPL",
    "gn:name":"Djinassogou",
    "gn:population":0,
    "gn:timezone":"Africa/Bamako",
    "iso:country":"ML",
    "wof:name":"Djinassogou",
    "wof:placetype":"locality"
},
  "geometry": {"coordinates":[-3.8087,13.6914],"type":"Point"}
}