{
  "type": "Feature",
  "properties": {
    "gn:admin1_code":"05",
    "gn:asciiname":"Dongonion",
    "gn:country_code":"ML",
    "gn:dem":293,
    "gn:feature_class":"P",
    "gn:feature_code":"PPL",
    "gn:name":"Dongonion",
    "gn:population":0,
    "gn:timezone":"Africa/Bamako",
    "iso:country":"ML",
    "wof:name":"Dongonion",
    "wof:placetype":"locality"
},
  "geometry": {"coordinates":[-7.0442,13.2279],"type":"Point"}
}