{
  "type": "Feature",
  "properties": {
    "gn:admin1_code":"03",
    "gn:asciiname":"Taraoule",
    "gn:country_code":"ML",
    "gn:dem":314,
    "gn:feature_class":"P",
    "gn:feature_code":"PPL",
    "gn:name":"Taraoul\u00e9",
    "gn:population":0,
    "gn:timezone":"Africa/Bamako",
    "iso:country":"ML",
    "wof:name":"Taraoule",
    "wof:placetype":"locality"
},
  "geometry": {"coordinates":[-10.3477,14.0014],"type":"Point"}
}