{
  "type": "Feature",
  "properties": {
    "gn:admin1_code":"7.0",
    "gn:asciiname":"Monsombougou",
    "gn:country_code":"ML",
    "gn:dem":443,
    "gn:feature_class":"P",
    "gn:feature_code":"PPL",
    "gn:name":"Monsombougou",
    "gn:population":0,
    "gn:timezone":"Africa/Bamako",
    "iso:country":"ML",
    "wof:name":"Monsombougou",
    "wof:placetype":"locality"
},
  "geometry": {"coordinates":[-7.92286,13.7741],"type":"Point"}
}