{
  "type": "Feature",
  "properties": {
    "gn:admin1_code":"04",
    "gn:asciiname":"Diabi",
    "gn:country_code":"ML",
    "gn:dem":264,
    "gn:feature_class":"P",
    "gn:feature_code":"PPL",
    "gn:name":"Diabi",
    "gn:population":0,
    "gn:timezone":"Africa/Bamako",
    "iso:country":"ML",
    "wof:name":"Diabi",
    "wof:placetype":"locality"
},
  "geometry": {"coordinates":[-4.13319,14.43749],"type":"Point"}
}