{
  "type": "Feature",
  "properties": {
    "gn:admin1_code":"07",
    "gn:asciiname":"Tombo",
    "gn:country_code":"ML",
    "gn:dem":340,
    "gn:feature_class":"P",
    "gn:feature_code":"PPL",
    "gn:name":"Tombo",
    "gn:population":0,
    "gn:timezone":"Africa/Bamako",
    "iso:country":"ML",
    "wof:name":"Tombo",
    "wof:placetype":"locality"
},
  "geometry": {"coordinates":[-7.28333,12.68333],"type":"Point"}
}