{
  "type": "Feature",
  "properties": {
    "gn:admin1_code":"07",
    "gn:asciiname":"Tombo",
    "gn:country_code":"ML",
    "gn:dem":340,
    "gn:feature_class":"P",
    "gn:feature_code":"PPL",
    "gn:name":"Tombo",
    "gn:population":0,
    "gn:timezone":"Africa/Bamako",
    "iso:country":"ML",
    "name:ceb_x_preferred":[
        "Tombo"
    ],
    "name:deu_x_preferred":[
        "Tombo"
    ],
    "name:glg_x_preferred":[
        "Tombo"
    ],
    "name:rus_x_preferred":[
        "\u0422\u043e\u043c\u0431\u043e"
    ],
    "name:spa_x_preferred":[
        "Tombo"
    ],
    "name:swe_x_preferred":[
        "Tombo"
    ],
    "name:ukr_x_preferred":[
        "\u0422\u043e\u043c\u0431\u043e"
    ],
    "wof:name":"Tombo",
    "wof:placetype":"locality"
},
  "geometry": {"coordinates":[-7.28333,12.68333],"type":"Point"}
}