{
  "type": "Feature",
  "properties": {
    "gn:admin1_code":"7.0",
    "gn:asciiname":"Mamarela",
    "gn:country_code":"ML",
    "gn:dem":408,
    "gn:feature_class":"P",
    "gn:feature_code":"PPL",
    "gn:name":"Mamar\u00e9la",
    "gn:population":0,
    "gn:timezone":"Africa/Bamako",
    "iso:country":"ML",
    "wof:name":"Mamarela",
    "wof:placetype":"locality"
},
  "geometry": {"coordinates":[-7.54201,13.42786],"type":"Point"}
}