{
  "type": "Feature",
  "properties": {
    "gn:admin1_code":"06",
    "gn:asciiname":"Diassola",
    "gn:country_code":"ML",
    "gn:dem":332,
    "gn:feature_class":"P",
    "gn:feature_code":"PPL",
    "gn:name":"Diassola",
    "gn:population":0,
    "gn:timezone":"Africa/Bamako",
    "iso:country":"ML",
    "wof:name":"Diassola",
    "wof:placetype":"locality"
},
  "geometry": {"coordinates":[-7.06104,11.89984],"type":"Point"}
}