{
  "type": "Feature",
  "properties": {
    "gn:admin1_code":"00",
    "gn:asciiname":"Sekorodi",
    "gn:country_code":"ML",
    "gn:dem":312,
    "gn:feature_class":"P",
    "gn:feature_code":"PPL",
    "gn:name":"S\u00e9korodi",
    "gn:population":0,
    "gn:timezone":"Africa/Bamako",
    "iso:country":"ML",
    "wof:name":"Sekorodi",
    "wof:placetype":"locality"
},
  "geometry": {"coordinates":[-9.83333,12.93333],"type":"Point"}
}