{
  "type": "Feature",
  "properties": {
    "gn:admin1_code":"06",
    "gn:asciiname":"Mpelasso",
    "gn:country_code":"ML",
    "gn:dem":469,
    "gn:feature_class":"P",
    "gn:feature_code":"PPL",
    "gn:name":"Mp\u00e9lasso",
    "gn:population":0,
    "gn:timezone":"Africa/Bamako",
    "iso:country":"ML",
    "wof:name":"Mpelasso",
    "wof:placetype":"locality"
},
  "geometry": {"coordinates":[-5.86705,11.10871],"type":"Point"}
}