{
  "type": "Feature",
  "properties": {
    "gn:admin1_code":"08",
    "gn:asciiname":"Guezou-Haoussa",
    "gn:country_code":"ML",
    "gn:dem":259,
    "gn:feature_class":"P",
    "gn:feature_code":"PPL",
    "gn:name":"Gu\u00e9zou-Haoussa",
    "gn:population":0,
    "gn:timezone":"Africa/Bamako",
    "iso:country":"ML",
    "wof:name":"Guezou-Haoussa",
    "wof:placetype":"locality"
},
  "geometry": {"coordinates":[-3.51704,16.15477000000001],"type":"Point"}
}