{
  "type": "Feature",
  "properties": {
    "gn:admin1_code":"03",
    "gn:asciiname":"Kourougue",
    "gn:country_code":"ML",
    "gn:dem":298,
    "gn:feature_class":"P",
    "gn:feature_code":"PPL",
    "gn:name":"Kourougu\u00e8",
    "gn:population":0,
    "gn:timezone":"Africa/Bamako",
    "iso:country":"ML",
    "wof:name":"Kourougue",
    "wof:placetype":"locality"
},
  "geometry": {"coordinates":[-9.60717,13.28947],"type":"Point"}
}