{
  "type": "Feature",
  "properties": {
    "gn:admin1_code":"03",
    "gn:asciiname":"Dabai Amate",
    "gn:country_code":"ML",
    "gn:dem":217,
    "gn:feature_class":"P",
    "gn:feature_code":"PPL",
    "gn:name":"Daba\u00ef Amate",
    "gn:population":0,
    "gn:timezone":"Africa/Bamako",
    "iso:country":"ML",
    "wof:name":"Dabai Amate",
    "wof:placetype":"locality"
},
  "geometry": {"coordinates":[-9.33984,15.64042],"type":"Point"}
}