{
  "type": "Feature",
  "properties": {
    "gn:admin1_code":"6.0",
    "gn:asciiname":"Kalifabougou",
    "gn:country_code":"ML",
    "gn:dem":323,
    "gn:feature_class":"P",
    "gn:feature_code":"PPL",
    "gn:name":"Kalifabougou",
    "gn:population":0,
    "gn:timezone":"Africa/Bamako",
    "iso:country":"ML",
    "wof:name":"Kalifabougou",
    "wof:placetype":"locality"
},
  "geometry": {"coordinates":[-6.2346,11.27748],"type":"Point"}
}