{
  "type": "Feature",
  "properties": {
    "gn:admin1_code":"6.0",
    "gn:asciiname":"Kalifabougou",
    "gn:country_code":"ML",
    "gn:dem":323,
    "gn:feature_class":"P",
    "gn:feature_code":"PPL",
    "gn:name":"Kalifabougou",
    "gn:population":0,
    "gn:timezone":"Africa/Bamako",
    "iso:country":"ML",
    "name:fin_x_preferred":[
        "Kalifabougou"
    ],
    "name:fra_x_preferred":[
        "Kalifabougou"
    ],
    "name:ita_x_preferred":[
        "Kalifabougou"
    ],
    "name:nld_x_preferred":[
        "Kalifabougou"
    ],
    "name:spa_x_preferred":[
        "Kalifabougou"
    ],
    "name:zho_x_preferred":[
        "\u5361\u5229\u6cd5\u5e03\u53e4"
    ],
    "wof:name":"Kalifabougou",
    "wof:placetype":"locality"
},
  "geometry": {"coordinates":[-6.2346,11.27748],"type":"Point"}
}