{
  "type": "Feature",
  "properties": {
    "gn:admin1_code":"7.0",
    "gn:asciiname":"Ntenefekabougou",
    "gn:country_code":"ML",
    "gn:dem":346,
    "gn:feature_class":"P",
    "gn:feature_code":"PPL",
    "gn:name":"Nt\u00e8n\u00e8f\u00e8kabougou",
    "gn:population":0,
    "gn:timezone":"Africa/Bamako",
    "iso:country":"ML",
    "wof:name":"Ntenefekabougou",
    "wof:placetype":"locality"
},
  "geometry": {"coordinates":[-7.15832,12.65486],"type":"Point"}
}