{
  "type": "Feature",
  "properties": {
    "gn:admin1_code":"06",
    "gn:asciiname":"Zantona",
    "gn:country_code":"ML",
    "gn:dem":330,
    "gn:feature_class":"P",
    "gn:feature_code":"PPL",
    "gn:name":"Zantona",
    "gn:population":0,
    "gn:timezone":"Africa/Bamako",
    "iso:country":"ML",
    "name:und_x_variant":[
        "Antona",
        "Zantoma",
        "Zantona"
    ],
    "wof:name":"Zantona",
    "wof:placetype":"locality"
},
  "geometry": {"coordinates":[-5.71861,12.50016],"type":"Point"}
}