{
  "type": "Feature",
  "properties": {
    "gn:admin1_code":"07",
    "gn:asciiname":"Warabougou",
    "gn:country_code":"ML",
    "gn:dem":329,
    "gn:feature_class":"P",
    "gn:feature_code":"PPL",
    "gn:name":"Warabougou",
    "gn:population":0,
    "gn:timezone":"Africa/Bamako",
    "iso:country":"ML",
    "name:fra_x_preferred":[
        "Warabougou"
    ],
    "name:fra_x_variant":[
        "Ouarabougou"
    ],
    "name:und_x_variant":[
        "Ouarabougou"
    ],
    "wof:name":"Warabougou",
    "wof:placetype":"locality"
},
  "geometry": {"coordinates":[-8.2755,13.4669],"type":"Point"}
}