{
  "type": "Feature",
  "properties": {
    "gn:admin1_code":"06",
    "gn:asciiname":"Djiguenesso",
    "gn:country_code":"ML",
    "gn:dem":371,
    "gn:feature_class":"P",
    "gn:feature_code":"PPL",
    "gn:name":"Djigu\u00e9n\u00e9sso",
    "gn:population":0,
    "gn:timezone":"Africa/Bamako",
    "iso:country":"ML",
    "wof:name":"Djiguenesso",
    "wof:placetype":"locality"
},
  "geometry": {"coordinates":[-6.07944,11.45299],"type":"Point"}
}