{
  "type": "Feature",
  "properties": {
    "gn:admin1_code":"00",
    "gn:asciiname":"Falea",
    "gn:country_code":"ML",
    "gn:dem":402,
    "gn:feature_class":"P",
    "gn:feature_code":"PPL",
    "gn:name":"Fal\u00e9a",
    "gn:population":0,
    "gn:timezone":"Africa/Bamako",
    "iso:country":"ML",
    "wof:name":"Falea",
    "wof:placetype":"locality"
},
  "geometry": {"coordinates":[-9.91667,12.36667],"type":"Point"}
}