{
  "type": "Feature",
  "properties": {
    "gn:admin1_code":"3.0",
    "gn:asciiname":"Sitani Soroma",
    "gn:country_code":"ML",
    "gn:dem":301,
    "gn:feature_class":"P",
    "gn:feature_code":"PPL",
    "gn:name":"Sitani Soroma",
    "gn:population":0,
    "gn:timezone":"Africa/Bamako",
    "iso:country":"ML",
    "wof:name":"Sitani Soroma",
    "wof:placetype":"locality"
},
  "geometry": {"coordinates":[-10.751,14.376],"type":"Point"}
}