{
  "type": "Feature",
  "properties": {
    "gn:admin1_code":"00",
    "gn:asciiname":"Tionkourani",
    "gn:country_code":"ML",
    "gn:dem":350,
    "gn:feature_class":"P",
    "gn:feature_code":"PPL",
    "gn:name":"Tionkourani",
    "gn:population":0,
    "gn:timezone":"Africa/Bamako",
    "iso:country":"ML",
    "wof:name":"Tionkourani",
    "wof:placetype":"locality"
},
  "geometry": {"coordinates":[-6.55,10.85],"type":"Point"}
}