{
  "type": "Feature",
  "properties": {
    "gn:admin1_code":"6.0",
    "gn:asciiname":"Katobougou",
    "gn:country_code":"ML",
    "gn:dem":418,
    "gn:feature_class":"P",
    "gn:feature_code":"PPL",
    "gn:name":"Katobougou",
    "gn:population":0,
    "gn:timezone":"Africa/Bamako",
    "iso:country":"ML",
    "name:und_x_variant":[
        "Katobogou"
    ],
    "wof:name":"Katobougou",
    "wof:placetype":"locality"
},
  "geometry": {"coordinates":[-5.88376,11.91838],"type":"Point"}
}