{
  "type": "Feature",
  "properties": {
    "gn:admin1_code":"04",
    "gn:asciiname":"Yorbou",
    "gn:country_code":"ML",
    "gn:dem":556,
    "gn:feature_class":"P",
    "gn:feature_code":"PPL",
    "gn:name":"Yorbou",
    "gn:population":0,
    "gn:timezone":"Africa/Bamako",
    "iso:country":"ML",
    "wof:name":"Yorbou",
    "wof:placetype":"locality"
},
  "geometry": {"coordinates":[-2.02961,15.10523],"type":"Point"}
}