{
  "type": "Feature",
  "properties": {
    "gn:admin1_code":"6.0",
    "gn:asciiname":"Tabakoro",
    "gn:country_code":"ML",
    "gn:dem":402,
    "gn:feature_class":"P",
    "gn:feature_code":"PPL",
    "gn:name":"Tabakoro",
    "gn:population":0,
    "gn:timezone":"Africa/Bamako",
    "iso:country":"ML",
    "wof:name":"Tabakoro",
    "wof:placetype":"locality"
},
  "geometry": {"coordinates":[-5.68438,11.2366],"type":"Point"}
}