{
  "type": "Feature",
  "properties": {
    "gn:admin1_code":"03",
    "gn:asciiname":"Segue",
    "gn:country_code":"ML",
    "gn:dem":148,
    "gn:feature_class":"P",
    "gn:feature_code":"PPL",
    "gn:name":"S\u00e9gu\u00e9",
    "gn:population":0,
    "gn:timezone":"Africa/Bamako",
    "iso:country":"ML",
    "name:fra_x_preferred":[
        "Segue"
    ],
    "name:ron_x_preferred":[
        "Segue"
    ],
    "wof:name":"Segue",
    "wof:placetype":"locality"
},
  "geometry": {"coordinates":[-11.0535,15.19431],"type":"Point"}
}