{
  "type": "Feature",
  "properties": {
    "gn:admin1_code":"7.0",
    "gn:asciiname":"Didieni",
    "gn:country_code":"ML",
    "gn:dem":395,
    "gn:feature_class":"P",
    "gn:feature_code":"PPL",
    "gn:name":"Didi\u00e9ni",
    "gn:population":0,
    "gn:timezone":"Africa/Bamako",
    "iso:country":"ML",
    "name:fin_x_preferred":[
        "Didi\u00e9ni"
    ],
    "name:fra_x_preferred":[
        "Didi\u00e9ni"
    ],
    "name:ita_x_preferred":[
        "Didi\u00e9ni"
    ],
    "name:nld_x_preferred":[
        "Didi\u00e9ni"
    ],
    "name:spa_x_preferred":[
        "Didieni"
    ],
    "wof:name":"Didieni",
    "wof:placetype":"locality"
},
  "geometry": {"coordinates":[-8.09292,13.88509],"type":"Point"}
}