{
  "type": "Feature",
  "properties": {
    "gn:admin1_code":"00",
    "gn:asciiname":"Faragangala",
    "gn:country_code":"ML",
    "gn:dem":370,
    "gn:feature_class":"P",
    "gn:feature_code":"PPL",
    "gn:name":"Faragangala",
    "gn:population":0,
    "gn:timezone":"Africa/Bamako",
    "iso:country":"ML",
    "wof:name":"Faragangala",
    "wof:placetype":"locality"
},
  "geometry": {"coordinates":[-9.08333,13.13333],"type":"Point"}
}