{
  "type": "Feature",
  "properties": {
    "gn:admin1_code":"05",
    "gn:asciiname":"Kenyie",
    "gn:country_code":"ML",
    "gn:dem":275,
    "gn:feature_class":"P",
    "gn:feature_code":"PPL",
    "gn:name":"Kenyi\u00e9",
    "gn:population":0,
    "gn:timezone":"Africa/Bamako",
    "iso:country":"ML",
    "name:und_x_variant":[
        "Keny\u00e9",
        "Kenyi\u00e9"
    ],
    "wof:name":"Kenyie",
    "wof:placetype":"locality"
},
  "geometry": {"coordinates":[-4.9934,13.6723],"type":"Point"}
}