{
  "type": "Feature",
  "properties": {
    "gn:admin1_code":"03",
    "gn:asciiname":"Lewa",
    "gn:country_code":"ML",
    "gn:dem":254,
    "gn:feature_class":"P",
    "gn:feature_code":"PPL",
    "gn:name":"L\u00e9wa",
    "gn:population":0,
    "gn:timezone":"Africa/Bamako",
    "iso:country":"ML",
    "wof:name":"Lewa",
    "wof:placetype":"locality"
},
  "geometry": {"coordinates":[-9.6036,14.7271],"type":"Point"}
}