{
  "type": "Feature",
  "properties": {
    "gn:admin1_code":"6.0",
    "gn:asciiname":"Zarabougou",
    "gn:country_code":"ML",
    "gn:dem":431,
    "gn:feature_class":"P",
    "gn:feature_code":"PPL",
    "gn:name":"Zarabougou",
    "gn:population":0,
    "gn:timezone":"Africa/Bamako",
    "iso:country":"ML",
    "wof:name":"Zarabougou",
    "wof:placetype":"locality"
},
  "geometry": {"coordinates":[-5.81286,11.17906],"type":"Point"}
}