{
  "type": "Feature",
  "properties": {
    "gn:admin1_code":"06",
    "gn:asciiname":"Yeoulasso",
    "gn:country_code":"ML",
    "gn:dem":377,
    "gn:feature_class":"P",
    "gn:feature_code":"PPL",
    "gn:name":"Y\u00e9oulasso",
    "gn:population":0,
    "gn:timezone":"Africa/Bamako",
    "iso:country":"ML",
    "name:fra_x_preferred":[
        "Y\u00e9oulasso"
    ],
    "wof:name":"Yeoulasso",
    "wof:placetype":"locality"
},
  "geometry": {"coordinates":[-6.04225,11.2388],"type":"Point"}
}