{
  "type": "Feature",
  "properties": {
    "gn:admin1_code":"5.0",
    "gn:asciiname":"Kobi",
    "gn:country_code":"ML",
    "gn:dem":290,
    "gn:feature_class":"P",
    "gn:feature_code":"PPL",
    "gn:name":"Kobi",
    "gn:population":0,
    "gn:timezone":"Africa/Bamako",
    "iso:country":"ML",
    "wof:name":"Kobi",
    "wof:placetype":"locality"
},
  "geometry": {"coordinates":[-6.41374,13.48763],"type":"Point"}
}