{
  "type": "Feature",
  "properties": {
    "gn:admin1_code":"8.0",
    "gn:asciiname":"Arkachene",
    "gn:country_code":"ML",
    "gn:dem":260,
    "gn:feature_class":"P",
    "gn:feature_code":"PPL",
    "gn:name":"Arkachene",
    "gn:population":0,
    "gn:timezone":"Africa/Bamako",
    "iso:country":"ML",
    "wof:name":"Arkachene",
    "wof:placetype":"locality"
},
  "geometry": {"coordinates":[-4.1947,16.7036],"type":"Point"}
}