{
  "type": "Feature",
  "properties": {
    "gn:admin1_code":"06",
    "gn:asciiname":"Oure",
    "gn:country_code":"ML",
    "gn:dem":344,
    "gn:feature_class":"P",
    "gn:feature_code":"PPL",
    "gn:name":"Our\u00e9",
    "gn:population":0,
    "gn:timezone":"Africa/Bamako",
    "iso:country":"ML",
    "name:und_x_variant":[
        "Dure",
        "Our\u00e9"
    ],
    "wof:name":"Oure",
    "wof:placetype":"locality"
},
  "geometry": {"coordinates":[-7.71129,11.87895],"type":"Point"}
}