{
  "type": "Feature",
  "properties": {
    "gn:admin1_code":"1.0",
    "gn:asciiname":"Ie Lido",
    "gn:country_code":"ML",
    "gn:dem":423,
    "gn:feature_class":"P",
    "gn:feature_code":"PPL",
    "gn:name":"Ie Lido",
    "gn:population":0,
    "gn:timezone":"Africa/Bamako",
    "iso:country":"ML",
    "wof:name":"Ie Lido",
    "wof:placetype":"locality"
},
  "geometry": {"coordinates":[-8.0434,12.6752],"type":"Point"}
}