{
  "type": "Feature",
  "properties": {
    "gn:admin1_code":"6.0",
    "gn:asciiname":"Koloni",
    "gn:country_code":"ML",
    "gn:dem":339,
    "gn:feature_class":"P",
    "gn:feature_code":"PPL",
    "gn:name":"Koloni",
    "gn:population":0,
    "gn:timezone":"Africa/Bamako",
    "iso:country":"ML",
    "wof:name":"Koloni",
    "wof:placetype":"locality"
},
  "geometry": {"coordinates":[-6.96332,11.0507],"type":"Point"}
}