{
  "type": "Feature",
  "properties": {
    "gn:admin1_code":"6.0",
    "gn:asciiname":"Dialanikoro",
    "gn:country_code":"ML",
    "gn:dem":384,
    "gn:feature_class":"P",
    "gn:feature_code":"PPL",
    "gn:name":"Dialanikoro",
    "gn:population":0,
    "gn:timezone":"Africa/Bamako",
    "iso:country":"ML",
    "wof:name":"Dialanikoro",
    "wof:placetype":"locality"
},
  "geometry": {"coordinates":[-7.0797,11.28602],"type":"Point"}
}