{
  "type": "Feature",
  "properties": {
    "gn:admin1_code":"5.0",
    "gn:asciiname":"Woune",
    "gn:country_code":"ML",
    "gn:dem":280,
    "gn:feature_class":"P",
    "gn:feature_code":"PPL",
    "gn:name":"Woun\u00e9",
    "gn:population":0,
    "gn:timezone":"Africa/Bamako",
    "iso:country":"ML",
    "wof:name":"Woune",
    "wof:placetype":"locality"
},
  "geometry": {"coordinates":[-4.6927,13.5221],"type":"Point"}
}