{
  "type": "Feature",
  "properties": {
    "gn:admin1_code":"00",
    "gn:asciiname":"Labanta",
    "gn:country_code":"ML",
    "gn:dem":502,
    "gn:feature_class":"P",
    "gn:feature_code":"PPL",
    "gn:name":"Labanta",
    "gn:population":0,
    "gn:timezone":"Africa/Bamako",
    "iso:country":"ML",
    "wof:name":"Labanta",
    "wof:placetype":"locality"
},
  "geometry": {"coordinates":[-10.13333,12.36667],"type":"Point"}
}