{
  "type": "Feature",
  "properties": {
    "gn:admin1_code":"7.0",
    "gn:asciiname":"Nialenko",
    "gn:country_code":"ML",
    "gn:dem":368,
    "gn:feature_class":"P",
    "gn:feature_code":"PPL",
    "gn:name":"Nial\u00e8nko",
    "gn:population":0,
    "gn:timezone":"Africa/Bamako",
    "iso:country":"ML",
    "wof:name":"Nialenko",
    "wof:placetype":"locality"
},
  "geometry": {"coordinates":[-8.41983,12.82801],"type":"Point"}
}