{
  "type": "Feature",
  "properties": {
    "gn:admin1_code":"9.0",
    "gn:asciiname":"Bobo Bera",
    "gn:country_code":"ML",
    "gn:dem":245,
    "gn:feature_class":"P",
    "gn:feature_code":"PPL",
    "gn:name":"Bobo Bera",
    "gn:population":0,
    "gn:timezone":"Africa/Bamako",
    "iso:country":"ML",
    "wof:name":"Bobo Bera",
    "wof:placetype":"locality"
},
  "geometry": {"coordinates":[0.4682,15.5655],"type":"Point"}
}