{
  "type": "Feature",
  "properties": {
    "gn:admin1_code":"08",
    "gn:asciiname":"Bougouni",
    "gn:country_code":"ML",
    "gn:dem":263,
    "gn:feature_class":"P",
    "gn:feature_code":"PPL",
    "gn:name":"Bougouni",
    "gn:population":0,
    "gn:timezone":"Africa/Bamako",
    "iso:country":"ML",
    "name:bam_x_preferred":[
        "Buguni"
    ],
    "name:ben_x_preferred":[
        "\u09ac\u09cc\u0997\u09cc\u09a8\u09bf"
    ],
    "name:cat_x_preferred":[
        "Bougouni"
    ],
    "name:ceb_x_preferred":[
        "Bougouni"
    ],
    "name:deu_x_preferred":[
        "Bougouni"
    ],
    "name:est_x_preferred":[
        "Bougouni"
    ],
    "name:fin_x_preferred":[
        "Bougouni"
    ],
    "name:fra_x_preferred":[
        "Bougouni"
    ],
    "name:heb_x_preferred":[
        "\u05d1\u05d5\u05d2\u05d5\u05e0\u05d9"
    ],
    "name:hin_x_preferred":[
        "\u092c\u0942\u0917\u093e\u0909\u0928\u0940"
    ],
    "name:hun_x_preferred":[
        "Bougouni"
    ],
    "name:ind_x_preferred":[
        "Bougouni"
    ],
    "name:ita_x_preferred":[
        "Bougouni"
    ],
    "name:kor_x_preferred":[
        "\ubd80\uace0\ub2c8"
    ],
    "name:lit_x_preferred":[
        "Bugunis"
    ],
    "name:nld_x_preferred":[
        "Bougouni"
    ],
    "name:pol_x_preferred":[
        "Bougouni"
    ],
    "name:por_x_preferred":[
        "Buguni"
    ],
    "name:rus_x_preferred":[
        "\u0411\u0443\u0433\u0443\u043d\u0438"
    ],
    "name:spa_x_preferred":[
        "Bougouni"
    ],
    "name:tur_x_preferred":[
        "Bougouni"
    ],
    "name:ukr_x_preferred":[
        "\u0411\u0443\u0433\u0443\u043d\u0456"
    ],
    "name:urd_x_preferred":[
        "\u0628\u0648\u06af\u0648\u0646\u06cc"
    ],
    "name:vie_x_preferred":[
        "Bougouni"
    ],
    "name:zho_x_preferred":[
        "\u5e03\u53e4\u5c3c"
    ],
    "wof:name":"Bougouni",
    "wof:placetype":"locality"
},
  "geometry": {"coordinates":[-2.50748,16.74103],"type":"Point"}
}