{
  "type": "Feature",
  "properties": {
    "gn:admin1_code":"08",
    "gn:asciiname":"Bougouni",
    "gn:country_code":"ML",
    "gn:dem":263,
    "gn:feature_class":"P",
    "gn:feature_code":"PPL",
    "gn:name":"Bougouni",
    "gn:population":0,
    "gn:timezone":"Africa/Bamako",
    "iso:country":"ML",
    "name:bam_x_preferred":[
        "Buguni"
    ],
    "name:cat_x_preferred":[
        "Bougouni"
    ],
    "name:ceb_x_preferred":[
        "Bougouni"
    ],
    "name:est_x_preferred":[
        "Bougouni"
    ],
    "name:fin_x_preferred":[
        "Bougouni"
    ],
    "name:fra_x_preferred":[
        "Bougouni"
    ],
    "name:hun_x_preferred":[
        "Bougouni"
    ],
    "name:ita_x_preferred":[
        "Bougouni"
    ],
    "name:lit_x_preferred":[
        "Bugunis"
    ],
    "name:nld_x_preferred":[
        "Bougouni"
    ],
    "name:pol_x_preferred":[
        "Bougouni"
    ],
    "name:por_x_preferred":[
        "Buguni"
    ],
    "name:rus_x_preferred":[
        "\u0411\u0443\u0433\u0443\u043d\u0438"
    ],
    "name:spa_x_preferred":[
        "Bougouni"
    ],
    "name:zho_x_preferred":[
        "\u5e03\u53e4\u5c3c"
    ],
    "wof:name":"Bougouni",
    "wof:placetype":"locality"
},
  "geometry": {"coordinates":[-2.50748,16.74103],"type":"Point"}
}