{
  "type": "Feature",
  "properties": {
    "gn:admin1_code":"3.0",
    "gn:asciiname":"Alahine",
    "gn:country_code":"ML",
    "gn:dem":302,
    "gn:feature_class":"P",
    "gn:feature_code":"PPL",
    "gn:name":"Alahin\u00e9",
    "gn:population":0,
    "gn:timezone":"Africa/Bamako",
    "iso:country":"ML",
    "wof:name":"Alahine",
    "wof:placetype":"locality"
},
  "geometry": {"coordinates":[-10.2293,14.6833],"type":"Point"}
}