{
  "type": "Feature",
  "properties": {
    "gn:admin1_code":"03",
    "gn:asciiname":"Manantali",
    "gn:country_code":"ML",
    "gn:dem":169,
    "gn:feature_class":"P",
    "gn:feature_code":"PPL",
    "gn:name":"Manantali",
    "gn:population":0,
    "gn:timezone":"Africa/Bamako",
    "iso:country":"ML",
    "name:deu_x_preferred":[
        "Manantali"
    ],
    "wof:name":"Manantali",
    "wof:placetype":"locality"
},
  "geometry": {"coordinates":[-10.462,13.2076],"type":"Point"}
}