{
  "type": "Feature",
  "properties": {
    "gn:admin1_code":"5.0",
    "gn:asciiname":"Kandola",
    "gn:country_code":"ML",
    "gn:dem":296,
    "gn:feature_class":"P",
    "gn:feature_code":"PPL",
    "gn:name":"Kandola",
    "gn:population":0,
    "gn:timezone":"Africa/Bamako",
    "iso:country":"ML",
    "wof:name":"Kandola",
    "wof:placetype":"locality"
},
  "geometry": {"coordinates":[-6.64949,13.69692],"type":"Point"}
}