{
  "type": "Feature",
  "properties": {
    "gn:admin1_code":"5.0",
    "gn:asciiname":"Mbiabougou",
    "gn:country_code":"ML",
    "gn:dem":282,
    "gn:feature_class":"P",
    "gn:feature_code":"PPL",
    "gn:name":"Mbiabougou",
    "gn:population":0,
    "gn:timezone":"Africa/Bamako",
    "iso:country":"ML",
    "wof:name":"Mbiabougou",
    "wof:placetype":"locality"
},
  "geometry": {"coordinates":[-5.60995,13.55589],"type":"Point"}
}