{
  "type": "Feature",
  "properties": {
    "gn:admin1_code":"05",
    "gn:asciiname":"Sibila",
    "gn:country_code":"ML",
    "gn:dem":290,
    "gn:feature_class":"P",
    "gn:feature_code":"PPL",
    "gn:name":"Sibila",
    "gn:population":0,
    "gn:timezone":"Africa/Bamako",
    "iso:country":"ML",
    "name:fin_x_preferred":[
        "Sibila"
    ],
    "name:fra_x_preferred":[
        "Sibila"
    ],
    "name:ita_x_preferred":[
        "Sibila"
    ],
    "name:nld_x_preferred":[
        "Sibila"
    ],
    "name:spa_x_preferred":[
        "Sibila"
    ],
    "name:zho_x_preferred":[
        "\u932b\u6bd4\u62c9"
    ],
    "wof:name":"Sibila",
    "wof:placetype":"locality"
},
  "geometry": {"coordinates":[-5.87776,13.77788],"type":"Point"}
}