{
  "type": "Feature",
  "properties": {
    "gn:admin1_code":"3.0",
    "gn:asciiname":"Gomedie",
    "gn:country_code":"ML",
    "gn:dem":247,
    "gn:feature_class":"P",
    "gn:feature_code":"PPL",
    "gn:name":"Gom\u00e9di\u00e9",
    "gn:population":0,
    "gn:timezone":"Africa/Bamako",
    "iso:country":"ML",
    "wof:name":"Gomedie",
    "wof:placetype":"locality"
},
  "geometry": {"coordinates":[-9.7526,13.7703],"type":"Point"}
}