{
  "type": "Feature",
  "properties": {
    "gn:admin1_code":"06",
    "gn:asciiname":"Zanfina",
    "gn:country_code":"ML",
    "gn:dem":320,
    "gn:feature_class":"P",
    "gn:feature_code":"PPL",
    "gn:name":"Zanfina",
    "gn:population":0,
    "gn:timezone":"Africa/Bamako",
    "iso:country":"ML",
    "name:fra_x_preferred":[
        "Zanfina"
    ],
    "name:fra_x_variant":[
        "Ravina"
    ],
    "wof:name":"Zanfina",
    "wof:placetype":"locality"
},
  "geometry": {"coordinates":[-6.37082,11.2685],"type":"Point"}
}