{
  "type": "Feature",
  "properties": {
    "gn:admin1_code":"04",
    "gn:asciiname":"Mohaboundou",
    "gn:country_code":"ML",
    "gn:dem":419,
    "gn:feature_class":"P",
    "gn:feature_code":"PPL",
    "gn:name":"Mohaboundou",
    "gn:population":0,
    "gn:timezone":"Africa/Bamako",
    "iso:country":"ML",
    "wof:name":"Mohaboundou",
    "wof:placetype":"locality"
},
  "geometry": {"coordinates":[-3.74499,14.2331],"type":"Point"}
}