{
  "type": "Feature",
  "properties": {
    "gn:admin1_code":"6.0",
    "gn:asciiname":"Koulikoro",
    "gn:country_code":"ML",
    "gn:dem":338,
    "gn:feature_class":"P",
    "gn:feature_code":"PPL",
    "gn:name":"Koulikoro",
    "gn:population":0,
    "gn:timezone":"Africa/Bamako",
    "iso:country":"ML",
    "name:ara_x_preferred":[
        "\u0643\u0648\u0644\u064a\u0643\u0648\u0631\u0648"
    ],
    "name:azb_x_preferred":[
        "\u06a9\u0648\u0644\u06cc\u06a9\u0648\u0631\u0648"
    ],
    "name:bam_x_preferred":[
        "Kulik\u0254r\u0254"
    ],
    "name:cat_x_preferred":[
        "Koulikoro"
    ],
    "name:ceb_x_preferred":[
        "Koulikoro"
    ],
    "name:dan_x_preferred":[
        "Koulikoro"
    ],
    "name:deu_x_preferred":[
        "Koulikoro"
    ],
    "name:ell_x_preferred":[
        "\u039a\u03bf\u03c5\u03bb\u03b9\u03ba\u03bf\u03c1\u03cc"
    ],
    "name:epo_x_preferred":[
        "Koulikoro"
    ],
    "name:eus_x_preferred":[
        "Koulikoro"
    ],
    "name:fas_x_preferred":[
        "\u06a9\u0648\u0644\u06cc\u06a9\u0648\u0631\u0648"
    ],
    "name:fin_x_preferred":[
        "Koulikoro"
    ],
    "name:fra_x_preferred":[
        "Koulikoro"
    ],
    "name:frr_x_preferred":[
        "Koulikoro"
    ],
    "name:heb_x_preferred":[
        "\u05e7\u05d5\u05dc\u05d9\u05e7\u05d5\u05e8\u05d5"
    ],
    "name:hun_x_preferred":[
        "Koulikoro"
    ],
    "name:ita_x_preferred":[
        "Koulikoro"
    ],
    "name:jpn_x_preferred":[
        "\u30af\u30ea\u30b3\u30ed"
    ],
    "name:kor_x_preferred":[
        "\ucfe8\ub9ac\ucf54\ub85c"
    ],
    "name:lit_x_preferred":[
        "Kulikoras"
    ],
    "name:ltz_x_preferred":[
        "Koulikoro"
    ],
    "name:nld_x_preferred":[
        "Koulikoro"
    ],
    "name:nor_x_preferred":[
        "Koulikoro"
    ],
    "name:pol_x_preferred":[
        "Koulikoro"
    ],
    "name:por_x_preferred":[
        "Kulikoro"
    ],
    "name:ron_x_preferred":[
        "Koulikoro"
    ],
    "name:rus_x_preferred":[
        "\u041a\u0443\u043b\u0438\u043a\u043e\u0440\u043e"
    ],
    "name:swe_x_preferred":[
        "Koulikoro"
    ],
    "name:ukr_x_preferred":[
        "\u041a\u0443\u043b\u0456\u043a\u043e\u0440\u043e"
    ],
    "name:urd_x_preferred":[
        "\u06a9\u0648\u0644\u06cc\u06a9\u0648\u0631\u0648"
    ],
    "name:zho_x_preferred":[
        "\u5eab\u5229\u79d1\u7f85"
    ],
    "wof:name":"Koulikoro",
    "wof:placetype":"locality"
},
  "geometry": {"coordinates":[-6.39097,11.64825],"type":"Point"}
}