{
  "type": "Feature",
  "properties": {
    "gn:admin1_code":"00",
    "gn:asciiname":"Karea",
    "gn:country_code":"ML",
    "gn:dem":349,
    "gn:feature_class":"P",
    "gn:feature_code":"PPL",
    "gn:name":"Kar\u00e9a",
    "gn:population":0,
    "gn:timezone":"Africa/Bamako",
    "iso:country":"ML",
    "wof:name":"Karea",
    "wof:placetype":"locality"
},
  "geometry": {"coordinates":[-9.45,13.13333],"type":"Point"}
}