{
  "type": "Feature",
  "properties": {
    "gn:admin1_code":"03",
    "gn:asciiname":"Mokoyafara",
    "gn:country_code":"ML",
    "gn:dem":58,
    "gn:feature_class":"P",
    "gn:feature_code":"PPL",
    "gn:name":"Mokoyafara",
    "gn:population":0,
    "gn:timezone":"Africa/Bamako",
    "iso:country":"ML",
    "wof:name":"Mokoyafara",
    "wof:placetype":"locality"
},
  "geometry": {"coordinates":[-11.10329,14.56521],"type":"Point"}
}