{
  "type": "Feature",
  "properties": {
    "gn:admin1_code":"08",
    "gn:asciiname":"Koryoume",
    "gn:country_code":"ML",
    "gn:dem":259,
    "gn:feature_class":"P",
    "gn:feature_code":"PPL",
    "gn:name":"Koryoum\u00e9",
    "gn:population":0,
    "gn:timezone":"Africa/Bamako",
    "iso:country":"ML",
    "name:und_x_variant":[
        "Karioum\u00e9",
        "Korioum\u00e9",
        "Koryoum\u00e9"
    ],
    "wof:name":"Koryoume",
    "wof:placetype":"locality"
},
  "geometry": {"coordinates":[-3.02624,16.66123],"type":"Point"}
}