{
  "type": "Feature",
  "properties": {
    "gn:admin1_code":"04",
    "gn:asciiname":"Dianguinare",
    "gn:country_code":"ML",
    "gn:dem":264,
    "gn:feature_class":"P",
    "gn:feature_code":"PPL",
    "gn:name":"Dianguinar\u00e9",
    "gn:population":0,
    "gn:timezone":"Africa/Bamako",
    "iso:country":"ML",
    "name:und_x_variant":[
        "Dianguinan\u00e9",
        "Diangamar\u00e9",
        "Dianguinar\u00e9"
    ],
    "wof:name":"Dianguinare",
    "wof:placetype":"locality"
},
  "geometry": {"coordinates":[-3.5985,15.4768],"type":"Point"}
}