{
  "type": "Feature",
  "properties": {
    "gn:admin1_code":"03",
    "gn:asciiname":"Tintiba",
    "gn:country_code":"ML",
    "gn:dem":308,
    "gn:feature_class":"P",
    "gn:feature_code":"PPL",
    "gn:name":"Tintiba",
    "gn:population":0,
    "gn:timezone":"Africa/Bamako",
    "iso:country":"ML",
    "wof:name":"Tintiba",
    "wof:placetype":"locality"
},
  "geometry": {"coordinates":[-10.3618,14.0186],"type":"Point"}
}