{
  "type": "Feature",
  "properties": {
    "gn:admin1_code":"5.0",
    "gn:asciiname":"Bina",
    "gn:country_code":"ML",
    "gn:dem":281,
    "gn:feature_class":"P",
    "gn:feature_code":"PPL",
    "gn:name":"Bina",
    "gn:population":0,
    "gn:timezone":"Africa/Bamako",
    "iso:country":"ML",
    "name:ceb_x_preferred":[
        "Bina"
    ],
    "name:deu_x_preferred":[
        "Bina"
    ],
    "name:heb_x_preferred":[
        "\u05d1\u05d9\u05e0\u05d4"
    ],
    "name:hin_x_preferred":[
        "\u092c\u0940\u0928\u093e"
    ],
    "name:ita_x_preferred":[
        "Bina"
    ],
    "name:por_x_preferred":[
        "Bina"
    ],
    "name:srp_x_preferred":[
        "\u0411\u0438\u043d\u0430"
    ],
    "name:swe_x_preferred":[
        "Bina"
    ],
    "name:tur_x_preferred":[
        "Bina"
    ],
    "wof:name":"Bina",
    "wof:placetype":"locality"
},
  "geometry": {"coordinates":[-4.7101,13.5431],"type":"Point"}
}