{
  "type": "Feature",
  "properties": {
    "gn:admin1_code":"05",
    "gn:asciiname":"Tominian",
    "gn:country_code":"ML",
    "gn:dem":301,
    "gn:feature_class":"P",
    "gn:feature_code":"PPLA2",
    "gn:name":"Tominian",
    "gn:population":0,
    "gn:timezone":"Africa/Bamako",
    "iso:country":"ML",
    "name:ceb_x_preferred":[
        "Tominian"
    ],
    "name:fin_x_preferred":[
        "Tominian"
    ],
    "name:fra_x_preferred":[
        "Tominian"
    ],
    "name:ita_x_preferred":[
        "Tominian"
    ],
    "name:nld_x_preferred":[
        "Tominian"
    ],
    "name:spa_x_preferred":[
        "Tominian"
    ],
    "name:swe_x_preferred":[
        "Tominian"
    ],
    "name:und_x_variant":[
        "Tomina",
        "Tominian"
    ],
    "name:zho_x_preferred":[
        "\u6258\u7c73\u5c3c\u5b89"
    ],
    "wof:name":"Tominian",
    "wof:placetype":"locality"
},
  "geometry": {"coordinates":[-4.59317,13.28737],"type":"Point"}
}