{
  "type": "Feature",
  "properties": {
    "gn:admin1_code":"05",
    "gn:asciiname":"Mpesso",
    "gn:country_code":"ML",
    "gn:dem":306,
    "gn:feature_class":"P",
    "gn:feature_code":"PPL",
    "gn:name":"Mpesso",
    "gn:population":0,
    "gn:timezone":"Africa/Bamako",
    "iso:country":"ML",
    "wof:name":"Mpesso",
    "wof:placetype":"locality"
},
  "geometry": {"coordinates":[-4.9331,12.9567],"type":"Point"}
}