{
  "type": "Feature",
  "properties": {
    "gn:admin1_code":"6.0",
    "gn:asciiname":"Tintala",
    "gn:country_code":"ML",
    "gn:dem":364,
    "gn:feature_class":"P",
    "gn:feature_code":"PPL",
    "gn:name":"Tintala",
    "gn:population":0,
    "gn:timezone":"Africa/Bamako",
    "iso:country":"ML",
    "wof:name":"Tintala",
    "wof:placetype":"locality"
},
  "geometry": {"coordinates":[-7.30866,11.82553],"type":"Point"}
}