{
  "type": "Feature",
  "properties": {
    "gn:admin1_code":"3.0",
    "gn:asciiname":"Sirakoro",
    "gn:country_code":"ML",
    "gn:dem":267,
    "gn:feature_class":"P",
    "gn:feature_code":"PPL",
    "gn:name":"Sirakoro",
    "gn:population":0,
    "gn:timezone":"Africa/Bamako",
    "iso:country":"ML",
    "name:ceb_x_preferred":[
        "Sirakoro"
    ],
    "name:fra_x_preferred":[
        "Sirakoro"
    ],
    "name:spa_x_preferred":[
        "Sirakoro"
    ],
    "name:swe_x_preferred":[
        "Sirakoro"
    ],
    "wof:name":"Sirakoro",
    "wof:placetype":"locality"
},
  "geometry": {"coordinates":[-9.5588,14.6914],"type":"Point"}
}