{
  "type": "Feature",
  "properties": {
    "gn:admin1_code":"07",
    "gn:asciiname":"Diouladougou Touna",
    "gn:country_code":"ML",
    "gn:dem":342,
    "gn:feature_class":"P",
    "gn:feature_code":"PPL",
    "gn:name":"Diouladougou Touna",
    "gn:population":0,
    "gn:timezone":"Africa/Bamako",
    "iso:country":"ML",
    "name:fra_x_preferred":[
        "Touna"
    ],
    "name:und_x_variant":[
        "Touna"
    ],
    "wof:name":"Diouladougou Touna",
    "wof:placetype":"locality"
},
  "geometry": {"coordinates":[-6.6547,11.96525],"type":"Point"}
}