{
  "type": "Feature",
  "properties": {
    "gn:admin1_code":"07",
    "gn:asciiname":"Sidoni",
    "gn:country_code":"ML",
    "gn:dem":403,
    "gn:feature_class":"P",
    "gn:feature_code":"PPL",
    "gn:name":"Sidoni",
    "gn:population":0,
    "gn:timezone":"Africa/Bamako",
    "iso:country":"ML",
    "name:fra_x_preferred":[
        "Sidoni"
    ],
    "wof:name":"Sidoni",
    "wof:placetype":"locality"
},
  "geometry": {"coordinates":[-8.0796,13.1223],"type":"Point"}
}