{
  "type": "Feature",
  "properties": {
    "gn:admin1_code":"08",
    "gn:asciiname":"Tarhayt-Gorou",
    "gn:country_code":"ML",
    "gn:dem":267,
    "gn:feature_class":"P",
    "gn:feature_code":"PPL",
    "gn:name":"Tarhayt-Gorou",
    "gn:population":0,
    "gn:timezone":"Africa/Bamako",
    "iso:country":"ML",
    "name:und_x_variant":[
        "Taka\u00ef Gorout",
        "Torhayt Gorou",
        "Tarhayt-Gorou"
    ],
    "wof:name":"Tarhayt-Gorou",
    "wof:placetype":"locality"
},
  "geometry": {"coordinates":[-3.07828,16.4378],"type":"Point"}
}