{
  "type": "Feature",
  "properties": {
    "gn:admin1_code":"6.0",
    "gn:asciiname":"Dopela",
    "gn:country_code":"ML",
    "gn:dem":331,
    "gn:feature_class":"P",
    "gn:feature_code":"PPL",
    "gn:name":"Dop\u00e9la",
    "gn:population":0,
    "gn:timezone":"Africa/Bamako",
    "iso:country":"ML",
    "wof:name":"Dopela",
    "wof:placetype":"locality"
},
  "geometry": {"coordinates":[-5.3339,12.146],"type":"Point"}
}