{
  "type": "Feature",
  "properties": {
    "gn:admin1_code":"04",
    "gn:asciiname":"Ninngo",
    "gn:country_code":"ML",
    "gn:dem":361,
    "gn:feature_class":"P",
    "gn:feature_code":"PPL",
    "gn:name":"Ninngo",
    "gn:population":0,
    "gn:timezone":"Africa/Bamako",
    "iso:country":"ML",
    "wof:name":"Ninngo",
    "wof:placetype":"locality"
},
  "geometry": {"coordinates":[-3.64039,14.8274],"type":"Point"}
}