{
  "type": "Feature",
  "properties": {
    "gn:admin1_code":"07",
    "gn:asciiname":"Kokoun",
    "gn:country_code":"ML",
    "gn:dem":309,
    "gn:feature_class":"P",
    "gn:feature_code":"PPL",
    "gn:name":"Kokoun",
    "gn:population":0,
    "gn:timezone":"Africa/Bamako",
    "iso:country":"ML",
    "name:fra_x_preferred":[
        "Kokoun"
    ],
    "name:fra_x_variant":[
        "Kokouri"
    ],
    "name:msa_x_preferred":[
        "Kokoun"
    ],
    "wof:name":"Kokoun",
    "wof:placetype":"locality"
},
  "geometry": {"coordinates":[-6.46838,11.88269],"type":"Point"}
}