{
  "type": "Feature",
  "properties": {
    "gn:admin1_code":"7.0",
    "gn:asciiname":"Dinkou",
    "gn:country_code":"ML",
    "gn:dem":570,
    "gn:feature_class":"P",
    "gn:feature_code":"PPL",
    "gn:name":"Dinkou",
    "gn:population":0,
    "gn:timezone":"Africa/Bamako",
    "iso:country":"ML",
    "wof:name":"Dinkou",
    "wof:placetype":"locality"
},
  "geometry": {"coordinates":[-8.79307,12.55619],"type":"Point"}
}