{
  "type": "Feature",
  "properties": {
    "gn:admin1_code":"7.0",
    "gn:asciiname":"Baninkouma",
    "gn:country_code":"ML",
    "gn:dem":538,
    "gn:feature_class":"P",
    "gn:feature_code":"PPL",
    "gn:name":"Baninkouma",
    "gn:population":0,
    "gn:timezone":"Africa/Bamako",
    "iso:country":"ML",
    "wof:name":"Baninkouma",
    "wof:placetype":"locality"
},
  "geometry": {"coordinates":[-8.73257,12.46979],"type":"Point"}
}