{
  "type": "Feature",
  "properties": {
    "gn:admin1_code":"4.0",
    "gn:asciiname":"Kena",
    "gn:country_code":"ML",
    "gn:dem":596,
    "gn:feature_class":"P",
    "gn:feature_code":"PPL",
    "gn:name":"K\u00e9na",
    "gn:population":0,
    "gn:timezone":"Africa/Bamako",
    "iso:country":"ML",
    "name:ceb_x_preferred":[
        "Kena"
    ],
    "name:deu_x_preferred":[
        "Kena"
    ],
    "name:lit_x_preferred":[
        "Kena"
    ],
    "name:swe_x_preferred":[
        "Kena"
    ],
    "wof:name":"Kena",
    "wof:placetype":"locality"
},
  "geometry": {"coordinates":[-3.28823,14.59677],"type":"Point"}
}