{
  "type": "Feature",
  "properties": {
    "gn:admin1_code":"05",
    "gn:asciiname":"Wa",
    "gn:country_code":"ML",
    "gn:dem":277,
    "gn:feature_class":"P",
    "gn:feature_code":"PPL",
    "gn:name":"Wa",
    "gn:population":0,
    "gn:timezone":"Africa/Bamako",
    "iso:country":"ML",
    "name:fin_x_preferred":[
        "Ouan"
    ],
    "name:fra_x_preferred":[
        "Ouan"
    ],
    "name:ita_x_preferred":[
        "Ouan"
    ],
    "name:nld_x_preferred":[
        "Ouan"
    ],
    "name:spa_x_preferred":[
        "Ouan"
    ],
    "name:und_x_variant":[
        "Nioumankui",
        "Ouan",
        "Oua",
        "Wa"
    ],
    "wof:name":"Wa",
    "wof:placetype":"locality"
},
  "geometry": {"coordinates":[-4.4005,13.6933],"type":"Point"}
}