{
  "type": "Feature",
  "properties": {
    "gn:admin1_code":"08",
    "gn:asciiname":"Danga",
    "gn:country_code":"ML",
    "gn:dem":266,
    "gn:feature_class":"P",
    "gn:feature_code":"PPL",
    "gn:name":"Danga",
    "gn:population":0,
    "gn:timezone":"Africa/Bamako",
    "iso:country":"ML",
    "name:und_x_variant":[
        "Denha",
        "Danga"
    ],
    "wof:name":"Danga",
    "wof:placetype":"locality"
},
  "geometry": {"coordinates":[-3.13809,16.46395],"type":"Point"}
}