{
  "type": "Feature",
  "properties": {
    "gn:admin1_code":"03",
    "gn:asciiname":"Gomintara",
    "gn:country_code":"ML",
    "gn:dem":298,
    "gn:feature_class":"P",
    "gn:feature_code":"PPL",
    "gn:name":"Gomintara",
    "gn:population":0,
    "gn:timezone":"Africa/Bamako",
    "iso:country":"ML",
    "name:und_x_variant":[
        "Wataye",
        "Gonintara",
        "Gomintara"
    ],
    "wof:name":"Gomintara",
    "wof:placetype":"locality"
},
  "geometry": {"coordinates":[-8.2749,14.4277],"type":"Point"}
}