{
  "type": "Feature",
  "properties": {
    "gn:admin1_code":"7.0",
    "gn:asciiname":"Marmoure",
    "gn:country_code":"ML",
    "gn:dem":279,
    "gn:feature_class":"P",
    "gn:feature_code":"PPL",
    "gn:name":"Marmour\u00e9",
    "gn:population":0,
    "gn:timezone":"Africa/Bamako",
    "iso:country":"ML",
    "wof:name":"Marmoure",
    "wof:placetype":"locality"
},
  "geometry": {"coordinates":[-7.46315,15.08375],"type":"Point"}
}