{
  "type": "Feature",
  "properties": {
    "gn:admin1_code":"07",
    "gn:asciiname":"Tarabakoro",
    "gn:country_code":"ML",
    "gn:dem":272,
    "gn:feature_class":"P",
    "gn:feature_code":"PPL",
    "gn:name":"Tarabakoro",
    "gn:population":0,
    "gn:timezone":"Africa/Bamako",
    "iso:country":"ML",
    "name:fra_x_preferred":[
        "Tarabakoro"
    ],
    "name:fra_x_variant":[
        "Torobokoro"
    ],
    "wof:name":"Tarabakoro",
    "wof:placetype":"locality"
},
  "geometry": {"coordinates":[-6.9951,14.8089],"type":"Point"}
}