{
  "type": "Feature",
  "properties": {
    "gn:admin1_code":"8.0",
    "gn:asciiname":"Amaghanane",
    "gn:country_code":"ML",
    "gn:dem":262,
    "gn:feature_class":"P",
    "gn:feature_code":"PPL",
    "gn:name":"Amaghanane",
    "gn:population":0,
    "gn:timezone":"Africa/Bamako",
    "iso:country":"ML",
    "wof:name":"Amaghanane",
    "wof:placetype":"locality"
},
  "geometry": {"coordinates":[-4.17412,16.71327999999999],"type":"Point"}
}