{
  "type": "Feature",
  "properties": {
    "gn:admin1_code":"5.0",
    "gn:asciiname":"Timini",
    "gn:country_code":"ML",
    "gn:dem":284,
    "gn:feature_class":"P",
    "gn:feature_code":"PPL",
    "gn:name":"Timini",
    "gn:population":0,
    "gn:timezone":"Africa/Bamako",
    "iso:country":"ML",
    "wof:name":"Timini",
    "wof:placetype":"locality"
},
  "geometry": {"coordinates":[-5.96522,13.5024],"type":"Point"}
}