{
  "type": "Feature",
  "properties": {
    "gn:admin1_code":"7.0",
    "gn:asciiname":"Noumoubakabougou",
    "gn:country_code":"ML",
    "gn:dem":312,
    "gn:feature_class":"P",
    "gn:feature_code":"PPL",
    "gn:name":"Noumoubakabougou",
    "gn:population":0,
    "gn:timezone":"Africa/Bamako",
    "iso:country":"ML",
    "wof:name":"Noumoubakabougou",
    "wof:placetype":"locality"
},
  "geometry": {"coordinates":[-7.38863,13.20741],"type":"Point"}
}