{
  "type": "Feature",
  "properties": {
    "gn:admin1_code":"7.0",
    "gn:asciiname":"Keninkoun",
    "gn:country_code":"ML",
    "gn:dem":497,
    "gn:feature_class":"P",
    "gn:feature_code":"PPL",
    "gn:name":"K\u00e9ninkoun",
    "gn:population":0,
    "gn:timezone":"Africa/Bamako",
    "iso:country":"ML",
    "wof:name":"Keninkoun",
    "wof:placetype":"locality"
},
  "geometry": {"coordinates":[-8.2132,12.59214],"type":"Point"}
}