{
  "type": "Feature",
  "properties": {
    "gn:admin1_code":"07",
    "gn:asciiname":"Kena",
    "gn:country_code":"ML",
    "gn:dem":394,
    "gn:feature_class":"P",
    "gn:feature_code":"PPL",
    "gn:name":"K\u00e9na",
    "gn:population":0,
    "gn:timezone":"Africa/Bamako",
    "iso:country":"ML",
    "wof:name":"Kena",
    "wof:placetype":"locality"
},
  "geometry": {"coordinates":[-7.9197,13.33736],"type":"Point"}
}