{
  "type": "Feature",
  "properties": {
    "gn:admin1_code":"03",
    "gn:asciiname":"Zebat",
    "gn:country_code":"ML",
    "gn:dem":140,
    "gn:feature_class":"P",
    "gn:feature_code":"PPL",
    "gn:name":"Z\u00e9bat",
    "gn:population":0,
    "gn:timezone":"Africa/Bamako",
    "iso:country":"ML",
    "name:und_x_variant":[
        "Z\u00e9bal",
        "Z\u00e9bat"
    ],
    "wof:name":"Zebat",
    "wof:placetype":"locality"
},
  "geometry": {"coordinates":[-11.30543,15.1455],"type":"Point"}
}