{
  "type": "Feature",
  "properties": {
    "gn:admin1_code":"7.0",
    "gn:asciiname":"Sakababougou",
    "gn:country_code":"ML",
    "gn:dem":343,
    "gn:feature_class":"P",
    "gn:feature_code":"PPL",
    "gn:name":"Sakababougou",
    "gn:population":0,
    "gn:timezone":"Africa/Bamako",
    "iso:country":"ML",
    "wof:name":"Sakababougou",
    "wof:placetype":"locality"
},
  "geometry": {"coordinates":[-7.67314,13.77285],"type":"Point"}
}