{
  "type": "Feature",
  "properties": {
    "gn:admin1_code":"7.0",
    "gn:asciiname":"Farafaradie",
    "gn:country_code":"ML",
    "gn:dem":399,
    "gn:feature_class":"P",
    "gn:feature_code":"PPL",
    "gn:name":"Farafaradi\u00e8",
    "gn:population":0,
    "gn:timezone":"Africa/Bamako",
    "iso:country":"ML",
    "wof:name":"Farafaradie",
    "wof:placetype":"locality"
},
  "geometry": {"coordinates":[-8.97497,12.47549],"type":"Point"}
}