{
  "type": "Feature",
  "properties": {
    "gn:admin1_code":"03",
    "gn:asciiname":"Fara",
    "gn:country_code":"ML",
    "gn:dem":207,
    "gn:feature_class":"P",
    "gn:feature_code":"PPL",
    "gn:name":"Fara",
    "gn:population":0,
    "gn:timezone":"Africa/Bamako",
    "iso:country":"ML",
    "wof:name":"Fara",
    "wof:placetype":"locality"
},
  "geometry": {"coordinates":[-10.5855,14.7076],"type":"Point"}
}