{
  "type": "Feature",
  "properties": {
    "gn:admin1_code":"5.0",
    "gn:asciiname":"Kako",
    "gn:country_code":"ML",
    "gn:dem":276,
    "gn:feature_class":"P",
    "gn:feature_code":"PPL",
    "gn:name":"Kako",
    "gn:population":0,
    "gn:timezone":"Africa/Bamako",
    "iso:country":"ML",
    "name:ceb_x_preferred":[
        "Kako"
    ],
    "name:deu_x_preferred":[
        "Kako"
    ],
    "name:epo_x_preferred":[
        "Kako"
    ],
    "name:est_x_preferred":[
        "Kako"
    ],
    "name:fra_x_preferred":[
        "Kako"
    ],
    "name:ita_x_preferred":[
        "Kako"
    ],
    "name:spa_x_preferred":[
        "Kako"
    ],
    "name:swe_x_preferred":[
        "Kako"
    ],
    "wof:name":"Kako",
    "wof:placetype":"locality"
},
  "geometry": {"coordinates":[-5.10714,13.59205],"type":"Point"}
}