{
  "type": "Feature",
  "properties": {
    "gn:admin1_code":"00",
    "gn:asciiname":"Kourouhinndo Kabalafata",
    "gn:country_code":"ML",
    "gn:dem":313,
    "gn:feature_class":"P",
    "gn:feature_code":"PPL",
    "gn:name":"Kourouhinndo Kabalafata",
    "gn:population":0,
    "gn:timezone":"Africa/Bamako",
    "iso:country":"ML",
    "wof:name":"Kourouhinndo Kabalafata",
    "wof:placetype":"locality"
},
  "geometry": {"coordinates":[-10.23333,12.55],"type":"Point"}
}