{
  "type": "Feature",
  "properties": {
    "gn:admin1_code":"06",
    "gn:asciiname":"Tyemala",
    "gn:country_code":"ML",
    "gn:dem":339,
    "gn:feature_class":"P",
    "gn:feature_code":"PPL",
    "gn:name":"Ty\u00e8mala",
    "gn:population":0,
    "gn:timezone":"Africa/Bamako",
    "iso:country":"ML",
    "wof:name":"Tyemala",
    "wof:placetype":"locality"
},
  "geometry": {"coordinates":[-7.30063,12.12178],"type":"Point"}
}