{
  "type": "Feature",
  "properties": {
    "gn:admin1_code":"08",
    "gn:asciiname":"Kayouaten",
    "gn:country_code":"ML",
    "gn:dem":261,
    "gn:feature_class":"P",
    "gn:feature_code":"PPL",
    "gn:name":"Kayouat\u00e8n",
    "gn:population":0,
    "gn:timezone":"Africa/Bamako",
    "iso:country":"ML",
    "wof:name":"Kayouaten",
    "wof:placetype":"locality"
},
  "geometry": {"coordinates":[-1.71556,16.9325],"type":"Point"}
}