{
  "type": "Feature",
  "properties": {
    "gn:admin1_code":"3.0",
    "gn:asciiname":"Guemou",
    "gn:country_code":"ML",
    "gn:dem":102,
    "gn:feature_class":"P",
    "gn:feature_code":"PPL",
    "gn:name":"Gu\u00e9mou",
    "gn:population":0,
    "gn:timezone":"Africa/Bamako",
    "iso:country":"ML",
    "wof:name":"Guemou",
    "wof:placetype":"locality"
},
  "geometry": {"coordinates":[-10.61315,15.24944],"type":"Point"}
}