{
  "type": "Feature",
  "properties": {
    "gn:admin1_code":"05",
    "gn:asciiname":"Sangarebougou",
    "gn:country_code":"ML",
    "gn:dem":284,
    "gn:feature_class":"P",
    "gn:feature_code":"PPL",
    "gn:name":"Sangar\u00e9bougou",
    "gn:population":0,
    "gn:timezone":"Africa/Bamako",
    "iso:country":"ML",
    "wof:name":"Sangarebougou",
    "wof:placetype":"locality"
},
  "geometry": {"coordinates":[-5.54809,13.93195],"type":"Point"}
}