{
  "type": "Feature",
  "properties": {
    "gn:admin1_code":"04",
    "gn:asciiname":"Nassagou",
    "gn:country_code":"ML",
    "gn:dem":322,
    "gn:feature_class":"P",
    "gn:feature_code":"PPL",
    "gn:name":"Nassagou",
    "gn:population":0,
    "gn:timezone":"Africa/Bamako",
    "iso:country":"ML",
    "wof:name":"Nassagou",
    "wof:placetype":"locality"
},
  "geometry": {"coordinates":[-3.7003,13.8301],"type":"Point"}
}