{
  "type": "Feature",
  "properties": {
    "gn:admin1_code":"5.0",
    "gn:asciiname":"Kambia",
    "gn:country_code":"ML",
    "gn:dem":280,
    "gn:feature_class":"P",
    "gn:feature_code":"PPL",
    "gn:name":"Kambia",
    "gn:population":0,
    "gn:timezone":"Africa/Bamako",
    "iso:country":"ML",
    "wof:name":"Kambia",
    "wof:placetype":"locality"
},
  "geometry": {"coordinates":[-6.07222,13.327],"type":"Point"}
}