{
  "type": "Feature",
  "properties": {
    "gn:admin1_code":"7.0",
    "gn:asciiname":"Bayorobougou",
    "gn:country_code":"ML",
    "gn:dem":365,
    "gn:feature_class":"P",
    "gn:feature_code":"PPL",
    "gn:name":"Bayorobougou",
    "gn:population":0,
    "gn:timezone":"Africa/Bamako",
    "iso:country":"ML",
    "wof:name":"Bayorobougou",
    "wof:placetype":"locality"
},
  "geometry": {"coordinates":[-7.26004,12.87125],"type":"Point"}
}