{
  "type": "Feature",
  "properties": {
    "gn:admin1_code":"03",
    "gn:asciiname":"Yom-Yom",
    "gn:country_code":"ML",
    "gn:dem":255,
    "gn:feature_class":"P",
    "gn:feature_code":"PPL",
    "gn:name":"Yom-Yom",
    "gn:population":0,
    "gn:timezone":"Africa/Bamako",
    "iso:country":"ML",
    "wof:name":"Yom-Yom",
    "wof:placetype":"locality"
},
  "geometry": {"coordinates":[-10.3387,14.4665],"type":"Point"}
}