{
  "type": "Feature",
  "properties": {
    "gn:admin1_code":"07",
    "gn:asciiname":"Massakoroma",
    "gn:country_code":"ML",
    "gn:dem":569,
    "gn:feature_class":"P",
    "gn:feature_code":"PPL",
    "gn:name":"Massakoroma",
    "gn:population":0,
    "gn:timezone":"Africa/Bamako",
    "iso:country":"ML",
    "name:und_x_variant":[
        "Masakoroma",
        "Massakoroma"
    ],
    "wof:name":"Massakoroma",
    "wof:placetype":"locality"
},
  "geometry": {"coordinates":[-8.77535,12.30016],"type":"Point"}
}