{
  "type": "Feature",
  "properties": {
    "gn:admin1_code":"08",
    "gn:asciiname":"Dyaloube",
    "gn:country_code":"ML",
    "gn:dem":260,
    "gn:feature_class":"P",
    "gn:feature_code":"PPL",
    "gn:name":"Dyaloub\u00e9",
    "gn:population":0,
    "gn:timezone":"Africa/Bamako",
    "iso:country":"ML",
    "name:und_x_variant":[
        "Dialloub\u00e9",
        "Dyaloub\u00e9"
    ],
    "wof:name":"Dyaloube",
    "wof:placetype":"locality"
},
  "geometry": {"coordinates":[-3.54806,16.36011],"type":"Point"}
}