{
  "type": "Feature",
  "properties": {
    "gn:admin1_code":"05",
    "gn:asciiname":"Forokouna",
    "gn:country_code":"ML",
    "gn:dem":280,
    "gn:feature_class":"P",
    "gn:feature_code":"PPL",
    "gn:name":"Forokouna",
    "gn:population":0,
    "gn:timezone":"Africa/Bamako",
    "iso:country":"ML",
    "name:und_x_variant":[
        "Bouiwa",
        "Forokouna"
    ],
    "wof:name":"Forokouna",
    "wof:placetype":"locality"
},
  "geometry": {"coordinates":[-4.3673,13.6616],"type":"Point"}
}