{
  "type": "Feature",
  "properties": {
    "gn:admin1_code":"4.0",
    "gn:asciiname":"Midio-Bouri",
    "gn:country_code":"ML",
    "gn:dem":317,
    "gn:feature_class":"P",
    "gn:feature_code":"PPL",
    "gn:name":"Midio-Bouri",
    "gn:population":0,
    "gn:timezone":"Africa/Bamako",
    "iso:country":"ML",
    "wof:name":"Midio-Bouri",
    "wof:placetype":"locality"
},
  "geometry": {"coordinates":[-3.7907,14.5876],"type":"Point"}
}