{
  "type": "Feature",
  "properties": {
    "gn:admin1_code":"05",
    "gn:asciiname":"Diguiyara",
    "gn:country_code":"ML",
    "gn:dem":287,
    "gn:feature_class":"P",
    "gn:feature_code":"PPL",
    "gn:name":"Diguiyara",
    "gn:population":0,
    "gn:timezone":"Africa/Bamako",
    "iso:country":"ML",
    "name:und_x_variant":[
        "Djigui\u00e9ra",
        "Diguira",
        "Diguiyara"
    ],
    "wof:name":"Diguiyara",
    "wof:placetype":"locality"
},
  "geometry": {"coordinates":[-4.9109,13.1838],"type":"Point"}
}