{
  "type": "Feature",
  "properties": {
    "gn:admin1_code":"06",
    "gn:asciiname":"Dionkala",
    "gn:country_code":"ML",
    "gn:dem":333,
    "gn:feature_class":"P",
    "gn:feature_code":"PPL",
    "gn:name":"Dionkala",
    "gn:population":0,
    "gn:timezone":"Africa/Bamako",
    "iso:country":"ML",
    "name:fra_x_preferred":[
        "Dionkala"
    ],
    "wof:name":"Dionkala",
    "wof:placetype":"locality"
},
  "geometry": {"coordinates":[-6.71623,11.77267],"type":"Point"}
}