{
  "type": "Feature",
  "properties": {
    "gn:admin1_code":"7.0",
    "gn:asciiname":"Diago Koro",
    "gn:country_code":"ML",
    "gn:dem":402,
    "gn:feature_class":"P",
    "gn:feature_code":"PPL",
    "gn:name":"Diago Koro",
    "gn:population":0,
    "gn:timezone":"Africa/Bamako",
    "iso:country":"ML",
    "wof:name":"Diago Koro",
    "wof:placetype":"locality"
},
  "geometry": {"coordinates":[-8.14931,12.81235],"type":"Point"}
}