{
  "type": "Feature",
  "properties": {
    "gn:admin1_code":"07",
    "gn:asciiname":"Douba",
    "gn:country_code":"ML",
    "gn:dem":364,
    "gn:feature_class":"P",
    "gn:feature_code":"PPL",
    "gn:name":"Douba",
    "gn:population":0,
    "gn:timezone":"Africa/Bamako",
    "iso:country":"ML",
    "name:und_x_variant":[
        "Diba",
        "Douba"
    ],
    "wof:name":"Douba",
    "wof:placetype":"locality"
},
  "geometry": {"coordinates":[-7.8338,12.3399],"type":"Point"}
}