{
  "type": "Feature",
  "properties": {
    "gn:admin1_code":"3.0",
    "gn:asciiname":"Bilajmi",
    "gn:country_code":"ML",
    "gn:dem":133,
    "gn:feature_class":"P",
    "gn:feature_code":"PPL",
    "gn:name":"Bilajmi",
    "gn:population":0,
    "gn:timezone":"Africa/Bamako",
    "iso:country":"ML",
    "name:und_x_variant":[
        "Biljami",
        "Bilajmi"
    ],
    "wof:name":"Bilajmi",
    "wof:placetype":"locality"
},
  "geometry": {"coordinates":[-11.25109,15.00908],"type":"Point"}
}