{
  "type": "Feature",
  "properties": {
    "gn:admin1_code":"03",
    "gn:asciiname":"Sofa",
    "gn:country_code":"ML",
    "gn:dem":235,
    "gn:feature_class":"P",
    "gn:feature_code":"PPL",
    "gn:name":"Sofa",
    "gn:population":0,
    "gn:timezone":"Africa/Bamako",
    "iso:country":"ML",
    "wof:name":"Sofa",
    "wof:placetype":"locality"
},
  "geometry": {"coordinates":[-9.8378,14.5897],"type":"Point"}
}