{
  "type": "Feature",
  "properties": {
    "gn:admin1_code":"07",
    "gn:asciiname":"Fouloungo",
    "gn:country_code":"ML",
    "gn:dem":377,
    "gn:feature_class":"P",
    "gn:feature_code":"PPL",
    "gn:name":"Fouloungo",
    "gn:population":0,
    "gn:timezone":"Africa/Bamako",
    "iso:country":"ML",
    "wof:name":"Fouloungo",
    "wof:placetype":"locality"
},
  "geometry": {"coordinates":[-7.84979,14.00588],"type":"Point"}
}