{
  "type": "Feature",
  "properties": {
    "gn:admin1_code":"07",
    "gn:asciiname":"Falani",
    "gn:country_code":"ML",
    "gn:dem":363,
    "gn:feature_class":"P",
    "gn:feature_code":"PPL",
    "gn:name":"Falani",
    "gn:population":0,
    "gn:timezone":"Africa/Bamako",
    "iso:country":"ML",
    "name:und_x_variant":[
        "Farani",
        "Falani"
    ],
    "wof:name":"Falani",
    "wof:placetype":"locality"
},
  "geometry": {"coordinates":[-7.79944,12.44416],"type":"Point"}
}