{
  "type": "Feature",
  "properties": {
    "gn:admin1_code":"04",
    "gn:asciiname":"Nangadourou",
    "gn:country_code":"ML",
    "gn:dem":285,
    "gn:feature_class":"P",
    "gn:feature_code":"PPL",
    "gn:name":"Nangadourou",
    "gn:population":0,
    "gn:timezone":"Africa/Bamako",
    "iso:country":"ML",
    "name:und_x_variant":[
        "Nangdourou",
        "Nangadourou"
    ],
    "wof:name":"Nangadourou",
    "wof:placetype":"locality"
},
  "geometry": {"coordinates":[-3.11979,14.3335],"type":"Point"}
}