{
  "type": "Feature",
  "properties": {
    "gn:admin1_code":"05",
    "gn:asciiname":"Samabouro",
    "gn:country_code":"ML",
    "gn:dem":298,
    "gn:feature_class":"P",
    "gn:feature_code":"PPL",
    "gn:name":"Samabouro",
    "gn:population":0,
    "gn:timezone":"Africa/Bamako",
    "iso:country":"ML",
    "name:und_x_variant":[
        "Samabogo",
        "Samabouro"
    ],
    "wof:name":"Samabouro",
    "wof:placetype":"locality"
},
  "geometry": {"coordinates":[-5.50596,12.85869],"type":"Point"}
}