{
  "type": "Feature",
  "properties": {
    "gn:admin1_code":"07",
    "gn:asciiname":"Semba",
    "gn:country_code":"ML",
    "gn:dem":351,
    "gn:feature_class":"P",
    "gn:feature_code":"PPL",
    "gn:name":"S\u00e8mba",
    "gn:population":0,
    "gn:timezone":"Africa/Bamako",
    "iso:country":"ML",
    "name:cat_x_preferred":[
        "Semba"
    ],
    "name:deu_x_preferred":[
        "Semba"
    ],
    "name:epo_x_preferred":[
        "Sembo"
    ],
    "name:fra_x_preferred":[
        "Semba"
    ],
    "name:jpn_x_preferred":[
        "\u30bb\u30f3\u30d0"
    ],
    "name:por_x_preferred":[
        "Semba"
    ],
    "name:rus_x_preferred":[
        "\u0421\u0435\u043c\u0431\u0430"
    ],
    "name:spa_x_preferred":[
        "Semba"
    ],
    "name:und_x_variant":[
        "Simba",
        "S\u00e8mba"
    ],
    "wof:name":"Semba",
    "wof:placetype":"locality"
},
  "geometry": {"coordinates":[-7.74164,12.879],"type":"Point"}
}