{
  "type": "Feature",
  "properties": {
    "gn:admin1_code":"07",
    "gn:asciiname":"Semba",
    "gn:country_code":"ML",
    "gn:dem":351,
    "gn:feature_class":"P",
    "gn:feature_code":"PPL",
    "gn:name":"S\u00e8mba",
    "gn:population":0,
    "gn:timezone":"Africa/Bamako",
    "iso:country":"ML",
    "name:und_x_variant":[
        "Simba",
        "S\u00e8mba"
    ],
    "wof:name":"Semba",
    "wof:placetype":"locality"
},
  "geometry": {"coordinates":[-7.74164,12.879],"type":"Point"}
}