{
  "type": "Feature",
  "properties": {
    "gn:admin1_code":"4.0",
    "gn:asciiname":"Tilde-Tarbaye",
    "gn:country_code":"ML",
    "gn:dem":269,
    "gn:feature_class":"P",
    "gn:feature_code":"PPL",
    "gn:name":"Tild\u00e9-Tarbaye",
    "gn:population":0,
    "gn:timezone":"Africa/Bamako",
    "iso:country":"ML",
    "wof:name":"Tilde-Tarbaye",
    "wof:placetype":"locality"
},
  "geometry": {"coordinates":[-4.73401,14.60819],"type":"Point"}
}