{
  "type": "Feature",
  "properties": {
    "gn:admin1_code":"07",
    "gn:asciiname":"Hasei",
    "gn:country_code":"ML",
    "gn:dem":287,
    "gn:feature_class":"P",
    "gn:feature_code":"PPL",
    "gn:name":"H\u00e2s\u00e8\u00ef",
    "gn:population":0,
    "gn:timezone":"Africa/Bamako",
    "iso:country":"ML",
    "name:und_x_variant":[
        "Hasse\u00ef",
        "H\u00e2s\u00e8\u00ef"
    ],
    "wof:name":"Hasei",
    "wof:placetype":"locality"
},
  "geometry": {"coordinates":[-8.56967,15.06519],"type":"Point"}
}