{
  "type": "Feature",
  "properties": {
    "gn:admin1_code":"03",
    "gn:asciiname":"Yeri Malo",
    "gn:country_code":"ML",
    "gn:dem":297,
    "gn:feature_class":"P",
    "gn:feature_code":"PPL",
    "gn:name":"Yeri Malo",
    "gn:population":0,
    "gn:timezone":"Africa/Bamako",
    "iso:country":"ML",
    "wof:name":"Yeri Malo",
    "wof:placetype":"locality"
},
  "geometry": {"coordinates":[-10.3568,14.076],"type":"Point"}
}