{
  "type": "Feature",
  "properties": {
    "gn:admin1_code":"04",
    "gn:asciiname":"Pelou",
    "gn:country_code":"ML",
    "gn:dem":525,
    "gn:feature_class":"P",
    "gn:feature_code":"PPL",
    "gn:name":"Pelou",
    "gn:population":0,
    "gn:timezone":"Africa/Bamako",
    "iso:country":"ML",
    "name:fin_x_preferred":[
        "P\u00e9lou"
    ],
    "name:fra_x_preferred":[
        "P\u00e9lou"
    ],
    "name:ita_x_preferred":[
        "Pelou"
    ],
    "name:nld_x_preferred":[
        "Pelou"
    ],
    "name:spa_x_preferred":[
        "Pelou"
    ],
    "name:und_x_variant":[
        "Pelu",
        "Pelou"
    ],
    "wof:name":"Pelou",
    "wof:placetype":"locality"
},
  "geometry": {"coordinates":[-3.44109,14.3414],"type":"Point"}
}