{
  "type": "Feature",
  "properties": {
    "gn:admin1_code":"7.0",
    "gn:asciiname":"Mariko I",
    "gn:country_code":"ML",
    "gn:dem":359,
    "gn:feature_class":"P",
    "gn:feature_code":"PPL",
    "gn:name":"Mariko I",
    "gn:population":0,
    "gn:timezone":"Africa/Bamako",
    "iso:country":"ML",
    "wof:name":"Mariko I",
    "wof:placetype":"locality"
},
  "geometry": {"coordinates":[-8.51903,12.81341],"type":"Point"}
}