{
  "type": "Feature",
  "properties": {
    "gn:admin1_code":"7.0",
    "gn:asciiname":"Nenebougou",
    "gn:country_code":"ML",
    "gn:dem":398,
    "gn:feature_class":"P",
    "gn:feature_code":"PPL",
    "gn:name":"N\u00e8n\u00e8bougou",
    "gn:population":0,
    "gn:timezone":"Africa/Bamako",
    "iso:country":"ML",
    "wof:name":"Nenebougou",
    "wof:placetype":"locality"
},
  "geometry": {"coordinates":[-7.82679,13.76133],"type":"Point"}
}