{
  "type": "Feature",
  "properties": {
    "gn:admin1_code":"07",
    "gn:asciiname":"Tola",
    "gn:country_code":"ML",
    "gn:dem":324,
    "gn:feature_class":"P",
    "gn:feature_code":"PPL",
    "gn:name":"Tola",
    "gn:population":0,
    "gn:timezone":"Africa/Bamako",
    "iso:country":"ML",
    "name:ceb_x_preferred":[
        "Tola"
    ],
    "name:deu_x_preferred":[
        "Tola"
    ],
    "name:fra_x_preferred":[
        "Tola"
    ],
    "name:ita_x_preferred":[
        "Tola"
    ],
    "name:nld_x_preferred":[
        "Tola"
    ],
    "name:pol_x_preferred":[
        "Tola"
    ],
    "name:por_x_preferred":[
        "Tola"
    ],
    "name:rus_x_preferred":[
        "\u0422\u043e\u043b\u0430"
    ],
    "name:spa_x_preferred":[
        "Tola"
    ],
    "name:swe_x_preferred":[
        "Tola"
    ],
    "name:ukr_x_preferred":[
        "\u0422\u043e\u043b\u0430"
    ],
    "name:vie_x_preferred":[
        "Tola"
    ],
    "wof:name":"Tola",
    "wof:placetype":"locality"
},
  "geometry": {"coordinates":[-7.5396,14.3088],"type":"Point"}
}