{
  "type": "Feature",
  "properties": {
    "gn:admin1_code":"07",
    "gn:asciiname":"Soutourabougou",
    "gn:country_code":"ML",
    "gn:dem":323,
    "gn:feature_class":"P",
    "gn:feature_code":"PPL",
    "gn:name":"Soutourabougou",
    "gn:population":0,
    "gn:timezone":"Africa/Bamako",
    "iso:country":"ML",
    "wof:name":"Soutourabougou",
    "wof:placetype":"locality"
},
  "geometry": {"coordinates":[-7.03758,13.54303],"type":"Point"}
}