{
  "type": "Feature",
  "properties": {
    "gn:admin1_code":"05",
    "gn:asciiname":"Teneni",
    "gn:country_code":"ML",
    "gn:dem":282,
    "gn:feature_class":"P",
    "gn:feature_code":"PPL",
    "gn:name":"T\u00e9n\u00e9ni",
    "gn:population":0,
    "gn:timezone":"Africa/Bamako",
    "iso:country":"ML",
    "name:und_x_variant":[
        "Tene",
        "T\u00e9n\u00e9ni"
    ],
    "wof:name":"Teneni",
    "wof:placetype":"locality"
},
  "geometry": {"coordinates":[-4.808,13.3356],"type":"Point"}
}