{
  "type": "Feature",
  "properties": {
    "gn:admin1_code":"7.0",
    "gn:asciiname":"Dangolon",
    "gn:country_code":"ML",
    "gn:dem":438,
    "gn:feature_class":"P",
    "gn:feature_code":"PPL",
    "gn:name":"Dangolon",
    "gn:population":0,
    "gn:timezone":"Africa/Bamako",
    "iso:country":"ML",
    "wof:name":"Dangolon",
    "wof:placetype":"locality"
},
  "geometry": {"coordinates":[-7.95445,13.76206],"type":"Point"}
}